Workbook

Sheet Cover
B2: Power generation technology assumptions
C9: Developed to serve as input to the Central_2018 scenario
D36: Prepared by JRC C.6
D42: 43763.865
B46: © European Union 2017-2019
B48: Legal Notice
B50: The information made available is property of the Joint Research Centre of the European Commission.
B51: Neither the European Commission nor any person acting on behalf of the Commission is responsible for the use which might be made of this information.
B53: Permission to Use
B54: Reproduction of the data is authorized provided the source is appropriately acknowledged.

Sheet tech_base
A1: Type | B1: Technology | C1: Co-generation | D1: Size | E1: Typical unit size of a new power plant (kW) | F1: Technical lifetime (years) | G1: Construction time | H1: Technical availability (%) | I1: Net efficiency | J1: Default emissions factor (t of CO2 / toe input) | K1: CCS factor (t of CO2 / toe input) | L1: Default steam to electricity ratio for CHP units | M1: Own consumption | N1: Capital costs €2010/kW | O1: Fix O&M costs €2010/kW | P1: Variable O&M costs €2010/MWh | Q1: Desired range of operation | T1: Available for investment
A2: Nuclear power plants | B2: Nuclear - current | C2: Electricity only | D2: L | E2: 1250000 | F2: 50 | G2: 9 | H2: 0.92 | I2: 0.33333333 | J2: 0 | K2: 0 | L2: 0 | M2: 0.044 | N2: 4900 | O2: 98 | P2: 8.042204 | Q2: 6500 | R2: 8500 | S2: 8760 | T2: 2010
A3: =A2 -> Nuclear power plants | B3: =B2 -> Nuclear - current | C3: =C2 -> Electricity only | D3: M | E3: 600000 | F3: 50 | G3: 9 | H3: 0.92 | I3: 0.33333333 | J3: 0 | K3: 0 | L3: 0 | M3: 0.066 | N3: 5145 | O3: 102.9 | P3: 8.4443142 | Q3: 4875 | R3: 7820.726 | S3: 8270.2066 | T3: 2010
A4: =A3 -> Nuclear power plants | B4: Nuclear III | C4: Electricity only | D4: L | E4: 1250000 | F4: 60 | G4: 9 | H4: 0.94 | I4: 0.38473626 | J4: 0 | K4: 0 | L4: 0 | M4: 0.04048 | N4: 6923.9588 | O4: 121.16928 | P4: 6.0878888 | Q4: 6000 | R4: 8600 | S4: 8760 | T4: 2010
A5: =A4 -> Nuclear power plants | B5: =B4 -> Nuclear III | C5: =C4 -> Electricity only | D5: M | E5: 600000 | F5: 60 | G5: 9 | H5: 0.94 | I5: 0.38475374 | J5: 0 | K5: 0 | L5: 0 | M5: 0.0594 | N5: 7263.9512 | O5: 127.11915 | P5: 6.3868269 | Q5: 4200 | R5: 7614.605 | S5: 8156.8733 | T5: 2010
A6: =A5 -> Nuclear power plants | B6: =B5 -> Nuclear III | C6: =C5 -> Electricity only | D6: S | E6: 300000 | F6: 60 | G6: 9 | H6: 0.94 | I6: 0.38483712 | J6: 0 | K6: 0 | L6: 0 | M6: 0.060588 | N6: 7964.7537 | O6: 139.38319 | P6: 7.0030074 | Q6: 2730 | R6: 6472.5077 | S6: 7483.528 | T6: 2025
A7: =A6 -> Nuclear power plants | B7: Nuclear IV | C7: Electricity only | D7: L | E7: 1250000 | F7: 60 | G7: 9 | H7: 0.95 | I7: 0.40816327 | J7: 0 | K7: 0 | L7: 0 | M7: 0.038456 | N7: 9626.8095 | O7: 144.40214 | P7: 5.642913 | Q7: 5750 | R7: 8600 | S7: 8760 | T7: 2035
A8: =A7 -> Nuclear power plants | B8: =B7 -> Nuclear IV | C8: =C7 -> Electricity only | D8: M | E8: 600000 | F8: 60 | G8: 9 | H8: 0.95 | I8: 0.40816327 | J8: 0 | K8: 0 | L8: 0 | M8: 0.05643 | N8: 10108.15 | O8: 151.62225 | P8: 5.9250586 | Q8: 4168.75 | R8: 7718.5718 | S8: 8214.3217 | T8: 2035
A9: Coal fired power plants | B9: Integrated gasification combined cycle | C9: Electricity only | D9: L | E9: 480000 | F9: 35 | G9: 3 | H9: 0.9 | I9: 0.48781523 | J9: 3.9607128 | K9: 0 | L9: 0 | M9: 0.06 | N9: 2479.8245 | O9: 56.681704 | P9: 4.9837371 | Q9: 6700 | R9: 8380 | S9: 8760 | T9: 2010
A10: =A9 -> Coal fired power plants | B10: =B9 -> Integrated gasification combined cycle | C10: =C9 -> Electricity only | D10: M | E10: 275000 | F10: 35 | G10: 3 | H10: 0.9 | I10: 0.46462172 | J10: 3.9607128 | K10: 0 | L10: 0 | M10: 0.063 | N10: 2665.127 | O10: 60.917188 | P10: 5.356142 | Q10: 4556 | R10: 7228.5564 | S10: 8109.7205 | T10: 2010
A11: =A10 -> Coal fired power plants | B11: =B10 -> Integrated gasification combined cycle | C11: CHP | D11: L | E11: 420000 | F11: 35 | G11: 3 | H11: 0.9 | I11: 0.44346777 | J11: 3.9607128 | K11: 0 | L11: 1.32 | M11: 0.066 | N11: 2869.8105 | O11: 63.627798 | P11: 5.7585032 | Q11: 5360 | R11: 7980 | S11: 8760 | T11: 2010
A12: =A11 -> Coal fired power plants | B12: =B11 -> Integrated gasification combined cycle | C12: =C11 -> CHP | D12: M | E12: 250000 | F12: 35 | G12: 3 | H12: 0.9 | I12: 0.42238101 | J12: 3.9607128 | K12: 0 | L12: 1.32 | M12: 0.0693 | N12: 3055.0565 | O12: 67.734966 | P12: 6.1156326 | Q12: 3216 | R12: 6604.2953 | S12: 7909.2328 | T12: 2010
A13: =A12 -> Coal fired power plants | B13: =B12 -> Integrated gasification combined cycle | C13: Electricity only with CCS | D13: L | E13: 480000 | F13: 35 | G13: 3 | H13: 0.9 | I13: 0.46457607 | J13: 0.39607128 | K13: 3.5646415 | L13: 0 | M13: 0.21 | N13: 3596 | O13: 86.304 | P13: 5.831385 | Q13: 6700 | R13: 8380 | S13: 8760 | T13: 2031
A14: =A13 -> Coal fired power plants | B14: =B13 -> Integrated gasification combined cycle | C14: =C13 -> Electricity only with CCS | D14: M | E14: 275000 | F14: 35 | G14: 3 | H14: 0.9 | I14: 0.4424534 | J14: 0.39607128 | K14: 3.5646415 | L14: 0 | M14: 0.2205 | N14: 3837.8 | O14: 92.1072 | P14: 6.2234954 | Q14: 4556 | R14: 7228.5564 | S14: 8109.7205 | T14: 2031
A15: =A14 -> Coal fired power plants | B15: =B14 -> Integrated gasification combined cycle | C15: CHP with CCS | D15: L | E15: 420000 | F15: 35 | G15: 3 | H15: 0.9 | I15: 0.42234189 | J15: 0.39607128 | K15: 3.5646415 | L15: 1.4267312 | M15: 0.231 | N15: 3986 | O15: 92.79408 | P15: 6.3845957 | Q15: 5360 | R15: 7980 | S15: 8760 | T15: 2031
A16: =A15 -> Coal fired power plants | B16: =B15 -> Integrated gasification combined cycle | C16: =C15 -> CHP with CCS | D16: M | E16: 250000 | F16: 35 | G16: 3 | H16: 0.9 | I16: 0.40223037 | J16: 0.39607128 | K16: 3.5646415 | L16: 1.4333631 | M16: 0.24255 | N16: 4227.8 | O16: 98.423184 | P16: 6.7614394 | Q16: 3216 | R16: 6604.2953 | S16: 7909.2328 | T16: 2031
A17: =A16 -> Coal fired power plants | B17: Supercritical steam turbine | C17: Electricity only | D17: L | E17: 650000 | F17: 40 | G17: 4 | H17: 0.91 | I17: 0.47625327 | J17: 3.9607128 | K17: 0 | L17: 0 | M17: 0.05 | N17: 1744.0798 | O17: 39.241796 | P17: 3.5781239 | Q17: 6550 | R17: 8530 | S17: 8760 | T17: 2010
A18: =A17 -> Coal fired power plants | B18: =B17 -> Supercritical steam turbine | C18: =C17 -> Electricity only | D18: M | E18: 300000 | F18: 40 | G18: 4 | H18: 0.91 | I18: 0.45361376 | J18: 3.9607128 | K18: 0 | L18: 0 | M18: 0.0525 | N18: 1900.3897 | O18: 42.758769 | P18: 3.8988066 | Q18: 4716 | R18: 7509.0721 | S18: 8202.9602 | T18: 2010
A19: =A18 -> Coal fired power plants | B19: =B18 -> Supercritical steam turbine | C19: CHP | D19: L | E19: 550000 | F19: 40 | G19: 4 | H19: 0.91 | I19: 0.43294991 | J19: 3.9607128 | K19: 0 | L19: 0.98 | M19: 0.055 | N19: 2159.0128 | O19: 47.120455 | P19: 4.497524 | Q19: 5240 | R19: 8115 | S19: 8760 | T19: 2010
A20: =A19 -> Coal fired power plants | B20: =B19 -> Supercritical steam turbine | C20: =C19 -> CHP | D20: M | E20: 275000 | F20: 40 | G20: 4 | H20: 0.91 | I20: 0.41236714 | J20: 3.9607128 | K20: 0 | L20: 0.98 | M20: 0.05775 | N20: 2315.2298 | O20: 50.529889 | P20: 4.803703 | Q20: 3799 | R20: 7186.7545 | S20: 8214.3217 | T20: 2010
A21: =A20 -> Coal fired power plants | B21: =B20 -> Supercritical steam turbine | C21: Electricity only with CCS | D21: L | E21: 650000 | F21: 40 | G21: 4 | H21: 0.91 | I21: 0.45351474 | J21: 0.39607128 | K21: 3.5646415 | L21: 0 | M21: 0.2125 | N21: 3141 | O21: 74.206125 | P21: 7.0705232 | Q21: 6550 | R21: 8530 | S21: 8760 | T21: 2031
A22: =A21 -> Coal fired power plants | B22: =B21 -> Supercritical steam turbine | C22: =C21 -> Electricity only with CCS | D22: M | E22: 300000 | F22: 40 | G22: 4 | H22: 0.91 | I22: 0.4319188 | J22: 0.39607128 | K22: 3.5646415 | L22: 0 | M22: 0.223125 | N22: 3367.85 | O22: 79.565456 | P22: 7.581172 | Q22: 4716 | R22: 7509.0721 | S22: 8202.9602 | T22: 2031
A23: =A22 -> Coal fired power plants | B23: =B22 -> Supercritical steam turbine | C23: CHP with CCS | D23: L | E23: 550000 | F23: 40 | G23: 4 | H23: 0.91 | I23: 0.41228613 | J23: 0.39607128 | K23: 3.5646415 | L23: 1.0657384 | M23: 0.23375 | N23: 3556 | O23: 81.490185 | P23: 7.948469 | Q23: 5240 | R23: 8115 | S23: 8760 | T23: 2031
A24: =A23 -> Coal fired power plants | B24: =B23 -> Supercritical steam turbine | C24: =C23 -> CHP with CCS | D24: M | E24: 275000 | F24: 40 | G24: 4 | H24: 0.91 | I24: 0.39265345 | J24: 0.39607128 | K24: 3.5646415 | L24: 1.0710616 | M24: 0.2454375 | N24: 3782.85 | O24: 86.688736 | P24: 8.4388642 | Q24: 3799 | R24: 7186.7545 | S24: 8214.3217 | T24: 2031
A25: =A24 -> Coal fired power plants | B25: Fluidized bed combustion | C25: Electricity only | D25: L | E25: 560000 | F25: 40 | G25: 4 | H25: 0.88 | I25: 0.42557613 | J25: 3.9607128 | K25: 0 | L25: 0 | M25: 0.047 | N25: 1814.3715 | O25: 36.287431 | P25: 3.2700321 | Q25: 6000 | R25: 7800 | S25: 8350 | T25: 2010
A26: =A25 -> Coal fired power plants | B26: =B25 -> Fluidized bed combustion | C26: =C25 -> Electricity only | D26: M | E26: 260000 | F26: 40 | G26: 4 | H26: 0.88 | I26: 0.40534692 | J26: 3.9607128 | K26: 0 | L26: 0 | M26: 0.04935 | N26: 1968.0051 | O26: 39.360103 | P26: 3.5469251 | Q26: 4290 | R26: 6868.1625 | S26: 7808.1417 | T26: 2010
A27: =A26 -> Coal fired power plants | B27: =B26 -> Fluidized bed combustion | C27: =C26 -> Electricity only | D27: S | E27: 35000 | F27: 40 | G27: 3 | H27: 0.88 | I27: 0.38612565 | J27: 3.9607128 | K27: 0 | L27: 0 | M27: 0.0518175 | N27: 2232.1251 | O27: 44.642503 | P27: 4.0229472 | Q27: 2895.75 | R27: 5950.3206 | S27: 7217.8597 | T27: 2010
A28: =A27 -> Coal fired power plants | B28: =B27 -> Fluidized bed combustion | C28: CHP | D28: L | E28: 450000 | F28: 40 | G28: 4 | H28: 0.88 | I28: 0.38686052 | J28: 3.9607128 | K28: 0 | L28: 1.4 | M28: 0.0517 | N28: 2162.7518 | O28: 41.957384 | P28: 3.9205059 | Q28: 4800 | R28: 7437.5 | S28: 8350 | T28: 2010
A29: =A28 -> Coal fired power plants | B29: =B28 -> Fluidized bed combustion | C29: =C28 -> CHP | D29: M | E29: 225000 | F29: 40 | G29: 4 | H29: 0.88 | I29: 0.36845296 | J29: 3.9607128 | K29: 0 | L29: 1.4 | M29: 0.054285 | N29: 2316.7077 | O29: 44.944129 | P29: 4.1862919 | Q29: 3432 | R29: 6571.7534 | S29: 7808.1417 | T29: 2010
A30: =A29 -> Coal fired power plants | B30: =B29 -> Fluidized bed combustion | C30: =C29 -> CHP | D30: S | E30: 15000 | F30: 40 | G30: 3 | H30: 0.88 | I30: 0.35094326 | J30: 3.9607128 | K30: 0 | L30: 1.65 | M30: 0.05699925 | N30: 2628.5924 | O30: 50.994693 | P30: 4.7498768 | Q30: 2316.6 | R30: 5716.1816 | S30: 7217.8597 | T30: 2010
A31: =A30 -> Coal fired power plants | B31: =B30 -> Fluidized bed combustion | C31: Electricity only with CCS | D31: L | E31: 560000 | F31: 40 | G31: 4 | H31: 0.88 | I31: 0.40526849 | J31: 0.39607128 | K31: 3.5646415 | L31: 0 | M31: 0.22325 | N31: 3766.125 | O31: 79.088625 | P31: 7.6081131 | Q31: 6000 | R31: 7800 | S31: 8350 | T31: 2031
A32: =A31 -> Coal fired power plants | B32: =B31 -> Fluidized bed combustion | C32: =C31 -> Electricity only with CCS | D32: M | E32: 260000 | F32: 40 | G32: 4 | H32: 0.88 | I32: 0.38596999 | J32: 0.39607128 | K32: 3.5646415 | L32: 0 | M32: 0.2344125 | N32: 4211.6813 | O32: 88.445306 | P32: 8.5082007 | Q32: 4290 | R32: 6868.1625 | S32: 7808.1417 | T32: 2031
A33: =A32 -> Coal fired power plants | B33: =B32 -> Fluidized bed combustion | C33: CHP with CCS | D33: L | E33: 450000 | F33: 40 | G33: 4 | H33: 0.88 | I33: 0.3684259 | J33: 0.39607128 | K33: 3.5646415 | L33: 1.534122 | M33: 0.245575 | N33: 4114.125 | O33: 83.804726 | P33: 8.1793741 | Q33: 4800 | R33: 7437.5 | S33: 8350 | T33: 2031
A34: =A33 -> Coal fired power plants | B34: =B33 -> Fluidized bed combustion | C34: =C33 -> CHP with CCS | D34: M | E34: 225000 | F34: 40 | G34: 4 | H34: 0.88 | I34: 0.35088181 | J34: 0.39607128 | K34: 3.5646415 | L34: 1.5425397 | M34: 0.25785375 | N34: 4559.6813 | O34: 92.880707 | P34: 9.044845 | Q34: 3432 | R34: 6571.7534 | S34: 7808.1417 | T34: 2031
A35: =A34 -> Coal fired power plants | B35: Steam turbine | C35: Electricity only | D35: L | E35: 500000 | F35: 40 | G35: 4 | H35: 0.92 | I35: 0.44523198 | J35: 3.9607128 | K35: 0 | L35: 0 | M35: 0.058 | N35: 1498.2034 | O35: 24.345805 | P35: 2.1954915 | Q35: 5750 | R35: 7200 | S35: 8100 | T35: 2010
A36: =A35 -> Coal fired power plants | B36: =B35 -> Steam turbine | C36: =C35 -> Electricity only | D36: M | E36: 230000 | F36: 40 | G36: 4 | H36: 0.92 | I36: 0.42388087 | J36: 3.9607128 | K36: 0 | L36: 0 | M36: 0.0609 | N36: 1615.2077 | O36: 26.247126 | P36: 2.3669516 | Q36: 4600 | R36: 6628.5001 | S36: 7746.4552 | T36: 2010
A37: =A36 -> Coal fired power plants | B37: =B36 -> Steam turbine | C37: =C36 -> Electricity only | D37: S | E37: 65000 | F37: 40 | G37: 3 | H37: 0.92 | I37: 0.40355341 | J37: 3.9607128 | K37: 0 | L37: 0 | M37: 0.063945 | N37: 1781.6532 | O37: 28.951864 | P37: 2.6108634 | Q37: 3450 | R37: 5975.1349 | S37: 7313.3317 | T37: 2010
A38: =A37 -> Coal fired power plants | B38: =B37 -> Steam turbine | C38: =C37 -> Electricity only | D38: XS | E38: 4500 | F38: 40 | G38: 1 | H38: 0.92 | I38: 0.38426361 | J38: 3.9607128 | K38: 0 | L38: 0 | M38: 0.06714225 | N38: 2135.9549 | O38: 34.709267 | P38: 3.1300629 | Q38: 2932.5 | R38: 5642.786 | S38: 7079.4424 | T38: 2010
A39: =A38 -> Coal fired power plants | B39: =B38 -> Steam turbine | C39: CHP | D39: L | E39: 450000 | F39: 40 | G39: 4 | H39: 0.92 | I39: 0.40448435 | J39: 3.9607128 | K39: 0 | L39: 0.92 | M39: 0.0638 | N39: 1885.3236 | O39: 29.717413 | P39: 2.8192283 | Q39: 5175 | R39: 6885 | S39: 8100 | T39: 2010
A40: =A39 -> Coal fired power plants | B40: =B39 -> Steam turbine | C40: =C39 -> CHP | D40: M | E40: 210000 | F40: 40 | G40: 4 | H40: 0.92 | I40: 0.38508351 | J40: 3.9607128 | K40: 0 | L40: 0.92 | M40: 0.06699 | N40: 2001.1458 | O40: 31.54306 | P40: 2.9808301 | Q40: 4140 | R40: 6352.9728 | S40: 7746.4552 | T40: 2010
A41: =A40 -> Coal fired power plants | B41: =B40 -> Steam turbine | C41: =C40 -> CHP | D41: S | E41: 35000 | F41: 40 | G41: 3 | H41: 0.92 | I41: 0.36664029 | J41: 3.9607128 | K41: 0 | L41: 1.2 | M41: 0.0703395 | N41: 2532.288 | O41: 39.91519 | P41: 3.9034302 | Q41: 3105 | R41: 5743.288 | S41: 7313.3317 | T41: 2010
A42: =A41 -> Coal fired power plants | B42: =B41 -> Steam turbine | C42: =C41 -> CHP | D42: XS | E42: 3500 | F42: 40 | G42: 1 | H42: 0.92 | I42: 0.34914453 | J42: 3.9607128 | K42: 0 | L42: 1.35 | M42: 0.073856475 | N42: 2571.0262 | O42: 40.5258 | P42: 3.8014554 | Q42: 2639.25 | R42: 5432.4796 | S42: 7079.4424 | T42: 2010
A43: =A42 -> Coal fired power plants | B43: =B42 -> Steam turbine | C43: Electricity only with CCS | D43: L | E43: 500000 | F43: 40 | G43: 4 | H43: 0.92 | I43: 0.42328042 | J43: 0.39607128 | K43: 3.5646415 | L43: 0 | M43: 0.2291 | N43: 3192.75 | O43: 54.476297 | P43: 5.5508483 | Q43: 5750 | R43: 7200 | S43: 8100 | T43: 2031
A44: =A43 -> Coal fired power plants | B44: =B43 -> Steam turbine | C44: =C43 -> Electricity only with CCS | D44: M | E44: 230000 | F44: 40 | G44: 4 | H44: 0.92 | I44: 0.40312421 | J44: 0.39607128 | K44: 3.5646415 | L44: 0 | M44: 0.240555 | N44: 3668.1375 | O44: 62.587596 | P44: 6.377347 | Q44: 4600 | R44: 6628.5001 | S44: 7746.4552 | T44: 2031
A45: =A44 -> Coal fired power plants | B45: =B44 -> Steam turbine | C45: CHP with CCS | D45: L | E45: 450000 | F45: 40 | G45: 4 | H45: 0.92 | I45: 0.38480038 | J45: 0.39607128 | K45: 3.5646415 | L45: 1.0064147 | M45: 0.25201 | N45: 3582.75 | O45: 59.296752 | P45: 6.1714685 | Q45: 5175 | R45: 6885 | S45: 8100 | T45: 2031
A46: =A45 -> Coal fired power plants | B46: =B45 -> Steam turbine | C46: =C45 -> CHP with CCS | D46: M | E46: 210000 | F46: 40 | G46: 4 | H46: 0.92 | I46: 0.36647656 | J46: 0.39607128 | K46: 3.5646415 | L46: 1.0118948 | M46: 0.2646105 | N46: 4058.1375 | O46: 67.164712 | P46: 6.9655619 | Q46: 4140 | R46: 6352.9728 | S46: 7746.4552 | T46: 2031
A47: Lignite fired power plants | B47: Integrated gasification combined cycle | C47: Electricity only | D47: L | E47: 500000 | F47: 37 | G47: 3 | H47: 0.88 | I47: 0.46296908 | J47: 4.228668 | K47: 0 | L47: 0 | M47: 0.08 | N47: 2939.8059 | O47: 67.536081 | P47: 5.5888074 | Q47: 6900 | R47: 8505 | S47: 8760 | T47: 2010
A48: =A47 -> Lignite fired power plants | B48: =B47 -> Integrated gasification combined cycle | C48: =C47 -> Electricity only | D48: M | E48: 300000 | F48: 37 | G48: 3 | H48: 0.88 | I48: 0.44094434 | J48: 4.228668 | K48: 0 | L48: 0 | M48: 0.084 | N48: 3159.5242 | O48: 72.583664 | P48: 6.0065097 | Q48: 4692 | R48: 7327.7344 | S48: 8109.7205 | T48: 2010
A49: =A48 -> Lignite fired power plants | B49: =B48 -> Integrated gasification combined cycle | C49: CHP | D49: L | E49: 450000 | F49: 37 | G49: 3 | H49: 0.88 | I49: 0.42088058 | J49: 4.228668 | K49: 0 | L49: 1.25 | M49: 0.088 | N49: 3309.797 | O49: 73.754802 | P49: 6.2393118 | Q49: 5520 | R49: 8092.5 | S49: 8760 | T49: 2020
A50: =A49 -> Lignite fired power plants | B50: =B49 -> Integrated gasification combined cycle | C50: =C49 -> CHP | D50: M | E50: 265000 | F50: 37 | G50: 3 | H50: 0.88 | I50: 0.40085699 | J50: 4.228668 | K50: 0 | L50: 1.25 | M50: 0.0924 | N50: 3529.476 | O50: 78.650081 | P50: 6.6404193 | Q50: 3312 | R50: 6687.0978 | S50: 7909.2328 | T50: 2020
A51: =A50 -> Lignite fired power plants | B51: =B50 -> Integrated gasification combined cycle | C51: Electricity only with CCS | D51: L | E51: 500000 | F51: 37 | G51: 3 | H51: 0.88 | I51: 0.44091711 | J51: 0.4228668 | K51: 3.8058012 | L51: 0 | M51: 0.26 | N51: 4410 | O51: 106.37635 | P51: 6.2878236 | Q51: 6900 | R51: 8505 | S51: 8760 | T51: 2031
A52: =A51 -> Lignite fired power plants | B52: =B51 -> Integrated gasification combined cycle | C52: =C51 -> Electricity only with CCS | D52: M | E52: 300000 | F52: 37 | G52: 3 | H52: 0.88 | I52: 0.41992105 | J52: 0.4228668 | K52: 3.8058012 | L52: 0 | M52: 0.273 | N52: 4704 | O52: 113.46811 | P52: 6.7070118 | Q52: 4692 | R52: 7327.7344 | S52: 8109.7205 | T52: 2031
A53: =A52 -> Lignite fired power plants | B53: =B52 -> Integrated gasification combined cycle | C53: CHP with CCS | D53: L | E53: 450000 | F53: 37 | G53: 3 | H53: 0.88 | I53: 0.40083373 | J53: 0.4228668 | K53: 3.8058012 | L53: 1.3785695 | M53: 0.286 | N53: 4780 | O53: 111.84231 | P53: 6.6942457 | Q53: 5520 | R53: 8092.5 | S53: 8760 | T53: 2031
A54: =A53 -> Lignite fired power plants | B54: =B53 -> Integrated gasification combined cycle | C54: =C53 -> CHP with CCS | D54: M | E54: 265000 | F54: 37 | G54: 3 | H54: 0.88 | I54: 0.38174641 | J54: 0.4228668 | K54: 3.8058012 | L54: 1.3870849 | M54: 0.3003 | N54: 5074 | O54: 118.72131 | P54: 7.0973738 | Q54: 3312 | R54: 6687.0978 | S54: 7909.2328 | T54: 2031
A55: =A54 -> Lignite fired power plants | B55: Supercritical steam turbine | C55: Electricity only | D55: L | E55: 750000 | F55: 42 | G55: 4 | H55: 0.89 | I55: 0.44846124 | J55: 4.228668 | K55: 0 | L55: 0 | M55: 0.061 | N55: 1864.1477 | O55: 40.833711 | P55: 3.9025031 | Q55: 6750 | R55: 8630 | S55: 8760 | T55: 2010
A56: =A55 -> Lignite fired power plants | B56: =B55 -> Supercritical steam turbine | C56: =C55 -> Electricity only | D56: M | E56: 350000 | F56: 42 | G56: 4 | H56: 0.89 | I56: 0.42712701 | J56: 4.228668 | K56: 0 | L56: 0 | M56: 0.06405 | N56: 2031.253 | O56: 44.494114 | P56: 4.25233 | Q56: 4860 | R56: 7591.1828 | S56: 8202.9602 | T56: 2010
A57: =A56 -> Lignite fired power plants | B57: =B56 -> Supercritical steam turbine | C57: CHP | D57: L | E57: 600000 | F57: 42 | G57: 4 | H57: 0.89 | I57: 0.40768774 | J57: 4.228668 | K57: 0 | L57: 0.96 | M57: 0.0671 | N57: 2259.126 | O57: 48.00105 | P57: 4.7766726 | Q57: 5400 | R57: 8205 | S57: 8760 | T57: 2010
A58: =A57 -> Lignite fired power plants | B58: =B57 -> Supercritical steam turbine | C58: =C57 -> CHP | D58: M | E58: 300000 | F58: 42 | G58: 4 | H58: 0.89 | I58: 0.38829219 | J58: 4.228668 | K58: 0 | L58: 0.96 | M58: 0.070455 | N58: 2446.1407 | O58: 51.974665 | P58: 5.1639128 | Q58: 3915 | R58: 7260.9615 | S58: 8214.3217 | T58: 2010
A59: =A58 -> Lignite fired power plants | B59: =B58 -> Supercritical steam turbine | C59: Electricity only with CCS | D59: L | E59: 750000 | F59: 42 | G59: 4 | H59: 0.89 | I59: 0.42707666 | J59: 0.4228668 | K59: 3.8058012 | L59: 0 | M59: 0.2745 | N59: 3543.5 | O59: 81.5005 | P59: 7.5157532 | Q59: 6750 | R59: 8630 | S59: 8760 | T59: 2031
A60: =A59 -> Lignite fired power plants | B60: =B59 -> Supercritical steam turbine | C60: =C59 -> Electricity only with CCS | D60: M | E60: 350000 | F60: 42 | G60: 4 | H60: 0.89 | I60: 0.40673968 | J60: 0.4228668 | K60: 3.8058012 | L60: 0 | M60: 0.288225 | N60: 3795.275 | O60: 87.291325 | P60: 8.0497673 | Q60: 4860 | R60: 7591.1828 | S60: 8202.9602 | T60: 2031
A61: =A60 -> Lignite fired power plants | B61: =B60 -> Supercritical steam turbine | C61: CHP with CCS | D61: L | E61: 600000 | F61: 42 | G61: 4 | H61: 0.89 | I61: 0.38825151 | J61: 0.4228668 | K61: 3.8058012 | L61: 1.0780792 | M61: 0.30195 | N61: 3938.5 | O61: 87.867935 | P61: 8.2567702 | Q61: 5400 | R61: 8205 | S61: 8760 | T61: 2031
A62: =A61 -> Lignite fired power plants | B62: =B61 -> Supercritical steam turbine | C62: =C61 -> CHP with CCS | D62: M | E62: 300000 | F62: 42 | G62: 4 | H62: 0.89 | I62: 0.36976334 | J62: 0.4228668 | K62: 3.8058012 | L62: 1.0859834 | M62: 0.3170475 | N62: 4210.275 | O62: 93.931235 | P62: 8.8223038 | Q62: 3915 | R62: 7260.9615 | S62: 8214.3217 | T62: 2031
A63: =A62 -> Lignite fired power plants | B63: Fluidized bed combustion | C63: Electricity only | D63: L | E63: 580000 | F63: 42 | G63: 4 | H63: 0.87 | I63: 0.40652941 | J63: 4.228668 | K63: 0 | L63: 0 | M63: 0.052 | N63: 1929.3985 | O63: 39.047351 | P63: 4.0913946 | Q63: 6300 | R63: 8225 | S63: 8500 | T63: 2010
A64: =A63 -> Lignite fired power plants | B64: =B63 -> Fluidized bed combustion | C64: =C63 -> Electricity only | D64: M | E64: 290000 | F64: 42 | G64: 4 | H64: 0.87 | I64: 0.38719214 | J64: 4.228668 | K64: 0 | L64: 0 | M64: 0.0546 | N64: 2092.8224 | O64: 42.35474 | P64: 4.4379438 | Q64: 4504.5 | R64: 7224.4837 | S64: 7948.4077 | T64: 2010
A65: =A64 -> Lignite fired power plants | B65: =B64 -> Fluidized bed combustion | C65: =C64 -> Electricity only | D65: S | E65: 40000 | F65: 42 | G65: 3 | H65: 0.87 | I65: 0.36880203 | J65: 4.228668 | K65: 0 | L65: 0 | M65: 0.05733 | N65: 2373.8206 | O65: 48.041607 | P65: 5.0338156 | Q65: 3040.5375 | R65: 6241.217 | S65: 7347.5219 | T65: 2010
A66: =A65 -> Lignite fired power plants | B66: =B65 -> Fluidized bed combustion | C66: CHP | D66: L | E66: 500000 | F66: 42 | G66: 4 | H66: 0.87 | I66: 0.36955669 | J66: 4.228668 | K66: 0 | L66: 1.35 | M66: 0.0572 | N66: 2259.7695 | O66: 44.361427 | P66: 4.7986161 | Q66: 5040 | R66: 7827.5 | S66: 8500 | T66: 2010
A67: =A66 -> Lignite fired power plants | B67: =B66 -> Fluidized bed combustion | C67: =C66 -> CHP | D67: M | E67: 250000 | F67: 42 | G67: 4 | H67: 0.87 | I67: 0.35196708 | J67: 4.228668 | K67: 0 | L67: 1.35 | M67: 0.06006 | N67: 2423.5159 | O67: 47.575925 | P67: 5.1315503 | Q67: 3603.6 | R67: 6899.4557 | S67: 7948.4077 | T67: 2010
A68: =A67 -> Lignite fired power plants | B68: =B67 -> Fluidized bed combustion | C68: =C67 -> CHP | D68: S | E68: 20000 | F68: 42 | G68: 3 | H68: 0.87 | I68: 0.33522755 | J68: 4.228668 | K68: 0 | L68: 1.52 | M68: 0.063063 | N68: 2755.2844 | O68: 54.088857 | P68: 5.8369236 | Q68: 2432.43 | R68: 5984.4714 | S68: 7347.5219 | T68: 2010
A69: =A68 -> Lignite fired power plants | B69: =B68 -> Fluidized bed combustion | C69: Electricity only with CCS | D69: L | E69: 580000 | F69: 42 | G69: 4 | H69: 0.87 | I69: 0.38714673 | J69: 0.4228668 | K69: 3.8058012 | L69: 0 | M69: 0.286 | N69: 4004.75 | O69: 85.100938 | P69: 7.8988287 | Q69: 6300 | R69: 8225 | S69: 8500 | T69: 2031
A70: =A69 -> Lignite fired power plants | B70: =B69 -> Fluidized bed combustion | C70: =C69 -> Electricity only with CCS | D70: M | E70: 290000 | F70: 42 | G70: 4 | H70: 0.87 | I70: 0.36871117 | J70: 0.4228668 | K70: 3.8058012 | L70: 0 | M70: 0.3003 | N70: 4438.4875 | O70: 94.317859 | P70: 8.7543173 | Q70: 4504.5 | R70: 7224.4837 | S70: 7948.4077 | T70: 2031
A71: =A70 -> Lignite fired power plants | B71: =B70 -> Fluidized bed combustion | C71: CHP with CCS | D71: L | E71: 500000 | F71: 42 | G71: 4 | H71: 0.87 | I71: 0.35195157 | J71: 0.4228668 | K71: 3.8058012 | L71: 1.5336419 | M71: 0.3146 | N71: 4334.75 | O71: 89.350034 | P71: 8.3948544 | Q71: 5040 | R71: 7827.5 | S71: 8500 | T71: 2031
A72: =A71 -> Lignite fired power plants | B72: =B71 -> Fluidized bed combustion | C72: =C71 -> CHP with CCS | D72: M | E72: 250000 | F72: 42 | G72: 4 | H72: 0.87 | I72: 0.33519197 | J72: 0.4228668 | K72: 3.8058012 | L72: 1.5460712 | M72: 0.33033 | N72: 4768.4875 | O72: 98.290449 | P72: 9.2176245 | Q72: 3603.6 | R72: 6899.4557 | S72: 7948.4077 | T72: 2031
A73: =A72 -> Lignite fired power plants | B73: Steam turbine | C73: Electricity only | D73: L | E73: 550000 | F73: 42 | G73: 4 | H73: 0.9 | I73: 0.41012665 | J73: 4.228668 | K73: 0 | L73: 0 | M73: 0.08 | N73: 1661.7364 | O73: 27.695606 | P73: 2.7830118 | Q73: 6150 | R73: 8125 | S73: 8400 | T73: 2010
A74: =A73 -> Lignite fired power plants | B74: =B73 -> Steam turbine | C74: =C73 -> Electricity only | D74: M | E74: 250000 | F74: 42 | G74: 4 | H74: 0.9 | I74: 0.39052779 | J74: 4.228668 | K74: 0 | L74: 0 | M74: 0.084 | N74: 1791.5064 | O74: 29.858441 | P74: 3.0003458 | Q74: 4920 | R74: 7449.8374 | S74: 8033.361 | T74: 2010
A75: =A74 -> Lignite fired power plants | B75: =B74 -> Steam turbine | C75: =C74 -> Electricity only | D75: S | E75: 70000 | F75: 42 | G75: 3 | H75: 0.9 | I75: 0.37189832 | J75: 4.228668 | K75: 0 | L75: 0 | M75: 0.0882 | N75: 1977.8639 | O75: 32.964398 | P75: 3.3124499 | Q75: 3690 | R75: 6680.9839 | S75: 7584.1958 | T75: 2010
A76: =A75 -> Lignite fired power plants | B76: =B75 -> Steam turbine | C76: =C75 -> Electricity only | D76: XS | E76: 5000 | F76: 42 | G76: 1 | H76: 0.9 | I76: 0.35413506 | J76: 4.228668 | K76: 0 | L76: 0 | M76: 0.09261 | N76: 2369.8328 | O76: 39.497214 | P76: 3.9689044 | Q76: 3136.5 | R76: 6291.3075 | S76: 7341.644 | T76: 2010
A77: =A76 -> Lignite fired power plants | B77: =B76 -> Steam turbine | C77: CHP | D77: L | E77: 495000 | F77: 42 | G77: 4 | H77: 0.9 | I77: 0.37274203 | J77: 4.228668 | K77: 0 | L77: 0.92 | M77: 0.088 | N77: 2048.9856 | O77: 33.125268 | P77: 3.4833175 | Q77: 5535 | R77: 7732.5 | S77: 8400 | T77: 2010
A78: =A77 -> Lignite fired power plants | B78: =B77 -> Steam turbine | C78: =C77 -> CHP | D78: M | E78: 230000 | F78: 42 | G78: 4 | H78: 0.9 | I78: 0.35493435 | J78: 4.228668 | K78: 0 | L78: 0.92 | M78: 0.0924 | N78: 2178.0017 | O78: 35.211028 | P78: 3.6894688 | Q78: 4428 | R78: 7106.5217 | S78: 8033.361 | T78: 2010
A79: =A78 -> Lignite fired power plants | B79: =B78 -> Steam turbine | C79: =C78 -> CHP | D79: S | E79: 40000 | F79: 42 | G79: 3 | H79: 0.9 | I79: 0.33800236 | J79: 4.228668 | K79: 0 | L79: 1.2 | M79: 0.09702 | N79: 2768.08 | O79: 44.750626 | P79: 4.8570356 | Q79: 3321 | R79: 6392.0953 | S79: 7584.1958 | T79: 2010
A80: =A79 -> Lignite fired power plants | B80: =B79 -> Steam turbine | C80: =C79 -> CHP | D80: XS | E80: 4000 | F80: 42 | G80: 1 | H80: 0.9 | I80: 0.32188375 | J80: 4.228668 | K80: 0 | L80: 1.35 | M80: 0.101871 | N80: 2806.1262 | O80: 45.365707 | P80: 4.7213384 | Q80: 2822.85 | R80: 6029.259 | S80: 7341.644 | T80: 2010
A81: =A80 -> Lignite fired power plants | B81: =B80 -> Steam turbine | C81: Electricity only with CCS | D81: L | E81: 550000 | F81: 42 | G81: 4 | H81: 0.9 | I81: 0.39032006 | J81: 0.4228668 | K81: 3.8058012 | L81: 0 | M81: 0.3 | N81: 3795 | O81: 66.4125 | P81: 7.6171337 | Q81: 6150 | R81: 8125 | S81: 8400 | T81: 2031
A82: =A81 -> Lignite fired power plants | B82: =B81 -> Steam turbine | C82: =C81 -> Electricity only with CCS | D82: M | E82: 250000 | F82: 42 | G82: 4 | H82: 0.9 | I82: 0.37173339 | J82: 0.4228668 | K82: 3.8058012 | L82: 0 | M82: 0.315 | N82: 4292.25 | O82: 75.114375 | P82: 8.615189 | Q82: 4920 | R82: 7449.8374 | S82: 8033.361 | T82: 2031
A83: =A82 -> Lignite fired power plants | B83: =B82 -> Steam turbine | C83: CHP with CCS | D83: L | E83: 495000 | F83: 42 | G83: 4 | H83: 0.9 | I83: 0.35483642 | J83: 0.4228668 | K83: 3.8058012 | L83: 1.0407726 | M83: 0.33 | N83: 4185 | O83: 71.040375 | P83: 8.2863037 | Q83: 5535 | R83: 7732.5 | S83: 8400 | T83: 2031
A84: =A83 -> Lignite fired power plants | B84: =B83 -> Steam turbine | C84: =C83 -> CHP with CCS | D84: M | E84: 230000 | F84: 42 | G84: 4 | H84: 0.9 | I84: 0.33793945 | J84: 0.4228668 | K84: 3.8058012 | L84: 1.0491737 | M84: 0.3465 | N84: 4682.25 | O84: 79.481194 | P84: 9.2457354 | Q84: 4428 | R84: 7106.5217 | S84: 8033.361 | T84: 2031
A85: Gas fired power plants (Natural gas, biogas) | B85: Gas turbine combined cycle | C85: Electricity only | D85: L | E85: 470000 | F85: 32 | G85: 2 | H85: 0.93 | I85: 0.58979193 | J85: 2.3487948 | K85: 0 | L85: 0 | M85: 0.03 | N85: 870.38734 | O85: 20.399703 | P85: 2.0726545 | Q85: 3500 | R85: 6250 | S85: 7000 | T85: 2010
A86: =A85 -> Gas fired power plants (Natural gas, biogas) | B86: =B85 -> Gas turbine combined cycle | C86: =C85 -> Electricity only | D86: M | E86: 190000 | F86: 32 | G86: 2 | H86: 0.93 | I86: 0.56065788 | J86: 2.3487948 | K86: 0 | L86: 0 | M86: 0.0315 | N86: 908.59237 | O86: 21.295134 | P86: 2.1636322 | Q86: 2800 | R86: 5752.6303 | S86: 6694.4675 | T86: 2010
A87: =A86 -> Gas fired power plants (Natural gas, biogas) | B87: =B86 -> Gas turbine combined cycle | C87: =C86 -> Electricity only | D87: S | E87: 50000 | F87: 32 | G87: 2 | H87: 0.93 | I87: 0.53359482 | J87: 2.3487948 | K87: 0 | L87: 0 | M87: 0.033075 | N87: 978.07375 | O87: 22.923603 | P87: 2.3290883 | Q87: 2100 | R87: 5184.1419 | S87: 6320.1632 | T87: 2010
A88: =A87 -> Gas fired power plants (Natural gas, biogas) | B88: =B87 -> Gas turbine combined cycle | C88: =C87 -> Electricity only | D88: XS | E88: 4500 | F88: 32 | G88: 1 | H88: 0.93 | I88: 0.50814679 | J88: 2.3487948 | K88: 0 | L88: 0 | M88: 0.03472875 | N88: 1124.9564 | O88: 26.366165 | P88: 2.6788601 | Q88: 1785 | R88: 4895.0273 | S88: 6118.0367 | T88: 2010
A89: =A88 -> Gas fired power plants (Natural gas, biogas) | B89: =B88 -> Gas turbine combined cycle | C89: CHP | D89: L | E89: 440000 | F89: 32 | G89: 2 | H89: 0.93 | I89: 0.53589056 | J89: 2.3487948 | K89: 0 | L89: 1.08 | M89: 0.033 | N89: 1194.9392 | O89: 27.166197 | P89: 2.9642726 | Q89: 2800 | R89: 5662.5 | S89: 6650 | T89: 2010
A90: =A89 -> Gas fired power plants (Natural gas, biogas) | B90: =B89 -> Gas turbine combined cycle | C90: =C89 -> CHP | D90: M | E90: 175000 | F90: 32 | G90: 2 | H90: 0.93 | I90: 0.50961721 | J90: 2.3487948 | K90: 0 | L90: 1.08 | M90: 0.03465 | N90: 1233.437 | O90: 28.041419 | P90: 3.051774 | Q90: 2240 | R90: 5224.4591 | S90: 6359.7441 | T90: 2010
A91: =A90 -> Gas fired power plants (Natural gas, biogas) | B91: =B90 -> Gas turbine combined cycle | C91: =C90 -> CHP | D91: S | E91: 45000 | F91: 32 | G91: 2 | H91: 0.93 | I91: 0.48507892 | J91: 2.3487948 | K91: 0 | L91: 1.25 | M91: 0.0363825 | N91: 1499.7623 | O91: 34.096158 | P91: 3.8256998 | Q91: 1680 | R91: 4722.5287 | S91: 6004.155 | T91: 2010
A92: =A91 -> Gas fired power plants (Natural gas, biogas) | B92: =B91 -> Gas turbine combined cycle | C92: =C91 -> CHP | D92: XS | E92: 4000 | F92: 32 | G92: 1 | H92: 0.93 | I92: 0.46195065 | J92: 2.3487948 | K92: 0 | L92: 1.4 | M92: 0.038201625 | N92: 1604.9624 | O92: 36.487818 | P92: 4.0209227 | Q92: 1428 | R92: 4466.675 | S92: 5812.1348 | T92: 2010
A93: =A92 -> Gas fired power plants (Natural gas, biogas) | B93: =B92 -> Gas turbine combined cycle | C93: Electricity only with CCS | D93: L | E93: 470000 | F93: 32 | G93: 2 | H93: 0.93 | I93: 0.56022409 | J93: 0.23487948 | K93: 2.1139153 | L93: 0 | M93: 0.165 | N93: 1618.75 | O93: 39.836426 | P93: 3.4380037 | Q93: 3500 | R93: 6250 | S93: 7000 | T93: 2031
A94: =A93 -> Gas fired power plants (Natural gas, biogas) | B94: =B93 -> Gas turbine combined cycle | C94: =C93 -> Electricity only with CCS | D94: M | E94: 190000 | F94: 32 | G94: 2 | H94: 0.93 | I94: 0.53354675 | J94: 0.23487948 | K94: 2.1139153 | L94: 0 | M94: 0.17325 | N94: 1980.9375 | O94: 48.749634 | P94: 4.2072405 | Q94: 2800 | R94: 5752.6303 | S94: 6694.4675 | T94: 2031
A95: =A94 -> Gas fired power plants (Natural gas, biogas) | B95: =B94 -> Gas turbine combined cycle | C95: CHP with CCS | D95: L | E95: 440000 | F95: 32 | G95: 2 | H95: 0.93 | I95: 0.50929778 | J95: 0.23487948 | K95: 2.1139153 | L95: 1.1544812 | M95: 0.1815 | N95: 1943.72 | O95: 46.398721 | P95: 4.1599689 | Q95: 2800 | R95: 5662.5 | S95: 6650 | T95: 2031
A96: =A95 -> Gas fired power plants (Natural gas, biogas) | B96: =B95 -> Gas turbine combined cycle | C96: =C95 -> CHP with CCS | D96: M | E96: 175000 | F96: 32 | G96: 2 | H96: 0.93 | I96: 0.48504523 | J96: 0.23487948 | K96: 2.1139153 | L96: 1.1588495 | M96: 0.190575 | N96: 2305.9051 | O96: 55.044477 | P96: 4.8969633 | Q96: 2240 | R96: 5224.4591 | S96: 6359.7441 | T96: 2031
A97: =A96 -> Gas fired power plants (Natural gas, biogas) | B97: Gas turbine | C97: Electricity only | D97: M | E97: 150000 | F97: 25 | G97: 2 | H97: 0.945 | I97: 0.39070517 | J97: 2.3487948 | K97: 0 | L97: 0 | M97: 0.025 | N97: 534.45137 | O97: 9.6201246 | P97: 2.3809088 | Q97: 1500 | R97: 3500 | S97: 4000 | T97: 2010
A98: =A97 -> Gas fired power plants (Natural gas, biogas) | B98: =B97 -> Gas turbine | C98: =C97 -> Electricity only | D98: S | E98: 35000 | F98: 25 | G98: 2 | H98: 0.945 | I98: 0.37210091 | J98: 2.3487948 | K98: 0 | L98: 0 | M98: 0.02625 | N98: 569.18494 | O98: 10.245329 | P98: 2.5356422 | Q98: 750 | R98: 2275.7373 | S98: 2828.4271 | T98: 2010
A99: =A98 -> Gas fired power plants (Natural gas, biogas) | B99: =B98 -> Gas turbine | C99: =C98 -> Electricity only | D99: XS | E99: 3500 | F99: 25 | G99: 1 | H99: 0.945 | I99: 0.35435363 | J99: 2.3487948 | K99: 0 | L99: 0 | M99: 0.0275625 | N99: 825.64652 | O99: 14.861637 | P99: 3.6781439 | Q99: 37.5 | R99: 835.64227 | S99: 1151.4259 | T99: 2010
A100: =A99 -> Gas fired power plants (Natural gas, biogas) | B100: =B99 -> Gas turbine | C100: CHP | D100: M | E100: 125000 | F100: 25 | G100: 2 | H100: 0.945 | I100: 0.35512388 | J100: 2.3487948 | K100: 0 | L100: 0.975 | M100: 0.0275 | N100: 794.88533 | O100: 13.878698 | P100: 3.7636311 | Q100: 1725 | R100: 4575 | S100: 4800 | T100: 2010
...

Sheet tech_proj
A1: Type: | B1: Technology: | C1: Co-generation: | D1: Size:
A6: =$I$7 -> Pump storage / Pump storage / Electricity only / M | J6: =J$125 -> 2010 | K6: =K$125 -> 2011 | L6: =L$125 -> 2012 | M6: =M$125 -> 2013 | N6: =N$125 -> 2014 | O6: =O$125 -> 2015 | P6: =P$125 -> 2016 | Q6: =Q$125 -> 2017 | ... AX6: =AX$125 -> 2050
A7: =$J$124 -> Efficiency | I7: =INDEX(F$126:F$397,$D$54)&" / "&INDEX(G$126:G$397,$D$54)&" / "&INDEX(H$126:H$397,$D$54)&" / "&INDEX(I$126:I$397,$D$54) -> Pump storage / Pump storage / Electricity only / M | J7: =IF(LEN(INDEX(J$126:J$397,$D$54))<=0,NA(),INDEX(J$126:J$397,$D$54)) -> 0.75 | K7: =IF(LEN(INDEX(K$126:K$397,$D$54))<=0,NA(),INDEX(K$126:K$397,$D$54)) -> 0.7500012 | L7: =IF(LEN(INDEX(L$126:L$397,$D$54))<=0,NA(),INDEX(L$126:L$397,$D$54)) -> 0.75000253 | M7: =IF(LEN(INDEX(M$126:M$397,$D$54))<=0,NA(),INDEX(M$126:M$397,$D$54)) -> 0.750004 | N7: =IF(LEN(INDEX(N$126:N$397,$D$54))<=0,NA(),INDEX(N$126:N$397,$D$54)) -> 0.75000562 | O7: =IF(LEN(INDEX(O$126:O$397,$D$54))<=0,NA(),INDEX(O$126:O$397,$D$54)) -> 0.75000741 | P7: =IF(LEN(INDEX(P$126:P$397,$D$54))<=0,NA(),INDEX(P$126:P$397,$D$54)) -> 0.75000939 | Q7: =IF(LEN(INDEX(Q$126:Q$397,$D$54))<=0,NA(),INDEX(Q$126:Q$397,$D$54)) -> 0.75001158 | ... AX7: =IF(LEN(INDEX(AX$126:AX$397,$D$54))<=0,NA(),INDEX(AX$126:AX$397,$D$54)) -> 0.75059041
A8: =$J$964 -> Capital costs €2010/kW gross | I8: =INDEX(F$966:F$1237,$D$54)&" / "&INDEX(G$966:G$1237,$D$54)&" / "&INDEX(H$966:H$1237,$D$54)&" / "&INDEX(I$966:I$1237,$D$54) -> Pump storage / Pump storage / Electricity only / M | J8: =IF(LEN(INDEX(J$966:J$1237,$D$54))<=0,NA(),INDEX(J$966:J$1237,$D$54)) -> 3851.4937 | K8: =IF(LEN(INDEX(K$966:K$1237,$D$54))<=0,NA(),INDEX(K$966:K$1237,$D$54)) -> 3851.4629 | L8: =IF(LEN(INDEX(L$966:L$1237,$D$54))<=0,NA(),INDEX(L$966:L$1237,$D$54)) -> 3851.4288 | M8: =IF(LEN(INDEX(M$966:M$1237,$D$54))<=0,NA(),INDEX(M$966:M$1237,$D$54)) -> 3851.3911 | N8: =IF(LEN(INDEX(N$966:N$1237,$D$54))<=0,NA(),INDEX(N$966:N$1237,$D$54)) -> 3851.3495 | O8: =IF(LEN(INDEX(O$966:O$1237,$D$54))<=0,NA(),INDEX(O$966:O$1237,$D$54)) -> 3851.3035 | P8: =IF(LEN(INDEX(P$966:P$1237,$D$54))<=0,NA(),INDEX(P$966:P$1237,$D$54)) -> 3851.2526 | Q8: =IF(LEN(INDEX(Q$966:Q$1237,$D$54))<=0,NA(),INDEX(Q$966:Q$1237,$D$54)) -> 3851.1965 | ... AX8: =IF(LEN(INDEX(AX$966:AX$1237,$D$54))<=0,NA(),INDEX(AX$966:AX$1237,$D$54)) -> 3836.3697
A9: =$J$1244 -> Fix O&M costs €2010/kW gross | I9: =INDEX(F$1246:F$1517,$D$54)&" / "&INDEX(G$1246:G$1517,$D$54)&" / "&INDEX(H$1246:H$1517,$D$54)&" / "&INDEX(I$1246:I$1517,$D$54) -> Pump storage / Pump storage / Electricity only / M | J9: =IF(LEN(INDEX(J$1246:J$1517,$D$54))<=0,NA(),INDEX(J$1246:J$1517,$D$54)) -> 38.514937 | K9: =IF(LEN(INDEX(K$1246:K$1517,$D$54))<=0,NA(),INDEX(K$1246:K$1517,$D$54)) -> 38.514629 | L9: =IF(LEN(INDEX(L$1246:L$1517,$D$54))<=0,NA(),INDEX(L$1246:L$1517,$D$54)) -> 38.514288 | M9: =IF(LEN(INDEX(M$1246:M$1517,$D$54))<=0,NA(),INDEX(M$1246:M$1517,$D$54)) -> 38.513911 | N9: =IF(LEN(INDEX(N$1246:N$1517,$D$54))<=0,NA(),INDEX(N$1246:N$1517,$D$54)) -> 38.513495 | O9: =IF(LEN(INDEX(O$1246:O$1517,$D$54))<=0,NA(),INDEX(O$1246:O$1517,$D$54)) -> 38.513035 | P9: =IF(LEN(INDEX(P$1246:P$1517,$D$54))<=0,NA(),INDEX(P$1246:P$1517,$D$54)) -> 38.512526 | Q9: =IF(LEN(INDEX(Q$1246:Q$1517,$D$54))<=0,NA(),INDEX(Q$1246:Q$1517,$D$54)) -> 38.511965 | ... AX9: =IF(LEN(INDEX(AX$1246:AX$1517,$D$54))<=0,NA(),INDEX(AX$1246:AX$1517,$D$54)) -> 38.363697
A10: =$J$1524 -> Variable O&M costs €2010/MWh gross | I10: =INDEX(F$1526:F$1797,$D$54)&" / "&INDEX(G$1526:G$1797,$D$54)&" / "&INDEX(H$1526:H$1797,$D$54)&" / "&INDEX(I$1526:I$1797,$D$54) -> Pump storage / Pump storage / Electricity only / M | J10: =IF(LEN(INDEX(J$1526:J$1797,$D$54))<=0,NA(),INDEX(J$1526:J$1797,$D$54)) -> 0.98157239 | K10: =IF(LEN(INDEX(K$1526:K$1797,$D$54))<=0,NA(),INDEX(K$1526:K$1797,$D$54)) -> 0.98156453 | L10: =IF(LEN(INDEX(L$1526:L$1797,$D$54))<=0,NA(),INDEX(L$1526:L$1797,$D$54)) -> 0.98155584 | M10: =IF(LEN(INDEX(M$1526:M$1797,$D$54))<=0,NA(),INDEX(M$1526:M$1797,$D$54)) -> 0.98154623 | N10: =IF(LEN(INDEX(N$1526:N$1797,$D$54))<=0,NA(),INDEX(N$1526:N$1797,$D$54)) -> 0.98153562 | O10: =IF(LEN(INDEX(O$1526:O$1797,$D$54))<=0,NA(),INDEX(O$1526:O$1797,$D$54)) -> 0.9815239 | P10: =IF(LEN(INDEX(P$1526:P$1797,$D$54))<=0,NA(),INDEX(P$1526:P$1797,$D$54)) -> 0.98151094 | Q10: =IF(LEN(INDEX(Q$1526:Q$1797,$D$54))<=0,NA(),INDEX(Q$1526:Q$1797,$D$54)) -> 0.98149663 | ... AX10: =IF(LEN(INDEX(AX$1526:AX$1797,$D$54))<=0,NA(),INDEX(AX$1526:AX$1797,$D$54)) -> 0.97771796
A12: =$J$124 -> Efficiency | J12: =J$125 -> 2010 | K12: =K$125 -> 2011 | L12: =L$125 -> 2012 | M12: =M$125 -> 2013 | N12: =N$125 -> 2014 | O12: =O$125 -> 2015 | P12: =P$125 -> 2016 | Q12: =Q$125 -> 2017 | ... AX12: =AX$125 -> 2050
A13: =INDEX(F$126:F$397,$D$55) -> Pump storage | B13: =INDEX(G$126:G$397,$D$55) -> Pump storage | C13: =INDEX(H$126:H$397,$D$55) -> Electricity only | D13: =INDEX(I$126:I$397,$D$55) -> L | I13: =A13&" / "&B13&" / "&C13&" / "&D13 -> Pump storage / Pump storage / Electricity only / L | J13: =INDEX(J$126:J$397,$D$55) -> 0.77 | K13: =INDEX(K$126:K$397,$D$55) -> 0.77000217 | L13: =INDEX(L$126:L$397,$D$55) -> 0.77000446 | M13: =INDEX(M$126:M$397,$D$55) -> 0.77000686 | N13: =INDEX(N$126:N$397,$D$55) -> 0.77000938 | O13: =INDEX(O$126:O$397,$D$55) -> 0.77001204 | P13: =INDEX(P$126:P$397,$D$55) -> 0.77001482 | Q13: =INDEX(Q$126:Q$397,$D$55) -> 0.77001775 | ... AX13: =INDEX(AX$126:AX$397,$D$55) -> 0.7702666
A14: =INDEX(F$126:F$397,$D$56) -> Pump storage | B14: =INDEX(G$126:G$397,$D$56) -> Pump storage | C14: =INDEX(H$126:H$397,$D$56) -> Electricity only | D14: =INDEX(I$126:I$397,$D$56) -> M | I14: =A14&" / "&B14&" / "&C14&" / "&D14 -> Pump storage / Pump storage / Electricity only / M | J14: =INDEX(J$126:J$397,$D$56) -> 0.75 | K14: =INDEX(K$126:K$397,$D$56) -> 0.7500012 | L14: =INDEX(L$126:L$397,$D$56) -> 0.75000253 | M14: =INDEX(M$126:M$397,$D$56) -> 0.750004 | N14: =INDEX(N$126:N$397,$D$56) -> 0.75000562 | O14: =INDEX(O$126:O$397,$D$56) -> 0.75000741 | P14: =INDEX(P$126:P$397,$D$56) -> 0.75000939 | Q14: =INDEX(Q$126:Q$397,$D$56) -> 0.75001158 | ... AX14: =INDEX(AX$126:AX$397,$D$56) -> 0.75059041
A15: =INDEX(F$126:F$397,$D$57) -> Pump storage | B15: =INDEX(G$126:G$397,$D$57) -> Pump storage | C15: =INDEX(H$126:H$397,$D$57) -> Electricity only | D15: =INDEX(I$126:I$397,$D$57) -> S | I15: =A15&" / "&B15&" / "&C15&" / "&D15 -> Pump storage / Pump storage / Electricity only / S | J15: =INDEX(J$126:J$397,$D$57) -> 0.71 | K15: =INDEX(K$126:K$397,$D$57) -> 0.71000036 | L15: =INDEX(L$126:L$397,$D$57) -> 0.71000078 | M15: =INDEX(M$126:M$397,$D$57) -> 0.71000127 | N15: =INDEX(N$126:N$397,$D$57) -> 0.71000184 | O15: =INDEX(O$126:O$397,$D$57) -> 0.7100025 | P15: =INDEX(P$126:P$397,$D$57) -> 0.71000327 | Q15: =INDEX(Q$126:Q$397,$D$57) -> 0.71000416 | ... AX15: =INDEX(AX$126:AX$397,$D$57) -> 0.71085296
A16: =INDEX(F$126:F$397,$D$58) -> Pump storage | B16: =INDEX(G$126:G$397,$D$58) -> Pump storage | C16: =INDEX(H$126:H$397,$D$58) -> Electricity only | D16: =INDEX(I$126:I$397,$D$58) -> XS | I16: =A16&" / "&B16&" / "&C16&" / "&D16 -> Pump storage / Pump storage / Electricity only / XS | J16: =INDEX(J$126:J$397,$D$58) -> 0.68 | K16: =INDEX(K$126:K$397,$D$58) -> 0.68000009 | L16: =INDEX(L$126:L$397,$D$58) -> 0.68000019 | M16: =INDEX(M$126:M$397,$D$58) -> 0.68000033 | N16: =INDEX(N$126:N$397,$D$58) -> 0.68000048 | O16: =INDEX(O$126:O$397,$D$58) -> 0.68000068 | P16: =INDEX(P$126:P$397,$D$58) -> 0.68000092 | Q16: =INDEX(Q$126:Q$397,$D$58) -> 0.68000121 | ... AX16: =INDEX(AX$126:AX$397,$D$58) -> 0.68109289
I17: min | J17: =MIN(J13:J16) -> 0.68 | K17: =MIN(K13:K16) -> 0.68000009 | L17: =MIN(L13:L16) -> 0.68000019 | M17: =MIN(M13:M16) -> 0.68000033 | N17: =MIN(N13:N16) -> 0.68000048 | O17: =MIN(O13:O16) -> 0.68000068 | P17: =MIN(P13:P16) -> 0.68000092 | Q17: =MIN(Q13:Q16) -> 0.68000121 | ... AX17: =MIN(AX13:AX16) -> 0.68109289
I18: max | J18: =MAX(J13:J16) -> 0.77 | K18: =MAX(K13:K16) -> 0.77000217 | L18: =MAX(L13:L16) -> 0.77000446 | M18: =MAX(M13:M16) -> 0.77000686 | N18: =MAX(N13:N16) -> 0.77000938 | O18: =MAX(O13:O16) -> 0.77001204 | P18: =MAX(P13:P16) -> 0.77001482 | Q18: =MAX(Q13:Q16) -> 0.77001775 | ... AX18: =MAX(AX13:AX16) -> 0.7702666
I19: diff | J19: =J18-J17 -> 0.09 | K19: =K18-K17 -> 0.090002087 | L19: =L18-L17 -> 0.090004265 | M19: =M18-M17 -> 0.090006536 | N19: =N18-N17 -> 0.0900089 | O19: =O18-O17 -> 0.090011358 | P19: =P18-P17 -> 0.090013907 | Q19: =Q18-Q17 -> 0.090016546 | ... AX19: =AX18-AX17 -> 0.089173715
A20: =$J$964 -> Capital costs €2010/kW gross | J20: =J$965 -> 2010 | K20: =K$965 -> 2011 | L20: =L$965 -> 2012 | M20: =M$965 -> 2013 | N20: =N$965 -> 2014 | O20: =O$965 -> 2015 | P20: =P$965 -> 2016 | Q20: =Q$965 -> 2017 | ... AX20: =AX$965 -> 2050
A21: =INDEX(F$966:F$1237,$D$55) -> Pump storage | B21: =INDEX(G$966:G$1237,$D$55) -> Pump storage | C21: =INDEX(H$966:H$1237,$D$55) -> Electricity only | D21: =INDEX(I$966:I$1237,$D$55) -> L | I21: =A21&" / "&B21&" / "&C21&" / "&D21 -> Pump storage / Pump storage / Electricity only / L | J21: =INDEX(J$966:J$1237,$D$55) -> 3349.125 | K21: =INDEX(K$966:K$1237,$D$55) -> 3349.0777 | L21: =INDEX(L$966:L$1237,$D$55) -> 3349.028 | M21: =INDEX(M$966:M$1237,$D$55) -> 3348.9758 | N21: =INDEX(N$966:N$1237,$D$55) -> 3348.9209 | O21: =INDEX(O$966:O$1237,$D$55) -> 3348.8632 | P21: =INDEX(P$966:P$1237,$D$55) -> 3348.8026 | Q21: =INDEX(Q$966:Q$1237,$D$55) -> 3348.7389 | ... AX21: =INDEX(AX$966:AX$1237,$D$55) -> 3343.3331
A22: =INDEX(F$966:F$1237,$D$56) -> Pump storage | B22: =INDEX(G$966:G$1237,$D$56) -> Pump storage | C22: =INDEX(H$966:H$1237,$D$56) -> Electricity only | D22: =INDEX(I$966:I$1237,$D$56) -> M | I22: =A22&" / "&B22&" / "&C22&" / "&D22 -> Pump storage / Pump storage / Electricity only / M | J22: =INDEX(J$966:J$1237,$D$56) -> 3851.4937 | K22: =INDEX(K$966:K$1237,$D$56) -> 3851.4629 | L22: =INDEX(L$966:L$1237,$D$56) -> 3851.4288 | M22: =INDEX(M$966:M$1237,$D$56) -> 3851.3911 | N22: =INDEX(N$966:N$1237,$D$56) -> 3851.3495 | O22: =INDEX(O$966:O$1237,$D$56) -> 3851.3035 | P22: =INDEX(P$966:P$1237,$D$56) -> 3851.2526 | Q22: =INDEX(Q$966:Q$1237,$D$56) -> 3851.1965 | ... AX22: =INDEX(AX$966:AX$1237,$D$56) -> 3836.3697
A23: =INDEX(F$966:F$1237,$D$57) -> Pump storage | B23: =INDEX(G$966:G$1237,$D$57) -> Pump storage | C23: =INDEX(H$966:H$1237,$D$57) -> Electricity only | D23: =INDEX(I$966:I$1237,$D$57) -> S | I23: =A23&" / "&B23&" / "&C23&" / "&D23 -> Pump storage / Pump storage / Electricity only / S | J23: =INDEX(J$966:J$1237,$D$57) -> 4814.3672 | K23: =INDEX(K$966:K$1237,$D$57) -> 4814.3549 | L23: =INDEX(L$966:L$1237,$D$57) -> 4814.3406 | M23: =INDEX(M$966:M$1237,$D$57) -> 4814.324 | N23: =INDEX(N$966:N$1237,$D$57) -> 4814.3047 | O23: =INDEX(O$966:O$1237,$D$57) -> 4814.2823 | P23: =INDEX(P$966:P$1237,$D$57) -> 4814.2563 | Q23: =INDEX(Q$966:Q$1237,$D$57) -> 4814.226 | ... AX23: =INDEX(AX$966:AX$1237,$D$57) -> 4785.5525
A24: =INDEX(F$966:F$1237,$D$58) -> Pump storage | B24: =INDEX(G$966:G$1237,$D$58) -> Pump storage | C24: =INDEX(H$966:H$1237,$D$58) -> Electricity only | D24: =INDEX(I$966:I$1237,$D$58) -> XS | I24: =A24&" / "&B24&" / "&C24&" / "&D24 -> Pump storage / Pump storage / Electricity only / XS | J24: =INDEX(J$966:J$1237,$D$58) -> 6499.3957 | K24: =INDEX(K$966:K$1237,$D$58) -> 6499.3915 | L24: =INDEX(L$966:L$1237,$D$58) -> 6499.3864 | M24: =INDEX(M$966:M$1237,$D$58) -> 6499.3802 | N24: =INDEX(N$966:N$1237,$D$58) -> 6499.3725 | O24: =INDEX(O$966:O$1237,$D$58) -> 6499.3632 | P24: =INDEX(P$966:P$1237,$D$58) -> 6499.3519 | Q24: =INDEX(Q$966:Q$1237,$D$58) -> 6499.338 | ... AX24: =INDEX(AX$966:AX$1237,$D$58) -> 6447.4179
I25: min | J25: =MIN(J21:J24) -> 3349.125 | K25: =MIN(K21:K24) -> 3349.0777 | L25: =MIN(L21:L24) -> 3349.028 | M25: =MIN(M21:M24) -> 3348.9758 | N25: =MIN(N21:N24) -> 3348.9209 | O25: =MIN(O21:O24) -> 3348.8632 | P25: =MIN(P21:P24) -> 3348.8026 | Q25: =MIN(Q21:Q24) -> 3348.7389 | ... AX25: =MIN(AX21:AX24) -> 3343.3331
I26: max | J26: =MAX(J21:J24) -> 6499.3957 | K26: =MAX(K21:K24) -> 6499.3915 | L26: =MAX(L21:L24) -> 6499.3864 | M26: =MAX(M21:M24) -> 6499.3802 | N26: =MAX(N21:N24) -> 6499.3725 | O26: =MAX(O21:O24) -> 6499.3632 | P26: =MAX(P21:P24) -> 6499.3519 | Q26: =MAX(Q21:Q24) -> 6499.338 | ... AX26: =MAX(AX21:AX24) -> 6447.4179
I27: diff | J27: =J26-J25 -> 3150.2707 | K27: =K26-K25 -> 3150.3138 | L27: =L26-L25 -> 3150.3584 | M27: =M26-M25 -> 3150.4044 | N27: =N26-N25 -> 3150.4516 | O27: =O26-O25 -> 3150.5 | P27: =P26-P25 -> 3150.5492 | Q27: =Q26-Q25 -> 3150.5991 | ... AX27: =AX26-AX25 -> 3104.0848
A28: =$J$1244 -> Fix O&M costs €2010/kW gross | J28: =J$1245 -> 2010 | K28: =K$1245 -> 2011 | L28: =L$1245 -> 2012 | M28: =M$1245 -> 2013 | N28: =N$1245 -> 2014 | O28: =O$1245 -> 2015 | P28: =P$1245 -> 2016 | Q28: =Q$1245 -> 2017 | ... AX28: =AX$1245 -> 2050
A29: =INDEX(F$1246:F$1517,$D$55) -> Pump storage | B29: =INDEX(G$1246:G$1517,$D$55) -> Pump storage | C29: =INDEX(H$1246:H$1517,$D$55) -> Electricity only | D29: =INDEX(I$1246:I$1517,$D$55) -> L | I29: =A29&" / "&B29&" / "&C29&" / "&D29 -> Pump storage / Pump storage / Electricity only / L | J29: =INDEX(J$1246:J$1517,$D$55) -> 33.49125 | K29: =INDEX(K$1246:K$1517,$D$55) -> 33.490777 | L29: =INDEX(L$1246:L$1517,$D$55) -> 33.49028 | M29: =INDEX(M$1246:M$1517,$D$55) -> 33.489758 | N29: =INDEX(N$1246:N$1517,$D$55) -> 33.489209 | O29: =INDEX(O$1246:O$1517,$D$55) -> 33.488632 | P29: =INDEX(P$1246:P$1517,$D$55) -> 33.488026 | Q29: =INDEX(Q$1246:Q$1517,$D$55) -> 33.487389 | ... AX29: =INDEX(AX$1246:AX$1517,$D$55) -> 33.433331
A30: =INDEX(F$1246:F$1517,$D$56) -> Pump storage | B30: =INDEX(G$1246:G$1517,$D$56) -> Pump storage | C30: =INDEX(H$1246:H$1517,$D$56) -> Electricity only | D30: =INDEX(I$1246:I$1517,$D$56) -> M | I30: =A30&" / "&B30&" / "&C30&" / "&D30 -> Pump storage / Pump storage / Electricity only / M | J30: =INDEX(J$1246:J$1517,$D$56) -> 38.514937 | K30: =INDEX(K$1246:K$1517,$D$56) -> 38.514629 | L30: =INDEX(L$1246:L$1517,$D$56) -> 38.514288 | M30: =INDEX(M$1246:M$1517,$D$56) -> 38.513911 | N30: =INDEX(N$1246:N$1517,$D$56) -> 38.513495 | O30: =INDEX(O$1246:O$1517,$D$56) -> 38.513035 | P30: =INDEX(P$1246:P$1517,$D$56) -> 38.512526 | Q30: =INDEX(Q$1246:Q$1517,$D$56) -> 38.511965 | ... AX30: =INDEX(AX$1246:AX$1517,$D$56) -> 38.363697
A31: =INDEX(F$1246:F$1517,$D$57) -> Pump storage | B31: =INDEX(G$1246:G$1517,$D$57) -> Pump storage | C31: =INDEX(H$1246:H$1517,$D$57) -> Electricity only | D31: =INDEX(I$1246:I$1517,$D$57) -> S | I31: =A31&" / "&B31&" / "&C31&" / "&D31 -> Pump storage / Pump storage / Electricity only / S | J31: =INDEX(J$1246:J$1517,$D$57) -> 48.143672 | K31: =INDEX(K$1246:K$1517,$D$57) -> 48.143549 | L31: =INDEX(L$1246:L$1517,$D$57) -> 48.143406 | M31: =INDEX(M$1246:M$1517,$D$57) -> 48.14324 | N31: =INDEX(N$1246:N$1517,$D$57) -> 48.143047 | O31: =INDEX(O$1246:O$1517,$D$57) -> 48.142823 | P31: =INDEX(P$1246:P$1517,$D$57) -> 48.142563 | Q31: =INDEX(Q$1246:Q$1517,$D$57) -> 48.14226 | ... AX31: =INDEX(AX$1246:AX$1517,$D$57) -> 47.855525
A32: =INDEX(F$1246:F$1517,$D$58) -> Pump storage | B32: =INDEX(G$1246:G$1517,$D$58) -> Pump storage | C32: =INDEX(H$1246:H$1517,$D$58) -> Electricity only | D32: =INDEX(I$1246:I$1517,$D$58) -> XS | I32: =A32&" / "&B32&" / "&C32&" / "&D32 -> Pump storage / Pump storage / Electricity only / XS | J32: =INDEX(J$1246:J$1517,$D$58) -> 64.993957 | K32: =INDEX(K$1246:K$1517,$D$58) -> 64.993915 | L32: =INDEX(L$1246:L$1517,$D$58) -> 64.993864 | M32: =INDEX(M$1246:M$1517,$D$58) -> 64.993802 | N32: =INDEX(N$1246:N$1517,$D$58) -> 64.993725 | O32: =INDEX(O$1246:O$1517,$D$58) -> 64.993632 | P32: =INDEX(P$1246:P$1517,$D$58) -> 64.993519 | Q32: =INDEX(Q$1246:Q$1517,$D$58) -> 64.99338 | ... AX32: =INDEX(AX$1246:AX$1517,$D$58) -> 64.474179
I33: min | J33: =MIN(J29:J32) -> 33.49125 | K33: =MIN(K29:K32) -> 33.490777 | L33: =MIN(L29:L32) -> 33.49028 | M33: =MIN(M29:M32) -> 33.489758 | N33: =MIN(N29:N32) -> 33.489209 | O33: =MIN(O29:O32) -> 33.488632 | P33: =MIN(P29:P32) -> 33.488026 | Q33: =MIN(Q29:Q32) -> 33.487389 | ... AX33: =MIN(AX29:AX32) -> 33.433331
I34: max | J34: =MAX(J29:J32) -> 64.993957 | K34: =MAX(K29:K32) -> 64.993915 | L34: =MAX(L29:L32) -> 64.993864 | M34: =MAX(M29:M32) -> 64.993802 | N34: =MAX(N29:N32) -> 64.993725 | O34: =MAX(O29:O32) -> 64.993632 | P34: =MAX(P29:P32) -> 64.993519 | Q34: =MAX(Q29:Q32) -> 64.99338 | ... AX34: =MAX(AX29:AX32) -> 64.474179
I35: diff | J35: =J34-J33 -> 31.502707 | K35: =K34-K33 -> 31.503138 | L35: =L34-L33 -> 31.503584 | M35: =M34-M33 -> 31.504044 | N35: =N34-N33 -> 31.504516 | O35: =O34-O33 -> 31.505 | P35: =P34-P33 -> 31.505492 | Q35: =Q34-Q33 -> 31.505991 | ... AX35: =AX34-AX33 -> 31.040848
A36: =$J$1524 -> Variable O&M costs €2010/MWh gross | J36: =J$1525 -> 2010 | K36: =K$1525 -> 2011 | L36: =L$1525 -> 2012 | M36: =M$1525 -> 2013 | N36: =N$1525 -> 2014 | O36: =O$1525 -> 2015 | P36: =P$1525 -> 2016 | Q36: =Q$1525 -> 2017 | ... AX36: =AX$1525 -> 2050
A37: =INDEX(F$1526:F$1797,$D$55) -> Pump storage | B37: =INDEX(G$1526:G$1797,$D$55) -> Pump storage | C37: =INDEX(H$1526:H$1797,$D$55) -> Electricity only | D37: =INDEX(I$1526:I$1797,$D$55) -> L | I37: =A37&" / "&B37&" / "&C37&" / "&D37 -> Pump storage / Pump storage / Electricity only / L | J37: =INDEX(J$1526:J$1797,$D$55) -> 0.98157239 | K37: =INDEX(K$1526:K$1797,$D$55) -> 0.98155853 | L37: =INDEX(L$1526:L$1797,$D$55) -> 0.98154397 | M37: =INDEX(M$1526:M$1797,$D$55) -> 0.98152866 | N37: =INDEX(N$1526:N$1797,$D$55) -> 0.98151258 | O37: =INDEX(O$1526:O$1797,$D$55) -> 0.98149567 | P37: =INDEX(P$1526:P$1797,$D$55) -> 0.98147791 | Q37: =INDEX(Q$1526:Q$1797,$D$55) -> 0.98145924 | ... AX37: =INDEX(AX$1526:AX$1797,$D$55) -> 0.97987488
A38: =INDEX(F$1526:F$1797,$D$56) -> Pump storage | B38: =INDEX(G$1526:G$1797,$D$56) -> Pump storage | C38: =INDEX(H$1526:H$1797,$D$56) -> Electricity only | D38: =INDEX(I$1526:I$1797,$D$56) -> M | I38: =A38&" / "&B38&" / "&C38&" / "&D38 -> Pump storage / Pump storage / Electricity only / M | J38: =INDEX(J$1526:J$1797,$D$56) -> 0.98157239 | K38: =INDEX(K$1526:K$1797,$D$56) -> 0.98156453 | L38: =INDEX(L$1526:L$1797,$D$56) -> 0.98155584 | M38: =INDEX(M$1526:M$1797,$D$56) -> 0.98154623 | N38: =INDEX(N$1526:N$1797,$D$56) -> 0.98153562 | O38: =INDEX(O$1526:O$1797,$D$56) -> 0.9815239 | P38: =INDEX(P$1526:P$1797,$D$56) -> 0.98151094 | Q38: =INDEX(Q$1526:Q$1797,$D$56) -> 0.98149663 | ... AX38: =INDEX(AX$1526:AX$1797,$D$56) -> 0.97771796
A39: =INDEX(F$1526:F$1797,$D$57) -> Pump storage | B39: =INDEX(G$1526:G$1797,$D$57) -> Pump storage | C39: =INDEX(H$1526:H$1797,$D$57) -> Electricity only | D39: =INDEX(I$1526:I$1797,$D$57) -> S | I39: =A39&" / "&B39&" / "&C39&" / "&D39 -> Pump storage / Pump storage / Electricity only / S | J39: =INDEX(J$1526:J$1797,$D$57) -> 0.98157239 | K39: =INDEX(K$1526:K$1797,$D$57) -> 0.98156988 | L39: =INDEX(L$1526:L$1797,$D$57) -> 0.98156697 | M39: =INDEX(M$1526:M$1797,$D$57) -> 0.98156358 | N39: =INDEX(N$1526:N$1797,$D$57) -> 0.98155965 | O39: =INDEX(O$1526:O$1797,$D$57) -> 0.98155508 | P39: =INDEX(P$1526:P$1797,$D$57) -> 0.98154977 | Q39: =INDEX(Q$1526:Q$1797,$D$57) -> 0.98154361 | ... AX39: =INDEX(AX$1526:AX$1797,$D$57) -> 0.97569753
A40: =INDEX(F$1526:F$1797,$D$58) -> Pump storage | B40: =INDEX(G$1526:G$1797,$D$58) -> Pump storage | C40: =INDEX(H$1526:H$1797,$D$58) -> Electricity only | D40: =INDEX(I$1526:I$1797,$D$58) -> XS | I40: =A40&" / "&B40&" / "&C40&" / "&D40 -> Pump storage / Pump storage / Electricity only / XS | J40: =INDEX(J$1526:J$1797,$D$58) -> 0.98157239 | K40: =INDEX(K$1526:K$1797,$D$58) -> 0.98157176 | L40: =INDEX(L$1526:L$1797,$D$58) -> 0.98157099 | M40: =INDEX(M$1526:M$1797,$D$58) -> 0.98157005 | N40: =INDEX(N$1526:N$1797,$D$58) -> 0.98156889 | O40: =INDEX(O$1526:O$1797,$D$58) -> 0.98156749 | P40: =INDEX(P$1526:P$1797,$D$58) -> 0.98156577 | Q40: =INDEX(Q$1526:Q$1797,$D$58) -> 0.98156367 | ... AX40: =INDEX(AX$1526:AX$1797,$D$58) -> 0.97372244
I41: min | J41: =MIN(J37:J40) -> 0.98157239 | K41: =MIN(K37:K40) -> 0.98155853 | L41: =MIN(L37:L40) -> 0.98154397 | M41: =MIN(M37:M40) -> 0.98152866 | N41: =MIN(N37:N40) -> 0.98151258 | O41: =MIN(O37:O40) -> 0.98149567 | P41: =MIN(P37:P40) -> 0.98147791 | Q41: =MIN(Q37:Q40) -> 0.98145924 | ... AX41: =MIN(AX37:AX40) -> 0.97372244
I42: max | J42: =MAX(J37:J40) -> 0.98157239 | K42: =MAX(K37:K40) -> 0.98157176 | L42: =MAX(L37:L40) -> 0.98157099 | M42: =MAX(M37:M40) -> 0.98157005 | N42: =MAX(N37:N40) -> 0.98156889 | O42: =MAX(O37:O40) -> 0.98156749 | P42: =MAX(P37:P40) -> 0.98156577 | Q42: =MAX(Q37:Q40) -> 0.98156367 | ... AX42: =MAX(AX37:AX40) -> 0.97987488
I43: diff | J43: =J42-J41 -> 0 | K43: =K42-K41 -> 1.3225797e-05 | L43: =L42-L41 -> 2.7018044e-05 | M43: =M42-M41 -> 4.1381553e-05 | N43: =N42-N41 -> 5.6316077e-05 | O43: =O42-O41 -> 7.1814873e-05 | P43: =P42-P41 -> 8.7862945e-05 | Q43: =Q42-Q41 -> 0.00010443488 | ... AX43: =AX42-AX41 -> 0.0061524452
A44: min
A45: range of values (different sizes)
A46: 17 | B46: 1 | C46: 1 | D46: 2
B47: =IF(LEN(B50)=0,1,IF(LEN(B51)=0,MIN(2,B46),IF(LEN(B52)=0,MIN(3,B46),MIN(4,B46)))) -> 1 | C47: =IF(LEN(C50)=0,1,IF(LEN(C51)=0,MIN(2,C46),IF(LEN(C52)=0,MIN(3,C46),MIN(4,C46)))) -> 1 | D47: =IF(LEN(D50)=0,1,IF(LEN(D51)=0,MIN(2,D46),IF(LEN(D52)=0,MIN(3,D46),MIN(4,D46)))) -> 2
B48: =INDEX(visuD!$H$1:$H$17,$A$46) -> 38 | C48: =INDEX(visuD!$H$18:$H$56,$B$48+$B$47) -> 104 | D48: =INDEX(visuD!$H$57:$H$161,$C$48+$C$47) -> 268
A49: =visuD!A1 -> Nuclear power plants | B49: =TRIM(INDEX(visuD!$D$1:$G$17,$A$46,1)) -> Pump storage | C49: =TRIM(INDEX(visuD!$D$18:$G$56,$B$48+$B$47,1)) -> Electricity only | D49: =TRIM(INDEX(visuD!$D$57:$G$161,$C$48+$C$47,1)) -> L
A50: =visuD!A2 -> Coal fired power plants | B50: =TRIM(INDEX(visuD!$D$1:$G$17,$A$46,2)) | C50: =TRIM(INDEX(visuD!$D$18:$G$56,$B$48+$B$47,2)) | D50: =TRIM(INDEX(visuD!$D$57:$G$161,$C$48+$C$47,2)) -> M
A51: =visuD!A3 -> Lignite fired power plants | B51: =TRIM(INDEX(visuD!$D$1:$G$17,$A$46,3)) | C51: =TRIM(INDEX(visuD!$D$18:$G$56,$B$48+$B$47,3)) | D51: =TRIM(INDEX(visuD!$D$57:$G$161,$C$48+$C$47,3)) -> S
A52: =visuD!A4 -> Gas fired power plants (Natural gas, biogas) | B52: =TRIM(INDEX(visuD!$D$1:$G$17,$A$46,4)) | C52: =TRIM(INDEX(visuD!$D$18:$G$56,$B$48+$B$47,4)) | D52: =TRIM(INDEX(visuD!$D$57:$G$161,$C$48+$C$47,4)) -> XS
A53: =visuD!A5 -> Derived gas fired power plants
A54: =visuD!A6 -> Refinery gas fired power plants | D54: =D48+D47 -> 270
A55: =visuD!A7 -> Diesel oil fired power plants | D55: =D48+1 -> 269
A56: =visuD!A8 -> Fuel oil fired power plants | D56: =IF(LEN(D50)>0,D55+1,D55) -> 270
A57: =visuD!A9 -> Biomass and waste fired power plants | D57: =IF(LEN(D51)>0,D56+1,D56) -> 271
A58: =visuD!A10 -> Fuel cells | D58: =IF(LEN(D52)>0,D57+1,D57) -> 272
A59: =visuD!A11 -> Wind power plants
A60: =visuD!A12 -> Solar PV power plants
A61: =visuD!A13 -> Solar thermal power plants
A62: =visuD!A14 -> Geothermal power plants
A63: =visuD!A15 -> Tide, wave and ocean power plants
A64: =visuD!A16 -> Hydro plants
A65: =visuD!A17 -> Pump storage
A124: Type | B124: Technology | C124: Co-generation | D124: Size | J124: Efficiency
J125: 2010 | K125: 2011 | L125: 2012 | M125: 2013 | N125: 2014 | O125: 2015 | P125: 2016 | Q125: 2017 | R125: 2018 | S125: 2019 | T125: 2020 | U125: 2021 | V125: 2022 | W125: 2023 | X125: 2024 | Y125: 2025 | Z125: 2026 | AA125: 2027 | AB125: 2028 | AC125: 2029 | AD125: 2030 | AE125: 2031 | AF125: 2032 | AG125: 2033 | AH125: 2034 | AI125: 2035 | AJ125: 2036 | AK125: 2037 | AL125: 2038 | AM125: 2039 | AN125: 2040 | AO125: 2041 | AP125: 2042 | AQ125: 2043 | AR125: 2044 | AS125: 2045 | AT125: 2046 | AU125: 2047 | AV125: 2048 | AW125: 2049 | AX125: 2050
A126: Nuclear power plants | B126: Nuclear - current | C126: Electricity only | D126: L | E126: =A126&"/"&B126&"/"&C126&"/"&D126 -> Nuclear power plants/Nuclear - current/Electricity only/L | F126: =A126 -> Nuclear power plants | G126: =B126 -> Nuclear - current | H126: =C126 -> Electricity only | I126: =D126 -> L | J126: 0.33333333 | K126: 0.33333333 | L126: 0.33333333 | M126: 0.33333333 | N126: 0.33333333 | O126: 0.33333333 | P126: 0.33333333 | Q126: 0.33333333 | R126: 0.33333333 | S126: 0.33333333 | T126: 0.33333333 | U126: 0.33333333 | V126: 0.33333333 | W126: 0.33333333 | X126: 0.33333333 | Y126: 0.33333333 | Z126: 0.33333333 | AA126: 0.33333333 | AB126: 0.33333333 | AC126: 0.33333333 | AD126: 0.33333333 | AE126: 0.33333333 | AF126: 0.33333333 | AG126: 0.33333333 | AH126: 0.33333333 | AI126: 0.33333333 | AJ126: 0.33333333 | AK126: 0.33333333 | AL126: 0.33333333 | AM126: 0.33333333 | AN126: 0.33333333 | AO126: 0.33333333 | AP126: 0.33333333 | AQ126: 0.33333333 | AR126: 0.33333333 | AS126: 0.33333333 | AT126: 0.33333333 | AU126: 0.33333333 | AV126: 0.33333333 | AW126: 0.33333333 | AX126: 0.33333333
D127: M | E127: =A126&"/"&B126&"/"&C126&"/"&D127 -> Nuclear power plants/Nuclear - current/Electricity only/M | F127: =A126 -> Nuclear power plants | G127: =B126 -> Nuclear - current | H127: =C126 -> Electricity only | I127: =D127 -> M | J127: 0.33333333 | K127: 0.33333333 | L127: 0.33333333 | M127: 0.33333333 | N127: 0.33333333 | O127: 0.33333333 | P127: 0.33333333 | Q127: 0.33333333 | R127: 0.33333333 | S127: 0.33333333 | T127: 0.33333333 | U127: 0.33333333 | V127: 0.33333333 | W127: 0.33333333 | X127: 0.33333333 | Y127: 0.33333333 | Z127: 0.33333333 | AA127: 0.33333333 | AB127: 0.33333333 | AC127: 0.33333333 | AD127: 0.33333333 | AE127: 0.33333333 | AF127: 0.33333333 | AG127: 0.33333333 | AH127: 0.33333333 | AI127: 0.33333333 | AJ127: 0.33333333 | AK127: 0.33333333 | AL127: 0.33333333 | AM127: 0.33333333 | AN127: 0.33333333 | AO127: 0.33333333 | AP127: 0.33333333 | AQ127: 0.33333333 | AR127: 0.33333333 | AS127: 0.33333333 | AT127: 0.33333333 | AU127: 0.33333333 | AV127: 0.33333333 | AW127: 0.33333333 | AX127: 0.33333333
B128: Nuclear III | C128: Electricity only | D128: L | E128: =A126&"/"&B128&"/"&C128&"/"&D128 -> Nuclear power plants/Nuclear III/Electricity only/L | F128: =A126 -> Nuclear power plants | G128: =B128 -> Nuclear III | H128: =C128 -> Electricity only | I128: =D128 -> L | J128: 0.38461538 | K128: 0.38463108 | L128: 0.38465021 | M128: 0.38467349 | N128: 0.38470182 | O128: 0.38473626 | P128: 0.38477809 | Q128: 0.38482882 | R128: 0.38489026 | S128: 0.38496453 | T128: 0.38505412 | U128: 0.38516189 | V128: 0.3852911 | W128: 0.38544543 | X128: 0.38562888 | Y128: 0.38584575 | Z128: 0.38610039 | AA128: 0.38639705 | AB128: 0.38673946 | AC128: 0.3871304 | AD128: 0.38757119 | AE128: 0.38806107 | AF128: 0.38859671 | AG128: 0.38917182 | AH128: 0.38977702 | AI128: 0.39040021 | AJ128: 0.39102724 | AK128: 0.39164308 | AL128: 0.39223316 | AM128: 0.39278473 | AN128: 0.39328792 | AO128: 0.39373639 | AP128: 0.39412738 | AQ128: 0.3944614 | AR128: 0.39474154 | AS128: 0.39497263 | AT128: 0.39516052 | AU128: 0.39531135 | AV128: 0.39543114 | AW128: 0.39552539 | AX128: 0.39559896
D129: M | E129: =A126&"/"&B128&"/"&C128&"/"&D129 -> Nuclear power plants/Nuclear III/Electricity only/M | F129: =A126 -> Nuclear power plants | G129: =B128 -> Nuclear III | H129: =C128 -> Electricity only | I129: =D129 -> M | J129: 0.38461538 | K129: 0.3846356 | L129: 0.38465901 | M129: 0.38468612 | N129: 0.38471748 | O129: 0.38475374 | P129: 0.38479563 | Q129: 0.38484399 | R129: 0.38489975 | S129: 0.38496398 | T129: 0.38503785 | U129: 0.38512268 | V129: 0.38521992 | W129: 0.38533115 | X129: 0.38545809 | Y129: 0.38560256 | Z129: 0.38576647 | AA129: 0.38595178 | AB129: 0.38616043 | AC129: 0.38639432 | AD129: 0.38665516 | AE129: 0.38694438 | AF129: 0.38726305 | AG129: 0.38761168 | AH129: 0.38799014 | AI129: 0.38839746 | AJ129: 0.38883182 | AK129: 0.38929039 | AL129: 0.38976938 | AM129: 0.39026407 | AN129: 0.39076897 | AO129: 0.39127798 | AP129: 0.39178472 | AQ129: 0.39228278 | AR129: 0.39276607 | AS129: 0.39322911 | AT129: 0.39366726 | AU129: 0.39407687 | AV129: 0.3944554 | AW129: 0.39480139 | AX129: 0.39511441
D130: S | E130: =A126&"/"&B128&"/"&C128&"/"&D130 -> Nuclear power plants/Nuclear III/Electricity only/S | F130: =A126 -> Nuclear power plants | G130: =B128 -> Nuclear III | H130: =C128 -> Electricity only | I130: =D130 -> S | Y130: 0.38573368 | Z130: 0.38587243 | AA130: 0.38602258 | AB130: 0.38618474 | AC130: 0.3863595 | AD130: 0.3865474 | AE130: 0.38674892 | AF130: 0.38696446 | AG130: 0.38719434 | AH130: 0.38743874 | AI130: 0.38769772 | AJ130: 0.38797118 | AK130: 0.38825884 | AL130: 0.38856025 | AM130: 0.38887473 | AN130: 0.38920142 | AO130: 0.38953921 | AP130: 0.38988681 | AQ130: 0.39024271 | AR130: 0.39060525 | AS130: 0.39097257 | AT130: 0.39134273 | AU130: 0.39171367 | AV130: 0.3920833 | AW130: 0.39244954 | AX130: 0.39281036
B131: Nuclear IV | C131: Electricity only | D131: L | E131: =A126&"/"&B131&"/"&C131&"/"&D131 -> Nuclear power plants/Nuclear IV/Electricity only/L | F131: =A126 -> Nuclear power plants | G131: =B131 -> Nuclear IV | H131: =C131 -> Electricity only | I131: =D131 -> L | AI131: 0.40892889 | AJ131: 0.40909272 | AK131: 0.40929012 | AL131: 0.40952727 | AM131: 0.40981113 | AN131: 0.41014942 | AO131: 0.41055046 | AP131: 0.41102284 | AQ131: 0.41157497 | AR131: 0.41221435 | AS131: 0.41294659 | AT131: 0.41377417 | AU131: 0.41469497 | AV131: 0.41570086 | AW131: 0.4167765 | AX131: 0.41789888
D132: M | E132: =A126&"/"&B131&"/"&C131&"/"&D132 -> Nuclear power plants/Nuclear IV/Electricity only/M | F132: =A126 -> Nuclear power plants | G132: =B131 -> Nuclear IV | H132: =C131 -> Electricity only | I132: =D132 -> M | AI132: 0.40835763 | AJ132: 0.40841233 | AK132: 0.40848222 | AL132: 0.40857143 | AM132: 0.40868509 | AN132: 0.40882958 | AO132: 0.40901277 | AP132: 0.40924419 | AQ132: 0.40953521 | AR132: 0.40989906 | AS132: 0.41035066 | AT132: 0.41090597 | AU132: 0.4115809 | AV132: 0.41238929 | AW132: 0.41334009 | AX132: 0.41443369
A133: Coal fired power plants | B133: Integrated gasification combined cycle | C133: Electricity only | D133: L | E133: =A133&"/"&B133&"/"&C133&"/"&D133 -> Coal fired power plants/Integrated gasification combined cycle/Electricity only/L | F133: =A133 -> Coal fired power plants | G133: =B133 -> Integrated gasification combined cycle | H133: =C133 -> Electricity only | I133: =D133 -> L | J133: 0.48780488 | K133: 0.48780606 | L133: 0.48780758 | M133: 0.48780952 | N133: 0.48781202 | O133: 0.48781523 | P133: 0.48781935 | Q133: 0.48782464 | R133: 0.48783144 | S133: 0.48784016 | T133: 0.48785135 | U133: 0.48786572 | V133: 0.48788415 | W133: 0.48790782 | X133: 0.48793818 | Y133: 0.48797712 | Z133: 0.48802707 | AA133: 0.4880911 | AB133: 0.48817316 | AC133: 0.48827824 | AD133: 0.48841272 | AE133: 0.48858466 | AF133: 0.48880424 | AG133: 0.4890842 | AH133: 0.48944046 | AI133: 0.48989267 | AJ133: 0.49046485 | AK133: 0.49118585 | AL133: 0.49208971 | AM133: 0.49321542 | AN133: 0.49460592 | AO133: 0.49630591 | AP133: 0.4983578 | AQ133: 0.50079567 | AR133: 0.50363692 | AS133: 0.5068726 | AT133: 0.51045804 | AU133: 0.51430709 | AV133: 0.51829349 | AW133: 0.52226217 | AX133: 0.52604997
D134: M | E134: =A133&"/"&B133&"/"&C133&"/"&D134 -> Coal fired power plants/Integrated gasification combined cycle/Electricity only/M | F134: =A133 -> Coal fired power plants | G134: =B133 -> Integrated gasification combined cycle | H134: =C133 -> Electricity only | I134: =D134 -> M | J134: 0.46457607 | K134: 0.46458196 | L134: 0.46458915 | M134: 0.46459792 | N134: 0.46460864 | O134: 0.46462172 | P134: 0.4646377 | Q134: 0.46465721 | R134: 0.46468102 | S134: 0.46471009 | T134: 0.46474556 | U134: 0.46478885 | V134: 0.46484167 | W134: 0.46490609 | X134: 0.46498464 | Y134: 0.46508038 | Z134: 0.46519703 | AA134: 0.46533906 | AB134: 0.4655119 | AC134: 0.46572204 | AD134: 0.46597728 | AE134: 0.46628692 | AF134: 0.466662 | AG134: 0.46711553 | AH134: 0.46766272 | AI134: 0.46832117 | AJ134: 0.46911095 | AK134: 0.47005458 | AL134: 0.4711768 | AM134: 0.47250393 | AN134: 0.47406287 | AO134: 0.47587952 | AP134: 0.4779765 | AQ134: 0.48037019 | AR134: 0.48306711 | AS134: 0.48606009 | AT134: 0.48932456 | AU134: 0.49281604 | AV134: 0.49646953 | AW134: 0.50020197 | AX134: 0.50391786
C135: CHP | D135: L | E135: =A133&"/"&B133&"/"&C135&"/"&D135 -> Coal fired power plants/Integrated gasification combined cycle/CHP/L | F135: =A133 -> Coal fired power plants | G135: =B133 -> Integrated gasification combined cycle | H135: =C135 -> CHP | I135: =D135 -> L | J135: 0.44345898 | K135: 0.44345998 | L135: 0.44346127 | M135: 0.44346292 | N135: 0.44346504 | O135: 0.44346777 | P135: 0.44347126 | Q135: 0.44347575 | R135: 0.44348151 | S135: 0.44348891 | T135: 0.44349841 | U135: 0.4435106 | V135: 0.44352624 | W135: 0.44354632 | X135: 0.44357208 | Y135: 0.44360512 | Z135: 0.4436475 | AA135: 0.44370182 | AB135: 0.44377142 | AC135: 0.44386056 | AD135: 0.44397463 | AE135: 0.44412046 | AF135: 0.44430667 | AG135: 0.44454405 | AH135: 0.44484607 | AI135: 0.44522935 | AJ135: 0.44571414 | AK135: 0.4463248 | AL135: 0.44708996 | AM135: 0.44804234 | AN135: 0.44921784 | AO135: 0.45065363 | AP135: 0.45238463 | AQ135: 0.45443838 | AR135: 0.45682801 | AS135: 0.45954414 | AT135: 0.46254728 | AU135: 0.46576342 | AV135: 0.4690857 | AW135: 0.4723844 | AX135: 0.47552441
D136: M | E136: =A133&"/"&B133&"/"&C135&"/"&D136 -> Coal fired power plants/Integrated gasification combined cycle/CHP/M | F136: =A133 -> Coal fired power plants | G136: =B133 -> Integrated gasification combined cycle | H136: =C135 -> CHP | I136: =D136 -> M | J136: 0.42234189 | K136: 0.42234693 | L136: 0.42235309 | M136: 0.42236061 | N136: 0.4223698 | O136: 0.42238101 | P136: 0.42239471 | Q136: 0.42241143 | R136: 0.42243184 | S136: 0.42245675 | T136: 0.42248716 | U136: 0.42252426 | V136: 0.42256952 | W136: 0.42262473 | X136: 0.42269204 | Y136: 0.42277409 | Z136: 0.42287404 | AA136: 0.42299574 | AB136: 0.42314382 | AC136: 0.42332384 | AD136: 0.42354247 | AE136: 0.42380765 | AF136: 0.42412882 | AG136: 0.42451709 | AH136: 0.4249854 | AI136: 0.42554875 | AJ136: 0.42622419 | AK136: 0.42703084 | AL136: 0.42798961 | AM136: 0.42912268 | AN136: 0.4304526 | AO136: 0.43200092 | AP136: 0.4337862 | AQ136: 0.43582149 | AR136: 0.43811128 | AS136: 0.44064824 | AT136: 0.44341025 | AU136: 0.44635839 | AV136: 0.44943668 | AW136: 0.45257437 | AX136: 0.45569091
C137: Electricity only with CCS | D137: L | E137: =A133&"/"&B133&"/"&C137&"/"&D137 -> Coal fired power plants/Integrated gasification combined cycle/Electricity only with CCS/L | F137: =A133 -> Coal fired power plants | G137: =B133 -> Integrated gasification combined cycle | H137: =C137 -> Electricity only with CCS | I137: =D137 -> L | AE137: 0.46464215 | AF137: 0.46466524 | AG137: 0.46469638 | AH137: 0.46473839 | AI137: 0.46479501 | AJ137: 0.46487132 | AK137: 0.46497409 | AL137: 0.46511239 | AM137: 0.46529829 | AN137: 0.46554782 | AO137: 0.46588212 | AP137: 0.46632879 | AQ137: 0.46692354 | AR137: 0.46771176 | AS137: 0.4687499 | AT137: 0.47010598 | AU137: 0.47185827 | AV137: 0.47409074 | AW137: 0.47688351 | AX137: 0.48029706
D138: M | E138: =A133&"/"&B133&"/"&C137&"/"&D138 -> Coal fired power plants/Integrated gasification combined cycle/Electricity only with CCS/M | F138: =A133 -> Coal fired power plants | G138: =B133 -> Integrated gasification combined cycle | H138: =C137 -> Electricity only with CCS | I138: =D138 -> M | AE138: 0.44247949 | AF138: 0.44249042 | AG138: 0.44250592 | AH138: 0.44252791 | AI138: 0.44255909 | AJ138: 0.4426033 | AK138: 0.44266596 | AL138: 0.44275471 | AM138: 0.44288031 | AN138: 0.4430579 | AO138: 0.44330858 | AP138: 0.44366167 | AQ138: 0.44415748 | AR138: 0.44485066 | AS138: 0.4458139 | AT138: 0.44714108 | AU138: 0.44894825 | AV138: 0.45136946 | AW138: 0.45454284 | AX138: 0.45858203
C139: CHP with CCS | D139: L | E139: =A133&"/"&B133&"/"&C139&"/"&D139 -> Coal fired power plants/Integrated gasification combined cycle/CHP with CCS/L | F139: =A133 -> Coal fired power plants | G139: =B133 -> Integrated gasification combined cycle | H139: =C139 -> CHP with CCS | I139: =D139 -> L | AE139: 0.42239852 | AF139: 0.42241831 | AG139: 0.422445 | AH139: 0.422481 | AI139: 0.42252954 | AJ139: 0.42259493 | AK139: 0.42268301 | AL139: 0.42280152 | AM139: 0.42296081 | AN139: 0.4231746 | AO139: 0.42346096 | AP139: 0.42384351 | AQ139: 0.42435274 | AR139: 0.42502736 | AS139: 0.42591545 | AT139: 0.42707477 | AU139: 0.42857154 | AV139: 0.43047636 | AW139: 0.43285594 | AX139: 0.43575935
D140: M | E140: =A133&"/"&B133&"/"&C139&"/"&D140 -> Coal fired power plants/Integrated gasification combined cycle/CHP with CCS/M | F140: =A133 -> Coal fired power plants | G140: =B133 -> Integrated gasification combined cycle | H140: =C139 -> CHP with CCS | I140: =D140 -> M | AE140: 0.4022525 | AF140: 0.40226177 | AG140: 0.40227493 | AH140: 0.40229358 | AI140: 0.40232004 | AJ140: 0.40235755 | AK140: 0.4024107 | AL140: 0.40248599 | AM140: 0.40259254 | AN140: 0.40274317 | AO140: 0.40295577 | AP140: 0.40325516 | AQ140: 0.40367544 | AR140: 0.40426281 | AS140: 0.40507856 | AT140: 0.40620166 | AU140: 0.40772935 | AV140: 0.40977321 | AW140: 0.41244692 | AX140: 0.41584161
B141: Supercritical steam turbine | C141: Electricity only | D141: L | E141: =A133&"/"&B141&"/"&C141&"/"&D141 -> Coal fired power plants/Supercritical steam turbine/Electricity only/L | F141: =A133 -> Coal fired power plants | G141: =B141 -> Supercritical steam turbine | H141: =C141 -> Electricity only | I141: =D141 -> L | J141: 0.47619048 | K141: 0.47619858 | L141: 0.47620848 | M141: 0.47622056 | N141: 0.4762353 | O141: 0.47625327 | P141: 0.4762752 | Q141: 0.47630193 | R141: 0.47633451 | S141: 0.4763742 | T141: 0.47642252 | U141: 0.4764813 | V141: 0.47655274 | W141: 0.47663949 | X141: 0.47674468 | Y141: 0.47687203 | Z141: 0.47702592 | AA141: 0.47721145 | AB141: 0.47743448 | AC141: 0.47770168 | AD141: 0.4780205 | AE141: 0.47839901 | AF141: 0.47884571 | AG141: 0.47936915 | AH141: 0.47997732 | AI141: 0.48067687 | AJ141: 0.48147204 | AK141: 0.48236349 | AL141: 0.48334698 | AM141: 0.48441228 | AN141: 0.48554243 | AO141: 0.48671389 | AP141: 0.48789757 | AQ141: 0.4890611 | AR141: 0.49017191 | AS141: 0.49120072 | AT141: 0.49212466 | AU141: 0.49292936 | AV141: 0.49360959 | AW141: 0.49416846 | AX141: 0.49461557
D142: M | E142: =A133&"/"&B141&"/"&C141&"/"&D142 -> Coal fired power plants/Supercritical steam turbine/Electricity only/M | F142: =A133 -> Coal fired power plants | G142: =B141 -> Supercritical steam turbine | H142: =C141 -> Electricity only | I142: =D142 -> M | J142: 0.45351474 | K142: 0.45352831 | L142: 0.45354446 | M142: 0.45356369 | N142: 0.45358656 | O142: 0.45361376 | P142: 0.45364611 | Q142: 0.45368456 | R142: 0.45373025 | S142: 0.45378451 | T142: 0.45384893 | U142: 0.45392533 | V142: 0.4540159 | W142: 0.45412313 | X142: 0.45424996 | Y142: 0.45439977 | Z142: 0.45457645 | AA142: 0.45478441 | AB142: 0.45502865 | AC142: 0.45531475 | AD142: 0.45564886 | AE142: 0.45603761 | AF142: 0.45648802 | AG142: 0.45700727 | AH142: 0.45760245 | AI142: 0.45828007 | AJ142: 0.45904561 | AK142: 0.45990281 | AL142: 0.46085295 | AM142: 0.46189408 | AN142: 0.46302028 | AO142: 0.46422114 | AP142: 0.46548157 | AQ142: 0.46678199 | AR142: 0.46809918 | AS142: 0.46940758 | AT142: 0.4706811 | AU142: 0.47189508 | AV142: 0.47302818 | AW142: 0.47406392 | AX142: 0.47499152
C143: CHP | D143: L | E143: =A133&"/"&B141&"/"&C143&"/"&D143 -> Coal fired power plants/Supercritical steam turbine/CHP/L | F143: =A133 -> Coal fired power plants | G143: =B141 -> Supercritical steam turbine | H143: =C143 -> CHP | I143: =D143 -> L | J143: 0.43290043 | K143: 0.43290682 | L143: 0.43291462 | M143: 0.43292413 | N143: 0.43293574 | O143: 0.43294991 | P143: 0.43296718 | Q143: 0.43298824 | R143: 0.43301391 | S143: 0.43304517 | T143: 0.43308322 | U143: 0.43312952 | V143: 0.43318578 | W143: 0.43325409 | X143: 0.43333691 | Y143: 0.43343716 | Z143: 0.43355828 | AA143: 0.43370426 | AB143: 0.4338797 | AC143: 0.43408982 | AD143: 0.43434042 | AE143: 0.43463779 | AF143: 0.43498853 | AG143: 0.43539925 | AH143: 0.43587606 | AI143: 0.436424 | AJ143: 0.43704618 | AK143: 0.43774284 | AL143: 0.43851039 | AM143: 0.43934055 | AN143: 0.44021984 | AO143: 0.44112973 | AP143: 0.44204751 | AQ143: 0.4429481 | AR143: 0.44380642 | AS143: 0.4446001 | AT143: 0.44531183 | AU143: 0.4459309 | AV143: 0.44645362 | AW143: 0.44688268 | AX143: 0.44722567
D144: M | E144: =A133&"/"&B141&"/"&C143&"/"&D144 -> Coal fired power plants/Supercritical steam turbine/CHP/M | F144: =A133 -> Coal fired power plants | G144: =B141 -> Supercritical steam turbine | H144: =C143 -> CHP | I144: =D144 -> M | J144: 0.41228613 | K144: 0.41229723 | L144: 0.41231045 | M144: 0.41232617 | N144: 0.41234488 | O144: 0.41236714 | P144: 0.4123936 | Q144: 0.41242506 | R144: 0.41246243 | S144: 0.41250682 | T144: 0.4125595 | U144: 0.41262199 | V144: 0.41269605 | W144: 0.41278373 | X144: 0.41288743 | Y144: 0.41300989 | Z144: 0.41315429 | AA144: 0.41332422 | AB144: 0.41352374 | AC144: 0.4137574 | AD144: 0.41403017 | AE144: 0.41434741 | AF144: 0.4147148 | AG144: 0.41513812 | AH144: 0.41562303 | AI144: 0.41617472 | AJ144: 0.41679747 | AK144: 0.41749414 | AL144: 0.41826556 | AM144: 0.41910987 | AN144: 0.42002203 | AO144: 0.42099336 | AP144: 0.42201139 | AQ144: 0.42306014 | AR144: 0.42412076 | AS144: 0.42517266 | AT144: 0.42619492 | AU144: 0.42716792 | AV144: 0.42807479 | AW144: 0.42890264 | AX144: 0.42964315
C145: Electricity only with CCS | D145: L | E145: =A133&"/"&B141&"/"&C145&"/"&D145 -> Coal fired power plants/Supercritical steam turbine/Electricity only with CCS/L | F145: =A133 -> Coal fired power plants | G145: =B141 -> Supercritical steam turbine | H145: =C145 -> Electricity only with CCS | I145: =D145 -> L | AE145: 0.45375785 | AF145: 0.45381135 | AG145: 0.45387654 | AH145: 0.45395593 | AI145: 0.45405255 | AJ145: 0.45417004 | AK145: 0.45431278 | AL145: 0.45448599 | AM145: 0.45469588 | AN145: 0.45494978 | AO145: 0.45525627 | AP145: 0.45562532 | AQ145: 0.45606834 | AR145: 0.45659823 | AS145: 0.45722921 | AT145: 0.45797665 | AU145: 0.45885651 | AV145: 0.45988457 | AW145: 0.46107536 | AX145: 0.46244062
D146: M | E146: =A133&"/"&B141&"/"&C145&"/"&D146 -> Coal fired power plants/Supercritical steam turbine/Electricity only with CCS/M | F146: =A133 -> Coal fired power plants | G146: =B141 -> Supercritical steam turbine | H146: =C145 -> Electricity only with CCS | I146: =D146 -> M | AE146: 0.4320161 | AF146: 0.43204367 | AG146: 0.43207903 | AH146: 0.43212436 | AI146: 0.43218245 | AJ146: 0.43225685 | AK146: 0.43235207 | AL146: 0.43247382 | AM146: 0.43262931 | AN146: 0.43282759 | AO146: 0.43307996 | AP146: 0.43340037 | AQ146: 0.43380591 | AR146: 0.43431716 | AS146: 0.43495845 | AT146: 0.4357578 | AU146: 0.43674632 | AV146: 0.4379568 | AW146: 0.43942122 | AX146: 0.44116675
C147: CHP with CCS | D147: L | E147: =A133&"/"&B141&"/"&C147&"/"&D147 -> Coal fired power plants/Supercritical steam turbine/CHP with CCS/L | F147: =A133 -> Coal fired power plants | G147: =B141 -> Supercritical steam turbine | H147: =C147 -> CHP with CCS | I147: =D147 -> L | AE147: 0.41247026 | AF147: 0.41251077 | AG147: 0.41256013 | AH147: 0.41262023 | AI147: 0.41269335 | AJ147: 0.41278227 | AK147: 0.41289026 | AL147: 0.41302127 | AM147: 0.41317996 | AN147: 0.41337184 | AO147: 0.41360335 | AP147: 0.41388194 | AQ147: 0.41421612 | AR147: 0.41461546 | AS147: 0.41509048 | AT147: 0.41565244 | AU147: 0.41631294 | AV147: 0.41708332 | AW147: 0.41797375 | AX147: 0.41899217
D148: M | E148: =A133&"/"&B141&"/"&C147&"/"&D148 -> Coal fired power plants/Supercritical steam turbine/CHP with CCS/M | F148: =A133 -> Coal fired power plants | G148: =B141 -> Supercritical steam turbine | H148: =C147 -> CHP with CCS | I148: =D148 -> M | AE148: 0.3927283 | AF148: 0.3927495 | AG148: 0.39277669 | AH148: 0.39281155 | AI148: 0.39285621 | AJ148: 0.39291341 | AK148: 0.39298661 | AL148: 0.39308018 | AM148: 0.39319965 | AN148: 0.39335196 | AO148: 0.39354573 | AP148: 0.39379162 | AQ148: 0.39410264 | AR148: 0.3944944 | AS148: 0.3949853 | AT148: 0.39559639 | AU148: 0.39635087 | AV148: 0.39727291 | AW148: 0.39838563 | AX148: 0.39970801
B149: Fluidized bed combustion | C149: Electricity only | D149: L | E149: =A133&"/"&B149&"/"&C149&"/"&D149 -> Coal fired power plants/Fluidized bed combustion/Electricity only/L | F149: =A133 -> Coal fired power plants | G149: =B149 -> Fluidized bed combustion | H149: =C149 -> Electricity only | I149: =D149 -> L | J149: 0.42553191 | K149: 0.42553762 | L149: 0.42554458 | M149: 0.42555308 | N149: 0.42556346 | O149: 0.42557613 | P149: 0.42559159 | Q149: 0.42561047 | R149: 0.4256335 | S149: 0.4256616 | T149: 0.42569588 | U149: 0.42573767 | V149: 0.4257886 | W149: 0.42585066 | X149: 0.42592622 | Y149: 0.42601815 | Z149: 0.42612993 | AA149: 0.42626568 | AB149: 0.42643035 | AC149: 0.4266298 | AD149: 0.42687092 | AE149: 0.42716177 | AF149: 0.42751165 | AG149: 0.42793115 | AH149: 0.42843213 | AI149: 0.4290275 | AJ149: 0.42973092 | AK149: 0.43055618 | AL149: 0.43151622 | AM149: 0.43262182 | AN149: 0.43387985 | AO149: 0.43529111 | AP149: 0.43684813 | AQ149: 0.43853298 | AR149: 0.44031601 | AS149: 0.44215585 | AT149: 0.44400142 | AU149: 0.44579614 | AV149: 0.447484 | AW149: 0.44901631 | AX149: 0.45035765
D150: M | E150: =A133&"/"&B149&"/"&C149&"/"&D150 -> Coal fired power plants/Fluidized bed combustion/Electricity only/M | F150: =A133 -> Coal fired power plants | G150: =B149 -> Fluidized bed combustion | H150: =C149 -> Electricity only | I150: =D150 -> M | J150: 0.40526849 | K150: 0.40527923 | L150: 0.40529202 | M150: 0.40530724 | N150: 0.40532536 | O150: 0.40534692 | P150: 0.40537259 | Q150: 0.40540312 | R150: 0.40543945 | S150: 0.40548264 | T150: 0.40553399 | U150: 0.405595 | V150: 0.40566748 | W150: 0.40575351 | X150: 0.40585557 | Y150: 0.40597654 | Z150: 0.40611981 | AA150: 0.40628928 | AB150: 0.40648949 | AC150: 0.40672564 | AD150: 0.40700365 | AE150: 0.40733024 | AF150: 0.40771288 | AG150: 0.40815981 | AH150: 0.40867992 | AI150: 0.40928262 | AJ150: 0.4099775 | AK150: 0.41077391 | AL150: 0.41168039 | AM150: 0.41270389 | AN150: 0.41384875 | AO150: 0.41511565 | AP150: 0.4165004 | AQ150: 0.41799283 | AR150: 0.41957606 | AS150: 0.42122615 | AT150: 0.42291263 | AU150: 0.42459999 | AV150: 0.42624998 | AW150: 0.42782477 | AX150: 0.42929031
D151: S | E151: =A133&"/"&B149&"/"&C149&"/"&D151 -> Coal fired power plants/Fluidized bed combustion/Electricity only/S | F151: =A133 -> Coal fired power plants | G151: =B149 -> Fluidized bed combustion | H151: =C149 -> Electricity only | I151: =D151 -> S | J151: 0.38596999 | K151: 0.3859926 | L151: 0.38601885 | M151: 0.38604931 | N151: 0.38608465 | O151: 0.38612565 | P151: 0.38617319 | Q151: 0.38622831 | R151: 0.38629219 | S151: 0.3863662 | T151: 0.38645191 | U151: 0.3865511 | V151: 0.38666583 | W151: 0.38679844 | X151: 0.38695158 | Y151: 0.38712828 | Z151: 0.38733191 | AA151: 0.38756629 | AB151: 0.38783565 | AC151: 0.38814469 | AD151: 0.38849853 | AE151: 0.38890274 | AF151: 0.38936328 | AG151: 0.38988637 | AH151: 0.39047844 | AI151: 0.39114589 | AJ151: 0.39189483 | AK151: 0.3927308 | AL151: 0.3936583 | AM151: 0.39468035 | AN151: 0.39579792 | AO151: 0.39700934 | AP151: 0.39830972 | AQ151: 0.39969051 | AR151: 0.40113914 | AS151: 0.40263896 | AT151: 0.40416959 | AU151: 0.40570756 | AV151: 0.40722748 | AW151: 0.40870344 | AX151: 0.41011074
C152: CHP | D152: L | E152: =A133&"/"&B149&"/"&C152&"/"&D152 -> Coal fired power plants/Fluidized bed combustion/CHP/L | F152: =A133 -> Coal fired power plants | G152: =B149 -> Fluidized bed combustion | H152: =C152 -> CHP | I152: =D152 -> L | J152: 0.3868472 | K152: 0.38684891 | L152: 0.38685101 | M152: 0.38685357 | N152: 0.3868567 | O152: 0.38686052 | P152: 0.38686518 | Q152: 0.38687087 | R152: 0.38687782 | S152: 0.38688631 | T152: 0.38689667 | U152: 0.38690932 | V152: 0.38692475 | W152: 0.38694359 | X152: 0.38696656 | Y152: 0.38699459 | Z152: 0.38702876 | AA152: 0.3870704 | AB152: 0.38712113 | AC152: 0.3871829 | AD152: 0.38725805 | AE152: 0.38734941 | AF152: 0.38746035 | AG152: 0.3875949 | AH152: 0.38775784 | AI152: 0.38795478 | AJ152: 0.38819226 | AK152: 0.38847786 | AL152: 0.38882015 | AM152: 0.38922872 | AN152: 0.38971401 | AO152: 0.39028697 | AP152: 0.39095865 | AQ152: 0.39173928 | AR152: 0.39263731 | AS152: 0.39365786 | AT152: 0.3948011 | AU152: 0.3960604 | AV152: 0.39742072 | AW152: 0.39885761 | AX152: 0.40033733
D153: M | E153: =A133&"/"&B149&"/"&C152&"/"&D153 -> Coal fired power plants/Fluidized bed combustion/CHP/M | F153: =A133 -> Coal fired power plants | G153: =B149 -> Fluidized bed combustion | H153: =C152 -> CHP | I153: =D153 -> M | J153: 0.3684259 | K153: 0.3684296 | L153: 0.36843401 | M153: 0.36843926 | N153: 0.36844552 | O153: 0.36845296 | P153: 0.36846183 | Q153: 0.36847239 | R153: 0.36848496 | S153: 0.36849992 | T153: 0.36851772 | U153: 0.36853891 | V153: 0.36856412 | W153: 0.36859411 | X153: 0.36862977 | Y153: 0.36867215 | Z153: 0.36872252 | AA153: 0.36878234 | AB153: 0.36885334 | AC153: 0.36893757 | AD153: 0.3690374 | AE153: 0.3691556 | AF153: 0.36929541 | AG153: 0.36946053 | AH153: 0.36965526 | AI153: 0.36988446 | AJ153: 0.37015362 | AK153: 0.37046886 | AL153: 0.37083691 | AM153: 0.37126504 | AN153: 0.37176086 | AO153: 0.37233213 | AP153: 0.3729864 | AQ153: 0.37373045 | AR153: 0.37456973 | AS153: 0.37550749 | AT153: 0.37654393 | AU153: 0.37767523 | AV153: 0.3788927 | AW153: 0.38018215 | AX153: 0.38152377
D154: S | E154: =A133&"/"&B149&"/"&C152&"/"&D154 -> Coal fired power plants/Fluidized bed combustion/CHP/S | F154: =A133 -> Coal fired power plants | G154: =B149 -> Fluidized bed combustion | H154: =C152 -> CHP | I154: =D154 -> S | J154: 0.35088181 | K154: 0.35089072 | L154: 0.35090108 | M154: 0.3509131 | N154: 0.35092705 | O154: 0.35094326 | P154: 0.35096206 | Q154: 0.35098389 | R154: 0.35100923 | S154: 0.35103862 | T154: 0.35107271 | U154: 0.35111225 | V154: 0.35115809 | W154: 0.35121121 | X154: 0.35127274 | Y154: 0.351344 | Z154: 0.35142646 | AA154: 0.35152183 | AB154: 0.35163205 | AC154: 0.35175931 | AD154: 0.35190613 | AE154: 0.3520753 | AF154: 0.35226997 | AG154: 0.35249364 | AH154: 0.35275018 | AI154: 0.35304382 | AJ154: 0.35337915 | AK154: 0.35376103 | AL154: 0.35419458 | AM154: 0.35468504 | AN154: 0.35523759 | AO154: 0.35585717 | AP154: 0.35654821 | AQ154: 0.35731425 | AR154: 0.35815756 | AS154: 0.35907869 | AT154: 0.360076 | AU154: 0.3611452 | AV154: 0.36227896 | AW154: 0.36346668 | AX154: 0.36469451
C155: Electricity only with CCS | D155: L | E155: =A133&"/"&B149&"/"&C155&"/"&D155 -> Coal fired power plants/Fluidized bed combustion/Electricity only with CCS/L | F155: =A133 -> Coal fired power plants | G155: =B149 -> Fluidized bed combustion | H155: =C155 -> Electricity only with CCS | I155: =D155 -> L | AE155: 0.40538648 | AF155: 0.40541992 | AG155: 0.4054628 | AH155: 0.40551778 | AI155: 0.40558824 | AJ155: 0.4056785 | AK155: 0.40579402 | AL155: 0.40594175 | AM155: 0.40613046 | AN155: 0.40637116 | AO155: 0.40667762 | AP155: 0.40706686 | AQ155: 0.40755976 | AR155: 0.40818154 | AS155: 0.40896211 | AT155: 0.40993605 | AU155: 0.411142 | AV155: 0.41262106 | AW155: 0.41441379 | AX155: 0.4165556
D156: M | E156: =A133&"/"&B149&"/"&C155&"/"&D156 -> Coal fired power plants/Fluidized bed combustion/Electricity only with CCS/M | F156: =A133 -> Coal fired power plants | G156: =B149 -> Fluidized bed combustion | H156: =C155 -> Electricity only with CCS | I156: =D156 -> M | AE156: 0.3860904 | AF156: 0.38612452 | AG156: 0.38616828 | AH156: 0.3862244 | AI156: 0.38629631 | AJ156: 0.38638843 | AK156: 0.38650635 | AL156: 0.38665716 | AM156: 0.38684984 | AN156: 0.38709564 | AO156: 0.38740865 | AP156: 0.38780632 | AQ156: 0.38831008 | AR156: 0.38894582 | AS156: 0.38974435 | AT156: 0.39074139 | AU156: 0.391977 | AV156: 0.39349405 | AW156: 0.39533524 | AX156: 0.39753844
C157: CHP with CCS | D157: L | E157: =A133&"/"&B149&"/"&C157&"/"&D157 -> Coal fired power plants/Fluidized bed combustion/CHP with CCS/L | F157: =A133 -> Coal fired power plants | G157: =B149 -> Fluidized bed combustion | H157: =C157 -> CHP with CCS | I157: =D157 -> L | AE157: 0.36851784 | AF157: 0.36854388 | AG157: 0.36857729 | AH157: 0.36862012 | AI157: 0.368675 | AJ157: 0.36874528 | AK157: 0.36883524 | AL157: 0.36895025 | AM157: 0.36909712 | AN157: 0.3692844 | AO157: 0.36952274 | AP157: 0.3698253 | AQ157: 0.37020817 | AR157: 0.37069074 | AS157: 0.3712959 | AT157: 0.37204993 | AU157: 0.37298201 | AV157: 0.37412276 | AW157: 0.37550188 | AX157: 0.37714437
D158: M | E158: =A133&"/"&B149&"/"&C157&"/"&D158 -> Coal fired power plants/Fluidized bed combustion/CHP with CCS/M | F158: =A133 -> Coal fired power plants | G158: =B149 -> Fluidized bed combustion | H158: =C157 -> CHP with CCS | I158: =D158 -> M | AE158: 0.35097667 | AF158: 0.35100355 | AG158: 0.35103802 | AH158: 0.35108221 | AI158: 0.35113885 | AJ158: 0.35121139 | AK158: 0.35130422 | AL158: 0.35142294 | AM158: 0.35157457 | AN158: 0.35176794 | AO158: 0.35201408 | AP158: 0.35232663 | AQ158: 0.35272228 | AR158: 0.35322116 | AS158: 0.35384711 | AT158: 0.3546276 | AU158: 0.35559318 | AV158: 0.35677619 | AW158: 0.35820823 | AX158: 0.35991641
B159: Steam turbine | C159: Electricity only | D159: L | E159: =A133&"/"&B159&"/"&C159&"/"&D159 -> Coal fired power plants/Steam turbine/Electricity only/L | F159: =A133 -> Coal fired power plants | G159: =B159 -> Steam turbine | H159: =C159 -> Electricity only | I159: =D159 -> L | J159: 0.44444444 | K159: 0.44460238 | L159: 0.44476018 | M159: 0.44491776 | N159: 0.44507505 | O159: 0.44523198 | P159: 0.44538845 | Q159: 0.44554439 | R159: 0.44569973 | S159: 0.4458544 | T159: 0.44600831 | U159: 0.44616141 | V159: 0.44631362 | W159: 0.44646487 | X159: 0.4466151 | Y159: 0.44676425 | Z159: 0.44691226 | AA159: 0.44705907 | AB159: 0.44720462 | AC159: 0.44734886 | AD159: 0.44749173 | AE159: 0.4476332 | AF159: 0.44777321 | AG159: 0.44791171 | AH159: 0.44804868 | AI159: 0.44818407 | AJ159: 0.44831784 | AK159: 0.44844995 | AL159: 0.44858039 | AM159: 0.44870912 | AN159: 0.44883612 | AO159: 0.44896135 | AP159: 0.4490848 | AQ159: 0.44920646 | AR159: 0.44932629 | AS159: 0.4494443 | AT159: 0.44956047 | AU159: 0.44967478 | AV159: 0.44978723 | AW159: 0.44989781 | AX159: 0.45000653
D160: M | E160: =A133&"/"&B159&"/"&C159&"/"&D160 -> Coal fired power plants/Steam turbine/Electricity only/M | F160: =A133 -> Coal fired power plants | G160: =B159 -> Steam turbine | H160: =C159 -> Electricity only | I160: =D160 -> M | J160: 0.42328042 | K160: 0.42340077 | L160: 0.42352105 | M160: 0.4236412 | N160: 0.42376116 | O160: 0.42388087 | P160: 0.42400027 | Q160: 0.4241193 | R160: 0.42423791 | S160: 0.42435603 | T160: 0.42447361 | U160: 0.4245906 | V160: 0.42470694 | W160: 0.42482258 | X160: 0.42493747 | Y160: 0.42505156 | Z160: 0.42516481 | AA160: 0.42527717 | AB160: 0.42538859 | AC160: 0.42549904 | AD160: 0.42560847 | AE160: 0.42571685 | AF160: 0.42582414 | AG160: 0.42593031 | AH160: 0.42603531 | AI160: 0.42613914 | AJ160: 0.42624174 | AK160: 0.4263431 | AL160: 0.4264432 | AM160: 0.42654201 | AN160: 0.4266395 | AO160: 0.42673567 | AP160: 0.42683049 | AQ160: 0.42692394 | AR160: 0.42701602 | AS160: 0.42710671 | AT160: 0.42719601 | AU160: 0.42728389 | AV160: 0.42737036 | AW160: 0.42745542 | AX160: 0.42753905
D161: S | E161: =A133&"/"&B159&"/"&C159&"/"&D161 -> Coal fired power plants/Steam turbine/Electricity only/S | F161: =A133 -> Coal fired power plants | G161: =B159 -> Steam turbine | H161: =C159 -> Electricity only | I161: =D161 -> S | J161: 0.40312421 | K161: 0.40321019 | L161: 0.40329614 | M161: 0.40338202 | N161: 0.40346779 | O161: 0.40355341 | P161: 0.40363883 | Q161: 0.40372401 | R161: 0.4038089 | S161: 0.40389348 | T161: 0.40397769 | U161: 0.40406149 | V161: 0.40414486 | W161: 0.40422775 | X161: 0.40431012 | Y161: 0.40439194 | Z161: 0.40447318 | AA161: 0.4045538 | AB161: 0.40463377 | AC161: 0.40471306 | AD161: 0.40479165 | AE161: 0.40486949 | AF161: 0.40494657 | AG161: 0.40502286 | AH161: 0.40509834 | AI161: 0.40517299 | AJ161: 0.40524677 | AK161: 0.40531969 | AL161: 0.4053917 | AM161: 0.40546281 | AN161: 0.40553298 | AO161: 0.40560222 | AP161: 0.40567049 | AQ161: 0.40573781 | AR161: 0.40580414 | AS161: 0.40586949 | AT161: 0.40593384 | AU161: 0.4059972 | AV161: 0.40605954 | AW161: 0.40612088 | AX161: 0.4061812
D162: XS | E162: =A133&"/"&B159&"/"&C159&"/"&D162 -> Coal fired power plants/Steam turbine/Electricity only/XS | F162: =A133 -> Coal fired power plants | G162: =B159 -> Steam turbine | H162: =C159 -> Electricity only | I162: =D162 -> XS | J162: 0.38392782 | K162: 0.38399566 | L162: 0.38406319 | M162: 0.38413038 | N162: 0.3841972 | O162: 0.38426361 | P162: 0.38432959 | Q162: 0.38439511 | R162: 0.38446015 | S162: 0.38452468 | T162: 0.38458868 | U162: 0.38465212 | V162: 0.38471498 | W162: 0.38477723 | X162: 0.38483887 | Y162: 0.38489986 | Z162: 0.3849602 | AA162: 0.38501986 | AB162: 0.38507882 | AC162: 0.38513708 | AD162: 0.38519461 | AE162: 0.38525141 | AF162: 0.38530746 | AG162: 0.38536275 | AH162: 0.38541727 | AI162: 0.38547102 | AJ162: 0.38552398 | AK162: 0.38557615 | AL162: 0.38562752 | AM162: 0.38567809 | AN162: 0.38572785 | AO162: 0.3857768 | AP162: 0.38582494 | AQ162: 0.38587226 | AR162: 0.38591877 | AS162: 0.38596446 | AT162: 0.38600934 | AU162: 0.38605341 | AV162: 0.38609666 | AW162: 0.38613911 | AX162: 0.38618076
C163: CHP | D163: L | E163: =A133&"/"&B159&"/"&C163&"/"&D163 -> Coal fired power plants/Steam turbine/CHP/L | F163: =A133 -> Coal fired power plants | G163: =B159 -> Steam turbine | H163: =C163 -> CHP | I163: =D163 -> L | J163: 0.4040404 | K163: 0.40412965 | L163: 0.40421868 | M163: 0.40430749 | N163: 0.40439605 | O163: 0.40448435 | P163: 0.40457236 | Q163: 0.40466008 | R163: 0.40474747 | S163: 0.40483452 | T163: 0.40492122 | U163: 0.40500755 | V163: 0.40509349 | W163: 0.40517902 | X163: 0.40526413 | Y163: 0.4053488 | Z163: 0.40543302 | AA163: 0.40551678 | AB163: 0.40560005 | AC163: 0.40568282 | AD163: 0.40576509 | AE163: 0.40584683 | AF163: 0.40592804 | AG163: 0.40600871 | AH163: 0.40608881 | AI163: 0.40616834 | AJ163: 0.4062473 | AK163: 0.40632566 | AL163: 0.40640342 | AM163: 0.40648057 | AN163: 0.40655709 | AO163: 0.40663299 | AP163: 0.40670825 | AQ163: 0.40678287 | AR163: 0.40685683 | AS163: 0.40693014 | AT163: 0.40700278 | AU163: 0.40707474 | AV163: 0.40714603 | AW163: 0.40721664 | AX163: 0.40728656
...

Sheet tech_cost
A1: Plant type for comparison (left): | B1: Technology: | C1: Co-generation: | D1: Size: | T1: Parameters to calculate levelized costs
T3: Discount rate (%): | AD3: Annual operating hours: | AN3: CO2 price (€2010 / t CO2):
A5: Plant type for comparison (right): | B5: Technology: | C5: Co-generation: | D5: Size:
T6: manual (discount rate): | AN6: manual (CO2 price):
T7: 0.072 | AN7: 88
A10: =I11 -> Wind power plants / Onshore / Electricity only / L | J10: =J$625 -> 2010 | K10: =K$625 -> 2011 | L10: =L$625 -> 2012 | M10: =M$625 -> 2013 | N10: =N$625 -> 2014 | O10: =O$625 -> 2015 | P10: =P$625 -> 2016 | Q10: =Q$625 -> 2017 | ... AX10: =AX$625 -> 2050
A11: =$J$344 -> Levelized costs (€2010 / MWh net) | H11: =A11&CHAR(13)&I11 -> Levelized costs (€2010 / MWh net)_x000D_Wind power plants / Onshore / Electricity only / L | I11: =INDEX(F$346:F$617,$D$119)&" / "&INDEX(G$346:G$617,$D$119)&" / "&INDEX(H$346:H$617,$D$119)&" / "&INDEX(I$346:I$617,$D$119) -> Wind power plants / Onshore / Electricity only / L | J11: =IF(LEN(INDEX(J$346:J$617,$D$119))<=0,NA(),INDEX(J$346:J$617,$D$119)) -> 36.793908 | K11: =IF(LEN(INDEX(K$346:K$617,$D$119))<=0,NA(),INDEX(K$346:K$617,$D$119)) -> 35.005996 | L11: =IF(LEN(INDEX(L$346:L$617,$D$119))<=0,NA(),INDEX(L$346:L$617,$D$119)) -> 33.832679 | M11: =IF(LEN(INDEX(M$346:M$617,$D$119))<=0,NA(),INDEX(M$346:M$617,$D$119)) -> 33.078404 | N11: =IF(LEN(INDEX(N$346:N$617,$D$119))<=0,NA(),INDEX(N$346:N$617,$D$119)) -> 32.64737 | O11: =IF(LEN(INDEX(O$346:O$617,$D$119))<=0,NA(),INDEX(O$346:O$617,$D$119)) -> 32.324129 | P11: =IF(LEN(INDEX(P$346:P$617,$D$119))<=0,NA(),INDEX(P$346:P$617,$D$119)) -> 31.803541 | Q11: =IF(LEN(INDEX(Q$346:Q$617,$D$119))<=0,NA(),INDEX(Q$346:Q$617,$D$119)) -> 31.461905 | ... AX11: =IF(LEN(INDEX(AX$346:AX$617,$D$119))<=0,NA(),INDEX(AX$346:AX$617,$D$119)) -> 22.377192
A12: =$J$624 -> Fixed annual levelized costs | I12: =INDEX(F$626:F$897,$D$119)&" / "&INDEX(G$626:G$897,$D$119)&" / "&INDEX(H$626:H$897,$D$119)&" / "&INDEX(I$626:I$897,$D$119) -> Wind power plants / Onshore / Electricity only / L | J12: =IF(LEN(INDEX(J$626:J$897,$D$119))<=0,NA(),INDEX(J$626:J$897,$D$119)) -> 36.224154 | K12: =IF(LEN(INDEX(K$626:K$897,$D$119))<=0,NA(),INDEX(K$626:K$897,$D$119)) -> 34.463928 | L12: =IF(LEN(INDEX(L$626:L$897,$D$119))<=0,NA(),INDEX(L$626:L$897,$D$119)) -> 33.30878 | M12: =IF(LEN(INDEX(M$626:M$897,$D$119))<=0,NA(),INDEX(M$626:M$897,$D$119)) -> 32.566185 | N12: =IF(LEN(INDEX(N$626:N$897,$D$119))<=0,NA(),INDEX(N$626:N$897,$D$119)) -> 32.141826 | O12: =IF(LEN(INDEX(O$626:O$897,$D$119))<=0,NA(),INDEX(O$626:O$897,$D$119)) -> 31.82359 | P12: =IF(LEN(INDEX(P$626:P$897,$D$119))<=0,NA(),INDEX(P$626:P$897,$D$119)) -> 31.311063 | Q12: =IF(LEN(INDEX(Q$626:Q$897,$D$119))<=0,NA(),INDEX(Q$626:Q$897,$D$119)) -> 30.974718 | ... AX12: =IF(LEN(INDEX(AX$626:AX$897,$D$119))<=0,NA(),INDEX(AX$626:AX$897,$D$119)) -> 22.030682
A13: =$J$904 -> Fuel and variable costs | I13: =INDEX(F$906:F$1177,$D$119)&" / "&INDEX(G$906:G$1177,$D$119)&" / "&INDEX(H$906:H$1177,$D$119)&" / "&INDEX(I$906:I$1177,$D$119) -> Wind power plants / Onshore / Electricity only / L | J13: =IF(LEN(INDEX(J$906:J$1177,$D$119))<=0,NA(),INDEX(J$906:J$1177,$D$119)) -> 0.56975381 | K13: =IF(LEN(INDEX(K$906:K$1177,$D$119))<=0,NA(),INDEX(K$906:K$1177,$D$119)) -> 0.542068 | L13: =IF(LEN(INDEX(L$906:L$1177,$D$119))<=0,NA(),INDEX(L$906:L$1177,$D$119)) -> 0.52389918 | M13: =IF(LEN(INDEX(M$906:M$1177,$D$119))<=0,NA(),INDEX(M$906:M$1177,$D$119)) -> 0.51221923 | N13: =IF(LEN(INDEX(N$906:N$1177,$D$119))<=0,NA(),INDEX(N$906:N$1177,$D$119)) -> 0.50554467 | O13: =IF(LEN(INDEX(O$906:O$1177,$D$119))<=0,NA(),INDEX(O$906:O$1177,$D$119)) -> 0.50053927 | P13: =IF(LEN(INDEX(P$906:P$1177,$D$119))<=0,NA(),INDEX(P$906:P$1177,$D$119)) -> 0.49247797 | Q13: =IF(LEN(INDEX(Q$906:Q$1177,$D$119))<=0,NA(),INDEX(Q$906:Q$1177,$D$119)) -> 0.48718773 | ... AX13: =IF(LEN(INDEX(AX$906:AX$1177,$D$119))<=0,NA(),INDEX(AX$906:AX$1177,$D$119)) -> 0.34651092
A14: =$J$1184 -> CO2 emission related costs | I14: =INDEX(F$1186:F$1457,$D$119)&" / "&INDEX(G$1186:G$1457,$D$119)&" / "&INDEX(H$1186:H$1457,$D$119)&" / "&INDEX(I$1186:I$1457,$D$119) -> Wind power plants / Onshore / Electricity only / L | J14: =IF(LEN(INDEX(J$1186:J$1457,$D$119))<=0,NA(),INDEX(J$1186:J$1457,$D$119)) -> 0 | K14: =IF(LEN(INDEX(K$1186:K$1457,$D$119))<=0,NA(),INDEX(K$1186:K$1457,$D$119)) -> 0 | L14: =IF(LEN(INDEX(L$1186:L$1457,$D$119))<=0,NA(),INDEX(L$1186:L$1457,$D$119)) -> 0 | M14: =IF(LEN(INDEX(M$1186:M$1457,$D$119))<=0,NA(),INDEX(M$1186:M$1457,$D$119)) -> 0 | N14: =IF(LEN(INDEX(N$1186:N$1457,$D$119))<=0,NA(),INDEX(N$1186:N$1457,$D$119)) -> 0 | O14: =IF(LEN(INDEX(O$1186:O$1457,$D$119))<=0,NA(),INDEX(O$1186:O$1457,$D$119)) -> 0 | P14: =IF(LEN(INDEX(P$1186:P$1457,$D$119))<=0,NA(),INDEX(P$1186:P$1457,$D$119)) -> 0 | Q14: =IF(LEN(INDEX(Q$1186:Q$1457,$D$119))<=0,NA(),INDEX(Q$1186:Q$1457,$D$119)) -> 0 | ... AX14: =IF(LEN(INDEX(AX$1186:AX$1457,$D$119))<=0,NA(),INDEX(AX$1186:AX$1457,$D$119)) -> 0
A15: Desired operating hours - minimum | H15: ="Operating hours"&CHAR(13)&I15 -> Operating hours_x000D_Wind power plants / Onshore / Electricity only / L | I15: =INDEX(tech_proj!F$1806:F$2077,$D$119)&" / "&INDEX(tech_proj!G$1806:G$2077,$D$119)&" / "&INDEX(tech_proj!H$1806:H$2077,$D$119)&" / "&INDEX(tech_proj!I$1806:I$2077,$D$119) -> Wind power plants / Onshore / Electricity only / L | J15: =IF(LEN(INDEX(tech_proj!J$1806:J$2077,$D$119))<=0,NA(),INDEX(tech_proj!J$1806:J$2077,$D$119)) -> 1400 | K15: =IF(LEN(INDEX(tech_proj!K$1806:K$2077,$D$119))<=0,NA(),INDEX(tech_proj!K$1806:K$2077,$D$119)) -> 1400 | L15: =IF(LEN(INDEX(tech_proj!L$1806:L$2077,$D$119))<=0,NA(),INDEX(tech_proj!L$1806:L$2077,$D$119)) -> 1400 | M15: =IF(LEN(INDEX(tech_proj!M$1806:M$2077,$D$119))<=0,NA(),INDEX(tech_proj!M$1806:M$2077,$D$119)) -> 1400 | N15: =IF(LEN(INDEX(tech_proj!N$1806:N$2077,$D$119))<=0,NA(),INDEX(tech_proj!N$1806:N$2077,$D$119)) -> 1400 | O15: =IF(LEN(INDEX(tech_proj!O$1806:O$2077,$D$119))<=0,NA(),INDEX(tech_proj!O$1806:O$2077,$D$119)) -> 1400 | P15: =IF(LEN(INDEX(tech_proj!P$1806:P$2077,$D$119))<=0,NA(),INDEX(tech_proj!P$1806:P$2077,$D$119)) -> 1400 | Q15: =IF(LEN(INDEX(tech_proj!Q$1806:Q$2077,$D$119))<=0,NA(),INDEX(tech_proj!Q$1806:Q$2077,$D$119)) -> 1400 | ... AX15: =IF(LEN(INDEX(tech_proj!AX$1806:AX$2077,$D$119))<=0,NA(),INDEX(tech_proj!AX$1806:AX$2077,$D$119)) -> 1400
A16: Desired operating hours - maximum | I16: =INDEX(tech_proj!F$2366:F$2637,$D$119)&" / "&INDEX(tech_proj!G$2366:G$2637,$D$119)&" / "&INDEX(tech_proj!H$2366:H$2637,$D$119)&" / "&INDEX(tech_proj!I$2366:I$2637,$D$119) -> Wind power plants / Onshore / Electricity only / L | J16: =IF(LEN(INDEX(tech_proj!J$2366:J$2637,$D$119))<=0,NA(),INDEX(tech_proj!J$2366:J$2637,$D$119)) -> 3750 | K16: =IF(LEN(INDEX(tech_proj!K$2366:K$2637,$D$119))<=0,NA(),INDEX(tech_proj!K$2366:K$2637,$D$119)) -> 3750 | L16: =IF(LEN(INDEX(tech_proj!L$2366:L$2637,$D$119))<=0,NA(),INDEX(tech_proj!L$2366:L$2637,$D$119)) -> 3750 | M16: =IF(LEN(INDEX(tech_proj!M$2366:M$2637,$D$119))<=0,NA(),INDEX(tech_proj!M$2366:M$2637,$D$119)) -> 3750 | N16: =IF(LEN(INDEX(tech_proj!N$2366:N$2637,$D$119))<=0,NA(),INDEX(tech_proj!N$2366:N$2637,$D$119)) -> 3750 | O16: =IF(LEN(INDEX(tech_proj!O$2366:O$2637,$D$119))<=0,NA(),INDEX(tech_proj!O$2366:O$2637,$D$119)) -> 3750 | P16: =IF(LEN(INDEX(tech_proj!P$2366:P$2637,$D$119))<=0,NA(),INDEX(tech_proj!P$2366:P$2637,$D$119)) -> 3750 | Q16: =IF(LEN(INDEX(tech_proj!Q$2366:Q$2637,$D$119))<=0,NA(),INDEX(tech_proj!Q$2366:Q$2637,$D$119)) -> 3750 | ... AX16: =IF(LEN(INDEX(tech_proj!AX$2366:AX$2637,$D$119))<=0,NA(),INDEX(tech_proj!AX$2366:AX$2637,$D$119)) -> 3750
A18: =I19 -> Wind power plants / Onshore / Electricity only / M | J18: =J$625 -> 2010 | K18: =K$625 -> 2011 | L18: =L$625 -> 2012 | M18: =M$625 -> 2013 | N18: =N$625 -> 2014 | O18: =O$625 -> 2015 | P18: =P$625 -> 2016 | Q18: =Q$625 -> 2017 | ... AX18: =AX$625 -> 2050
A19: =$J$344 -> Levelized costs (€2010 / MWh net) | H19: =A19&CHAR(13)&I19 -> Levelized costs (€2010 / MWh net)_x000D_Wind power plants / Onshore / Electricity only / M | I19: =INDEX(F$346:F$617,$D$139)&" / "&INDEX(G$346:G$617,$D$139)&" / "&INDEX(H$346:H$617,$D$139)&" / "&INDEX(I$346:I$617,$D$139) -> Wind power plants / Onshore / Electricity only / M | J19: =IF(LEN(INDEX(J$346:J$617,$D$139))<=0,NA(),INDEX(J$346:J$617,$D$139)) -> 39.949821 | K19: =IF(LEN(INDEX(K$346:K$617,$D$139))<=0,NA(),INDEX(K$346:K$617,$D$139)) -> 38.96766 | L19: =IF(LEN(INDEX(L$346:L$617,$D$139))<=0,NA(),INDEX(L$346:L$617,$D$139)) -> 38.28014 | M19: =IF(LEN(INDEX(M$346:M$617,$D$139))<=0,NA(),INDEX(M$346:M$617,$D$139)) -> 37.779057 | N19: =IF(LEN(INDEX(N$346:N$617,$D$139))<=0,NA(),INDEX(N$346:N$617,$D$139)) -> 37.264124 | O19: =IF(LEN(INDEX(O$346:O$617,$D$139))<=0,NA(),INDEX(O$346:O$617,$D$139)) -> 36.529874 | P19: =IF(LEN(INDEX(P$346:P$617,$D$139))<=0,NA(),INDEX(P$346:P$617,$D$139)) -> 35.85617 | Q19: =IF(LEN(INDEX(Q$346:Q$617,$D$139))<=0,NA(),INDEX(Q$346:Q$617,$D$139)) -> 35.423876 | ... AX19: =IF(LEN(INDEX(AX$346:AX$617,$D$139))<=0,NA(),INDEX(AX$346:AX$617,$D$139)) -> 25.611284
A20: =$J$624 -> Fixed annual levelized costs | I20: =INDEX(F$626:F$897,$D$139)&" / "&INDEX(G$626:G$897,$D$139)&" / "&INDEX(H$626:H$897,$D$139)&" / "&INDEX(I$626:I$897,$D$139) -> Wind power plants / Onshore / Electricity only / M | J20: =IF(LEN(INDEX(J$626:J$897,$D$139))<=0,NA(),INDEX(J$626:J$897,$D$139)) -> 39.354636 | K20: =IF(LEN(INDEX(K$626:K$897,$D$139))<=0,NA(),INDEX(K$626:K$897,$D$139)) -> 38.387108 | L20: =IF(LEN(INDEX(L$626:L$897,$D$139))<=0,NA(),INDEX(L$626:L$897,$D$139)) -> 37.709831 | M20: =IF(LEN(INDEX(M$626:M$897,$D$139))<=0,NA(),INDEX(M$626:M$897,$D$139)) -> 37.216213 | N20: =IF(LEN(INDEX(N$626:N$897,$D$139))<=0,NA(),INDEX(N$626:N$897,$D$139)) -> 36.708952 | O20: =IF(LEN(INDEX(O$626:O$897,$D$139))<=0,NA(),INDEX(O$626:O$897,$D$139)) -> 35.985641 | P20: =IF(LEN(INDEX(P$626:P$897,$D$139))<=0,NA(),INDEX(P$626:P$897,$D$139)) -> 35.321974 | Q20: =IF(LEN(INDEX(Q$626:Q$897,$D$139))<=0,NA(),INDEX(Q$626:Q$897,$D$139)) -> 34.896121 | ... AX20: =IF(LEN(INDEX(AX$626:AX$897,$D$139))<=0,NA(),INDEX(AX$626:AX$897,$D$139)) -> 25.229719
A21: =$J$904 -> Fuel and variable costs | I21: =INDEX(F$906:F$1177,$D$139)&" / "&INDEX(G$906:G$1177,$D$139)&" / "&INDEX(H$906:H$1177,$D$139)&" / "&INDEX(I$906:I$1177,$D$139) -> Wind power plants / Onshore / Electricity only / M | J21: =IF(LEN(INDEX(J$906:J$1177,$D$139))<=0,NA(),INDEX(J$906:J$1177,$D$139)) -> 0.59518442 | K21: =IF(LEN(INDEX(K$906:K$1177,$D$139))<=0,NA(),INDEX(K$906:K$1177,$D$139)) -> 0.5805519 | L21: =IF(LEN(INDEX(L$906:L$1177,$D$139))<=0,NA(),INDEX(L$906:L$1177,$D$139)) -> 0.57030901 | M21: =IF(LEN(INDEX(M$906:M$1177,$D$139))<=0,NA(),INDEX(M$906:M$1177,$D$139)) -> 0.56284373 | N21: =IF(LEN(INDEX(N$906:N$1177,$D$139))<=0,NA(),INDEX(N$906:N$1177,$D$139)) -> 0.55517211 | O21: =IF(LEN(INDEX(O$906:O$1177,$D$139))<=0,NA(),INDEX(O$906:O$1177,$D$139)) -> 0.54423302 | P21: =IF(LEN(INDEX(P$906:P$1177,$D$139))<=0,NA(),INDEX(P$906:P$1177,$D$139)) -> 0.53419598 | Q21: =IF(LEN(INDEX(Q$906:Q$1177,$D$139))<=0,NA(),INDEX(Q$906:Q$1177,$D$139)) -> 0.52775554 | ... AX21: =IF(LEN(INDEX(AX$906:AX$1177,$D$139))<=0,NA(),INDEX(AX$906:AX$1177,$D$139)) -> 0.3815646
A22: =$J$1184 -> CO2 emission related costs | I22: =INDEX(F$1186:F$1457,$D$139)&" / "&INDEX(G$1186:G$1457,$D$139)&" / "&INDEX(H$1186:H$1457,$D$139)&" / "&INDEX(I$1186:I$1457,$D$139) -> Wind power plants / Onshore / Electricity only / M | J22: =IF(LEN(INDEX(J$1186:J$1457,$D$139))<=0,NA(),INDEX(J$1186:J$1457,$D$139)) -> 0 | K22: =IF(LEN(INDEX(K$1186:K$1457,$D$139))<=0,NA(),INDEX(K$1186:K$1457,$D$139)) -> 0 | L22: =IF(LEN(INDEX(L$1186:L$1457,$D$139))<=0,NA(),INDEX(L$1186:L$1457,$D$139)) -> 0 | M22: =IF(LEN(INDEX(M$1186:M$1457,$D$139))<=0,NA(),INDEX(M$1186:M$1457,$D$139)) -> 0 | N22: =IF(LEN(INDEX(N$1186:N$1457,$D$139))<=0,NA(),INDEX(N$1186:N$1457,$D$139)) -> 0 | O22: =IF(LEN(INDEX(O$1186:O$1457,$D$139))<=0,NA(),INDEX(O$1186:O$1457,$D$139)) -> 0 | P22: =IF(LEN(INDEX(P$1186:P$1457,$D$139))<=0,NA(),INDEX(P$1186:P$1457,$D$139)) -> 0 | Q22: =IF(LEN(INDEX(Q$1186:Q$1457,$D$139))<=0,NA(),INDEX(Q$1186:Q$1457,$D$139)) -> 0 | ... AX22: =IF(LEN(INDEX(AX$1186:AX$1457,$D$139))<=0,NA(),INDEX(AX$1186:AX$1457,$D$139)) -> 0
A23: Desired operating hours - minimum | H23: ="Operating hours"&CHAR(13)&I23 -> Operating hours_x000D_Wind power plants / Onshore / Electricity only / M | I23: =INDEX(tech_proj!F$1806:F$2077,$D$139)&" / "&INDEX(tech_proj!G$1806:G$2077,$D$139)&" / "&INDEX(tech_proj!H$1806:H$2077,$D$139)&" / "&INDEX(tech_proj!I$1806:I$2077,$D$139) -> Wind power plants / Onshore / Electricity only / M | J23: =IF(LEN(INDEX(tech_proj!J$1806:J$2077,$D$139))<=0,NA(),INDEX(tech_proj!J$1806:J$2077,$D$139)) -> 1400 | K23: =IF(LEN(INDEX(tech_proj!K$1806:K$2077,$D$139))<=0,NA(),INDEX(tech_proj!K$1806:K$2077,$D$139)) -> 1400 | L23: =IF(LEN(INDEX(tech_proj!L$1806:L$2077,$D$139))<=0,NA(),INDEX(tech_proj!L$1806:L$2077,$D$139)) -> 1400 | M23: =IF(LEN(INDEX(tech_proj!M$1806:M$2077,$D$139))<=0,NA(),INDEX(tech_proj!M$1806:M$2077,$D$139)) -> 1400 | N23: =IF(LEN(INDEX(tech_proj!N$1806:N$2077,$D$139))<=0,NA(),INDEX(tech_proj!N$1806:N$2077,$D$139)) -> 1400 | O23: =IF(LEN(INDEX(tech_proj!O$1806:O$2077,$D$139))<=0,NA(),INDEX(tech_proj!O$1806:O$2077,$D$139)) -> 1400 | P23: =IF(LEN(INDEX(tech_proj!P$1806:P$2077,$D$139))<=0,NA(),INDEX(tech_proj!P$1806:P$2077,$D$139)) -> 1400 | Q23: =IF(LEN(INDEX(tech_proj!Q$1806:Q$2077,$D$139))<=0,NA(),INDEX(tech_proj!Q$1806:Q$2077,$D$139)) -> 1400 | ... AX23: =IF(LEN(INDEX(tech_proj!AX$1806:AX$2077,$D$139))<=0,NA(),INDEX(tech_proj!AX$1806:AX$2077,$D$139)) -> 1400
A24: Desired operating hours - maximum | I24: =INDEX(tech_proj!F$2366:F$2637,$D$139)&" / "&INDEX(tech_proj!G$2366:G$2637,$D$139)&" / "&INDEX(tech_proj!H$2366:H$2637,$D$139)&" / "&INDEX(tech_proj!I$2366:I$2637,$D$139) -> Wind power plants / Onshore / Electricity only / M | J24: =IF(LEN(INDEX(tech_proj!J$2366:J$2637,$D$139))<=0,NA(),INDEX(tech_proj!J$2366:J$2637,$D$139)) -> 3375 | K24: =IF(LEN(INDEX(tech_proj!K$2366:K$2637,$D$139))<=0,NA(),INDEX(tech_proj!K$2366:K$2637,$D$139)) -> 3375 | L24: =IF(LEN(INDEX(tech_proj!L$2366:L$2637,$D$139))<=0,NA(),INDEX(tech_proj!L$2366:L$2637,$D$139)) -> 3375 | M24: =IF(LEN(INDEX(tech_proj!M$2366:M$2637,$D$139))<=0,NA(),INDEX(tech_proj!M$2366:M$2637,$D$139)) -> 3375 | N24: =IF(LEN(INDEX(tech_proj!N$2366:N$2637,$D$139))<=0,NA(),INDEX(tech_proj!N$2366:N$2637,$D$139)) -> 3375 | O24: =IF(LEN(INDEX(tech_proj!O$2366:O$2637,$D$139))<=0,NA(),INDEX(tech_proj!O$2366:O$2637,$D$139)) -> 3375 | P24: =IF(LEN(INDEX(tech_proj!P$2366:P$2637,$D$139))<=0,NA(),INDEX(tech_proj!P$2366:P$2637,$D$139)) -> 3375 | Q24: =IF(LEN(INDEX(tech_proj!Q$2366:Q$2637,$D$139))<=0,NA(),INDEX(tech_proj!Q$2366:Q$2637,$D$139)) -> 3375 | ... AX24: =IF(LEN(INDEX(tech_proj!AX$2366:AX$2637,$D$139))<=0,NA(),INDEX(tech_proj!AX$2366:AX$2637,$D$139)) -> 3375
A26: ="LEFT "&$J$344 -> LEFT Levelized costs (€2010 / MWh net) | J26: =J$345 -> 2010 | K26: =K$345 -> 2011 | L26: =L$345 -> 2012 | M26: =M$345 -> 2013 | N26: =N$345 -> 2014 | O26: =O$345 -> 2015 | P26: =P$345 -> 2016 | Q26: =Q$345 -> 2017 | ... AX26: =AX$345 -> 2050
A27: =INDEX(F$346:F$617,$D$120) -> Wind power plants | B27: =INDEX(G$346:G$617,$D$120) -> Onshore | C27: =INDEX(H$346:H$617,$D$120) -> Electricity only | D27: =INDEX(I$346:I$617,$D$120) -> L | I27: =A27&" / "&B27&" / "&C27&" / "&D27 -> Wind power plants / Onshore / Electricity only / L | J27: =INDEX(J$346:J$617,$D$120) -> 36.793908 | K27: =INDEX(K$346:K$617,$D$120) -> 35.005996 | L27: =INDEX(L$346:L$617,$D$120) -> 33.832679 | M27: =INDEX(M$346:M$617,$D$120) -> 33.078404 | N27: =INDEX(N$346:N$617,$D$120) -> 32.64737 | O27: =INDEX(O$346:O$617,$D$120) -> 32.324129 | P27: =INDEX(P$346:P$617,$D$120) -> 31.803541 | Q27: =INDEX(Q$346:Q$617,$D$120) -> 31.461905 | ... AX27: =INDEX(AX$346:AX$617,$D$120) -> 22.377192
A28: =INDEX(F$346:F$617,$D$121) -> Wind power plants | B28: =INDEX(G$346:G$617,$D$121) -> Onshore | C28: =INDEX(H$346:H$617,$D$121) -> Electricity only | D28: =INDEX(I$346:I$617,$D$121) -> M | I28: =A28&" / "&B28&" / "&C28&" / "&D28 -> Wind power plants / Onshore / Electricity only / M | J28: =INDEX(J$346:J$617,$D$121) -> 39.949821 | K28: =INDEX(K$346:K$617,$D$121) -> 38.96766 | L28: =INDEX(L$346:L$617,$D$121) -> 38.28014 | M28: =INDEX(M$346:M$617,$D$121) -> 37.779057 | N28: =INDEX(N$346:N$617,$D$121) -> 37.264124 | O28: =INDEX(O$346:O$617,$D$121) -> 36.529874 | P28: =INDEX(P$346:P$617,$D$121) -> 35.85617 | Q28: =INDEX(Q$346:Q$617,$D$121) -> 35.423876 | ... AX28: =INDEX(AX$346:AX$617,$D$121) -> 25.611284
A29: =INDEX(F$346:F$617,$D$122) -> Wind power plants | B29: =INDEX(G$346:G$617,$D$122) -> Onshore | C29: =INDEX(H$346:H$617,$D$122) -> Electricity only | D29: =INDEX(I$346:I$617,$D$122) -> S | I29: =A29&" / "&B29&" / "&C29&" / "&D29 -> Wind power plants / Onshore / Electricity only / S | J29: =INDEX(J$346:J$617,$D$122) -> 43.08282 | K29: =INDEX(K$346:K$617,$D$122) -> 42.409645 | L29: =INDEX(L$346:L$617,$D$122) -> 41.989748 | M29: =INDEX(M$346:M$617,$D$122) -> 41.574008 | N29: =INDEX(N$346:N$617,$D$122) -> 41.162384 | O29: =INDEX(O$346:O$617,$D$122) -> 40.754836 | P29: =INDEX(P$346:P$617,$D$122) -> 40.097093 | Q29: =INDEX(Q$346:Q$617,$D$122) -> 39.472238 | ... AX29: =INDEX(AX$346:AX$617,$D$122) -> 28.465507
A30: =INDEX(F$346:F$617,$D$123) -> Wind power plants | B30: =INDEX(G$346:G$617,$D$123) -> Onshore | C30: =INDEX(H$346:H$617,$D$123) -> Electricity only | D30: =INDEX(I$346:I$617,$D$123) -> XS | I30: =A30&" / "&B30&" / "&C30&" / "&D30 -> Wind power plants / Onshore / Electricity only / XS | J30: =INDEX(J$346:J$617,$D$123) -> 51.610007 | K30: =INDEX(K$346:K$617,$D$123) -> 51.132755 | L30: =INDEX(L$346:L$617,$D$123) -> 50.726939 | M30: =INDEX(M$346:M$617,$D$123) -> 50.324344 | N30: =INDEX(N$346:N$617,$D$123) -> 49.924945 | O30: =INDEX(O$346:O$617,$D$123) -> 49.528715 | P30: =INDEX(P$346:P$617,$D$123) -> 49.145397 | Q30: =INDEX(Q$346:Q$617,$D$123) -> 48.658809 | ... AX30: =INDEX(AX$346:AX$617,$D$123) -> 39.020179
I31: min | J31: =MIN(J27:J30) -> 36.793908 | K31: =MIN(K27:K30) -> 35.005996 | L31: =MIN(L27:L30) -> 33.832679 | M31: =MIN(M27:M30) -> 33.078404 | N31: =MIN(N27:N30) -> 32.64737 | O31: =MIN(O27:O30) -> 32.324129 | P31: =MIN(P27:P30) -> 31.803541 | Q31: =MIN(Q27:Q30) -> 31.461905 | ... AX31: =MIN(AX27:AX30) -> 22.377192
I32: max | J32: =MAX(J27:J30) -> 51.610007 | K32: =MAX(K27:K30) -> 51.132755 | L32: =MAX(L27:L30) -> 50.726939 | M32: =MAX(M27:M30) -> 50.324344 | N32: =MAX(N27:N30) -> 49.924945 | O32: =MAX(O27:O30) -> 49.528715 | P32: =MAX(P27:P30) -> 49.145397 | Q32: =MAX(Q27:Q30) -> 48.658809 | ... AX32: =MAX(AX27:AX30) -> 39.020179
I33: diff | J33: =J32-J31 -> 14.816099 | K33: =K32-K31 -> 16.126758 | L33: =L32-L31 -> 16.89426 | M33: =M32-M31 -> 17.24594 | N33: =N32-N31 -> 17.277574 | O33: =O32-O31 -> 17.204586 | P33: =P32-P31 -> 17.341855 | Q33: =Q32-Q31 -> 17.196903 | ... AX33: =AX32-AX31 -> 16.642986
A34: ="LEFT "&$J$624 -> LEFT Fixed annual levelized costs | J34: =J$625 -> 2010 | K34: =K$625 -> 2011 | L34: =L$625 -> 2012 | M34: =M$625 -> 2013 | N34: =N$625 -> 2014 | O34: =O$625 -> 2015 | P34: =P$625 -> 2016 | Q34: =Q$625 -> 2017 | ... AX34: =AX$625 -> 2050
A35: =INDEX(F$626:F$897,$D$120) -> Wind power plants | B35: =INDEX(G$626:G$897,$D$120) -> Onshore | C35: =INDEX(H$626:H$897,$D$120) -> Electricity only | D35: =INDEX(I$626:I$897,$D$120) -> L | I35: =A35&" / "&B35&" / "&C35&" / "&D35 -> Wind power plants / Onshore / Electricity only / L | J35: =INDEX(J$626:J$897,$D$120) -> 36.224154 | K35: =INDEX(K$626:K$897,$D$120) -> 34.463928 | L35: =INDEX(L$626:L$897,$D$120) -> 33.30878 | M35: =INDEX(M$626:M$897,$D$120) -> 32.566185 | N35: =INDEX(N$626:N$897,$D$120) -> 32.141826 | O35: =INDEX(O$626:O$897,$D$120) -> 31.82359 | P35: =INDEX(P$626:P$897,$D$120) -> 31.311063 | Q35: =INDEX(Q$626:Q$897,$D$120) -> 30.974718 | ... AX35: =INDEX(AX$626:AX$897,$D$120) -> 22.030682
A36: =INDEX(F$626:F$897,$D$121) -> Wind power plants | B36: =INDEX(G$626:G$897,$D$121) -> Onshore | C36: =INDEX(H$626:H$897,$D$121) -> Electricity only | D36: =INDEX(I$626:I$897,$D$121) -> M | I36: =A36&" / "&B36&" / "&C36&" / "&D36 -> Wind power plants / Onshore / Electricity only / M | J36: =INDEX(J$626:J$897,$D$121) -> 39.354636 | K36: =INDEX(K$626:K$897,$D$121) -> 38.387108 | L36: =INDEX(L$626:L$897,$D$121) -> 37.709831 | M36: =INDEX(M$626:M$897,$D$121) -> 37.216213 | N36: =INDEX(N$626:N$897,$D$121) -> 36.708952 | O36: =INDEX(O$626:O$897,$D$121) -> 35.985641 | P36: =INDEX(P$626:P$897,$D$121) -> 35.321974 | Q36: =INDEX(Q$626:Q$897,$D$121) -> 34.896121 | ... AX36: =INDEX(AX$626:AX$897,$D$121) -> 25.229719
A37: =INDEX(F$626:F$897,$D$122) -> Wind power plants | B37: =INDEX(G$626:G$897,$D$122) -> Onshore | C37: =INDEX(H$626:H$897,$D$122) -> Electricity only | D37: =INDEX(I$626:I$897,$D$122) -> S | I37: =A37&" / "&B37&" / "&C37&" / "&D37 -> Wind power plants / Onshore / Electricity only / S | J37: =INDEX(J$626:J$897,$D$122) -> 42.485119 | K37: =INDEX(K$626:K$897,$D$122) -> 41.821284 | L37: =INDEX(L$626:L$897,$D$122) -> 41.407211 | M37: =INDEX(M$626:M$897,$D$122) -> 40.997239 | N37: =INDEX(N$626:N$897,$D$122) -> 40.591326 | O37: =INDEX(O$626:O$897,$D$122) -> 40.189431 | P37: =INDEX(P$626:P$897,$D$122) -> 39.540814 | Q37: =INDEX(Q$626:Q$897,$D$122) -> 38.924628 | ... AX37: =INDEX(AX$626:AX$897,$D$122) -> 28.070596
A38: =INDEX(F$626:F$897,$D$123) -> Wind power plants | B38: =INDEX(G$626:G$897,$D$123) -> Onshore | C38: =INDEX(H$626:H$897,$D$123) -> Electricity only | D38: =INDEX(I$626:I$897,$D$123) -> XS | I38: =A38&" / "&B38&" / "&C38&" / "&D38 -> Wind power plants / Onshore / Electricity only / XS | J38: =INDEX(J$626:J$897,$D$123) -> 51.011956 | K38: =INDEX(K$626:K$897,$D$123) -> 50.540234 | L38: =INDEX(L$626:L$897,$D$123) -> 50.139121 | M38: =INDEX(M$626:M$897,$D$123) -> 49.741192 | N38: =INDEX(N$626:N$897,$D$123) -> 49.346421 | O38: =INDEX(O$626:O$897,$D$123) -> 48.954782 | P38: =INDEX(P$626:P$897,$D$123) -> 48.575906 | Q38: =INDEX(Q$626:Q$897,$D$123) -> 48.094956 | ... AX38: =INDEX(AX$626:AX$897,$D$123) -> 38.568018
I39: min | J39: =MIN(J35:J38) -> 36.224154 | K39: =MIN(K35:K38) -> 34.463928 | L39: =MIN(L35:L38) -> 33.30878 | M39: =MIN(M35:M38) -> 32.566185 | N39: =MIN(N35:N38) -> 32.141826 | O39: =MIN(O35:O38) -> 31.82359 | P39: =MIN(P35:P38) -> 31.311063 | Q39: =MIN(Q35:Q38) -> 30.974718 | ... AX39: =MIN(AX35:AX38) -> 22.030682
I40: max | J40: =MAX(J35:J38) -> 51.011956 | K40: =MAX(K35:K38) -> 50.540234 | L40: =MAX(L35:L38) -> 50.139121 | M40: =MAX(M35:M38) -> 49.741192 | N40: =MAX(N35:N38) -> 49.346421 | O40: =MAX(O35:O38) -> 48.954782 | P40: =MAX(P35:P38) -> 48.575906 | Q40: =MAX(Q35:Q38) -> 48.094956 | ... AX40: =MAX(AX35:AX38) -> 38.568018
I41: diff | J41: =J40-J39 -> 14.787803 | K41: =K40-K39 -> 16.076306 | L41: =L40-L39 -> 16.830341 | M41: =M40-M39 -> 17.175007 | N41: =N40-N39 -> 17.204595 | O41: =O40-O39 -> 17.131192 | P41: =P40-P39 -> 17.264842 | Q41: =Q40-Q39 -> 17.120239 | ... AX41: =AX40-AX39 -> 16.537336
A42: ="LEFT "&$J$904 -> LEFT Fuel and variable costs | J42: =J$905 -> 2010 | K42: =K$905 -> 2011 | L42: =L$905 -> 2012 | M42: =M$905 -> 2013 | N42: =N$905 -> 2014 | O42: =O$905 -> 2015 | P42: =P$905 -> 2016 | Q42: =Q$905 -> 2017 | ... AX42: =AX$905 -> 2050
A43: =INDEX(F$906:F$1177,$D$120) -> Wind power plants | B43: =INDEX(G$906:G$1177,$D$120) -> Onshore | C43: =INDEX(H$906:H$1177,$D$120) -> Electricity only | D43: =INDEX(I$906:I$1177,$D$120) -> L | I43: =A43&" / "&B43&" / "&C43&" / "&D43 -> Wind power plants / Onshore / Electricity only / L | J43: =INDEX(J$906:J$1177,$D$120) -> 0.56975381 | K43: =INDEX(K$906:K$1177,$D$120) -> 0.542068 | L43: =INDEX(L$906:L$1177,$D$120) -> 0.52389918 | M43: =INDEX(M$906:M$1177,$D$120) -> 0.51221923 | N43: =INDEX(N$906:N$1177,$D$120) -> 0.50554467 | O43: =INDEX(O$906:O$1177,$D$120) -> 0.50053927 | P43: =INDEX(P$906:P$1177,$D$120) -> 0.49247797 | Q43: =INDEX(Q$906:Q$1177,$D$120) -> 0.48718773 | ... AX43: =INDEX(AX$906:AX$1177,$D$120) -> 0.34651092
A44: =INDEX(F$906:F$1177,$D$121) -> Wind power plants | B44: =INDEX(G$906:G$1177,$D$121) -> Onshore | C44: =INDEX(H$906:H$1177,$D$121) -> Electricity only | D44: =INDEX(I$906:I$1177,$D$121) -> M | I44: =A44&" / "&B44&" / "&C44&" / "&D44 -> Wind power plants / Onshore / Electricity only / M | J44: =INDEX(J$906:J$1177,$D$121) -> 0.59518442 | K44: =INDEX(K$906:K$1177,$D$121) -> 0.5805519 | L44: =INDEX(L$906:L$1177,$D$121) -> 0.57030901 | M44: =INDEX(M$906:M$1177,$D$121) -> 0.56284373 | N44: =INDEX(N$906:N$1177,$D$121) -> 0.55517211 | O44: =INDEX(O$906:O$1177,$D$121) -> 0.54423302 | P44: =INDEX(P$906:P$1177,$D$121) -> 0.53419598 | Q44: =INDEX(Q$906:Q$1177,$D$121) -> 0.52775554 | ... AX44: =INDEX(AX$906:AX$1177,$D$121) -> 0.3815646
A45: =INDEX(F$906:F$1177,$D$122) -> Wind power plants | B45: =INDEX(G$906:G$1177,$D$122) -> Onshore | C45: =INDEX(H$906:H$1177,$D$122) -> Electricity only | D45: =INDEX(I$906:I$1177,$D$122) -> S | I45: =A45&" / "&B45&" / "&C45&" / "&D45 -> Wind power plants / Onshore / Electricity only / S | J45: =INDEX(J$906:J$1177,$D$122) -> 0.59770105 | K45: =INDEX(K$906:K$1177,$D$122) -> 0.5883619 | L45: =INDEX(L$906:L$1177,$D$122) -> 0.58253654 | M45: =INDEX(M$906:M$1177,$D$122) -> 0.57676885 | N45: =INDEX(N$906:N$1177,$D$122) -> 0.57105827 | O45: =INDEX(O$906:O$1177,$D$122) -> 0.56540422 | P45: =INDEX(P$906:P$1177,$D$122) -> 0.55627916 | Q45: =INDEX(Q$906:Q$1177,$D$122) -> 0.54761036 | ... AX45: =INDEX(AX$906:AX$1177,$D$122) -> 0.39491063
A46: =INDEX(F$906:F$1177,$D$123) -> Wind power plants | B46: =INDEX(G$906:G$1177,$D$123) -> Onshore | C46: =INDEX(H$906:H$1177,$D$123) -> Electricity only | D46: =INDEX(I$906:I$1177,$D$123) -> XS | I46: =A46&" / "&B46&" / "&C46&" / "&D46 -> Wind power plants / Onshore / Electricity only / XS | J46: =INDEX(J$906:J$1177,$D$123) -> 0.59805059 | K46: =INDEX(K$906:K$1177,$D$123) -> 0.59252024 | L46: =INDEX(L$906:L$1177,$D$123) -> 0.5878177 | M46: =INDEX(M$906:M$1177,$D$123) -> 0.58315248 | N46: =INDEX(N$906:N$1177,$D$123) -> 0.57852429 | O46: =INDEX(O$906:O$1177,$D$123) -> 0.57393282 | P46: =INDEX(P$906:P$1177,$D$123) -> 0.56949098 | Q46: =INDEX(Q$906:Q$1177,$D$123) -> 0.56385245 | ... AX46: =INDEX(AX$906:AX$1177,$D$123) -> 0.45216116
I47: min | J47: =MIN(J43:J46) -> 0.56975381 | K47: =MIN(K43:K46) -> 0.542068 | L47: =MIN(L43:L46) -> 0.52389918 | M47: =MIN(M43:M46) -> 0.51221923 | N47: =MIN(N43:N46) -> 0.50554467 | O47: =MIN(O43:O46) -> 0.50053927 | P47: =MIN(P43:P46) -> 0.49247797 | Q47: =MIN(Q43:Q46) -> 0.48718773 | ... AX47: =MIN(AX43:AX46) -> 0.34651092
I48: max | J48: =MAX(J43:J46) -> 0.59805059 | K48: =MAX(K43:K46) -> 0.59252024 | L48: =MAX(L43:L46) -> 0.5878177 | M48: =MAX(M43:M46) -> 0.58315248 | N48: =MAX(N43:N46) -> 0.57852429 | O48: =MAX(O43:O46) -> 0.57393282 | P48: =MAX(P43:P46) -> 0.56949098 | Q48: =MAX(Q43:Q46) -> 0.56385245 | ... AX48: =MAX(AX43:AX46) -> 0.45216116
I49: diff | J49: =J48-J47 -> 0.028296776 | K49: =K48-K47 -> 0.050452247 | L49: =L48-L47 -> 0.063918521 | M49: =M48-M47 -> 0.070933255 | N49: =N48-N47 -> 0.072979621 | O49: =O48-O47 -> 0.073393551 | P49: =P48-P47 -> 0.07701301 | Q49: =Q48-Q47 -> 0.076664718 | ... AX49: =AX48-AX47 -> 0.10565025
A50: ="LEFT "&$J$1184 -> LEFT CO2 emission related costs | J50: =J$1185 -> 2010 | K50: =K$1185 -> 2011 | L50: =L$1185 -> 2012 | M50: =M$1185 -> 2013 | N50: =N$1185 -> 2014 | O50: =O$1185 -> 2015 | P50: =P$1185 -> 2016 | Q50: =Q$1185 -> 2017 | ... AX50: =AX$1185 -> 2050
A51: =INDEX(F$1186:F$1457,$D$120) -> Wind power plants | B51: =INDEX(G$1186:G$1457,$D$120) -> Onshore | C51: =INDEX(H$1186:H$1457,$D$120) -> Electricity only | D51: =INDEX(I$1186:I$1457,$D$120) -> L | I51: =A51&" / "&B51&" / "&C51&" / "&D51 -> Wind power plants / Onshore / Electricity only / L | J51: =INDEX(J$1186:J$1457,$D$120) -> 0 | K51: =INDEX(K$1186:K$1457,$D$120) -> 0 | L51: =INDEX(L$1186:L$1457,$D$120) -> 0 | M51: =INDEX(M$1186:M$1457,$D$120) -> 0 | N51: =INDEX(N$1186:N$1457,$D$120) -> 0 | O51: =INDEX(O$1186:O$1457,$D$120) -> 0 | P51: =INDEX(P$1186:P$1457,$D$120) -> 0 | Q51: =INDEX(Q$1186:Q$1457,$D$120) -> 0 | ... AX51: =INDEX(AX$1186:AX$1457,$D$120) -> 0
A52: =INDEX(F$1186:F$1457,$D$121) -> Wind power plants | B52: =INDEX(G$1186:G$1457,$D$121) -> Onshore | C52: =INDEX(H$1186:H$1457,$D$121) -> Electricity only | D52: =INDEX(I$1186:I$1457,$D$121) -> M | I52: =A52&" / "&B52&" / "&C52&" / "&D52 -> Wind power plants / Onshore / Electricity only / M | J52: =INDEX(J$1186:J$1457,$D$121) -> 0 | K52: =INDEX(K$1186:K$1457,$D$121) -> 0 | L52: =INDEX(L$1186:L$1457,$D$121) -> 0 | M52: =INDEX(M$1186:M$1457,$D$121) -> 0 | N52: =INDEX(N$1186:N$1457,$D$121) -> 0 | O52: =INDEX(O$1186:O$1457,$D$121) -> 0 | P52: =INDEX(P$1186:P$1457,$D$121) -> 0 | Q52: =INDEX(Q$1186:Q$1457,$D$121) -> 0 | ... AX52: =INDEX(AX$1186:AX$1457,$D$121) -> 0
A53: =INDEX(F$1186:F$1457,$D$122) -> Wind power plants | B53: =INDEX(G$1186:G$1457,$D$122) -> Onshore | C53: =INDEX(H$1186:H$1457,$D$122) -> Electricity only | D53: =INDEX(I$1186:I$1457,$D$122) -> S | I53: =A53&" / "&B53&" / "&C53&" / "&D53 -> Wind power plants / Onshore / Electricity only / S | J53: =INDEX(J$1186:J$1457,$D$122) -> 0 | K53: =INDEX(K$1186:K$1457,$D$122) -> 0 | L53: =INDEX(L$1186:L$1457,$D$122) -> 0 | M53: =INDEX(M$1186:M$1457,$D$122) -> 0 | N53: =INDEX(N$1186:N$1457,$D$122) -> 0 | O53: =INDEX(O$1186:O$1457,$D$122) -> 0 | P53: =INDEX(P$1186:P$1457,$D$122) -> 0 | Q53: =INDEX(Q$1186:Q$1457,$D$122) -> 0 | ... AX53: =INDEX(AX$1186:AX$1457,$D$122) -> 0
A54: =INDEX(F$1186:F$1457,$D$123) -> Wind power plants | B54: =INDEX(G$1186:G$1457,$D$123) -> Onshore | C54: =INDEX(H$1186:H$1457,$D$123) -> Electricity only | D54: =INDEX(I$1186:I$1457,$D$123) -> XS | I54: =A54&" / "&B54&" / "&C54&" / "&D54 -> Wind power plants / Onshore / Electricity only / XS | J54: =INDEX(J$1186:J$1457,$D$123) -> 0 | K54: =INDEX(K$1186:K$1457,$D$123) -> 0 | L54: =INDEX(L$1186:L$1457,$D$123) -> 0 | M54: =INDEX(M$1186:M$1457,$D$123) -> 0 | N54: =INDEX(N$1186:N$1457,$D$123) -> 0 | O54: =INDEX(O$1186:O$1457,$D$123) -> 0 | P54: =INDEX(P$1186:P$1457,$D$123) -> 0 | Q54: =INDEX(Q$1186:Q$1457,$D$123) -> 0 | ... AX54: =INDEX(AX$1186:AX$1457,$D$123) -> 0
I55: min | J55: =MIN(J51:J54) -> 0 | K55: =MIN(K51:K54) -> 0 | L55: =MIN(L51:L54) -> 0 | M55: =MIN(M51:M54) -> 0 | N55: =MIN(N51:N54) -> 0 | O55: =MIN(O51:O54) -> 0 | P55: =MIN(P51:P54) -> 0 | Q55: =MIN(Q51:Q54) -> 0 | ... AX55: =MIN(AX51:AX54) -> 0
I56: max | J56: =MAX(J51:J54) -> 0 | K56: =MAX(K51:K54) -> 0 | L56: =MAX(L51:L54) -> 0 | M56: =MAX(M51:M54) -> 0 | N56: =MAX(N51:N54) -> 0 | O56: =MAX(O51:O54) -> 0 | P56: =MAX(P51:P54) -> 0 | Q56: =MAX(Q51:Q54) -> 0 | ... AX56: =MAX(AX51:AX54) -> 0
I57: diff | J57: =J56-J55 -> 0 | K57: =K56-K55 -> 0 | L57: =L56-L55 -> 0 | M57: =M56-M55 -> 0 | N57: =N56-N55 -> 0 | O57: =O56-O55 -> 0 | P57: =P56-P55 -> 0 | Q57: =Q56-Q55 -> 0 | ... AX57: =AX56-AX55 -> 0
A58: LEFT Desired operating hours - maximum to minimum diff | J58: =J16-J15 -> 2350 | K58: =K16-K15 -> 2350 | L58: =L16-L15 -> 2350 | M58: =M16-M15 -> 2350 | N58: =N16-N15 -> 2350 | O58: =O16-O15 -> 2350 | P58: =P16-P15 -> 2350 | Q58: =Q16-Q15 -> 2350 | ... AX58: =AX16-AX15 -> 2350
A59: ="RIGHT "&$J$344 -> RIGHT Levelized costs (€2010 / MWh net) | J59: =J$345 -> 2010 | K59: =K$345 -> 2011 | L59: =L$345 -> 2012 | M59: =M$345 -> 2013 | N59: =N$345 -> 2014 | O59: =O$345 -> 2015 | P59: =P$345 -> 2016 | Q59: =Q$345 -> 2017 | ... AX59: =AX$345 -> 2050
A60: =INDEX(F$346:F$617,$D$140) -> Wind power plants | B60: =INDEX(G$346:G$617,$D$140) -> Onshore | C60: =INDEX(H$346:H$617,$D$140) -> Electricity only | D60: =INDEX(I$346:I$617,$D$140) -> L | I60: =A60&" / "&B60&" / "&C60&" / "&D60 -> Wind power plants / Onshore / Electricity only / L | J60: =INDEX(J$346:J$617,$D$140) -> 36.793908 | K60: =INDEX(K$346:K$617,$D$140) -> 35.005996 | L60: =INDEX(L$346:L$617,$D$140) -> 33.832679 | M60: =INDEX(M$346:M$617,$D$140) -> 33.078404 | N60: =INDEX(N$346:N$617,$D$140) -> 32.64737 | O60: =INDEX(O$346:O$617,$D$140) -> 32.324129 | P60: =INDEX(P$346:P$617,$D$140) -> 31.803541 | Q60: =INDEX(Q$346:Q$617,$D$140) -> 31.461905 | ... AX60: =INDEX(AX$346:AX$617,$D$140) -> 22.377192
A61: =INDEX(F$346:F$617,$D$141) -> Wind power plants | B61: =INDEX(G$346:G$617,$D$141) -> Onshore | C61: =INDEX(H$346:H$617,$D$141) -> Electricity only | D61: =INDEX(I$346:I$617,$D$141) -> M | I61: =A61&" / "&B61&" / "&C61&" / "&D61 -> Wind power plants / Onshore / Electricity only / M | J61: =INDEX(J$346:J$617,$D$141) -> 39.949821 | K61: =INDEX(K$346:K$617,$D$141) -> 38.96766 | L61: =INDEX(L$346:L$617,$D$141) -> 38.28014 | M61: =INDEX(M$346:M$617,$D$141) -> 37.779057 | N61: =INDEX(N$346:N$617,$D$141) -> 37.264124 | O61: =INDEX(O$346:O$617,$D$141) -> 36.529874 | P61: =INDEX(P$346:P$617,$D$141) -> 35.85617 | Q61: =INDEX(Q$346:Q$617,$D$141) -> 35.423876 | ... AX61: =INDEX(AX$346:AX$617,$D$141) -> 25.611284
A62: =INDEX(F$346:F$617,$D$142) -> Wind power plants | B62: =INDEX(G$346:G$617,$D$142) -> Onshore | C62: =INDEX(H$346:H$617,$D$142) -> Electricity only | D62: =INDEX(I$346:I$617,$D$142) -> S | I62: =A62&" / "&B62&" / "&C62&" / "&D62 -> Wind power plants / Onshore / Electricity only / S | J62: =INDEX(J$346:J$617,$D$142) -> 43.08282 | K62: =INDEX(K$346:K$617,$D$142) -> 42.409645 | L62: =INDEX(L$346:L$617,$D$142) -> 41.989748 | M62: =INDEX(M$346:M$617,$D$142) -> 41.574008 | N62: =INDEX(N$346:N$617,$D$142) -> 41.162384 | O62: =INDEX(O$346:O$617,$D$142) -> 40.754836 | P62: =INDEX(P$346:P$617,$D$142) -> 40.097093 | Q62: =INDEX(Q$346:Q$617,$D$142) -> 39.472238 | ... AX62: =INDEX(AX$346:AX$617,$D$142) -> 28.465507
A63: =INDEX(F$346:F$617,$D$143) -> Wind power plants | B63: =INDEX(G$346:G$617,$D$143) -> Onshore | C63: =INDEX(H$346:H$617,$D$143) -> Electricity only | D63: =INDEX(I$346:I$617,$D$143) -> XS | I63: =A63&" / "&B63&" / "&C63&" / "&D63 -> Wind power plants / Onshore / Electricity only / XS | J63: =INDEX(J$346:J$617,$D$143) -> 51.610007 | K63: =INDEX(K$346:K$617,$D$143) -> 51.132755 | L63: =INDEX(L$346:L$617,$D$143) -> 50.726939 | M63: =INDEX(M$346:M$617,$D$143) -> 50.324344 | N63: =INDEX(N$346:N$617,$D$143) -> 49.924945 | O63: =INDEX(O$346:O$617,$D$143) -> 49.528715 | P63: =INDEX(P$346:P$617,$D$143) -> 49.145397 | Q63: =INDEX(Q$346:Q$617,$D$143) -> 48.658809 | ... AX63: =INDEX(AX$346:AX$617,$D$143) -> 39.020179
I64: min | J64: =MIN(J60:J63) -> 36.793908 | K64: =MIN(K60:K63) -> 35.005996 | L64: =MIN(L60:L63) -> 33.832679 | M64: =MIN(M60:M63) -> 33.078404 | N64: =MIN(N60:N63) -> 32.64737 | O64: =MIN(O60:O63) -> 32.324129 | P64: =MIN(P60:P63) -> 31.803541 | Q64: =MIN(Q60:Q63) -> 31.461905 | ... AX64: =MIN(AX60:AX63) -> 22.377192
I65: max | J65: =MAX(J60:J63) -> 51.610007 | K65: =MAX(K60:K63) -> 51.132755 | L65: =MAX(L60:L63) -> 50.726939 | M65: =MAX(M60:M63) -> 50.324344 | N65: =MAX(N60:N63) -> 49.924945 | O65: =MAX(O60:O63) -> 49.528715 | P65: =MAX(P60:P63) -> 49.145397 | Q65: =MAX(Q60:Q63) -> 48.658809 | ... AX65: =MAX(AX60:AX63) -> 39.020179
I66: diff | J66: =J65-J64 -> 14.816099 | K66: =K65-K64 -> 16.126758 | L66: =L65-L64 -> 16.89426 | M66: =M65-M64 -> 17.24594 | N66: =N65-N64 -> 17.277574 | O66: =O65-O64 -> 17.204586 | P66: =P65-P64 -> 17.341855 | Q66: =Q65-Q64 -> 17.196903 | ... AX66: =AX65-AX64 -> 16.642986
A67: ="RIGHT "&$J$624 -> RIGHT Fixed annual levelized costs | J67: =J$625 -> 2010 | K67: =K$625 -> 2011 | L67: =L$625 -> 2012 | M67: =M$625 -> 2013 | N67: =N$625 -> 2014 | O67: =O$625 -> 2015 | P67: =P$625 -> 2016 | Q67: =Q$625 -> 2017 | ... AX67: =AX$625 -> 2050
A68: =INDEX(F$626:F$897,$D$140) -> Wind power plants | B68: =INDEX(G$626:G$897,$D$140) -> Onshore | C68: =INDEX(H$626:H$897,$D$140) -> Electricity only | D68: =INDEX(I$626:I$897,$D$140) -> L | I68: =A68&" / "&B68&" / "&C68&" / "&D68 -> Wind power plants / Onshore / Electricity only / L | J68: =INDEX(J$626:J$897,$D$140) -> 36.224154 | K68: =INDEX(K$626:K$897,$D$140) -> 34.463928 | L68: =INDEX(L$626:L$897,$D$140) -> 33.30878 | M68: =INDEX(M$626:M$897,$D$140) -> 32.566185 | N68: =INDEX(N$626:N$897,$D$140) -> 32.141826 | O68: =INDEX(O$626:O$897,$D$140) -> 31.82359 | P68: =INDEX(P$626:P$897,$D$140) -> 31.311063 | Q68: =INDEX(Q$626:Q$897,$D$140) -> 30.974718 | ... AX68: =INDEX(AX$626:AX$897,$D$140) -> 22.030682
A69: =INDEX(F$626:F$897,$D$141) -> Wind power plants | B69: =INDEX(G$626:G$897,$D$141) -> Onshore | C69: =INDEX(H$626:H$897,$D$141) -> Electricity only | D69: =INDEX(I$626:I$897,$D$141) -> M | I69: =A69&" / "&B69&" / "&C69&" / "&D69 -> Wind power plants / Onshore / Electricity only / M | J69: =INDEX(J$626:J$897,$D$141) -> 39.354636 | K69: =INDEX(K$626:K$897,$D$141) -> 38.387108 | L69: =INDEX(L$626:L$897,$D$141) -> 37.709831 | M69: =INDEX(M$626:M$897,$D$141) -> 37.216213 | N69: =INDEX(N$626:N$897,$D$141) -> 36.708952 | O69: =INDEX(O$626:O$897,$D$141) -> 35.985641 | P69: =INDEX(P$626:P$897,$D$141) -> 35.321974 | Q69: =INDEX(Q$626:Q$897,$D$141) -> 34.896121 | ... AX69: =INDEX(AX$626:AX$897,$D$141) -> 25.229719
A70: =INDEX(F$626:F$897,$D$142) -> Wind power plants | B70: =INDEX(G$626:G$897,$D$142) -> Onshore | C70: =INDEX(H$626:H$897,$D$142) -> Electricity only | D70: =INDEX(I$626:I$897,$D$142) -> S | I70: =A70&" / "&B70&" / "&C70&" / "&D70 -> Wind power plants / Onshore / Electricity only / S | J70: =INDEX(J$626:J$897,$D$142) -> 42.485119 | K70: =INDEX(K$626:K$897,$D$142) -> 41.821284 | L70: =INDEX(L$626:L$897,$D$142) -> 41.407211 | M70: =INDEX(M$626:M$897,$D$142) -> 40.997239 | N70: =INDEX(N$626:N$897,$D$142) -> 40.591326 | O70: =INDEX(O$626:O$897,$D$142) -> 40.189431 | P70: =INDEX(P$626:P$897,$D$142) -> 39.540814 | Q70: =INDEX(Q$626:Q$897,$D$142) -> 38.924628 | ... AX70: =INDEX(AX$626:AX$897,$D$142) -> 28.070596
A71: =INDEX(F$626:F$897,$D$143) -> Wind power plants | B71: =INDEX(G$626:G$897,$D$143) -> Onshore | C71: =INDEX(H$626:H$897,$D$143) -> Electricity only | D71: =INDEX(I$626:I$897,$D$143) -> XS | I71: =A71&" / "&B71&" / "&C71&" / "&D71 -> Wind power plants / Onshore / Electricity only / XS | J71: =INDEX(J$626:J$897,$D$143) -> 51.011956 | K71: =INDEX(K$626:K$897,$D$143) -> 50.540234 | L71: =INDEX(L$626:L$897,$D$143) -> 50.139121 | M71: =INDEX(M$626:M$897,$D$143) -> 49.741192 | N71: =INDEX(N$626:N$897,$D$143) -> 49.346421 | O71: =INDEX(O$626:O$897,$D$143) -> 48.954782 | P71: =INDEX(P$626:P$897,$D$143) -> 48.575906 | Q71: =INDEX(Q$626:Q$897,$D$143) -> 48.094956 | ... AX71: =INDEX(AX$626:AX$897,$D$143) -> 38.568018
I72: min | J72: =MIN(J68:J71) -> 36.224154 | K72: =MIN(K68:K71) -> 34.463928 | L72: =MIN(L68:L71) -> 33.30878 | M72: =MIN(M68:M71) -> 32.566185 | N72: =MIN(N68:N71) -> 32.141826 | O72: =MIN(O68:O71) -> 31.82359 | P72: =MIN(P68:P71) -> 31.311063 | Q72: =MIN(Q68:Q71) -> 30.974718 | ... AX72: =MIN(AX68:AX71) -> 22.030682
I73: max | J73: =MAX(J68:J71) -> 51.011956 | K73: =MAX(K68:K71) -> 50.540234 | L73: =MAX(L68:L71) -> 50.139121 | M73: =MAX(M68:M71) -> 49.741192 | N73: =MAX(N68:N71) -> 49.346421 | O73: =MAX(O68:O71) -> 48.954782 | P73: =MAX(P68:P71) -> 48.575906 | Q73: =MAX(Q68:Q71) -> 48.094956 | ... AX73: =MAX(AX68:AX71) -> 38.568018
I74: diff | J74: =J73-J72 -> 14.787803 | K74: =K73-K72 -> 16.076306 | L74: =L73-L72 -> 16.830341 | M74: =M73-M72 -> 17.175007 | N74: =N73-N72 -> 17.204595 | O74: =O73-O72 -> 17.131192 | P74: =P73-P72 -> 17.264842 | Q74: =Q73-Q72 -> 17.120239 | ... AX74: =AX73-AX72 -> 16.537336
A75: ="RIGHT "&$J$904 -> RIGHT Fuel and variable costs | J75: =J$905 -> 2010 | K75: =K$905 -> 2011 | L75: =L$905 -> 2012 | M75: =M$905 -> 2013 | N75: =N$905 -> 2014 | O75: =O$905 -> 2015 | P75: =P$905 -> 2016 | Q75: =Q$905 -> 2017 | ... AX75: =AX$905 -> 2050
A76: =INDEX(F$906:F$1177,$D$140) -> Wind power plants | B76: =INDEX(G$906:G$1177,$D$140) -> Onshore | C76: =INDEX(H$906:H$1177,$D$140) -> Electricity only | D76: =INDEX(I$906:I$1177,$D$140) -> L | I76: =A76&" / "&B76&" / "&C76&" / "&D76 -> Wind power plants / Onshore / Electricity only / L | J76: =INDEX(J$906:J$1177,$D$140) -> 0.56975381 | K76: =INDEX(K$906:K$1177,$D$140) -> 0.542068 | L76: =INDEX(L$906:L$1177,$D$140) -> 0.52389918 | M76: =INDEX(M$906:M$1177,$D$140) -> 0.51221923 | N76: =INDEX(N$906:N$1177,$D$140) -> 0.50554467 | O76: =INDEX(O$906:O$1177,$D$140) -> 0.50053927 | P76: =INDEX(P$906:P$1177,$D$140) -> 0.49247797 | Q76: =INDEX(Q$906:Q$1177,$D$140) -> 0.48718773 | ... AX76: =INDEX(AX$906:AX$1177,$D$140) -> 0.34651092
A77: =INDEX(F$906:F$1177,$D$141) -> Wind power plants | B77: =INDEX(G$906:G$1177,$D$141) -> Onshore | C77: =INDEX(H$906:H$1177,$D$141) -> Electricity only | D77: =INDEX(I$906:I$1177,$D$141) -> M | I77: =A77&" / "&B77&" / "&C77&" / "&D77 -> Wind power plants / Onshore / Electricity only / M | J77: =INDEX(J$906:J$1177,$D$141) -> 0.59518442 | K77: =INDEX(K$906:K$1177,$D$141) -> 0.5805519 | L77: =INDEX(L$906:L$1177,$D$141) -> 0.57030901 | M77: =INDEX(M$906:M$1177,$D$141) -> 0.56284373 | N77: =INDEX(N$906:N$1177,$D$141) -> 0.55517211 | O77: =INDEX(O$906:O$1177,$D$141) -> 0.54423302 | P77: =INDEX(P$906:P$1177,$D$141) -> 0.53419598 | Q77: =INDEX(Q$906:Q$1177,$D$141) -> 0.52775554 | ... AX77: =INDEX(AX$906:AX$1177,$D$141) -> 0.3815646
A78: =INDEX(F$906:F$1177,$D$142) -> Wind power plants | B78: =INDEX(G$906:G$1177,$D$142) -> Onshore | C78: =INDEX(H$906:H$1177,$D$142) -> Electricity only | D78: =INDEX(I$906:I$1177,$D$142) -> S | I78: =A78&" / "&B78&" / "&C78&" / "&D78 -> Wind power plants / Onshore / Electricity only / S | J78: =INDEX(J$906:J$1177,$D$142) -> 0.59770105 | K78: =INDEX(K$906:K$1177,$D$142) -> 0.5883619 | L78: =INDEX(L$906:L$1177,$D$142) -> 0.58253654 | M78: =INDEX(M$906:M$1177,$D$142) -> 0.57676885 | N78: =INDEX(N$906:N$1177,$D$142) -> 0.57105827 | O78: =INDEX(O$906:O$1177,$D$142) -> 0.56540422 | P78: =INDEX(P$906:P$1177,$D$142) -> 0.55627916 | Q78: =INDEX(Q$906:Q$1177,$D$142) -> 0.54761036 | ... AX78: =INDEX(AX$906:AX$1177,$D$142) -> 0.39491063
A79: =INDEX(F$906:F$1177,$D$143) -> Wind power plants | B79: =INDEX(G$906:G$1177,$D$143) -> Onshore | C79: =INDEX(H$906:H$1177,$D$143) -> Electricity only | D79: =INDEX(I$906:I$1177,$D$143) -> XS | I79: =A79&" / "&B79&" / "&C79&" / "&D79 -> Wind power plants / Onshore / Electricity only / XS | J79: =INDEX(J$906:J$1177,$D$143) -> 0.59805059 | K79: =INDEX(K$906:K$1177,$D$143) -> 0.59252024 | L79: =INDEX(L$906:L$1177,$D$143) -> 0.5878177 | M79: =INDEX(M$906:M$1177,$D$143) -> 0.58315248 | N79: =INDEX(N$906:N$1177,$D$143) -> 0.57852429 | O79: =INDEX(O$906:O$1177,$D$143) -> 0.57393282 | P79: =INDEX(P$906:P$1177,$D$143) -> 0.56949098 | Q79: =INDEX(Q$906:Q$1177,$D$143) -> 0.56385245 | ... AX79: =INDEX(AX$906:AX$1177,$D$143) -> 0.45216116
I80: min | J80: =MIN(J76:J79) -> 0.56975381 | K80: =MIN(K76:K79) -> 0.542068 | L80: =MIN(L76:L79) -> 0.52389918 | M80: =MIN(M76:M79) -> 0.51221923 | N80: =MIN(N76:N79) -> 0.50554467 | O80: =MIN(O76:O79) -> 0.50053927 | P80: =MIN(P76:P79) -> 0.49247797 | Q80: =MIN(Q76:Q79) -> 0.48718773 | ... AX80: =MIN(AX76:AX79) -> 0.34651092
I81: max | J81: =MAX(J76:J79) -> 0.59805059 | K81: =MAX(K76:K79) -> 0.59252024 | L81: =MAX(L76:L79) -> 0.5878177 | M81: =MAX(M76:M79) -> 0.58315248 | N81: =MAX(N76:N79) -> 0.57852429 | O81: =MAX(O76:O79) -> 0.57393282 | P81: =MAX(P76:P79) -> 0.56949098 | Q81: =MAX(Q76:Q79) -> 0.56385245 | ... AX81: =MAX(AX76:AX79) -> 0.45216116
I82: diff | J82: =J81-J80 -> 0.028296776 | K82: =K81-K80 -> 0.050452247 | L82: =L81-L80 -> 0.063918521 | M82: =M81-M80 -> 0.070933255 | N82: =N81-N80 -> 0.072979621 | O82: =O81-O80 -> 0.073393551 | P82: =P81-P80 -> 0.07701301 | Q82: =Q81-Q80 -> 0.076664718 | ... AX82: =AX81-AX80 -> 0.10565025
A83: ="RIGHT "&$J$1184 -> RIGHT CO2 emission related costs | J83: =J$1185 -> 2010 | K83: =K$1185 -> 2011 | L83: =L$1185 -> 2012 | M83: =M$1185 -> 2013 | N83: =N$1185 -> 2014 | O83: =O$1185 -> 2015 | P83: =P$1185 -> 2016 | Q83: =Q$1185 -> 2017 | ... AX83: =AX$1185 -> 2050
A84: =INDEX(F$1186:F$1457,$D$140) -> Wind power plants | B84: =INDEX(G$1186:G$1457,$D$140) -> Onshore | C84: =INDEX(H$1186:H$1457,$D$140) -> Electricity only | D84: =INDEX(I$1186:I$1457,$D$140) -> L | I84: =A84&" / "&B84&" / "&C84&" / "&D84 -> Wind power plants / Onshore / Electricity only / L | J84: =INDEX(J$1186:J$1457,$D$140) -> 0 | K84: =INDEX(K$1186:K$1457,$D$140) -> 0 | L84: =INDEX(L$1186:L$1457,$D$140) -> 0 | M84: =INDEX(M$1186:M$1457,$D$140) -> 0 | N84: =INDEX(N$1186:N$1457,$D$140) -> 0 | O84: =INDEX(O$1186:O$1457,$D$140) -> 0 | P84: =INDEX(P$1186:P$1457,$D$140) -> 0 | Q84: =INDEX(Q$1186:Q$1457,$D$140) -> 0 | ... AX84: =INDEX(AX$1186:AX$1457,$D$140) -> 0
A85: =INDEX(F$1186:F$1457,$D$141) -> Wind power plants | B85: =INDEX(G$1186:G$1457,$D$141) -> Onshore | C85: =INDEX(H$1186:H$1457,$D$141) -> Electricity only | D85: =INDEX(I$1186:I$1457,$D$141) -> M | I85: =A85&" / "&B85&" / "&C85&" / "&D85 -> Wind power plants / Onshore / Electricity only / M | J85: =INDEX(J$1186:J$1457,$D$141) -> 0 | K85: =INDEX(K$1186:K$1457,$D$141) -> 0 | L85: =INDEX(L$1186:L$1457,$D$141) -> 0 | M85: =INDEX(M$1186:M$1457,$D$141) -> 0 | N85: =INDEX(N$1186:N$1457,$D$141) -> 0 | O85: =INDEX(O$1186:O$1457,$D$141) -> 0 | P85: =INDEX(P$1186:P$1457,$D$141) -> 0 | Q85: =INDEX(Q$1186:Q$1457,$D$141) -> 0 | ... AX85: =INDEX(AX$1186:AX$1457,$D$141) -> 0
A86: =INDEX(F$1186:F$1457,$D$142) -> Wind power plants | B86: =INDEX(G$1186:G$1457,$D$142) -> Onshore | C86: =INDEX(H$1186:H$1457,$D$142) -> Electricity only | D86: =INDEX(I$1186:I$1457,$D$142) -> S | I86: =A86&" / "&B86&" / "&C86&" / "&D86 -> Wind power plants / Onshore / Electricity only / S | J86: =INDEX(J$1186:J$1457,$D$142) -> 0 | K86: =INDEX(K$1186:K$1457,$D$142) -> 0 | L86: =INDEX(L$1186:L$1457,$D$142) -> 0 | M86: =INDEX(M$1186:M$1457,$D$142) -> 0 | N86: =INDEX(N$1186:N$1457,$D$142) -> 0 | O86: =INDEX(O$1186:O$1457,$D$142) -> 0 | P86: =INDEX(P$1186:P$1457,$D$142) -> 0 | Q86: =INDEX(Q$1186:Q$1457,$D$142) -> 0 | ... AX86: =INDEX(AX$1186:AX$1457,$D$142) -> 0
A87: =INDEX(F$1186:F$1457,$D$143) -> Wind power plants | B87: =INDEX(G$1186:G$1457,$D$143) -> Onshore | C87: =INDEX(H$1186:H$1457,$D$143) -> Electricity only | D87: =INDEX(I$1186:I$1457,$D$143) -> XS | I87: =A87&" / "&B87&" / "&C87&" / "&D87 -> Wind power plants / Onshore / Electricity only / XS | J87: =INDEX(J$1186:J$1457,$D$143) -> 0 | K87: =INDEX(K$1186:K$1457,$D$143) -> 0 | L87: =INDEX(L$1186:L$1457,$D$143) -> 0 | M87: =INDEX(M$1186:M$1457,$D$143) -> 0 | N87: =INDEX(N$1186:N$1457,$D$143) -> 0 | O87: =INDEX(O$1186:O$1457,$D$143) -> 0 | P87: =INDEX(P$1186:P$1457,$D$143) -> 0 | Q87: =INDEX(Q$1186:Q$1457,$D$143) -> 0 | ... AX87: =INDEX(AX$1186:AX$1457,$D$143) -> 0
I88: min | J88: =MIN(J84:J87) -> 0 | K88: =MIN(K84:K87) -> 0 | L88: =MIN(L84:L87) -> 0 | M88: =MIN(M84:M87) -> 0 | N88: =MIN(N84:N87) -> 0 | O88: =MIN(O84:O87) -> 0 | P88: =MIN(P84:P87) -> 0 | Q88: =MIN(Q84:Q87) -> 0 | ... AX88: =MIN(AX84:AX87) -> 0
I89: max | J89: =MAX(J84:J87) -> 0 | K89: =MAX(K84:K87) -> 0 | L89: =MAX(L84:L87) -> 0 | M89: =MAX(M84:M87) -> 0 | N89: =MAX(N84:N87) -> 0 | O89: =MAX(O84:O87) -> 0 | P89: =MAX(P84:P87) -> 0 | Q89: =MAX(Q84:Q87) -> 0 | ... AX89: =MAX(AX84:AX87) -> 0
I90: diff | J90: =J89-J88 -> 0 | K90: =K89-K88 -> 0 | L90: =L89-L88 -> 0 | M90: =M89-M88 -> 0 | N90: =N89-N88 -> 0 | O90: =O89-O88 -> 0 | P90: =P89-P88 -> 0 | Q90: =Q89-Q88 -> 0 | ... AX90: =AX89-AX88 -> 0
A91: RIGHT Desired operating hours - maximum to minimum diff | J91: =SUM(J24)-SUM(J23) -> 1975 | K91: =SUM(K24)-SUM(K23) -> 1975 | L91: =SUM(L24)-SUM(L23) -> 1975 | M91: =SUM(M24)-SUM(M23) -> 1975 | N91: =SUM(N24)-SUM(N23) -> 1975 | O91: =SUM(O24)-SUM(O23) -> 1975 | P91: =SUM(P24)-SUM(P23) -> 1975 | Q91: =SUM(Q24)-SUM(Q23) -> 1975 | ... AX91: =SUM(AX24)-SUM(AX23) -> 1975
A92: Annual operating hours parameter set by user | J92: =$L$110 -> 4000 | K92: =$L$110 -> 4000 | L92: =$L$110 -> 4000 | M92: =$L$110 -> 4000 | N92: =$L$110 -> 4000 | O92: =$L$110 -> 4000 | P92: =$L$110 -> 4000 | Q92: =$L$110 -> 4000 | ... AX92: =$L$110 -> 4000
A93: ="COMBINED "&$J$344 -> COMBINED Levelized costs (€2010 / MWh net) | I93: min | J93: =IF(J31=0,J64,IF(J64=0,J31,MIN(J31,J64))) -> 36.793908 | K93: =IF(K31=0,K64,IF(K64=0,K31,MIN(K31,K64))) -> 35.005996 | L93: =IF(L31=0,L64,IF(L64=0,L31,MIN(L31,L64))) -> 33.832679 | M93: =IF(M31=0,M64,IF(M64=0,M31,MIN(M31,M64))) -> 33.078404 | N93: =IF(N31=0,N64,IF(N64=0,N31,MIN(N31,N64))) -> 32.64737 | O93: =IF(O31=0,O64,IF(O64=0,O31,MIN(O31,O64))) -> 32.324129 | P93: =IF(P31=0,P64,IF(P64=0,P31,MIN(P31,P64))) -> 31.803541 | Q93: =IF(Q31=0,Q64,IF(Q64=0,Q31,MIN(Q31,Q64))) -> 31.461905 | ... AX93: =IF(AX31=0,AX64,IF(AX64=0,AX31,MIN(AX31,AX64))) -> 22.377192
I94: single | J94: =IF(J31=0,J65,IF(J64=0,J32,MIN(MAX(J31,J64),MIN(J32,J65)))) -> 36.793908 | K94: =IF(K31=0,K65,IF(K64=0,K32,MIN(MAX(K31,K64),MIN(K32,K65)))) -> 35.005996 | L94: =IF(L31=0,L65,IF(L64=0,L32,MIN(MAX(L31,L64),MIN(L32,L65)))) -> 33.832679 | M94: =IF(M31=0,M65,IF(M64=0,M32,MIN(MAX(M31,M64),MIN(M32,M65)))) -> 33.078404 | N94: =IF(N31=0,N65,IF(N64=0,N32,MIN(MAX(N31,N64),MIN(N32,N65)))) -> 32.64737 | O94: =IF(O31=0,O65,IF(O64=0,O32,MIN(MAX(O31,O64),MIN(O32,O65)))) -> 32.324129 | P94: =IF(P31=0,P65,IF(P64=0,P32,MIN(MAX(P31,P64),MIN(P32,P65)))) -> 31.803541 | Q94: =IF(Q31=0,Q65,IF(Q64=0,Q32,MIN(MAX(Q31,Q64),MIN(Q32,Q65)))) -> 31.461905 | ... AX94: =IF(AX31=0,AX65,IF(AX64=0,AX32,MIN(MAX(AX31,AX64),MIN(AX32,AX65)))) -> 22.377192
I95: white | J95: =IF(MAX(J31,J64)>J94,MAX(J31,J64),J94) -> 36.793908 | K95: =IF(MAX(K31,K64)>K94,MAX(K31,K64),K94) -> 35.005996 | L95: =IF(MAX(L31,L64)>L94,MAX(L31,L64),L94) -> 33.832679 | M95: =IF(MAX(M31,M64)>M94,MAX(M31,M64),M94) -> 33.078404 | N95: =IF(MAX(N31,N64)>N94,MAX(N31,N64),N94) -> 32.64737 | O95: =IF(MAX(O31,O64)>O94,MAX(O31,O64),O94) -> 32.324129 | P95: =IF(MAX(P31,P64)>P94,MAX(P31,P64),P94) -> 31.803541 | Q95: =IF(MAX(Q31,Q64)>Q94,MAX(Q31,Q64),Q94) -> 31.461905 | ... AX95: =IF(MAX(AX31,AX64)>AX94,MAX(AX31,AX64),AX94) -> 22.377192
I96: common | J96: =MAX(J95,MIN(J32,J65)) -> 51.610007 | K96: =MAX(K95,MIN(K32,K65)) -> 51.132755 | L96: =MAX(L95,MIN(L32,L65)) -> 50.726939 | M96: =MAX(M95,MIN(M32,M65)) -> 50.324344 | N96: =MAX(N95,MIN(N32,N65)) -> 49.924945 | O96: =MAX(O95,MIN(O32,O65)) -> 49.528715 | P96: =MAX(P95,MIN(P32,P65)) -> 49.145397 | Q96: =MAX(Q95,MIN(Q32,Q65)) -> 48.658809 | ... AX96: =MAX(AX95,MIN(AX32,AX65)) -> 39.020179
I97: single | J97: =MAX(J32,J65) -> 51.610007 | K97: =MAX(K32,K65) -> 51.132755 | L97: =MAX(L32,L65) -> 50.726939 | M97: =MAX(M32,M65) -> 50.324344 | N97: =MAX(N32,N65) -> 49.924945 | O97: =MAX(O32,O65) -> 49.528715 | P97: =MAX(P32,P65) -> 49.145397 | Q97: =MAX(Q32,Q65) -> 48.658809 | ... AX97: =MAX(AX32,AX65) -> 39.020179
I98: min | J98: =J93 -> 36.793908 | K98: =K93 -> 35.005996 | L98: =L93 -> 33.832679 | M98: =M93 -> 33.078404 | N98: =N93 -> 32.64737 | O98: =O93 -> 32.324129 | P98: =P93 -> 31.803541 | Q98: =Q93 -> 31.461905 | ... AX98: =AX93 -> 22.377192
I99: single | J99: =J94-J93 -> 0 | K99: =K94-K93 -> 0 | L99: =L94-L93 -> 0 | M99: =M94-M93 -> 0 | N99: =N94-N93 -> 0 | O99: =O94-O93 -> 0 | P99: =P94-P93 -> 0 | Q99: =Q94-Q93 -> 0 | ... AX99: =AX94-AX93 -> 0
I100: white | J100: =J95-J94 -> 0 | K100: =K95-K94 -> 0 | L100: =L95-L94 -> 0 | M100: =M95-M94 -> 0 | N100: =N95-N94 -> 0 | O100: =O95-O94 -> 0 | P100: =P95-P94 -> 0 | Q100: =Q95-Q94 -> 0 | ... AX100: =AX95-AX94 -> 0
I101: common | J101: =J96-J95 -> 14.816099 | K101: =K96-K95 -> 16.126758 | L101: =L96-L95 -> 16.89426 | M101: =M96-M95 -> 17.24594 | N101: =N96-N95 -> 17.277574 | O101: =O96-O95 -> 17.204586 | P101: =P96-P95 -> 17.341855 | Q101: =Q96-Q95 -> 17.196903 | ... AX101: =AX96-AX95 -> 16.642986
I102: single | J102: =J97-J96 -> 0 | K102: =K97-K96 -> 0 | L102: =L97-L96 -> 0 | M102: =M97-M96 -> 0 | N102: =N97-N96 -> 0 | O102: =O97-O96 -> 0 | P102: =P97-P96 -> 0 | Q102: =Q97-Q96 -> 0 | ... AX102: =AX97-AX96 -> 0
A103: Diff (Left-Right) | J103: =J$625 -> 2010 | K103: =K$625 -> 2011 | L103: =L$625 -> 2012 | M103: =M$625 -> 2013 | N103: =N$625 -> 2014 | O103: =O$625 -> 2015 | P103: =P$625 -> 2016 | Q103: =Q$625 -> 2017 | ... AX103: =AX$625 -> 2050
A104: ="Difference in "&A11 -> Difference in Levelized costs (€2010 / MWh net) | H104: =A104&CHAR(13)&I104 -> Difference in Levelized costs (€2010 / MWh net)_x000D_Wind power plants / Onshore / Electricity only / M | I104: =INDEX(F$346:F$617,$D$139)&" / "&INDEX(G$346:G$617,$D$139)&" / "&INDEX(H$346:H$617,$D$139)&" / "&INDEX(I$346:I$617,$D$139) -> Wind power plants / Onshore / Electricity only / M | J104: =J11-J19 -> -3.155913 | K104: =K11-K19 -> -3.9616641 | L104: =L11-L19 -> -4.4474606 | M104: =M11-M19 -> -4.7006527 | N104: =N11-N19 -> -4.6167538 | O104: =O11-O19 -> -4.2057447 | P104: =P11-P19 -> -4.0526284 | Q104: =Q11-Q19 -> -3.9619707 | ... AX104: =AX11-AX19 -> -3.2340916
A105: ="Difference in "&A12&" (€2010 / MWh net)" -> Difference in Fixed annual levelized costs (€2010 / MWh net) | H105: =A105&CHAR(13)&I105 -> Difference in Fixed annual levelized costs (€2010 / MWh net)_x000D_Wind power plants / Onshore / Electricity only / M | I105: =INDEX(F$346:F$617,$D$139)&" / "&INDEX(G$346:G$617,$D$139)&" / "&INDEX(H$346:H$617,$D$139)&" / "&INDEX(I$346:I$617,$D$139) -> Wind power plants / Onshore / Electricity only / M | J105: =J12-J20 -> -3.1304824 | K105: =K12-K20 -> -3.9231802 | L105: =L12-L20 -> -4.4010508 | M105: =M12-M20 -> -4.6500282 | N105: =N12-N20 -> -4.5671264 | O105: =O12-O20 -> -4.1620509 | P105: =P12-P20 -> -4.0109104 | Q105: =Q12-Q20 -> -3.9214029 | ... AX105: =AX12-AX20 -> -3.1990379
A106: ="Difference in "&A13&" (€2010 / MWh net)" -> Difference in Fuel and variable costs (€2010 / MWh net) | H106: =A106&CHAR(13)&I106 -> Difference in Fuel and variable costs (€2010 / MWh net)_x000D_Wind power plants / Onshore / Electricity only / M | I106: =INDEX(F$346:F$617,$D$139)&" / "&INDEX(G$346:G$617,$D$139)&" / "&INDEX(H$346:H$617,$D$139)&" / "&INDEX(I$346:I$617,$D$139) -> Wind power plants / Onshore / Electricity only / M | J106: =J13-J21 -> -0.025430607 | K106: =K13-K21 -> -0.038483903 | L106: =L13-L21 -> -0.046409835 | M106: =M13-M21 -> -0.050624503 | N106: =N13-N21 -> -0.049627442 | O106: =O13-O21 -> -0.043693751 | P106: =P13-P21 -> -0.04171801 | Q106: =Q13-Q21 -> -0.040567804 | ... AX106: =AX13-AX21 -> -0.035053678
...

Sheet visuD
A1: Nuclear power plants | D1: Nuclear - current | E1: Nuclear III | F1: Nuclear IV | H1: 0
A2: Coal fired power plants | D2: Integrated gasification combined cycle | E2: Supercritical steam turbine | F2: Fluidized bed combustion | G2: Steam turbine | H2: =COUNTA($D$1:$G1) -> 3
A3: Lignite fired power plants | D3: Integrated gasification combined cycle | E3: Supercritical steam turbine | F3: Fluidized bed combustion | G3: Steam turbine | H3: =COUNTA($D$1:$G2) -> 7
A4: Gas fired power plants (Natural gas, biogas) | D4: Gas turbine combined cycle | E4: Gas turbine | F4: Steam turbine | G4: Internal combustion engine | H4: =COUNTA($D$1:$G3) -> 11
A5: Derived gas fired power plants | D5: Steam turbine | H5: =COUNTA($D$1:$G4) -> 15
A6: Refinery gas fired power plants | D6: Steam turbine | H6: =COUNTA($D$1:$G5) -> 16
A7: Diesel oil fired power plants | D7: Gas turbine combined cycle | E7: Gas turbine | F7: Steam turbine | G7: Internal combustion engine | H7: =COUNTA($D$1:$G6) -> 17
A8: Fuel oil fired power plants | D8: Integrated gasification combined cycle | E8: Supercritical steam turbine | F8: Steam turbine | H8: =COUNTA($D$1:$G7) -> 21
A9: Biomass and waste fired power plants | D9: Integrated gasification combined cycle | E9: Fluidized bed combustion | F9: Steam turbine | H9: =COUNTA($D$1:$G8) -> 24
A10: Fuel cells | D10: Natural gas fuel cell power plant | E10: Hydrogen fuel cell power plant | H10: =COUNTA($D$1:$G9) -> 27
A11: Wind power plants | D11: Onshore | E11: Offshore | H11: =COUNTA($D$1:$G10) -> 29
A12: Solar PV power plants | D12: Solar PV power plants | H12: =COUNTA($D$1:$G11) -> 31
A13: Solar thermal power plants | D13: Solar thermal power plants | H13: =COUNTA($D$1:$G12) -> 32
A14: Geothermal power plants | D14: Geothermal power plants | H14: =COUNTA($D$1:$G13) -> 33
A15: Tide, wave and ocean power plants | D15: Tidal | E15: Wave | H15: =COUNTA($D$1:$G14) -> 34
A16: Hydro plants | D16: Run-of-river | E16: Reservoirs (dams) | H16: =COUNTA($D$1:$G15) -> 36
A17: Pump storage | D17: Pump storage | H17: =COUNTA($D$1:$G16) -> 38
A18: Nuclear power plants | B18: Nuclear - current | D18: Electricity only | H18: 0
A19: Nuclear power plants | B19: Nuclear III | D19: Electricity only | H19: =COUNTA($D$18:$G18) -> 1
A20: Nuclear power plants | B20: Nuclear IV | D20: Electricity only | H20: =COUNTA($D$18:$G19) -> 2
A21: Coal fired power plants | B21: Integrated gasification combined cycle | D21: Electricity only | E21: CHP | F21: Electricity only with CCS | G21: CHP with CCS | H21: =COUNTA($D$18:$G20) -> 3
A22: Coal fired power plants | B22: Supercritical steam turbine | D22: Electricity only | E22: CHP | F22: Electricity only with CCS | G22: CHP with CCS | H22: =COUNTA($D$18:$G21) -> 7
A23: Coal fired power plants | B23: Fluidized bed combustion | D23: Electricity only | E23: CHP | F23: Electricity only with CCS | G23: CHP with CCS | H23: =COUNTA($D$18:$G22) -> 11
A24: Coal fired power plants | B24: Steam turbine | D24: Electricity only | E24: CHP | F24: Electricity only with CCS | G24: CHP with CCS | H24: =COUNTA($D$18:$G23) -> 15
A25: Lignite fired power plants | B25: Integrated gasification combined cycle | D25: Electricity only | E25: CHP | F25: Electricity only with CCS | G25: CHP with CCS | H25: =COUNTA($D$18:$G24) -> 19
A26: Lignite fired power plants | B26: Supercritical steam turbine | D26: Electricity only | E26: CHP | F26: Electricity only with CCS | G26: CHP with CCS | H26: =COUNTA($D$18:$G25) -> 23
A27: Lignite fired power plants | B27: Fluidized bed combustion | D27: Electricity only | E27: CHP | F27: Electricity only with CCS | G27: CHP with CCS | H27: =COUNTA($D$18:$G26) -> 27
A28: Lignite fired power plants | B28: Steam turbine | D28: Electricity only | E28: CHP | F28: Electricity only with CCS | G28: CHP with CCS | H28: =COUNTA($D$18:$G27) -> 31
A29: Gas fired power plants (Natural gas, biogas) | B29: Gas turbine combined cycle | D29: Electricity only | E29: CHP | F29: Electricity only with CCS | G29: CHP with CCS | H29: =COUNTA($D$18:$G28) -> 35
A30: Gas fired power plants (Natural gas, biogas) | B30: Gas turbine | D30: Electricity only | E30: CHP | H30: =COUNTA($D$18:$G29) -> 39
A31: Gas fired power plants (Natural gas, biogas) | B31: Steam turbine | D31: Electricity only | E31: CHP | F31: Electricity only with CCS | G31: CHP with CCS | H31: =COUNTA($D$18:$G30) -> 41
A32: Gas fired power plants (Natural gas, biogas) | B32: Internal combustion engine | D32: Electricity only | E32: CHP | H32: =COUNTA($D$18:$G31) -> 45
A33: Derived gas fired power plants | B33: Steam turbine | D33: Electricity only | E33: CHP | F33: Electricity only with CCS | G33: CHP with CCS | H33: =COUNTA($D$18:$G32) -> 47
A34: Refinery gas fired power plants | B34: Steam turbine | D34: Electricity only | E34: CHP | F34: Electricity only with CCS | G34: CHP with CCS | H34: =COUNTA($D$18:$G33) -> 51
A35: Diesel oil fired power plants | B35: Gas turbine combined cycle | D35: Electricity only | E35: CHP | F35: Electricity only with CCS | G35: CHP with CCS | H35: =COUNTA($D$18:$G34) -> 55
A36: Diesel oil fired power plants | B36: Gas turbine | D36: Electricity only | E36: CHP | F36: Electricity only with CCS | G36: CHP with CCS | H36: =COUNTA($D$18:$G35) -> 59
A37: Diesel oil fired power plants | B37: Steam turbine | D37: Electricity only | E37: CHP | F37: Electricity only with CCS | G37: CHP with CCS | H37: =COUNTA($D$18:$G36) -> 63
A38: Diesel oil fired power plants | B38: Internal combustion engine | D38: Electricity only | E38: CHP | H38: =COUNTA($D$18:$G37) -> 67
A39: Fuel oil fired power plants | B39: Integrated gasification combined cycle | D39: Electricity only | E39: CHP | F39: Electricity only with CCS | G39: CHP with CCS | H39: =COUNTA($D$18:$G38) -> 69
A40: Fuel oil fired power plants | B40: Supercritical steam turbine | D40: Electricity only | E40: CHP | F40: Electricity only with CCS | G40: CHP with CCS | H40: =COUNTA($D$18:$G39) -> 73
A41: Fuel oil fired power plants | B41: Steam turbine | D41: Electricity only | E41: CHP | F41: Electricity only with CCS | G41: CHP with CCS | H41: =COUNTA($D$18:$G40) -> 77
A42: Biomass and waste fired power plants | B42: Integrated gasification combined cycle | D42: Electricity only | E42: CHP | F42: Electricity only with CCS | G42: CHP with CCS | H42: =COUNTA($D$18:$G41) -> 81
A43: Biomass and waste fired power plants | B43: Fluidized bed combustion | D43: Electricity only | E43: CHP | F43: Electricity only with CCS | G43: CHP with CCS | H43: =COUNTA($D$18:$G42) -> 85
A44: Biomass and waste fired power plants | B44: Steam turbine | D44: Electricity only | E44: CHP | F44: Electricity only with CCS | G44: CHP with CCS | H44: =COUNTA($D$18:$G43) -> 89
A45: Fuel cells | B45: Natural gas fuel cell power plant | D45: Electricity only | H45: =COUNTA($D$18:$G44) -> 93
A46: Fuel cells | B46: Hydrogen fuel cell power plant | D46: Electricity only | H46: =COUNTA($D$18:$G45) -> 94
A47: Wind power plants | B47: Onshore | D47: Electricity only | H47: =COUNTA($D$18:$G46) -> 95
A48: Wind power plants | B48: Offshore | D48: Electricity only | H48: =COUNTA($D$18:$G47) -> 96
A49: Solar PV power plants | B49: Solar PV power plants | D49: Electricity only | H49: =COUNTA($D$18:$G48) -> 97
A50: Solar thermal power plants | B50: Solar thermal power plants | D50: Electricity only | H50: =COUNTA($D$18:$G49) -> 98
A51: Geothermal power plants | B51: Geothermal power plants | D51: Electricity only | H51: =COUNTA($D$18:$G50) -> 99
A52: Tide, wave and ocean power plants | B52: Tidal | D52: Electricity only | H52: =COUNTA($D$18:$G51) -> 100
A53: Tide, wave and ocean power plants | B53: Wave | D53: Electricity only | H53: =COUNTA($D$18:$G52) -> 101
A54: Hydro plants | B54: Run-of-river | D54: Electricity only | H54: =COUNTA($D$18:$G53) -> 102
A55: Hydro plants | B55: Reservoirs (dams) | D55: Electricity only | H55: =COUNTA($D$18:$G54) -> 103
A56: Pump storage | B56: Pump storage | D56: Electricity only | H56: =COUNTA($D$18:$G55) -> 104
A57: Nuclear power plants | B57: Nuclear - current | C57: Electricity only | D57: L | E57: M | H57: 0
A58: Nuclear power plants | B58: Nuclear III | C58: Electricity only | D58: L | E58: M | F58: S | H58: =COUNTA($D$57:$G57) -> 2
A59: Nuclear power plants | B59: Nuclear IV | C59: Electricity only | D59: L | E59: M | H59: =COUNTA($D$57:$G58) -> 5
A60: Coal fired power plants | B60: Integrated gasification combined cycle | C60: Electricity only | D60: L | E60: M | H60: =COUNTA($D$57:$G59) -> 7
A61: Coal fired power plants | B61: Integrated gasification combined cycle | C61: CHP | D61: L | E61: M | H61: =COUNTA($D$57:$G60) -> 9
A62: Coal fired power plants | B62: Integrated gasification combined cycle | C62: Electricity only with CCS | D62: L | E62: M | H62: =COUNTA($D$57:$G61) -> 11
A63: Coal fired power plants | B63: Integrated gasification combined cycle | C63: CHP with CCS | D63: L | E63: M | H63: =COUNTA($D$57:$G62) -> 13
A64: Coal fired power plants | B64: Supercritical steam turbine | C64: Electricity only | D64: L | E64: M | H64: =COUNTA($D$57:$G63) -> 15
A65: Coal fired power plants | B65: Supercritical steam turbine | C65: CHP | D65: L | E65: M | H65: =COUNTA($D$57:$G64) -> 17
A66: Coal fired power plants | B66: Supercritical steam turbine | C66: Electricity only with CCS | D66: L | E66: M | H66: =COUNTA($D$57:$G65) -> 19
A67: Coal fired power plants | B67: Supercritical steam turbine | C67: CHP with CCS | D67: L | E67: M | H67: =COUNTA($D$57:$G66) -> 21
A68: Coal fired power plants | B68: Fluidized bed combustion | C68: Electricity only | D68: L | E68: M | F68: S | H68: =COUNTA($D$57:$G67) -> 23
A69: Coal fired power plants | B69: Fluidized bed combustion | C69: CHP | D69: L | E69: M | F69: S | H69: =COUNTA($D$57:$G68) -> 26
A70: Coal fired power plants | B70: Fluidized bed combustion | C70: Electricity only with CCS | D70: L | E70: M | H70: =COUNTA($D$57:$G69) -> 29
A71: Coal fired power plants | B71: Fluidized bed combustion | C71: CHP with CCS | D71: L | E71: M | H71: =COUNTA($D$57:$G70) -> 31
A72: Coal fired power plants | B72: Steam turbine | C72: Electricity only | D72: L | E72: M | F72: S | G72: XS | H72: =COUNTA($D$57:$G71) -> 33
A73: Coal fired power plants | B73: Steam turbine | C73: CHP | D73: L | E73: M | F73: S | G73: XS | H73: =COUNTA($D$57:$G72) -> 37
A74: Coal fired power plants | B74: Steam turbine | C74: Electricity only with CCS | D74: L | E74: M | H74: =COUNTA($D$57:$G73) -> 41
A75: Coal fired power plants | B75: Steam turbine | C75: CHP with CCS | D75: L | E75: M | H75: =COUNTA($D$57:$G74) -> 43
A76: Lignite fired power plants | B76: Integrated gasification combined cycle | C76: Electricity only | D76: L | E76: M | H76: =COUNTA($D$57:$G75) -> 45
A77: Lignite fired power plants | B77: Integrated gasification combined cycle | C77: CHP | D77: L | E77: M | H77: =COUNTA($D$57:$G76) -> 47
A78: Lignite fired power plants | B78: Integrated gasification combined cycle | C78: Electricity only with CCS | D78: L | E78: M | H78: =COUNTA($D$57:$G77) -> 49
A79: Lignite fired power plants | B79: Integrated gasification combined cycle | C79: CHP with CCS | D79: L | E79: M | H79: =COUNTA($D$57:$G78) -> 51
A80: Lignite fired power plants | B80: Supercritical steam turbine | C80: Electricity only | D80: L | E80: M | H80: =COUNTA($D$57:$G79) -> 53
A81: Lignite fired power plants | B81: Supercritical steam turbine | C81: CHP | D81: L | E81: M | H81: =COUNTA($D$57:$G80) -> 55
A82: Lignite fired power plants | B82: Supercritical steam turbine | C82: Electricity only with CCS | D82: L | E82: M | H82: =COUNTA($D$57:$G81) -> 57
A83: Lignite fired power plants | B83: Supercritical steam turbine | C83: CHP with CCS | D83: L | E83: M | H83: =COUNTA($D$57:$G82) -> 59
A84: Lignite fired power plants | B84: Fluidized bed combustion | C84: Electricity only | D84: L | E84: M | F84: S | H84: =COUNTA($D$57:$G83) -> 61
A85: Lignite fired power plants | B85: Fluidized bed combustion | C85: CHP | D85: L | E85: M | F85: S | H85: =COUNTA($D$57:$G84) -> 64
A86: Lignite fired power plants | B86: Fluidized bed combustion | C86: Electricity only with CCS | D86: L | E86: M | H86: =COUNTA($D$57:$G85) -> 67
A87: Lignite fired power plants | B87: Fluidized bed combustion | C87: CHP with CCS | D87: L | E87: M | H87: =COUNTA($D$57:$G86) -> 69
A88: Lignite fired power plants | B88: Steam turbine | C88: Electricity only | D88: L | E88: M | F88: S | G88: XS | H88: =COUNTA($D$57:$G87) -> 71
A89: Lignite fired power plants | B89: Steam turbine | C89: CHP | D89: L | E89: M | F89: S | G89: XS | H89: =COUNTA($D$57:$G88) -> 75
A90: Lignite fired power plants | B90: Steam turbine | C90: Electricity only with CCS | D90: L | E90: M | H90: =COUNTA($D$57:$G89) -> 79
A91: Lignite fired power plants | B91: Steam turbine | C91: CHP with CCS | D91: L | E91: M | H91: =COUNTA($D$57:$G90) -> 81
A92: Gas fired power plants (Natural gas, biogas) | B92: Gas turbine combined cycle | C92: Electricity only | D92: L | E92: M | F92: S | G92: XS | H92: =COUNTA($D$57:$G91) -> 83
A93: Gas fired power plants (Natural gas, biogas) | B93: Gas turbine combined cycle | C93: CHP | D93: L | E93: M | F93: S | G93: XS | H93: =COUNTA($D$57:$G92) -> 87
A94: Gas fired power plants (Natural gas, biogas) | B94: Gas turbine combined cycle | C94: Electricity only with CCS | D94: L | E94: M | H94: =COUNTA($D$57:$G93) -> 91
A95: Gas fired power plants (Natural gas, biogas) | B95: Gas turbine combined cycle | C95: CHP with CCS | D95: L | E95: M | H95: =COUNTA($D$57:$G94) -> 93
A96: Gas fired power plants (Natural gas, biogas) | B96: Gas turbine | C96: Electricity only | D96: M | E96: S | F96: XS | H96: =COUNTA($D$57:$G95) -> 95
A97: Gas fired power plants (Natural gas, biogas) | B97: Gas turbine | C97: CHP | D97: M | E97: S | F97: XS | H97: =COUNTA($D$57:$G96) -> 98
A98: Gas fired power plants (Natural gas, biogas) | B98: Steam turbine | C98: Electricity only | D98: L | E98: M | F98: S | G98: XS | H98: =COUNTA($D$57:$G97) -> 101
A99: Gas fired power plants (Natural gas, biogas) | B99: Steam turbine | C99: CHP | D99: L | E99: M | F99: S | G99: XS | H99: =COUNTA($D$57:$G98) -> 105
A100: Gas fired power plants (Natural gas, biogas) | B100: Steam turbine | C100: Electricity only with CCS | D100: L | E100: M | H100: =COUNTA($D$57:$G99) -> 109
...

Sheet fuel_costs
A1: International fuel prices (€2010/toe) | B1: 2010 | C1: 2011 | D1: 2012 | E1: 2013 | F1: 2014 | G1: 2015 | H1: 2016 | I1: 2017 | J1: 2018 | K1: 2019 | L1: 2020 | M1: 2021 | N1: 2022 | O1: 2023 | P1: 2024 | Q1: 2025 | R1: 2026 | S1: 2027 | T1: 2028 | U1: 2029 | V1: 2030 | W1: 2031 | X1: 2032 | Y1: 2033 | Z1: 2034 | AA1: 2035 | AB1: 2036 | AC1: 2037 | AD1: 2038 | AE1: 2039 | AF1: 2040 | AG1: 2041 | AH1: 2042 | AI1: 2043 | AJ1: 2044 | AK1: 2045 | AL1: 2046 | AM1: 2047 | AN1: 2048 | AO1: 2049 | AP1: 2050
A2: Oil | B2: 432.50851 | C2: 567.1238 | D2: 605.4629 | E2: 566.28321 | F2: 506.11756 | G2: 311.44361 | H2: 265.7999 | I2: 320.51602 | J2: 369.33151 | K2: 412.10059 | L2: 453.31233 | M2: 492.52733 | N2: 518.74267 | O2: 550.88551 | P2: 578.73655 | Q2: 602.32467 | R2: 617.36741 | S2: 630.96818 | T2: 640.21955 | U2: 654.73369 | V2: 663.52902 | W2: 671.90603 | X2: 676.02741 | Y2: 680.77053 | Z2: 686.1332 | AA2: 692.17466 | AB2: 699.00274 | AC2: 706.7833 | AD2: 715.22499 | AE2: 723.9703 | AF2: 732.90112 | AG2: 733.51203 | AH2: 736.35113 | AI2: 739.38719 | AJ2: 746.25674 | AK2: 749.71954 | AL2: 753.16586 | AM2: 756.53218 | AN2: 759.77573 | AO2: 762.86432 | AP2: 767.04886
A3: Gas | B3: 275.63555 | C3: 329.17264 | D3: 379.94187 | E3: 375.46077 | F3: 314.88575 | G3: 264.4282 | H3: 168.44346 | I3: 203.73387 | J3: 228.33522 | K3: 253.14166 | L3: 277.65791 | M3: 301.55885 | N3: 317.10316 | O3: 335.5205 | P3: 352.91296 | Q3: 369.30195 | R3: 375.14844 | S3: 380.6194 | T3: 386.69014 | U3: 392.76787 | V3: 401.61579 | W3: 407.21959 | X3: 413.61904 | Y3: 419.34825 | Z3: 424.54489 | AA3: 428.93039 | AB3: 433.06392 | AC3: 436.43287 | AD3: 439.70671 | AE3: 443.34124 | AF3: 443.39448 | AG3: 444.56158 | AH3: 445.79514 | AI3: 447.30048 | AJ3: 449.58432 | AK3: 452.48351 | AL3: 455.22104 | AM3: 457.68103 | AN3: 459.63886 | AO3: 459.48251 | AP3: 459.46104
A4: Coal | B4: 116.29076 | C4: 143.79839 | D4: 115.78734 | E4: 98.370521 | F4: 89.261228 | G4: 77.971583 | H4: 83.936722 | I4: 115.27499 | J4: 115.84599 | K4: 116.40825 | L4: 116.96196 | M4: 120.08622 | N4: 119.91243 | O4: 119.53029 | P4: 120.14593 | Q4: 120.91936 | R4: 125.55243 | S4: 130.175 | T4: 134.96445 | U4: 139.79767 | V4: 145.11887 | W4: 146.4175 | X4: 148.29051 | Y4: 150.25848 | Z4: 152.06373 | AA4: 153.66455 | AB4: 154.68942 | AC4: 155.96158 | AD4: 157.41339 | AE4: 159.01415 | AF4: 160.16709 | AG4: 161.28264 | AH4: 162.37244 | AI4: 163.45782 | AJ4: 164.68967 | AK4: 165.9583 | AL4: 166.64222 | AM4: 167.80852 | AN4: 168.70817 | AO4: 169.46613 | AP4: 170.58266
A5: IF_BMS | B5: 253.77538 | C5: 253.77538 | D5: 253.77538 | E5: 253.77538 | F5: 253.77538 | G5: 253.77538 | H5: 255.64675 | I5: 256.32259 | J5: 257.14598 | K5: 258.69015 | L5: 261.36185 | M5: 264.14445 | N5: 267.19611 | O5: 270.3905 | P5: 273.50446 | Q5: 276.72642 | R5: 279.91904 | S5: 283.43597 | T5: 288.10739 | U5: 295.22967 | V5: 302.22263 | W5: 306.99275 | X5: 309.82579 | Y5: 312.25903 | Z5: 314.42512 | AA5: 316.75935 | AB5: 319.14995 | AC5: 321.3186 | AD5: 323.20559 | AE5: 324.39299 | AF5: 325.36252 | AG5: 326.37754 | AH5: 327.51545 | AI5: 328.72449 | AJ5: 329.46617 | AK5: 330.56908 | AL5: 331.40141 | AM5: 333.05902 | AN5: 334.84565 | AO5: 336.67709 | AP5: 338.37174
A7: End-user prices (€2010/toe) | B7: 2010 | C7: 2011 | D7: 2012 | E7: 2013 | F7: 2014 | G7: 2015 | H7: 2016 | I7: 2017 | J7: 2018 | K7: 2019 | L7: 2020 | M7: 2021 | N7: 2022 | O7: 2023 | P7: 2024 | Q7: 2025 | R7: 2026 | S7: 2027 | T7: 2028 | U7: 2029 | V7: 2030 | W7: 2031 | X7: 2032 | Y7: 2033 | Z7: 2034 | AA7: 2035 | AB7: 2036 | AC7: 2037 | AD7: 2038 | AE7: 2039 | AF7: 2040 | AG7: 2041 | AH7: 2042 | AI7: 2043 | AJ7: 2044 | AK7: 2045 | AL7: 2046 | AM7: 2047 | AN7: 2048 | AO7: 2049 | AP7: 2050
A8: Nuclear power plants | B8: 33.45 | C8: 33.45 | D8: 33.45 | E8: 33.45 | F8: 33.45 | G8: 33.45 | H8: 33.45 | I8: 33.45 | J8: 33.45 | K8: 33.45 | L8: 33.45 | M8: 33.45 | N8: 33.45 | O8: 33.45 | P8: 33.45 | Q8: 33.45 | R8: 33.45 | S8: 33.45 | T8: 33.45 | U8: 33.45 | V8: 33.45 | W8: 33.45 | X8: 33.45 | Y8: 33.45 | Z8: 33.45 | AA8: 33.45 | AB8: 33.45 | AC8: 33.45 | AD8: 33.45 | AE8: 33.45 | AF8: 33.45 | AG8: 33.45 | AH8: 33.45 | AI8: 33.45 | AJ8: 33.45 | AK8: 33.45 | AL8: 33.45 | AM8: 33.45 | AN8: 33.45 | AO8: 33.45 | AP8: 33.45
A9: Coal fired power plants | B9: =(B$4+7.54355073276415)*1.05+3.99416685537934 -> 134.0202 | C9: =(C$4+11.6381182796937)*1.0504+4.08130700537217 -> 167.35181 | D9: =(D$4+15.7326858266233)*1.0508+4.16844715536501 -> 142.36969 | E9: =(E$4+19.8272533735528)*1.0512+4.25558730535784 -> 128.50509 | F9: =(F$4+23.9218209204824)*1.0516+4.34272745535067 -> 123.36602 | G9: =(G$4+28.0163884674119)*1.052+4.42986760534351 -> 115.92921 | H9: =(H$4+28.2405195751512)*1.0524+4.42986760534351 -> 122.4852 | I9: =(I$4+28.4646506828905)*1.0528+4.42986760534351 -> 155.75896 | J9: =(J$4+28.6887817906298)*1.0532+4.42986760534351 -> 156.65389 | K9: =(K$4+28.9129128983691)*1.0536+4.42986760534351 -> 157.54024 | L9: =(L$4+29.1370440061084)*1.054+4.42986760534351 -> 158.41822 | M9: =(M$4+29.3701403581573)*1.0544+4.42986760534351 -> 162.01666 | N9: =(N$4+29.6032367102061)*1.0548+4.42986760534351 -> 162.13899 | O9: =(O$4+29.836333062255)*1.0552+4.42986760534351 -> 162.04153 | P9: =(P$4+30.0694294143039)*1.0556+4.42986760534351 -> 162.9972 | Q9: =(Q$4+30.3025257663527)*1.056+4.42986760534351 -> 164.12018 | R9: =(R$4+30.5449459724836)*1.0564+4.42986760534351 -> 169.33114 | S9: =(S$4+30.7873661786144)*1.0568+4.42986760534351 -> 174.53489 | T9: =(T$4+31.0297863847452)*1.0572+4.42986760534351 -> 179.91898 | U9: =(U$4+31.272206590876)*1.0576+4.42986760534351 -> 185.35337 | V9: =(V$4+31.5146267970068)*1.058+4.42986760534351 -> 191.3081 | W9: =(W$4+31.7667438113829)*1.0584+4.42986760534351 -> 193.02008 | X9: =(X$4+32.0188608257589)*1.0588+4.42986760534351 -> 195.34143 | Y9: =(Y$4+32.270977840135)*1.0592+4.42986760534351 -> 197.76506 | Z9: =(Z$4+32.5230948545111)*1.0596+4.42986760534351 -> 200.01807 | AA9: =(AA$4+32.7752118688871)*1.06+4.42986760534351 -> 202.05601 | AB9: =(AB$4+33.0374135638382)*1.0604+4.42986760534351 -> 203.4954 | AC9: =(AC$4+33.2996152587893)*1.0608+4.42986760534351 -> 205.19815 | AD9: =(AD$4+33.5618169537404)*1.0612+4.42986760534351 -> 207.09275 | AE9: =(AE$4+33.8240186486915)*1.0616+4.42986760534351 -> 209.14687 | AF9: =(AF$4+34.0862203436426)*1.062+4.42986760534351 -> 210.72689 | AG9: =(AG$4+34.3589101063917)*1.0624+4.42986760534351 -> 212.27945 | AH9: =(AH$4+34.6315998691409)*1.0628+4.42986760534351 -> 213.80576 | AI9: =(AI$4+34.90428963189)*1.0632+4.42986760534351 -> 215.32846 | AJ9: =(AJ$4+35.1769793946392)*1.0636+4.42986760534351 -> 217.00804 | AK9: =(AK$4+35.4496691573883)*1.064+4.42986760534351 -> 218.72794 | AL9: =(AL$4+35.7332665106474)*1.0644+4.42986760534351 -> 219.83834 | AM9: =(AM$4+36.0168638639065)*1.0648+4.42986760534351 -> 221.46314 | AN9: =(AN$4+36.3004612171656)*1.0652+4.42986760534351 -> 222.80506 | AO9: =(AO$4+36.5840585704247)*1.0656+4.42986760534351 -> 223.99695 | AP9: =(AP$4+36.8676559236838)*1.066+4.42986760534351 -> 225.57191
A10: Lignite fired power plants | B10: 85.91897 | C10: 85.981965 | D10: 86.044961 | E10: 86.107956 | F10: 86.170951 | G10: 86.233947 | H10: 86.578883 | I10: 86.923818 | J10: 87.268754 | K10: 87.61369 | L10: 87.958626 | M10: 88.31046 | N10: 88.662295 | O10: 89.014129 | P10: 89.365964 | Q10: 89.717798 | R10: 90.076669 | S10: 90.435541 | T10: 90.794412 | U10: 91.153283 | V10: 91.512154 | W10: 91.878203 | X10: 92.244251 | Y10: 92.6103 | Z10: 92.976349 | AA10: 93.342397 | AB10: 93.715767 | AC10: 94.089136 | AD10: 94.462506 | AE10: 94.835876 | AF10: 95.209245 | AG10: 95.590082 | AH10: 95.970919 | AI10: 96.351756 | AJ10: 96.732593 | AK10: 97.11343 | AL10: 97.501884 | AM10: 97.890338 | AN10: 98.278791 | AO10: 98.667245 | AP10: 99.055699
A11: Gas fired power plants (Natural gas, biogas) | B11: =(B$3+40.8631351145839)*1.025+17.6689580895606 -> 342.08011 | C11: =(C$3+34.4899856285991)*1.0254+18.6328302182585 -> 391.53249 | D11: =(D$3+28.1168361426143)*1.0258+19.5967023469563 -> 438.18332 | E11: =(E$3+21.7436866566296)*1.0262+20.5605744756542 -> 428.17179 | F11: =(F$3+15.3705371706448)*1.0266+21.524446604352 -> 360.56555 | G11: =(G$3+8.99738768466)*1.027+22.4883187330499 -> 303.2964 | H11: =(H$3+9.01538246002932)*1.0274+22.4883187330499 -> 204.80954 | I11: =(I$3+9.03337723539864)*1.0278+22.4883187330499 -> 241.17049 | J11: =(J$3+9.05137201076796)*1.0282+22.4883187330499 -> 266.56921 | K11: =(K$3+9.06936678613728)*1.0286+22.4883187330499 -> 292.19858 | L11: =(L$3+9.0873615615066)*1.029+22.4883187330499 -> 317.5492 | M11: =(M$3+9.10553628462961)*1.0294+22.4883187330499 -> 342.28624 | N11: =(N$3+9.12371100775263)*1.0298+22.4883187330499 -> 358.43675 | O11: =(O$3+9.14188573087564)*1.0302+22.4883187330499 -> 377.55951 | P11: =(P$3+9.16006045399865)*1.0306+22.4883187330499 -> 395.64077 | Q11: =(Q$3+9.17823517712166)*1.031+22.4883187330499 -> 412.70139 | R11: =(R$3+9.19659164747591)*1.0314+22.4883187330499 -> 418.90178 | S11: =(S$3+9.21494811783015)*1.0318+22.4883187330499 -> 424.7194 | T11: =(T$3+9.23330458818439)*1.0322+22.4883187330499 -> 431.1605 | U11: =(U$3+9.25166105853864)*1.0326+22.4883187330499 -> 437.61369 | V11: =(V$3+9.27001752889288)*1.033+22.4883187330499 -> 446.93335 | W11: =(W$3+9.28855756395067)*1.0334+22.4883187330499 -> 452.90784 | X11: =(X$3+9.30709759900845)*1.0338+22.4883187330499 -> 459.70936 | Y11: =(Y$3+9.32563763406624)*1.0342+22.4883187330499 -> 465.82286 | Z11: =(Z$3+9.34417766912402)*1.0346+22.4883187330499 -> 471.38995 | AA11: =(AA$3+9.36271770418181)*1.035+22.4883187330499 -> 476.12168 | AB11: =(AB$3+9.38144313959017)*1.0354+22.4883187330499 -> 480.59625 | AC11: =(AC$3+9.40016857499854)*1.0358+22.4883187330499 -> 484.28218 | AD11: =(AD$3+9.4188940104069)*1.0362+22.4883187330499 -> 487.87227 | AE11: =(AE$3+9.43761944581526)*1.0366+22.4883187330499 -> 491.83888 | AF11: =(AF$3+9.45634488122363)*1.037+22.4883187330499 -> 492.09463 | AG11: =(AG$3+9.47525757098607)*1.0374+22.4883187330499 -> 493.50614 | AH11: =(AH$3+9.49417026074852)*1.0378+22.4883187330499 -> 494.98757 | AI11: =(AI$3+9.51308295051097)*1.0382+22.4883187330499 -> 496.75216 | AJ11: =(AJ$3+9.53199564027341)*1.0386+22.4883187330499 -> 499.32653 | AK11: =(AK$3+9.55090833003586)*1.039+22.4883187330499 -> 502.54208 | AL11: =(AL$3+9.57001014669594)*1.0394+22.4883187330499 -> 505.59213 | AM11: =(AM$3+9.58911196335601)*1.0398+22.4883187330499 -> 508.35581 | AN11: =(AN$3+9.60821378001608)*1.0402+22.4883187330499 -> 510.59912 | AO11: =(AO$3+9.62731559667615)*1.0406+22.4883187330499 -> 510.644 | AP11: =(AP$3+9.64641741333622)*1.041+22.4883187330499 -> 510.82918
A12: Derived gas fired power plants | B12: =(B$4+82.6200171126463)*0.2 -> 39.782156 | C12: =(C$4+87.2487771279665)*0.201 -> 46.44048 | D12: =(D$4+91.8775371432867)*0.202 -> 41.948305 | E12: =(E$4+96.5062971586069)*0.203 -> 39.559994 | F12: =(F$4+101.135057173927)*0.204 -> 38.840842 | G12: =(G$4+105.763817189247)*0.205 -> 37.665757 | H12: =(H$4+105.869581006437)*0.206 -> 39.100099 | I12: =(I$4+105.975344823626)*0.207 -> 45.798818 | J12: =(J$4+106.081108640815)*0.208 -> 46.160837 | K12: =(K$4+106.186872458004)*0.209 -> 46.522381 | L12: =(L$4+106.292636275194)*0.21 -> 46.883465 | M12: =(M$4+106.398928911469)*0.211 -> 47.788367 | N12: =(N$4+106.505221547744)*0.212 -> 48.000541 | O12: =(O$4+106.611514184019)*0.213 -> 48.168205 | P12: =(P$4+106.717806820294)*0.214 -> 48.54884 | Q12: =(Q$4+106.824099456569)*0.215 -> 48.964845 | R12: =(R$4+106.930923556026)*0.216 -> 50.216404 | S12: =(S$4+107.037747655483)*0.217 -> 51.475166 | T12: =(T$4+107.144571754939)*0.218 -> 52.779767 | U12: =(U$4+107.251395854396)*0.219 -> 54.103746 | V12: =(V$4+107.358219953852)*0.22 -> 55.544959 | W12: =(W$4+107.465578173806)*0.221 -> 56.108161 | X12: =(X$4+107.57293639376)*0.222 -> 56.801685 | Y12: =(Y$4+107.680294613714)*0.223 -> 57.520346 | Z12: =(Z$4+107.787652833668)*0.224 -> 58.20671 | AA12: =(AA$4+107.895011053622)*0.225 -> 58.850901 | AB12: =(AB$4+108.002906064675)*0.226 -> 59.368466 | AC12: =(AC$4+108.110801075729)*0.227 -> 59.944431 | AD12: =(AD$4+108.218696086782)*0.228 -> 60.564115 | AE12: =(AE$4+108.326591097836)*0.229 -> 61.22103 | AF12: =(AF$4+108.43448610889)*0.23 -> 61.778363 | AG12: =(AG$4+108.542920594999)*0.231 -> 62.329705 | AH12: =(AH$4+108.651355081107)*0.232 -> 62.87752 | AI12: =(AI$4+108.759789567216)*0.233 -> 63.426702 | AJ12: =(AJ$4+108.868224053325)*0.234 -> 64.012547 | AK12: =(AK$4+108.976658539434)*0.235 -> 64.609715 | AL12: =(AL$4+109.085635197974)*0.236 -> 65.071775 | AM12: =(AM$4+109.194611856513)*0.237 -> 65.649742 | AN12: =(AN$4+109.303588515052)*0.238 -> 66.166799 | AO12: =(AO$4+109.412565173592)*0.239 -> 66.652009 | AP12: =(AP$4+109.521541832131)*0.24 -> 67.225009
A13: Refinery gas fired power plants | B13: =(B$2+1139.87468230279)*0.02 -> 31.447664 | C13: =(C$2+1137.31275865761)*0.02 -> 34.088731 | D13: =(D$2+1134.75083501244)*0.02 -> 34.804275 | E13: =(E$2+1132.18891136727)*0.02 -> 33.969442 | F13: =(F$2+1129.6269877221)*0.02 -> 32.714891 | G13: =(G$2+1127.06506407693)*0.02 -> 28.770174 | H13: =(H$2+1128.192129141)*0.02 -> 27.879841 | I13: =(I$2+1129.31919420508)*0.02 -> 28.996704 | J13: =(J$2+1130.44625926916)*0.02 -> 29.995555 | K13: =(K$2+1131.57332433323)*0.02 -> 30.873478 | L13: =(L$2+1132.70038939731)*0.02 -> 31.720254 | M13: =(M$2+1133.83308978671)*0.02 -> 32.527208 | N13: =(N$2+1134.96579017611)*0.02 -> 33.074169 | O13: =(O$2+1136.0984905655)*0.02 -> 33.73968 | P13: =(P$2+1137.2311909549)*0.02 -> 34.319355 | Q13: =(Q$2+1138.3638913443)*0.02 -> 34.813771 | R13: =(R$2+1139.50225523564)*0.02 -> 35.137393 | S13: =(S$2+1140.64061912699)*0.02 -> 35.432176 | T13: =(T$2+1141.77898301833)*0.02 -> 35.639971 | U13: =(U$2+1142.91734690967)*0.02 -> 35.953021 | V13: =(V$2+1144.05571080102)*0.02 -> 36.151695 | W13: =(W$2+1145.19976651182)*0.02 -> 36.342116 | X13: =(X$2+1146.34382222262)*0.02 -> 36.447425 | Y13: =(Y$2+1147.48787793342)*0.02 -> 36.565168 | Z13: =(Z$2+1148.63193364422)*0.02 -> 36.695303 | AA13: =(AA$2+1149.77598935502)*0.02 -> 36.839013 | AB13: =(AB$2+1150.92576534438)*0.02 -> 36.99857 | AC13: =(AC$2+1152.07554133373)*0.02 -> 37.177177 | AD13: =(AD$2+1153.22531732309)*0.02 -> 37.369006 | AE13: =(AE$2+1154.37509331244)*0.02 -> 37.566908 | AF13: =(AF$2+1155.5248693018)*0.02 -> 37.76852 | AG13: =(AG$2+1156.6803941711)*0.02 -> 37.803849 | AH13: =(AH$2+1157.8359190404)*0.02 -> 37.883741 | AI13: =(AI$2+1158.9914439097)*0.02 -> 37.967573 | AJ13: =(AJ$2+1160.14696877901)*0.02 -> 38.128074 | AK13: =(AK$2+1161.30249364831)*0.02 -> 38.220441 | AL13: =(AL$2+1162.46379614196)*0.02 -> 38.312593 | AM13: =(AM$2+1163.6250986356)*0.02 -> 38.403146 | AN13: =(AN$2+1164.78640112925)*0.02 -> 38.491243 | AO13: =(AO$2+1165.9477036229)*0.02 -> 38.57624 | AP13: =(AP$2+1167.10900611655)*0.02 -> 38.683157
A14: Diesel oil fired power plants | B14: =(B$2+142.766765676215)*1.03+203.198094570823 -> 795.73163 | C14: =(C$2+148.3277771089)*1.0304+203.976808479523 -> 941.17811 | D14: =(D$2+153.888788541584)*1.0308+204.755522388222 -> 987.49525 | E14: =(E$2+159.449799974268)*1.0312+205.534236296922 -> 953.91012 | F14: =(F$2+165.010811406952)*1.0316+206.312950205621 -> 898.64898 | G14: =(G$2+170.571822839636)*1.032+207.091664114321 -> 704.53159 | H14: =(H$2+171.254110130995)*1.0324+207.091664114321 -> 658.30622 | I14: =(I$2+171.936397422353)*1.0328+207.091664114321 -> 715.69652 | J14: =(J$2+172.618684713712)*1.0332+207.091664114321 -> 767.03461 | K14: =(K$2+173.30097200507)*1.0336+207.091664114321 -> 812.16272 | L14: =(L$2+173.983259296429)*1.034+207.091664114321 -> 855.7153 | M14: =(M$2+174.679192333615)*1.0344+207.091664114321 -> 897.25009 | N14: =(N$2+175.3751253708)*1.0348+207.091664114321 -> 925.36476 | O14: =(O$2+176.071058407986)*1.0352+207.091664114321 -> 959.63711 | P14: =(P$2+176.766991445172)*1.0356+207.091664114321 -> 989.49113 | Q14: =(Q$2+177.462924482357)*1.036+207.091664114321 -> 1014.9516 | R14: =(R$2+178.172776180287)*1.0364+207.091664114321 -> 1031.5895 | S14: =(S$2+178.882627878216)*1.0368+207.091664114321 -> 1046.745 | T14: =(T$2+179.592479576146)*1.0372+207.091664114321 -> 1057.4007 | U14: =(U$2+180.302331274075)*1.0376+207.091664114321 -> 1073.525 | V14: =(V$2+181.012182972005)*1.038+207.091664114321 -> 1083.7254 | W14: =(W$2+181.736231703893)*1.0384+207.091664114321 -> 1093.5138 | X14: =(X$2+182.460280435781)*1.0388+207.091664114321 -> 1098.8887 | Y14: =(Y$2+183.184329167669)*1.0392+207.091664114321 -> 1104.9136 | Z14: =(Z$2+183.908377899557)*1.0396+207.091664114321 -> 1111.5869 | AA14: =(AA$2+184.632426631445)*1.04+207.091664114321 -> 1118.971 | AB14: =(AB$2+185.37095633797)*1.0404+207.091664114321 -> 1127.1941 | AC14: =(AC$2+186.109486044496)*1.0408+207.091664114321 -> 1136.4145 | AD14: =(AD$2+186.848015751022)*1.0412+207.091664114321 -> 1146.3301 | AE14: =(AE$2+187.586545457548)*1.0416+207.091664114321 -> 1156.5693 | AF14: =(AF$2+188.325075164074)*1.042+207.091664114321 -> 1167.0094 | AG14: =(AG$2+189.07837546473)*1.0424+207.091664114321 -> 1168.7999 | AH14: =(AH$2+189.831675765386)*1.0428+207.091664114321 -> 1172.9151 | AI14: =(AI$2+190.584976066042)*1.0432+207.091664114321 -> 1177.2386 | AJ14: =(AJ$2+191.338276366699)*1.0436+207.091664114321 -> 1185.5658 | AK14: =(AK$2+192.091576667355)*1.044+207.091664114321 -> 1190.3425 | AL14: =(AL$2+192.859942974024)*1.0444+207.091664114321 -> 1195.121 | AM14: =(AM$2+193.628309280694)*1.0448+207.091664114321 -> 1199.8193 | AN14: =(AN$2+194.396675587363)*1.0452+207.091664114321 -> 1204.3927 | AO14: =(AO$2+195.165041894033)*1.0456+207.091664114321 -> 1208.8072 | AP14: =(AP$2+195.933408200702)*1.046+207.091664114321 -> 1214.3711
A15: Fuel oil fired power plants | B15: =(B$2+43.1184299781623)*0.85+32.5791747572926 -> 436.86208 | C15: =(C$2+46.5304851560515)*0.8502+32.0303297243418 -> 553.7592 | D15: =(D$2+49.9425403339406)*0.8504+31.481484691391 -> 588.83827 | E15: =(E$2+53.3545955118298)*0.8506+30.9326396584403 -> 557.99656 | F15: =(F$2+56.766650689719)*0.8508+30.3837946254895 -> 509.28568 | G15: =(G$2+60.1787058676082)*0.851+29.8349495925387 -> 346.08554 | H15: =(H$2+60.2388845734758)*0.8512+29.8349495925387 -> 307.35916 | I15: =(I$2+60.2990632793434)*0.8514+29.8349495925387 -> 354.06091 | J15: =(J$2+60.359241985211)*0.8516+29.8349495925387 -> 395.75959 | K15: =(K$2+60.4194206910786)*0.8518+29.8349495925387 -> 432.32749 | L15: =(L$2+60.4795993969462)*0.852+29.8349495925387 -> 467.58567 | M15: =(M$2+60.5400789963432)*0.8522+29.8349495925387 -> 501.159 | N15: =(N$2+60.6005585957401)*0.8524+29.8349495925387 -> 523.66712 | O15: =(O$2+60.6610381951371)*0.8526+29.8349495925387 -> 551.23954 | P15: =(P$2+60.721517794534)*0.8528+29.8349495925387 -> 575.16479 | Q15: =(Q$2+60.7819973939309)*0.853+29.8349495925387 -> 595.46494 | R15: =(R$2+60.8427793913249)*0.8532+29.8349495925387 -> 608.48388 | S15: =(S$2+60.9035613887188)*0.8534+29.8349495925387 -> 620.27829 | T15: =(T$2+60.9643433861127)*0.8536+29.8349495925387 -> 628.36552 | U15: =(U$2+61.0251253835067)*0.8538+29.8349495925387 -> 640.94982 | V15: =(V$2+61.0859073809006)*0.854+29.8349495925387 -> 648.6561 | W15: =(W$2+61.1469932882815)*0.8542+29.8349495925387 -> 656.00885 | X15: =(X$2+61.2080791956624)*0.8544+29.8349495925387 -> 659.72895 | Y15: =(Y$2+61.2691651030433)*0.8546+29.8349495925387 -> 663.98208 | Z15: =(Z$2+61.3302510104242)*0.8548+29.8349495925387 -> 668.76671 | AA15: =(AA$2+61.3913369178051)*0.855+29.8349495925387 -> 674.13388 | AB15: =(AB$2+61.4527282547229)*0.8552+29.8349495925387 -> 680.17647 | AC15: =(AC$2+61.5141195916407)*0.8554+29.8349495925387 -> 687.03656 | AD15: =(AD$2+61.5755109285585)*0.8556+29.8349495925387 -> 694.46546 | AE15: =(AE$2+61.6369022654763)*0.8558+29.8349495925387 -> 702.15759 | AF15: =(AF$2+61.6982936023941)*0.856+29.8349495925387 -> 710.01204 | AG15: =(AG$2+61.7599918959965)*0.8562+29.8349495925387 -> 710.74686 | AH15: =(AH$2+61.8216901895989)*0.8564+29.8349495925387 -> 713.39016 | AI15: =(AI$2+61.8833884832013)*0.8566+29.8349495925387 -> 716.20333 | AJ15: =(AJ$2+61.9450867768037)*0.8568+29.8349495925387 -> 722.30227 | AK15: =(AK$2+62.0067850704061)*0.857+29.8349495925387 -> 725.48441 | AL15: =(AL$2+62.0687918554765)*0.8572+29.8349495925387 -> 728.6541 | AM15: =(AM$2+62.1307986405469)*0.8574+29.8349495925387 -> 731.75659 | AN15: =(AN$2+62.1928054256173)*0.8576+29.8349495925387 -> 734.75517 | AO15: =(AO$2+62.2548122106877)*0.8578+29.8349495925387 -> 737.62214 | AP15: =(AP$2+62.3168189957581)*0.858+29.8349495925387 -> 741.4307
A16: Biomass and waste fired power plants | B16: =(B$5+20.9432757503314)*1.028 -> 282.41078 | C16: =(C$5+28.5161304421512)*1.0282 -> 290.25213 | D16: =(D$5+36.088985133971)*1.0284 -> 298.09652 | E16: =(E$5+43.6618398257909)*1.0286 -> 305.94393 | F16: =(F$5+51.2346945176107)*1.0288 -> 313.79437 | G16: =(G$5+58.8075492094306)*1.029 -> 321.64784 | H16: =(H$5+59.0427794062683)*1.0292 -> 323.87846 | I16: =(I$5+59.278009603106)*1.0294 -> 324.87926 | J16: =(J$5+59.5132397999437)*1.0296 -> 326.03233 | K16: =(K$5+59.7484699967815)*1.0298 -> 327.9281 | L16: =(L$5+59.9837001936192)*1.03 -> 330.98592 | M16: =(M$5+60.2236349943936)*1.0302 -> 334.16401 | N16: =(N$5+60.4635697951681)*1.0304 -> 337.62053 | O16: =(O$5+60.7035045959426)*1.0306 -> 341.22548 | P16: =(P$5+60.9434393967171)*1.0308 -> 344.7489 | Q16: =(Q$5+61.1833741974916)*1.031 -> 348.385 | R16: =(R$5+61.4281076942815)*1.0312 -> 351.99718 | S16: =(S$5+61.6728411910715)*1.0314 -> 355.94523 | T16: =(T$5+61.9175746878615)*1.0316 -> 361.08575 | U16: =(U$5+62.1623081846514)*1.0318 -> 368.75704 | V16: =(V$5+62.4070416814414)*1.032 -> 376.29782 | W16: =(W$5+62.6566698481671)*1.0322 -> 381.55214 | X16: =(X$5+62.9062980148929)*1.0324 -> 384.80861 | Y16: =(Y$5+63.1559261816187)*1.0326 -> 387.65348 | Z16: =(Z$5+63.4055543483445)*1.0328 -> 390.22352 | AA16: =(AA$5+63.6551825150702)*1.033 -> 392.96822 | AB16: =(AB$5+63.9098032451305)*1.0332 -> 395.77734 | AC16: =(AC$5+64.1644239751908)*1.0334 -> 398.35816 | AD16: =(AD$5+64.4190447052511)*1.0336 -> 400.64882 | AE16: =(AE$5+64.6736654353113)*1.0338 -> 402.2171 | AF16: =(AF$5+64.9282861653716)*1.034 -> 403.56069 | AG16: =(AG$5+65.1879993100331)*1.0342 -> 404.95708 | AH16: =(AH$5+65.4477124546946)*1.0344 -> 406.4811 | AI16: =(AI$5+65.7074255993561)*1.0346 -> 408.07926 | AJ16: =(AJ$5+65.9671387440176)*1.0348 -> 409.19439 | AK16: =(AK$5+66.2268518886791)*1.035 -> 410.68379 | AL16: =(AL$5+66.4917592962338)*1.0352 -> 411.89901 | AM16: =(AM$5+66.7566667037885)*1.0354 -> 413.96916 | AN16: =(AN$5+67.0215741113432)*1.0356 -> 416.1737 | AO16: =(AO$5+67.2864815188979)*1.0358 -> 418.42547 | AP16: =(AP$5+67.5513889264526)*1.036 -> 420.53637
A17: Fuel cells / NGS | B17: =(B$3+40.8631351145839)*1.025+17.6689580895606 -> 342.08011 | C17: =(C$3+34.4899856285991)*1.0254+18.6328302182585 -> 391.53249 | D17: =(D$3+28.1168361426143)*1.0258+19.5967023469563 -> 438.18332 | E17: =(E$3+21.7436866566296)*1.0262+20.5605744756542 -> 428.17179 | F17: =(F$3+15.3705371706448)*1.0266+21.524446604352 -> 360.56555 | G17: =(G$3+8.99738768466)*1.027+22.4883187330499 -> 303.2964 | H17: =(H$3+9.01538246002932)*1.0274+22.4883187330499 -> 204.80954 | I17: =(I$3+9.03337723539864)*1.0278+22.4883187330499 -> 241.17049 | J17: =(J$3+9.05137201076796)*1.0282+22.4883187330499 -> 266.56921 | K17: =(K$3+9.06936678613728)*1.0286+22.4883187330499 -> 292.19858 | L17: =(L$3+9.0873615615066)*1.029+22.4883187330499 -> 317.5492 | M17: =(M$3+9.10553628462961)*1.0294+22.4883187330499 -> 342.28624 | N17: =(N$3+9.12371100775263)*1.0298+22.4883187330499 -> 358.43675 | O17: =(O$3+9.14188573087564)*1.0302+22.4883187330499 -> 377.55951 | P17: =(P$3+9.16006045399865)*1.0306+22.4883187330499 -> 395.64077 | Q17: =(Q$3+9.17823517712166)*1.031+22.4883187330499 -> 412.70139 | R17: =(R$3+9.19659164747591)*1.0314+22.4883187330499 -> 418.90178 | S17: =(S$3+9.21494811783015)*1.0318+22.4883187330499 -> 424.7194 | T17: =(T$3+9.23330458818439)*1.0322+22.4883187330499 -> 431.1605 | U17: =(U$3+9.25166105853864)*1.0326+22.4883187330499 -> 437.61369 | V17: =(V$3+9.27001752889288)*1.033+22.4883187330499 -> 446.93335 | W17: =(W$3+9.28855756395067)*1.0334+22.4883187330499 -> 452.90784 | X17: =(X$3+9.30709759900845)*1.0338+22.4883187330499 -> 459.70936 | Y17: =(Y$3+9.32563763406624)*1.0342+22.4883187330499 -> 465.82286 | Z17: =(Z$3+9.34417766912402)*1.0346+22.4883187330499 -> 471.38995 | AA17: =(AA$3+9.36271770418181)*1.035+22.4883187330499 -> 476.12168 | AB17: =(AB$3+9.38144313959017)*1.0354+22.4883187330499 -> 480.59625 | AC17: =(AC$3+9.40016857499854)*1.0358+22.4883187330499 -> 484.28218 | AD17: =(AD$3+9.4188940104069)*1.0362+22.4883187330499 -> 487.87227 | AE17: =(AE$3+9.43761944581526)*1.0366+22.4883187330499 -> 491.83888 | AF17: =(AF$3+9.45634488122363)*1.037+22.4883187330499 -> 492.09463 | AG17: =(AG$3+9.47525757098607)*1.0374+22.4883187330499 -> 493.50614 | AH17: =(AH$3+9.49417026074852)*1.0378+22.4883187330499 -> 494.98757 | AI17: =(AI$3+9.51308295051097)*1.0382+22.4883187330499 -> 496.75216 | AJ17: =(AJ$3+9.53199564027341)*1.0386+22.4883187330499 -> 499.32653 | AK17: =(AK$3+9.55090833003586)*1.039+22.4883187330499 -> 502.54208 | AL17: =(AL$3+9.57001014669594)*1.0394+22.4883187330499 -> 505.59213 | AM17: =(AM$3+9.58911196335601)*1.0398+22.4883187330499 -> 508.35581 | AN17: =(AN$3+9.60821378001608)*1.0402+22.4883187330499 -> 510.59912 | AO17: =(AO$3+9.62731559667615)*1.0406+22.4883187330499 -> 510.644 | AP17: =(AP$3+9.64641741333622)*1.041+22.4883187330499 -> 510.82918
A18: Fuel cells / H2 | B18: 2024.2748 | C18: 1987.0763 | D18: 1949.8777 | E18: 1912.6792 | F18: 1875.4807 | G18: 1838.2822 | H18: 1797.84 | I18: 1757.3978 | J18: 1716.9556 | K18: 1676.5133 | L18: 1636.0711 | M18: 1600.0776 | N18: 1564.084 | O18: 1528.0904 | P18: 1492.0969 | Q18: 1456.1033 | R18: 1424.069 | S18: 1392.0348 | T18: 1360.0005 | U18: 1327.9662 | V18: 1295.9319 | W18: 1267.4214 | X18: 1238.9109 | Y18: 1210.4004 | Z18: 1181.8899 | AA18: 1153.3794 | AB18: 1128.0051 | AC18: 1102.6307 | AD18: 1077.2564 | AE18: 1051.882 | AF18: 1026.5077 | AG18: 1003.9245 | AH18: 981.34136 | AI18: 958.75819 | AJ18: 936.17502 | AK18: 913.59185 | AL18: 893.49283 | AM18: 873.39381 | AN18: 853.29479 | AO18: 833.19577 | AP18: 813.09675
A19: Wind power plants | B19: 0 | C19: 0 | D19: 0 | E19: 0 | F19: 0 | G19: 0 | H19: 0 | I19: 0 | J19: 0 | K19: 0 | L19: 0 | M19: 0 | N19: 0 | O19: 0 | P19: 0 | Q19: 0 | R19: 0 | S19: 0 | T19: 0 | U19: 0 | V19: 0 | W19: 0 | X19: 0 | Y19: 0 | Z19: 0 | AA19: 0 | AB19: 0 | AC19: 0 | AD19: 0 | AE19: 0 | AF19: 0 | AG19: 0 | AH19: 0 | AI19: 0 | AJ19: 0 | AK19: 0 | AL19: 0 | AM19: 0 | AN19: 0 | AO19: 0 | AP19: 0
A20: Solar PV power plants | B20: 0 | C20: 0 | D20: 0 | E20: 0 | F20: 0 | G20: 0 | H20: 0 | I20: 0 | J20: 0 | K20: 0 | L20: 0 | M20: 0 | N20: 0 | O20: 0 | P20: 0 | Q20: 0 | R20: 0 | S20: 0 | T20: 0 | U20: 0 | V20: 0 | W20: 0 | X20: 0 | Y20: 0 | Z20: 0 | AA20: 0 | AB20: 0 | AC20: 0 | AD20: 0 | AE20: 0 | AF20: 0 | AG20: 0 | AH20: 0 | AI20: 0 | AJ20: 0 | AK20: 0 | AL20: 0 | AM20: 0 | AN20: 0 | AO20: 0 | AP20: 0
A21: Solar thermal power plants | B21: 0 | C21: 0 | D21: 0 | E21: 0 | F21: 0 | G21: 0 | H21: 0 | I21: 0 | J21: 0 | K21: 0 | L21: 0 | M21: 0 | N21: 0 | O21: 0 | P21: 0 | Q21: 0 | R21: 0 | S21: 0 | T21: 0 | U21: 0 | V21: 0 | W21: 0 | X21: 0 | Y21: 0 | Z21: 0 | AA21: 0 | AB21: 0 | AC21: 0 | AD21: 0 | AE21: 0 | AF21: 0 | AG21: 0 | AH21: 0 | AI21: 0 | AJ21: 0 | AK21: 0 | AL21: 0 | AM21: 0 | AN21: 0 | AO21: 0 | AP21: 0
A22: Geothermal power plants | B22: 0 | C22: 0 | D22: 0 | E22: 0 | F22: 0 | G22: 0 | H22: 0 | I22: 0 | J22: 0 | K22: 0 | L22: 0 | M22: 0 | N22: 0 | O22: 0 | P22: 0 | Q22: 0 | R22: 0 | S22: 0 | T22: 0 | U22: 0 | V22: 0 | W22: 0 | X22: 0 | Y22: 0 | Z22: 0 | AA22: 0 | AB22: 0 | AC22: 0 | AD22: 0 | AE22: 0 | AF22: 0 | AG22: 0 | AH22: 0 | AI22: 0 | AJ22: 0 | AK22: 0 | AL22: 0 | AM22: 0 | AN22: 0 | AO22: 0 | AP22: 0
A23: Tide, wave and ocean power plants | B23: 0 | C23: 0 | D23: 0 | E23: 0 | F23: 0 | G23: 0 | H23: 0 | I23: 0 | J23: 0 | K23: 0 | L23: 0 | M23: 0 | N23: 0 | O23: 0 | P23: 0 | Q23: 0 | R23: 0 | S23: 0 | T23: 0 | U23: 0 | V23: 0 | W23: 0 | X23: 0 | Y23: 0 | Z23: 0 | AA23: 0 | AB23: 0 | AC23: 0 | AD23: 0 | AE23: 0 | AF23: 0 | AG23: 0 | AH23: 0 | AI23: 0 | AJ23: 0 | AK23: 0 | AL23: 0 | AM23: 0 | AN23: 0 | AO23: 0 | AP23: 0
A24: Hydro plants | B24: 0 | C24: 0 | D24: 0 | E24: 0 | F24: 0 | G24: 0 | H24: 0 | I24: 0 | J24: 0 | K24: 0 | L24: 0 | M24: 0 | N24: 0 | O24: 0 | P24: 0 | Q24: 0 | R24: 0 | S24: 0 | T24: 0 | U24: 0 | V24: 0 | W24: 0 | X24: 0 | Y24: 0 | Z24: 0 | AA24: 0 | AB24: 0 | AC24: 0 | AD24: 0 | AE24: 0 | AF24: 0 | AG24: 0 | AH24: 0 | AI24: 0 | AJ24: 0 | AK24: 0 | AL24: 0 | AM24: 0 | AN24: 0 | AO24: 0 | AP24: 0
A25: Pump storage | B25: 0 | C25: 0 | D25: 0 | E25: 0 | F25: 0 | G25: 0 | H25: 0 | I25: 0 | J25: 0 | K25: 0 | L25: 0 | M25: 0 | N25: 0 | O25: 0 | P25: 0 | Q25: 0 | R25: 0 | S25: 0 | T25: 0 | U25: 0 | V25: 0 | W25: 0 | X25: 0 | Y25: 0 | Z25: 0 | AA25: 0 | AB25: 0 | AC25: 0 | AD25: 0 | AE25: 0 | AF25: 0 | AG25: 0 | AH25: 0 | AI25: 0 | AJ25: 0 | AK25: 0 | AL25: 0 | AM25: 0 | AN25: 0 | AO25: 0 | AP25: 0
