Workbook

Sheet Context
B15: AIDRES - EU industrial plants database (NUTS3)
B17: The AIDRES database (Advancing industrial decarbonization by assessing the future use of renewable energies in industrial processes), is a spatially explicit database covering 2030 and 2050 demands for renewable energy carriers (electricity, gases, liquid fuels and heat) representing future pathways for 6 energy intensive energy industrial sectors (steel, cement, glass, refinery, chemical and fertiliser) in the European Union. This geographical database at the level of plant location and aggregated at NUTS3 granularity combines information on the type of installations, industrial parameters and current, 2030 and 2050 energy and feedstock demands, production rates, GHG emissions and related cost parameters for a mixture of the selected future technology pathways.
B22: Consult key results of the AIDRES project through the Energy and Industry Geographt lab (EIGL - JRC)
B23: [link to EIGL]
B25: Download open access full database (SQL) and reports describing the AIDRES database:
B26: [link to JRC open database catalogue]
B28: Full project report describing AIDRES methodology and results:
B29: [link to DG ENER website]
B31: Rights and licensing
B32: This data is licensed under Creative Commons (https://creativecommons.org/licenses/by/4.0/). This data can be reused under the terms of the CC BY 4.0 licence. You are free to share, copy and redistribute the datasets. You are also free to adapt, remix, transform, and build upon the datasets for any purpose, even commercially. Under the following terms: 1.you must give appropriate credit: AIDRES database, Energyville | VITO, 2023 prepared for the European Commission, DG ENER, under service contract N° ENER/2020/OP/0011/C2/SER/2019-569/SI2.840687 - Following copyright notice: © European Union, 1995-2023 - A link to the material: LINK TO ENER SITE 2.you must indicate if changes were made. 3.you may not apply legal terms or technological measures that legally restrict others from doing anything the license permits.

Sheet Main assumptions

Sheet Glossary
A13: Group | B13: Sheet | C13: Description
A14: Feedstock and energy inputs | B14: Total energy & feedstock inputs | C14: Sum of all individual energy and feedstock parameters
B15: Electricity [PJ/y] | C15: Electricity annual energy consumptionin PJ pear y
B16: Alternative fuel mixture [PJ/y] | C16: Alternative fuel mixture annual energy consumption
B17: Biomass [PJ/y] | C17: Biomass annual energy consumption
B18: Biomass waste [PJ/y] | C18: Biomass waste annual energy consumption
B19: Coal [PJ/y] | C19: Coal annual energy consumption
B20: Coke [PJ/y] | C20: Coke annual energy consumption
B21: Crude oil [PJ/y] | C21: Crude oil annual energy consumption
B22: Hydrogen [PJ/y] | C22: Hydrogen annual energy consumption
B23: Methanol [PJ/y] | C23: Methanol annual energy consumption
B24: Naphtha [PJ/y] | C24: Naphtha annual energy consumption
B25: Natural gas [PJ/y] | C25: Natural gas annual energy consumption
B26: Plastic mix [PJ/y] | C26: Plastic mix annual energy consumption
A29: Product flow
B30: product_flow [kt/y] | C30: Annual production
A32: Emissions
B33: Direct emission [ktCO2/y] | C33: Direct annual CO2 emissions at the plant
B34: Total emission [ktCO2/y] | C34: Direct at the plant and indirect upstream annual CO2 emissions
B35: Captured CO2 [ktCO2/y] | C35: Captured CO2 at the plant annually (production process and fumes)
B36: Direct emission reduction [%] | C36: Direct emission reduction
B37: Total emission reduction [%] | C37: Total emission reduction
A39: Costs
B40: totex [mEUR/y] | C40: Annualized total expenditure (TOTEX)
B41: opex var [mEUR/y] | C41: Annual operation expenditure from the energy consuption
B42: CO2 allowance [mEUR/y] | C42: Annual CO2 allowance
B43: opex cst [mEUR/y] | C43: Annual constant operation expenditure (OPEX)
B44: opex [mEUR/y] | C44: Annual operation expenditure (OPEX)
B45: opex ccs storage [mEUR/y] | C45: Annual carbon storage operation expenditure
B46: opex ccs transport [mEUR/y] | C46: Annual carbon transport operation expenditure
B47: opex ccs [mEUR/y] | C47: Annual carbon transport and storage expenditure
B48: capex [mEUR/y] | C48: Annual capital expenditure (CAPEX)

Sheet Total energy & feedstock inputs
F12: 2018 | M12: 2030 | T12: 2050
A13: NUTS ID | B13: NUTS LEVEL | C13: Country code | D13: NUTS region name (Latin) | E13: NUTS_NAME | F13: All sectors (PJ/y) | G13: Steel (PJ/y) | H13: Cement (PJ/y) | I13: Glass (PJ/y) | J13: Refineries (PJ/y) | K13: Fertilisers (PJ/y) | L13: Chemical (PJ/y) | M13: All sectors (PJ/y) | N13: Steel (PJ/y) | O13: Cement (PJ/y) | P13: Glass (PJ/y) | Q13: Refineries (PJ/y) | R13: Fertilisers (PJ/y) | S13: Chemical (PJ/y) | T13: All sectors (PJ/y) | U13: Steel (PJ/y) | V13: Cement (PJ/y) | W13: Glass (PJ/y) | X13: Refineries (PJ/y) | Y13: Fertilisers (PJ/y) | Z13: Chemical (PJ/y)
A14: AT121 | B14: 3 | C14: AT | D14: Mostviertel-Eisenwurzen | E14: Mostviertel-Eisenwurzen | F14: 1.1221212 | I14: 1.1221212 | M14: 1.118078 | P14: 1.118078 | T14: 1.0934878 | W14: 1.0934878
A15: AT122 | B15: 3 | C15: AT | D15: Niederösterreich-Süd | E15: Niederösterreich-Süd | F15: 1.1777767 | H15: 1.1777767 | M15: 1.2330791 | O15: 1.2330791 | T15: 1.569413 | V15: 1.569413
A16: AT124 | B16: 3 | C16: AT | D16: Waldviertel | E16: Waldviertel | F16: 0.44779015 | L16: 0.44779015 | M16: 0.45016337 | S16: 0.45016337 | T16: 0.45554936 | Z16: 0.45554936
A17: AT127 | B17: 3 | C17: AT | D17: Wiener Umland/Südteil | E17: Wiener Umland/Südteil | F17: 513.74884 | H17: 2.4435252 | J17: 432.47472 | L17: 78.830596 | M17: 457.86021 | O17: 2.5582607 | Q17: 371.68234 | S17: 83.619606 | T17: 233.2226 | V17: 3.2560502 | X17: 135.497 | Z17: 94.469547
A18: AT213 | B18: 3 | C18: AT | D18: Unterkärnten | E18: Unterkärnten | F18: 1.7672346 | H18: 1.7672346 | M18: 1.8502149 | O18: 1.8502149 | T18: 2.3548783 | V18: 2.3548783
A19: AT221 | B19: 3 | C19: AT | D19: Graz | E19: Graz | F19: 0.60668147 | G19: 0.60668147 | M19: 0.60668147 | N19: 0.60668147 | T19: 0.60668147 | U19: 0.60668147
A20: AT223 | B20: 3 | C20: AT | D20: Östliche Obersteiermark | E20: Östliche Obersteiermark | F20: 25.781885 | G20: 25.781885 | M20: 23.102472 | N20: 23.102472 | T20: 19.516591 | U20: 19.516591
A21: AT225 | B21: 3 | C21: AT | D21: West- und Südsteiermark | E21: West- und Südsteiermark | F21: 2.2857082 | H21: 1.311029 | I21: 0.97467924 | M21: 2.3437555 | O21: 1.3725882 | P21: 0.97116729 | T21: 2.6967827 | V21: 1.7469745 | W21: 0.9498082
A22: AT312 | B22: 3 | C22: AT | D22: Linz-Wels | E22: Linz-Wels | F22: 107.53083 | G22: 95.480476 | K22: 11.639763 | L22: 0.41058815 | M22: 97.040076 | N22: 85.240678 | R22: 11.386456 | S22: 0.4129417 | T22: 82.767879 | U22: 71.536676 | Y22: 10.81292 | Z22: 0.41828276
A23: AT314 | B23: 3 | C23: AT | D23: Steyr-Kirchdorf | E23: Steyr-Kirchdorf | F23: 2.1851098 | H23: 0.90765151 | I23: 1.2774583 | M23: 2.2231256 | O23: 0.95027021 | P23: 1.2728554 | T23: 2.4543265 | V23: 1.2094653 | W23: 1.2448612
A24: AT315 | B24: 3 | C24: AT | D24: Traunviertel | E24: Traunviertel | F24: 1.3248425 | H24: 1.3248425 | M24: 1.3870503 | O24: 1.3870503 | T24: 1.7653813 | V24: 1.7653813
A25: AT323 | B25: 3 | C25: AT | D25: Salzburg und Umgebung | E25: Salzburg und Umgebung | F25: 1.2545387 | H25: 1.2545387 | M25: 1.3134455 | O25: 1.3134455 | T25: 1.6717 | V25: 1.6717
A26: AT331 | B26: 3 | C26: AT | D26: Außerfern | E26: Außerfern | F26: 0.86572066 | H26: 0.86572066 | M26: 0.90637049 | O26: 0.90637049 | T26: 1.1535915 | V26: 1.1535915
A27: BE211 | B27: 3 | C27: BE | D27: Arr. Antwerpen | E27: Arr. Antwerpen | F27: 1963.5174 | J27: 1734.3574 | K27: 16.784084 | L27: 212.37594 | M27: 1728.6025 | Q27: 1490.5611 | R27: 16.418827 | S27: 221.62253 | T27: 801.54961 | X27: 543.38489 | Y27: 15.59181 | Z27: 242.57291
A28: BE213 | B28: 3 | C28: BE | D28: Arr. Turnhout | E28: Arr. Turnhout | F28: 15.893854 | I28: 1.0587338 | L28: 14.835121 | M28: 15.971672 | P28: 1.0553694 | S28: 14.916302 | T28: 16.135436 | W28: 1.0348963 | Z28: 15.100539
A29: BE224 | B29: 3 | C29: BE | D29: Arr. Hasselt | E29: Arr. Hasselt | F29: 2.9626429 | G29: 1.8834146 | L29: 1.0792283 | M29: 2.9674864 | N29: 1.8834146 | S29: 1.0840719 | T29: 2.9784802 | U29: 1.8834146 | Z29: 1.0950656
A30: BE233 | B30: 3 | C30: BE | D30: Arr. Eeklo | E30: Arr. Eeklo | F30: 2.7014047 | L30: 2.7014047 | M30: 2.8414003 | S30: 2.8414003 | T30: 3.1585824 | Z30: 3.1585824
A31: BE234 | B31: 3 | C31: BE | D31: Arr. Gent | E31: Arr. Gent | F31: 104.3071 | G31: 103.36118 | L31: 0.945921 | M31: 93.227563 | N31: 92.27622 | S31: 0.95134315 | T31: 78.404773 | U31: 77.441125 | Z31: 0.96364799
A32: BE236 | B32: 3 | C32: BE | D32: Arr. Sint-Niklaas | E32: Arr. Sint-Niklaas | F32: 10.526831 | L32: 10.526831 | M32: 10.586785 | S32: 10.586785 | T32: 10.722844 | Z32: 10.722844
A33: BE255 | B33: 3 | C33: BE | D33: Arr. Oostende | E33: Arr. Oostende | F33: 0.41058815 | L33: 0.41058815 | M33: 0.4129417 | S33: 0.4129417 | T33: 0.41828276 | Z33: 0.41828276
A34: BE323 | B34: 3 | C34: BE | D34: Arr. Mons | E34: Arr. Mons | F34: 15.881779 | H34: 3.6049001 | I34: 1.1834319 | K34: 8.3920422 | L34: 2.7014047 | M34: 16.004149 | O34: 3.7741678 | P34: 1.1791678 | R34: 8.2094134 | S34: 2.8414003 | T34: 16.911329 | V34: 4.8036074 | W34: 1.1532341 | Y34: 7.795905 | Z34: 3.1585824
A35: BE328 | B35: 3 | C35: BE | D35: Arr. Tournai-Mouscron | E35: Arr. Tournai-Mouscron | F35: 6.8621567 | H35: 6.8621567 | M35: 7.1843687 | O35: 7.1843687 | T35: 9.1439724 | V35: 9.1439724
A36: BE32B | B36: 3 | C36: BE | D36: Arr. Charleroi | E36: Arr. Charleroi | F36: 3.4529267 | G36: 3.4529267 | M36: 3.4529267 | N36: 3.4529267 | T36: 3.4529267 | U36: 3.4529267
A37: BE32C | B37: 3 | C37: BE | D37: Arr. Soignies | E37: Arr. Soignies | F37: 4.3110007 | I37: 0.29083642 | L37: 4.0201642 | M37: 4.3329969 | P37: 0.28978848 | S37: 4.0432084 | T37: 4.3789191 | W37: 0.28341511 | Z37: 4.095504
A38: BE32D | B38: 3 | C38: BE | D38: Arr. Thuin | E38: Arr. Thuin | F38: 0.43965186 | I38: 0.43965186 | M38: 0.43806771 | P38: 0.43806771 | T38: 0.42843319 | W38: 0.42843319
A39: BE332 | B39: 3 | C39: BE | D39: Arr. Liège | E39: Arr. Liège | F39: 4.0590791 | H39: 4.0590791 | M39: 4.2496728 | O39: 4.2496728 | T39: 5.4088108 | V39: 5.4088108
A40: BE335 | B40: 3 | C40: BE | D40: Arr. Verviers — communes francophones | E40: Arr. Verviers — communes francophones | F40: 1.4061998 | I40: 1.4061998 | M40: 1.3972033 | P40: 1.3972033 | T40: 1.3426362 | W40: 1.3426362
A41: BE352 | B41: 3 | C41: BE | D41: Arr. Namur | E41: Arr. Namur | F41: 5.6391499 | I41: 4.7478624 | L41: 0.8912875 | M41: 5.6245335 | P41: 4.7327747 | S41: 0.8917588 | T41: 5.533799 | W41: 4.6409637 | Z41: 0.89283524
A42: BG313 | B42: 3 | C42: BG | D42: Vratsa | E42: Враца | F42: 1.6245685 | H42: 1.6245685 | M42: 1.7008499 | O42: 1.7008499 | T42: 2.1647727 | V42: 2.1647727
A43: BG314 | B43: 3 | C43: BG | D43: Pleven | E43: Плевен | F43: 0.73153058 | I43: 0.73153058 | M43: 0.72889474 | P43: 0.72889474 | T43: 0.712864 | W43: 0.712864
A44: BG315 | B44: 3 | C44: BG | D44: Lovech | E44: Ловеч | F44: 1.9623408 | H44: 1.9623408 | M44: 2.0544824 | O44: 2.0544824 | T44: 2.6148616 | V44: 2.6148616
A45: BG331 | B45: 3 | C45: BG | D45: Varna | E45: Варна | F45: 11.361808 | H45: 2.8648654 | K45: 8.4969427 | M45: 11.311416 | O45: 2.9993849 | R45: 8.312031 | T45: 11.710849 | V45: 3.8174952 | Y45: 7.8933538
A46: BG333 | B46: 3 | C46: BG | D46: Shumen | E46: Шумен | F46: 0.44089872 | I46: 0.44089872 | M46: 0.43931008 | P46: 0.43931008 | T46: 0.42964824 | W46: 0.42964824
A47: BG334 | B47: 3 | C47: BG | D47: Targovishte | E47: Търговище | F47: 4.4075012 | I47: 4.4075012 | M47: 4.3931095 | P47: 4.3931095 | T47: 4.3055446 | W47: 4.3055446
A48: BG341 | B48: 3 | C48: BG | D48: Burgas | E48: Бургас | F48: 436.93322 | J48: 436.93322 | M48: 375.51412 | Q48: 375.51412 | T48: 136.89388 | X48: 136.89388
A49: BG411 | B49: 3 | C49: BG | D49: Sofia (stolitsa) | E49: София (столица) | F49: 0.71838978 | I49: 0.71838978 | M49: 0.71580129 | P49: 0.71580129 | T49: 0.70005852 | W49: 0.70005852
A50: BG414 | B50: 3 | C50: BG | D50: Pernik | E50: Перник | F50: 1.3211908 | G50: 1.3211908 | M50: 1.3211908 | N50: 1.3211908 | T50: 1.3211908 | U50: 1.3211908
A51: BG421 | B51: 3 | C51: BG | D51: Plovdiv | E51: Пловдив | F51: 2.2189787 | I51: 2.2189787 | M51: 2.2109833 | P51: 2.2109833 | T51: 2.1623567 | W51: 2.1623567
A52: BG422 | B52: 3 | C52: BG | D52: Haskovo | E52: Хасково | F52: 9.4410475 | K52: 9.4410475 | M52: 9.23559 | R52: 9.23559 | T52: 8.7703931 | Y52: 8.7703931
A53: CY000 | B53: 3 | C53: CY | D53: Kýpros | E53: Κύπρος | F53: 5.2032205 | H53: 5.2032205 | M53: 5.4475373 | O53: 5.4475373 | T53: 6.933404 | V53: 6.933404
A54: CZ010 | B54: 3 | C54: CZ | D54: Hlavní město Praha | E54: Hlavní město Praha | F54: 1.9607891 | H54: 1.9607891 | M54: 2.0528578 | O54: 2.0528578 | T54: 2.6127939 | V54: 2.6127939
A55: CZ020 | B55: 3 | C55: CZ | D55: Středočeský kraj | E55: Středočeský kraj | F55: 154.86035 | I55: 0.12208087 | J55: 151.58908 | L55: 3.1491948 | M55: 133.69361 | P55: 0.12164099 | Q55: 130.28041 | S55: 3.2915637 | T55: 51.226892 | W55: 0.11896571 | X55: 47.493795 | Z55: 3.6141317
A56: CZ032 | B56: 3 | C56: CZ | D56: Plzeňský kraj | E56: Plzeňský kraj | F56: 0.69166337 | G56: 0.27001314 | I56: 0.42165023 | M56: 0.69014408 | N56: 0.27001314 | P56: 0.42013094 | T56: 0.68090405 | U56: 0.27001314 | W56: 0.41089091
A57: CZ041 | B57: 3 | C57: CZ | D57: Karlovarský kraj | E57: Karlovarský kraj | F57: 1.0567873 | I57: 1.0567873 | M57: 1.0529795 | P57: 1.0529795 | T57: 1.0298211 | W57: 1.0298211
A58: CZ042 | B58: 3 | C58: CZ | D58: Ústecký kraj | E58: Ústecký kraj | F58: 332.66535 | H58: 1.7370006 | I58: 4.8887363 | J58: 240.75912 | L58: 85.280492 | M58: 304.09412 | O58: 1.8185613 | P58: 4.8712644 | Q58: 206.91594 | S58: 90.488353 | T58: 184.79816 | V58: 2.314591 | W58: 4.7650182 | X58: 75.431321 | Z58: 102.28723
A59: CZ051 | B59: 3 | C59: CZ | D59: Liberecký kraj | E59: Liberecký kraj | F59: 0.20022919 | I59: 0.20022919 | M59: 0.19950772 | P59: 0.19950772 | T59: 0.19511991 | W59: 0.19511991
A60: CZ053 | B60: 3 | C60: CZ | D60: Pardubický kraj | E60: Pardubický kraj | F60: 39.132074 | H60: 2.3268195 | I60: 1.1372364 | J60: 35.668018 | M60: 34.220249 | O60: 2.4360751 | P60: 1.1299606 | Q60: 30.654214 | T60: 15.361378 | V60: 3.1005374 | W60: 1.0858306 | X60: 11.175011
A61: CZ063 | B61: 3 | C61: CZ | D61: Kraj Vysočina | E61: Kraj Vysočina | F61: 0.32722446 | I61: 0.32722446 | M61: 0.32604541 | P61: 0.32604541 | T61: 0.31887462 | W61: 0.31887462
A62: CZ064 | B62: 3 | C62: CZ | D62: Jihomoravský kraj | E62: Jihomoravský kraj | F62: 5.0849759 | H62: 2.8066735 | I62: 2.2783024 | M62: 5.2070029 | O62: 2.9384606 | P62: 2.2685424 | T62: 5.9491955 | V62: 3.7399532 | W62: 2.2092423
A63: CZ071 | B63: 3 | C63: CZ | D63: Olomoucký kraj | E63: Olomoucký kraj | F63: 5.0681967 | H63: 2.3667921 | L63: 2.7014047 | M63: 5.3193249 | O63: 2.4779246 | S63: 2.8414003 | T63: 6.312384 | V63: 3.1538017 | Z63: 3.1585824
A64: CZ080 | B64: 3 | C64: CZ | D64: Moravskoslezský kraj | E64: Moravskoslezský kraj | F64: 102.68122 | G64: 91.758915 | I64: 0.8778674 | K64: 7.3430369 | L64: 2.7014047 | M64: 92.83829 | N64: 81.941402 | P64: 0.872251 | R64: 7.1832367 | S64: 2.8414003 | T64: 79.620731 | U64: 68.802546 | W64: 0.83818569 | Y64: 6.8214169 | Z64: 3.1585824
A65: DE11C | B65: 3 | C65: DE | D65: Heidenheim | E65: Heidenheim | F65: 2.2107853 | H65: 2.2107853 | M65: 2.3145925 | O65: 2.3145925 | T65: 2.9459192 | V65: 2.9459192
A66: DE122 | B66: 3 | C66: DE | D66: Karlsruhe, Stadtkreis | E66: Karlsruhe, Stadtkreis | F66: 691.06784 | J66: 691.06784 | M66: 593.92539 | Q66: 593.92539 | T66: 216.51583 | X66: 216.51583
A67: DE123 | B67: 3 | C67: DE | D67: Karlsruhe, Landkreis | E67: Karlsruhe, Landkreis | F67: 1.9334683 | H67: 1.9334683 | M67: 2.0242541 | O67: 2.0242541 | T67: 2.5763884 | V67: 2.5763884
A68: DE126 | B68: 3 | C68: DE | D68: Mannheim, Stadtkreis | E68: Mannheim, Stadtkreis | F68: 0.55653661 | I68: 0.55653661 | M68: 0.55476807 | P68: 0.55476807 | T68: 0.54400613 | W68: 0.54400613
A69: DE128 | B69: 3 | C69: DE | D69: Rhein-Neckar-Kreis | E69: Rhein-Neckar-Kreis | F69: 2.0320663 | H69: 2.0320663 | M69: 2.1274818 | O69: 2.1274818 | T69: 2.7077723 | V69: 2.7077723
A70: DE131 | B70: 3 | C70: DE | D70: Freiburg im Breisgau, Stadtkreis | E70: Freiburg im Breisgau, Stadtkreis | F70: 0.44779015 | L70: 0.44779015 | M70: 0.45016337 | S70: 0.45016337 | T70: 0.45554936 | Z70: 0.45554936
A71: DE134 | B71: 3 | C71: DE | D71: Ortenaukreis | E71: Ortenaukreis | F71: 4.2653741 | G71: 4.2653741 | M71: 4.2653741 | N71: 4.2653741 | T71: 4.2653741 | U71: 4.2653741
A72: DE143 | B72: 3 | C72: DE | D72: Zollernalbkreis | E72: Zollernalbkreis | F72: 2.9502747 | H72: 2.9502747 | M72: 3.0888046 | O72: 3.0888046 | T72: 3.9313049 | V72: 3.9313049
A73: DE145 | B73: 3 | C73: DE | D73: Alb-Donau-Kreis | E73: Alb-Donau-Kreis | F73: 5.7177132 | H73: 5.7177132 | M73: 5.9861879 | O73: 5.9861879 | T73: 7.6189766 | V73: 7.6189766
A74: DE148 | B74: 3 | C74: DE | D74: Ravensburg | E74: Ravensburg | F74: 1.8964008 | I74: 1.8964008 | M74: 1.8895677 | P74: 1.8895677 | T74: 1.84801 | W74: 1.84801
A75: DE214 | B75: 3 | C75: DE | D75: Altötting | E75: Altötting | F75: 237.45075 | J75: 164.96458 | L75: 72.486164 | M75: 218.57731 | Q75: 141.77574 | S75: 76.801573 | T75: 138.26298 | X75: 51.684424 | Z75: 86.578554
A76: DE219 | B76: 3 | C76: DE | D76: Eichstätt | E76: Eichstätt | F76: 245.88497 | I76: 0.66735106 | J76: 245.21762 | M76: 211.41266 | P76: 0.66494647 | Q76: 210.74772 | T76: 77.478519 | W76: 0.65032217 | X76: 76.828197
A77: DE21I | B77: 3 | C77: DE | D77: Neuburg-Schrobenhausen | E77: Neuburg-Schrobenhausen | F77: 1.3425194 | I77: 1.3425194 | M77: 1.337682 | P77: 1.337682 | T77: 1.3082621 | W77: 1.3082621
A78: DE21J | B78: 3 | C78: DE | D78: Pfaffenhofen a. d. Ilm | E78: Pfaffenhofen a. d. Ilm | F78: 8.0797267 | L78: 8.0797267 | M78: 8.5651915 | S78: 8.5651915 | T78: 9.6650569 | Z78: 9.6650569
A79: DE21K | B79: 3 | C79: DE | D79: Rosenheim, Landkreis | E79: Rosenheim, Landkreis | F79: 3.2709801 | H79: 3.2709801 | M79: 3.4245687 | O79: 3.4245687 | T79: 4.3586518 | V79: 4.3586518
A80: DE226 | B80: 3 | C80: DE | D80: Kelheim | E80: Kelheim | F80: 205.0911 | J80: 205.0911 | M80: 176.26173 | Q80: 176.26173 | T80: 64.25631 | X80: 64.25631
A81: DE229 | B81: 3 | C81: DE | D81: Regen | E81: Regen | F81: 0.52379585 | I81: 0.52379585 | M81: 0.52190851 | P81: 0.52190851 | T81: 0.51043007 | W81: 0.51043007
A82: DE237 | B82: 3 | C82: DE | D82: Neustadt a. d. Waldnaab | E82: Neustadt a. d. Waldnaab | F82: 2.8313371 | I82: 2.8313371 | M82: 2.8223397 | P82: 2.8223397 | T82: 2.7675892 | W82: 2.7675892
A83: DE239 | B83: 3 | C83: DE | D83: Schwandorf | E83: Schwandorf | F83: 3.5126342 | H83: 3.5126342 | M83: 3.6775696 | O83: 3.6775696 | T83: 4.6806611 | V83: 4.6806611
A84: DE24A | B84: 3 | C84: DE | D84: Kronach | E84: Kronach | F84: 2.7858499 | I84: 2.7858499 | M84: 2.7758119 | P84: 2.7758119 | T84: 2.7147629 | W84: 2.7147629
A85: DE24D | B85: 3 | C85: DE | D85: Wunsiedel i. Fichtelgebirge | E85: Wunsiedel i. Fichtelgebirge | F85: 0.23626267 | I85: 0.23626267 | M85: 0.23551188 | P85: 0.23551188 | T85: 0.23094319 | W85: 0.23094319
A86: DE25C | B86: 3 | C86: DE | D86: Weißenburg-Gunzenhausen | E86: Weißenburg-Gunzenhausen | F86: 1.2683874 | H86: 1.2683874 | M86: 1.3279444 | O86: 1.3279444 | T86: 1.6901537 | V86: 1.6901537
A87: DE26A | B87: 3 | C87: DE | D87: Main-Spessart | E87: Main-Spessart | F87: 6.3593936 | H87: 5.177379 | I87: 1.1820146 | M87: 6.598238 | O87: 5.4204824 | P87: 1.1777556 | T87: 8.0508226 | V87: 6.8989696 | W87: 1.1518529
A88: DE276 | B88: 3 | C88: DE | D88: Augsburg, Landkreis | E88: Augsburg, Landkreis | F88: 2.0132566 | G88: 2.0132566 | M88: 2.0132566 | N88: 2.0132566 | T88: 2.0132566 | U88: 2.0132566
A89: DE27D | B89: 3 | C89: DE | D89: Donau-Ries | E89: Donau-Ries | F89: 2.5016612 | H89: 2.5016612 | M89: 2.6191265 | O89: 2.6191265 | T89: 3.3335178 | V89: 3.3335178
A90: DE401 | B90: 3 | C90: DE | D90: Brandenburg an der Havel, Kreisfreie Stadt | E90: Brandenburg an der Havel, Kreisfreie Stadt | F90: 3.0710694 | G90: 3.0710694 | M90: 3.0710694 | N90: 3.0710694 | T90: 3.0710694 | U90: 3.0710694
A91: DE409 | B91: 3 | C91: DE | D91: Märkisch-Oderland | E91: Märkisch-Oderland | F91: 5.7497485 | H91: 4.9681582 | I91: 0.78159031 | M91: 5.9802117 | O91: 5.2014376 | P91: 0.77877409 | T91: 7.3818247 | V91: 6.6201784 | W91: 0.76164635
A92: DE40A | B92: 3 | C92: DE | D92: Oberhavel | E92: Oberhavel | F92: 1.7061496 | G92: 1.7061496 | M92: 1.7061496 | N92: 1.7061496 | T92: 1.7061496 | U92: 1.7061496
A93: DE40C | B93: 3 | C93: DE | D93: Oder-Spree | E93: Oder-Spree | F93: 44.545716 | G93: 44.545716 | M93: 39.768413 | N93: 39.768413 | T93: 33.374912 | U93: 33.374912
A94: DE40G | B94: 3 | C94: DE | D94: Spree-Neiße | E94: Spree-Neiße | F94: 1.3747915 | I94: 1.3747915 | M94: 1.3700367 | P94: 1.3700367 | T94: 1.3411138 | W94: 1.3411138
A95: DE40I | B95: 3 | C95: DE | D95: Uckermark | E95: Uckermark | F95: 490.43524 | J95: 490.43524 | M95: 421.49544 | Q95: 421.49544 | T95: 153.65639 | X95: 153.65639
A96: DE501 | B96: 3 | C96: DE | D96: Bremen, Kreisfreie Stadt | E96: Bremen, Kreisfreie Stadt | F96: 70.530717 | G96: 70.530717 | M96: 62.966655 | N96: 62.966655 | T96: 52.84361 | U96: 52.84361
A97: DE600 | B97: 3 | C97: DE | D97: Hamburg | E97: Hamburg | F97: 470.72551 | G97: 20.416786 | J97: 450.30872 | M97: 405.23664 | N97: 18.227189 | Q97: 387.00945 | T97: 156.38134 | U97: 15.296834 | X97: 141.08451
A98: DE712 | B98: 3 | C98: DE | D98: Frankfurt am Main, Kreisfreie Stadt | E98: Frankfurt am Main, Kreisfreie Stadt | F98: 21.140851 | L98: 21.140851 | M98: 22.406896 | S98: 22.406896 | T98: 25.275245 | Z98: 25.275245
A99: DE714 | B99: 3 | C99: DE | D99: Wiesbaden, Kreisfreie Stadt | E99: Wiesbaden, Kreisfreie Stadt | F99: 0.7752103 | H99: 0.7752103 | M99: 0.81161023 | O99: 0.81161023 | T99: 1.0329845 | V99: 1.0329845
A100: DE722 | B100: 3 | C100: DE | D100: Lahn-Dill-Kreis | E100: Lahn-Dill-Kreis | F100: 0.68245986 | G100: 0.68245986 | M100: 0.68245986 | N100: 0.68245986 | T100: 0.68245986 | U100: 0.68245986
A101: DE732 | B101: 3 | C101: DE | D101: Fulda | E101: Fulda | F101: 0.55143528 | H101: 0.55143528 | M101: 0.57732787 | O101: 0.57732787 | T101: 0.73479944 | V101: 0.73479944
A102: DE80M | B102: 3 | C102: DE | D102: Nordwestmecklenburg | E102: Nordwestmecklenburg | F102: 2.7014047 | L102: 2.7014047 | M102: 2.8414003 | S102: 2.8414003 | T102: 3.1585824 | Z102: 3.1585824
A103: DE80O | B103: 3 | C103: DE | D103: Ludwigslust-Parchim | E103: Ludwigslust-Parchim | F103: 0.51290264 | I103: 0.51290264 | M103: 0.5096212 | P103: 0.5096212 | T103: 0.48971821 | W103: 0.48971821
A104: DE912 | B104: 3 | C104: DE | D104: Salzgitter, Kreisfreie Stadt | E104: Salzgitter, Kreisfreie Stadt | F104: 103.94 | G104: 103.94 | M104: 92.792965 | N104: 92.792965 | T104: 77.874794 | U104: 77.874794
A105: DE91A | B105: 3 | C105: DE | D105: Peine | E105: Peine | F105: 1.7061496 | G105: 1.7061496 | M105: 1.7061496 | N105: 1.7061496 | T105: 1.7061496 | U105: 1.7061496
A106: DE91C | B106: 3 | C106: DE | D106: Göttingen | E106: Göttingen | F106: 0.037202001 | L106: 0.037202001 | M106: 0.037221673 | S106: 0.037221673 | T106: 0.037266602 | Z106: 0.037266602
A107: DE922 | B107: 3 | C107: DE | D107: Diepholz | E107: Diepholz | F107: 0.037202001 | L107: 0.037202001 | M107: 0.037221673 | S107: 0.037221673 | T107: 0.037266602 | Z107: 0.037266602
A108: DE923 | B108: 3 | C108: DE | D108: Hameln-Pyrmont | E108: Hameln-Pyrmont | F108: 0.35873219 | I108: 0.35873219 | M108: 0.35743961 | P108: 0.35743961 | T108: 0.34957836 | W108: 0.34957836
A109: DE926 | B109: 3 | C109: DE | D109: Holzminden | E109: Holzminden | F109: 2.1522665 | I109: 2.1522665 | M109: 2.1445115 | P109: 2.1445115 | T109: 2.0973468 | W109: 2.0973468
A110: DE927 | B110: 3 | C110: DE | D110: Nienburg (Weser) | E110: Nienburg (Weser) | F110: 2.2546498 | I110: 1.8440616 | L110: 0.41058815 | M110: 2.2503588 | P110: 1.8374171 | S110: 0.4129417 | T110: 2.2152892 | W110: 1.7970064 | Z110: 0.41828276
A111: DE928 | B111: 3 | C111: DE | D111: Schaumburg | E111: Schaumburg | F111: 2.1292628 | I111: 2.1292628 | M111: 2.1215906 | P111: 2.1215906 | T111: 2.0749301 | W111: 2.0749301
...

Sheet Electricity (PJ per y)
F12: 2018 | M12: 2030 | T12: 2050
A13: NUTS ID | B13: NUTS LEVEL | C13: Country code | D13: NUTS region name (Latin) | E13: NUTS_NAME | F13: All sectors (PJ/y) | G13: Steel (PJ/y) | H13: Cement (PJ/y) | I13: Glass (PJ/y) | J13: Refineries (PJ/y) | K13: Fertilisers (PJ/y) | L13: Chemical (PJ/y) | M13: All sectors (PJ/y) | N13: Steel (PJ/y) | O13: Cement (PJ/y) | P13: Glass (PJ/y) | Q13: Refineries (PJ/y) | R13: Fertilisers (PJ/y) | S13: Chemical (PJ/y) | T13: All sectors (PJ/y) | U13: Steel (PJ/y) | V13: Cement (PJ/y) | W13: Glass (PJ/y) | X13: Refineries (PJ/y) | Y13: Fertilisers (PJ/y) | Z13: Chemical (PJ/y)
A14: AT121 | B14: 3 | C14: AT | D14: Mostviertel-Eisenwurzen | E14: Mostviertel-Eisenwurzen | F14: 0.20566984 | I14: 0.20566984 | M14: 0.24734312 | P14: 0.24734312 | T14: 0.50079813 | W14: 0.50079813
A15: AT122 | B15: 3 | C15: AT | D15: Niederösterreich-Süd | E15: Niederösterreich-Süd | F15: 0.12979009 | H15: 0.12979009 | M15: 0.14563243 | O15: 0.14563243 | T15: 0.24198074 | V15: 0.24198074
A16: AT124 | B16: 3 | C16: AT | D16: Waldviertel | E16: Waldviertel | F16: 0.079474115 | L16: 0.079474115 | M16: 0.11260432 | S16: 0.11260432 | T16: 0.18766951 | Z16: 0.18766951
A17: AT127 | B17: 3 | C17: AT | D17: Wiener Umland/Südteil | E17: Wiener Umland/Südteil | F17: 2.588142 | H17: 0.26927459 | J17: 0.88812599 | L17: 1.4307414 | M17: 17.810308 | O17: 0.30214259 | Q17: 6.5743016 | S17: 10.933864 | T17: 45.813702 | V17: 0.50203577 | X17: 12.856985 | Z17: 32.454682
A18: AT213 | B18: 3 | C18: AT | D18: Unterkärnten | E18: Unterkärnten | F18: 0.19474789 | H18: 0.19474789 | M18: 0.21851906 | O18: 0.21851906 | T18: 0.36308812 | V18: 0.36308812
A19: AT221 | B19: 3 | C19: AT | D19: Graz | E19: Graz | F19: 0.45838203 | G19: 0.45838203 | M19: 0.45838203 | N19: 0.45838203 | T19: 0.45838203 | U19: 0.45838203
A20: AT223 | B20: 3 | C20: AT | D20: Östliche Obersteiermark | E20: Östliche Obersteiermark | F20: 1.4528744 | G20: 1.4528744 | M20: 1.9546246 | N20: 1.9546246 | T20: 4.0467298 | U20: 4.0467298
A21: AT225 | B21: 3 | C21: AT | D21: West- und Südsteiermark | E21: West- und Südsteiermark | F21: 0.32312008 | H21: 0.14447438 | I21: 0.1786457 | M21: 0.3769524 | O21: 0.16210911 | P21: 0.21484329 | T21: 0.70435355 | V21: 0.26935816 | W21: 0.43499539
A22: AT312 | B22: 3 | C22: AT | D22: Linz-Wels | E22: Linz-Wels | F22: 4.0999599 | G22: 3.2486777 | K22: 0.79502779 | L22: 0.056254407 | M22: 6.1764168 | N22: 5.1661943 | R22: 0.92215271 | S22: 0.088069791 | T22: 14.531823 | U22: 13.161501 | Y22: 1.2101646 | Z22: 0.16015725
A23: AT314 | B23: 3 | C23: AT | D23: Steyr-Kirchdorf | E23: Steyr-Kirchdorf | F23: 0.33416356 | H23: 0.1000225 | I23: 0.23414106 | M23: 0.39381462 | O23: 0.11223137 | P23: 0.28158325 | T23: 0.75660649 | V23: 0.18648203 | W23: 0.57012446
A24: AT315 | B24: 3 | C24: AT | D24: Traunviertel | E24: Traunviertel | F24: 0.14599662 | H24: 0.14599662 | M24: 0.16381715 | O24: 0.16381715 | T24: 0.27219622 | V24: 0.27219622
A25: AT323 | B25: 3 | C25: AT | D25: Salzburg und Umgebung | E25: Salzburg und Umgebung | F25: 0.1382492 | H25: 0.1382492 | M25: 0.15512408 | O25: 0.15512408 | T25: 0.25775193 | V25: 0.25775193
A26: AT331 | B26: 3 | C26: AT | D26: Außerfern | E26: Außerfern | F26: 0.095401749 | H26: 0.095401749 | M26: 0.10704661 | O26: 0.10704661 | T26: 0.1778671 | V26: 0.1778671
A27: BE211 | B27: 3 | C27: BE | D27: Arr. Antwerpen | E27: Arr. Antwerpen | F27: 18.042426 | J27: 3.5616599 | K27: 1.1463991 | L27: 13.334367 | M27: 63.643471 | Q27: 26.364983 | R27: 1.3297083 | S27: 35.94878 | T27: 140.47284 | X27: 51.560485 | Y27: 1.7450103 | Z27: 87.167349
A28: BE213 | B28: 3 | C28: BE | D28: Arr. Turnhout | E28: Arr. Turnhout | F28: 2.5283383 | I28: 0.13486539 | L28: 2.3934729 | M28: 3.6868289 | P28: 0.17504669 | S28: 3.5117822 | T28: 6.4650555 | W28: 0.41943044 | Z28: 6.045625
A29: BE224 | B29: 3 | C29: BE | D29: Arr. Hasselt | E29: Arr. Hasselt | F29: 1.6965983 | G29: 1.4230258 | L29: 0.27357252 | M29: 1.7693494 | N29: 1.4230258 | S29: 0.34632356 | T29: 1.9341794 | U29: 1.4230258 | Z29: 0.51115355
A30: BE233 | B30: 3 | C30: BE | D30: Arr. Eeklo | E30: Arr. Eeklo | F30: 0.11832492 | L30: 0.11832492 | M30: 0.42373055 | S30: 0.42373055 | T30: 1.1153909 | Z30: 1.1153909
A31: BE234 | B31: 3 | C31: BE | D31: Arr. Gent | E31: Arr. Gent | F31: 3.646415 | G31: 3.516815 | L31: 0.1296 | M31: 5.7954953 | N31: 5.5925984 | S31: 0.2028969 | T31: 14.61679 | U31: 14.247816 | Z31: 0.36897339
A32: BE236 | B32: 3 | C32: BE | D32: Arr. Sint-Niklaas | E32: Arr. Sint-Niklaas | F32: 1.4785194 | L32: 1.4785194 | M32: 2.2910799 | S32: 2.2910799 | T32: 4.1321805 | Z32: 4.1321805
A33: BE255 | B33: 3 | C33: BE | D33: Arr. Oostende | E33: Arr. Oostende | F33: 0.056254407 | L33: 0.056254407 | M33: 0.088069791 | S33: 0.088069791 | T33: 0.16015725 | Z33: 0.16015725
A34: BE323 | B34: 3 | C34: BE | D34: Arr. Mons | E34: Arr. Mons | F34: 1.305689 | H34: 0.39725721 | I34: 0.21690728 | K34: 0.57319956 | L34: 0.11832492 | M34: 1.7951892 | O34: 0.44574693 | P34: 0.26085752 | R34: 0.66485416 | S34: 0.42373055 | T34: 3.2567036 | V34: 0.74064667 | W34: 0.52816087 | Y34: 0.87250515 | Z34: 1.1153909
A35: BE328 | B35: 3 | C35: BE | D35: Arr. Tournai-Mouscron | E35: Arr. Tournai-Mouscron | F35: 0.75620438 | H35: 0.75620438 | M35: 0.84850765 | O35: 0.84850765 | T35: 1.4098681 | V35: 1.4098681
A36: BE32B | B36: 3 | C36: BE | D36: Arr. Charleroi | E36: Arr. Charleroi | F36: 2.6088807 | G36: 2.6088807 | M36: 2.6088807 | N36: 2.6088807 | T36: 2.6088807 | U36: 2.6088807
A37: BE32C | B37: 3 | C37: BE | D37: Arr. Soignies | E37: Arr. Soignies | F37: 0.60410644 | I37: 0.053306436 | L37: 0.5508 | M37: 0.92641935 | P37: 0.064107505 | S37: 0.86231184 | T37: 1.697936 | W37: 0.12979912 | Z37: 1.5681369
A38: BE32D | B38: 3 | C38: BE | D38: Arr. Thuin | E38: Arr. Thuin | F38: 0.080582319 | I38: 0.080582319 | M38: 0.096910089 | P38: 0.096910089 | T38: 0.19621484 | W38: 0.19621484
A39: BE332 | B39: 3 | C39: BE | D39: Arr. Liège | E39: Arr. Liège | F39: 0.44730739 | H39: 0.44730739 | M39: 0.5019063 | O39: 0.5019063 | T39: 0.83396027 | V39: 0.83396027
A40: BE335 | B40: 3 | C40: BE | D40: Arr. Verviers — communes francophones | E40: Arr. Verviers — communes francophones | F40: 0.32154913 | I40: 0.32154913 | M40: 0.35688706 | P40: 0.35688706 | T40: 0.57169824 | W40: 0.57169824
A41: BE352 | B41: 3 | C41: BE | D41: Arr. Namur | E41: Arr. Namur | F41: 1.1610991 | I41: 0.60480009 | L41: 0.556299 | M41: 1.3727916 | P41: 0.78499202 | S41: 0.58779957 | T41: 2.5400644 | W41: 1.8809241 | Z41: 0.65914025
A42: BG313 | B42: 3 | C42: BG | D42: Vratsa | E42: Враца | F42: 0.17902619 | H42: 0.17902619 | M42: 0.20087836 | O42: 0.20087836 | T42: 0.33377659 | V42: 0.33377659
A43: BG314 | B43: 3 | C43: BG | D43: Pleven | E43: Плевен | F43: 0.1340798 | I43: 0.1340798 | M43: 0.16124734 | P43: 0.16124734 | T43: 0.32647913 | W43: 0.32647913
A44: BG315 | B44: 3 | C44: BG | D44: Lovech | E44: Ловеч | F44: 0.21624845 | H44: 0.21624845 | M44: 0.24264401 | O44: 0.24264401 | T44: 0.40317379 | V44: 0.40317379
A45: BG331 | B45: 3 | C45: BG | D45: Varna | E45: Варна | F45: 0.89607052 | H45: 0.31570596 | K45: 0.58036455 | M45: 1.0274063 | O45: 0.35424143 | R45: 0.67316483 | T45: 1.4720139 | V45: 0.58860246 | Y45: 0.88341147
A46: BG333 | B46: 3 | C46: BG | D46: Shumen | E46: Шумен | F46: 0.080810853 | I46: 0.080810853 | M46: 0.097184929 | P46: 0.097184929 | T46: 0.19677131 | W46: 0.19677131
A47: BG334 | B47: 3 | C47: BG | D47: Targovishte | E47: Търговище | F47: 0.61211758 | I47: 0.61211758 | M47: 0.77865394 | P47: 0.77865394 | T47: 1.7915301 | W47: 1.7915301
A48: BG341 | B48: 3 | C48: BG | D48: Burgas | E48: Бургас | F48: 0.89728192 | J48: 0.89728192 | M48: 6.6420779 | Q48: 6.6420779 | T48: 12.989531 | X48: 12.989531
A49: BG411 | B49: 3 | C49: BG | D49: Sofia (stolitsa) | E49: София (столица) | F49: 0.13167126 | I49: 0.13167126 | M49: 0.15835079 | P49: 0.15835079 | T49: 0.32061445 | W49: 0.32061445
A50: BG414 | B50: 3 | C50: BG | D50: Pernik | E50: Перник | F50: 0.9982341 | G50: 0.9982341 | M50: 0.9982341 | N50: 0.9982341 | T50: 0.9982341 | U50: 0.9982341
A51: BG421 | B51: 3 | C51: BG | D51: Plovdiv | E51: Пловдив | F51: 0.40670919 | I51: 0.40670919 | M51: 0.48911752 | P51: 0.48911752 | T51: 0.99032119 | W51: 0.99032119
A52: BG422 | B52: 3 | C52: BG | D52: Haskovo | E52: Хасково | F52: 0.64484951 | K52: 0.64484951 | M52: 0.74796092 | R52: 0.74796092 | T52: 0.98156829 | Y52: 0.98156829
A53: CY000 | B53: 3 | C53: CY | D53: Kýpros | E53: Κύπρος | F53: 0.57339089 | H53: 0.57339089 | M53: 0.64337971 | O53: 0.64337971 | T53: 1.0690305 | V53: 1.0690305
A54: CZ010 | B54: 3 | C54: CZ | D54: Hlavní město Praha | E54: Hlavní město Praha | F54: 0.21607745 | H54: 0.21607745 | M54: 0.24245214 | O54: 0.24245214 | T54: 0.40285498 | V54: 0.40285498
A55: CZ020 | B55: 3 | C55: CZ | D55: Středočeský kraj | E55: Středočeský kraj | F55: 0.53147673 | I55: 0.022375794 | J55: 0.31130189 | L55: 0.19779904 | M55: 2.8676389 | P55: 0.026909628 | Q55: 2.3043944 | S55: 0.53633487 | T55: 5.8641166 | W55: 0.054484197 | X55: 4.506572 | Z55: 1.3030604
A56: CZ032 | B56: 3 | C56: CZ | D56: Plzeňský kraj | E56: Plzeňský kraj | F56: 0.281293 | G56: 0.20401014 | I56: 0.077282861 | M56: 0.29695223 | N56: 0.20401014 | P56: 0.092942087 | T56: 0.39219092 | U56: 0.20401014 | W56: 0.18818078
A57: CZ041 | B57: 3 | C57: CZ | D57: Karlovarský kraj | E57: Karlovarský kraj | F57: 0.19369502 | I57: 0.19369502 | M57: 0.23294194 | P57: 0.23294194 | T57: 0.4716399 | W57: 0.4716399
A58: CZ042 | B58: 3 | C58: CZ | D58: Ústecký kraj | E58: Ústecký kraj | F58: 2.8629665 | H58: 0.19141613 | I58: 0.70695094 | J58: 0.49442065 | L58: 1.4701788 | M58: 16.533491 | O58: 0.21478063 | P58: 0.88525942 | Q58: 3.6599205 | S58: 11.77353 | T58: 44.590574 | V58: 0.3568764 | W58: 1.9696916 | X58: 7.1574966 | Z58: 35.10651
A59: CZ051 | B59: 3 | C59: CZ | D59: Liberecký kraj | E59: Liberecký kraj | F59: 0.036699338 | I59: 0.036699338 | M59: 0.04413544 | P59: 0.04413544 | T59: 0.089361473 | W59: 0.089361473
A60: CZ053 | B60: 3 | C60: CZ | D60: Pardubický kraj | E60: Pardubický kraj | F60: 0.58970774 | H60: 0.25641372 | I60: 0.26004652 | J60: 0.073247504 | M60: 1.1185477 | O60: 0.2877119 | P60: 0.28862538 | Q60: 0.54221044 | T60: 2.0007775 | V60: 0.47805795 | W60: 0.46234968 | X60: 1.0603699
A61: CZ063 | B61: 3 | C61: CZ | D61: Kraj Vysočina | E61: Kraj Vysočina | F61: 0.059975878 | I61: 0.059975878 | M61: 0.072128324 | P61: 0.072128324 | T61: 0.14603895 | W61: 0.14603895
A62: CZ064 | B62: 3 | C62: CZ | D62: Jihomoravský kraj | E62: Jihomoravský kraj | F62: 0.75205848 | H62: 0.30929325 | I62: 0.44276523 | M62: 0.86775896 | O62: 0.34704598 | P62: 0.52071298 | T62: 1.5713898 | V62: 0.5766466 | W62: 0.99474321
A63: CZ071 | B63: 3 | C63: CZ | D63: Olomoucký kraj | E63: Olomoucký kraj | F63: 0.37914359 | H63: 0.26081867 | L63: 0.11832492 | M63: 0.71638507 | O63: 0.29265452 | S63: 0.42373055 | T63: 1.6016615 | V63: 0.48627054 | Z63: 1.1153909
A64: CZ080 | B64: 3 | C64: CZ | D64: Moravskoslezský kraj | E64: Moravskoslezský kraj | F64: 4.0985242 | G64: 3.2779118 | I64: 0.20073783 | K64: 0.50154961 | L64: 0.11832492 | M64: 6.3446275 | N64: 5.1163509 | P64: 0.22279872 | R64: 0.58174739 | S64: 0.42373055 | T64: 15.017669 | U64: 12.781934 | W64: 0.3569018 | Y64: 0.76344201 | Z64: 1.1153909
A65: DE11C | B65: 3 | C65: DE | D65: Heidenheim | E65: Heidenheim | F65: 0.24362683 | H65: 0.24362683 | M65: 0.27336423 | O65: 0.27336423 | T65: 0.45421807 | V65: 0.45421807
A66: DE122 | B66: 3 | C66: DE | D66: Karlsruhe, Stadtkreis | E66: Karlsruhe, Stadtkreis | F66: 1.4191704 | J66: 1.4191704 | M66: 10.505327 | Q66: 10.505327 | T66: 20.544666 | X66: 20.544666
A67: DE123 | B67: 3 | C67: DE | D67: Karlsruhe, Landkreis | E67: Karlsruhe, Landkreis | F67: 0.21306672 | H67: 0.21306672 | M67: 0.23907391 | O67: 0.23907391 | T67: 0.39724177 | V67: 0.39724177
A68: DE126 | B68: 3 | C68: DE | D68: Mannheim, Stadtkreis | E68: Mannheim, Stadtkreis | F68: 0.070893672 | I68: 0.070893672 | M68: 0.092015473 | P68: 0.092015473 | T68: 0.22047883 | W68: 0.22047883
A69: DE128 | B69: 3 | C69: DE | D69: Rhein-Neckar-Kreis | E69: Rhein-Neckar-Kreis | F69: 0.22393214 | H69: 0.22393214 | M69: 0.25126558 | O69: 0.25126558 | T69: 0.41749927 | V69: 0.41749927
A70: DE131 | B70: 3 | C70: DE | D70: Freiburg im Breisgau, Stadtkreis | E70: Freiburg im Breisgau, Stadtkreis | F70: 0.079474115 | L70: 0.079474115 | M70: 0.11260432 | S70: 0.11260432 | T70: 0.18766951 | Z70: 0.18766951
A71: DE134 | B71: 3 | C71: DE | D71: Ortenaukreis | E71: Ortenaukreis | F71: 3.2227305 | G71: 3.2227305 | M71: 3.2227305 | N71: 3.2227305 | T71: 3.2227305 | U71: 3.2227305
A72: DE143 | B72: 3 | C72: DE | D72: Zollernalbkreis | E72: Zollernalbkreis | F72: 0.325118 | H72: 0.325118 | M72: 0.36480232 | O72: 0.36480232 | T72: 0.60615027 | V72: 0.60615027
A73: DE145 | B73: 3 | C73: DE | D73: Alb-Donau-Kreis | E73: Alb-Donau-Kreis | F73: 0.63008759 | H73: 0.63008759 | M73: 0.70699688 | O73: 0.70699688 | T73: 1.1747358 | V73: 1.1747358
A74: DE148 | B74: 3 | C74: DE | D74: Ravensburg | E74: Ravensburg | F74: 0.34758496 | I74: 0.34758496 | M74: 0.4180134 | P74: 0.4180134 | T74: 0.84635597 | W74: 0.84635597
A75: DE214 | B75: 3 | C75: DE | D75: Altötting | E75: Altötting | F75: 2.1667435 | J75: 0.33876971 | L75: 1.8279738 | M75: 12.979225 | Q75: 2.5077233 | S75: 10.471502 | T75: 34.949973 | X75: 4.9042107 | Z75: 30.045762
A76: DE219 | B76: 3 | C76: DE | D76: Eichstätt | E76: Eichstätt | F76: 0.62589314 | I76: 0.12231655 | J76: 0.50357659 | M76: 3.8747974 | P76: 0.1471006 | Q76: 3.7276968 | T76: 7.5878789 | W76: 0.29783607 | X76: 7.2900429
A77: DE21I | B77: 3 | C77: DE | D77: Neuburg-Schrobenhausen | E77: Neuburg-Schrobenhausen | F77: 0.24606589 | I77: 0.24606589 | M77: 0.29592431 | P77: 0.29592431 | T77: 0.59916096 | W77: 0.59916096
A78: DE21J | B78: 3 | C78: DE | D78: Pfaffenhofen a. d. Ilm | E78: Pfaffenhofen a. d. Ilm | F78: 0.21892317 | L78: 0.21892317 | M78: 1.183878 | S78: 1.183878 | T78: 3.3691162 | Z78: 3.3691162
A79: DE21K | B79: 3 | C79: DE | D79: Rosenheim, Landkreis | E79: Rosenheim, Landkreis | F79: 0.36045949 | H79: 0.36045949 | M79: 0.40445763 | O79: 0.40445763 | T79: 0.67204098 | V79: 0.67204098
A80: DE226 | B80: 3 | C80: DE | D80: Kelheim | E80: Kelheim | F80: 0.42117315 | J80: 0.42117315 | M80: 3.11771 | Q80: 3.11771 | T80: 6.0971268 | X80: 6.0971268
A81: DE229 | B81: 3 | C81: DE | D81: Regen | E81: Regen | F81: 0.09600479 | I81: 0.09600479 | M81: 0.11545749 | P81: 0.11545749 | T81: 0.23376796 | W81: 0.23376796
A82: DE237 | B82: 3 | C82: DE | D82: Neustadt a. d. Waldnaab | E82: Neustadt a. d. Waldnaab | F82: 0.36066609 | I82: 0.36066609 | M82: 0.46812161 | P82: 0.46812161 | T82: 1.121669 | W82: 1.121669
A83: DE239 | B83: 3 | C83: DE | D83: Schwandorf | E83: Schwandorf | F83: 0.38708958 | H83: 0.38708958 | M83: 0.43433823 | O83: 0.43433823 | T83: 0.72169014 | V83: 0.72169014
A84: DE24A | B84: 3 | C84: DE | D84: Kronach | E84: Kronach | F84: 0.51060911 | I84: 0.51060911 | M84: 0.61406987 | P84: 0.61406987 | T84: 1.2433135 | W84: 1.2433135
A85: DE24D | B85: 3 | C85: DE | D85: Wunsiedel i. Fichtelgebirge | E85: Wunsiedel i. Fichtelgebirge | F85: 0.030096004 | I85: 0.030096004 | M85: 0.039062696 | P85: 0.039062696 | T85: 0.093598364 | W85: 0.093598364
A86: DE25C | B86: 3 | C86: DE | D86: Weißenburg-Gunzenhausen | E86: Weißenburg-Gunzenhausen | F86: 0.13977532 | H86: 0.13977532 | M86: 0.15683647 | O86: 0.15683647 | T86: 0.26059721 | V86: 0.26059721
A87: DE26A | B87: 3 | C87: DE | D87: Main-Spessart | E87: Main-Spessart | F87: 0.78719068 | H87: 0.57054318 | I87: 0.2166475 | M87: 0.90072951 | O87: 0.6401844 | P87: 0.26054511 | T87: 1.5912495 | V87: 1.0637212 | W87: 0.52752832
A88: DE276 | B88: 3 | C88: DE | D88: Augsburg, Landkreis | E88: Augsburg, Landkreis | F88: 1.5211288 | G88: 1.5211288 | M88: 1.5211288 | N88: 1.5211288 | T88: 1.5211288 | U88: 1.5211288
A89: DE27D | B89: 3 | C89: DE | D89: Donau-Ries | E89: Donau-Ries | F89: 0.27568114 | H89: 0.27568114 | M89: 0.30933113 | O89: 0.30933113 | T89: 0.51398015 | V89: 0.51398015
A90: DE401 | B90: 3 | C90: DE | D90: Brandenburg an der Havel, Kreisfreie Stadt | E90: Brandenburg an der Havel, Kreisfreie Stadt | F90: 2.3203659 | G90: 2.3203659 | M90: 2.3203659 | N90: 2.3203659 | T90: 2.3203659 | U90: 2.3203659
A91: DE409 | B91: 3 | C91: DE | D91: Märkisch-Oderland | E91: Märkisch-Oderland | F91: 0.69074228 | H91: 0.54748721 | I91: 0.14325508 | M91: 0.78659593 | O91: 0.61431419 | P91: 0.17228174 | T91: 1.3695562 | V91: 1.0207356 | W91: 0.34882059
A92: DE40A | B92: 3 | C92: DE | D92: Oberhavel | E92: Oberhavel | F92: 1.2890922 | G92: 1.2890922 | M92: 1.2890922 | N92: 1.2890922 | T92: 1.2890922 | U92: 1.2890922
A93: DE40C | B93: 3 | C93: DE | D93: Oder-Spree | E93: Oder-Spree | F93: 1.5156468 | G93: 1.5156468 | M93: 2.4102501 | N93: 2.4102501 | T93: 6.1404016 | U93: 6.1404016
A94: DE40G | B94: 3 | C94: DE | D94: Spree-Neiße | E94: Spree-Neiße | F94: 0.22585356 | I94: 0.22585356 | M94: 0.27729106 | P94: 0.27729106 | T94: 0.59013291 | W94: 0.59013291
A95: DE40I | B95: 3 | C95: DE | D95: Uckermark | E95: Uckermark | F95: 1.0071532 | J95: 1.0071532 | M95: 7.4553936 | Q95: 7.4553936 | T95: 14.580086 | X95: 14.580086
A96: DE501 | B96: 3 | C96: DE | D96: Bremen, Kreisfreie Stadt | E96: Bremen, Kreisfreie Stadt | F96: 2.399774 | G96: 2.399774 | M96: 3.8162293 | N96: 3.8162293 | T96: 9.7223026 | U96: 9.7223026
A97: DE600 | B97: 3 | C97: DE | D97: Hamburg | E97: Hamburg | F97: 1.6194212 | G97: 0.69467143 | J97: 0.92474974 | M97: 7.9501048 | N97: 1.1046979 | Q97: 6.8454068 | T97: 16.20152 | U97: 2.8143507 | X97: 13.38717
A98: DE712 | B98: 3 | C98: DE | D98: Frankfurt am Main, Kreisfreie Stadt | E98: Frankfurt am Main, Kreisfreie Stadt | F98: 0.43620867 | L98: 0.43620867 | M98: 2.9694168 | S98: 2.9694168 | T98: 8.7061608 | Z98: 8.7061608
A99: DE714 | B99: 3 | C99: DE | D99: Wiesbaden, Kreisfreie Stadt | E99: Wiesbaden, Kreisfreie Stadt | F99: 0.085427577 | H99: 0.085427577 | M99: 0.095854976 | O99: 0.095854976 | T99: 0.15927125 | V99: 0.15927125
A100: DE722 | B100: 3 | C100: DE | D100: Lahn-Dill-Kreis | E100: Lahn-Dill-Kreis | F100: 0.51563687 | G100: 0.51563687 | M100: 0.51563687 | N100: 0.51563687 | T100: 0.51563687 | U100: 0.51563687
A101: DE732 | B101: 3 | C101: DE | D101: Fulda | E101: Fulda | F101: 0.060767743 | H101: 0.060767743 | M101: 0.06818513 | O101: 0.06818513 | T101: 0.11329543 | V101: 0.11329543
A102: DE80M | B102: 3 | C102: DE | D102: Nordwestmecklenburg | E102: Nordwestmecklenburg | F102: 0.11832492 | L102: 0.11832492 | M102: 0.42373055 | S102: 0.42373055 | T102: 1.1153909 | Z102: 1.1153909
A103: DE80O | B103: 3 | C103: DE | D103: Ludwigslust-Parchim | E103: Ludwigslust-Parchim | F103: 0.11728304 | I103: 0.11728304 | M103: 0.13017233 | P103: 0.13017233 | T103: 0.20852337 | W103: 0.20852337
A104: DE912 | B104: 3 | C104: DE | D104: Salzgitter, Kreisfreie Stadt | E104: Salzgitter, Kreisfreie Stadt | F104: 3.5365091 | G104: 3.5365091 | M104: 5.6239168 | N104: 5.6239168 | T104: 14.327604 | U104: 14.327604
A105: DE91A | B105: 3 | C105: DE | D105: Peine | E105: Peine | F105: 1.2890922 | G105: 1.2890922 | M105: 1.2890922 | N105: 1.2890922 | T105: 1.2890922 | U105: 1.2890922
A106: DE91C | B106: 3 | C106: DE | D106: Göttingen | E106: Göttingen | F106: 0.023219708 | L106: 0.023219708 | M106: 0.02453453 | S106: 0.02453453 | T106: 0.027512263 | Z106: 0.027512263
A107: DE922 | B107: 3 | C107: DE | D107: Diepholz | E107: Diepholz | F107: 0.023219708 | L107: 0.023219708 | M107: 0.02453453 | S107: 0.02453453 | T107: 0.027512263 | Z107: 0.027512263
A108: DE923 | B108: 3 | C108: DE | D108: Hameln-Pyrmont | E108: Hameln-Pyrmont | F108: 0.065750823 | I108: 0.065750823 | M108: 0.079073402 | P108: 0.079073402 | T108: 0.16010072 | W108: 0.16010072
A109: DE926 | B109: 3 | C109: DE | D109: Holzminden | E109: Holzminden | F109: 0.39448173 | I109: 0.39448173 | M109: 0.4744125 | P109: 0.4744125 | T109: 0.9605478 | W109: 0.9605478
A110: DE927 | B110: 3 | C110: DE | D110: Nienburg (Weser) | E110: Nienburg (Weser) | F110: 0.39424629 | I110: 0.33799189 | L110: 0.056254407 | M110: 0.49454635 | P110: 0.40647656 | S110: 0.088069791 | T110: 0.98315446 | W110: 0.82299721 | Z110: 0.16015725
A111: DE928 | B111: 3 | C111: DE | D111: Schaumburg | E111: Schaumburg | F111: 0.39026546 | I111: 0.39026546 | M111: 0.46934192 | P111: 0.46934192 | T111: 0.95028134 | W111: 0.95028134
...

Sheet Hydrogen (PJ per y)
F12: 2018 | M12: 2030 | T12: 2050
A13: NUTS ID | B13: NUTS LEVEL | C13: Country code | D13: NUTS region name (Latin) | E13: NUTS_NAME | F13: All sectors (PJ/y) | G13: Steel (PJ/y) | H13: Cement (PJ/y) | I13: Glass (PJ/y) | J13: Refineries (PJ/y) | K13: Fertilisers (PJ/y) | L13: Chemical (PJ/y) | M13: All sectors (PJ/y) | N13: Steel (PJ/y) | O13: Cement (PJ/y) | P13: Glass (PJ/y) | Q13: Refineries (PJ/y) | R13: Fertilisers (PJ/y) | S13: Chemical (PJ/y) | T13: All sectors (PJ/y) | U13: Steel (PJ/y) | V13: Cement (PJ/y) | W13: Glass (PJ/y) | X13: Refineries (PJ/y) | Y13: Fertilisers (PJ/y) | Z13: Chemical (PJ/y)
A14: AT121 | B14: 3 | C14: AT | D14: Mostviertel-Eisenwurzen | E14: Mostviertel-Eisenwurzen | F14: 0.008446715 | I14: 0.008446715 | M14: 0.059577989 | P14: 0.059577989 | T14: 0.37055546 | W14: 0.37055546
A15: AT122 | B15: 3 | C15: AT | D15: Niederösterreich-Süd | E15: Niederösterreich-Süd | F15: 0 | H15: 0 | M15: 0 | O15: 0 | T15: 0 | V15: 0
A16: AT124 | B16: 3 | C16: AT | D16: Waldviertel | E16: Waldviertel | F16: 0.00028158 | L16: 0.00028158 | M16: 0.038183538 | S16: 0.038183538 | T16: 0.12405894 | Z16: 0.12405894
A17: AT127 | B17: 3 | C17: AT | D17: Wiener Umland/Südteil | E17: Wiener Umland/Südteil | F17: 0.00028158 | H17: 0 | J17: 0 | L17: 0.00028158 | M17: 1.1906385 | O17: 0 | Q17: 0.32403534 | S17: 0.86660313 | T17: 3.2395763 | V17: 0 | X17: 0.41071599 | Z17: 2.8288603
A18: AT213 | B18: 3 | C18: AT | D18: Unterkärnten | E18: Unterkärnten | F18: 0 | H18: 0 | M18: 0 | O18: 0 | T18: 0 | V18: 0
A19: AT221 | B19: 3 | C19: AT | D19: Graz | E19: Graz | F19: 0 | G19: 0 | M19: 0 | N19: 0 | T19: 0 | U19: 0
A20: AT223 | B20: 3 | C20: AT | D20: Östliche Obersteiermark | E20: Östliche Obersteiermark | F20: 0 | G20: 0 | M20: 0.36946785 | N20: 0.36946785 | T20: 8.5999848 | U20: 8.5999848
A21: AT225 | B21: 3 | C21: AT | D21: West- und Südsteiermark | E21: West- und Südsteiermark | F21: 0.007336853 | H21: 0 | I21: 0.007336853 | M21: 0.051749695 | O21: 0 | P21: 0.051749695 | T21: 0.32186605 | V21: 0 | W21: 0.32186605
A22: AT312 | B22: 3 | C22: AT | D22: Linz-Wels | E22: Linz-Wels | F22: 0 | G22: 0 | K22: 0 | L22: 0 | M22: 3.3410438 | N22: 1.411979 | R22: 1.8926883 | S22: 0.036376502 | T22: 39.165332 | U22: 32.866184 | Y22: 6.1803508 | Z22: 0.11879741
A23: AT314 | B23: 3 | C23: AT | D23: Steyr-Kirchdorf | E23: Steyr-Kirchdorf | F23: 0.009616008 | H23: 0 | I23: 0.009616008 | M23: 0.06782547 | O23: 0 | P23: 0.06782547 | T23: 0.42185208 | V23: 0 | W23: 0.42185208
A24: AT315 | B24: 3 | C24: AT | D24: Traunviertel | E24: Traunviertel | F24: 0 | H24: 0 | M24: 0 | O24: 0 | T24: 0 | V24: 0
A25: AT323 | B25: 3 | C25: AT | D25: Salzburg und Umgebung | E25: Salzburg und Umgebung | F25: 0 | H25: 0 | M25: 0 | O25: 0 | T25: 0 | V25: 0
A26: AT331 | B26: 3 | C26: AT | D26: Außerfern | E26: Außerfern | F26: 0 | H26: 0 | M26: 0 | O26: 0 | T26: 0 | V26: 0
A27: BE211 | B27: 3 | C27: BE | D27: Arr. Antwerpen | E27: Arr. Antwerpen | F27: 0.025697213 | J27: 0 | K27: 0 | L27: 0.025697213 | M27: 11.36171 | Q27: 1.2994819 | R27: 2.7291828 | S27: 7.3330452 | T27: 34.447426 | X27: 1.6470982 | Y27: 8.9118253 | Z27: 23.888503
A28: BE213 | B28: 3 | C28: BE | D28: Arr. Turnhout | E28: Arr. Turnhout | F28: 0.013032831 | I28: 0.007425022 | L28: 0.005607809 | M28: 1.3408095 | P28: 0.056128498 | S28: 1.284681 | T28: 4.53508 | W28: 0.35234581 | Z28: 4.1827342
A29: BE224 | B29: 3 | C29: BE | D29: Arr. Hasselt | E29: Arr. Hasselt | F29: 0.00195318 | G29: 0 | L29: 0.00195318 | M29: 0.085287524 | N29: 0 | S29: 0.085287524 | T29: 0.27409146 | U29: 0 | Z29: 0.27409146
A30: BE233 | B30: 3 | C30: BE | D30: Arr. Eeklo | E30: Arr. Eeklo | F30: 0.00028158 | L30: 0.00028158 | M30: 0.062001752 | S30: 0.062001752 | T30: 0.20182573 | Z30: 0.20182573
A31: BE234 | B31: 3 | C31: BE | D31: Arr. Gent | E31: Arr. Gent | F31: 0 | G31: 0 | L31: 0 | M31: 1.612325 | N31: 1.5285201 | S31: 0.083804896 | T31: 35.85256 | U31: 35.578872 | Z31: 0.27368778
A32: BE236 | B32: 3 | C32: BE | D32: Arr. Sint-Niklaas | E32: Arr. Sint-Niklaas | F32: 0.000563159 | L32: 0.000563159 | M32: 0.92965817 | S32: 0.92965817 | T32: 3.0347731 | Z32: 3.0347731
A33: BE255 | B33: 3 | C33: BE | D33: Arr. Oostende | E33: Arr. Oostende | F33: 0 | L33: 0 | M33: 0.036376502 | S33: 0.036376502 | T33: 0.11879741 | Z33: 0.11879741
A34: BE323 | B34: 3 | C34: BE | D34: Arr. Mons | E34: Arr. Mons | F34: 0.009189809 | H34: 0 | I34: 0.008908229 | K34: 0 | L34: 0.00028158 | M34: 1.4894264 | O34: 0 | P34: 0.062833226 | R34: 1.3645914 | S34: 0.062001752 | T34: 5.0485403 | V34: 0 | W34: 0.39080197 | Y34: 4.4559126 | Z34: 0.20182573
A35: BE328 | B35: 3 | C35: BE | D35: Arr. Tournai-Mouscron | E35: Arr. Tournai-Mouscron | F35: 0 | H35: 0 | M35: 0 | O35: 0 | T35: 0 | V35: 0
A36: BE32B | B36: 3 | C36: BE | D36: Arr. Charleroi | E36: Arr. Charleroi | F36: 0 | G36: 0 | M36: 0 | N36: 0 | T36: 0 | U36: 0
A37: BE32C | B37: 3 | C37: BE | D37: Arr. Soignies | E37: Arr. Soignies | F37: 0.002189258 | I37: 0.002189258 | L37: 0 | M37: 0.3716125 | P37: 0.015441692 | S37: 0.35617081 | T37: 1.2592153 | W37: 0.096042234 | Z37: 1.1631731
A38: BE32D | B38: 3 | C38: BE | D38: Arr. Thuin | E38: Arr. Thuin | F38: 0.003309459 | I38: 0.003309459 | M38: 0.02334291 | P38: 0.02334291 | T38: 0.14518521 | W38: 0.14518521
A39: BE332 | B39: 3 | C39: BE | D39: Arr. Liège | E39: Arr. Liège | F39: 0 | H39: 0 | M39: 0 | O39: 0 | T39: 0 | V39: 0
A40: BE335 | B40: 3 | C40: BE | D40: Arr. Verviers — communes francophones | E40: Arr. Verviers — communes francophones | F40: 0.006550075 | I40: 0.006550075 | M40: 0.07130858 | P40: 0.07130858 | T40: 0.46486522 | W40: 0.46486522
A41: BE352 | B41: 3 | C41: BE | D41: Arr. Namur | E41: Arr. Namur | F41: 0.040043403 | I41: 0.033297303 | L41: 0.0067461 | M41: 0.29499974 | P41: 0.25170668 | S41: 0.043293058 | T41: 1.706141 | W41: 1.580085 | Z41: 0.12605603
A42: BG313 | B42: 3 | C42: BG | D42: Vratsa | E42: Враца | F42: 0 | H42: 0 | M42: 0 | O42: 0 | T42: 0 | V42: 0
A43: BG314 | B43: 3 | C43: BG | D43: Pleven | E43: Плевен | F43: 0.005506563 | I43: 0.005506563 | M43: 0.038839941 | P43: 0.038839941 | T43: 0.24157164 | W43: 0.24157164
A44: BG315 | B44: 3 | C44: BG | D44: Lovech | E44: Ловеч | F44: 0 | H44: 0 | M44: 0 | O44: 0 | T44: 0 | V44: 0
A45: BG331 | B45: 3 | C45: BG | D45: Varna | E45: Варна | F45: 0 | H45: 0 | K45: 0 | M45: 1.3816488 | O45: 0 | R45: 1.3816488 | T45: 4.5116115 | V45: 0 | Y45: 4.5116115
A46: BG333 | B46: 3 | C46: BG | D46: Shumen | E46: Шумен | F46: 0.003318845 | I46: 0.003318845 | M46: 0.023409111 | P46: 0.023409111 | T46: 0.14559696 | W46: 0.14559696
A47: BG334 | B47: 3 | C47: BG | D47: Targovishte | E47: Търговище | F47: 0.03137654 | I47: 0.03137654 | M47: 0.23373444 | P47: 0.23373444 | T47: 1.464482 | W47: 1.464482
A48: BG341 | B48: 3 | C48: BG | D48: Burgas | E48: Бургас | F48: 0 | J48: 0 | M48: 0.32737591 | Q48: 0.32737591 | T48: 0.41495018 | X48: 0.41495018
A49: BG411 | B49: 3 | C49: BG | D49: Sofia (stolitsa) | E49: София (столица) | F49: 0.005407646 | I49: 0.005407646 | M49: 0.038142243 | P49: 0.038142243 | T49: 0.23723218 | W49: 0.23723218
A50: BG414 | B50: 3 | C50: BG | D50: Pernik | E50: Перник | F50: 0 | G50: 0 | M50: 0 | N50: 0 | T50: 0 | U50: 0
A51: BG421 | B51: 3 | C51: BG | D51: Plovdiv | E51: Пловдив | F51: 0.01670326 | I51: 0.01670326 | M51: 0.11781463 | P51: 0.11781463 | T51: 0.73276816 | W51: 0.73276816
A52: BG422 | B52: 3 | C52: BG | D52: Haskovo | E52: Хасково | F52: 0 | K52: 0 | M52: 1.5351653 | R52: 1.5351653 | T52: 5.0129017 | Y52: 5.0129017
A53: CY000 | B53: 3 | C53: CY | D53: Kýpros | E53: Κύπρος | F53: 0 | H53: 0 | M53: 0 | O53: 0 | T53: 0 | V53: 0
A54: CZ010 | B54: 3 | C54: CZ | D54: Hlavní město Praha | E54: Hlavní město Praha | F54: 0 | H54: 0 | M54: 0 | O54: 0 | T54: 0 | V54: 0
A55: CZ020 | B55: 3 | C55: CZ | D55: Středočeský kraj | E55: Středočeský kraj | F55: 0.001482117 | I55: 0.000918958 | J55: 0 | L55: 0.000563159 | M55: 0.22024646 | P55: 0.006481771 | Q55: 0.1135794 | S55: 0.10018529 | T55: 0.51016146 | W55: 0.040314481 | X55: 0.14396231 | Z55: 0.32588467
A56: CZ032 | B56: 3 | C56: CZ | D56: Plzeňský kraj | E56: Plzeňský kraj | F56: 0.003173953 | G56: 0 | I56: 0.003173953 | M56: 0.02238713 | N56: 0 | P56: 0.02238713 | T56: 0.13924057 | U56: 0 | W56: 0.13924057
A57: CZ041 | B57: 3 | C57: CZ | D57: Karlovarský kraj | E57: Karlovarský kraj | F57: 0.007954918 | I57: 0.007954918 | M57: 0.056109149 | P57: 0.056109149 | T57: 0.34898042 | W57: 0.34898042
A58: CZ042 | B58: 3 | C58: CZ | D58: Ústecký kraj | E58: Ústecký kraj | F58: 0.033320942 | H58: 0 | I58: 0.033320942 | J58: 0 | L58: 0 | M58: 1.3397105 | O58: 0 | P58: 0.25799922 | Q58: 0.18039081 | S58: 0.90132052 | T58: 4.7958563 | V58: 0 | W58: 1.6243864 | X58: 0.22864602 | Z58: 2.9428239
A59: CZ051 | B59: 3 | C59: CZ | D59: Liberecký kraj | E59: Liberecký kraj | F59: 0.001507216 | I59: 0.001507216 | M59: 0.010630984 | P59: 0.010630984 | T59: 0.066121217 | W59: 0.066121217
A60: CZ053 | B60: 3 | C60: CZ | D60: Pardubický kraj | E60: Pardubický kraj | F60: 0.005297244 | H60: 0 | I60: 0.005297244 | J60: 0 | M60: 0.084393973 | O60: 0 | P60: 0.057669409 | Q60: 0.026724564 | T60: 0.40982407 | V60: 0 | W60: 0.37595059 | X60: 0.033873484
A61: CZ063 | B61: 3 | C61: CZ | D61: Kraj Vysočina | E61: Kraj Vysočina | F61: 0.002463167 | I61: 0.002463167 | M61: 0.017373681 | P61: 0.017373681 | T61: 0.10805857 | W61: 0.10805857
A62: CZ064 | B62: 3 | C62: CZ | D62: Jihomoravský kraj | E62: Jihomoravský kraj | F62: 0.015557416 | H62: 0 | I62: 0.015557416 | M62: 0.1196414 | O62: 0 | P62: 0.1196414 | T62: 0.75255546 | V62: 0 | W62: 0.75255546
A63: CZ071 | B63: 3 | C63: CZ | D63: Olomoucký kraj | E63: Olomoucký kraj | F63: 0.00028158 | H63: 0 | L63: 0.00028158 | M63: 0.062001752 | O63: 0 | S63: 0.062001752 | T63: 0.20182573 | V63: 0 | Z63: 0.20182573
A64: CZ080 | B64: 3 | C64: CZ | D64: Moravskoslezský kraj | E64: Moravskoslezský kraj | F64: 0.004370684 | G64: 0 | I64: 0.004089104 | K64: 0 | L64: 0.00028158 | M64: 2.6542857 | N64: 1.3537497 | P64: 0.044516772 | R64: 1.1940175 | S64: 0.062001752 | T64: 35.901754 | U64: 31.510797 | W64: 0.2902077 | Y64: 3.8989236 | Z64: 0.20182573
A65: DE11C | B65: 3 | C65: DE | D65: Heidenheim | E65: Heidenheim | F65: 0 | H65: 0 | M65: 0 | O65: 0 | T65: 0 | V65: 0
A66: DE122 | B66: 3 | C66: DE | D66: Karlsruhe, Stadtkreis | E66: Karlsruhe, Stadtkreis | F66: 0 | J66: 0 | M66: 0.51778843 | Q66: 0.51778843 | T66: 0.65629875 | X66: 0.65629875
A67: DE123 | B67: 3 | C67: DE | D67: Karlsruhe, Landkreis | E67: Karlsruhe, Landkreis | F67: 0 | H67: 0 | M67: 0 | O67: 0 | T67: 0 | V67: 0
A68: DE126 | B68: 3 | C68: DE | D68: Mannheim, Stadtkreis | E68: Mannheim, Stadtkreis | F68: 0.003903055 | I68: 0.003903055 | M68: 0.029504643 | P68: 0.029504643 | T68: 0.18521496 | W68: 0.18521496
A69: DE128 | B69: 3 | C69: DE | D69: Rhein-Neckar-Kreis | E69: Rhein-Neckar-Kreis | F69: 0 | H69: 0 | M69: 0 | O69: 0 | T69: 0 | V69: 0
A70: DE131 | B70: 3 | C70: DE | D70: Freiburg im Breisgau, Stadtkreis | E70: Freiburg im Breisgau, Stadtkreis | F70: 0.00028158 | L70: 0.00028158 | M70: 0.038183538 | S70: 0.038183538 | T70: 0.12405894 | Z70: 0.12405894
A71: DE134 | B71: 3 | C71: DE | D71: Ortenaukreis | E71: Ortenaukreis | F71: 0 | G71: 0 | M71: 0 | N71: 0 | T71: 0 | U71: 0
A72: DE143 | B72: 3 | C72: DE | D72: Zollernalbkreis | E72: Zollernalbkreis | F72: 0 | H72: 0 | M72: 0 | O72: 0 | T72: 0 | V72: 0
A73: DE145 | B73: 3 | C73: DE | D73: Alb-Donau-Kreis | E73: Alb-Donau-Kreis | F73: 0 | H73: 0 | M73: 0 | O73: 0 | T73: 0 | V73: 0
A74: DE148 | B74: 3 | C74: DE | D74: Ravensburg | E74: Ravensburg | F74: 0.014275069 | I74: 0.014275069 | M74: 0.10068765 | P74: 0.10068765 | T74: 0.626244 | W74: 0.626244
A75: DE214 | B75: 3 | C75: DE | D75: Altötting | E75: Altötting | F75: 0.005373 | J75: 0 | L75: 0.005373 | M75: 1.0127894 | Q75: 0.12360111 | S75: 0.88918834 | T75: 3.0477769 | X75: 0.15666486 | Z75: 2.8911121
A76: DE219 | B76: 3 | C76: DE | D76: Eichstätt | E76: Eichstätt | F76: 0.005023454 | I76: 0.005023454 | J76: 0 | M76: 0.21916377 | P76: 0.035432389 | Q76: 0.18373138 | T76: 0.45325799 | W76: 0.22037779 | X76: 0.2328802
A77: DE21I | B77: 3 | C77: DE | D77: Neuburg-Schrobenhausen | E77: Neuburg-Schrobenhausen | F77: 0.010105753 | I77: 0.010105753 | M77: 0.071279829 | P77: 0.071279829 | T77: 0.44333705 | W77: 0.44333705
A78: DE21J | B78: 3 | C78: DE | D78: Pfaffenhofen a. d. Ilm | E78: Pfaffenhofen a. d. Ilm | F78: 0.000993133 | L78: 0.000993133 | M78: 0.090380443 | S78: 0.090380443 | T78: 0.29284152 | Z78: 0.29284152
A79: DE21K | B79: 3 | C79: DE | D79: Rosenheim, Landkreis | E79: Rosenheim, Landkreis | F79: 0 | H79: 0 | M79: 0 | O79: 0 | T79: 0 | V79: 0
A80: DE226 | B80: 3 | C80: DE | D80: Kelheim | E80: Kelheim | F80: 0 | J80: 0 | M80: 0.15366624 | Q80: 0.15366624 | T80: 0.19477253 | X80: 0.19477253
A81: DE229 | B81: 3 | C81: DE | D81: Regen | E81: Regen | F81: 0.003942849 | I81: 0.003942849 | M81: 0.027810457 | P81: 0.027810457 | T81: 0.17297188 | W81: 0.17297188
A82: DE237 | B82: 3 | C82: DE | D82: Neustadt a. d. Waldnaab | E82: Neustadt a. d. Waldnaab | F82: 0.019856491 | I82: 0.019856491 | M82: 0.1501026 | P82: 0.1501026 | T82: 0.94226682 | W82: 0.94226682
A83: DE239 | B83: 3 | C83: DE | D83: Schwandorf | E83: Schwandorf | F83: 0 | H83: 0 | M83: 0 | O83: 0 | T83: 0 | V83: 0
A84: DE24A | B84: 3 | C84: DE | D84: Kronach | E84: Kronach | F84: 0.020970356 | I84: 0.020970356 | M84: 0.14791213 | P84: 0.14791213 | T84: 0.91996471 | W84: 0.91996471
A85: DE24D | B85: 3 | C85: DE | D85: Wunsiedel i. Fichtelgebirge | E85: Wunsiedel i. Fichtelgebirge | F85: 0.001656937 | I85: 0.001656937 | M85: 0.012525404 | P85: 0.012525404 | T85: 0.078628035 | W85: 0.078628035
A86: DE25C | B86: 3 | C86: DE | D86: Weißenburg-Gunzenhausen | E86: Weißenburg-Gunzenhausen | F86: 0 | H86: 0 | M86: 0 | O86: 0 | T86: 0 | V86: 0
A87: DE26A | B87: 3 | C87: DE | D87: Main-Spessart | E87: Main-Spessart | F87: 0.00889756 | H87: 0 | I87: 0.00889756 | M87: 0.062757974 | O87: 0 | P87: 0.062757974 | T87: 0.39033392 | V87: 0 | W87: 0.39033392
A88: DE276 | B88: 3 | C88: DE | D88: Augsburg, Landkreis | E88: Augsburg, Landkreis | F88: 0 | G88: 0 | M88: 0 | N88: 0 | T88: 0 | U88: 0
A89: DE27D | B89: 3 | C89: DE | D89: Donau-Ries | E89: Donau-Ries | F89: 0 | H89: 0 | M89: 0 | O89: 0 | T89: 0 | V89: 0
A90: DE401 | B90: 3 | C90: DE | D90: Brandenburg an der Havel, Kreisfreie Stadt | E90: Brandenburg an der Havel, Kreisfreie Stadt | F90: 0 | G90: 0 | M90: 0 | N90: 0 | T90: 0 | U90: 0
A91: DE409 | B91: 3 | C91: DE | D91: Märkisch-Oderland | E91: Märkisch-Oderland | F91: 0.005883385 | H91: 0 | I91: 0.005883385 | M91: 0.041497817 | O91: 0 | P91: 0.041497817 | T91: 0.25810275 | V91: 0 | W91: 0.25810275
A92: DE40A | B92: 3 | C92: DE | D92: Oberhavel | E92: Oberhavel | F92: 0 | G92: 0 | M92: 0 | N92: 0 | T92: 0 | U92: 0
A93: DE40C | B93: 3 | C93: DE | D93: Oder-Spree | E93: Oder-Spree | F93: 0 | G93: 0 | M93: 0.65874846 | N93: 0.65874846 | T93: 15.333477 | U93: 15.333477
A94: DE40G | B94: 3 | C94: DE | D94: Spree-Neiße | E94: Spree-Neiße | F94: 0.010108293 | I94: 0.010108293 | M94: 0.072956205 | P94: 0.072956205 | T94: 0.45519606 | W94: 0.45519606
A95: DE40I | B95: 3 | C95: DE | D95: Uckermark | E95: Uckermark | F95: 0 | J95: 0 | M95: 0.36746276 | Q95: 0.36746276 | T95: 0.4657604 | X95: 0.4657604
A96: DE501 | B96: 3 | C96: DE | D96: Bremen, Kreisfreie Stadt | E96: Bremen, Kreisfreie Stadt | F96: 0 | G96: 0 | M96: 1.0430184 | N96: 1.0430184 | T96: 24.278005 | U96: 24.278005
A97: DE600 | B97: 3 | C97: DE | D97: Hamburg | E97: Hamburg | F97: 0 | G97: 0 | J97: 0 | M97: 0.639324 | N97: 0.30192638 | Q97: 0.33739762 | T97: 7.4554964 | U97: 7.0278437 | X97: 0.42765273
A98: DE712 | B98: 3 | C98: DE | D98: Frankfurt am Main, Kreisfreie Stadt | E98: Frankfurt am Main, Kreisfreie Stadt | F98: 0.00028158 | L98: 0.00028158 | M98: 0.25688631 | S98: 0.25688631 | T98: 0.8381265 | Z98: 0.8381265
A99: DE714 | B99: 3 | C99: DE | D99: Wiesbaden, Kreisfreie Stadt | E99: Wiesbaden, Kreisfreie Stadt | F99: 0 | H99: 0 | M99: 0 | O99: 0 | T99: 0 | V99: 0
A100: DE722 | B100: 3 | C100: DE | D100: Lahn-Dill-Kreis | E100: Lahn-Dill-Kreis | F100: 0 | G100: 0 | M100: 0 | N100: 0 | T100: 0 | U100: 0
A101: DE732 | B101: 3 | C101: DE | D101: Fulda | E101: Fulda | F101: 0 | H101: 0 | M101: 0 | O101: 0 | T101: 0 | V101: 0
A102: DE80M | B102: 3 | C102: DE | D102: Nordwestmecklenburg | E102: Nordwestmecklenburg | F102: 0.00028158 | L102: 0.00028158 | M102: 0.062001752 | S102: 0.062001752 | T102: 0.20182573 | Z102: 0.20182573
A103: DE80O | B103: 3 | C103: DE | D103: Ludwigslust-Parchim | E103: Ludwigslust-Parchim | F103: 0.002389099 | I103: 0.002389099 | M103: 0.026009361 | P103: 0.026009361 | T103: 0.1695567 | W103: 0.1695567
A104: DE912 | B104: 3 | C104: DE | D104: Salzgitter, Kreisfreie Stadt | E104: Salzgitter, Kreisfreie Stadt | F104: 0 | G104: 0 | M104: 1.5370798 | N104: 1.5370798 | T104: 35.778113 | U104: 35.778113
A105: DE91A | B105: 3 | C105: DE | D105: Peine | E105: Peine | F105: 0 | G105: 0 | M105: 0 | N105: 0 | T105: 0 | U105: 0
A106: DE91C | B106: 3 | C106: DE | D106: Göttingen | E106: Göttingen | F106: 0.00028158 | L106: 0.00028158 | M106: 0.001807036 | S106: 0.001807036 | T106: 0.00526153 | Z106: 0.00526153
A107: DE922 | B107: 3 | C107: DE | D107: Diepholz | E107: Diepholz | F107: 0.00028158 | L107: 0.00028158 | M107: 0.001807036 | S107: 0.001807036 | T107: 0.00526153 | Z107: 0.00526153
A108: DE923 | B108: 3 | C108: DE | D108: Hameln-Pyrmont | E108: Hameln-Pyrmont | F108: 0.00270034 | I108: 0.00270034 | M108: 0.019046555 | P108: 0.019046555 | T108: 0.11846329 | W108: 0.11846329
A109: DE926 | B109: 3 | C109: DE | D109: Holzminden | E109: Holzminden | F109: 0.016201087 | I109: 0.016201087 | M109: 0.1142726 | P109: 0.1142726 | T109: 0.71073794 | W109: 0.71073794
A110: DE927 | B110: 3 | C110: DE | D110: Nienburg (Weser) | E110: Nienburg (Weser) | F110: 0.013881089 | I110: 0.013881089 | L110: 0 | M110: 0.13428525 | P110: 0.09790875 | S110: 0.036376502 | T110: 0.72775757 | W110: 0.60896016 | Z110: 0.11879741
A111: DE928 | B111: 3 | C111: DE | D111: Schaumburg | E111: Schaumburg | F111: 0.016027927 | I111: 0.016027927 | M111: 0.11305124 | P111: 0.11305124 | T111: 0.70314148 | W111: 0.70314148
...

Sheet Natural gas (PJ per y)
F12: 2018 | M12: 2030 | T12: 2050
A13: NUTS ID | B13: NUTS LEVEL | C13: Country code | D13: NUTS region name (Latin) | E13: NUTS_NAME | F13: All sectors (PJ/y) | G13: Steel (PJ/y) | H13: Cement (PJ/y) | I13: Glass (PJ/y) | J13: Refineries (PJ/y) | K13: Fertilisers (PJ/y) | L13: Chemical (PJ/y) | M13: All sectors (PJ/y) | N13: Steel (PJ/y) | O13: Cement (PJ/y) | P13: Glass (PJ/y) | Q13: Refineries (PJ/y) | R13: Fertilisers (PJ/y) | S13: Chemical (PJ/y) | T13: All sectors (PJ/y) | U13: Steel (PJ/y) | V13: Cement (PJ/y) | W13: Glass (PJ/y) | X13: Refineries (PJ/y) | Y13: Fertilisers (PJ/y) | Z13: Chemical (PJ/y)
A14: AT121 | B14: 3 | C14: AT | D14: Mostviertel-Eisenwurzen | E14: Mostviertel-Eisenwurzen | F14: 0.90800462 | I14: 0.90800462 | M14: 0.81115685 | P14: 0.81115685 | T14: 0.22213425 | W14: 0.22213425
A15: AT122 | B15: 3 | C15: AT | D15: Niederösterreich-Süd | E15: Niederösterreich-Süd | F15: 0 | H15: 0 | M15: 0.002117016 | O15: 0.002117016 | T15: 0.014993034 | V15: 0.014993034
A16: AT124 | B16: 3 | C16: AT | D16: Waldviertel | E16: Waldviertel | F16: 0.36803446 | L16: 0.36803446 | M16: 0.29937551 | S16: 0.29937551 | T16: 0.14382092 | Z16: 0.14382092
A17: AT127 | B17: 3 | C17: AT | D17: Wiener Umland/Südteil | E17: Wiener Umland/Südteil | F17: 15.898821 | H17: 0 | J17: 15.530787 | L17: 0.36803446 | M17: 11.582432 | O17: 0.004392159 | Q17: 11.195718 | S17: 0.38232177 | T17: 2.3965457 | V17: 0.031105943 | X17: 1.9508471 | Z17: 0.41459259
A18: AT213 | B18: 3 | C18: AT | D18: Unterkärnten | E18: Unterkärnten | F18: 0 | H18: 0 | M18: 0.003176548 | O18: 0.003176548 | T18: 0.0224968 | V18: 0.0224968
A19: AT221 | B19: 3 | C19: AT | D19: Graz | E19: Graz | F19: 0.057827974 | G19: 0.057827974 | M19: 0.057827974 | N19: 0.057827974 | T19: 0.057827974 | U19: 0.057827974
A20: AT223 | B20: 3 | C20: AT | D20: Östliche Obersteiermark | E20: Östliche Obersteiermark | F20: 0.076047746 | G20: 0.076047746 | M20: 2.1231535 | N20: 2.1231535 | T20: 1.7912979 | U20: 1.7912979
A21: AT225 | B21: 3 | C21: AT | D21: West- und Südsteiermark | E21: West- und Südsteiermark | F21: 0.78869669 | H21: 0 | I21: 0.78869669 | M21: 0.70693083 | O21: 0.002356533 | P21: 0.7045743 | T21: 0.20963609 | V21: 0.016689328 | W21: 0.19294676
A22: AT312 | B22: 3 | C22: AT | D22: Linz-Wels | E22: Linz-Wels | F22: 11.199068 | G22: 0 | K22: 10.844735 | L22: 0.35433375 | M22: 16.445953 | N22: 7.8233339 | R22: 8.3341239 | S22: 0.28849541 | T22: 9.3412203 | U22: 6.5550961 | Y22: 2.646796 | Z22: 0.13932811
A23: AT314 | B23: 3 | C23: AT | D23: Steyr-Kirchdorf | E23: Steyr-Kirchdorf | F23: 1.0337012 | H23: 0 | I23: 1.0337012 | M23: 0.92507814 | O23: 0.001631475 | P23: 0.92344666 | T23: 0.26443902 | V23: 0.011554355 | W23: 0.25288467
A24: AT315 | B24: 3 | C24: AT | D24: Traunviertel | E24: Traunviertel | F24: 0 | H24: 0 | M24: 0.002381362 | O24: 0.002381362 | T24: 0.016865173 | V24: 0.016865173
A25: AT323 | B25: 3 | C25: AT | D25: Salzburg und Umgebung | E25: Salzburg und Umgebung | F25: 0 | H25: 0 | M25: 0.002254994 | O25: 0.002254994 | T25: 0.01597021 | V25: 0.01597021
A26: AT331 | B26: 3 | C26: AT | D26: Außerfern | E26: Außerfern | F26: 0 | H26: 0 | M26: 0.001556105 | O26: 0.001556105 | T26: 0.011020577 | V26: 0.011020577
A27: BE211 | B27: 3 | C27: BE | D27: Arr. Antwerpen | E27: Arr. Antwerpen | F27: 134.02329 | J27: 62.283258 | K27: 15.637685 | L27: 56.102345 | M27: 102.72261 | Q27: 44.898291 | R27: 12.017482 | S27: 45.806833 | T27: 34.120887 | X27: 7.8235003 | Y27: 3.8165768 | Z27: 22.48081
A28: BE213 | B28: 3 | C28: BE | D28: Arr. Turnhout | E28: Arr. Turnhout | F28: 13.352483 | I28: 0.91644342 | L28: 12.43604 | M28: 10.944033 | P28: 0.82419422 | S28: 10.119839 | T28: 5.1353003 | W28: 0.26312007 | Z28: 4.8721803
A29: BE224 | B29: 3 | C29: BE | D29: Arr. Hasselt | E29: Arr. Hasselt | F29: 0.98322688 | G29: 0.17952427 | L29: 0.80370261 | M29: 0.83198504 | N29: 0.17952427 | S29: 0.65246077 | T29: 0.4893449 | U29: 0.17952427 | Z29: 0.30982063
A30: BE233 | B30: 3 | C30: BE | D30: Arr. Eeklo | E30: Arr. Eeklo | F30: 0.36803446 | L30: 0.36803446 | M30: 0.30176033 | S30: 0.30176033 | T30: 0.15160598 | Z30: 0.15160598
A31: BE234 | B31: 3 | C31: BE | D31: Arr. Gent | E31: Arr. Gent | F31: 0.816321 | G31: 0 | L31: 0.816321 | M31: 9.1336927 | N31: 8.4690513 | S31: 0.66464135 | T31: 7.4171233 | U31: 7.0961365 | Z31: 0.32098682
A32: BE236 | B32: 3 | C32: BE | D32: Arr. Sint-Niklaas | E32: Arr. Sint-Niklaas | F32: 9.0477485 | L32: 9.0477485 | M32: 7.3660471 | S32: 7.3660471 | T32: 3.5558899 | Z32: 3.5558899
A33: BE255 | B33: 3 | C33: BE | D33: Arr. Oostende | E33: Arr. Oostende | F33: 0.35433375 | L33: 0.35433375 | M33: 0.28849541 | S33: 0.28849541 | T33: 0.13932811 | Z33: 0.13932811
A34: BE323 | B34: 3 | C34: BE | D34: Arr. Mons | E34: Arr. Mons | F34: 9.1444935 | H34: 0 | I34: 0.95761642 | K34: 7.8188426 | L34: 0.36803446 | M34: 7.1724582 | O34: 0.006479694 | P34: 0.85547705 | R34: 6.0087411 | S34: 0.30176033 | T34: 2.3400559 | V34: 0.045890183 | W34: 0.23427128 | Y34: 1.9082884 | Z34: 0.15160598
A35: BE328 | B35: 3 | C35: BE | D35: Arr. Tournai-Mouscron | E35: Arr. Tournai-Mouscron | F35: 0 | H35: 0 | M35: 0.01233451 | O35: 0.01233451 | T35: 0.087354883 | V35: 0.087354883
A36: BE32B | B36: 3 | C36: BE | D36: Arr. Charleroi | E36: Arr. Charleroi | F36: 0.32912783 | G36: 0.32912783 | M36: 0.32912783 | N36: 0.32912783 | T36: 0.32912783 | U36: 0.32912783
A37: BE32C | B37: 3 | C37: BE | D37: Arr. Soignies | E37: Arr. Soignies | F37: 3.704705 | I37: 0.23534073 | L37: 3.4693642 | M37: 3.034965 | P37: 0.21023929 | S37: 2.8247257 | T37: 1.4217677 | W37: 0.057573756 | Z37: 1.364194
A38: BE32D | B38: 3 | C38: BE | D38: Arr. Thuin | E38: Arr. Thuin | F38: 0.35576008 | I38: 0.35576008 | M38: 0.31781471 | P38: 0.31781471 | T38: 0.087033146 | W38: 0.087033146
A39: BE332 | B39: 3 | C39: BE | D39: Arr. Liège | E39: Arr. Liège | F39: 0 | H39: 0 | M39: 0.007296066 | O39: 0.007296066 | T39: 0.051671857 | V39: 0.051671857
A40: BE335 | B40: 3 | C40: BE | D40: Arr. Verviers — communes francophones | E40: Arr. Verviers — communes francophones | F40: 1.0781006 | I40: 1.0781006 | M40: 0.96900764 | P40: 0.96900764 | T40: 0.30607277 | W40: 0.30607277
A41: BE352 | B41: 3 | C41: BE | D41: Arr. Namur | E41: Arr. Namur | F41: 4.4380074 | I41: 4.109765 | L41: 0.3282424 | M41: 3.9567422 | P41: 3.696076 | S41: 0.26066618 | T41: 1.2875936 | W41: 1.1799546 | Z41: 0.10763897
A42: BG313 | B42: 3 | C42: BG | D42: Vratsa | E42: Враца | F42: 0 | H42: 0 | M42: 0.00292011 | O42: 0.00292011 | T42: 0.020680669 | V42: 0.020680669
A43: BG314 | B43: 3 | C43: BG | D43: Pleven | E43: Плевен | F43: 0.59194422 | I43: 0.59194422 | M43: 0.52880745 | P43: 0.52880745 | T43: 0.14481324 | W43: 0.14481324
A44: BG315 | B44: 3 | C44: BG | D44: Lovech | E44: Ловеч | F44: 0 | H44: 0 | M44: 0.003527246 | O44: 0.003527246 | T44: 0.024980493 | V44: 0.024980493
A45: BG331 | B45: 3 | C45: BG | D45: Varna | E45: Варна | F45: 7.9165782 | H45: 0 | K45: 7.9165782 | M45: 6.0889999 | O45: 0.005149505 | R45: 6.0838504 | T45: 1.9686116 | V45: 0.036469582 | Y45: 1.932142
A46: BG333 | B46: 3 | C46: BG | D46: Shumen | E46: Шумен | F46: 0.35676903 | I46: 0.35676903 | M46: 0.31871604 | P46: 0.31871604 | T46: 0.087279974 | W46: 0.087279974
A47: BG334 | B47: 3 | C47: BG | D47: Targovishte | E47: Търговище | F47: 3.7640071 | I47: 3.7640071 | M47: 3.3807211 | P47: 3.3807211 | T47: 1.0495325 | W47: 1.0495325
A48: BG341 | B48: 3 | C48: BG | D48: Burgas | E48: Бургас | F48: 15.690898 | J48: 15.690898 | M48: 11.311137 | Q48: 11.311137 | T48: 1.9709589 | X48: 1.9709589
A49: BG411 | B49: 3 | C49: BG | D49: Sofia (stolitsa) | E49: София (столица) | F49: 0.58131087 | I49: 0.58131087 | M49: 0.51930826 | P49: 0.51930826 | T49: 0.14221189 | W49: 0.14221189
A50: BG414 | B50: 3 | C50: BG | D50: Pernik | E50: Перник | F50: 0.12593394 | G50: 0.12593394 | M50: 0.12593394 | N50: 0.12593394 | T50: 0.12593394 | U50: 0.12593394
A51: BG421 | B51: 3 | C51: BG | D51: Plovdiv | E51: Пловдив | F51: 1.7955662 | I51: 1.7955662 | M51: 1.6040512 | P51: 1.6040512 | T51: 0.43926733 | W51: 0.43926733
A52: BG422 | B52: 3 | C52: BG | D52: Haskovo | E52: Хасково | F52: 8.796198 | K52: 8.796198 | M52: 6.7598338 | R52: 6.7598338 | T52: 2.1468245 | Y52: 2.1468245
A53: CY000 | B53: 3 | C53: CY | D53: Kýpros | E53: Κύπρος | F53: 0 | H53: 0 | M53: 0.009352624 | O53: 0.009352624 | T53: 0.066236715 | V53: 0.066236715
A54: CZ010 | B54: 3 | C54: CZ | D54: Hlavní město Praha | E54: Hlavní město Praha | F54: 0 | H54: 0 | M54: 0.003524456 | O54: 0.003524456 | T54: 0.024960739 | V54: 0.024960739
A55: CZ020 | B55: 3 | C55: CZ | D55: Středočeský kraj | E55: Středočeský kraj | F55: 6.278636 | I55: 0.098786117 | J55: 5.4437809 | L55: 0.73606892 | M55: 4.6136576 | P55: 0.088249589 | Q55: 3.9242722 | S55: 0.60113585 | T55: 1.003396 | W55: 0.024167036 | X55: 0.68380208 | Z55: 0.2954269
A56: CZ032 | B56: 3 | C56: CZ | D56: Plzeňský kraj | E56: Plzeňský kraj | F56: 0.36693066 | G56: 0.02573725 | I56: 0.34119341 | M56: 0.33053897 | N56: 0.02573725 | P56: 0.30480172 | T56: 0.10920681 | U56: 0.02573725 | W56: 0.083469557
A57: CZ041 | B57: 3 | C57: CZ | D57: Karlovarský kraj | E57: Karlovarský kraj | F57: 0.8551374 | I57: 0.8551374 | M57: 0.76392844 | P57: 0.76392844 | T57: 0.20920081 | W57: 0.20920081
A58: CZ042 | B58: 3 | C58: CZ | D58: Ústecký kraj | E58: Ústecký kraj | F58: 12.794469 | H58: 0 | I58: 4.1484645 | J58: 8.646005 | L58: 0 | M58: 10.054041 | O58: 0.003122204 | P58: 3.7280058 | Q58: 6.2326676 | S58: 0.090245526 | T58: 2.5736903 | V58: 0.022111924 | W58: 1.1709402 | X58: 1.0860386 | Z58: 0.29459958
A59: CZ051 | B59: 3 | C59: CZ | D59: Liberecký kraj | E59: Liberecký kraj | F59: 0.16202263 | I59: 0.16202263 | M59: 0.1447413 | P59: 0.1447413 | T59: 0.039637216 | W59: 0.039637216
A60: CZ053 | B60: 3 | C60: CZ | D60: Pardubický kraj | E60: Pardubický kraj | F60: 2.1527823 | H60: 0 | I60: 0.87189265 | J60: 1.2808896 | M60: 1.7112064 | O60: 0.004182384 | P60: 0.78366583 | Q60: 0.92335816 | T60: 0.43804522 | V60: 0.029620286 | W60: 0.24753032 | X60: 0.16089461
A61: CZ063 | B61: 3 | C61: CZ | D61: Kraj Vysočina | E61: Kraj Vysočina | F61: 0.26478542 | I61: 0.26478542 | M61: 0.2365434 | P61: 0.2365434 | T61: 0.064777104 | W61: 0.064777104
A62: CZ064 | B62: 3 | C62: CZ | D62: Jihomoravský kraj | E62: Jihomoravský kraj | F62: 1.8199797 | H62: 0 | I62: 1.8199797 | M62: 1.6332329 | O62: 0.005044907 | P62: 1.628188 | T62: 0.49767243 | V62: 0.035728801 | W62: 0.46194363
A63: CZ071 | B63: 3 | C63: CZ | D63: Olomoucký kraj | E63: Olomoucký kraj | F63: 0.36803446 | H63: 0 | L63: 0.36803446 | M63: 0.30601457 | O63: 0.004254234 | S63: 0.30176033 | T63: 0.18173511 | V63: 0.030129135 | Z63: 0.15160598
A64: CZ080 | B64: 3 | C64: CZ | D64: Moravskoslezský kraj | E64: Moravskoslezský kraj | F64: 7.903152 | G64: 0.0205898 | I64: 0.67304047 | K64: 6.8414873 | L64: 0.36803446 | M64: 13.685637 | N64: 7.521293 | P64: 0.60493551 | R64: 5.2576485 | S64: 0.30176033 | T64: 8.3177913 | U64: 6.3053567 | W64: 0.19107619 | Y64: 1.6697524 | Z64: 0.15160598
A65: DE11C | B65: 3 | C65: DE | D65: Heidenheim | E65: Heidenheim | F65: 0 | H65: 0 | M65: 0.003973817 | O65: 0.003973817 | T65: 0.028143177 | V65: 0.028143177
A66: DE122 | B66: 3 | C66: DE | D66: Karlsruhe, Stadtkreis | E66: Karlsruhe, Stadtkreis | F66: 24.817237 | J66: 24.817237 | M66: 17.890064 | Q66: 17.890064 | T66: 3.117333 | X66: 3.117333
A67: DE123 | B67: 3 | C67: DE | D67: Karlsruhe, Landkreis | E67: Karlsruhe, Landkreis | F67: 0 | H67: 0 | M67: 0.003475348 | O67: 0.003475348 | T67: 0.024612947 | V67: 0.024612947
A68: DE126 | B68: 3 | C68: DE | D68: Mannheim, Stadtkreis | E68: Mannheim, Stadtkreis | F68: 0.48173989 | I68: 0.48173989 | M68: 0.43324795 | P68: 0.43324795 | T68: 0.13831234 | W68: 0.13831234
A69: DE128 | B69: 3 | C69: DE | D69: Rhein-Neckar-Kreis | E69: Rhein-Neckar-Kreis | F69: 0 | H69: 0 | M69: 0.003652575 | O69: 0.003652575 | T69: 0.025868094 | V69: 0.025868094
A70: DE131 | B70: 3 | C70: DE | D70: Freiburg im Breisgau, Stadtkreis | E70: Freiburg im Breisgau, Stadtkreis | F70: 0.36803446 | L70: 0.36803446 | M70: 0.29937551 | S70: 0.29937551 | T70: 0.14382092 | Z70: 0.14382092
A71: DE134 | B71: 3 | C71: DE | D71: Ortenaukreis | E71: Ortenaukreis | F71: 0.4065691 | G71: 0.4065691 | M71: 0.4065691 | N71: 0.4065691 | T71: 0.4065691 | U71: 0.4065691
A72: DE143 | B72: 3 | C72: DE | D72: Zollernalbkreis | E72: Zollernalbkreis | F72: 0 | H72: 0 | M72: 0.005303025 | O72: 0.005303025 | T72: 0.037556838 | V72: 0.037556838
A73: DE145 | B73: 3 | C73: DE | D73: Alb-Donau-Kreis | E73: Alb-Donau-Kreis | F73: 0 | H73: 0 | M73: 0.010277409 | O73: 0.010277409 | T73: 0.07278618 | V73: 0.07278618
A74: DE148 | B74: 3 | C74: DE | D74: Ravensburg | E74: Ravensburg | F74: 1.5345407 | I74: 1.5345407 | M74: 1.3708666 | P74: 1.3708666 | T74: 0.37541005 | W74: 0.37541005
A75: DE214 | B75: 3 | C75: DE | D75: Altötting | E75: Altötting | F75: 7.2485478 | J75: 5.9241145 | L75: 1.3244332 | M75: 5.4182796 | Q75: 4.2705315 | S75: 1.1477481 | T75: 1.4915465 | X75: 0.74413756 | Z75: 0.74740898
A76: DE219 | B76: 3 | C76: DE | D76: Eichstätt | E76: Eichstätt | F76: 9.3461273 | I76: 0.54001106 | J76: 8.8061162 | M76: 6.8305008 | P76: 0.48241348 | Q76: 6.3480874 | T76: 1.2382587 | W76: 0.13210831 | X76: 1.1061504
A77: DE21I | B77: 3 | C77: DE | D77: Neuburg-Schrobenhausen | E77: Neuburg-Schrobenhausen | F77: 1.0863478 | I77: 1.0863478 | M77: 0.9704779 | P77: 0.9704779 | T77: 0.26576411 | W77: 0.26576411
A78: DE21J | B78: 3 | C78: DE | D78: Pfaffenhofen a. d. Ilm | E78: Pfaffenhofen a. d. Ilm | F78: 0.04832251 | L78: 0.04832251 | M78: 0.046785492 | S78: 0.046785492 | T78: 0.043304139 | Z78: 0.043304139
A79: DE21K | B79: 3 | C79: DE | D79: Rosenheim, Landkreis | E79: Rosenheim, Landkreis | F79: 0 | H79: 0 | M79: 0.005879483 | O79: 0.005879483 | T79: 0.0416394 | V79: 0.0416394
A80: DE226 | B80: 3 | C80: DE | D80: Kelheim | E80: Kelheim | F80: 7.3651154 | J80: 7.3651154 | M80: 5.3093094 | Q80: 5.3093094 | T80: 0.92514399 | X80: 0.92514399
A81: DE229 | B81: 3 | C81: DE | D81: Regen | E81: Regen | F81: 0.42384821 | I81: 0.42384821 | M81: 0.37864056 | P81: 0.37864056 | T81: 0.10369023 | W81: 0.10369023
A82: DE237 | B82: 3 | C82: DE | D82: Neustadt a. d. Waldnaab | E82: Neustadt a. d. Waldnaab | F82: 2.4508145 | I82: 2.4508145 | M82: 2.2041155 | P82: 2.2041155 | T82: 0.70365335 | W82: 0.70365335
A83: DE239 | B83: 3 | C83: DE | D83: Schwandorf | E83: Schwandorf | F83: 0 | H83: 0 | M83: 0.006313849 | O83: 0.006313849 | T83: 0.044715643 | V83: 0.044715643
A84: DE24A | B84: 3 | C84: DE | D84: Kronach | E84: Kronach | F84: 2.2542704 | I84: 2.2542704 | M84: 2.0138299 | P84: 2.0138299 | T84: 0.55148471 | W84: 0.55148471
A85: DE24D | B85: 3 | C85: DE | D85: Wunsiedel i. Fichtelgebirge | E85: Wunsiedel i. Fichtelgebirge | F85: 0.20450973 | I85: 0.20450973 | M85: 0.18392378 | P85: 0.18392378 | T85: 0.058716787 | W85: 0.058716787
A86: DE25C | B86: 3 | C86: DE | D86: Weißenburg-Gunzenhausen | E86: Weißenburg-Gunzenhausen | F86: 0 | H86: 0 | M86: 0.002279886 | O86: 0.002279886 | T86: 0.016146503 | V86: 0.016146503
A87: DE26A | B87: 3 | C87: DE | D87: Main-Spessart | E87: Main-Spessart | F87: 0.95646953 | H87: 0 | I87: 0.95646953 | M87: 0.86375866 | O87: 0.009306175 | P87: 0.85445249 | T87: 0.29989846 | V87: 0.065907755 | W87: 0.2339907
A88: DE276 | B88: 3 | C88: DE | D88: Augsburg, Landkreis | E88: Augsburg, Landkreis | F88: 0.19190062 | G88: 0.19190062 | M88: 0.19190062 | N88: 0.19190062 | T88: 0.19190062 | U88: 0.19190062
A89: DE27D | B89: 3 | C89: DE | D89: Donau-Ries | E89: Donau-Ries | F89: 0 | H89: 0 | M89: 0.004496657 | O89: 0.004496657 | T89: 0.031846012 | V89: 0.031846012
A90: DE401 | B90: 3 | C90: DE | D90: Brandenburg an der Havel, Kreisfreie Stadt | E90: Brandenburg an der Havel, Kreisfreie Stadt | F90: 0.29272975 | G90: 0.29272975 | M90: 0.29272975 | N90: 0.29272975 | T90: 0.29272975 | U90: 0.29272975
A91: DE409 | B91: 3 | C91: DE | D91: Märkisch-Oderland | E91: Märkisch-Oderland | F91: 0.63245185 | H91: 0 | I91: 0.63245185 | M91: 0.57392464 | O91: 0.008930107 | P91: 0.56499454 | T91: 0.21796741 | V91: 0.063244385 | W91: 0.15472302
A92: DE40A | B92: 3 | C92: DE | D92: Oberhavel | E92: Oberhavel | F92: 0.16262764 | G92: 0.16262764 | M92: 0.16262764 | N92: 0.16262764 | T92: 0.16262764 | U92: 0.16262764
A93: DE40C | B93: 3 | C93: DE | D93: Oder-Spree | E93: Oder-Spree | F93: 0 | G93: 0 | M93: 3.6499191 | N93: 3.6499191 | T93: 3.058232 | U93: 3.058232
A94: DE40G | B94: 3 | C94: DE | D94: Spree-Neiße | E94: Spree-Neiße | F94: 1.1388296 | I94: 1.1388296 | M94: 1.0197894 | P94: 1.0197894 | T94: 0.29578481 | W94: 0.29578481
A95: DE40I | B95: 3 | C95: DE | D95: Uckermark | E95: Uckermark | F95: 17.612232 | J95: 17.612232 | M95: 12.696175 | Q95: 12.696175 | T95: 2.2123009 | X95: 2.2123009
A96: DE501 | B96: 3 | C96: DE | D96: Bremen, Kreisfreie Stadt | E96: Bremen, Kreisfreie Stadt | F96: 0 | G96: 0 | M96: 5.7790385 | N96: 5.7790385 | T96: 4.8422007 | U96: 4.8422007
A97: DE600 | B97: 3 | C97: DE | D97: Hamburg | E97: Hamburg | F97: 16.171232 | G97: 0 | J97: 16.171232 | M97: 13.330276 | N97: 1.6728796 | Q97: 11.657397 | T97: 3.4329841 | U97: 1.4016897 | X97: 2.0312944
A98: DE712 | B98: 3 | C98: DE | D98: Frankfurt am Main, Kreisfreie Stadt | E98: Frankfurt am Main, Kreisfreie Stadt | F98: 0.36803446 | L98: 0.36803446 | M98: 0.32127332 | S98: 0.32127332 | T98: 0.21530464 | Z98: 0.21530464
A99: DE714 | B99: 3 | C99: DE | D99: Wiesbaden, Kreisfreie Stadt | E99: Wiesbaden, Kreisfreie Stadt | F99: 0 | H99: 0 | M99: 0.001393416 | O99: 0.001393416 | T99: 0.009868385 | V99: 0.009868385
A100: DE722 | B100: 3 | C100: DE | D100: Lahn-Dill-Kreis | E100: Lahn-Dill-Kreis | F100: 0.065051057 | G100: 0.065051057 | M100: 0.065051057 | N100: 0.065051057 | T100: 0.065051057 | U100: 0.065051057
A101: DE732 | B101: 3 | C101: DE | D101: Fulda | E101: Fulda | F101: 0 | H101: 0 | M101: 0.000991187 | O101: 0.000991187 | T101: 0.007019741 | V101: 0.007019741
A102: DE80M | B102: 3 | C102: DE | D102: Nordwestmecklenburg | E102: Nordwestmecklenburg | F102: 0.36803446 | L102: 0.36803446 | M102: 0.30176033 | S102: 0.30176033 | T102: 0.15160598 | Z102: 0.15160598
A103: DE80O | B103: 3 | C103: DE | D103: Ludwigslust-Parchim | E103: Ludwigslust-Parchim | F103: 0.3932305 | I103: 0.3932305 | M103: 0.3534395 | P103: 0.3534395 | T103: 0.11163814 | W103: 0.11163814
A104: DE912 | B104: 3 | C104: DE | D104: Salzgitter, Kreisfreie Stadt | E104: Salzgitter, Kreisfreie Stadt | F104: 0 | G104: 0 | M104: 8.5164778 | N104: 8.5164778 | T104: 7.1358747 | U104: 7.1358747
A105: DE91A | B105: 3 | C105: DE | D105: Peine | E105: Peine | F105: 0.16262764 | G105: 0.16262764 | M105: 0.16262764 | N105: 0.16262764 | T105: 0.16262764 | U105: 0.16262764
A106: DE91C | B106: 3 | C106: DE | D106: Göttingen | E106: Göttingen | F106: 0.013700713 | L106: 0.013700713 | M106: 0.010880107 | S106: 0.010880107 | T106: 0.004492809 | Z106: 0.004492809
A107: DE922 | B107: 3 | C107: DE | D107: Diepholz | E107: Diepholz | F107: 0.013700713 | L107: 0.013700713 | M107: 0.010880107 | S107: 0.010880107 | T107: 0.004492809 | Z107: 0.004492809
A108: DE923 | B108: 3 | C108: DE | D108: Hameln-Pyrmont | E108: Hameln-Pyrmont | F108: 0.29028102 | I108: 0.29028102 | M108: 0.25931965 | P108: 0.25931965 | T108: 0.071014349 | W108: 0.071014349
A109: DE926 | B109: 3 | C109: DE | D109: Holzminden | E109: Holzminden | F109: 1.7415837 | I109: 1.7415837 | M109: 1.5558264 | P109: 1.5558264 | T109: 0.42606103 | W109: 0.42606103
A110: DE927 | B110: 3 | C110: DE | D110: Nienburg (Weser) | E110: Nienburg (Weser) | F110: 1.8465224 | I110: 1.4921886 | L110: 0.35433375 | M110: 1.6215272 | P110: 1.3330318 | S110: 0.28849541 | T110: 0.50437714 | W110: 0.36504903 | Z110: 0.13932811
A111: DE928 | B111: 3 | C111: DE | D111: Schaumburg | E111: Schaumburg | F111: 1.7229694 | I111: 1.7229694 | M111: 1.5391975 | P111: 1.5391975 | T111: 0.42150723 | W111: 0.42150723
...

Sheet Crude oil (PJ per y)
F12: 2018 | M12: 2030 | T12: 2050
A13: NUTS ID | B13: NUTS LEVEL | C13: Country code | D13: NUTS region name (Latin) | E13: NUTS_NAME | F13: All sectors (PJ/y) | G13: Steel (PJ/y) | H13: Cement (PJ/y) | I13: Glass (PJ/y) | J13: Refineries (PJ/y) | K13: Fertilisers (PJ/y) | L13: Chemical (PJ/y) | M13: All sectors (PJ/y) | N13: Steel (PJ/y) | O13: Cement (PJ/y) | P13: Glass (PJ/y) | Q13: Refineries (PJ/y) | R13: Fertilisers (PJ/y) | S13: Chemical (PJ/y) | T13: All sectors (PJ/y) | U13: Steel (PJ/y) | V13: Cement (PJ/y) | W13: Glass (PJ/y) | X13: Refineries (PJ/y) | Y13: Fertilisers (PJ/y) | Z13: Chemical (PJ/y)
A14: AT121 | B14: 3 | C14: AT | D14: Mostviertel-Eisenwurzen | E14: Mostviertel-Eisenwurzen | F14: 0 | I14: 0 | M14: 0 | P14: 0 | T14: 0 | W14: 0
A15: AT122 | B15: 3 | C15: AT | D15: Niederösterreich-Süd | E15: Niederösterreich-Süd | F15: 0 | H15: 0 | M15: 0 | O15: 0 | T15: 0 | V15: 0
A16: AT124 | B16: 3 | C16: AT | D16: Waldviertel | E16: Waldviertel | F16: 0 | L16: 0 | M16: 0 | S16: 0 | T16: 0 | Z16: 0
A17: AT127 | B17: 3 | C17: AT | D17: Wiener Umland/Südteil | E17: Wiener Umland/Südteil | F17: 416.0558 | H17: 0 | J17: 416.0558 | L17: 0 | M17: 313.39509 | O17: 0 | Q17: 313.39509 | S17: 0 | T17: 69.337106 | V17: 0 | X17: 69.337106 | Z17: 0
A18: AT213 | B18: 3 | C18: AT | D18: Unterkärnten | E18: Unterkärnten | F18: 0 | H18: 0 | M18: 0 | O18: 0 | T18: 0 | V18: 0
A19: AT221 | B19: 3 | C19: AT | D19: Graz | E19: Graz | F19: 0 | G19: 0 | M19: 0 | N19: 0 | T19: 0 | U19: 0
A20: AT223 | B20: 3 | C20: AT | D20: Östliche Obersteiermark | E20: Östliche Obersteiermark | F20: 0 | G20: 0 | M20: 0 | N20: 0 | T20: 0 | U20: 0
A21: AT225 | B21: 3 | C21: AT | D21: West- und Südsteiermark | E21: West- und Südsteiermark | F21: 0 | H21: 0 | I21: 0 | M21: 0 | O21: 0 | P21: 0 | T21: 0 | V21: 0 | W21: 0
A22: AT312 | B22: 3 | C22: AT | D22: Linz-Wels | E22: Linz-Wels | F22: 0 | G22: 0 | K22: 0 | L22: 0 | M22: 0 | N22: 0 | R22: 0 | S22: 0 | T22: 0 | U22: 0 | Y22: 0 | Z22: 0
A23: AT314 | B23: 3 | C23: AT | D23: Steyr-Kirchdorf | E23: Steyr-Kirchdorf | F23: 0 | H23: 0 | I23: 0 | M23: 0 | O23: 0 | P23: 0 | T23: 0 | V23: 0 | W23: 0
A24: AT315 | B24: 3 | C24: AT | D24: Traunviertel | E24: Traunviertel | F24: 0 | H24: 0 | M24: 0 | O24: 0 | T24: 0 | V24: 0
A25: AT323 | B25: 3 | C25: AT | D25: Salzburg und Umgebung | E25: Salzburg und Umgebung | F25: 0 | H25: 0 | M25: 0 | O25: 0 | T25: 0 | V25: 0
A26: AT331 | B26: 3 | C26: AT | D26: Außerfern | E26: Außerfern | F26: 0 | H26: 0 | M26: 0 | O26: 0 | T26: 0 | V26: 0
A27: BE211 | B27: 3 | C27: BE | D27: Arr. Antwerpen | E27: Arr. Antwerpen | F27: 1668.5124 | J27: 1668.5124 | K27: 0 | L27: 0 | M27: 1256.8112 | Q27: 1256.8112 | R27: 0 | S27: 0 | T27: 278.06324 | X27: 278.06324 | Y27: 0 | Z27: 0
A28: BE213 | B28: 3 | C28: BE | D28: Arr. Turnhout | E28: Arr. Turnhout | F28: 0 | I28: 0 | L28: 0 | M28: 0 | P28: 0 | S28: 0 | T28: 0 | W28: 0 | Z28: 0
A29: BE224 | B29: 3 | C29: BE | D29: Arr. Hasselt | E29: Arr. Hasselt | F29: 0 | G29: 0 | L29: 0 | M29: 0 | N29: 0 | S29: 0 | T29: 0 | U29: 0 | Z29: 0
A30: BE233 | B30: 3 | C30: BE | D30: Arr. Eeklo | E30: Arr. Eeklo | F30: 0 | L30: 0 | M30: 0 | S30: 0 | T30: 0 | Z30: 0
A31: BE234 | B31: 3 | C31: BE | D31: Arr. Gent | E31: Arr. Gent | F31: 0 | G31: 0 | L31: 0 | M31: 0 | N31: 0 | S31: 0 | T31: 0 | U31: 0 | Z31: 0
A32: BE236 | B32: 3 | C32: BE | D32: Arr. Sint-Niklaas | E32: Arr. Sint-Niklaas | F32: 0 | L32: 0 | M32: 0 | S32: 0 | T32: 0 | Z32: 0
A33: BE255 | B33: 3 | C33: BE | D33: Arr. Oostende | E33: Arr. Oostende | F33: 0 | L33: 0 | M33: 0 | S33: 0 | T33: 0 | Z33: 0
A34: BE323 | B34: 3 | C34: BE | D34: Arr. Mons | E34: Arr. Mons | F34: 0 | H34: 0 | I34: 0 | K34: 0 | L34: 0 | M34: 0 | O34: 0 | P34: 0 | R34: 0 | S34: 0 | T34: 0 | V34: 0 | W34: 0 | Y34: 0 | Z34: 0
A35: BE328 | B35: 3 | C35: BE | D35: Arr. Tournai-Mouscron | E35: Arr. Tournai-Mouscron | F35: 0 | H35: 0 | M35: 0 | O35: 0 | T35: 0 | V35: 0
A36: BE32B | B36: 3 | C36: BE | D36: Arr. Charleroi | E36: Arr. Charleroi | F36: 0 | G36: 0 | M36: 0 | N36: 0 | T36: 0 | U36: 0
A37: BE32C | B37: 3 | C37: BE | D37: Arr. Soignies | E37: Arr. Soignies | F37: 0 | I37: 0 | L37: 0 | M37: 0 | P37: 0 | S37: 0 | T37: 0 | W37: 0 | Z37: 0
A38: BE32D | B38: 3 | C38: BE | D38: Arr. Thuin | E38: Arr. Thuin | F38: 0 | I38: 0 | M38: 0 | P38: 0 | T38: 0 | W38: 0
A39: BE332 | B39: 3 | C39: BE | D39: Arr. Liège | E39: Arr. Liège | F39: 0 | H39: 0 | M39: 0 | O39: 0 | T39: 0 | V39: 0
A40: BE335 | B40: 3 | C40: BE | D40: Arr. Verviers — communes francophones | E40: Arr. Verviers — communes francophones | F40: 0 | I40: 0 | M40: 0 | P40: 0 | T40: 0 | W40: 0
A41: BE352 | B41: 3 | C41: BE | D41: Arr. Namur | E41: Arr. Namur | F41: 0 | I41: 0 | L41: 0 | M41: 0 | P41: 0 | S41: 0 | T41: 0 | W41: 0 | Z41: 0
A42: BG313 | B42: 3 | C42: BG | D42: Vratsa | E42: Враца | F42: 0 | H42: 0 | M42: 0 | O42: 0 | T42: 0 | V42: 0
A43: BG314 | B43: 3 | C43: BG | D43: Pleven | E43: Плевен | F43: 0 | I43: 0 | M43: 0 | P43: 0 | T43: 0 | W43: 0
A44: BG315 | B44: 3 | C44: BG | D44: Lovech | E44: Ловеч | F44: 0 | H44: 0 | M44: 0 | O44: 0 | T44: 0 | V44: 0
A45: BG331 | B45: 3 | C45: BG | D45: Varna | E45: Варна | F45: 0 | H45: 0 | K45: 0 | M45: 0 | O45: 0 | R45: 0 | T45: 0 | V45: 0 | Y45: 0
A46: BG333 | B46: 3 | C46: BG | D46: Shumen | E46: Шумен | F46: 0 | I46: 0 | M46: 0 | P46: 0 | T46: 0 | W46: 0
A47: BG334 | B47: 3 | C47: BG | D47: Targovishte | E47: Търговище | F47: 0 | I47: 0 | M47: 0 | P47: 0 | T47: 0 | W47: 0
A48: BG341 | B48: 3 | C48: BG | D48: Burgas | E48: Бургас | F48: 420.34504 | J48: 420.34504 | M48: 316.62597 | Q48: 316.62597 | T48: 70.051921 | X48: 70.051921
A49: BG411 | B49: 3 | C49: BG | D49: Sofia (stolitsa) | E49: София (столица) | F49: 0 | I49: 0 | M49: 0 | P49: 0 | T49: 0 | W49: 0
A50: BG414 | B50: 3 | C50: BG | D50: Pernik | E50: Перник | F50: 0 | G50: 0 | M50: 0 | N50: 0 | T50: 0 | U50: 0
A51: BG421 | B51: 3 | C51: BG | D51: Plovdiv | E51: Пловдив | F51: 0 | I51: 0 | M51: 0 | P51: 0 | T51: 0 | W51: 0
A52: BG422 | B52: 3 | C52: BG | D52: Haskovo | E52: Хасково | F52: 0 | K52: 0 | M52: 0 | R52: 0 | T52: 0 | Y52: 0
A53: CY000 | B53: 3 | C53: CY | D53: Kýpros | E53: Κύπρος | F53: 0 | H53: 0 | M53: 0 | O53: 0 | T53: 0 | V53: 0
A54: CZ010 | B54: 3 | C54: CZ | D54: Hlavní město Praha | E54: Hlavní město Praha | F54: 0 | H54: 0 | M54: 0 | O54: 0 | T54: 0 | V54: 0
A55: CZ020 | B55: 3 | C55: CZ | D55: Středočeský kraj | E55: Středočeský kraj | F55: 145.83399 | I55: 0 | J55: 145.83399 | L55: 0 | M55: 109.84983 | P55: 0 | Q55: 109.84983 | S55: 0 | T55: 24.303728 | W55: 0 | X55: 24.303728 | Z55: 0
A56: CZ032 | B56: 3 | C56: CZ | D56: Plzeňský kraj | E56: Plzeňský kraj | F56: 0 | G56: 0 | I56: 0 | M56: 0 | N56: 0 | P56: 0 | T56: 0 | U56: 0 | W56: 0
A57: CZ041 | B57: 3 | C57: CZ | D57: Karlovarský kraj | E57: Karlovarský kraj | F57: 0 | I57: 0 | M57: 0 | P57: 0 | T57: 0 | W57: 0
A58: CZ042 | B58: 3 | C58: CZ | D58: Ústecký kraj | E58: Ústecký kraj | F58: 231.61869 | H58: 0 | I58: 0 | J58: 231.61869 | L58: 0 | M58: 174.46737 | O58: 0 | P58: 0 | Q58: 174.46737 | S58: 0 | T58: 38.600038 | V58: 0 | W58: 0 | X58: 38.600038 | Z58: 0
A59: CZ051 | B59: 3 | C59: CZ | D59: Liberecký kraj | E59: Liberecký kraj | F59: 0 | I59: 0 | M59: 0 | P59: 0 | T59: 0 | W59: 0
A60: CZ053 | B60: 3 | C60: CZ | D60: Pardubický kraj | E60: Pardubický kraj | F60: 34.313881 | H60: 0 | I60: 0 | J60: 34.313881 | M60: 25.847018 | O60: 0 | P60: 0 | Q60: 25.847018 | T60: 5.7185242 | V60: 0 | W60: 0 | X60: 5.7185242
A61: CZ063 | B61: 3 | C61: CZ | D61: Kraj Vysočina | E61: Kraj Vysočina | F61: 0 | I61: 0 | M61: 0 | P61: 0 | T61: 0 | W61: 0
A62: CZ064 | B62: 3 | C62: CZ | D62: Jihomoravský kraj | E62: Jihomoravský kraj | F62: 0 | H62: 0 | I62: 0 | M62: 0 | O62: 0 | P62: 0 | T62: 0 | V62: 0 | W62: 0
A63: CZ071 | B63: 3 | C63: CZ | D63: Olomoucký kraj | E63: Olomoucký kraj | F63: 0 | H63: 0 | L63: 0 | M63: 0 | O63: 0 | S63: 0 | T63: 0 | V63: 0 | Z63: 0
A64: CZ080 | B64: 3 | C64: CZ | D64: Moravskoslezský kraj | E64: Moravskoslezský kraj | F64: 0 | G64: 0 | I64: 0 | K64: 0 | L64: 0 | M64: 0 | N64: 0 | P64: 0 | R64: 0 | S64: 0 | T64: 0 | U64: 0 | W64: 0 | Y64: 0 | Z64: 0
A65: DE11C | B65: 3 | C65: DE | D65: Heidenheim | E65: Heidenheim | F65: 0 | H65: 0 | M65: 0 | O65: 0 | T65: 0 | V65: 0
A66: DE122 | B66: 3 | C66: DE | D66: Karlsruhe, Stadtkreis | E66: Karlsruhe, Stadtkreis | F66: 664.83144 | J66: 664.83144 | M66: 500.78597 | Q66: 500.78597 | T66: 110.79641 | X66: 110.79641
A67: DE123 | B67: 3 | C67: DE | D67: Karlsruhe, Landkreis | E67: Karlsruhe, Landkreis | F67: 0 | H67: 0 | M67: 0 | O67: 0 | T67: 0 | V67: 0
A68: DE126 | B68: 3 | C68: DE | D68: Mannheim, Stadtkreis | E68: Mannheim, Stadtkreis | F68: 0 | I68: 0 | M68: 0 | P68: 0 | T68: 0 | W68: 0
A69: DE128 | B69: 3 | C69: DE | D69: Rhein-Neckar-Kreis | E69: Rhein-Neckar-Kreis | F69: 0 | H69: 0 | M69: 0 | O69: 0 | T69: 0 | V69: 0
A70: DE131 | B70: 3 | C70: DE | D70: Freiburg im Breisgau, Stadtkreis | E70: Freiburg im Breisgau, Stadtkreis | F70: 0 | L70: 0 | M70: 0 | S70: 0 | T70: 0 | Z70: 0
A71: DE134 | B71: 3 | C71: DE | D71: Ortenaukreis | E71: Ortenaukreis | F71: 0 | G71: 0 | M71: 0 | N71: 0 | T71: 0 | U71: 0
A72: DE143 | B72: 3 | C72: DE | D72: Zollernalbkreis | E72: Zollernalbkreis | F72: 0 | H72: 0 | M72: 0 | O72: 0 | T72: 0 | V72: 0
A73: DE145 | B73: 3 | C73: DE | D73: Alb-Donau-Kreis | E73: Alb-Donau-Kreis | F73: 0 | H73: 0 | M73: 0 | O73: 0 | T73: 0 | V73: 0
A74: DE148 | B74: 3 | C74: DE | D74: Ravensburg | E74: Ravensburg | F74: 0 | I74: 0 | M74: 0 | P74: 0 | T74: 0 | W74: 0
A75: DE214 | B75: 3 | C75: DE | D75: Altötting | E75: Altötting | F75: 158.7017 | J75: 158.7017 | L75: 0 | M75: 119.54246 | Q75: 119.54246 | S75: 0 | T75: 26.448174 | X75: 26.448174 | Z75: 0
A76: DE219 | B76: 3 | C76: DE | D76: Eichstätt | E76: Eichstätt | F76: 235.90793 | I76: 0 | J76: 235.90793 | M76: 177.69825 | P76: 0 | Q76: 177.69825 | T76: 39.314854 | W76: 0 | X76: 39.314854
A77: DE21I | B77: 3 | C77: DE | D77: Neuburg-Schrobenhausen | E77: Neuburg-Schrobenhausen | F77: 0 | I77: 0 | M77: 0 | P77: 0 | T77: 0 | W77: 0
A78: DE21J | B78: 3 | C78: DE | D78: Pfaffenhofen a. d. Ilm | E78: Pfaffenhofen a. d. Ilm | F78: 0 | L78: 0 | M78: 0 | S78: 0 | T78: 0 | Z78: 0
A79: DE21K | B79: 3 | C79: DE | D79: Rosenheim, Landkreis | E79: Rosenheim, Landkreis | F79: 0 | H79: 0 | M79: 0 | O79: 0 | T79: 0 | V79: 0
A80: DE226 | B80: 3 | C80: DE | D80: Kelheim | E80: Kelheim | F80: 197.30481 | J80: 197.30481 | M80: 148.62035 | Q80: 148.62035 | T80: 32.881514 | X80: 32.881514
A81: DE229 | B81: 3 | C81: DE | D81: Regen | E81: Regen | F81: 0 | I81: 0 | M81: 0 | P81: 0 | T81: 0 | W81: 0
A82: DE237 | B82: 3 | C82: DE | D82: Neustadt a. d. Waldnaab | E82: Neustadt a. d. Waldnaab | F82: 0 | I82: 0 | M82: 0 | P82: 0 | T82: 0 | W82: 0
A83: DE239 | B83: 3 | C83: DE | D83: Schwandorf | E83: Schwandorf | F83: 0 | H83: 0 | M83: 0 | O83: 0 | T83: 0 | V83: 0
A84: DE24A | B84: 3 | C84: DE | D84: Kronach | E84: Kronach | F84: 0 | I84: 0 | M84: 0 | P84: 0 | T84: 0 | W84: 0
A85: DE24D | B85: 3 | C85: DE | D85: Wunsiedel i. Fichtelgebirge | E85: Wunsiedel i. Fichtelgebirge | F85: 0 | I85: 0 | M85: 0 | P85: 0 | T85: 0 | W85: 0
A86: DE25C | B86: 3 | C86: DE | D86: Weißenburg-Gunzenhausen | E86: Weißenburg-Gunzenhausen | F86: 0 | H86: 0 | M86: 0 | O86: 0 | T86: 0 | V86: 0
A87: DE26A | B87: 3 | C87: DE | D87: Main-Spessart | E87: Main-Spessart | F87: 0 | H87: 0 | I87: 0 | M87: 0 | O87: 0 | P87: 0 | T87: 0 | V87: 0 | W87: 0
A88: DE276 | B88: 3 | C88: DE | D88: Augsburg, Landkreis | E88: Augsburg, Landkreis | F88: 0 | G88: 0 | M88: 0 | N88: 0 | T88: 0 | U88: 0
A89: DE27D | B89: 3 | C89: DE | D89: Donau-Ries | E89: Donau-Ries | F89: 0 | H89: 0 | M89: 0 | O89: 0 | T89: 0 | V89: 0
A90: DE401 | B90: 3 | C90: DE | D90: Brandenburg an der Havel, Kreisfreie Stadt | E90: Brandenburg an der Havel, Kreisfreie Stadt | F90: 0 | G90: 0 | M90: 0 | N90: 0 | T90: 0 | U90: 0
A91: DE409 | B91: 3 | C91: DE | D91: Märkisch-Oderland | E91: Märkisch-Oderland | F91: 0 | H91: 0 | I91: 0 | M91: 0 | O91: 0 | P91: 0 | T91: 0 | V91: 0 | W91: 0
A92: DE40A | B92: 3 | C92: DE | D92: Oberhavel | E92: Oberhavel | F92: 0 | G92: 0 | M92: 0 | N92: 0 | T92: 0 | U92: 0
A93: DE40C | B93: 3 | C93: DE | D93: Oder-Spree | E93: Oder-Spree | F93: 0 | G93: 0 | M93: 0 | N93: 0 | T93: 0 | U93: 0
A94: DE40G | B94: 3 | C94: DE | D94: Spree-Neiße | E94: Spree-Neiße | F94: 0 | I94: 0 | M94: 0 | P94: 0 | T94: 0 | W94: 0
A95: DE40I | B95: 3 | C95: DE | D95: Uckermark | E95: Uckermark | F95: 471.81586 | J95: 471.81586 | M95: 355.39649 | Q95: 355.39649 | T95: 78.629708 | X95: 78.629708
A96: DE501 | B96: 3 | C96: DE | D96: Bremen, Kreisfreie Stadt | E96: Bremen, Kreisfreie Stadt | F96: 0 | G96: 0 | M96: 0 | N96: 0 | T96: 0 | U96: 0
A97: DE600 | B97: 3 | C97: DE | D97: Hamburg | E97: Hamburg | F97: 433.21274 | G97: 0 | J97: 433.21274 | M97: 326.3186 | N97: 0 | Q97: 326.3186 | T97: 72.196368 | U97: 0 | X97: 72.196368
A98: DE712 | B98: 3 | C98: DE | D98: Frankfurt am Main, Kreisfreie Stadt | E98: Frankfurt am Main, Kreisfreie Stadt | F98: 0 | L98: 0 | M98: 0 | S98: 0 | T98: 0 | Z98: 0
A99: DE714 | B99: 3 | C99: DE | D99: Wiesbaden, Kreisfreie Stadt | E99: Wiesbaden, Kreisfreie Stadt | F99: 0 | H99: 0 | M99: 0 | O99: 0 | T99: 0 | V99: 0
A100: DE722 | B100: 3 | C100: DE | D100: Lahn-Dill-Kreis | E100: Lahn-Dill-Kreis | F100: 0 | G100: 0 | M100: 0 | N100: 0 | T100: 0 | U100: 0
A101: DE732 | B101: 3 | C101: DE | D101: Fulda | E101: Fulda | F101: 0 | H101: 0 | M101: 0 | O101: 0 | T101: 0 | V101: 0
A102: DE80M | B102: 3 | C102: DE | D102: Nordwestmecklenburg | E102: Nordwestmecklenburg | F102: 0 | L102: 0 | M102: 0 | S102: 0 | T102: 0 | Z102: 0
A103: DE80O | B103: 3 | C103: DE | D103: Ludwigslust-Parchim | E103: Ludwigslust-Parchim | F103: 0 | I103: 0 | M103: 0 | P103: 0 | T103: 0 | W103: 0
A104: DE912 | B104: 3 | C104: DE | D104: Salzgitter, Kreisfreie Stadt | E104: Salzgitter, Kreisfreie Stadt | F104: 0 | G104: 0 | M104: 0 | N104: 0 | T104: 0 | U104: 0
A105: DE91A | B105: 3 | C105: DE | D105: Peine | E105: Peine | F105: 0 | G105: 0 | M105: 0 | N105: 0 | T105: 0 | U105: 0
A106: DE91C | B106: 3 | C106: DE | D106: Göttingen | E106: Göttingen | F106: 0 | L106: 0 | M106: 0 | S106: 0 | T106: 0 | Z106: 0
A107: DE922 | B107: 3 | C107: DE | D107: Diepholz | E107: Diepholz | F107: 0 | L107: 0 | M107: 0 | S107: 0 | T107: 0 | Z107: 0
A108: DE923 | B108: 3 | C108: DE | D108: Hameln-Pyrmont | E108: Hameln-Pyrmont | F108: 0 | I108: 0 | M108: 0 | P108: 0 | T108: 0 | W108: 0
A109: DE926 | B109: 3 | C109: DE | D109: Holzminden | E109: Holzminden | F109: 0 | I109: 0 | M109: 0 | P109: 0 | T109: 0 | W109: 0
A110: DE927 | B110: 3 | C110: DE | D110: Nienburg (Weser) | E110: Nienburg (Weser) | F110: 0 | I110: 0 | L110: 0 | M110: 0 | P110: 0 | S110: 0 | T110: 0 | W110: 0 | Z110: 0
A111: DE928 | B111: 3 | C111: DE | D111: Schaumburg | E111: Schaumburg | F111: 0 | I111: 0 | M111: 0 | P111: 0 | T111: 0 | W111: 0
...

Sheet Alternative fuel mix (PJ per y)
F12: 2018 | M12: 2030 | T12: 2050
A13: NUTS ID | B13: NUTS LEVEL | C13: Country code | D13: NUTS region name (Latin) | E13: NUTS_NAME | F13: All sectors (PJ/y) | G13: Steel (PJ/y) | H13: Cement (PJ/y) | I13: Glass (PJ/y) | J13: Refineries (PJ/y) | K13: Fertilisers (PJ/y) | L13: Chemical (PJ/y) | M13: All sectors (PJ/y) | N13: Steel (PJ/y) | O13: Cement (PJ/y) | P13: Glass (PJ/y) | Q13: Refineries (PJ/y) | R13: Fertilisers (PJ/y) | S13: Chemical (PJ/y) | T13: All sectors (PJ/y) | U13: Steel (PJ/y) | V13: Cement (PJ/y) | W13: Glass (PJ/y) | X13: Refineries (PJ/y) | Y13: Fertilisers (PJ/y) | Z13: Chemical (PJ/y)
A14: AT121 | B14: 3 | C14: AT | D14: Mostviertel-Eisenwurzen | E14: Mostviertel-Eisenwurzen | F14: 0 | I14: 0 | M14: 0 | P14: 0 | T14: 0 | W14: 0
A15: AT122 | B15: 3 | C15: AT | D15: Niederösterreich-Süd | E15: Niederösterreich-Süd | F15: 0.33195414 | H15: 0.33195414 | M15: 0.35246523 | O15: 0.35246523 | T15: 0.47719769 | V15: 0.47719769
A16: AT124 | B16: 3 | C16: AT | D16: Waldviertel | E16: Waldviertel | F16: 0 | L16: 0 | M16: 0 | S16: 0 | T16: 0 | Z16: 0
A17: AT127 | B17: 3 | C17: AT | D17: Wiener Umland/Südteil | E17: Wiener Umland/Südteil | F17: 0.68870295 | H17: 0.68870295 | J17: 0 | L17: 0 | M17: 0.73125715 | O17: 0.73125715 | Q17: 0 | S17: 0 | T17: 0.99003872 | V17: 0.99003872 | X17: 0 | Z17: 0
A18: AT213 | B18: 3 | C18: AT | D18: Unterkärnten | E18: Unterkärnten | F18: 0.49809172 | H18: 0.49809172 | M18: 0.52886826 | O18: 0.52886826 | T18: 0.71602727 | V18: 0.71602727
A19: AT221 | B19: 3 | C19: AT | D19: Graz | E19: Graz | F19: 0 | G19: 0 | M19: 0 | N19: 0 | T19: 0 | U19: 0
A20: AT223 | B20: 3 | C20: AT | D20: Östliche Obersteiermark | E20: Östliche Obersteiermark | F20: 0 | G20: 0 | M20: 0 | N20: 0 | T20: 0 | U20: 0
A21: AT225 | B21: 3 | C21: AT | D21: West- und Südsteiermark | E21: West- und Südsteiermark | F21: 0.36951104 | H21: 0.36951104 | I21: 0 | M21: 0.39234272 | O21: 0.39234272 | P21: 0 | T21: 0.53118726 | V21: 0.53118726 | W21: 0
A22: AT312 | B22: 3 | C22: AT | D22: Linz-Wels | E22: Linz-Wels | F22: 0 | G22: 0 | K22: 0 | L22: 0 | M22: 0 | N22: 0 | R22: 0 | S22: 0 | T22: 0 | U22: 0 | Y22: 0 | Z22: 0
A23: AT314 | B23: 3 | C23: AT | D23: Steyr-Kirchdorf | E23: Steyr-Kirchdorf | F23: 0.25581986 | H23: 0.25581986 | I23: 0 | M23: 0.27162669 | O23: 0.27162669 | P23: 0 | T23: 0.36775154 | V23: 0.36775154 | W23: 0
A24: AT315 | B24: 3 | C24: AT | D24: Traunviertel | E24: Traunviertel | F24: 0.37340435 | H24: 0.37340435 | M24: 0.39647659 | O24: 0.39647659 | T24: 0.53678405 | V24: 0.53678405
A25: AT323 | B25: 3 | C25: AT | D25: Salzburg und Umgebung | E25: Salzburg und Umgebung | F25: 0.35358937 | H25: 0.35358937 | M25: 0.37543728 | O25: 0.37543728 | T25: 0.50829922 | V25: 0.50829922
A26: AT331 | B26: 3 | C26: AT | D26: Außerfern | E26: Außerfern | F26: 0.24400173 | H26: 0.24400173 | M26: 0.25907833 | O26: 0.25907833 | T26: 0.35076249 | V26: 0.35076249
A27: BE211 | B27: 3 | C27: BE | D27: Arr. Antwerpen | E27: Arr. Antwerpen | F27: 0 | J27: 0 | K27: 0 | L27: 0 | M27: 0 | Q27: 0 | R27: 0 | S27: 0 | T27: 0 | X27: 0 | Y27: 0 | Z27: 0
A28: BE213 | B28: 3 | C28: BE | D28: Arr. Turnhout | E28: Arr. Turnhout | F28: 0 | I28: 0 | L28: 0 | M28: 0 | P28: 0 | S28: 0 | T28: 0 | W28: 0 | Z28: 0
A29: BE224 | B29: 3 | C29: BE | D29: Arr. Hasselt | E29: Arr. Hasselt | F29: 0 | G29: 0 | L29: 0 | M29: 0 | N29: 0 | S29: 0 | T29: 0 | U29: 0 | Z29: 0
A30: BE233 | B30: 3 | C30: BE | D30: Arr. Eeklo | E30: Arr. Eeklo | F30: 0 | L30: 0 | M30: 0 | S30: 0 | T30: 0 | Z30: 0
A31: BE234 | B31: 3 | C31: BE | D31: Arr. Gent | E31: Arr. Gent | F31: 0 | G31: 0 | L31: 0 | M31: 0 | N31: 0 | S31: 0 | T31: 0 | U31: 0 | Z31: 0
A32: BE236 | B32: 3 | C32: BE | D32: Arr. Sint-Niklaas | E32: Arr. Sint-Niklaas | F32: 0 | L32: 0 | M32: 0 | S32: 0 | T32: 0 | Z32: 0
A33: BE255 | B33: 3 | C33: BE | D33: Arr. Oostende | E33: Arr. Oostende | F33: 0 | L33: 0 | M33: 0 | S33: 0 | T33: 0 | Z33: 0
A34: BE323 | B34: 3 | C34: BE | D34: Arr. Mons | E34: Arr. Mons | F34: 1.0160343 | H34: 1.0160343 | I34: 0 | K34: 0 | L34: 0 | M34: 1.0788139 | O34: 1.0788139 | P34: 0 | R34: 0 | S34: 0 | T34: 1.4605909 | V34: 1.4605909 | W34: 0 | Y34: 0 | Z34: 0
A35: BE328 | B35: 3 | C35: BE | D35: Arr. Tournai-Mouscron | E35: Arr. Tournai-Mouscron | F35: 1.9340859 | H35: 1.9340859 | M35: 2.053591 | O35: 2.053591 | T35: 2.7803278 | V35: 2.7803278
A36: BE32B | B36: 3 | C36: BE | D36: Arr. Charleroi | E36: Arr. Charleroi | F36: 0 | G36: 0 | M36: 0 | N36: 0 | T36: 0 | U36: 0
A37: BE32C | B37: 3 | C37: BE | D37: Arr. Soignies | E37: Arr. Soignies | F37: 0 | I37: 0 | L37: 0 | M37: 0 | P37: 0 | S37: 0 | T37: 0 | W37: 0 | Z37: 0
A38: BE32D | B38: 3 | C38: BE | D38: Arr. Thuin | E38: Arr. Thuin | F38: 0 | I38: 0 | M38: 0 | P38: 0 | T38: 0 | W38: 0
A39: BE332 | B39: 3 | C39: BE | D39: Arr. Liège | E39: Arr. Liège | F39: 1.1440438 | H39: 1.1440438 | M39: 1.214733 | O39: 1.214733 | T39: 1.6446098 | V39: 1.6446098
A40: BE335 | B40: 3 | C40: BE | D40: Arr. Verviers — communes francophones | E40: Arr. Verviers — communes francophones | F40: 0 | I40: 0 | M40: 0 | P40: 0 | T40: 0 | W40: 0
A41: BE352 | B41: 3 | C41: BE | D41: Arr. Namur | E41: Arr. Namur | F41: 0 | I41: 0 | L41: 0 | M41: 0 | P41: 0 | S41: 0 | T41: 0 | W41: 0 | Z41: 0
A42: BG313 | B42: 3 | C42: BG | D42: Vratsa | E42: Враца | F42: 0.45788156 | H42: 0.45788156 | M42: 0.48617356 | O42: 0.48617356 | T42: 0.65822351 | V42: 0.65822351
A43: BG314 | B43: 3 | C43: BG | D43: Pleven | E43: Плевен | F43: 0 | I43: 0 | M43: 0 | P43: 0 | T43: 0 | W43: 0
A44: BG315 | B44: 3 | C44: BG | D44: Lovech | E44: Ловеч | F44: 0.55308206 | H44: 0.55308206 | M44: 0.5872564 | O44: 0.5872564 | T44: 0.79507813 | V44: 0.79507813
A45: BG331 | B45: 3 | C45: BG | D45: Varna | E45: Варна | F45: 0.80745691 | H45: 0.80745691 | K45: 0 | M45: 0.85734879 | O45: 0.85734879 | R45: 0 | T45: 1.1607524 | V45: 1.1607524 | Y45: 0
A46: BG333 | B46: 3 | C46: BG | D46: Shumen | E46: Шумен | F46: 0 | I46: 0 | M46: 0 | P46: 0 | T46: 0 | W46: 0
A47: BG334 | B47: 3 | C47: BG | D47: Targovishte | E47: Търговище | F47: 0 | I47: 0 | M47: 0 | P47: 0 | T47: 0 | W47: 0
A48: BG341 | B48: 3 | C48: BG | D48: Burgas | E48: Бургас | F48: 0 | J48: 0 | M48: 0 | Q48: 0 | T48: 0 | X48: 0
A49: BG411 | B49: 3 | C49: BG | D49: Sofia (stolitsa) | E49: София (столица) | F49: 0 | I49: 0 | M49: 0 | P49: 0 | T49: 0 | W49: 0
A50: BG414 | B50: 3 | C50: BG | D50: Pernik | E50: Перник | F50: 0 | G50: 0 | M50: 0 | N50: 0 | T50: 0 | U50: 0
A51: BG421 | B51: 3 | C51: BG | D51: Plovdiv | E51: Пловдив | F51: 0 | I51: 0 | M51: 0 | P51: 0 | T51: 0 | W51: 0
A52: BG422 | B52: 3 | C52: BG | D52: Haskovo | E52: Хасково | F52: 0 | K52: 0 | M52: 0 | R52: 0 | T52: 0 | Y52: 0
A53: CY000 | B53: 3 | C53: CY | D53: Kýpros | E53: Κύπρος | F53: 1.4665179 | H53: 1.4665179 | M53: 1.5571324 | O53: 1.5571324 | T53: 2.1081796 | V53: 2.1081796
A54: CZ010 | B54: 3 | C54: CZ | D54: Hlavní město Praha | E54: Hlavní město Praha | F54: 0.55264471 | H54: 0.55264471 | M54: 0.58679202 | O54: 0.58679202 | T54: 0.79444942 | V54: 0.79444942
A55: CZ020 | B55: 3 | C55: CZ | D55: Středočeský kraj | E55: Středočeský kraj | F55: 0 | I55: 0 | J55: 0 | L55: 0 | M55: 0 | P55: 0 | Q55: 0 | S55: 0 | T55: 0 | W55: 0 | X55: 0 | Z55: 0
A56: CZ032 | B56: 3 | C56: CZ | D56: Plzeňský kraj | E56: Plzeňský kraj | F56: 0 | G56: 0 | I56: 0 | M56: 0 | N56: 0 | P56: 0 | T56: 0 | U56: 0 | W56: 0
A57: CZ041 | B57: 3 | C57: CZ | D57: Karlovarský kraj | E57: Karlovarský kraj | F57: 0 | I57: 0 | M57: 0 | P57: 0 | T57: 0 | W57: 0
A58: CZ042 | B58: 3 | C58: CZ | D58: Ústecký kraj | E58: Ústecký kraj | F58: 0.48957035 | H58: 0.48957035 | I58: 0 | J58: 0 | L58: 0 | M58: 0.51982037 | O58: 0.51982037 | P58: 0 | Q58: 0 | S58: 0 | T58: 0.70377745 | V58: 0.70377745 | W58: 0 | X58: 0 | Z58: 0
A59: CZ051 | B59: 3 | C59: CZ | D59: Liberecký kraj | E59: Liberecký kraj | F59: 0 | I59: 0 | M59: 0 | P59: 0 | T59: 0 | W59: 0
A60: CZ053 | B60: 3 | C60: CZ | D60: Pardubický kraj | E60: Pardubický kraj | F60: 0.65580969 | H60: 0.65580969 | I60: 0 | J60: 0 | M60: 0.69633145 | O60: 0.69633145 | P60: 0 | Q60: 0 | T60: 0.94275331 | V60: 0.94275331 | W60: 0 | X60: 0
A61: CZ063 | B61: 3 | C61: CZ | D61: Kraj Vysočina | E61: Kraj Vysočina | F61: 0 | I61: 0 | M61: 0 | P61: 0 | T61: 0 | W61: 0
A62: CZ064 | B62: 3 | C62: CZ | D62: Jihomoravský kraj | E62: Jihomoravský kraj | F62: 0.79105562 | H62: 0.79105562 | I62: 0 | M62: 0.83993408 | O62: 0.83993408 | P62: 0 | T62: 1.1371749 | V62: 1.1371749 | W62: 0
A63: CZ071 | B63: 3 | C63: CZ | D63: Olomoucký kraj | E63: Olomoucký kraj | F63: 0.66707588 | H63: 0.66707588 | L63: 0 | M63: 0.70829377 | O63: 0.70829377 | S63: 0 | T63: 0.95894892 | V63: 0.95894892 | Z63: 0
A64: CZ080 | B64: 3 | C64: CZ | D64: Moravskoslezský kraj | E64: Moravskoslezský kraj | F64: 0 | G64: 0 | I64: 0 | K64: 0 | L64: 0 | M64: 0 | N64: 0 | P64: 0 | R64: 0 | S64: 0 | T64: 0 | U64: 0 | W64: 0 | Y64: 0 | Z64: 0
A65: DE11C | B65: 3 | C65: DE | D65: Heidenheim | E65: Heidenheim | F65: 0.62310565 | H65: 0.62310565 | M65: 0.66160667 | O65: 0.66160667 | T65: 0.89573992 | V65: 0.89573992
A66: DE122 | B66: 3 | C66: DE | D66: Karlsruhe, Stadtkreis | E66: Karlsruhe, Stadtkreis | F66: 0 | J66: 0 | M66: 0 | Q66: 0 | T66: 0 | X66: 0
A67: DE123 | B67: 3 | C67: DE | D67: Karlsruhe, Landkreis | E67: Karlsruhe, Landkreis | F67: 0.54494439 | H67: 0.54494439 | M67: 0.57861591 | O67: 0.57861591 | T67: 0.7833799 | V67: 0.7833799
A68: DE126 | B68: 3 | C68: DE | D68: Mannheim, Stadtkreis | E68: Mannheim, Stadtkreis | F68: 0 | I68: 0 | M68: 0 | P68: 0 | T68: 0 | W68: 0
A69: DE128 | B69: 3 | C69: DE | D69: Rhein-Neckar-Kreis | E69: Rhein-Neckar-Kreis | F69: 0.57273405 | H69: 0.57273405 | M69: 0.60812266 | O69: 0.60812266 | T69: 0.82332867 | V69: 0.82332867
A70: DE131 | B70: 3 | C70: DE | D70: Freiburg im Breisgau, Stadtkreis | E70: Freiburg im Breisgau, Stadtkreis | F70: 0 | L70: 0 | M70: 0 | S70: 0 | T70: 0 | Z70: 0
A71: DE134 | B71: 3 | C71: DE | D71: Ortenaukreis | E71: Ortenaukreis | F71: 0 | G71: 0 | M71: 0 | N71: 0 | T71: 0 | U71: 0
A72: DE143 | B72: 3 | C72: DE | D72: Zollernalbkreis | E72: Zollernalbkreis | F72: 0.83152936 | H72: 0.83152936 | M72: 0.88290865 | O72: 0.88290865 | T72: 1.1953575 | V72: 1.1953575
A73: DE145 | B73: 3 | C73: DE | D73: Alb-Donau-Kreis | E73: Alb-Donau-Kreis | F73: 1.6115267 | H73: 1.6115267 | M73: 1.7111011 | O73: 1.7111011 | T73: 2.3166357 | V73: 2.3166357
A74: DE148 | B74: 3 | C74: DE | D74: Ravensburg | E74: Ravensburg | F74: 0 | I74: 0 | M74: 0 | P74: 0 | T74: 0 | W74: 0
A75: DE214 | B75: 3 | C75: DE | D75: Altötting | E75: Altötting | F75: 0 | J75: 0 | L75: 0 | M75: 0 | Q75: 0 | S75: 0 | T75: 0 | X75: 0 | Z75: 0
A76: DE219 | B76: 3 | C76: DE | D76: Eichstätt | E76: Eichstätt | F76: 0 | I76: 0 | J76: 0 | M76: 0 | P76: 0 | Q76: 0 | T76: 0 | W76: 0 | X76: 0
A77: DE21I | B77: 3 | C77: DE | D77: Neuburg-Schrobenhausen | E77: Neuburg-Schrobenhausen | F77: 0 | I77: 0 | M77: 0 | P77: 0 | T77: 0 | W77: 0
A78: DE21J | B78: 3 | C78: DE | D78: Pfaffenhofen a. d. Ilm | E78: Pfaffenhofen a. d. Ilm | F78: 0 | L78: 0 | M78: 0 | S78: 0 | T78: 0 | Z78: 0
A79: DE21K | B79: 3 | C79: DE | D79: Rosenheim, Landkreis | E79: Rosenheim, Landkreis | F79: 0.92191957 | H79: 0.92191957 | M79: 0.97888398 | O79: 0.97888398 | T79: 1.3252972 | V79: 1.3252972
A80: DE226 | B80: 3 | C80: DE | D80: Kelheim | E80: Kelheim | F80: 0 | J80: 0 | M80: 0 | Q80: 0 | T80: 0 | X80: 0
A81: DE229 | B81: 3 | C81: DE | D81: Regen | E81: Regen | F81: 0 | I81: 0 | M81: 0 | P81: 0 | T81: 0 | W81: 0
A82: DE237 | B82: 3 | C82: DE | D82: Neustadt a. d. Waldnaab | E82: Neustadt a. d. Waldnaab | F82: 0 | I82: 0 | M82: 0 | P82: 0 | T82: 0 | W82: 0
A83: DE239 | B83: 3 | C83: DE | D83: Schwandorf | E83: Schwandorf | F83: 0.99002931 | H83: 0.99002931 | M83: 1.0512021 | O83: 1.0512021 | T83: 1.4232077 | V83: 1.4232077
A84: DE24A | B84: 3 | C84: DE | D84: Kronach | E84: Kronach | F84: 0 | I84: 0 | M84: 0 | P84: 0 | T84: 0 | W84: 0
A85: DE24D | B85: 3 | C85: DE | D85: Wunsiedel i. Fichtelgebirge | E85: Wunsiedel i. Fichtelgebirge | F85: 0 | I85: 0 | M85: 0 | P85: 0 | T85: 0 | W85: 0
A86: DE25C | B86: 3 | C86: DE | D86: Weißenburg-Gunzenhausen | E86: Weißenburg-Gunzenhausen | F86: 0.3574926 | H86: 0.3574926 | M86: 0.37958167 | O86: 0.37958167 | T86: 0.51391026 | V86: 0.51391026
A87: DE26A | B87: 3 | C87: DE | D87: Main-Spessart | E87: Main-Spessart | F87: 1.4592345 | H87: 1.4592345 | I87: 0 | M87: 1.549399 | O87: 1.549399 | P87: 0 | T87: 2.0977094 | V87: 2.0977094 | W87: 0
A88: DE276 | B88: 3 | C88: DE | D88: Augsburg, Landkreis | E88: Augsburg, Landkreis | F88: 0 | G88: 0 | M88: 0 | N88: 0 | T88: 0 | U88: 0
A89: DE27D | B89: 3 | C89: DE | D89: Donau-Ries | E89: Donau-Ries | F89: 0.7050885 | H89: 0.7050885 | M89: 0.74865514 | O89: 0.74865514 | T89: 1.0135936 | V89: 1.0135936
A90: DE401 | B90: 3 | C90: DE | D90: Brandenburg an der Havel, Kreisfreie Stadt | E90: Brandenburg an der Havel, Kreisfreie Stadt | F90: 0 | G90: 0 | M90: 0 | N90: 0 | T90: 0 | U90: 0
A91: DE409 | B91: 3 | C91: DE | D91: Märkisch-Oderland | E91: Märkisch-Oderland | F91: 1.400266 | H91: 1.400266 | I91: 0 | M91: 1.4867869 | O91: 1.4867869 | P91: 0 | T91: 2.0129398 | V91: 2.0129398 | W91: 0
A92: DE40A | B92: 3 | C92: DE | D92: Oberhavel | E92: Oberhavel | F92: 0 | G92: 0 | M92: 0 | N92: 0 | T92: 0 | U92: 0
A93: DE40C | B93: 3 | C93: DE | D93: Oder-Spree | E93: Oder-Spree | F93: 0 | G93: 0 | M93: 0 | N93: 0 | T93: 0 | U93: 0
A94: DE40G | B94: 3 | C94: DE | D94: Spree-Neiße | E94: Spree-Neiße | F94: 0 | I94: 0 | M94: 0 | P94: 0 | T94: 0 | W94: 0
A95: DE40I | B95: 3 | C95: DE | D95: Uckermark | E95: Uckermark | F95: 0 | J95: 0 | M95: 0 | Q95: 0 | T95: 0 | X95: 0
A96: DE501 | B96: 3 | C96: DE | D96: Bremen, Kreisfreie Stadt | E96: Bremen, Kreisfreie Stadt | F96: 0 | G96: 0 | M96: 0 | N96: 0 | T96: 0 | U96: 0
A97: DE600 | B97: 3 | C97: DE | D97: Hamburg | E97: Hamburg | F97: 0 | G97: 0 | J97: 0 | M97: 0 | N97: 0 | Q97: 0 | T97: 0 | U97: 0 | X97: 0
A98: DE712 | B98: 3 | C98: DE | D98: Frankfurt am Main, Kreisfreie Stadt | E98: Frankfurt am Main, Kreisfreie Stadt | F98: 0 | L98: 0 | M98: 0 | S98: 0 | T98: 0 | Z98: 0
A99: DE714 | B99: 3 | C99: DE | D99: Wiesbaden, Kreisfreie Stadt | E99: Wiesbaden, Kreisfreie Stadt | F99: 0.21849156 | H99: 0.21849156 | M99: 0.23199191 | O99: 0.23199191 | T99: 0.31409057 | V99: 0.31409057
A100: DE722 | B100: 3 | C100: DE | D100: Lahn-Dill-Kreis | E100: Lahn-Dill-Kreis | F100: 0 | G100: 0 | M100: 0 | N100: 0 | T100: 0 | U100: 0
A101: DE732 | B101: 3 | C101: DE | D101: Fulda | E101: Fulda | F101: 0.15542099 | H101: 0.15542099 | M101: 0.16502428 | O101: 0.16502428 | T101: 0.22342405 | V101: 0.22342405
A102: DE80M | B102: 3 | C102: DE | D102: Nordwestmecklenburg | E102: Nordwestmecklenburg | F102: 0 | L102: 0 | M102: 0 | S102: 0 | T102: 0 | Z102: 0
A103: DE80O | B103: 3 | C103: DE | D103: Ludwigslust-Parchim | E103: Ludwigslust-Parchim | F103: 0 | I103: 0 | M103: 0 | P103: 0 | T103: 0 | W103: 0
A104: DE912 | B104: 3 | C104: DE | D104: Salzgitter, Kreisfreie Stadt | E104: Salzgitter, Kreisfreie Stadt | F104: 0 | G104: 0 | M104: 0 | N104: 0 | T104: 0 | U104: 0
A105: DE91A | B105: 3 | C105: DE | D105: Peine | E105: Peine | F105: 0 | G105: 0 | M105: 0 | N105: 0 | T105: 0 | U105: 0
A106: DE91C | B106: 3 | C106: DE | D106: Göttingen | E106: Göttingen | F106: 0 | L106: 0 | M106: 0 | S106: 0 | T106: 0 | Z106: 0
A107: DE922 | B107: 3 | C107: DE | D107: Diepholz | E107: Diepholz | F107: 0 | L107: 0 | M107: 0 | S107: 0 | T107: 0 | Z107: 0
A108: DE923 | B108: 3 | C108: DE | D108: Hameln-Pyrmont | E108: Hameln-Pyrmont | F108: 0 | I108: 0 | M108: 0 | P108: 0 | T108: 0 | W108: 0
A109: DE926 | B109: 3 | C109: DE | D109: Holzminden | E109: Holzminden | F109: 0 | I109: 0 | M109: 0 | P109: 0 | T109: 0 | W109: 0
A110: DE927 | B110: 3 | C110: DE | D110: Nienburg (Weser) | E110: Nienburg (Weser) | F110: 0 | I110: 0 | L110: 0 | M110: 0 | P110: 0 | S110: 0 | T110: 0 | W110: 0 | Z110: 0
A111: DE928 | B111: 3 | C111: DE | D111: Schaumburg | E111: Schaumburg | F111: 0 | I111: 0 | M111: 0 | P111: 0 | T111: 0 | W111: 0
...

Sheet Biomass (PJ per y)
F12: 2018 | M12: 2030 | T12: 2050
A13: NUTS ID | B13: NUTS LEVEL | C13: Country code | D13: NUTS region name (Latin) | E13: NUTS_NAME | F13: All sectors (PJ/y) | G13: Steel (PJ/y) | H13: Cement (PJ/y) | I13: Glass (PJ/y) | J13: Refineries (PJ/y) | K13: Fertilisers (PJ/y) | L13: Chemical (PJ/y) | M13: All sectors (PJ/y) | N13: Steel (PJ/y) | O13: Cement (PJ/y) | P13: Glass (PJ/y) | Q13: Refineries (PJ/y) | R13: Fertilisers (PJ/y) | S13: Chemical (PJ/y) | T13: All sectors (PJ/y) | U13: Steel (PJ/y) | V13: Cement (PJ/y) | W13: Glass (PJ/y) | X13: Refineries (PJ/y) | Y13: Fertilisers (PJ/y) | Z13: Chemical (PJ/y)
A14: AT121 | B14: 3 | C14: AT | D14: Mostviertel-Eisenwurzen | E14: Mostviertel-Eisenwurzen | F14: 0 | I14: 0 | M14: 0 | P14: 0 | T14: 0 | W14: 0
A15: AT122 | B15: 3 | C15: AT | D15: Niederösterreich-Süd | E15: Niederösterreich-Süd | F15: 0 | H15: 0 | M15: 0 | O15: 0 | T15: 0 | V15: 0
A16: AT124 | B16: 3 | C16: AT | D16: Waldviertel | E16: Waldviertel | F16: 0 | L16: 0 | M16: 0 | S16: 0 | T16: 0 | Z16: 0
A17: AT127 | B17: 3 | C17: AT | D17: Wiener Umland/Südteil | E17: Wiener Umland/Südteil | F17: 0 | H17: 0 | J17: 0 | L17: 0 | M17: 48.929524 | O17: 0 | Q17: 40.193194 | S17: 8.7363299 | T17: 79.465586 | V17: 0 | X17: 50.941349 | Z17: 28.524237
A18: AT213 | B18: 3 | C18: AT | D18: Unterkärnten | E18: Unterkärnten | F18: 0 | H18: 0 | M18: 0 | O18: 0 | T18: 0 | V18: 0
A19: AT221 | B19: 3 | C19: AT | D19: Graz | E19: Graz | F19: 0 | G19: 0 | M19: 0 | N19: 0 | T19: 0 | U19: 0
A20: AT223 | B20: 3 | C20: AT | D20: Östliche Obersteiermark | E20: Östliche Obersteiermark | F20: 0 | G20: 0 | M20: 0 | N20: 0 | T20: 0 | U20: 0
A21: AT225 | B21: 3 | C21: AT | D21: West- und Südsteiermark | E21: West- und Südsteiermark | F21: 0 | H21: 0 | I21: 0 | M21: 0 | O21: 0 | P21: 0 | T21: 0 | V21: 0 | W21: 0
A22: AT312 | B22: 3 | C22: AT | D22: Linz-Wels | E22: Linz-Wels | F22: 0 | G22: 0 | K22: 0 | L22: 0 | M22: 0.23749138 | N22: 0 | R22: 0.23749138 | S22: 0 | T22: 0.77560869 | U22: 0 | Y22: 0.77560869 | Z22: 0
A23: AT314 | B23: 3 | C23: AT | D23: Steyr-Kirchdorf | E23: Steyr-Kirchdorf | F23: 0 | H23: 0 | I23: 0 | M23: 0 | O23: 0 | P23: 0 | T23: 0 | V23: 0 | W23: 0
A24: AT315 | B24: 3 | C24: AT | D24: Traunviertel | E24: Traunviertel | F24: 0 | H24: 0 | M24: 0 | O24: 0 | T24: 0 | V24: 0
A25: AT323 | B25: 3 | C25: AT | D25: Salzburg und Umgebung | E25: Salzburg und Umgebung | F25: 0 | H25: 0 | M25: 0 | O25: 0 | T25: 0 | V25: 0
A26: AT331 | B26: 3 | C26: AT | D26: Außerfern | E26: Außerfern | F26: 0 | H26: 0 | M26: 0 | O26: 0 | T26: 0 | V26: 0
A27: BE211 | B27: 3 | C27: BE | D27: Arr. Antwerpen | E27: Arr. Antwerpen | F27: 0 | J27: 0 | K27: 0 | L27: 0 | M27: 177.73776 | Q27: 161.18714 | R27: 0.34245333 | S27: 16.208163 | T27: 258.32884 | X27: 204.29056 | Y27: 1.1183975 | Z27: 52.919877
A28: BE213 | B28: 3 | C28: BE | D28: Arr. Turnhout | E28: Arr. Turnhout | F28: 0 | I28: 0 | L28: 0 | M28: 0 | P28: 0 | S28: 0 | T28: 0 | W28: 0 | Z28: 0
A29: BE224 | B29: 3 | C29: BE | D29: Arr. Hasselt | E29: Arr. Hasselt | F29: 0 | G29: 0 | L29: 0 | M29: 0 | N29: 0 | S29: 0 | T29: 0 | U29: 0 | Z29: 0
A30: BE233 | B30: 3 | C30: BE | D30: Arr. Eeklo | E30: Arr. Eeklo | F30: 0 | L30: 0 | M30: 0.25118162 | S30: 0.25118162 | T30: 0.82011144 | Z30: 0.82011144
A31: BE234 | B31: 3 | C31: BE | D31: Arr. Gent | E31: Arr. Gent | F31: 0 | G31: 0 | L31: 0 | M31: 0 | N31: 0 | S31: 0 | T31: 0 | U31: 0 | Z31: 0
A32: BE236 | B32: 3 | C32: BE | D32: Arr. Sint-Niklaas | E32: Arr. Sint-Niklaas | F32: 0 | L32: 0 | M32: 0 | S32: 0 | T32: 0 | Z32: 0
A33: BE255 | B33: 3 | C33: BE | D33: Arr. Oostende | E33: Arr. Oostende | F33: 0 | L33: 0 | M33: 0 | S33: 0 | T33: 0 | Z33: 0
A34: BE323 | B34: 3 | C34: BE | D34: Arr. Mons | E34: Arr. Mons | F34: 0 | H34: 0 | I34: 0 | K34: 0 | L34: 0 | M34: 0.42240828 | O34: 0 | P34: 0 | R34: 0.17122666 | S34: 0.25118162 | T34: 1.3793102 | V34: 0 | W34: 0 | Y34: 0.55919877 | Z34: 0.82011144
A35: BE328 | B35: 3 | C35: BE | D35: Arr. Tournai-Mouscron | E35: Arr. Tournai-Mouscron | F35: 0 | H35: 0 | M35: 0 | O35: 0 | T35: 0 | V35: 0
A36: BE32B | B36: 3 | C36: BE | D36: Arr. Charleroi | E36: Arr. Charleroi | F36: 0 | G36: 0 | M36: 0 | N36: 0 | T36: 0 | U36: 0
A37: BE32C | B37: 3 | C37: BE | D37: Arr. Soignies | E37: Arr. Soignies | F37: 0 | I37: 0 | L37: 0 | M37: 0 | P37: 0 | S37: 0 | T37: 0 | W37: 0 | Z37: 0
A38: BE32D | B38: 3 | C38: BE | D38: Arr. Thuin | E38: Arr. Thuin | F38: 0 | I38: 0 | M38: 0 | P38: 0 | T38: 0 | W38: 0
A39: BE332 | B39: 3 | C39: BE | D39: Arr. Liège | E39: Arr. Liège | F39: 0 | H39: 0 | M39: 0 | O39: 0 | T39: 0 | V39: 0
A40: BE335 | B40: 3 | C40: BE | D40: Arr. Verviers — communes francophones | E40: Arr. Verviers — communes francophones | F40: 0 | I40: 0 | M40: 0 | P40: 0 | T40: 0 | W40: 0
A41: BE352 | B41: 3 | C41: BE | D41: Arr. Namur | E41: Arr. Namur | F41: 0 | I41: 0 | L41: 0 | M41: 0 | P41: 0 | S41: 0 | T41: 0 | W41: 0 | Z41: 0
A42: BG313 | B42: 3 | C42: BG | D42: Vratsa | E42: Враца | F42: 0 | H42: 0 | M42: 0 | O42: 0 | T42: 0 | V42: 0
A43: BG314 | B43: 3 | C43: BG | D43: Pleven | E43: Плевен | F43: 0 | I43: 0 | M43: 0 | P43: 0 | T43: 0 | W43: 0
A44: BG315 | B44: 3 | C44: BG | D44: Lovech | E44: Ловеч | F44: 0 | H44: 0 | M44: 0 | O44: 0 | T44: 0 | V44: 0
A45: BG331 | B45: 3 | C45: BG | D45: Varna | E45: Варна | F45: 0 | H45: 0 | K45: 0 | M45: 0.173367 | O45: 0 | R45: 0.173367 | T45: 0.56618875 | V45: 0 | Y45: 0.56618875
A46: BG333 | B46: 3 | C46: BG | D46: Shumen | E46: Шумен | F46: 0 | I46: 0 | M46: 0 | P46: 0 | T46: 0 | W46: 0
A47: BG334 | B47: 3 | C47: BG | D47: Targovishte | E47: Търговище | F47: 0 | I47: 0 | M47: 0 | P47: 0 | T47: 0 | W47: 0
A48: BG341 | B48: 3 | C48: BG | D48: Burgas | E48: Бургас | F48: 0 | J48: 0 | M48: 40.607557 | Q48: 40.607557 | T48: 51.466517 | X48: 51.466517
A49: BG411 | B49: 3 | C49: BG | D49: Sofia (stolitsa) | E49: София (столица) | F49: 0 | I49: 0 | M49: 0 | P49: 0 | T49: 0 | W49: 0
A50: BG414 | B50: 3 | C50: BG | D50: Pernik | E50: Перник | F50: 0 | G50: 0 | M50: 0 | N50: 0 | T50: 0 | U50: 0
A51: BG421 | B51: 3 | C51: BG | D51: Plovdiv | E51: Пловдив | F51: 0 | I51: 0 | M51: 0 | P51: 0 | T51: 0 | W51: 0
A52: BG422 | B52: 3 | C52: BG | D52: Haskovo | E52: Хасково | F52: 0 | K52: 0 | M52: 0.19263 | R52: 0.19263 | T52: 0.62909862 | Y52: 0.62909862
A53: CY000 | B53: 3 | C53: CY | D53: Kýpros | E53: Κύπρος | F53: 0 | H53: 0 | M53: 0 | O53: 0 | T53: 0 | V53: 0
A54: CZ010 | B54: 3 | C54: CZ | D54: Hlavní město Praha | E54: Hlavní město Praha | F54: 0 | H54: 0 | M54: 0 | O54: 0 | T54: 0 | V54: 0
A55: CZ020 | B55: 3 | C55: CZ | D55: Středočeský kraj | E55: Středočeský kraj | F55: 0 | I55: 0 | J55: 0 | L55: 0 | M55: 14.339518 | P55: 0 | Q55: 14.088336 | S55: 0.25118162 | T55: 18.675842 | W55: 0 | X55: 17.85573 | Z55: 0.82011144
A56: CZ032 | B56: 3 | C56: CZ | D56: Plzeňský kraj | E56: Plzeňský kraj | F56: 0 | G56: 0 | I56: 0 | M56: 0 | N56: 0 | P56: 0 | T56: 0 | U56: 0 | W56: 0
A57: CZ041 | B57: 3 | C57: CZ | D57: Karlovarský kraj | E57: Karlovarský kraj | F57: 0 | I57: 0 | M57: 0 | P57: 0 | T57: 0 | W57: 0
A58: CZ042 | B58: 3 | C58: CZ | D58: Ústecký kraj | E58: Ústecký kraj | F58: 0 | H58: 0 | I58: 0 | J58: 0 | L58: 0 | M58: 31.88072 | O58: 0 | P58: 0 | Q58: 22.375593 | S58: 9.5051269 | T58: 59.393472 | V58: 0 | W58: 0 | X58: 28.359101 | Z58: 31.03437
A59: CZ051 | B59: 3 | C59: CZ | D59: Liberecký kraj | E59: Liberecký kraj | F59: 0 | I59: 0 | M59: 0 | P59: 0 | T59: 0 | W59: 0
A60: CZ053 | B60: 3 | C60: CZ | D60: Pardubický kraj | E60: Pardubický kraj | F60: 0 | H60: 0 | I60: 0 | J60: 0 | M60: 3.3149026 | O60: 0 | P60: 0 | Q60: 3.3149026 | T60: 4.2013483 | V60: 0 | W60: 0 | X60: 4.2013483
A61: CZ063 | B61: 3 | C61: CZ | D61: Kraj Vysočina | E61: Kraj Vysočina | F61: 0 | I61: 0 | M61: 0 | P61: 0 | T61: 0 | W61: 0
A62: CZ064 | B62: 3 | C62: CZ | D62: Jihomoravský kraj | E62: Jihomoravský kraj | F62: 0 | H62: 0 | I62: 0 | M62: 0 | O62: 0 | P62: 0 | T62: 0 | V62: 0 | W62: 0
A63: CZ071 | B63: 3 | C63: CZ | D63: Olomoucký kraj | E63: Olomoucký kraj | F63: 0 | H63: 0 | L63: 0 | M63: 0.25118162 | O63: 0 | S63: 0.25118162 | T63: 0.82011144 | V63: 0 | Z63: 0.82011144
A64: CZ080 | B64: 3 | C64: CZ | D64: Moravskoslezský kraj | E64: Moravskoslezský kraj | F64: 0 | G64: 0 | I64: 0 | K64: 0 | L64: 0 | M64: 0.40100495 | N64: 0 | P64: 0 | R64: 0.14982333 | S64: 0.25118162 | T64: 1.3094104 | U64: 0 | W64: 0 | Y64: 0.48929892 | Z64: 0.82011144
A65: DE11C | B65: 3 | C65: DE | D65: Heidenheim | E65: Heidenheim | F65: 0 | H65: 0 | M65: 0 | O65: 0 | T65: 0 | V65: 0
A66: DE122 | B66: 3 | C66: DE | D66: Karlsruhe, Stadtkreis | E66: Karlsruhe, Stadtkreis | F66: 0 | J66: 0 | M66: 64.226238 | Q66: 64.226238 | T66: 81.401124 | X66: 81.401124
A67: DE123 | B67: 3 | C67: DE | D67: Karlsruhe, Landkreis | E67: Karlsruhe, Landkreis | F67: 0 | H67: 0 | M67: 0 | O67: 0 | T67: 0 | V67: 0
A68: DE126 | B68: 3 | C68: DE | D68: Mannheim, Stadtkreis | E68: Mannheim, Stadtkreis | F68: 0 | I68: 0 | M68: 0 | P68: 0 | T68: 0 | W68: 0
A69: DE128 | B69: 3 | C69: DE | D69: Rhein-Neckar-Kreis | E69: Rhein-Neckar-Kreis | F69: 0 | H69: 0 | M69: 0 | O69: 0 | T69: 0 | V69: 0
A70: DE131 | B70: 3 | C70: DE | D70: Freiburg im Breisgau, Stadtkreis | E70: Freiburg im Breisgau, Stadtkreis | F70: 0 | L70: 0 | M70: 0 | S70: 0 | T70: 0 | Z70: 0
A71: DE134 | B71: 3 | C71: DE | D71: Ortenaukreis | E71: Ortenaukreis | F71: 0 | G71: 0 | M71: 0 | N71: 0 | T71: 0 | U71: 0
A72: DE143 | B72: 3 | C72: DE | D72: Zollernalbkreis | E72: Zollernalbkreis | F72: 0 | H72: 0 | M72: 0 | O72: 0 | T72: 0 | V72: 0
A73: DE145 | B73: 3 | C73: DE | D73: Alb-Donau-Kreis | E73: Alb-Donau-Kreis | F73: 0 | H73: 0 | M73: 0 | O73: 0 | T73: 0 | V73: 0
A74: DE148 | B74: 3 | C74: DE | D74: Ravensburg | E74: Ravensburg | F74: 0 | I74: 0 | M74: 0 | P74: 0 | T74: 0 | W74: 0
A75: DE214 | B75: 3 | C75: DE | D75: Altötting | E75: Altötting | F75: 0 | J75: 0 | L75: 0 | M75: 23.194122 | Q75: 15.331425 | S75: 7.8626969 | T75: 45.10305 | X75: 19.431236 | Z75: 25.671814
A76: DE219 | B76: 3 | C76: DE | D76: Eichstätt | E76: Eichstätt | F76: 0 | I76: 0 | J76: 0 | M76: 22.789956 | P76: 0 | Q76: 22.789956 | T76: 28.88427 | W76: 0 | X76: 28.88427
A77: DE21I | B77: 3 | C77: DE | D77: Neuburg-Schrobenhausen | E77: Neuburg-Schrobenhausen | F77: 0 | I77: 0 | M77: 0 | P77: 0 | T77: 0 | W77: 0
A78: DE21J | B78: 3 | C78: DE | D78: Pfaffenhofen a. d. Ilm | E78: Pfaffenhofen a. d. Ilm | F78: 0 | L78: 0 | M78: 0.88591942 | S78: 0.88591942 | T78: 2.8925391 | Z78: 2.8925391
A79: DE21K | B79: 3 | C79: DE | D79: Rosenheim, Landkreis | E79: Rosenheim, Landkreis | F79: 0 | H79: 0 | M79: 0 | O79: 0 | T79: 0 | V79: 0
A80: DE226 | B80: 3 | C80: DE | D80: Kelheim | E80: Kelheim | F80: 0 | J80: 0 | M80: 19.06069 | Q80: 19.06069 | T80: 24.157753 | X80: 24.157753
A81: DE229 | B81: 3 | C81: DE | D81: Regen | E81: Regen | F81: 0 | I81: 0 | M81: 0 | P81: 0 | T81: 0 | W81: 0
A82: DE237 | B82: 3 | C82: DE | D82: Neustadt a. d. Waldnaab | E82: Neustadt a. d. Waldnaab | F82: 0 | I82: 0 | M82: 0 | P82: 0 | T82: 0 | W82: 0
A83: DE239 | B83: 3 | C83: DE | D83: Schwandorf | E83: Schwandorf | F83: 0 | H83: 0 | M83: 0 | O83: 0 | T83: 0 | V83: 0
A84: DE24A | B84: 3 | C84: DE | D84: Kronach | E84: Kronach | F84: 0 | I84: 0 | M84: 0 | P84: 0 | T84: 0 | W84: 0
A85: DE24D | B85: 3 | C85: DE | D85: Wunsiedel i. Fichtelgebirge | E85: Wunsiedel i. Fichtelgebirge | F85: 0 | I85: 0 | M85: 0 | P85: 0 | T85: 0 | W85: 0
A86: DE25C | B86: 3 | C86: DE | D86: Weißenburg-Gunzenhausen | E86: Weißenburg-Gunzenhausen | F86: 0 | H86: 0 | M86: 0 | O86: 0 | T86: 0 | V86: 0
A87: DE26A | B87: 3 | C87: DE | D87: Main-Spessart | E87: Main-Spessart | F87: 0 | H87: 0 | I87: 0 | M87: 0 | O87: 0 | P87: 0 | T87: 0 | V87: 0 | W87: 0
A88: DE276 | B88: 3 | C88: DE | D88: Augsburg, Landkreis | E88: Augsburg, Landkreis | F88: 0 | G88: 0 | M88: 0 | N88: 0 | T88: 0 | U88: 0
A89: DE27D | B89: 3 | C89: DE | D89: Donau-Ries | E89: Donau-Ries | F89: 0 | H89: 0 | M89: 0 | O89: 0 | T89: 0 | V89: 0
A90: DE401 | B90: 3 | C90: DE | D90: Brandenburg an der Havel, Kreisfreie Stadt | E90: Brandenburg an der Havel, Kreisfreie Stadt | F90: 0 | G90: 0 | M90: 0 | N90: 0 | T90: 0 | U90: 0
A91: DE409 | B91: 3 | C91: DE | D91: Märkisch-Oderland | E91: Märkisch-Oderland | F91: 0 | H91: 0 | I91: 0 | M91: 0 | O91: 0 | P91: 0 | T91: 0 | V91: 0 | W91: 0
A92: DE40A | B92: 3 | C92: DE | D92: Oberhavel | E92: Oberhavel | F92: 0 | G92: 0 | M92: 0 | N92: 0 | T92: 0 | U92: 0
A93: DE40C | B93: 3 | C93: DE | D93: Oder-Spree | E93: Oder-Spree | F93: 0 | G93: 0 | M93: 0 | N93: 0 | T93: 0 | U93: 0
A94: DE40G | B94: 3 | C94: DE | D94: Spree-Neiße | E94: Spree-Neiße | F94: 0 | I94: 0 | M94: 0 | P94: 0 | T94: 0 | W94: 0
A95: DE40I | B95: 3 | C95: DE | D95: Uckermark | E95: Uckermark | F95: 0 | J95: 0 | M95: 45.579911 | Q95: 45.579911 | T95: 57.76854 | X95: 57.76854
A96: DE501 | B96: 3 | C96: DE | D96: Bremen, Kreisfreie Stadt | E96: Bremen, Kreisfreie Stadt | F96: 0 | G96: 0 | M96: 0 | N96: 0 | T96: 0 | U96: 0
A97: DE600 | B97: 3 | C97: DE | D97: Hamburg | E97: Hamburg | F97: 0 | G97: 0 | J97: 0 | M97: 41.850646 | N97: 0 | Q97: 41.850646 | T97: 53.042023 | U97: 0 | X97: 53.042023
A98: DE712 | B98: 3 | C98: DE | D98: Frankfurt am Main, Kreisfreie Stadt | E98: Frankfurt am Main, Kreisfreie Stadt | F98: 0 | L98: 0 | M98: 2.3063911 | S98: 2.3063911 | T98: 7.5303987 | Z98: 7.5303987
A99: DE714 | B99: 3 | C99: DE | D99: Wiesbaden, Kreisfreie Stadt | E99: Wiesbaden, Kreisfreie Stadt | F99: 0 | H99: 0 | M99: 0 | O99: 0 | T99: 0 | V99: 0
A100: DE722 | B100: 3 | C100: DE | D100: Lahn-Dill-Kreis | E100: Lahn-Dill-Kreis | F100: 0 | G100: 0 | M100: 0 | N100: 0 | T100: 0 | U100: 0
A101: DE732 | B101: 3 | C101: DE | D101: Fulda | E101: Fulda | F101: 0 | H101: 0 | M101: 0 | O101: 0 | T101: 0 | V101: 0
A102: DE80M | B102: 3 | C102: DE | D102: Nordwestmecklenburg | E102: Nordwestmecklenburg | F102: 0 | L102: 0 | M102: 0.25118162 | S102: 0.25118162 | T102: 0.82011144 | Z102: 0.82011144
A103: DE80O | B103: 3 | C103: DE | D103: Ludwigslust-Parchim | E103: Ludwigslust-Parchim | F103: 0 | I103: 0 | M103: 0 | P103: 0 | T103: 0 | W103: 0
A104: DE912 | B104: 3 | C104: DE | D104: Salzgitter, Kreisfreie Stadt | E104: Salzgitter, Kreisfreie Stadt | F104: 0 | G104: 0 | M104: 0 | N104: 0 | T104: 0 | U104: 0
A105: DE91A | B105: 3 | C105: DE | D105: Peine | E105: Peine | F105: 0 | G105: 0 | M105: 0 | N105: 0 | T105: 0 | U105: 0
A106: DE91C | B106: 3 | C106: DE | D106: Göttingen | E106: Göttingen | F106: 0 | L106: 0 | M106: 0 | S106: 0 | T106: 0 | Z106: 0
A107: DE922 | B107: 3 | C107: DE | D107: Diepholz | E107: Diepholz | F107: 0 | L107: 0 | M107: 0 | S107: 0 | T107: 0 | Z107: 0
A108: DE923 | B108: 3 | C108: DE | D108: Hameln-Pyrmont | E108: Hameln-Pyrmont | F108: 0 | I108: 0 | M108: 0 | P108: 0 | T108: 0 | W108: 0
A109: DE926 | B109: 3 | C109: DE | D109: Holzminden | E109: Holzminden | F109: 0 | I109: 0 | M109: 0 | P109: 0 | T109: 0 | W109: 0
A110: DE927 | B110: 3 | C110: DE | D110: Nienburg (Weser) | E110: Nienburg (Weser) | F110: 0 | I110: 0 | L110: 0 | M110: 0 | P110: 0 | S110: 0 | T110: 0 | W110: 0 | Z110: 0
A111: DE928 | B111: 3 | C111: DE | D111: Schaumburg | E111: Schaumburg | F111: 0 | I111: 0 | M111: 0 | P111: 0 | T111: 0 | W111: 0
...

Sheet Biomass waste (PJ per y)
F12: 2018 | M12: 2030 | T12: 2050
A13: NUTS ID | B13: NUTS LEVEL | C13: Country code | D13: NUTS region name (Latin) | E13: NUTS_NAME | F13: All sectors (PJ/y) | G13: Steel (PJ/y) | H13: Cement (PJ/y) | I13: Glass (PJ/y) | J13: Refineries (PJ/y) | K13: Fertilisers (PJ/y) | L13: Chemical (PJ/y) | M13: All sectors (PJ/y) | N13: Steel (PJ/y) | O13: Cement (PJ/y) | P13: Glass (PJ/y) | Q13: Refineries (PJ/y) | R13: Fertilisers (PJ/y) | S13: Chemical (PJ/y) | T13: All sectors (PJ/y) | U13: Steel (PJ/y) | V13: Cement (PJ/y) | W13: Glass (PJ/y) | X13: Refineries (PJ/y) | Y13: Fertilisers (PJ/y) | Z13: Chemical (PJ/y)
A14: AT121 | B14: 3 | C14: AT | D14: Mostviertel-Eisenwurzen | E14: Mostviertel-Eisenwurzen | F14: 0 | I14: 0 | M14: 0 | P14: 0 | T14: 0 | W14: 0
A15: AT122 | B15: 3 | C15: AT | D15: Niederösterreich-Süd | E15: Niederösterreich-Süd | F15: 0.19912983 | H15: 0.19912983 | M15: 0.27195413 | O15: 0.27195413 | T15: 0.71484749 | V15: 0.71484749
A16: AT124 | B16: 3 | C16: AT | D16: Waldviertel | E16: Waldviertel | F16: 0 | L16: 0 | M16: 0 | S16: 0 | T16: 0 | Z16: 0
A17: AT127 | B17: 3 | C17: AT | D17: Wiener Umland/Südteil | E17: Wiener Umland/Südteil | F17: 0.41313327 | H17: 0.41313327 | J17: 0 | L17: 0 | M17: 0.56422134 | O17: 0.56422134 | Q17: 0 | S17: 0 | T17: 1.4830891 | V17: 1.4830891 | X17: 0 | Z17: 0
A18: AT213 | B18: 3 | C18: AT | D18: Unterkärnten | E18: Unterkärnten | F18: 0.29879103 | H18: 0.29879103 | M18: 0.40806269 | O18: 0.40806269 | T18: 1.0726169 | V18: 1.0726169
A19: AT221 | B19: 3 | C19: AT | D19: Graz | E19: Graz | F19: 0 | G19: 0 | M19: 0 | N19: 0 | T19: 0 | U19: 0
A20: AT223 | B20: 3 | C20: AT | D20: Östliche Obersteiermark | E20: Östliche Obersteiermark | F20: 0 | G20: 0 | M20: 0 | N20: 0 | T20: 0 | U20: 0
A21: AT225 | B21: 3 | C21: AT | D21: West- und Südsteiermark | E21: West- und Südsteiermark | F21: 0.22165914 | H21: 0.22165914 | I21: 0 | M21: 0.30272269 | O21: 0.30272269 | P21: 0 | T21: 0.79572448 | V21: 0.79572448 | W21: 0
A22: AT312 | B22: 3 | C22: AT | D22: Linz-Wels | E22: Linz-Wels | F22: 0 | G22: 0 | K22: 0 | L22: 0 | M22: 0 | N22: 0 | R22: 0 | S22: 0 | T22: 0 | U22: 0 | Y22: 0 | Z22: 0
A23: AT314 | B23: 3 | C23: AT | D23: Steyr-Kirchdorf | E23: Steyr-Kirchdorf | F23: 0.15345904 | H23: 0.15345904 | I23: 0 | M23: 0.20958096 | O23: 0.20958096 | P23: 0 | T23: 0.55089594 | V23: 0.55089594 | W23: 0
A24: AT315 | B24: 3 | C24: AT | D24: Traunviertel | E24: Traunviertel | F24: 0.22399462 | H24: 0.22399462 | M24: 0.30591229 | O24: 0.30591229 | T24: 0.80410854 | V24: 0.80410854
A25: AT323 | B25: 3 | C25: AT | D25: Salzburg und Umgebung | E25: Salzburg und Umgebung | F25: 0.21210819 | H25: 0.21210819 | M25: 0.28967884 | O25: 0.28967884 | T25: 0.76143794 | V25: 0.76143794
A26: AT331 | B26: 3 | C26: AT | D26: Außerfern | E26: Außerfern | F26: 0.14636968 | H26: 0.14636968 | M26: 0.19989893 | O26: 0.19989893 | T26: 0.52544615 | V26: 0.52544615
A27: BE211 | B27: 3 | C27: BE | D27: Arr. Antwerpen | E27: Arr. Antwerpen | F27: 0 | J27: 0 | K27: 0 | L27: 0 | M27: 0 | Q27: 0 | R27: 0 | S27: 0 | T27: 0 | X27: 0 | Y27: 0 | Z27: 0
A28: BE213 | B28: 3 | C28: BE | D28: Arr. Turnhout | E28: Arr. Turnhout | F28: 0 | I28: 0 | L28: 0 | M28: 0 | P28: 0 | S28: 0 | T28: 0 | W28: 0 | Z28: 0
A29: BE224 | B29: 3 | C29: BE | D29: Arr. Hasselt | E29: Arr. Hasselt | F29: 0 | G29: 0 | L29: 0 | M29: 0 | N29: 0 | S29: 0 | T29: 0 | U29: 0 | Z29: 0
A30: BE233 | B30: 3 | C30: BE | D30: Arr. Eeklo | E30: Arr. Eeklo | F30: 0 | L30: 0 | M30: 0 | S30: 0 | T30: 0 | Z30: 0
A31: BE234 | B31: 3 | C31: BE | D31: Arr. Gent | E31: Arr. Gent | F31: 0 | G31: 0 | L31: 0 | M31: 0 | N31: 0 | S31: 0 | T31: 0 | U31: 0 | Z31: 0
A32: BE236 | B32: 3 | C32: BE | D32: Arr. Sint-Niklaas | E32: Arr. Sint-Niklaas | F32: 0 | L32: 0 | M32: 0 | S32: 0 | T32: 0 | Z32: 0
A33: BE255 | B33: 3 | C33: BE | D33: Arr. Oostende | E33: Arr. Oostende | F33: 0 | L33: 0 | M33: 0 | S33: 0 | T33: 0 | Z33: 0
A34: BE323 | B34: 3 | C34: BE | D34: Arr. Mons | E34: Arr. Mons | F34: 0.60949 | H34: 0.60949 | I34: 0 | K34: 0 | L34: 0 | M34: 0.83238821 | O34: 0.83238821 | P34: 0 | R34: 0 | S34: 0 | T34: 2.1879816 | V34: 2.1879816 | W34: 0 | Y34: 0 | Z34: 0
A35: BE328 | B35: 3 | C35: BE | D35: Arr. Tournai-Mouscron | E35: Arr. Tournai-Mouscron | F35: 1.160203 | H35: 1.160203 | M35: 1.5845039 | O35: 1.5845039 | T35: 4.1649622 | V35: 4.1649622
A36: BE32B | B36: 3 | C36: BE | D36: Arr. Charleroi | E36: Arr. Charleroi | F36: 0 | G36: 0 | M36: 0 | N36: 0 | T36: 0 | U36: 0
A37: BE32C | B37: 3 | C37: BE | D37: Arr. Soignies | E37: Arr. Soignies | F37: 0 | I37: 0 | L37: 0 | M37: 0 | P37: 0 | S37: 0 | T37: 0 | W37: 0 | Z37: 0
A38: BE32D | B38: 3 | C38: BE | D38: Arr. Thuin | E38: Arr. Thuin | F38: 0 | I38: 0 | M38: 0 | P38: 0 | T38: 0 | W38: 0
A39: BE332 | B39: 3 | C39: BE | D39: Arr. Liège | E39: Arr. Liège | F39: 0.68627925 | H39: 0.68627925 | M39: 0.93726027 | O39: 0.93726027 | T39: 2.463644 | V39: 2.463644
A40: BE335 | B40: 3 | C40: BE | D40: Arr. Verviers — communes francophones | E40: Arr. Verviers — communes francophones | F40: 0 | I40: 0 | M40: 0 | P40: 0 | T40: 0 | W40: 0
A41: BE352 | B41: 3 | C41: BE | D41: Arr. Namur | E41: Arr. Namur | F41: 0 | I41: 0 | L41: 0 | M41: 0 | P41: 0 | S41: 0 | T41: 0 | W41: 0 | Z41: 0
A42: BG313 | B42: 3 | C42: BG | D42: Vratsa | E42: Враца | F42: 0.27467009 | H42: 0.27467009 | M42: 0.37512042 | O42: 0.37512042 | T42: 0.9860262 | V42: 0.9860262
A43: BG314 | B43: 3 | C43: BG | D43: Pleven | E43: Плевен | F43: 0 | I43: 0 | M43: 0 | P43: 0 | T43: 0 | W43: 0
A44: BG315 | B44: 3 | C44: BG | D44: Lovech | E44: Ловеч | F44: 0.33177816 | H44: 0.33177816 | M44: 0.45311364 | O44: 0.45311364 | T44: 1.191036 | V44: 1.191036
A45: BG331 | B45: 3 | C45: BG | D45: Varna | E45: Варна | F45: 0.48437039 | H45: 0.48437039 | K45: 0 | M45: 0.66151077 | O45: 0.66151077 | R45: 0 | T45: 1.7388201 | V45: 1.7388201 | Y45: 0
A46: BG333 | B46: 3 | C46: BG | D46: Shumen | E46: Шумен | F46: 0 | I46: 0 | M46: 0 | P46: 0 | T46: 0 | W46: 0
A47: BG334 | B47: 3 | C47: BG | D47: Targovishte | E47: Търговище | F47: 0 | I47: 0 | M47: 0 | P47: 0 | T47: 0 | W47: 0
A48: BG341 | B48: 3 | C48: BG | D48: Burgas | E48: Бургас | F48: 0 | J48: 0 | M48: 0 | Q48: 0 | T48: 0 | X48: 0
A49: BG411 | B49: 3 | C49: BG | D49: Sofia (stolitsa) | E49: София (столица) | F49: 0 | I49: 0 | M49: 0 | P49: 0 | T49: 0 | W49: 0
A50: BG414 | B50: 3 | C50: BG | D50: Pernik | E50: Перник | F50: 0 | G50: 0 | M50: 0 | N50: 0 | T50: 0 | U50: 0
A51: BG421 | B51: 3 | C51: BG | D51: Plovdiv | E51: Пловдив | F51: 0 | I51: 0 | M51: 0 | P51: 0 | T51: 0 | W51: 0
A52: BG422 | B52: 3 | C52: BG | D52: Haskovo | E52: Хасково | F52: 0 | K52: 0 | M52: 0 | R52: 0 | T52: 0 | Y52: 0
A53: CY000 | B53: 3 | C53: CY | D53: Kýpros | E53: Κύπρος | F53: 0.87972227 | H53: 0.87972227 | M53: 1.2014478 | O53: 1.2014478 | T53: 3.1580767 | V53: 3.1580767
A54: CZ010 | B54: 3 | C54: CZ | D54: Hlavní město Praha | E54: Hlavní město Praha | F54: 0.33151581 | H54: 0.33151581 | M54: 0.45275533 | O54: 0.45275533 | T54: 1.1900942 | V54: 1.1900942
A55: CZ020 | B55: 3 | C55: CZ | D55: Středočeský kraj | E55: Středočeský kraj | F55: 0 | I55: 0 | J55: 0 | L55: 0 | M55: 0 | P55: 0 | Q55: 0 | S55: 0 | T55: 0 | W55: 0 | X55: 0 | Z55: 0
A56: CZ032 | B56: 3 | C56: CZ | D56: Plzeňský kraj | E56: Plzeňský kraj | F56: 0 | G56: 0 | I56: 0 | M56: 0 | N56: 0 | P56: 0 | T56: 0 | U56: 0 | W56: 0
A57: CZ041 | B57: 3 | C57: CZ | D57: Karlovarský kraj | E57: Karlovarský kraj | F57: 0 | I57: 0 | M57: 0 | P57: 0 | T57: 0 | W57: 0
A58: CZ042 | B58: 3 | C58: CZ | D58: Ústecký kraj | E58: Ústecký kraj | F58: 0.2936793 | H58: 0.2936793 | I58: 0 | J58: 0 | L58: 0 | M58: 0.40108154 | O58: 0.40108154 | P58: 0 | Q58: 0 | S58: 0 | T58: 1.0542665 | V58: 1.0542665 | W58: 0 | X58: 0 | Z58: 0
A59: CZ051 | B59: 3 | C59: CZ | D59: Liberecký kraj | E59: Liberecký kraj | F59: 0 | I59: 0 | M59: 0 | P59: 0 | T59: 0 | W59: 0
A60: CZ053 | B60: 3 | C60: CZ | D60: Pardubický kraj | E60: Pardubický kraj | F60: 0.39340154 | H60: 0.39340154 | I60: 0 | J60: 0 | M60: 0.53727346 | O60: 0.53727346 | P60: 0 | Q60: 0 | T60: 1.412255 | V60: 1.412255 | W60: 0 | X60: 0
A61: CZ063 | B61: 3 | C61: CZ | D61: Kraj Vysočina | E61: Kraj Vysočina | F61: 0 | I61: 0 | M61: 0 | P61: 0 | T61: 0 | W61: 0
A62: CZ064 | B62: 3 | C62: CZ | D62: Jihomoravský kraj | E62: Jihomoravský kraj | F62: 0.47453172 | H62: 0.47453172 | I62: 0 | M62: 0.64807397 | O62: 0.64807397 | P62: 0 | T62: 1.7035007 | V62: 1.7035007 | W62: 0
A63: CZ071 | B63: 3 | C63: CZ | D63: Olomoucký kraj | E63: Olomoucký kraj | F63: 0.40015981 | H63: 0.40015981 | L63: 0 | M63: 0.54650331 | O63: 0.54650331 | S63: 0 | T63: 1.4365163 | V63: 1.4365163 | Z63: 0
A64: CZ080 | B64: 3 | C64: CZ | D64: Moravskoslezský kraj | E64: Moravskoslezský kraj | F64: 0 | G64: 0 | I64: 0 | K64: 0 | L64: 0 | M64: 0 | N64: 0 | P64: 0 | R64: 0 | S64: 0 | T64: 0 | U64: 0 | W64: 0 | Y64: 0 | Z64: 0
A65: DE11C | B65: 3 | C65: DE | D65: Heidenheim | E65: Heidenheim | F65: 0.37378332 | H65: 0.37378332 | M65: 0.51048061 | O65: 0.51048061 | T65: 1.3418285 | V65: 1.3418285
A66: DE122 | B66: 3 | C66: DE | D66: Karlsruhe, Stadtkreis | E66: Karlsruhe, Stadtkreis | F66: 0 | J66: 0 | M66: 0 | Q66: 0 | T66: 0 | X66: 0
A67: DE123 | B67: 3 | C67: DE | D67: Karlsruhe, Landkreis | E67: Karlsruhe, Landkreis | F67: 0.32689661 | H67: 0.32689661 | M67: 0.44644684 | O67: 0.44644684 | T67: 1.1735119 | V67: 1.1735119
A68: DE126 | B68: 3 | C68: DE | D68: Mannheim, Stadtkreis | E68: Mannheim, Stadtkreis | F68: 0 | I68: 0 | M68: 0 | P68: 0 | T68: 0 | W68: 0
A69: DE128 | B69: 3 | C69: DE | D69: Rhein-Neckar-Kreis | E69: Rhein-Neckar-Kreis | F69: 0.34356683 | H69: 0.34356683 | M69: 0.46921357 | O69: 0.46921357 | T69: 1.2333556 | V69: 1.2333556
A70: DE131 | B70: 3 | C70: DE | D70: Freiburg im Breisgau, Stadtkreis | E70: Freiburg im Breisgau, Stadtkreis | F70: 0 | L70: 0 | M70: 0 | S70: 0 | T70: 0 | Z70: 0
A71: DE134 | B71: 3 | C71: DE | D71: Ortenaukreis | E71: Ortenaukreis | F71: 0 | G71: 0 | M71: 0 | N71: 0 | T71: 0 | U71: 0
A72: DE143 | B72: 3 | C72: DE | D72: Zollernalbkreis | E72: Zollernalbkreis | F72: 0.49881076 | H72: 0.49881076 | M72: 0.68123217 | O72: 0.68123217 | T72: 1.790659 | V72: 1.790659
A73: DE145 | B73: 3 | C73: DE | D73: Alb-Donau-Kreis | E73: Alb-Donau-Kreis | F73: 0.96670892 | H73: 0.96670892 | M73: 1.3202466 | O73: 1.3202466 | T73: 3.4703462 | V73: 3.4703462
A74: DE148 | B74: 3 | C74: DE | D74: Ravensburg | E74: Ravensburg | F74: 0 | I74: 0 | M74: 0 | P74: 0 | T74: 0 | W74: 0
A75: DE214 | B75: 3 | C75: DE | D75: Altötting | E75: Altötting | F75: 0 | J75: 0 | L75: 0 | M75: 0 | Q75: 0 | S75: 0 | T75: 0 | X75: 0 | Z75: 0
A76: DE219 | B76: 3 | C76: DE | D76: Eichstätt | E76: Eichstätt | F76: 0 | I76: 0 | J76: 0 | M76: 0 | P76: 0 | Q76: 0 | T76: 0 | W76: 0 | X76: 0
A77: DE21I | B77: 3 | C77: DE | D77: Neuburg-Schrobenhausen | E77: Neuburg-Schrobenhausen | F77: 0 | I77: 0 | M77: 0 | P77: 0 | T77: 0 | W77: 0
A78: DE21J | B78: 3 | C78: DE | D78: Pfaffenhofen a. d. Ilm | E78: Pfaffenhofen a. d. Ilm | F78: 0 | L78: 0 | M78: 0 | S78: 0 | T78: 0 | Z78: 0
A79: DE21K | B79: 3 | C79: DE | D79: Rosenheim, Landkreis | E79: Rosenheim, Landkreis | F79: 0.55303327 | H79: 0.55303327 | M79: 0.75528454 | O79: 0.75528454 | T79: 1.9853101 | V79: 1.9853101
A80: DE226 | B80: 3 | C80: DE | D80: Kelheim | E80: Kelheim | F80: 0 | J80: 0 | M80: 0 | Q80: 0 | T80: 0 | X80: 0
A81: DE229 | B81: 3 | C81: DE | D81: Regen | E81: Regen | F81: 0 | I81: 0 | M81: 0 | P81: 0 | T81: 0 | W81: 0
A82: DE237 | B82: 3 | C82: DE | D82: Neustadt a. d. Waldnaab | E82: Neustadt a. d. Waldnaab | F82: 0 | I82: 0 | M82: 0 | P82: 0 | T82: 0 | W82: 0
A83: DE239 | B83: 3 | C83: DE | D83: Schwandorf | E83: Schwandorf | F83: 0.59389037 | H83: 0.59389037 | M83: 0.81108359 | O83: 0.81108359 | T83: 2.1319811 | V83: 2.1319811
A84: DE24A | B84: 3 | C84: DE | D84: Kronach | E84: Kronach | F84: 0 | I84: 0 | M84: 0 | P84: 0 | T84: 0 | W84: 0
A85: DE24D | B85: 3 | C85: DE | D85: Wunsiedel i. Fichtelgebirge | E85: Wunsiedel i. Fichtelgebirge | F85: 0 | I85: 0 | M85: 0 | P85: 0 | T85: 0 | W85: 0
A86: DE25C | B86: 3 | C86: DE | D86: Weißenburg-Gunzenhausen | E86: Weißenburg-Gunzenhausen | F86: 0.21444962 | H86: 0.21444962 | M86: 0.29287656 | O86: 0.29287656 | T86: 0.76984334 | V86: 0.76984334
A87: DE26A | B87: 3 | C87: DE | D87: Main-Spessart | E87: Main-Spessart | F87: 0.87535318 | H87: 0.87535318 | I87: 0 | M87: 1.1954809 | O87: 1.1954809 | P87: 0 | T87: 3.1423923 | V87: 3.1423923 | W87: 0
A88: DE276 | B88: 3 | C88: DE | D88: Augsburg, Landkreis | E88: Augsburg, Landkreis | F88: 0 | G88: 0 | M88: 0 | N88: 0 | T88: 0 | U88: 0
A89: DE27D | B89: 3 | C89: DE | D89: Donau-Ries | E89: Donau-Ries | F89: 0.42296249 | H89: 0.42296249 | M89: 0.57764523 | O89: 0.57764523 | T89: 1.5183746 | V89: 1.5183746
A90: DE401 | B90: 3 | C90: DE | D90: Brandenburg an der Havel, Kreisfreie Stadt | E90: Brandenburg an der Havel, Kreisfreie Stadt | F90: 0 | G90: 0 | M90: 0 | N90: 0 | T90: 0 | U90: 0
A91: DE409 | B91: 3 | C91: DE | D91: Märkisch-Oderland | E91: Märkisch-Oderland | F91: 0.83997966 | H91: 0.83997966 | I91: 0 | M91: 1.1471709 | O91: 1.1471709 | P91: 0 | T91: 3.0154064 | V91: 3.0154064 | W91: 0
A92: DE40A | B92: 3 | C92: DE | D92: Oberhavel | E92: Oberhavel | F92: 0 | G92: 0 | M92: 0 | N92: 0 | T92: 0 | U92: 0
A93: DE40C | B93: 3 | C93: DE | D93: Oder-Spree | E93: Oder-Spree | F93: 0 | G93: 0 | M93: 0 | N93: 0 | T93: 0 | U93: 0
A94: DE40G | B94: 3 | C94: DE | D94: Spree-Neiße | E94: Spree-Neiße | F94: 0 | I94: 0 | M94: 0 | P94: 0 | T94: 0 | W94: 0
A95: DE40I | B95: 3 | C95: DE | D95: Uckermark | E95: Uckermark | F95: 0 | J95: 0 | M95: 0 | Q95: 0 | T95: 0 | X95: 0
A96: DE501 | B96: 3 | C96: DE | D96: Bremen, Kreisfreie Stadt | E96: Bremen, Kreisfreie Stadt | F96: 0 | G96: 0 | M96: 0 | N96: 0 | T96: 0 | U96: 0
A97: DE600 | B97: 3 | C97: DE | D97: Hamburg | E97: Hamburg | F97: 0 | G97: 0 | J97: 0 | M97: 0 | N97: 0 | Q97: 0 | T97: 0 | U97: 0 | X97: 0
A98: DE712 | B98: 3 | C98: DE | D98: Frankfurt am Main, Kreisfreie Stadt | E98: Frankfurt am Main, Kreisfreie Stadt | F98: 0 | L98: 0 | M98: 0 | S98: 0 | T98: 0 | Z98: 0
A99: DE714 | B99: 3 | C99: DE | D99: Wiesbaden, Kreisfreie Stadt | E99: Wiesbaden, Kreisfreie Stadt | F99: 0.13106686 | H99: 0.13106686 | M99: 0.17899967 | O99: 0.17899967 | T99: 0.4705112 | V99: 0.4705112
A100: DE722 | B100: 3 | C100: DE | D100: Lahn-Dill-Kreis | E100: Lahn-Dill-Kreis | F100: 0 | G100: 0 | M100: 0 | N100: 0 | T100: 0 | U100: 0
A101: DE732 | B101: 3 | C101: DE | D101: Fulda | E101: Fulda | F101: 0.093232623 | H101: 0.093232623 | M101: 0.12732897 | O101: 0.12732897 | T101: 0.33469173 | V101: 0.33469173
A102: DE80M | B102: 3 | C102: DE | D102: Nordwestmecklenburg | E102: Nordwestmecklenburg | F102: 0 | L102: 0 | M102: 0 | S102: 0 | T102: 0 | Z102: 0
A103: DE80O | B103: 3 | C103: DE | D103: Ludwigslust-Parchim | E103: Ludwigslust-Parchim | F103: 0 | I103: 0 | M103: 0 | P103: 0 | T103: 0 | W103: 0
A104: DE912 | B104: 3 | C104: DE | D104: Salzgitter, Kreisfreie Stadt | E104: Salzgitter, Kreisfreie Stadt | F104: 0 | G104: 0 | M104: 0 | N104: 0 | T104: 0 | U104: 0
A105: DE91A | B105: 3 | C105: DE | D105: Peine | E105: Peine | F105: 0 | G105: 0 | M105: 0 | N105: 0 | T105: 0 | U105: 0
A106: DE91C | B106: 3 | C106: DE | D106: Göttingen | E106: Göttingen | F106: 0 | L106: 0 | M106: 0 | S106: 0 | T106: 0 | Z106: 0
A107: DE922 | B107: 3 | C107: DE | D107: Diepholz | E107: Diepholz | F107: 0 | L107: 0 | M107: 0 | S107: 0 | T107: 0 | Z107: 0
A108: DE923 | B108: 3 | C108: DE | D108: Hameln-Pyrmont | E108: Hameln-Pyrmont | F108: 0 | I108: 0 | M108: 0 | P108: 0 | T108: 0 | W108: 0
A109: DE926 | B109: 3 | C109: DE | D109: Holzminden | E109: Holzminden | F109: 0 | I109: 0 | M109: 0 | P109: 0 | T109: 0 | W109: 0
A110: DE927 | B110: 3 | C110: DE | D110: Nienburg (Weser) | E110: Nienburg (Weser) | F110: 0 | I110: 0 | L110: 0 | M110: 0 | P110: 0 | S110: 0 | T110: 0 | W110: 0 | Z110: 0
A111: DE928 | B111: 3 | C111: DE | D111: Schaumburg | E111: Schaumburg | F111: 0 | I111: 0 | M111: 0 | P111: 0 | T111: 0 | W111: 0
...

Sheet Coal (PJ per y)
F12: 2018 | M12: 2030 | T12: 2050
A13: NUTS ID | B13: NUTS LEVEL | C13: Country code | D13: NUTS region name (Latin) | E13: NUTS_NAME | F13: All sectors (PJ/y) | G13: Steel (PJ/y) | H13: Cement (PJ/y) | I13: Glass (PJ/y) | J13: Refineries (PJ/y) | K13: Fertilisers (PJ/y) | L13: Chemical (PJ/y) | M13: All sectors (PJ/y) | N13: Steel (PJ/y) | O13: Cement (PJ/y) | P13: Glass (PJ/y) | Q13: Refineries (PJ/y) | R13: Fertilisers (PJ/y) | S13: Chemical (PJ/y) | T13: All sectors (PJ/y) | U13: Steel (PJ/y) | V13: Cement (PJ/y) | W13: Glass (PJ/y) | X13: Refineries (PJ/y) | Y13: Fertilisers (PJ/y) | Z13: Chemical (PJ/y)
A14: AT121 | B14: 3 | C14: AT | D14: Mostviertel-Eisenwurzen | E14: Mostviertel-Eisenwurzen | F14: 0 | I14: 0 | M14: 0 | P14: 0 | T14: 0 | W14: 0
A15: AT122 | B15: 3 | C15: AT | D15: Niederösterreich-Süd | E15: Niederösterreich-Süd | F15: 0.51690266 | H15: 0.51690266 | M15: 0.46091031 | O15: 0.46091031 | T15: 0.12039401 | V15: 0.12039401
A16: AT124 | B16: 3 | C16: AT | D16: Waldviertel | E16: Waldviertel | F16: 0 | L16: 0 | M16: 0 | S16: 0 | T16: 0 | Z16: 0
A17: AT127 | B17: 3 | C17: AT | D17: Wiener Umland/Südteil | E17: Wiener Umland/Südteil | F17: 1.0724143 | H17: 1.0724143 | J17: 0 | L17: 0 | M17: 0.95624742 | O17: 0.95624742 | Q17: 0 | S17: 0 | T17: 0.24978061 | V17: 0.24978061 | X17: 0 | Z17: 0
A18: AT213 | B18: 3 | C18: AT | D18: Unterkärnten | E18: Unterkärnten | F18: 0.77560392 | H18: 0.77560392 | M18: 0.69158833 | O18: 0.69158833 | T18: 0.18064922 | V18: 0.18064922
A19: AT221 | B19: 3 | C19: AT | D19: Graz | E19: Graz | F19: 0.090471466 | G19: 0.090471466 | M19: 0.090471466 | N19: 0.090471466 | T19: 0.090471466 | U19: 0.090471466
A20: AT223 | B20: 3 | C20: AT | D20: Östliche Obersteiermark | E20: Östliche Obersteiermark | F20: 22.809541 | G20: 22.809541 | M20: 17.497025 | N20: 17.497025 | T20: 4.5783105 | U20: 4.5783105
A21: AT225 | B21: 3 | C21: AT | D21: West- und Südsteiermark | E21: West- und Südsteiermark | F21: 0.57538441 | H21: 0.57538441 | I21: 0 | M21: 0.51305716 | O21: 0.51305716 | P21: 0 | T21: 0.13401524 | V21: 0.13401524 | W21: 0
A22: AT312 | B22: 3 | C22: AT | D22: Linz-Wels | E22: Linz-Wels | F22: 86.715533 | G22: 86.715533 | K22: 0 | L22: 0 | M22: 66.412925 | N22: 66.412925 | R22: 0 | S22: 0 | T22: 17.042042 | U22: 17.042042 | Y22: 0 | Z22: 0
A23: AT314 | B23: 3 | C23: AT | D23: Steyr-Kirchdorf | E23: Steyr-Kirchdorf | F23: 0.39835011 | H23: 0.39835011 | I23: 0 | M23: 0.35519971 | O23: 0.35519971 | P23: 0 | T23: 0.092781425 | V23: 0.092781425 | W23: 0
A24: AT315 | B24: 3 | C24: AT | D24: Traunviertel | E24: Traunviertel | F24: 0.58144688 | H24: 0.58144688 | M24: 0.51846292 | O24: 0.51846292 | T24: 0.13542728 | V24: 0.13542728
A25: AT323 | B25: 3 | C25: AT | D25: Salzburg und Umgebung | E25: Salzburg und Umgebung | F25: 0.55059198 | H25: 0.55059198 | M25: 0.49095031 | O25: 0.49095031 | T25: 0.12824073 | V25: 0.12824073
A26: AT331 | B26: 3 | C26: AT | D26: Außerfern | E26: Außerfern | F26: 0.37994749 | H26: 0.37994749 | M26: 0.33879052 | O26: 0.33879052 | T26: 0.088495194 | V26: 0.088495194
A27: BE211 | B27: 3 | C27: BE | D27: Arr. Antwerpen | E27: Arr. Antwerpen | F27: 0 | J27: 0 | K27: 0 | L27: 0 | M27: 0 | Q27: 0 | R27: 0 | S27: 0 | T27: 0 | X27: 0 | Y27: 0 | Z27: 0
A28: BE213 | B28: 3 | C28: BE | D28: Arr. Turnhout | E28: Arr. Turnhout | F28: 0 | I28: 0 | L28: 0 | M28: 0 | P28: 0 | S28: 0 | T28: 0 | W28: 0 | Z28: 0
A29: BE224 | B29: 3 | C29: BE | D29: Arr. Hasselt | E29: Arr. Hasselt | F29: 0.28086448 | G29: 0.28086448 | L29: 0 | M29: 0.28086448 | N29: 0.28086448 | S29: 0 | T29: 0.28086448 | U29: 0.28086448 | Z29: 0
A30: BE233 | B30: 3 | C30: BE | D30: Arr. Eeklo | E30: Arr. Eeklo | F30: 0 | L30: 0 | M30: 0 | S30: 0 | T30: 0 | Z30: 0
A31: BE234 | B31: 3 | C31: BE | D31: Arr. Gent | E31: Arr. Gent | F31: 93.872805 | G31: 93.872805 | L31: 0 | M31: 71.894474 | N31: 71.894474 | S31: 0 | T31: 18.448647 | U31: 18.448647 | Z31: 0
A32: BE236 | B32: 3 | C32: BE | D32: Arr. Sint-Niklaas | E32: Arr. Sint-Niklaas | F32: 0 | L32: 0 | M32: 0 | S32: 0 | T32: 0 | Z32: 0
A33: BE255 | B33: 3 | C33: BE | D33: Arr. Oostende | E33: Arr. Oostende | F33: 0 | L33: 0 | M33: 0 | S33: 0 | T33: 0 | Z33: 0
A34: BE323 | B34: 3 | C34: BE | D34: Arr. Mons | E34: Arr. Mons | F34: 1.5821186 | H34: 1.5821186 | I34: 0 | K34: 0 | L34: 0 | M34: 1.4107391 | O34: 1.4107391 | P34: 0 | R34: 0 | S34: 0 | T34: 0.368498 | V34: 0.368498 | W34: 0 | Y34: 0 | Z34: 0
A35: BE328 | B35: 3 | C35: BE | D35: Arr. Tournai-Mouscron | E35: Arr. Tournai-Mouscron | F35: 3.0116634 | H35: 3.0116634 | M35: 2.6854316 | O35: 2.6854316 | T35: 0.7014594 | V35: 0.7014594
A36: BE32B | B36: 3 | C36: BE | D36: Arr. Charleroi | E36: Arr. Charleroi | F36: 0.51491822 | G36: 0.51491822 | M36: 0.51491822 | N36: 0.51491822 | T36: 0.51491822 | U36: 0.51491822
A37: BE32C | B37: 3 | C37: BE | D37: Arr. Soignies | E37: Arr. Soignies | F37: 0 | I37: 0 | L37: 0 | M37: 0 | P37: 0 | S37: 0 | T37: 0 | W37: 0 | Z37: 0
A38: BE32D | B38: 3 | C38: BE | D38: Arr. Thuin | E38: Arr. Thuin | F38: 0 | I38: 0 | M38: 0 | P38: 0 | T38: 0 | W38: 0
A39: BE332 | B39: 3 | C39: BE | D39: Arr. Liège | E39: Arr. Liège | F39: 1.7814487 | H39: 1.7814487 | M39: 1.5884772 | O39: 1.5884772 | T39: 0.41492483 | V39: 0.41492483
A40: BE335 | B40: 3 | C40: BE | D40: Arr. Verviers — communes francophones | E40: Arr. Verviers — communes francophones | F40: 0 | I40: 0 | M40: 0 | P40: 0 | T40: 0 | W40: 0
A41: BE352 | B41: 3 | C41: BE | D41: Arr. Namur | E41: Arr. Namur | F41: 0 | I41: 0 | L41: 0 | M41: 0 | P41: 0 | S41: 0 | T41: 0 | W41: 0 | Z41: 0
A42: BG313 | B42: 3 | C42: BG | D42: Vratsa | E42: Враца | F42: 0.71299063 | H42: 0.71299063 | M42: 0.63575749 | O42: 0.63575749 | T42: 0.1660657 | V42: 0.1660657
A43: BG314 | B43: 3 | C43: BG | D43: Pleven | E43: Плевен | F43: 0 | I43: 0 | M43: 0 | P43: 0 | T43: 0 | W43: 0
A44: BG315 | B44: 3 | C44: BG | D44: Lovech | E44: Ловеч | F44: 0.86123217 | H44: 0.86123217 | M44: 0.76794109 | O44: 0.76794109 | T44: 0.20059326 | V44: 0.20059326
A45: BG331 | B45: 3 | C45: BG | D45: Varna | E45: Варна | F45: 1.2573322 | H45: 1.2573322 | K45: 0 | M45: 1.1211344 | O45: 1.1211344 | R45: 0 | T45: 0.29285061 | V45: 0.29285061 | Y45: 0
A46: BG333 | B46: 3 | C46: BG | D46: Shumen | E46: Шумен | F46: 0 | I46: 0 | M46: 0 | P46: 0 | T46: 0 | W46: 0
A47: BG334 | B47: 3 | C47: BG | D47: Targovishte | E47: Търговище | F47: 0 | I47: 0 | M47: 0 | P47: 0 | T47: 0 | W47: 0
A48: BG341 | B48: 3 | C48: BG | D48: Burgas | E48: Бургас | F48: 0 | J48: 0 | M48: 0 | Q48: 0 | T48: 0 | X48: 0
A49: BG411 | B49: 3 | C49: BG | D49: Sofia (stolitsa) | E49: София (столица) | F49: 0 | I49: 0 | M49: 0 | P49: 0 | T49: 0 | W49: 0
A50: BG414 | B50: 3 | C50: BG | D50: Pernik | E50: Перник | F50: 0.19702278 | G50: 0.19702278 | M50: 0.19702278 | N50: 0.19702278 | T50: 0.19702278 | U50: 0.19702278
A51: BG421 | B51: 3 | C51: BG | D51: Plovdiv | E51: Пловдив | F51: 0 | I51: 0 | M51: 0 | P51: 0 | T51: 0 | W51: 0
A52: BG422 | B52: 3 | C52: BG | D52: Haskovo | E52: Хасково | F52: 0 | K52: 0 | M52: 0 | R52: 0 | T52: 0 | Y52: 0
A53: CY000 | B53: 3 | C53: CY | D53: Kýpros | E53: Κύπρος | F53: 2.2835895 | H53: 2.2835895 | M53: 2.0362247 | O53: 2.0362247 | T53: 0.53188059 | V53: 0.53188059
A54: CZ010 | B54: 3 | C54: CZ | D54: Hlavní město Praha | E54: Hlavní město Praha | F54: 0.86055115 | H54: 0.86055115 | M54: 0.76733384 | O54: 0.76733384 | T54: 0.20043464 | V54: 0.20043464
A55: CZ020 | B55: 3 | C55: CZ | D55: Středočeský kraj | E55: Středočeský kraj | F55: 0 | I55: 0 | J55: 0 | L55: 0 | M55: 0 | P55: 0 | Q55: 0 | S55: 0 | T55: 0 | W55: 0 | X55: 0 | Z55: 0
A56: CZ032 | B56: 3 | C56: CZ | D56: Plzeňský kraj | E56: Plzeňský kraj | F56: 0.04026575 | G56: 0.04026575 | I56: 0 | M56: 0.04026575 | N56: 0.04026575 | P56: 0 | T56: 0.04026575 | U56: 0.04026575 | W56: 0
A57: CZ041 | B57: 3 | C57: CZ | D57: Karlovarský kraj | E57: Karlovarský kraj | F57: 0 | I57: 0 | M57: 0 | P57: 0 | T57: 0 | W57: 0
A58: CZ042 | B58: 3 | C58: CZ | D58: Ústecký kraj | E58: Ústecký kraj | F58: 0.76233486 | H58: 0.76233486 | I58: 0 | J58: 0 | L58: 0 | M58: 0.67975661 | O58: 0.67975661 | P58: 0 | Q58: 0 | S58: 0 | T58: 0.17755867 | V58: 0.17755867 | W58: 0 | X58: 0 | Z58: 0
A59: CZ051 | B59: 3 | C59: CZ | D59: Liberecký kraj | E59: Liberecký kraj | F59: 0 | I59: 0 | M59: 0 | P59: 0 | T59: 0 | W59: 0
A60: CZ053 | B60: 3 | C60: CZ | D60: Pardubický kraj | E60: Pardubický kraj | F60: 1.0211946 | H60: 1.0211946 | I60: 0 | J60: 0 | M60: 0.91057592 | O60: 0.91057592 | P60: 0 | Q60: 0 | T60: 0.23785079 | V60: 0.23785079 | W60: 0 | X60: 0
A61: CZ063 | B61: 3 | C61: CZ | D61: Kraj Vysočina | E61: Kraj Vysočina | F61: 0 | I61: 0 | M61: 0 | P61: 0 | T61: 0 | W61: 0
A62: CZ064 | B62: 3 | C62: CZ | D62: Jihomoravský kraj | E62: Jihomoravský kraj | F62: 1.2317929 | H62: 1.2317929 | I62: 0 | M62: 1.0983616 | O62: 1.0983616 | P62: 0 | T62: 0.28690215 | V62: 0.28690215 | W62: 0
A63: CZ071 | B63: 3 | C63: CZ | D63: Olomoucký kraj | E63: Olomoucký kraj | F63: 1.0387377 | H63: 1.0387377 | L63: 0 | M63: 0.92621876 | O63: 0.92621876 | S63: 0 | T63: 0.24193685 | V63: 0.24193685 | Z63: 0
A64: CZ080 | B64: 3 | C64: CZ | D64: Moravskoslezský kraj | E64: Moravskoslezský kraj | F64: 83.171636 | G64: 83.171636 | I64: 0 | K64: 0 | L64: 0 | M64: 63.706299 | N64: 63.706299 | P64: 0 | R64: 0 | S64: 0 | T64: 16.371448 | U64: 16.371448 | W64: 0 | Y64: 0 | Z64: 0
A65: DE11C | B65: 3 | C65: DE | D65: Heidenheim | E65: Heidenheim | F65: 0.97026946 | H65: 0.97026946 | M65: 0.86516716 | O65: 0.86516716 | T65: 0.22598961 | V65: 0.22598961
A66: DE122 | B66: 3 | C66: DE | D66: Karlsruhe, Stadtkreis | E66: Karlsruhe, Stadtkreis | F66: 0 | J66: 0 | M66: 0 | Q66: 0 | T66: 0 | X66: 0
A67: DE123 | B67: 3 | C67: DE | D67: Karlsruhe, Landkreis | E67: Karlsruhe, Landkreis | F67: 0.8485606 | H67: 0.8485606 | M67: 0.75664213 | O67: 0.75664213 | T67: 0.19764187 | V67: 0.19764187
A68: DE126 | B68: 3 | C68: DE | D68: Mannheim, Stadtkreis | E68: Mannheim, Stadtkreis | F68: 0 | I68: 0 | M68: 0 | P68: 0 | T68: 0 | W68: 0
A69: DE128 | B69: 3 | C69: DE | D69: Rhein-Neckar-Kreis | E69: Rhein-Neckar-Kreis | F69: 0.89183328 | H69: 0.89183328 | M69: 0.7952274 | O69: 0.7952274 | T69: 0.2077207 | V69: 0.2077207
A70: DE131 | B70: 3 | C70: DE | D70: Freiburg im Breisgau, Stadtkreis | E70: Freiburg im Breisgau, Stadtkreis | F70: 0 | L70: 0 | M70: 0 | S70: 0 | T70: 0 | Z70: 0
A71: DE134 | B71: 3 | C71: DE | D71: Ortenaukreis | E71: Ortenaukreis | F71: 0.63607456 | G71: 0.63607456 | M71: 0.63607456 | N71: 0.63607456 | T71: 0.63607456 | U71: 0.63607456
A72: DE143 | B72: 3 | C72: DE | D72: Zollernalbkreis | E72: Zollernalbkreis | F72: 1.2948166 | H72: 1.2948166 | M72: 1.1545584 | O72: 1.1545584 | T72: 0.30158127 | V72: 0.30158127
A73: DE145 | B73: 3 | C73: DE | D73: Alb-Donau-Kreis | E73: Alb-Donau-Kreis | F73: 2.50939 | H73: 2.50939 | M73: 2.2375659 | O73: 2.2375659 | T73: 0.58447276 | V73: 0.58447276
A74: DE148 | B74: 3 | C74: DE | D74: Ravensburg | E74: Ravensburg | F74: 0 | I74: 0 | M74: 0 | P74: 0 | T74: 0 | W74: 0
A75: DE214 | B75: 3 | C75: DE | D75: Altötting | E75: Altötting | F75: 0 | J75: 0 | L75: 0 | M75: 0 | Q75: 0 | S75: 0 | T75: 0 | X75: 0 | Z75: 0
A76: DE219 | B76: 3 | C76: DE | D76: Eichstätt | E76: Eichstätt | F76: 0 | I76: 0 | J76: 0 | M76: 0 | P76: 0 | Q76: 0 | T76: 0 | W76: 0 | X76: 0
A77: DE21I | B77: 3 | C77: DE | D77: Neuburg-Schrobenhausen | E77: Neuburg-Schrobenhausen | F77: 0 | I77: 0 | M77: 0 | P77: 0 | T77: 0 | W77: 0
A78: DE21J | B78: 3 | C78: DE | D78: Pfaffenhofen a. d. Ilm | E78: Pfaffenhofen a. d. Ilm | F78: 0 | L78: 0 | M78: 0 | S78: 0 | T78: 0 | Z78: 0
A79: DE21K | B79: 3 | C79: DE | D79: Rosenheim, Landkreis | E79: Rosenheim, Landkreis | F79: 1.4355678 | H79: 1.4355678 | M79: 1.2800631 | O79: 1.2800631 | T79: 0.33436423 | V79: 0.33436423
A80: DE226 | B80: 3 | C80: DE | D80: Kelheim | E80: Kelheim | F80: 0 | J80: 0 | M80: 0 | Q80: 0 | T80: 0 | X80: 0
A81: DE229 | B81: 3 | C81: DE | D81: Regen | E81: Regen | F81: 0 | I81: 0 | M81: 0 | P81: 0 | T81: 0 | W81: 0
A82: DE237 | B82: 3 | C82: DE | D82: Neustadt a. d. Waldnaab | E82: Neustadt a. d. Waldnaab | F82: 0 | I82: 0 | M82: 0 | P82: 0 | T82: 0 | W82: 0
A83: DE239 | B83: 3 | C83: DE | D83: Schwandorf | E83: Schwandorf | F83: 1.5416249 | H83: 1.5416249 | M83: 1.3746318 | O83: 1.3746318 | T83: 0.35906645 | V83: 0.35906645
A84: DE24A | B84: 3 | C84: DE | D84: Kronach | E84: Kronach | F84: 0 | I84: 0 | M84: 0 | P84: 0 | T84: 0 | W84: 0
A85: DE24D | B85: 3 | C85: DE | D85: Wunsiedel i. Fichtelgebirge | E85: Wunsiedel i. Fichtelgebirge | F85: 0 | I85: 0 | M85: 0 | P85: 0 | T85: 0 | W85: 0
A86: DE25C | B86: 3 | C86: DE | D86: Weißenburg-Gunzenhausen | E86: Weißenburg-Gunzenhausen | F86: 0.55666988 | H86: 0.55666988 | M86: 0.49636984 | O86: 0.49636984 | T86: 0.12965636 | V86: 0.12965636
A87: DE26A | B87: 3 | C87: DE | D87: Main-Spessart | E87: Main-Spessart | F87: 2.2722482 | H87: 2.2722482 | I87: 0 | M87: 2.0261119 | O87: 2.0261119 | P87: 0 | T87: 0.52923903 | V87: 0.52923903 | W87: 0
A88: DE276 | B88: 3 | C88: DE | D88: Augsburg, Landkreis | E88: Augsburg, Landkreis | F88: 0.30022719 | G88: 0.30022719 | M88: 0.30022719 | N88: 0.30022719 | T88: 0.30022719 | U88: 0.30022719
A89: DE27D | B89: 3 | C89: DE | D89: Donau-Ries | E89: Donau-Ries | F89: 1.0979291 | H89: 1.0979291 | M89: 0.97899836 | O89: 0.97899836 | T89: 0.25572336 | V89: 0.25572336
A90: DE401 | B90: 3 | C90: DE | D90: Brandenburg an der Havel, Kreisfreie Stadt | E90: Brandenburg an der Havel, Kreisfreie Stadt | F90: 0.45797368 | G90: 0.45797368 | M90: 0.45797368 | N90: 0.45797368 | T90: 0.45797368 | U90: 0.45797368
A91: DE409 | B91: 3 | C91: DE | D91: Märkisch-Oderland | E91: Märkisch-Oderland | F91: 2.1804253 | H91: 2.1804253 | I91: 0 | M91: 1.9442356 | O91: 1.9442356 | P91: 0 | T91: 0.50785218 | V91: 0.50785218 | W91: 0
A92: DE40A | B92: 3 | C92: DE | D92: Oberhavel | E92: Oberhavel | F92: 0.25442982 | G92: 0.25442982 | M92: 0.25442982 | N92: 0.25442982 | T92: 0.25442982 | U92: 0.25442982
A93: DE40C | B93: 3 | C93: DE | D93: Oder-Spree | E93: Oder-Spree | F93: 40.456496 | G93: 40.456496 | M93: 30.984463 | N93: 30.984463 | T93: 7.9508397 | U93: 7.9508397
A94: DE40G | B94: 3 | C94: DE | D94: Spree-Neiße | E94: Spree-Neiße | F94: 0 | I94: 0 | M94: 0 | P94: 0 | T94: 0 | W94: 0
A95: DE40I | B95: 3 | C95: DE | D95: Uckermark | E95: Uckermark | F95: 0 | J95: 0 | M95: 0 | Q95: 0 | T95: 0 | X95: 0
A96: DE501 | B96: 3 | C96: DE | D96: Bremen, Kreisfreie Stadt | E96: Bremen, Kreisfreie Stadt | F96: 64.056119 | G96: 64.056119 | M96: 49.058734 | N96: 49.058734 | T96: 12.58883 | U96: 12.58883
A97: DE600 | B97: 3 | C97: DE | D97: Hamburg | E97: Hamburg | F97: 18.542561 | G97: 18.542561 | J97: 0 | M97: 14.201212 | N97: 14.201212 | Q97: 0 | T97: 3.6441349 | U97: 3.6441349 | X97: 0
A98: DE712 | B98: 3 | C98: DE | D98: Frankfurt am Main, Kreisfreie Stadt | E98: Frankfurt am Main, Kreisfreie Stadt | F98: 0 | L98: 0 | M98: 0 | S98: 0 | T98: 0 | Z98: 0
A99: DE714 | B99: 3 | C99: DE | D99: Wiesbaden, Kreisfreie Stadt | E99: Wiesbaden, Kreisfreie Stadt | F99: 0.3402243 | H99: 0.3402243 | M99: 0.30337025 | O99: 0.30337025 | T99: 0.079243097 | V99: 0.079243097
A100: DE722 | B100: 3 | C100: DE | D100: Lahn-Dill-Kreis | E100: Lahn-Dill-Kreis | F100: 0.10177193 | G100: 0.10177193 | M100: 0.10177193 | N100: 0.10177193 | T100: 0.10177193 | U100: 0.10177193
A101: DE732 | B101: 3 | C101: DE | D101: Fulda | E101: Fulda | F101: 0.24201392 | H101: 0.24201392 | M101: 0.2157983 | O101: 0.2157983 | T101: 0.056368497 | V101: 0.056368497
A102: DE80M | B102: 3 | C102: DE | D102: Nordwestmecklenburg | E102: Nordwestmecklenburg | F102: 0 | L102: 0 | M102: 0 | S102: 0 | T102: 0 | Z102: 0
A103: DE80O | B103: 3 | C103: DE | D103: Ludwigslust-Parchim | E103: Ludwigslust-Parchim | F103: 0 | I103: 0 | M103: 0 | P103: 0 | T103: 0 | W103: 0
A104: DE912 | B104: 3 | C104: DE | D104: Salzgitter, Kreisfreie Stadt | E104: Salzgitter, Kreisfreie Stadt | F104: 94.398491 | G104: 94.398491 | M104: 72.297081 | N104: 72.297081 | T104: 18.551959 | U104: 18.551959
A105: DE91A | B105: 3 | C105: DE | D105: Peine | E105: Peine | F105: 0.25442982 | G105: 0.25442982 | M105: 0.25442982 | N105: 0.25442982 | T105: 0.25442982 | U105: 0.25442982
A106: DE91C | B106: 3 | C106: DE | D106: Göttingen | E106: Göttingen | F106: 0 | L106: 0 | M106: 0 | S106: 0 | T106: 0 | Z106: 0
A107: DE922 | B107: 3 | C107: DE | D107: Diepholz | E107: Diepholz | F107: 0 | L107: 0 | M107: 0 | S107: 0 | T107: 0 | Z107: 0
A108: DE923 | B108: 3 | C108: DE | D108: Hameln-Pyrmont | E108: Hameln-Pyrmont | F108: 0 | I108: 0 | M108: 0 | P108: 0 | T108: 0 | W108: 0
A109: DE926 | B109: 3 | C109: DE | D109: Holzminden | E109: Holzminden | F109: 0 | I109: 0 | M109: 0 | P109: 0 | T109: 0 | W109: 0
A110: DE927 | B110: 3 | C110: DE | D110: Nienburg (Weser) | E110: Nienburg (Weser) | F110: 0 | I110: 0 | L110: 0 | M110: 0 | P110: 0 | S110: 0 | T110: 0 | W110: 0 | Z110: 0
A111: DE928 | B111: 3 | C111: DE | D111: Schaumburg | E111: Schaumburg | F111: 0 | I111: 0 | M111: 0 | P111: 0 | T111: 0 | W111: 0
...

Sheet Coke (PJ per y)
F12: 2018 | M12: 2030 | T12: 2050
A13: NUTS ID | B13: NUTS LEVEL | C13: Country code | D13: NUTS region name (Latin) | E13: NUTS_NAME | F13: All sectors (PJ/y) | G13: Steel (PJ/y) | H13: Cement (PJ/y) | I13: Glass (PJ/y) | J13: Refineries (PJ/y) | K13: Fertilisers (PJ/y) | L13: Chemical (PJ/y) | M13: All sectors (PJ/y) | N13: Steel (PJ/y) | O13: Cement (PJ/y) | P13: Glass (PJ/y) | Q13: Refineries (PJ/y) | R13: Fertilisers (PJ/y) | S13: Chemical (PJ/y) | T13: All sectors (PJ/y) | U13: Steel (PJ/y) | V13: Cement (PJ/y) | W13: Glass (PJ/y) | X13: Refineries (PJ/y) | Y13: Fertilisers (PJ/y) | Z13: Chemical (PJ/y)
A14: AT121 | B14: 3 | C14: AT | D14: Mostviertel-Eisenwurzen | E14: Mostviertel-Eisenwurzen | F14: 0 | I14: 0 | M14: 0 | P14: 0 | T14: 0 | W14: 0
A15: AT122 | B15: 3 | C15: AT | D15: Niederösterreich-Süd | E15: Niederösterreich-Süd | F15: 0 | H15: 0 | M15: 0 | O15: 0 | T15: 0 | V15: 0
A16: AT124 | B16: 3 | C16: AT | D16: Waldviertel | E16: Waldviertel | F16: 0 | L16: 0 | M16: 0 | S16: 0 | T16: 0 | Z16: 0
A17: AT127 | B17: 3 | C17: AT | D17: Wiener Umland/Südteil | E17: Wiener Umland/Südteil | F17: 0 | H17: 0 | J17: 0 | L17: 0 | M17: 0 | O17: 0 | Q17: 0 | S17: 0 | T17: 0 | V17: 0 | X17: 0 | Z17: 0
A18: AT213 | B18: 3 | C18: AT | D18: Unterkärnten | E18: Unterkärnten | F18: 0 | H18: 0 | M18: 0 | O18: 0 | T18: 0 | V18: 0
A19: AT221 | B19: 3 | C19: AT | D19: Graz | E19: Graz | F19: 0 | G19: 0 | M19: 0 | N19: 0 | T19: 0 | U19: 0
A20: AT223 | B20: 3 | C20: AT | D20: Östliche Obersteiermark | E20: Östliche Obersteiermark | F20: 1.4434227 | G20: 1.4434227 | M20: 1.1011006 | N20: 1.1011006 | T20: 0.27237386 | U20: 0.27237386
A21: AT225 | B21: 3 | C21: AT | D21: West- und Südsteiermark | E21: West- und Südsteiermark | F21: 0 | H21: 0 | I21: 0 | M21: 0 | O21: 0 | P21: 0 | T21: 0 | V21: 0 | W21: 0
A22: AT312 | B22: 3 | C22: AT | D22: Linz-Wels | E22: Linz-Wels | F22: 5.516265 | G22: 5.516265 | K22: 0 | L22: 0 | M22: 4.2080276 | N22: 4.2080276 | R22: 0 | S22: 0 | T22: 1.0409192 | U22: 1.0409192 | Y22: 0 | Z22: 0
A23: AT314 | B23: 3 | C23: AT | D23: Steyr-Kirchdorf | E23: Steyr-Kirchdorf | F23: 0 | H23: 0 | I23: 0 | M23: 0 | O23: 0 | P23: 0 | T23: 0 | V23: 0 | W23: 0
A24: AT315 | B24: 3 | C24: AT | D24: Traunviertel | E24: Traunviertel | F24: 0 | H24: 0 | M24: 0 | O24: 0 | T24: 0 | V24: 0
A25: AT323 | B25: 3 | C25: AT | D25: Salzburg und Umgebung | E25: Salzburg und Umgebung | F25: 0 | H25: 0 | M25: 0 | O25: 0 | T25: 0 | V25: 0
A26: AT331 | B26: 3 | C26: AT | D26: Außerfern | E26: Außerfern | F26: 0 | H26: 0 | M26: 0 | O26: 0 | T26: 0 | V26: 0
A27: BE211 | B27: 3 | C27: BE | D27: Arr. Antwerpen | E27: Arr. Antwerpen | F27: 0 | J27: 0 | K27: 0 | L27: 0 | M27: 0 | Q27: 0 | R27: 0 | S27: 0 | T27: 0 | X27: 0 | Y27: 0 | Z27: 0
A28: BE213 | B28: 3 | C28: BE | D28: Arr. Turnhout | E28: Arr. Turnhout | F28: 0 | I28: 0 | L28: 0 | M28: 0 | P28: 0 | S28: 0 | T28: 0 | W28: 0 | Z28: 0
A29: BE224 | B29: 3 | C29: BE | D29: Arr. Hasselt | E29: Arr. Hasselt | F29: 0 | G29: 0 | L29: 0 | M29: 0 | N29: 0 | S29: 0 | T29: 0 | U29: 0 | Z29: 0
A30: BE233 | B30: 3 | C30: BE | D30: Arr. Eeklo | E30: Arr. Eeklo | F30: 0 | L30: 0 | M30: 0 | S30: 0 | T30: 0 | Z30: 0
A31: BE234 | B31: 3 | C31: BE | D31: Arr. Gent | E31: Arr. Gent | F31: 5.971563 | G31: 5.971563 | L31: 0 | M31: 4.5553471 | N31: 4.5553471 | S31: 0 | T31: 1.1268339 | U31: 1.1268339 | Z31: 0
A32: BE236 | B32: 3 | C32: BE | D32: Arr. Sint-Niklaas | E32: Arr. Sint-Niklaas | F32: 0 | L32: 0 | M32: 0 | S32: 0 | T32: 0 | Z32: 0
A33: BE255 | B33: 3 | C33: BE | D33: Arr. Oostende | E33: Arr. Oostende | F33: 0 | L33: 0 | M33: 0 | S33: 0 | T33: 0 | Z33: 0
A34: BE323 | B34: 3 | C34: BE | D34: Arr. Mons | E34: Arr. Mons | F34: 0 | H34: 0 | I34: 0 | K34: 0 | L34: 0 | M34: 0 | O34: 0 | P34: 0 | R34: 0 | S34: 0 | T34: 0 | V34: 0 | W34: 0 | Y34: 0 | Z34: 0
A35: BE328 | B35: 3 | C35: BE | D35: Arr. Tournai-Mouscron | E35: Arr. Tournai-Mouscron | F35: 0 | H35: 0 | M35: 0 | O35: 0 | T35: 0 | V35: 0
A36: BE32B | B36: 3 | C36: BE | D36: Arr. Charleroi | E36: Arr. Charleroi | F36: 0 | G36: 0 | M36: 0 | N36: 0 | T36: 0 | U36: 0
A37: BE32C | B37: 3 | C37: BE | D37: Arr. Soignies | E37: Arr. Soignies | F37: 0 | I37: 0 | L37: 0 | M37: 0 | P37: 0 | S37: 0 | T37: 0 | W37: 0 | Z37: 0
A38: BE32D | B38: 3 | C38: BE | D38: Arr. Thuin | E38: Arr. Thuin | F38: 0 | I38: 0 | M38: 0 | P38: 0 | T38: 0 | W38: 0
A39: BE332 | B39: 3 | C39: BE | D39: Arr. Liège | E39: Arr. Liège | F39: 0 | H39: 0 | M39: 0 | O39: 0 | T39: 0 | V39: 0
A40: BE335 | B40: 3 | C40: BE | D40: Arr. Verviers — communes francophones | E40: Arr. Verviers — communes francophones | F40: 0 | I40: 0 | M40: 0 | P40: 0 | T40: 0 | W40: 0
A41: BE352 | B41: 3 | C41: BE | D41: Arr. Namur | E41: Arr. Namur | F41: 0 | I41: 0 | L41: 0 | M41: 0 | P41: 0 | S41: 0 | T41: 0 | W41: 0 | Z41: 0
A42: BG313 | B42: 3 | C42: BG | D42: Vratsa | E42: Враца | F42: 0 | H42: 0 | M42: 0 | O42: 0 | T42: 0 | V42: 0
A43: BG314 | B43: 3 | C43: BG | D43: Pleven | E43: Плевен | F43: 0 | I43: 0 | M43: 0 | P43: 0 | T43: 0 | W43: 0
A44: BG315 | B44: 3 | C44: BG | D44: Lovech | E44: Ловеч | F44: 0 | H44: 0 | M44: 0 | O44: 0 | T44: 0 | V44: 0
A45: BG331 | B45: 3 | C45: BG | D45: Varna | E45: Варна | F45: 0 | H45: 0 | K45: 0 | M45: 0 | O45: 0 | R45: 0 | T45: 0 | V45: 0 | Y45: 0
A46: BG333 | B46: 3 | C46: BG | D46: Shumen | E46: Шумен | F46: 0 | I46: 0 | M46: 0 | P46: 0 | T46: 0 | W46: 0
A47: BG334 | B47: 3 | C47: BG | D47: Targovishte | E47: Търговище | F47: 0 | I47: 0 | M47: 0 | P47: 0 | T47: 0 | W47: 0
A48: BG341 | B48: 3 | C48: BG | D48: Burgas | E48: Бургас | F48: 0 | J48: 0 | M48: 0 | Q48: 0 | T48: 0 | X48: 0
A49: BG411 | B49: 3 | C49: BG | D49: Sofia (stolitsa) | E49: София (столица) | F49: 0 | I49: 0 | M49: 0 | P49: 0 | T49: 0 | W49: 0
A50: BG414 | B50: 3 | C50: BG | D50: Pernik | E50: Перник | F50: 0 | G50: 0 | M50: 0 | N50: 0 | T50: 0 | U50: 0
A51: BG421 | B51: 3 | C51: BG | D51: Plovdiv | E51: Пловдив | F51: 0 | I51: 0 | M51: 0 | P51: 0 | T51: 0 | W51: 0
A52: BG422 | B52: 3 | C52: BG | D52: Haskovo | E52: Хасково | F52: 0 | K52: 0 | M52: 0 | R52: 0 | T52: 0 | Y52: 0
A53: CY000 | B53: 3 | C53: CY | D53: Kýpros | E53: Κύπρος | F53: 0 | H53: 0 | M53: 0 | O53: 0 | T53: 0 | V53: 0
A54: CZ010 | B54: 3 | C54: CZ | D54: Hlavní město Praha | E54: Hlavní město Praha | F54: 0 | H54: 0 | M54: 0 | O54: 0 | T54: 0 | V54: 0
A55: CZ020 | B55: 3 | C55: CZ | D55: Středočeský kraj | E55: Středočeský kraj | F55: 0 | I55: 0 | J55: 0 | L55: 0 | M55: 0 | P55: 0 | Q55: 0 | S55: 0 | T55: 0 | W55: 0 | X55: 0 | Z55: 0
A56: CZ032 | B56: 3 | C56: CZ | D56: Plzeňský kraj | E56: Plzeňský kraj | F56: 0 | G56: 0 | I56: 0 | M56: 0 | N56: 0 | P56: 0 | T56: 0 | U56: 0 | W56: 0
A57: CZ041 | B57: 3 | C57: CZ | D57: Karlovarský kraj | E57: Karlovarský kraj | F57: 0 | I57: 0 | M57: 0 | P57: 0 | T57: 0 | W57: 0
A58: CZ042 | B58: 3 | C58: CZ | D58: Ústecký kraj | E58: Ústecký kraj | F58: 0 | H58: 0 | I58: 0 | J58: 0 | L58: 0 | M58: 0 | O58: 0 | P58: 0 | Q58: 0 | S58: 0 | T58: 0 | V58: 0 | W58: 0 | X58: 0 | Z58: 0
A59: CZ051 | B59: 3 | C59: CZ | D59: Liberecký kraj | E59: Liberecký kraj | F59: 0 | I59: 0 | M59: 0 | P59: 0 | T59: 0 | W59: 0
A60: CZ053 | B60: 3 | C60: CZ | D60: Pardubický kraj | E60: Pardubický kraj | F60: 0 | H60: 0 | I60: 0 | J60: 0 | M60: 0 | O60: 0 | P60: 0 | Q60: 0 | T60: 0 | V60: 0 | W60: 0 | X60: 0
A61: CZ063 | B61: 3 | C61: CZ | D61: Kraj Vysočina | E61: Kraj Vysočina | F61: 0 | I61: 0 | M61: 0 | P61: 0 | T61: 0 | W61: 0
A62: CZ064 | B62: 3 | C62: CZ | D62: Jihomoravský kraj | E62: Jihomoravský kraj | F62: 0 | H62: 0 | I62: 0 | M62: 0 | O62: 0 | P62: 0 | T62: 0 | V62: 0 | W62: 0
A63: CZ071 | B63: 3 | C63: CZ | D63: Olomoucký kraj | E63: Olomoucký kraj | F63: 0 | H63: 0 | L63: 0 | M63: 0 | O63: 0 | S63: 0 | T63: 0 | V63: 0 | Z63: 0
A64: CZ080 | B64: 3 | C64: CZ | D64: Moravskoslezský kraj | E64: Moravskoslezský kraj | F64: 5.2887767 | G64: 5.2887767 | I64: 0 | K64: 0 | L64: 0 | M64: 4.0344904 | N64: 4.0344904 | P64: 0 | R64: 0 | S64: 0 | T64: 0.99799217 | U64: 0.99799217 | W64: 0 | Y64: 0 | Z64: 0
A65: DE11C | B65: 3 | C65: DE | D65: Heidenheim | E65: Heidenheim | F65: 0 | H65: 0 | M65: 0 | O65: 0 | T65: 0 | V65: 0
A66: DE122 | B66: 3 | C66: DE | D66: Karlsruhe, Stadtkreis | E66: Karlsruhe, Stadtkreis | F66: 0 | J66: 0 | M66: 0 | Q66: 0 | T66: 0 | X66: 0
A67: DE123 | B67: 3 | C67: DE | D67: Karlsruhe, Landkreis | E67: Karlsruhe, Landkreis | F67: 0 | H67: 0 | M67: 0 | O67: 0 | T67: 0 | V67: 0
A68: DE126 | B68: 3 | C68: DE | D68: Mannheim, Stadtkreis | E68: Mannheim, Stadtkreis | F68: 0 | I68: 0 | M68: 0 | P68: 0 | T68: 0 | W68: 0
A69: DE128 | B69: 3 | C69: DE | D69: Rhein-Neckar-Kreis | E69: Rhein-Neckar-Kreis | F69: 0 | H69: 0 | M69: 0 | O69: 0 | T69: 0 | V69: 0
A70: DE131 | B70: 3 | C70: DE | D70: Freiburg im Breisgau, Stadtkreis | E70: Freiburg im Breisgau, Stadtkreis | F70: 0 | L70: 0 | M70: 0 | S70: 0 | T70: 0 | Z70: 0
A71: DE134 | B71: 3 | C71: DE | D71: Ortenaukreis | E71: Ortenaukreis | F71: 0 | G71: 0 | M71: 0 | N71: 0 | T71: 0 | U71: 0
A72: DE143 | B72: 3 | C72: DE | D72: Zollernalbkreis | E72: Zollernalbkreis | F72: 0 | H72: 0 | M72: 0 | O72: 0 | T72: 0 | V72: 0
A73: DE145 | B73: 3 | C73: DE | D73: Alb-Donau-Kreis | E73: Alb-Donau-Kreis | F73: 0 | H73: 0 | M73: 0 | O73: 0 | T73: 0 | V73: 0
A74: DE148 | B74: 3 | C74: DE | D74: Ravensburg | E74: Ravensburg | F74: 0 | I74: 0 | M74: 0 | P74: 0 | T74: 0 | W74: 0
A75: DE214 | B75: 3 | C75: DE | D75: Altötting | E75: Altötting | F75: 0 | J75: 0 | L75: 0 | M75: 0 | Q75: 0 | S75: 0 | T75: 0 | X75: 0 | Z75: 0
A76: DE219 | B76: 3 | C76: DE | D76: Eichstätt | E76: Eichstätt | F76: 0 | I76: 0 | J76: 0 | M76: 0 | P76: 0 | Q76: 0 | T76: 0 | W76: 0 | X76: 0
A77: DE21I | B77: 3 | C77: DE | D77: Neuburg-Schrobenhausen | E77: Neuburg-Schrobenhausen | F77: 0 | I77: 0 | M77: 0 | P77: 0 | T77: 0 | W77: 0
A78: DE21J | B78: 3 | C78: DE | D78: Pfaffenhofen a. d. Ilm | E78: Pfaffenhofen a. d. Ilm | F78: 0 | L78: 0 | M78: 0 | S78: 0 | T78: 0 | Z78: 0
A79: DE21K | B79: 3 | C79: DE | D79: Rosenheim, Landkreis | E79: Rosenheim, Landkreis | F79: 0 | H79: 0 | M79: 0 | O79: 0 | T79: 0 | V79: 0
A80: DE226 | B80: 3 | C80: DE | D80: Kelheim | E80: Kelheim | F80: 0 | J80: 0 | M80: 0 | Q80: 0 | T80: 0 | X80: 0
A81: DE229 | B81: 3 | C81: DE | D81: Regen | E81: Regen | F81: 0 | I81: 0 | M81: 0 | P81: 0 | T81: 0 | W81: 0
A82: DE237 | B82: 3 | C82: DE | D82: Neustadt a. d. Waldnaab | E82: Neustadt a. d. Waldnaab | F82: 0 | I82: 0 | M82: 0 | P82: 0 | T82: 0 | W82: 0
A83: DE239 | B83: 3 | C83: DE | D83: Schwandorf | E83: Schwandorf | F83: 0 | H83: 0 | M83: 0 | O83: 0 | T83: 0 | V83: 0
A84: DE24A | B84: 3 | C84: DE | D84: Kronach | E84: Kronach | F84: 0 | I84: 0 | M84: 0 | P84: 0 | T84: 0 | W84: 0
A85: DE24D | B85: 3 | C85: DE | D85: Wunsiedel i. Fichtelgebirge | E85: Wunsiedel i. Fichtelgebirge | F85: 0 | I85: 0 | M85: 0 | P85: 0 | T85: 0 | W85: 0
A86: DE25C | B86: 3 | C86: DE | D86: Weißenburg-Gunzenhausen | E86: Weißenburg-Gunzenhausen | F86: 0 | H86: 0 | M86: 0 | O86: 0 | T86: 0 | V86: 0
A87: DE26A | B87: 3 | C87: DE | D87: Main-Spessart | E87: Main-Spessart | F87: 0 | H87: 0 | I87: 0 | M87: 0 | O87: 0 | P87: 0 | T87: 0 | V87: 0 | W87: 0
A88: DE276 | B88: 3 | C88: DE | D88: Augsburg, Landkreis | E88: Augsburg, Landkreis | F88: 0 | G88: 0 | M88: 0 | N88: 0 | T88: 0 | U88: 0
A89: DE27D | B89: 3 | C89: DE | D89: Donau-Ries | E89: Donau-Ries | F89: 0 | H89: 0 | M89: 0 | O89: 0 | T89: 0 | V89: 0
A90: DE401 | B90: 3 | C90: DE | D90: Brandenburg an der Havel, Kreisfreie Stadt | E90: Brandenburg an der Havel, Kreisfreie Stadt | F90: 0 | G90: 0 | M90: 0 | N90: 0 | T90: 0 | U90: 0
A91: DE409 | B91: 3 | C91: DE | D91: Märkisch-Oderland | E91: Märkisch-Oderland | F91: 0 | H91: 0 | I91: 0 | M91: 0 | O91: 0 | P91: 0 | T91: 0 | V91: 0 | W91: 0
A92: DE40A | B92: 3 | C92: DE | D92: Oberhavel | E92: Oberhavel | F92: 0 | G92: 0 | M92: 0 | N92: 0 | T92: 0 | U92: 0
A93: DE40C | B93: 3 | C93: DE | D93: Oder-Spree | E93: Oder-Spree | F93: 2.573573 | G93: 2.573573 | M93: 1.9632244 | N93: 1.9632244 | T93: 0.48563322 | U93: 0.48563322
A94: DE40G | B94: 3 | C94: DE | D94: Spree-Neiße | E94: Spree-Neiße | F94: 0 | I94: 0 | M94: 0 | P94: 0 | T94: 0 | W94: 0
A95: DE40I | B95: 3 | C95: DE | D95: Uckermark | E95: Uckermark | F95: 0 | J95: 0 | M95: 0 | Q95: 0 | T95: 0 | X95: 0
A96: DE501 | B96: 3 | C96: DE | D96: Bremen, Kreisfreie Stadt | E96: Bremen, Kreisfreie Stadt | F96: 4.0748239 | G96: 4.0748239 | M96: 3.1084387 | N96: 3.1084387 | T96: 0.76891927 | U96: 0.76891927
A97: DE600 | B97: 3 | C97: DE | D97: Hamburg | E97: Hamburg | F97: 1.1795543 | G97: 1.1795543 | J97: 0 | M97: 0.89981119 | N97: 0.89981119 | Q97: 0 | T97: 0.22258189 | U97: 0.22258189 | X97: 0
A98: DE712 | B98: 3 | C98: DE | D98: Frankfurt am Main, Kreisfreie Stadt | E98: Frankfurt am Main, Kreisfreie Stadt | F98: 0 | L98: 0 | M98: 0 | S98: 0 | T98: 0 | Z98: 0
A99: DE714 | B99: 3 | C99: DE | D99: Wiesbaden, Kreisfreie Stadt | E99: Wiesbaden, Kreisfreie Stadt | F99: 0 | H99: 0 | M99: 0 | O99: 0 | T99: 0 | V99: 0
A100: DE722 | B100: 3 | C100: DE | D100: Lahn-Dill-Kreis | E100: Lahn-Dill-Kreis | F100: 0 | G100: 0 | M100: 0 | N100: 0 | T100: 0 | U100: 0
A101: DE732 | B101: 3 | C101: DE | D101: Fulda | E101: Fulda | F101: 0 | H101: 0 | M101: 0 | O101: 0 | T101: 0 | V101: 0
A102: DE80M | B102: 3 | C102: DE | D102: Nordwestmecklenburg | E102: Nordwestmecklenburg | F102: 0 | L102: 0 | M102: 0 | S102: 0 | T102: 0 | Z102: 0
A103: DE80O | B103: 3 | C103: DE | D103: Ludwigslust-Parchim | E103: Ludwigslust-Parchim | F103: 0 | I103: 0 | M103: 0 | P103: 0 | T103: 0 | W103: 0
A104: DE912 | B104: 3 | C104: DE | D104: Salzgitter, Kreisfreie Stadt | E104: Salzgitter, Kreisfreie Stadt | F104: 6.0050036 | G104: 6.0050036 | M104: 4.580857 | N104: 4.580857 | T104: 1.1331442 | U104: 1.1331442
A105: DE91A | B105: 3 | C105: DE | D105: Peine | E105: Peine | F105: 0 | G105: 0 | M105: 0 | N105: 0 | T105: 0 | U105: 0
A106: DE91C | B106: 3 | C106: DE | D106: Göttingen | E106: Göttingen | F106: 0 | L106: 0 | M106: 0 | S106: 0 | T106: 0 | Z106: 0
A107: DE922 | B107: 3 | C107: DE | D107: Diepholz | E107: Diepholz | F107: 0 | L107: 0 | M107: 0 | S107: 0 | T107: 0 | Z107: 0
A108: DE923 | B108: 3 | C108: DE | D108: Hameln-Pyrmont | E108: Hameln-Pyrmont | F108: 0 | I108: 0 | M108: 0 | P108: 0 | T108: 0 | W108: 0
A109: DE926 | B109: 3 | C109: DE | D109: Holzminden | E109: Holzminden | F109: 0 | I109: 0 | M109: 0 | P109: 0 | T109: 0 | W109: 0
A110: DE927 | B110: 3 | C110: DE | D110: Nienburg (Weser) | E110: Nienburg (Weser) | F110: 0 | I110: 0 | L110: 0 | M110: 0 | P110: 0 | S110: 0 | T110: 0 | W110: 0 | Z110: 0
A111: DE928 | B111: 3 | C111: DE | D111: Schaumburg | E111: Schaumburg | F111: 0 | I111: 0 | M111: 0 | P111: 0 | T111: 0 | W111: 0
...

Sheet Methanol (PJ per y)
F12: 2018 | M12: 2030 | T12: 2050
A13: NUTS ID | B13: NUTS LEVEL | C13: Country code | D13: NUTS region name (Latin) | E13: NUTS_NAME | F13: All sectors (PJ/y) | G13: Steel (PJ/y) | H13: Cement (PJ/y) | I13: Glass (PJ/y) | J13: Refineries (PJ/y) | K13: Fertilisers (PJ/y) | L13: Chemical (PJ/y) | M13: All sectors (PJ/y) | N13: Steel (PJ/y) | O13: Cement (PJ/y) | P13: Glass (PJ/y) | Q13: Refineries (PJ/y) | R13: Fertilisers (PJ/y) | S13: Chemical (PJ/y) | T13: All sectors (PJ/y) | U13: Steel (PJ/y) | V13: Cement (PJ/y) | W13: Glass (PJ/y) | X13: Refineries (PJ/y) | Y13: Fertilisers (PJ/y) | Z13: Chemical (PJ/y)
A14: AT121 | B14: 3 | C14: AT | D14: Mostviertel-Eisenwurzen | E14: Mostviertel-Eisenwurzen | F14: 0 | I14: 0 | M14: 0 | P14: 0 | T14: 0 | W14: 0
A15: AT122 | B15: 3 | C15: AT | D15: Niederösterreich-Süd | E15: Niederösterreich-Süd | F15: 0 | H15: 0 | M15: 0 | O15: 0 | T15: 0 | V15: 0
A16: AT124 | B16: 3 | C16: AT | D16: Waldviertel | E16: Waldviertel | F16: 0 | L16: 0 | M16: 0 | S16: 0 | T16: 0 | Z16: 0
A17: AT127 | B17: 3 | C17: AT | D17: Wiener Umland/Südteil | E17: Wiener Umland/Südteil | F17: 0 | H17: 0 | J17: 0 | L17: 0 | M17: 5.9444202 | O17: 0 | Q17: 0 | S17: 5.9444202 | T17: 19.405756 | V17: 0 | X17: 0 | Z17: 19.405756
A18: AT213 | B18: 3 | C18: AT | D18: Unterkärnten | E18: Unterkärnten | F18: 0 | H18: 0 | M18: 0 | O18: 0 | T18: 0 | V18: 0
A19: AT221 | B19: 3 | C19: AT | D19: Graz | E19: Graz | F19: 0 | G19: 0 | M19: 0 | N19: 0 | T19: 0 | U19: 0
A20: AT223 | B20: 3 | C20: AT | D20: Östliche Obersteiermark | E20: Östliche Obersteiermark | F20: 0 | G20: 0 | M20: 0 | N20: 0 | T20: 0 | U20: 0
A21: AT225 | B21: 3 | C21: AT | D21: West- und Südsteiermark | E21: West- und Südsteiermark | F21: 0 | H21: 0 | I21: 0 | M21: 0 | O21: 0 | P21: 0 | T21: 0 | V21: 0 | W21: 0
A22: AT312 | B22: 3 | C22: AT | D22: Linz-Wels | E22: Linz-Wels | F22: 0 | G22: 0 | K22: 0 | L22: 0 | M22: 0 | N22: 0 | R22: 0 | S22: 0 | T22: 0 | U22: 0 | Y22: 0 | Z22: 0
A23: AT314 | B23: 3 | C23: AT | D23: Steyr-Kirchdorf | E23: Steyr-Kirchdorf | F23: 0 | H23: 0 | I23: 0 | M23: 0 | O23: 0 | P23: 0 | T23: 0 | V23: 0 | W23: 0
A24: AT315 | B24: 3 | C24: AT | D24: Traunviertel | E24: Traunviertel | F24: 0 | H24: 0 | M24: 0 | O24: 0 | T24: 0 | V24: 0
A25: AT323 | B25: 3 | C25: AT | D25: Salzburg und Umgebung | E25: Salzburg und Umgebung | F25: 0 | H25: 0 | M25: 0 | O25: 0 | T25: 0 | V25: 0
A26: AT331 | B26: 3 | C26: AT | D26: Außerfern | E26: Außerfern | F26: 0 | H26: 0 | M26: 0 | O26: 0 | T26: 0 | V26: 0
A27: BE211 | B27: 3 | C27: BE | D27: Arr. Antwerpen | E27: Arr. Antwerpen | F27: 0 | J27: 0 | K27: 0 | L27: 0 | M27: 11.028445 | Q27: 0 | R27: 0 | S27: 11.028445 | T27: 36.002723 | X27: 0 | Y27: 0 | Z27: 36.002723
A28: BE213 | B28: 3 | C28: BE | D28: Arr. Turnhout | E28: Arr. Turnhout | F28: 0 | I28: 0 | L28: 0 | M28: 0 | P28: 0 | S28: 0 | T28: 0 | W28: 0 | Z28: 0
A29: BE224 | B29: 3 | C29: BE | D29: Arr. Hasselt | E29: Arr. Hasselt | F29: 0 | G29: 0 | L29: 0 | M29: 0 | N29: 0 | S29: 0 | T29: 0 | U29: 0 | Z29: 0
A30: BE233 | B30: 3 | C30: BE | D30: Arr. Eeklo | E30: Arr. Eeklo | F30: 0 | L30: 0 | M30: 0.17091033 | S30: 0.17091033 | T30: 0.55794243 | Z30: 0.55794243
A31: BE234 | B31: 3 | C31: BE | D31: Arr. Gent | E31: Arr. Gent | F31: 0 | G31: 0 | L31: 0 | M31: 0 | N31: 0 | S31: 0 | T31: 0 | U31: 0 | Z31: 0
A32: BE236 | B32: 3 | C32: BE | D32: Arr. Sint-Niklaas | E32: Arr. Sint-Niklaas | F32: 0 | L32: 0 | M32: 0 | S32: 0 | T32: 0 | Z32: 0
A33: BE255 | B33: 3 | C33: BE | D33: Arr. Oostende | E33: Arr. Oostende | F33: 0 | L33: 0 | M33: 0 | S33: 0 | T33: 0 | Z33: 0
A34: BE323 | B34: 3 | C34: BE | D34: Arr. Mons | E34: Arr. Mons | F34: 0 | H34: 0 | I34: 0 | K34: 0 | L34: 0 | M34: 0.17091033 | O34: 0 | P34: 0 | R34: 0 | S34: 0.17091033 | T34: 0.55794243 | V34: 0 | W34: 0 | Y34: 0 | Z34: 0.55794243
A35: BE328 | B35: 3 | C35: BE | D35: Arr. Tournai-Mouscron | E35: Arr. Tournai-Mouscron | F35: 0 | H35: 0 | M35: 0 | O35: 0 | T35: 0 | V35: 0
A36: BE32B | B36: 3 | C36: BE | D36: Arr. Charleroi | E36: Arr. Charleroi | F36: 0 | G36: 0 | M36: 0 | N36: 0 | T36: 0 | U36: 0
A37: BE32C | B37: 3 | C37: BE | D37: Arr. Soignies | E37: Arr. Soignies | F37: 0 | I37: 0 | L37: 0 | M37: 0 | P37: 0 | S37: 0 | T37: 0 | W37: 0 | Z37: 0
A38: BE32D | B38: 3 | C38: BE | D38: Arr. Thuin | E38: Arr. Thuin | F38: 0 | I38: 0 | M38: 0 | P38: 0 | T38: 0 | W38: 0
A39: BE332 | B39: 3 | C39: BE | D39: Arr. Liège | E39: Arr. Liège | F39: 0 | H39: 0 | M39: 0 | O39: 0 | T39: 0 | V39: 0
A40: BE335 | B40: 3 | C40: BE | D40: Arr. Verviers — communes francophones | E40: Arr. Verviers — communes francophones | F40: 0 | I40: 0 | M40: 0 | P40: 0 | T40: 0 | W40: 0
A41: BE352 | B41: 3 | C41: BE | D41: Arr. Namur | E41: Arr. Namur | F41: 0 | I41: 0 | L41: 0 | M41: 0 | P41: 0 | S41: 0 | T41: 0 | W41: 0 | Z41: 0
A42: BG313 | B42: 3 | C42: BG | D42: Vratsa | E42: Враца | F42: 0 | H42: 0 | M42: 0 | O42: 0 | T42: 0 | V42: 0
A43: BG314 | B43: 3 | C43: BG | D43: Pleven | E43: Плевен | F43: 0 | I43: 0 | M43: 0 | P43: 0 | T43: 0 | W43: 0
A44: BG315 | B44: 3 | C44: BG | D44: Lovech | E44: Ловеч | F44: 0 | H44: 0 | M44: 0 | O44: 0 | T44: 0 | V44: 0
A45: BG331 | B45: 3 | C45: BG | D45: Varna | E45: Варна | F45: 0 | H45: 0 | K45: 0 | M45: 0 | O45: 0 | R45: 0 | T45: 0 | V45: 0 | Y45: 0
A46: BG333 | B46: 3 | C46: BG | D46: Shumen | E46: Шумен | F46: 0 | I46: 0 | M46: 0 | P46: 0 | T46: 0 | W46: 0
A47: BG334 | B47: 3 | C47: BG | D47: Targovishte | E47: Търговище | F47: 0 | I47: 0 | M47: 0 | P47: 0 | T47: 0 | W47: 0
A48: BG341 | B48: 3 | C48: BG | D48: Burgas | E48: Бургас | F48: 0 | J48: 0 | M48: 0 | Q48: 0 | T48: 0 | X48: 0
A49: BG411 | B49: 3 | C49: BG | D49: Sofia (stolitsa) | E49: София (столица) | F49: 0 | I49: 0 | M49: 0 | P49: 0 | T49: 0 | W49: 0
A50: BG414 | B50: 3 | C50: BG | D50: Pernik | E50: Перник | F50: 0 | G50: 0 | M50: 0 | N50: 0 | T50: 0 | U50: 0
A51: BG421 | B51: 3 | C51: BG | D51: Plovdiv | E51: Пловдив | F51: 0 | I51: 0 | M51: 0 | P51: 0 | T51: 0 | W51: 0
A52: BG422 | B52: 3 | C52: BG | D52: Haskovo | E52: Хасково | F52: 0 | K52: 0 | M52: 0 | R52: 0 | T52: 0 | Y52: 0
A53: CY000 | B53: 3 | C53: CY | D53: Kýpros | E53: Κύπρος | F53: 0 | H53: 0 | M53: 0 | O53: 0 | T53: 0 | V53: 0
A54: CZ010 | B54: 3 | C54: CZ | D54: Hlavní město Praha | E54: Hlavní město Praha | F54: 0 | H54: 0 | M54: 0 | O54: 0 | T54: 0 | V54: 0
A55: CZ020 | B55: 3 | C55: CZ | D55: Středočeský kraj | E55: Středočeský kraj | F55: 0 | I55: 0 | J55: 0 | L55: 0 | M55: 0.17091033 | P55: 0 | Q55: 0 | S55: 0.17091033 | T55: 0.55794243 | W55: 0 | X55: 0 | Z55: 0.55794243
A56: CZ032 | B56: 3 | C56: CZ | D56: Plzeňský kraj | E56: Plzeňský kraj | F56: 0 | G56: 0 | I56: 0 | M56: 0 | N56: 0 | P56: 0 | T56: 0 | U56: 0 | W56: 0
A57: CZ041 | B57: 3 | C57: CZ | D57: Karlovarský kraj | E57: Karlovarský kraj | F57: 0 | I57: 0 | M57: 0 | P57: 0 | T57: 0 | W57: 0
A58: CZ042 | B58: 3 | C58: CZ | D58: Ústecký kraj | E58: Ústecký kraj | F58: 0 | H58: 0 | I58: 0 | J58: 0 | L58: 0 | M58: 6.4675291 | O58: 0 | P58: 0 | Q58: 0 | S58: 6.4675291 | T58: 21.113463 | V58: 0 | W58: 0 | X58: 0 | Z58: 21.113463
A59: CZ051 | B59: 3 | C59: CZ | D59: Liberecký kraj | E59: Liberecký kraj | F59: 0 | I59: 0 | M59: 0 | P59: 0 | T59: 0 | W59: 0
A60: CZ053 | B60: 3 | C60: CZ | D60: Pardubický kraj | E60: Pardubický kraj | F60: 0 | H60: 0 | I60: 0 | J60: 0 | M60: 0 | O60: 0 | P60: 0 | Q60: 0 | T60: 0 | V60: 0 | W60: 0 | X60: 0
A61: CZ063 | B61: 3 | C61: CZ | D61: Kraj Vysočina | E61: Kraj Vysočina | F61: 0 | I61: 0 | M61: 0 | P61: 0 | T61: 0 | W61: 0
A62: CZ064 | B62: 3 | C62: CZ | D62: Jihomoravský kraj | E62: Jihomoravský kraj | F62: 0 | H62: 0 | I62: 0 | M62: 0 | O62: 0 | P62: 0 | T62: 0 | V62: 0 | W62: 0
A63: CZ071 | B63: 3 | C63: CZ | D63: Olomoucký kraj | E63: Olomoucký kraj | F63: 0 | H63: 0 | L63: 0 | M63: 0.17091033 | O63: 0 | S63: 0.17091033 | T63: 0.55794243 | V63: 0 | Z63: 0.55794243
A64: CZ080 | B64: 3 | C64: CZ | D64: Moravskoslezský kraj | E64: Moravskoslezský kraj | F64: 0 | G64: 0 | I64: 0 | K64: 0 | L64: 0 | M64: 0.17091033 | N64: 0 | P64: 0 | R64: 0 | S64: 0.17091033 | T64: 0.55794243 | U64: 0 | W64: 0 | Y64: 0 | Z64: 0.55794243
A65: DE11C | B65: 3 | C65: DE | D65: Heidenheim | E65: Heidenheim | F65: 0 | H65: 0 | M65: 0 | O65: 0 | T65: 0 | V65: 0
A66: DE122 | B66: 3 | C66: DE | D66: Karlsruhe, Stadtkreis | E66: Karlsruhe, Stadtkreis | F66: 0 | J66: 0 | M66: 0 | Q66: 0 | T66: 0 | X66: 0
A67: DE123 | B67: 3 | C67: DE | D67: Karlsruhe, Landkreis | E67: Karlsruhe, Landkreis | F67: 0 | H67: 0 | M67: 0 | O67: 0 | T67: 0 | V67: 0
A68: DE126 | B68: 3 | C68: DE | D68: Mannheim, Stadtkreis | E68: Mannheim, Stadtkreis | F68: 0 | I68: 0 | M68: 0 | P68: 0 | T68: 0 | W68: 0
A69: DE128 | B69: 3 | C69: DE | D69: Rhein-Neckar-Kreis | E69: Rhein-Neckar-Kreis | F69: 0 | H69: 0 | M69: 0 | O69: 0 | T69: 0 | V69: 0
A70: DE131 | B70: 3 | C70: DE | D70: Freiburg im Breisgau, Stadtkreis | E70: Freiburg im Breisgau, Stadtkreis | F70: 0 | L70: 0 | M70: 0 | S70: 0 | T70: 0 | Z70: 0
A71: DE134 | B71: 3 | C71: DE | D71: Ortenaukreis | E71: Ortenaukreis | F71: 0 | G71: 0 | M71: 0 | N71: 0 | T71: 0 | U71: 0
A72: DE143 | B72: 3 | C72: DE | D72: Zollernalbkreis | E72: Zollernalbkreis | F72: 0 | H72: 0 | M72: 0 | O72: 0 | T72: 0 | V72: 0
A73: DE145 | B73: 3 | C73: DE | D73: Alb-Donau-Kreis | E73: Alb-Donau-Kreis | F73: 0 | H73: 0 | M73: 0 | O73: 0 | T73: 0 | V73: 0
A74: DE148 | B74: 3 | C74: DE | D74: Ravensburg | E74: Ravensburg | F74: 0 | I74: 0 | M74: 0 | P74: 0 | T74: 0 | W74: 0
A75: DE214 | B75: 3 | C75: DE | D75: Altötting | E75: Altötting | F75: 0 | J75: 0 | L75: 0 | M75: 5.3499781 | Q75: 0 | S75: 5.3499781 | T75: 17.46518 | X75: 0 | Z75: 17.46518
A76: DE219 | B76: 3 | C76: DE | D76: Eichstätt | E76: Eichstätt | F76: 0 | I76: 0 | J76: 0 | M76: 0 | P76: 0 | Q76: 0 | T76: 0 | W76: 0 | X76: 0
A77: DE21I | B77: 3 | C77: DE | D77: Neuburg-Schrobenhausen | E77: Neuburg-Schrobenhausen | F77: 0 | I77: 0 | M77: 0 | P77: 0 | T77: 0 | W77: 0
A78: DE21J | B78: 3 | C78: DE | D78: Pfaffenhofen a. d. Ilm | E78: Pfaffenhofen a. d. Ilm | F78: 0 | L78: 0 | M78: 0.60280201 | S78: 0.60280201 | T78: 1.9678671 | Z78: 1.9678671
A79: DE21K | B79: 3 | C79: DE | D79: Rosenheim, Landkreis | E79: Rosenheim, Landkreis | F79: 0 | H79: 0 | M79: 0 | O79: 0 | T79: 0 | V79: 0
A80: DE226 | B80: 3 | C80: DE | D80: Kelheim | E80: Kelheim | F80: 0 | J80: 0 | M80: 0 | Q80: 0 | T80: 0 | X80: 0
A81: DE229 | B81: 3 | C81: DE | D81: Regen | E81: Regen | F81: 0 | I81: 0 | M81: 0 | P81: 0 | T81: 0 | W81: 0
A82: DE237 | B82: 3 | C82: DE | D82: Neustadt a. d. Waldnaab | E82: Neustadt a. d. Waldnaab | F82: 0 | I82: 0 | M82: 0 | P82: 0 | T82: 0 | W82: 0
A83: DE239 | B83: 3 | C83: DE | D83: Schwandorf | E83: Schwandorf | F83: 0 | H83: 0 | M83: 0 | O83: 0 | T83: 0 | V83: 0
A84: DE24A | B84: 3 | C84: DE | D84: Kronach | E84: Kronach | F84: 0 | I84: 0 | M84: 0 | P84: 0 | T84: 0 | W84: 0
A85: DE24D | B85: 3 | C85: DE | D85: Wunsiedel i. Fichtelgebirge | E85: Wunsiedel i. Fichtelgebirge | F85: 0 | I85: 0 | M85: 0 | P85: 0 | T85: 0 | W85: 0
A86: DE25C | B86: 3 | C86: DE | D86: Weißenburg-Gunzenhausen | E86: Weißenburg-Gunzenhausen | F86: 0 | H86: 0 | M86: 0 | O86: 0 | T86: 0 | V86: 0
A87: DE26A | B87: 3 | C87: DE | D87: Main-Spessart | E87: Main-Spessart | F87: 0 | H87: 0 | I87: 0 | M87: 0 | O87: 0 | P87: 0 | T87: 0 | V87: 0 | W87: 0
A88: DE276 | B88: 3 | C88: DE | D88: Augsburg, Landkreis | E88: Augsburg, Landkreis | F88: 0 | G88: 0 | M88: 0 | N88: 0 | T88: 0 | U88: 0
A89: DE27D | B89: 3 | C89: DE | D89: Donau-Ries | E89: Donau-Ries | F89: 0 | H89: 0 | M89: 0 | O89: 0 | T89: 0 | V89: 0
A90: DE401 | B90: 3 | C90: DE | D90: Brandenburg an der Havel, Kreisfreie Stadt | E90: Brandenburg an der Havel, Kreisfreie Stadt | F90: 0 | G90: 0 | M90: 0 | N90: 0 | T90: 0 | U90: 0
A91: DE409 | B91: 3 | C91: DE | D91: Märkisch-Oderland | E91: Märkisch-Oderland | F91: 0 | H91: 0 | I91: 0 | M91: 0 | O91: 0 | P91: 0 | T91: 0 | V91: 0 | W91: 0
A92: DE40A | B92: 3 | C92: DE | D92: Oberhavel | E92: Oberhavel | F92: 0 | G92: 0 | M92: 0 | N92: 0 | T92: 0 | U92: 0
A93: DE40C | B93: 3 | C93: DE | D93: Oder-Spree | E93: Oder-Spree | F93: 0 | G93: 0 | M93: 0 | N93: 0 | T93: 0 | U93: 0
A94: DE40G | B94: 3 | C94: DE | D94: Spree-Neiße | E94: Spree-Neiße | F94: 0 | I94: 0 | M94: 0 | P94: 0 | T94: 0 | W94: 0
A95: DE40I | B95: 3 | C95: DE | D95: Uckermark | E95: Uckermark | F95: 0 | J95: 0 | M95: 0 | Q95: 0 | T95: 0 | X95: 0
A96: DE501 | B96: 3 | C96: DE | D96: Bremen, Kreisfreie Stadt | E96: Bremen, Kreisfreie Stadt | F96: 0 | G96: 0 | M96: 0 | N96: 0 | T96: 0 | U96: 0
A97: DE600 | B97: 3 | C97: DE | D97: Hamburg | E97: Hamburg | F97: 0 | G97: 0 | J97: 0 | M97: 0 | N97: 0 | Q97: 0 | T97: 0 | U97: 0 | X97: 0
A98: DE712 | B98: 3 | C98: DE | D98: Frankfurt am Main, Kreisfreie Stadt | E98: Frankfurt am Main, Kreisfreie Stadt | F98: 0 | L98: 0 | M98: 1.5693269 | S98: 1.5693269 | T98: 5.1231196 | Z98: 5.1231196
A99: DE714 | B99: 3 | C99: DE | D99: Wiesbaden, Kreisfreie Stadt | E99: Wiesbaden, Kreisfreie Stadt | F99: 0 | H99: 0 | M99: 0 | O99: 0 | T99: 0 | V99: 0
A100: DE722 | B100: 3 | C100: DE | D100: Lahn-Dill-Kreis | E100: Lahn-Dill-Kreis | F100: 0 | G100: 0 | M100: 0 | N100: 0 | T100: 0 | U100: 0
A101: DE732 | B101: 3 | C101: DE | D101: Fulda | E101: Fulda | F101: 0 | H101: 0 | M101: 0 | O101: 0 | T101: 0 | V101: 0
A102: DE80M | B102: 3 | C102: DE | D102: Nordwestmecklenburg | E102: Nordwestmecklenburg | F102: 0 | L102: 0 | M102: 0.17091033 | S102: 0.17091033 | T102: 0.55794243 | Z102: 0.55794243
A103: DE80O | B103: 3 | C103: DE | D103: Ludwigslust-Parchim | E103: Ludwigslust-Parchim | F103: 0 | I103: 0 | M103: 0 | P103: 0 | T103: 0 | W103: 0
A104: DE912 | B104: 3 | C104: DE | D104: Salzgitter, Kreisfreie Stadt | E104: Salzgitter, Kreisfreie Stadt | F104: 0 | G104: 0 | M104: 0 | N104: 0 | T104: 0 | U104: 0
A105: DE91A | B105: 3 | C105: DE | D105: Peine | E105: Peine | F105: 0 | G105: 0 | M105: 0 | N105: 0 | T105: 0 | U105: 0
A106: DE91C | B106: 3 | C106: DE | D106: Göttingen | E106: Göttingen | F106: 0 | L106: 0 | M106: 0 | S106: 0 | T106: 0 | Z106: 0
A107: DE922 | B107: 3 | C107: DE | D107: Diepholz | E107: Diepholz | F107: 0 | L107: 0 | M107: 0 | S107: 0 | T107: 0 | Z107: 0
A108: DE923 | B108: 3 | C108: DE | D108: Hameln-Pyrmont | E108: Hameln-Pyrmont | F108: 0 | I108: 0 | M108: 0 | P108: 0 | T108: 0 | W108: 0
A109: DE926 | B109: 3 | C109: DE | D109: Holzminden | E109: Holzminden | F109: 0 | I109: 0 | M109: 0 | P109: 0 | T109: 0 | W109: 0
A110: DE927 | B110: 3 | C110: DE | D110: Nienburg (Weser) | E110: Nienburg (Weser) | F110: 0 | I110: 0 | L110: 0 | M110: 0 | P110: 0 | S110: 0 | T110: 0 | W110: 0 | Z110: 0
A111: DE928 | B111: 3 | C111: DE | D111: Schaumburg | E111: Schaumburg | F111: 0 | I111: 0 | M111: 0 | P111: 0 | T111: 0 | W111: 0
...

Sheet Naphtha (PJ per y)
F12: 2018 | M12: 2030 | T12: 2050
A13: NUTS ID | B13: NUTS LEVEL | C13: Country code | D13: NUTS region name (Latin) | E13: NUTS_NAME | F13: All sectors (PJ/y) | G13: Steel (PJ/y) | H13: Cement (PJ/y) | I13: Glass (PJ/y) | J13: Refineries (PJ/y) | K13: Fertilisers (PJ/y) | L13: Chemical (PJ/y) | M13: All sectors (PJ/y) | N13: Steel (PJ/y) | O13: Cement (PJ/y) | P13: Glass (PJ/y) | Q13: Refineries (PJ/y) | R13: Fertilisers (PJ/y) | S13: Chemical (PJ/y) | T13: All sectors (PJ/y) | U13: Steel (PJ/y) | V13: Cement (PJ/y) | W13: Glass (PJ/y) | X13: Refineries (PJ/y) | Y13: Fertilisers (PJ/y) | Z13: Chemical (PJ/y)
A14: AT121 | B14: 3 | C14: AT | D14: Mostviertel-Eisenwurzen | E14: Mostviertel-Eisenwurzen | F14: 0 | I14: 0 | M14: 0 | P14: 0 | T14: 0 | W14: 0
A15: AT122 | B15: 3 | C15: AT | D15: Niederösterreich-Süd | E15: Niederösterreich-Süd | F15: 0 | H15: 0 | M15: 0 | O15: 0 | T15: 0 | V15: 0
A16: AT124 | B16: 3 | C16: AT | D16: Waldviertel | E16: Waldviertel | F16: 0 | L16: 0 | M16: 0 | S16: 0 | T16: 0 | Z16: 0
A17: AT127 | B17: 3 | C17: AT | D17: Wiener Umland/Südteil | E17: Wiener Umland/Südteil | F17: 77.031538 | H17: 0 | J17: 0 | L17: 77.031538 | M17: 56.756067 | O17: 0 | Q17: 0 | S17: 56.756067 | T17: 10.841419 | V17: 0 | X17: 0 | Z17: 10.841419
A18: AT213 | B18: 3 | C18: AT | D18: Unterkärnten | E18: Unterkärnten | F18: 0 | H18: 0 | M18: 0 | O18: 0 | T18: 0 | V18: 0
A19: AT221 | B19: 3 | C19: AT | D19: Graz | E19: Graz | F19: 0 | G19: 0 | M19: 0 | N19: 0 | T19: 0 | U19: 0
A20: AT223 | B20: 3 | C20: AT | D20: Östliche Obersteiermark | E20: Östliche Obersteiermark | F20: 0 | G20: 0 | M20: 0 | N20: 0 | T20: 0 | U20: 0
A21: AT225 | B21: 3 | C21: AT | D21: West- und Südsteiermark | E21: West- und Südsteiermark | F21: 0 | H21: 0 | I21: 0 | M21: 0 | O21: 0 | P21: 0 | T21: 0 | V21: 0 | W21: 0
A22: AT312 | B22: 3 | C22: AT | D22: Linz-Wels | E22: Linz-Wels | F22: 0 | G22: 0 | K22: 0 | L22: 0 | M22: 0 | N22: 0 | R22: 0 | S22: 0 | T22: 0 | U22: 0 | Y22: 0 | Z22: 0
A23: AT314 | B23: 3 | C23: AT | D23: Steyr-Kirchdorf | E23: Steyr-Kirchdorf | F23: 0 | H23: 0 | I23: 0 | M23: 0 | O23: 0 | P23: 0 | T23: 0 | V23: 0 | W23: 0
A24: AT315 | B24: 3 | C24: AT | D24: Traunviertel | E24: Traunviertel | F24: 0 | H24: 0 | M24: 0 | O24: 0 | T24: 0 | V24: 0
A25: AT323 | B25: 3 | C25: AT | D25: Salzburg und Umgebung | E25: Salzburg und Umgebung | F25: 0 | H25: 0 | M25: 0 | O25: 0 | T25: 0 | V25: 0
A26: AT331 | B26: 3 | C26: AT | D26: Außerfern | E26: Außerfern | F26: 0 | H26: 0 | M26: 0 | O26: 0 | T26: 0 | V26: 0
A27: BE211 | B27: 3 | C27: BE | D27: Arr. Antwerpen | E27: Arr. Antwerpen | F27: 142.91353 | J27: 0 | K27: 0 | L27: 142.91353 | M27: 105.29726 | Q27: 0 | R27: 0 | S27: 105.29726 | T27: 20.11365 | X27: 0 | Y27: 0 | Z27: 20.11365
A28: BE213 | B28: 3 | C28: BE | D28: Arr. Turnhout | E28: Arr. Turnhout | F28: 0 | I28: 0 | L28: 0 | M28: 0 | P28: 0 | S28: 0 | T28: 0 | W28: 0 | Z28: 0
A29: BE224 | B29: 3 | C29: BE | D29: Arr. Hasselt | E29: Arr. Hasselt | F29: 0 | G29: 0 | L29: 0 | M29: 0 | N29: 0 | S29: 0 | T29: 0 | U29: 0 | Z29: 0
A30: BE233 | B30: 3 | C30: BE | D30: Arr. Eeklo | E30: Arr. Eeklo | F30: 2.2147637 | L30: 2.2147637 | M30: 1.6318157 | S30: 1.6318157 | T30: 0.31170584 | Z30: 0.31170584
A31: BE234 | B31: 3 | C31: BE | D31: Arr. Gent | E31: Arr. Gent | F31: 0 | G31: 0 | L31: 0 | M31: 0 | N31: 0 | S31: 0 | T31: 0 | U31: 0 | Z31: 0
A32: BE236 | B32: 3 | C32: BE | D32: Arr. Sint-Niklaas | E32: Arr. Sint-Niklaas | F32: 0 | L32: 0 | M32: 0 | S32: 0 | T32: 0 | Z32: 0
A33: BE255 | B33: 3 | C33: BE | D33: Arr. Oostende | E33: Arr. Oostende | F33: 0 | L33: 0 | M33: 0 | S33: 0 | T33: 0 | Z33: 0
A34: BE323 | B34: 3 | C34: BE | D34: Arr. Mons | E34: Arr. Mons | F34: 2.2147637 | H34: 0 | I34: 0 | K34: 0 | L34: 2.2147637 | M34: 1.6318157 | O34: 0 | P34: 0 | R34: 0 | S34: 1.6318157 | T34: 0.31170584 | V34: 0 | W34: 0 | Y34: 0 | Z34: 0.31170584
A35: BE328 | B35: 3 | C35: BE | D35: Arr. Tournai-Mouscron | E35: Arr. Tournai-Mouscron | F35: 0 | H35: 0 | M35: 0 | O35: 0 | T35: 0 | V35: 0
A36: BE32B | B36: 3 | C36: BE | D36: Arr. Charleroi | E36: Arr. Charleroi | F36: 0 | G36: 0 | M36: 0 | N36: 0 | T36: 0 | U36: 0
A37: BE32C | B37: 3 | C37: BE | D37: Arr. Soignies | E37: Arr. Soignies | F37: 0 | I37: 0 | L37: 0 | M37: 0 | P37: 0 | S37: 0 | T37: 0 | W37: 0 | Z37: 0
A38: BE32D | B38: 3 | C38: BE | D38: Arr. Thuin | E38: Arr. Thuin | F38: 0 | I38: 0 | M38: 0 | P38: 0 | T38: 0 | W38: 0
A39: BE332 | B39: 3 | C39: BE | D39: Arr. Liège | E39: Arr. Liège | F39: 0 | H39: 0 | M39: 0 | O39: 0 | T39: 0 | V39: 0
A40: BE335 | B40: 3 | C40: BE | D40: Arr. Verviers — communes francophones | E40: Arr. Verviers — communes francophones | F40: 0 | I40: 0 | M40: 0 | P40: 0 | T40: 0 | W40: 0
A41: BE352 | B41: 3 | C41: BE | D41: Arr. Namur | E41: Arr. Namur | F41: 0 | I41: 0 | L41: 0 | M41: 0 | P41: 0 | S41: 0 | T41: 0 | W41: 0 | Z41: 0
A42: BG313 | B42: 3 | C42: BG | D42: Vratsa | E42: Враца | F42: 0 | H42: 0 | M42: 0 | O42: 0 | T42: 0 | V42: 0
A43: BG314 | B43: 3 | C43: BG | D43: Pleven | E43: Плевен | F43: 0 | I43: 0 | M43: 0 | P43: 0 | T43: 0 | W43: 0
A44: BG315 | B44: 3 | C44: BG | D44: Lovech | E44: Ловеч | F44: 0 | H44: 0 | M44: 0 | O44: 0 | T44: 0 | V44: 0
A45: BG331 | B45: 3 | C45: BG | D45: Varna | E45: Варна | F45: 0 | H45: 0 | K45: 0 | M45: 0 | O45: 0 | R45: 0 | T45: 0 | V45: 0 | Y45: 0
A46: BG333 | B46: 3 | C46: BG | D46: Shumen | E46: Шумен | F46: 0 | I46: 0 | M46: 0 | P46: 0 | T46: 0 | W46: 0
A47: BG334 | B47: 3 | C47: BG | D47: Targovishte | E47: Търговище | F47: 0 | I47: 0 | M47: 0 | P47: 0 | T47: 0 | W47: 0
A48: BG341 | B48: 3 | C48: BG | D48: Burgas | E48: Бургас | F48: 0 | J48: 0 | M48: 0 | Q48: 0 | T48: 0 | X48: 0
A49: BG411 | B49: 3 | C49: BG | D49: Sofia (stolitsa) | E49: София (столица) | F49: 0 | I49: 0 | M49: 0 | P49: 0 | T49: 0 | W49: 0
A50: BG414 | B50: 3 | C50: BG | D50: Pernik | E50: Перник | F50: 0 | G50: 0 | M50: 0 | N50: 0 | T50: 0 | U50: 0
A51: BG421 | B51: 3 | C51: BG | D51: Plovdiv | E51: Пловдив | F51: 0 | I51: 0 | M51: 0 | P51: 0 | T51: 0 | W51: 0
A52: BG422 | B52: 3 | C52: BG | D52: Haskovo | E52: Хасково | F52: 0 | K52: 0 | M52: 0 | R52: 0 | T52: 0 | Y52: 0
A53: CY000 | B53: 3 | C53: CY | D53: Kýpros | E53: Κύπρος | F53: 0 | H53: 0 | M53: 0 | O53: 0 | T53: 0 | V53: 0
A54: CZ010 | B54: 3 | C54: CZ | D54: Hlavní město Praha | E54: Hlavní město Praha | F54: 0 | H54: 0 | M54: 0 | O54: 0 | T54: 0 | V54: 0
A55: CZ020 | B55: 3 | C55: CZ | D55: Středočeský kraj | E55: Středočeský kraj | F55: 2.2147637 | I55: 0 | J55: 0 | L55: 2.2147637 | M55: 1.6318157 | P55: 0 | Q55: 0 | S55: 1.6318157 | T55: 0.31170584 | W55: 0 | X55: 0 | Z55: 0.31170584
A56: CZ032 | B56: 3 | C56: CZ | D56: Plzeňský kraj | E56: Plzeňský kraj | F56: 0 | G56: 0 | I56: 0 | M56: 0 | N56: 0 | P56: 0 | T56: 0 | U56: 0 | W56: 0
A57: CZ041 | B57: 3 | C57: CZ | D57: Karlovarský kraj | E57: Karlovarský kraj | F57: 0 | I57: 0 | M57: 0 | P57: 0 | T57: 0 | W57: 0
A58: CZ042 | B58: 3 | C58: CZ | D58: Ústecký kraj | E58: Ústecký kraj | F58: 83.810314 | H58: 0 | I58: 0 | J58: 0 | L58: 83.810314 | M58: 61.750601 | O58: 0 | P58: 0 | Q58: 0 | S58: 61.750601 | T58: 11.795464 | V58: 0 | W58: 0 | X58: 0 | Z58: 11.795464
A59: CZ051 | B59: 3 | C59: CZ | D59: Liberecký kraj | E59: Liberecký kraj | F59: 0 | I59: 0 | M59: 0 | P59: 0 | T59: 0 | W59: 0
A60: CZ053 | B60: 3 | C60: CZ | D60: Pardubický kraj | E60: Pardubický kraj | F60: 0 | H60: 0 | I60: 0 | J60: 0 | M60: 0 | O60: 0 | P60: 0 | Q60: 0 | T60: 0 | V60: 0 | W60: 0 | X60: 0
A61: CZ063 | B61: 3 | C61: CZ | D61: Kraj Vysočina | E61: Kraj Vysočina | F61: 0 | I61: 0 | M61: 0 | P61: 0 | T61: 0 | W61: 0
A62: CZ064 | B62: 3 | C62: CZ | D62: Jihomoravský kraj | E62: Jihomoravský kraj | F62: 0 | H62: 0 | I62: 0 | M62: 0 | O62: 0 | P62: 0 | T62: 0 | V62: 0 | W62: 0
