Workbook
Name rng_VBA_Formats: OFFSET([5]VBA!$K$21, 0, 0, [5]VBA!$C$19)
Name rng_VBA_LineStyles: OFFSET([5]VBA!$L$21, 0, 0, [5]VBA!$C$19)
Name rng_VBA_Names: OFFSET([5]VBA!$B$21:$I$21, 0, 0, [5]VBA!$C$19)

Sheet COVER
C4: Dataset | E4: 1H 2022 LCOE Update - Charts
C8: Date | E8: 44742
C10: Contact | E10: Amar Vasdev Tifenn Brandily
E11: Bloomberg Terminal: press <Help> key twice
E12: support.bnef@bloomberg.net
C14: Description | E14: This spreadsheet contains data and charts from the 1H 2022 LCOE update.
C16: Contents
C17: Global LCOE benchmarks | E17: Global LCOE benchmarks
C18: Key messages -->
C19: Global LCOEs by tech | E19: Global LCOEs by technology
C20: Turbine prices | E20: Regional onshore wind turbine prices by signing date (USD)
C21: Global wind LCOE benchmarks | E21: Global onshore and offshore wind LCOE benchmarks with and without China, 1H 2021-2022
C22: PV cost inflation | E22: PV cost inflation
C23: Onshore wind cost inflation | E23: Onshore wind cost inflation
C24: Battery costs | E24: Energy storage project costs 2021, based on usable capacity
C25: Storage LCOE | E25: Storage LCOE 1H 2021 versus 1H 2022
C26: Coal & gas cost inflation | E26: Coal & gas cost inflation
C27: Key long-term trends ->
C28: PV mono vs multi panels | E28: Mono vs multi share
C29: PV bifacial vs monofacial | E29: Share of bifacial module among all silicon PV
C30: Project size, Utility-scale PV | E30: Project size, Utility-scale PV
C31: Turbine size, Onshore wind | E31: Turbine size, Onshore wind
C32: Project size, Onshore wind | E32: Project size, Onshore wind
C33: Onshore wind capacity factors | E33: Onshore wind capacity factors, global
C34: Turbine Size, Offshore wind | E34: Turbine size, offshore wind
C35: Project size, Offshore wind | E35: Project size, Offshore wind
C36: Battery storage characteristics | E36: Battery storage project characteristics, global
C37: APAC spotlight -->
C38: Central bank base rates | E38: Central bank base rates
C39: PV module imports, India | E39: PV module imports, India
C40: Onshore wind in Vietnam | E40: Onshore wind in Vietnam
C41: Dollar exchange rate | E41: Dollar exchange rate
C42: Appendix ->
C43: Carbon Prices | E43: Carbon price forecast
C44: Coal Prices | E44: Coal price forecasts
C45: Oil Prices | E45: Brent price forecasts
C46: Gas prices | E46: Natural gas prices forecasts. 1H 2022
C47: PV Capex | E47: PV capex forecasts 2021-50, select countries
C48: PV module price | E48: PV module price
C49: Onshore wind capex | E49: Onshore wind capex
C50: Onshore wind CF | E50: Onshore wind capacity factor forecast, China
C51: Offshore wind capex | E51: Offshore wind capex forecast, global
C52: Offshore wind CF | E52: Offshore wind capacity factors, select countries
C53: Coal capex | E53: Coal-fired power plant capex
C54: Coal & gas WACC | E54: Coal and gas power WACC
... C63: Copyright and Disclaimer | E63: © Bloomberg Finance L.P. 2022. This publication is the copyright of Bloomberg Finance L.P. in connection with BloombergNEF. No portion of this document may be photocopied, reproduced, scanned into an electronic system or transmitted, forwarded or distributed in any way without prior consent of BloombergNEF. The BloombergNEF ("BNEF"), service/information is derived from selected public sources. Bloomberg Finance L.P. and its affiliates, in providing the service/information, believe that the information it uses comes from reliable sources, but do not guarantee the accuracy or completeness of this information, which is subject to change without notice, and nothing in this document shall be construed as such a guarantee. The statements in this service/document reflect the current judgment of the authors of the relevant articles or features, and do not necessarily reflect the opinion of Bloomberg Finance L.P., Bloomberg L.P. or any of their affiliates (“Bloomberg”). Bloomberg disclaims any liability arising from use of this document, its contents and/or this service. Nothing herein shall constitute or be construed as an offering of financial instruments or as investment advice or recommendations by Bloomberg of an investment or other strategy (e.g., whether or not to “buy”, “sell”, or “hold” an investment). The information available through this service is not based on consideration of a subscriber’s individual circumstances and should not be considered as information sufficient upon which to base an investment decision. You should determine on your own whether you agree with the content. This service should not be construed as tax or accounting advice or as a service designed to facilitate any subscriber’s compliance with its tax, accounting or other legal obligations. Employees involved in this service may hold positions in the companies mentioned in the services/information. The data included in these materials are for illustrative purposes only. The BLOOMBERG TERMINAL service and Bloomberg data products (the “Services”) are owned and distributed by Bloomberg Finance L.P. (“BFLP”) except (i) in Argentina, Australia and certain jurisdictions in the Pacific islands, Bermuda, China, India, Japan, Korea and New Zealand, where Bloomberg L.P. and its subsidiaries (“BLP”) distribute these products, and (ii) in Singapore and the jurisdictions serviced by Bloomberg’s Singapore office, where a subsidiary of BFLP distributes these products. BLP provides BFLP and its subsidiaries with global marketing and operational support and service. Certain features, functions, products and services are available only to sophisticated investors and only where permitted. BFLP, BLP and their affiliates do not guarantee the accuracy of prices or other information in the Services. Nothing in the Services shall constitute or be construed as an offering of financial instruments by BFLP, BLP or their affiliates, or as investment advice or recommendations by BFLP, BLP or their affiliates of an investment strategy or whether or not to “buy”, “sell” or “hold” an investment. Information available via the Services should not be considered as information sufficient upon which to base an investment decision. The following are trademarks and service marks of BFLP, a Delaware limited partnership, or its subsidiaries: BLOOMBERG, BLOOMBERG ANYWHERE, BLOOMBERG MARKETS, BLOOMBERG NEWS, BLOOMBERG PROFESSIONAL, BLOOMBERG TERMINAL and BLOOMBERG.COM. Absence of any trademark or service mark from this list does not waive Bloomberg’s intellectual property rights in that name, mark or logo. All rights reserved. © 2022 Bloomberg.

Sheet Global LCOE benchmarks
F1: Global LCOE benchmarks
A3: Dataset | B3: Global LCOE benchmarks
A4: Units | B4: $/MWh, nominal
A5: Source | B5: BloombergNEF
A6: Subject to terms and conditions
B41: LCOE
B42: $/MWh, nominal
B43: Technology | C43: 2009 | D43: 2010 | F43: 2011 | H43: 2012 | J43: 2013 | L43: 2014 | N43: 2015 | P43: 2016 | R43: 2017 | T43: 2018 | V43: 2019 | X43: 2020 | Z43: 2021 | AB43: 2022
C44: 2H | D44: 1H | E44: 2H | F44: 1H | G44: 2H | H44: 1H | I44: 2H | J44: 1H | K44: 2H | L44: 1H | M44: 2H | N44: 1H | O44: 2H | P44: 1H | Q44: 2H | R44: 1H | S44: 2H | T44: 1H | U44: 2H | V44: 1H | W44: 2H | X44: 1H | Y44: 2H | Z44: 1H | AA44: 2H | AB44: 1H
B45: Onshore wind | C45: 92.935 | D45: 85.74 | E45: 87.815 | F45: 85.795 | G45: 78.45 | H45: 78.185 | I45: 82.43 | J45: 79.72 | K45: #N/A | L45: 81.8 | M45: 81.96 | N45: 85.482938 | O45: 82.522439 | P45: 81.155008 | Q45: 68.197511 | R45: 67.500013 | S45: #N/A | T45: 55.578615 | U45: 52.298475 | V45: 50.623614 | W45: 48.20022 | X45: 46.044489 | Y45: 42.324922 | Z45: 43.044772 | AA45: 45.229307 | AB45: 45.921197
B46: Offshore wind | C46: 159.82 | D46: 176.96 | E46: 180.29 | F46: 186.685 | G46: 213.71 | H46: 226.835 | I46: 219.12 | J46: 215.415 | K46: #N/A | L46: 212 | M46: 203.08 | N46: 175.66629 | O46: 174.12551 | P46: 160.80905 | Q46: 126.20742 | R46: 123.87 | S46: #N/A | T46: 117.53773 | U46: 114.8365 | V46: 91.141152 | W46: 79.975058 | X46: 83.99342 | Y46: 86.603173 | Z46: 89.630816 | AA46: 91.607388 | AB46: 86.466617
B47: Fixed-axis PV | C47: 303.6 | D47: 303.925 | E47: 278.09 | F47: 239.825 | G47: 198.685 | H47: 176.185 | I47: 164.145 | J47: 136.2 | K47: #N/A | L47: 149 | M47: 142.86452 | N47: 128.50676 | O47: 122.03676 | P47: 99.383707 | Q47: 100.71087 | R47: 85.6 | S47: #N/A | T47: 69.652024 | U47: 60 | V47: 58.297716 | W47: 51.651356 | X47: 52.022032 | Y47: 44.453278 | Z47: 40.060758 | AA47: 44.652919 | AB47: 45.454075
B48: Tracking PV | C48: 291.46 | D48: 283.08 | E48: 241.245 | F48: 224.175 | G48: 164.74 | H48: 154.775 | I48: 133.645 | J48: 123.67 | K48: #N/A | L48: 147.92 | M48: 142.2 | N48: 138.79148 | O48: 133.03751 | P48: 106.12507 | Q48: 83.181289 | R48: 55.5 | S48: #N/A | T48: 49 | U48: 46 | V48: 51.736311 | W48: 47.183326 | X48: 40.868281 | Y48: 40.555389 | Z48: 38.697029 | AA48: 41.402367 | AB48: 40.118476
B49: Battery storage (4 hours) | T49: 288.17458 | U49: 193.25677 | V49: 190.99739 | W49: 194.44511 | X49: 157.5803 | Y49: 139.03601 | Z49: 141.18206 | AA49: 141.15952 | AB49: 153
B50: Battery storage (4 hours, implied by historic battery pack prices) | I50: 720.89288 | J50: 706.11527 | K50: 691.33765 | L50: 607.04555 | M50: 522.75345 | N50: 531.39315 | O50: 540.03285 | P50: 501.62833 | Q50: 463.22381 | R50: 383.39901 | S50: 303.57422 | T50: 288.17458
B51: Coal | L51: 84.705638 | M51: 77.019444 | N51: 77.114352 | O51: 86.593863 | P51: 70.672659 | Q51: 69.374037 | R51: 71.32419 | S51: 69.195069 | T51: 60.460641 | U51: 62.309705 | V51: 69.724707 | W51: 69.924135 | X51: 75.055211 | Y51: 76.600519 | Z51: 67.477761 | AA51: 67.792696 | AB51: 73.718419
B52: Gas | L52: 68.560469 | M52: 48.452659 | N52: 42.503103 | O52: 47.973337 | P52: 46.289953 | Q52: 51.586443 | R52: 50.504901 | S52: 53.015845 | T52: 56.834729 | U52: 58.463014 | V52: 60.782486 | W52: 61.13457 | X52: 65.457232 | Y52: 64.732833 | Z52: 74.020084 | AA52: 77.28105 | AB52: 80.935848
B53: The global benchmark is a country weighted-average using the latest annual capacity additions. The storage LCOE is reflective of a utility-scale Li-ion battery storage system with four-hour duration running at a daily cycle and includes charging costs assumed to be 60% of wholesale average power price.
B54: All LCOEs calculations are unsubsidized. In 2H 2017, BNEF did not publish any update. Dashed pink lines reflects derived LCOEs based on historic battery pack prices. Continuous pink line reflects collected project data from 2018.
B55: For hydrogen-fired power, coal- and gas-fired power with carbon capture and storage (CCS), the global LCOE benchmark is a simple country average including China, Europe, U.S., Japan and India

Sheet Key messages -->
F1: Key messages

Sheet Global LCOEs by tech
F1: Global LCOEs by technology
A3: Dataset | B3: Global LCOEs by technology
A4: Units | B4: $/MWh (nominal)
A5: Source | B5: BNEF LCOE analysis
A6: Subject to terms and conditions
B28: Global LCOEs
B29: $/MWh (nominal at COD)
B30: Technology | D30: Wind onshore | F30: Wind offshore | H30: PV fixed-axis | J30: PV tracking | L30: Utility-scale battery (4h) | N30: CCGT | P30: Coal
B31: Metric | C31: LCOE Scenario | D31: 2021 | E31: 2022 | F31: =D31 -> 2021 | G31: =E31 -> 2022 | H31: =F31 -> 2021 | I31: =G31 -> 2022 | J31: =H31 -> 2021 | K31: =I31 -> 2022 | L31: =J31 -> 2021 | M31: =K31 -> 2022 | ... Q31: =O31 -> 2022
B32: Min | C32: Low | D32: 17.593589 | E32: 18.922491 | F32: 53.329309 | G32: 57.154351 | H32: 22.41187 | I32: 25.299621 | J32: 22.696487 | K32: 21.282783 | L32: 119.89393 | M32: 108.36698 | N32: 33.699347 | O32: 43.466924 | P32: 40.759872 | Q32: 40.378554
B33: Simple average | C33: Low | D33: 47.306838 | E33: 49.041682 | F33: 81.210233 | G33: 86.345804 | H33: 57.901679 | I33: 57.106946 | J33: 35.041232 | K33: 36.118683 | L33: 135.85286 | M33: 144.36641 | N33: 70.532537 | O33: 84.339597 | P33: 83.901587 | Q33: 107.45067
B34: Median | C34: Low | D34: 39.585223 | E34: 40.902154 | F34: 76.723956 | G34: 77.612333 | H34: 51.532683 | I34: 48.774367 | J34: 32.034375 | K34: 34.256131 | L34: 133.97924 | M34: 124.59196 | N34: 72.712819 | O34: 83.847824 | P34: 62.446955 | Q34: 72.014091
B35: Max | C35: Low | D35: 93.204692 | E35: 102.06594 | F35: 139.68705 | G35: 142.12143 | H35: 129.35469 | I35: 141.15859 | J35: 46.025423 | K35: 46.404411 | L35: 154.79473 | M35: 283.62186 | N35: 102.84608 | O35: 134.94218 | P35: 185.09707 | Q35: 288.00888
B36: Min | C36: Mid | D36: 22.584514 | E36: 26.958404 | F36: 72.248758 | G36: 72.763221 | H36: 26.967734 | I36: 33.39796 | J36: 34.794014 | K36: 31.220805 | L36: 124.97653 | M36: 114.60423 | N36: 39.788132 | O36: 51.943866 | P36: 58.431315 | Q36: 58.511562
B37: Simple average | C37: Mid | D37: 63.439389 | E37: 67.873123 | F37: 102.05275 | G37: 106.06245 | H37: 77.227838 | I37: 75.541265 | J37: 44.035811 | K37: 45.688068 | L37: 147.43981 | M37: 164.56094 | N37: 78.844632 | O37: 93.205792 | P37: 96.485302 | Q37: 121.5687
B38: Median | C38: Mid | D38: 52.994482 | E38: 55.283492 | F38: 96.345351 | G38: 93.037533 | H38: 69.430475 | I38: 65.37159 | J38: 43.136494 | K38: 44.849185 | L38: 147.68108 | M38: 139.83523 | N38: 83.11176 | O38: 90.571553 | P38: 74.304999 | Q38: 86.532603
B39: Max | C39: Mid | D39: 131.33515 | E39: 135.57757 | F39: 185.12159 | G39: 178.80894 | H39: 163.91466 | I39: 169.34483 | J39: 58.223872 | K39: 62.796677 | L39: 168.81713 | M39: 344.23484 | N39: 109.06836 | O39: 140.83799 | P39: 196.64769 | Q39: 294.9857
B40: Min | C40: High | D40: 32.836234 | E40: 40.057177 | F40: 79.432097 | G40: 76.518422 | H40: 37.314825 | I40: 46.642706 | J40: 38.290833 | K40: 42.594219 | L40: 129.44149 | M40: 135.69561 | N40: 56.102944 | O40: 74.490674 | P40: 70.682451 | Q40: 71.059256
B41: Simple average | C41: High | D41: 87.502403 | E41: 95.369567 | F41: 123.19217 | G41: 128.07264 | H41: 103.03873 | I41: 99.782823 | J41: 55.505969 | K41: 57.474429 | L41: 165.52231 | M41: 222.1413 | N41: 90.817847 | O41: 109.17748 | P41: 122.48334 | Q41: 149.63248
B42: Median | C42: High | D42: 70.721285 | E42: 72.44604 | F42: 111.46328 | G42: 110.39099 | H42: 99.666898 | I42: 96.6114 | J42: 54.288122 | K42: 53.294717 | L42: 163.02868 | M42: 162.21479 | N42: 94.859066 | O42: 104.35774 | P42: 99.789515 | Q42: 122.03913
B43: Max | C43: High | D43: 200.30183 | E43: 205.17723 | F43: 237.4241 | G43: 220.96386 | H43: 218.05711 | I43: 221.98864 | J43: 75.343357 | K43: 83.333923 | L43: 216.91337 | M43: 632.55055 | N43: 119.7984 | O43: 160.24977 | P43: 215.10723 | Q43: 303.23103
B44: Global weighted average | D44: 43.044772 | E44: 45.921197 | F44: 89.630816 | G44: 86.466617 | H44: 40.060758 | I44: 45.454075 | J44: 38.697029 | K44: 40.118476 | L44: 141.18206 | M44: 153 | N44: 74.020084 | O44: 80.935848 | P44: 67.477761 | Q44: 73.718419
B47: For charting purposes
D48: Onshore wind | F48: Offshore wind | H48: Fixed-axis PV | J48: Tracking PV | L48: Battery storage | N48: Gas | P48: Coal
D49: 2021 | E49: 2022 | F49: 2021 | G49: 2022 | H49: =F49 -> 2021 | I49: =G49 -> 2022 | J49: =H49 -> 2021 | K49: =I49 -> 2022 | L49: 2021 | M49: =K49 -> 2022 | N49: =L49 -> 2021 | O49: =M49 -> 2022 | P49: =N49 -> 2021 | Q49: =O49 -> 2022
B50: Low | D50: 17.593589 | E50: 18.922491 | F50: 53.329309 | G50: 57.154351 | H50: 22.41187 | I50: 25.299621 | J50: 22.696487 | K50: 22.696487 | L50: 119.89393 | M50: 108.36698 | N50: 33.699347 | O50: 43.466924 | P50: 40.759872 | Q50: 40.378554
B51: Low - Min Mid | D51: 4.9909252 | E51: 8.035913 | F51: 18.919449 | G51: 15.60887 | H51: 4.5558636 | I51: 8.0983383 | J51: 12.097527 | K51: 12.097527 | L51: 5.0826075 | M51: 6.2372532 | N51: 6.0887847 | O51: 8.4769419 | P51: 17.671444 | Q51: 18.133008
B52: Min Mid - Max Mid | D52: 108.75063 | E52: 108.61917 | F52: 112.87283 | G52: 106.04572 | H52: 136.94693 | I52: 135.94687 | J52: 23.429858 | K52: 23.429858 | L52: 43.840593 | M52: 229.6306 | N52: 69.280226 | O52: 88.894125 | P52: 138.21638 | Q52: 236.47413
B53: Max Mid - Max High | D53: 68.966683 | E53: 69.599652 | F53: 52.302518 | G53: 42.154924 | H53: 54.142441 | I53: 52.643819 | J53: 17.119485 | K53: 17.119485 | L53: 48.096247 | M53: 288.31572 | N53: 10.730046 | O53: 19.411778 | P53: 18.45954 | Q53: 8.2453299
B54: Global weighted average | D54: 43.044772 | E54: 45.921197 | F54: 89.630816 | G54: 86.466617 | H54: 40.060758 | I54: 45.454075 | J54: 38.697029 | K54: 40.118476 | L54: 141.18206 | M54: 153 | N54: 74.020084 | O54: 80.935848 | P54: 67.477761 | Q54: 73.718419
B55: Median mid | D55: 52.994482 | E55: 55.283492 | F55: 96.345351 | G55: 93.037533 | H55: 69.430475 | I55: 65.37159 | J55: 43.136494 | K55: 43.136494 | L55: 147.68108 | M55: 139.83523 | N55: 83.11176 | O55: 90.571553 | P55: 74.304999 | Q55: 86.532603
B56: Label top | D56: 50 | E56: 50 | F56: 50 | G56: 50 | H56: 50 | I56: 50 | J56: 50 | K56: 50 | L56: 50 | M56: 50 | N56: 50 | O56: 50 | P56: 50 | Q56: 50

Sheet Turbine prices
F1: Regional turbine prices (signing date-USD)
A3: Dataset | B3: Regional onshore wind turbine prices by signing date (USD)
A4: Units | B4: $m/MW (nominal)
A5: Source | B5: BloombergNEF
A6: Subject to terms and conditions
B29: Regional pricing by signing date
B30: $m/MW (nominal) | C30: 2008 | E30: 2009 | G30: 2010 | I30: 2011 | K30: 2012 | M30: 2013 | O30: 2014 | Q30: 2015 | S30: 2016 | U30: 2017 | W30: 2018 | Y30: 2019 | AA30: 2020 | AC30: 2021
C31: 1H | D31: 2H | E31: 1H | F31: 2H | G31: 1H | H31: 2H | I31: 1H | J31: 2H | K31: 1H | L31: 2H | M31: 1H | N31: 2H | O31: 1H | P31: 2H | Q31: 1H | R31: 2H | S31: 1H | T31: 2H | U31: 1H | V31: 2H | W31: 1H | X31: 2H | Y31: 1H | Z31: 2H | AA31: 1H | AB31: 2H | AC31: 1H | AD31: 2H
B32: AMER | C32: 1.9498981 | D32: 1.9346063 | E32: #N/A | F32: 1.3894109 | G32: 1.4099183 | H32: 1.2178937 | I32: 1.34274 | J32: 1.0813504 | K32: 1.0629152 | L32: 1.1412846 | M32: 1.1142587 | N32: 1.0624285 | O32: 1.378459 | P32: 1.2553159 | Q32: 1.0257398 | R32: 1.0953395 | S32: 1.0509426 | T32: 0.88670301 | U32: 0.78273962 | V32: 1.021752 | W32: 0.73869956 | X32: 0.66167737 | Y32: 0.7623967 | Z32: 0.67855264 | AA32: 0.61926064 | AB32: 0.63386288 | AC32: 0.6292304 | AD32: 0.77048914
B33: EMEA | C33: 1.7459447 | D33: 1.6707643 | E33: 1.5273692 | F33: 1.5182688 | G33: 1.385131 | H33: 1.2967784 | I33: 1.3285733 | J33: 1.3155268 | K33: 1.1563285 | L33: 1.201144 | M33: 1.1051631 | N33: 1.1569821 | O33: 1.1738606 | P33: 1.1251409 | Q33: 0.96460524 | R33: 0.87643068 | S33: 0.88077838 | T33: 0.9114014 | U33: 0.91225546 | V33: 0.79636404 | W33: 0.78887567 | X33: 0.79016106 | Y33: 0.76294586 | Z33: 0.74329817 | AA33: 0.80786727 | AB33: 0.88351499 | AC33: 0.90216994 | AD33: 1.047693
B34: China | C34: 1.1583478 | D34: 1.1583478 | E34: 0.96110997 | F34: 0.96110997 | G34: 0.88950114 | H34: 0.78549217 | I34: 0.7369429 | J34: 0.74477439 | K34: 0.78550876 | L34: 0.79032414 | M34: 0.8086732 | N34: 0.84513146 | O34: 0.85520518 | P34: 0.83076488 | Q34: 0.8466611 | R34: 0.83819449 | S34: 0.78069037 | T34: 0.78069037 | U34: 0.73083374 | V34: 0.70272475 | W34: 0.64045345 | X34: 0.65001246 | Y34: 0.6329407 | Z34: 0.66684311 | AA34: 0.69877905 | AB34: 0.61022024 | AC34: 0.52187291 | AD34: 0.47051332
B35: Global average | C35: 1.7544428 | D35: 1.6800254 | E35: 1.5211911 | F35: 1.4683883 | G35: 1.3335079 | H35: 1.2633795 | I35: 1.3629074 | J35: 1.2407897 | K35: 1.1190139 | L35: 1.1860689 | M35: 1.1078382 | N35: 1.107454 | O35: 1.2633724 | P35: 1.1685326 | Q35: 0.99517251 | R35: 0.99430467 | S35: 0.92331944 | T35: 0.90570177 | U35: 0.81667063 | V35: 0.89376207 | W35: 0.77940623 | X35: 0.74651455 | Y35: 0.76278896 | Z35: 0.7187478 | AA35: 0.78271972 | AB35: 0.8169411 | AC35: 0.85162558 | AD35: 0.93355025

Sheet Commodity & Labor prices
F1: Commodity, labor and freight prices
A3: Dataset | B3: Commodity, labor and freight price index, 2019-2022
A4: Units | B4: January 2019 = 100%
A5: Source | B5: Bloomberg Terminal, Third Party Data Providers
A6: Subject to terms and conditions
B39: Commodity, labor and freight price indexes (100% = January 2019)
D40: Date | E40: Copper | F40: Cobalt | G40: Lithium | H40: Nickel | I40: Zinc | J40: Chromium | K40: Molybdene | L40: Aluminum | M40: Steel | N40: Cement | O40: Coal | P40: Natural gas | Q40: Freight from Asia | R40: Oil | S40: Labor (US)
B41: 2019 | C41: J | D41: 43480 | E41: 1 | F41: 1 | G41: 1 | H41: 1 | I41: 1 | J41: 1 | K41: 1 | L41: 1 | M41: 1 | N41: 1 | O41: 1 | P41: 1 | Q41: 1 | R41: 1 | S41: 1
D42: 43511 | E42: 1.123877 | F42: 0.78860972 | G42: 1.0031579 | H42: 1.1017049 | I42: 1.0583304 | J42: 1.0222698 | K42: 1.0186154 | L42: 1.0111459 | M42: 1.015873 | N42: 0.99762564 | O42: 0.96967375 | P42: 0.83492418 | Q42: 0.88845406 | R42: 1.0695639 | S42: 1
C43: M | D43: 43539 | E43: 1.226528 | F43: 0.7697748 | G43: 0.99157895 | H43: 1.1321233 | I43: 1.1041615 | J43: 1.0204752 | K43: 1.0393894 | L43: 1.0148383 | M43: 1.0335097 | N43: 0.99406411 | O43: 0.9565719 | P43: 0.7250822 | Q43: 0.76478412 | R43: 1.1126595 | S43: 1.043106
D44: 43570 | E44: 1.3030545 | F44: 0.82300391 | G44: 0.96842105 | H44: 1.1095907 | I44: 1.1162381 | J44: 1.0167024 | K44: 1.0389128 | L44: 0.9987087 | M44: 1.0186949 | N44: 1.0114761 | O44: 0.83997483 | P44: 0.6942386 | Q44: 0.68127174 | R44: 1.1890354 | S44: 1.043106
C45: M | D45: 43600 | E45: 1.1610136 | F45: 0.8393821 | G45: 0.95368421 | H45: 1.0393195 | I45: 1.024875 | J45: 0.98255674 | K45: 1.0118998 | L45: 0.96911615 | M45: 0.89770723 | N45: 1.0213692 | O45: 0.8580298 | P45: 0.60722465 | Q45: 0.75025578 | R45: 1.1670316 | S45: 1.043106
D46: 43631 | E46: 1.1737255 | F46: 0.70775879 | G46: 0.93684211 | H46: 1.0371725 | I46: 0.97497168 | J46: 0.82932041 | K46: 0.99347955 | L46: 0.9547435 | M46: 0.7989418 | N46: 1.0197863 | O46: 0.7252237 | P46: 0.48603409 | Q46: 0.75864539 | R46: 1.0464318 | S46: 1.043106
C47: J | D47: 43661 | E47: 1.2153748 | F47: 0.67167747 | G47: 0.84421053 | H47: 1.1740052 | I47: 0.95698245 | J47: 0.76734754 | K47: 0.99643845 | L47: 0.97429827 | M47: 0.8042328 | N47: 1.0110803 | O47: 0.74217888 | P47: 0.50154177 | Q47: 0.69431655 | R47: 1.0659664 | S47: 1.043106
D48: 43692 | E48: 1.1530806 | F48: 0.74037361 | G48: 0.75157895 | H48: 1.3574652 | I48: 0.89395181 | J48: 0.7490364 | K48: 0.99581357 | L48: 0.94795084 | M48: 0.86243386 | N48: 1.0106846 | O48: 0.67432203 | P48: 0.45764015 | Q48: 0.82259055 | R48: 0.98773108 | S48: 1.043106
C49: S | D49: 43723 | E49: 1.1957461 | F49: 0.8775538 | G49: 0.71578947 | H49: 1.515646 | I49: 0.91032305 | J49: 0.73787895 | K49: 0.98815205 | L49: 0.95268116 | M49: 0.81128748 | N49: 1.0110803 | O49: 0.66518738 | P49: 0.43181446 | Q49: 0.71196542 | R49: 1.0339675 | S49: 1.043106
D50: 43753 | E50: 1.1992344 | F50: 0.86631816 | G50: 0.69894737 | H50: 1.4643959 | I50: 0.94860426 | J50: 0.73192832 | K50: 0.98894734 | L50: 0.92841922 | M50: 0.73015873 | N50: 1.0106846 | O50: 0.67531936 | P50: 0.46276848 | Q50: 0.64927358 | R50: 0.98989499 | S50: 1.043106
C51: N | D51: 43784 | E51: 1.2157648 | F51: 0.87238824 | G51: 0.66947368 | H51: 1.3111167 | I51: 0.93803828 | J51: 0.72570613 | K51: 0.94986169 | L51: 0.94653557 | M51: 0.75132275 | N51: 1.0094974 | O51: 0.67809454 | P51: 0.66086764 | Q51: 0.82796194 | R51: 1.040979 | S51: 1.043106
D52: 43814 | E52: 1.2321495 | F52: 0.82416993 | G52: 0.63157895 | H52: 1.1990151 | I52: 0.89000384 | J52: 0.71948608 | K52: 0.94910344 | L52: 0.95419461 | M52: 0.80987654 | N52: 1.0091017 | O52: 0.67201351 | P52: 0.59969982 | Q52: 0.94604732 | R52: 1.0818862 | S52: 1.043106
B53: 2020 | C53: J | D53: 43845 | E53: 1.3073843 | F53: 0.79138638 | G53: 0.59789474 | H53: 1.1728272 | I53: 0.91857323 | J53: 0.70255532 | K53: 0.96406096 | L53: 0.96006816 | M53: 0.86772487 | N53: 1.0059359 | O53: 0.6970128 | P53: 0.50444537 | Q53: 1.1314713 | R53: 1.0569682 | S53: 1.043106
D54: 43876 | E54: 1.2423566 | F54: 0.82403758 | G54: #VALUE! | H54: 1.1047911 | I54: 0.83315583 | J54: 0.69321199 | K54: 0.95362824 | L54: 0.91741861 | M54: 0.86772487 | N54: 1.0053423 | O54: 0.69049695 | P54: 0.41791808 | Q54: 1.0043227 | R54: 0.92092734 | S54: 1.043106
C55: M | D55: 43905 | E55: 1.1938166 | F55: 0.76451033 | G55: 0.57263158 | H55: 1.0283579 | I55: 0.75245511 | J55: 0.6875803 | K55: 0.92691415 | L55: 0.87477636 | M55: 0.87195767 | N55: 1.0047487 | O55: 0.66854036 | P55: 0.38873485 | Q55: 0.88615204 | R55: 0.55990342 | S55: 1.0818251
D56: 43936 | E56: 1.1726584 | F56: 0.72633166 | G56: 0.54947368 | H56: 1.0247071 | I56: 0.75102352 | J56: 0.67922912 | K56: 0.87318218 | L56: 0.80169537 | M56: 0.76190476 | N56: 1.0178077 | O56: 0.61384717 | P56: 0.28769364 | Q56: 0.76253325 | R56: 0.44208212 | S56: 1.0818251
C57: M | D57: 43966 | E57: 1.198862 | F57: 0.7262725 | G57: 0.52631579 | H57: 1.057194 | I57: 0.7751005 | J57: 0.67192606 | K57: 0.86863021 | L57: 0.80237391 | M57: 0.68289242 | N57: 1.0138504 | O57: 0.5215021 | P57: 0.20213967 | Q57: 0.81811439 | R57: 0.53803811 | S57: 1.0818251
D58: 43997 | E58: 1.2435698 | F58: 0.7142775 | G58: 0.50947368 | H58: 1.1040377 | I58: 0.79750787 | J58: 0.65728561 | K58: 0.87170767 | L58: 0.85178604 | M58: 0.73368607 | N58: 1.0225564 | O58: 0.54237599 | P58: 0.22994062 | Q58: 0.88640782 | R58: 0.67682789 | S58: 1.0818251
C59: J | D59: 44027 | E59: 1.4426973 | F59: 0.70058568 | G59: 0.49263158 | H59: 1.1609062 | I59: 0.85815049 | J59: 0.6169258 | K59: 0.88099437 | L59: 0.89824452 | M59: 0.68994709 | N59: 1.0277008 | O59: 0.52726544 | P59: 0.22738463 | Q59: 0.93083691 | R59: 0.71748874 | S59: 1.0818251
D60: 44058 | E60: 1.4923125 | F60: 0.80849447 | G60: 0.50105263 | H60: 1.2588472 | I60: 0.9533765 | J60: 0.60972775 | K60: 0.90397649 | L60: 0.95027201 | M60: 0.68606702 | N60: 1.0273051 | O60: 0.50953233 | P60: 0.36626671 | Q60: 0.95316656 | R60: 0.74733268 | S60: 1.0818251
C61: S | D61: 44089 | E61: 1.4936167 | F61: 0.82256421 | G61: 0.50105263 | H61: 1.2863096 | I61: 0.96693515 | J61: 0.60513919 | K61: 0.9243282 | L61: 0.95388547 | M61: 0.75485009 | N61: 1.0280966 | O61: 0.52503097 | P61: 0.53947261 | Q61: 1.1341314 | R61: 0.695103 | S61: 1.0818251
D62: 44119 | E62: 1.5485082 | F62: 0.81631854 | G62: 0.50526316 | H62: 1.3189523 | I62: 0.96382222 | J62: 0.60519628 | K62: 0.93939192 | L62: 0.97601168 | M62: 0.92416226 | N62: 1.0277008 | O62: 0.58014041 | P62: 0.67374573 | Q62: 1.1285042 | R62: 0.68930054 | S62: 1.0818251
C63: N | D63: 44150 | E63: 1.6196411 | F63: 0.79202164 | G63: 0.51368421 | H63: 1.3683381 | I63: 1.053506 | J63: 0.60770878 | K63: 0.95320589 | L63: 1.0435262 | M63: 1.021164 | N63: 1.0269094 | O63: 0.63319589 | P63: 0.66818799 | Q63: 1.424954 | R63: 0.73006866 | S63: 1.0818251
D64: 44180 | E64: 1.6728243 | F64: 0.78326107 | G64: 0.56421053 | H64: 1.4571216 | I64: 1.1010125 | J64: 0.61917884 | K64: 0.96289765 | L64: 1.0852703 | M64: 1.2380952 | N64: 1.0273051 | O64: 0.78993255 | P64: 0.81098788 | Q64: 2.9480254 | R64: 0.83362258 | S64: 1.0818251
B65: 2021 | C65: J | D65: 44211 | E65: 1.8463988 | F65: 0.93070134 | G65: 0.79578947 | H65: 1.5461982 | I65: 1.0710167 | J65: 0.64704497 | K65: 0.98583284 | L65: 1.0737333 | M65: 1.4998236 | N65: 1.0306688 | O65: 0.85719038 | P65: 1.01963 | Q65: 4.5404901 | R65: 0.91833773 | S65: 1.0818251
D66: 44242 | E66: 1.875815 | F66: 1.16735 | G66: 0.94736842 | H66: 1.6079596 | I66: 1.0841249 | J66: 0.66329764 | K66: 1.0115936 | L66: 1.1164133 | M66: 1.6666667 | N66: 1.0340324 | O66: 0.86887533 | P66: 0.86188268 | Q66: 4.3595253 | R66: 1.0338738 | S66: 1.0818251
C67: M | D67: 44270 | E67: 1.7123762 | F67: 1.287686 | G67: 1.0821053 | H67: 1.4202349 | I67: 1.1025685 | J67: 0.68779443 | K67: 1.0579604 | L67: 1.1841475 | M67: 1.8077601 | N67: 1.0472893 | O67: 0.91769994 | P67: 0.8650153 | Q67: 4.02522 | R67: 1.0906571 | S67: 1.1492812
D68: 44301 | E68: 1.6969876 | F68: 1.2043053 | G68: 1.1536842 | H68: 1.4297669 | I68: 1.1176608 | J68: 0.71156316 | K68: 1.0418396 | L68: 1.2471174 | M68: 1.9611993 | N68: 1.0605461 | O68: 0.94784695 | P68: 1.0210777 | Q68: 3.9615306 | R68: 1.0844553 | S68: 1.1492812
C69: M | D69: 44331 | E69: 1.7518954 | F69: 1.0870143 | G69: 1.1768421 | H69: 1.5199748 | I69: 1.1701127 | J69: 0.77135129 | K69: 1.0946626 | L69: 1.3142771 | M69: 2.1287478 | N69: 1.0613376 | O69: 1.013897 | P69: 1.2537992 | Q69: 4.7813076 | R69: 1.1339312 | S69: 1.1492812
D70: 44362 | E70: 1.7655885 | F70: 1.0846298 | G70: 1.1494737 | H70: 1.5539023 | I70: 1.1647623 | J70: 0.79906189 | K70: 1.1991553 | L70: 1.3150368 | M70: 2.3236332 | N70: 1.062129 | O70: 1.2649704 | P70: 1.438824 | Q70: 5.6469971 | R70: 1.2185769 | S70: 1.1492812
C71: J | D71: 44392 | E71: 1.7000464 | F71: 1.268876 | G71: 1.1557895 | H71: 1.62505 | I71: 1.1625949 | J71: 0.85738758 | K71: 1.2813426 | L71: 1.3440516 | M71: 2.5283951 | N71: 1.0676553 | O71: 1.4728124 | P71: 1.7505153 | Q71: 6.58584 | R71: 1.2332755 | S71: 1.1492812
D72: 44423 | E72: 1.6502692 | F72: 1.2686667 | G72: 1.3431579 | H72: 1.652562 | I72: 1.1758511 | J72: 0.85995717 | K72: 1.3807177 | L72: 1.3896428 | M72: 2.6358025 | N72: 1.0731816 | O72: 1.6878126 | P72: 2.1382523 | Q72: 7.0040413 | R72: 1.1705274 | S72: 1.1492812
C73: S | D73: 44454 | E73: 1.6529787 | F73: 1.2725338 | G73: 2.0884211 | H73: 1.670775 | I73: 1.196516 | J73: 0.8878964 | K73: 1.4153774 | L73: 1.5260026 | M73: 2.7619048 | N73: 1.0751642 | O73: 1.8586473 | P73: 3.0826872 | Q73: 7.3223859 | R73: 1.2429488 | S73: 1.1492812
D74: 44484 | E74: 1.6736625 | F74: 1.3457781 | G74: 2.5284211 | H74: 1.6665385 | I74: 1.3099326 | J74: 0.98866523 | K74: 1.4246839 | L74: 1.5803218 | M74: 2.7400353 | N74: 1.0762841 | O74: 2.376792 | P74: 4.1566063 | Q74: 7.4213475 | R74: 1.390188 | S74: 1.1492812
C75: N | D75: 44515 | E75: 1.661631 | F75: 1.4841709 | G75: 2.6442105 | H75: 1.7097587 | I75: 1.2801459 | J75: 1.0252677 | K75: 1.3483748 | L75: 1.4135337 | M75: 2.6137566 | N75: 1.0762841 | O75: 1.5519662 | P75: 3.8152656 | Q75: 6.9666974 | R75: 1.3421037 | S75: 1.1492812
D76: 44545 | E76: 1.6948998 | F76: 1.7036719 | G76: 3.3052632 | H76: 1.7185803 | I76: 1.3174828 | J76: 0.98273904 | K76: 1.2889054 | L76: 1.4434103 | M76: 2.3816578 | N76: 1.0762841 | O76: 1.66181 | P76: 5.2872111 | Q76: 6.9463628 | R76: 1.2417461 | S76: 1.1492812
B77: 2022 | C77: J | D77: 44576 | E77: 1.6383247 | F77: 1.7326578 | G77: 4.6084211 | H77: 1.9057559 | I77: 1.4028427 | J77: 0.94962245 | K77: 1.3737404 | L77: 1.6078488 | M77: 2.0987654 | N77: 1.0762841 | O77: 2.116077 | P77: 3.8997522 | Q77: 7.0884489 | R77: 1.4205028 | S77: 1.1492812
D78: 44607 | E78: 1.584364 | F78: 1.7583687 | G78: 5.9515789 | H78: 2.0368495 | I78: 1.4167554 | J78: 0.94866167 | K78: 1.4244171 | L78: 1.7220593 | M78: 1.6014109 | N78: 1.0762841 | O78: 2.3848139 | P78: 3.7534843 | Q78: 6.9812769 | R78: 1.5620863 | S78: 1.1492812
C79: M | D79: 44635 | E79: 1.4715253 | F79: 1.9766204 | G79: 6.6989474 | H79: 2.9122039 | I79: 1.552474 | J79: 1.0818732 | K79: 1.4567353 | L79: 1.8794462 | M79: 1.6984127 | N79: 1.0762841 | O79: 3.4853154 | P79: 5.8349487 | Q79: 6.1556169 | R79: 1.8668882 | S79: 1.2363185
D80: 44666 | E80: 1.3837461 | F80: 2.0093424 | G80: 6.1178947 | H80: 2.8622649 | I80: 1.6912288 | J80: 1.1369022 | K80: 1.4913975 | L80: 1.7475875 | M80: 2.0557319 | N80: 1.0762841 | O80: 3.0952232 | P80: 4.4856292 | Q80: 5.3694751 | R80: 1.7582238 | S80: 1.2363185
C81: M | D81: 44696 | E81: 1.2957071 | F81: 1.9046943 | G81: 5.8421053 | H81: 2.4287045 | I81: 1.4668704 | J81: 1.0976445 | K81: 1.3865195 | L81: 1.5303921 | M81: 2.047619 | N81: 1.0762841 | O81: 3.9411967 | P81: 3.8767851 | Q81: 5.0331236 | R81: 1.8585301 | S81: 1.2363185
D82: 44727 | E82: 1.393635 | F82: 1.7688429 | G82: #N/A | H82: 2.2344756 | I82: 1.4100304 | J82: 1.0557173 | K82: 1.3744838 | L82: 1.3886845 | M82: 1.6578483 | N82: 1.0762841 | O82: 3.9898591 | P82: 4.6096457 | Q82: 4.9270514 | R82: 1.9510601 | S82: 1.2363185
B83: Source: Bloomberg. Note: Bloomberg tickers are as follows: Chromium (C9CNRLJI AMTL Index), Zinc (LMZSDS03 Comdty), Molybdenum (MBCNLUFJ SMET Index), Aluminum (LMAHDS03 Comdty), Steel (STANHCXW KLSH Index), Cobalt (LMCODY LME Comdty), Copper (SHSZ300 Index),
B84: Nickel (LMNIDS03 Comdty), Freight from Asia (WCIDSHRO Index), US hourly compensation (COMPNFRY Index), Natural gas is TTF (TTFGDAHD OECM Index). Coal is ARA (XW1 Comdty). Oil is Brent (CO1 Comdty).

Sheet Global wind LCOE benchmarks
F1: Global wind LCOE benchmarks
A3: Dataset | B3: Global onshore and offshore wind LCOE benchmarks with and without China, 1H 2021-2022
A4: Units | B4: $/MWh (nominal)
A5: Source | B5: BloombergNEF
A6: Subject to terms and conditions
B9: Onshore wind | E9: Offshore wind
B35: LCOE
B36: $/MWh (nominal)
B37: Type | C37: 1H 2021 | D37: 1H 2022
B38: ex. China | C38: 42.263863 | D38: 49.369979
B39: incl. China | C39: 43.044772 | D39: 45.921197
B40: ex. China | C40: 89.163562 | D40: 94.384056
B41: incl. China | C41: 89.630816 | D41: 86.466617
B42: All LCOEs calculations are unsubsidized.
B43: The global benchmark is a country weighted-average using the latest annual capacity additions.
B44: The storage LCOE is reflective of a utility-scale Li-ion battery storage system with four-hour duration running at a daily cycle and includes charging costs assumed to be 60% of wholesale average power price.

Sheet PV cost inflation
E1: PV cost inflation
A3: Dataset | B3: PV cost inflation
A4: Units | B4: %
A5: Source | B5: BloombergNEF
A6: Subject to terms and conditions
B28: Year-on-year USD nominal cost change, fixed-axis PV
B29: %
B30: Short name | C30: Long name | D30: LCOE | E30: Capex
B31: Chile | C31: Chile | D31: -0.16569364 | E31: -0.097331862
B32: Japan | C32: Japan | D32: -0.12774826 | E32: -0.034782609
B33: Mex. | C33: Mexico | D33: -0.086659478 | E33: -0.1
B34: Canada | C34: Canada | D34: -0.0021564253 | E34: -0.0058059197
B35: South Korea | C35: South Korea | D35: 0.040605705 | E35: 0.082646712
B36: South Africa | C36: South Africa | D36: 0.046330553 | E36: 0.062973918
B37: Thai. | C37: Thailand | D37: 0.058780191 | E37: 0.074603659
B38: UK | C38: UK | D38: 0.059134817 | E38: 0.076485107
B39: France | C39: France | D39: 0.093900993 | E39: 0.12985557
B40: Austr. | C40: Australia | D40: 0.097139024 | E40: 0.11746657
B41: Ger. | C41: Germany | D41: 0.098973377 | E41: 0.12985557
B42: Italy | C42: Italy | D42: 0.10481379 | E42: 0.12985557
... B47: India | C47: India | D47: 0.2471736 | E47: 0.2894103
B48: Global | C48: Global | D48: 0.135

Sheet Onshore wind cost inflation
E1: Onshore wind cost inflation
A3: Dataset | B3: Onshore wind cost inflation
A4: Units | B4: %
A5: Source | B5: BloombergNEF
A6: Subject to terms and conditions
B28: Year-on-year USD nominal cost change, onshore wind
B29: %
B30: Short name | C30: Long name | D30: LCOE | E30: Capex
B31: China | C31: China | D31: -0.04540514 | E31: -0.13
B32: Chile | C32: Chile | D32: 0.038350563 | E32: 0
B33: Thai. | C33: Thailand | D33: 0.075803788 | E33: 0.04
B34: India | C34: India | D34: 0.08241019 | E34: 0.046882795
B35: Italy | C35: Italy | D35: 0.082631095 | E35: 0.12985557
B36: South Korea | C36: South Korea | D36: 0.10462775 | E36: 0.11
B37: Mexico | C37: Mexico | D37: 0.10654498 | E37: 0.06
B38: Ger. | C38: Germany | D38: 0.1147974 | E38: 0.12985557
B39: France | C39: France | D39: 0.12302557 | E39: 0.12985557
B40: US | C40: US | D40: 0.14073003 | E40: 0.12
B41: Canada | C41: Canada | D41: 0.14341743 | E41: 0.12
B42: UK | C42: UK | D42: 0.15178713 | E42: 0.12
... B47: Japan | C47: Japan | D47: 0.27508791 | E47: 0.18
B48: Global | C48: Global | D48: 0.067

Sheet Battery costs
F1: Battery costs
A3: Dataset | B3: Energy storage project costs 2021, based on usable capacity
A4: Units | B4: $/kWh, based on usable capacity
A5: Source | B5: BloombergNEF
A6: Subject to terms and conditions
B37: 4-hour duration battery nergy storage project costs 2021 vs 2022
B38: $/kWh
C39: 2021 survey | D39: 44256 | E39: 44287 | F39: 44317 | G39: 44348 | H39: 44378 | I39: 44409 | J39: 44440 | K39: 44470 | L39: 44501 | M39: 44531 | N39: 44562 | O39: 44593 | P39: 44621 | Q39: 44652 | R39: 44682 | S39: 44713
B40: Cell | C40: 103 | D40: 82.221384 | E40: 83.156897 | F40: 83.46201 | G40: 83.407392 | H40: 83.643658 | I40: 86.048677 | J40: 91.715209 | K40: 99.919911 | L40: 103.13706 | M40: 109.25416 | N40: 123.2722 | O40: 139.14686 | P40: 153.22997 | Q40: 150.4984 | R40: 140.20605 | S40: 142.68032
B41: Pack | C41: 49 | D41: 49 | E41: 49 | F41: 49 | G41: 49 | H41: 49 | I41: 49 | J41: 49 | K41: 49 | L41: 49 | M41: 49 | N41: 49 | O41: 49 | P41: 49 | Q41: 49 | R41: 49 | S41: 49
B42: Battery rack | C42: 152 | D42: 131.22138 | E42: 132.1569 | F42: 132.46201 | G42: 132.40739 | H42: 132.64366 | I42: 135.04868 | J42: 140.71521 | K42: 148.91991 | L42: 152.13706 | M42: 158.25416 | N42: 172.2722 | O42: 188.14686 | P42: 202.22997 | Q42: 199.4984 | R42: 189.20605 | S42: 191.68032
B43: Balance of system | C43: 35.371958 | D43: 35.371958 | E43: 35.371958 | F43: 35.371958 | G43: 35.371958 | H43: 35.371958 | I43: 35.371958 | J43: 35.371958 | K43: 35.371958 | L43: 35.371958 | M43: 35.371958 | N43: 35.371958 | O43: 35.371958 | P43: 35.371958 | Q43: 35.371958 | R43: 35.371958 | S43: 35.371958
B44: PCS | C44: 12.289209 | D44: 12.289209 | E44: 12.289209 | F44: 12.289209 | G44: 12.289209 | H44: 12.289209 | I44: 12.289209 | J44: 12.289209 | K44: 12.289209 | L44: 12.289209 | M44: 12.289209 | N44: 12.289209 | O44: 12.289209 | P44: 12.289209 | Q44: 12.289209 | R44: 12.289209 | S44: 12.289209
B45: EMS | C45: 5.5363225 | D45: 5.5363225 | E45: 5.5363225 | F45: 5.5363225 | G45: 5.5363225 | H45: 5.5363225 | I45: 5.5363225 | J45: 5.5363225 | K45: 5.5363225 | L45: 5.5363225 | M45: 5.5363225 | N45: 5.5363225 | O45: 5.5363225 | P45: 5.5363225 | Q45: 5.5363225 | R45: 5.5363225 | S45: 5.5363225
B46: Transformer | C46: 4.3972727 | D46: 4.3972727 | E46: 4.3972727 | F46: 4.3972727 | G46: 4.3972727 | H46: 4.3972727 | I46: 4.3972727 | J46: 4.3972727 | K46: 4.3972727 | L46: 4.3972727 | M46: 4.3972727 | N46: 4.3972727 | O46: 4.3972727 | P46: 4.3972727 | Q46: 4.3972727 | R46: 4.3972727 | S46: 4.3972727
B47: Margin & expenses | C47: 24.083902 | D47: 24.083902 | E47: 24.083902 | F47: 24.083902 | G47: 24.083902 | H47: 24.083902 | I47: 24.083902 | J47: 24.083902 | K47: 24.083902 | L47: 24.083902 | M47: 24.083902 | N47: 24.083902 | O47: 24.083902 | P47: 24.083902 | Q47: 24.083902 | R47: 24.083902 | S47: 24.083902
B48: EPC & grid connection addition | C48: 25.292244 | D48: 25.292244 | E48: 25.292244 | F48: 25.292244 | G48: 25.292244 | H48: 25.292244 | I48: 25.292244 | J48: 25.292244 | K48: 25.292244 | L48: 25.292244 | M48: 25.292244 | N48: 25.292244 | O48: 25.292244 | P48: 25.292244 | Q48: 25.292244 | R48: 25.292244 | S48: 25.292244
B49: Developer overhead & margin | C49: 24.535714 | D49: 24.535714 | E49: 24.535714 | F49: 24.535714 | G49: 24.535714 | H49: 24.535714 | I49: 24.535714 | J49: 24.535714 | K49: 24.535714 | L49: 24.535714 | M49: 24.535714 | N49: 24.535714 | O49: 24.535714 | P49: 24.535714 | Q49: 24.535714 | R49: 24.535714 | S49: 24.535714
B50: Fully-installed system | C50: 283.50662 | D50: 262.72801 | E50: 263.66352 | F50: 263.96863 | G50: 263.91402 | H50: 264.15028 | I50: 266.5553 | J50: 272.22183 | K50: 280.42653 | L50: 283.64369 | M50: 289.76079 | N50: 303.77882 | O50: 319.65348 | P50: 333.73659 | Q50: 331.00502 | R50: 320.71267 | S50: 323.18695

Sheet Storage LCOE
F1: Storage LCOE
A3: Dataset | B3: Storage LCOE 1H 2021 versus 1H 2022
A4: Units | B4: $/MWh (nominal)
A5: Source | B5: BloombergNEF
A6: Subject to terms and conditions
B37: Utility-scale battery (4h) LCOE
B38: $/MWh (nominal)
C39: Scenario | D39: Low | E39: Mid | F39: High | G39: Range | H39: % increase
B40: Germany | C40: 2021 | D40: 126.5686 | E40: 131.19855 | F40: 135.81634 | G40: 9.2477407
C41: 2022 | D41: 163.68616 | E41: 184.71611 | F41: 210.6893 | G41: 47.003138 | H41: 0.40791272
B42: UK | C42: 21 | D42: 127.52727 | E42: 134.11597 | F42: 140.70872 | G42: 13.181443
C43: 22 | D43: 162.34602 | E43: 182.82724 | F43: 208.45914 | G43: 46.113121 | H43: 0.36320257
B44: US | C44: 21 | D44: 119.20035 | E44: 123.64453 | F44: 128.0887 | G44: 8.888346
C45: 22 | D45: 116.38064 | E45: 131.63625 | F45: 163.71527 | G45: 47.334636 | H45: 0.064634654
B46: Japan | C46: 21 | D46: 422.13124 | E46: 438.20253 | F46: 454.27381 | G46: 32.142576
C47: 22 | D47: 283.62186 | E47: 344.23484 | F47: 632.55055 | G47: 348.9287 | H47: -0.21443895

Sheet Coal & gas cost inflation
F1: Coal & gas cost inflation
A3: Dataset | B3: Coal & gas cost inflation
A4: Units | B4: %
A5: Source | B5: BloombergNEF
A6: Subject to terms and conditions
B8: CCGT | L8: Coal-fired power plants
B34: Year-on-year USD nominal cost change | L34: Year-on-year USD nominal cost change
B35: % | L35: %
C36: Gas prices (15-year offtake) | D36: CCGT LCOE | M36: Coal prices (15-year offtake) | N36: Coal LCOE
B37: China | C37: 0.014152943 | D37: -0.11197791 | L37: Indonesia | M37: 0.11407863 | N37: 0.0052084115
B38: Indon. | C38: 0.072372699 | D38: 0.058167814 | L38: South Korea | M38: -0.0086697533 | N38: 0.008980413
B39: Thai. | C39: 0.065252727 | D39: 0.13202148 | L39: Thailand | M39: 0.078329007 | N39: 0.039335441
B40: Viet. | C40: 0.23184717 | D40: 0.14453318 | L40: Australia | M40: 0.096520304 | N40: 0.056336549
B41: India | C41: 0.17628815 | D41: 0.15117734 | L41: India | M41: 0.082222387 | N41: 0.071962032
B42: Brazil | C42: 0.11359212 | D42: 0.15195097 | L42: Japan | M42: 0.064024262 | N42: 0.098319087
B43: South Korea | C43: 0.13723271 | D43: 0.16540982 | L43: China | M43: 0.19078621 | N43: 0.2389588
B44: Canada | C44: 0.41307844 | D44: 0.17685997 | L44: Poland | M44: 0.096520304 | N44: 0.24239687
B45: Japan | C45: 0.10862531 | D45: 0.19769139
B46: EU | C46: 0.20783108 | D46: 0.2154059
B47: US | C47: 0.4605397 | D47: 0.21809207
B48: Austr. | C48: 0.23849816 | D48: 0.21810293
B49: Mexico | C49: 0.47379258 | D49: 0.25080806
B50: UK | C50: 0.20185172 | D50: 0.30491226

Sheet LCOE map
F1: LCOE map
A3: Dataset | B3: Cheapest source of new-build bulk generation, 1H 2022
A4: Units | B4: $/MWh, nominal
A5: Source | B5: BloombergNEF
A6: Subject to terms and conditions
B8: Cheapest source of bulk generation, 1H 2022
B9: New-build solar, wind, coal and gas
B43: List of countries with lowest-cost new build technology
B44: Country | C44: Technology
B45: Belgium | C45: Offshore wind
B46: Denmark | C46: Offshore wind
B47: France | C47: Fixed-axis PV
B48: Germany | C48: Fixed-axis PV
B49: Greece | C49: Fixed-axis PV
B50: Ireland | C50: Fixed-axis PV
B51: Italy | C51: Fixed-axis PV
B52: Netherlands | C52: Onshore wind
B53: Poland | C53: Onshore wind
B54: Portugal | C54: Fixed-axis PV
B55: Russian Federation | C55: CCGT
... B87: Zambia | C87: Fixed-axis PV

Sheet LCOE vs marginal cost map
F1: LCOE versus marginal cost map
A3: Dataset | B3: Cheapest source of new-build PV, wind versus existing coal and gas, 1H 2022
A4: Units | B4: $/MWh, nominal
A5: Source | B5: BloombergNEF
A6: Subject to terms and conditions
B8: Cheapest source of bulk generation, 1H 2022
B9: New-build solar and wind versus existing coal and gas
B44: List of countries with lowest-cost technology, new solar, wind versus existing gas, coal
B45: Country | C45: Technology
B46: Belgium | C46: Offshore wind
B47: Denmark | C47: Offshore wind
B48: France | C48: Fixed-axis PV
B49: Germany | C49: Fixed-axis PV
B50: Greece | C50: Fixed-axis PV
B51: Ireland | C51: Fixed-axis PV
B52: Italy | C52: Fixed-axis PV
B53: Netherlands | C53: Onshore wind
B54: Poland | C54: Onshore wind
B55: Portugal | C55: Fixed-axis PV
B56: Russian Federation | C56: CCGT
... B87: South Africa | C87: Tracking PV

Sheet Key long-term trends ->
F1: Key long-term trends

Sheet PV mono vs multi panels
F1: PV mono vs multi panels
A3: Dataset | B3: Mono vs multi share
A4: Units | B4: %
A5: Source | B5: BloombergNEF
A6: Subject to terms and conditions
B28: Share of market
B29: %
C30: Multi c-Si | D30: Mono c-Si
B31: 2016 | C31: 0.8 | D31: 0.2
B32: 2017 | C32: 0.72 | D32: 0.28
B33: 2018 | C33: 0.58461538 | D33: 0.41538462
B34: 2019 | C34: 0.41120028 | D34: 0.58879972
B35: 2020 | C35: 0.17085961 | D35: 0.82914039
B36: 2021 | C36: 0.071064283 | D36: 0.92893572
B37: Note: Multi after 2019 including mono-like wafer made of the casting process which is supposedly less than 1%

Sheet PV bifacial vs monofacial
F1: PV bifacial vs monofacial
A3: Dataset | B3: Share of bifacial module among all silicon PV
A4: Units | B4: %
A5: Source | B5: BloombegNEF, CPIA 2021
A6: Subject to terms and conditions
B28: Share of bifacial module among all silicon PV
B29: %
B30: Year | C30: Bifacial modules | D30: Other
B31: 2018 | C31: 0.03 | D31: =1-C31 -> 0.97
B32: 2019 | C32: 0.18 | D32: =1-C32 -> 0.82
B33: 2020 | C33: 0.3 | D33: =1-C33 -> 0.7
B34: 2021 | C34: 0.374 | D34: =1-C34 -> 0.626

Sheet Project size, Utility-scale PV
F1: Project size, Utility-scale PV
A3: Dataset | B3: Project size, Utility-scale PV
A4: Units | B4: MW
A5: Source | B5: BNEF Renewable Asset Database
A6: Subject to terms and conditions
B41: Distribution of utility-scale PV project size, global
B42: MW | E42: Financing date ->
B43: Technology | D43: Metric | E43: 2010 | F43: 2011 | G43: 2012 | H43: 2013 | I43: 2014 | J43: 2015 | K43: 2016 | L43: 2017 | M43: 2018 | N43: 2019 | O43: 2020 | P43: 2021 | Q43: 2022
B44: Solar PV | D44: Min | E44: 1 | F44: 1 | G44: 1 | H44: 1 | I44: 1 | J44: 1 | K44: 1 | L44: 1 | M44: 1 | N44: 1 | O44: 1 | P44: 1 | Q44: 1
B45: Solar PV | D45: Decile 1 | E45: 1 | F45: 1.1 | G45: 1.2 | H45: 1.2 | I45: 1.246 | J45: 1.553 | K45: 1.8 | L45: 1.8 | M45: 1.69 | N45: 1.8 | O45: 2 | P45: 2.4 | Q45: 2.5
B46: Solar PV | D46: Quartile 1 | E46: 1.7 | F46: 2 | G46: 1.9 | H46: 1.82 | I46: 2 | J46: 2.6 | K46: 3 | L46: 3 | M46: 2.7 | N46: 2.68 | O46: 3.22 | P46: 4.005 | Q46: 5.5
B47: Solar PV | D47: Median | E47: 3.2 | F47: 4.4 | G47: 4 | H47: 3.75 | I47: 5 | J47: 6.95 | K47: 8 | L47: 7.8 | M47: 7.2 | N47: 5.2 | O47: 10 | P47: 12.665 | Q47: 30
B48: Solar PV | D48: Average | E48: 6.3857764 | F48: 8.9529694 | G48: 10.391537 | H48: 10.647682 | I48: 14.590711 | J48: 17.388827 | K48: 19.205588 | L48: 19.562342 | M48: 22.663368 | N48: 25.26508 | O48: 45.40539 | P48: 65.20469 | Q48: 91.192324
B49: Solar PV | D49: Quartile 3 | E49: 7.2 | F49: 9.8 | G49: 10 | H49: 11.5 | I49: 17.75 | J49: 20 | K49: 20 | L49: 20 | M49: 25 | N49: 20.88 | O49: 50 | P49: 68 | Q49: 100
B50: Solar PV | D50: Decile 9 | E50: 13.77 | F50: 20 | G50: 22.3 | H50: 22.776 | I50: 32.13 | J50: 49.74 | K50: 50 | L50: 50 | M50: 50 | N50: 70 | O50: 117.65 | P50: 158.875 | Q50: 232.791
B51: Solar PV | D51: Max | E51: 83.5 | F51: 390 | G51: 715 | H51: 376.4 | I51: 530 | J51: 380 | K51: 1000 | L51: 1177.4 | M51: 709 | N51: 600 | O51: 2101 | P51: 3000 | Q51: 1745
B52: Solar PV | D52: Number | E52: 810 | F52: 1533 | G52: 1795 | H52: 2651 | I52: 2785 | J52: 3582 | K52: 3532 | L52: 4746 | M52: 3275 | N52: 3099 | O52: 2350 | P52: 2572 | Q52: 658
B53: Solar PV | D53: Min-Max range | E53: 82.5 | F53: 389 | G53: 714 | H53: 375.4 | I53: 529 | J53: 379 | K53: 999 | L53: 1176.4 | M53: 708 | N53: 599 | O53: 2100 | P53: 2999 | Q53: 1744
B54: Solar PV | D54: Quartile range | E54: 5.5 | F54: 7.8 | G54: 8.1 | H54: 9.68 | I54: 15.75 | J54: 17.4 | K54: 17 | L54: 17 | M54: 22.3 | N54: 18.2 | O54: 46.78 | P54: 63.995 | Q54: 94.5
B57: For Chart | D57: Metric | E57: 2010 | G57: 12 | I57: 14 | K57: 16 | M57: 18 | O57: 20 | Q57: 22 ytd
D58: Min | E58: =E44 -> 1 | F58: =F44 -> 1 | G58: =G44 -> 1 | H58: =H44 -> 1 | I58: =I44 -> 1 | J58: =J44 -> 1 | K58: =K44 -> 1 | L58: =L44 -> 1 | ... Q58: =Q44 -> 1
B59: Min to Q1 | D59: 25% smallest | E59: =E46-E44 -> 0.7 | F59: =F46-F44 -> 1 | G59: =G46-G44 -> 0.9 | H59: =H46-H44 -> 0.82 | I59: =I46-I44 -> 1 | J59: =J46-J44 -> 1.6 | K59: =K46-K44 -> 2 | L59: =L46-L44 -> 2 | ... Q59: =Q46-Q44 -> 4.5
B60: Q1 tp Q3 | D60: 50% of projects | E60: =E49-E45 -> 6.2 | F60: =F49-F45 -> 8.7 | G60: =G49-G45 -> 8.8 | H60: =H49-H45 -> 10.3 | I60: =I49-I45 -> 16.504 | J60: =J49-J45 -> 18.447 | K60: =K49-K45 -> 18.2 | L60: =L49-L45 -> 18.2 | ... Q60: =Q49-Q45 -> 97.5
B61: Q3 to max | D61: 25% largest | E61: =E51-E49 -> 76.3 | F61: =F51-F49 -> 380.2 | G61: =G51-G49 -> 705 | H61: =H51-H49 -> 364.9 | I61: =I51-I49 -> 512.25 | J61: =J51-J49 -> 360 | K61: =K51-K49 -> 980 | L61: =L51-L49 -> 1157.4 | ... Q61: =Q51-Q49 -> 1645
B65: Median project size, by country
B66: MW
B67: Technology | D67: Metric | E67: 2010 | F67: 2011 | G67: 2012 | H67: 2013 | I67: 2014 | J67: 2015 | K67: 2016 | L67: 2017 | M67: 2018 | N67: 2019 | O67: 2020 | P67: 2021 | Q67: 2022
B68: Solar PV | C68: Australia | E68: 1.35 | F68: #N/A | G68: 1.125 | H68: 43.2 | I68: 3.1 | J68: 8.25 | K68: 4.885 | L68: 30 | M68: 5.73 | N68: 5.8 | O68: 5.88 | P68: 5.88 | Q68: 5.88
B69: Solar PV | C69: China | E69: 5 | F69: 9.8 | G69: 10 | H69: 20 | I69: 20 | J69: 20 | K69: 20 | L69: 10 | M69: 10 | N69: 6.27 | O69: 50 | P69: 50 | Q69: 49.765
B70: Solar PV | C70: Germany | E70: 4.5 | F70: 6.5 | G70: 4.1 | H70: 3.8 | I70: 4.2 | J70: 3.2 | K70: 3.7 | L70: 4.6 | M70: 2.9 | N70: 6.5 | O70: 7.85 | P70: 9.035 | Q70: 4.775
B71: Solar PV | C71: India | E71: 2 | F71: 5 | G71: 5 | H71: 2.5 | I71: 5.1 | J71: 6 | K71: 5 | L71: 20 | M71: 9.15 | N71: 13.5 | O71: 8 | P71: 15.725 | Q71: 75
B72: Solar PV | C72: Japan | E72: 1.16 | F72: 1.5 | G72: 1.83 | H72: 1.89 | I72: 1.99 | J72: 2.06 | K72: 2.32 | L72: 2.43 | M72: 2.43 | N72: 2.68 | O72: 2.39 | P72: 3.2 | Q72: 2.425
B73: Solar PV | C73: United Kingdom | E73: 5 | F73: 4.6 | G73: 5 | H73: 7 | I73: 10 | J73: 5 | K73: 5 | L73: 5 | M73: 4.75 | N73: 5.2 | O73: 8.295 | P73: 19.2 | Q73: 49.95
B74: Solar PV | C74: United States | E74: 2 | F74: 2.9 | G74: 3.06 | H74: 5 | I74: 5.52 | J74: 6.5 | K74: 6.9 | L74: 6.8 | M74: 5.9 | N74: 6.5 | O74: 7.49 | P74: 6.7 | Q74: 11.66
B75: Solar PV | C75: Spain | E75: 3.3 | F75: 2.85 | G75: 2.3 | H75: 4.5 | I75: 2.95 | J75: #N/A | K75: #N/A | L75: 3.9 | M75: 42 | N75: 49.88 | O75: 30.4 | P75: 22 | Q75: 49.75
B76: Solar PV | C76: France | E76: 5.85 | F76: 4 | G76: 6.2 | H76: 4.885 | I76: 7.025 | J76: 4.6 | K76: 4.4 | L76: 5 | M76: 4.32 | N76: 4.41 | O76: 4.99 | P76: 5 | Q76: 5
B77: Solar PV | C77: Brazil | E77: 1 | F77: 1 | G77: 1.5 | H77: 3.068 | I77: 1.1 | J77: 37.2 | K77: 38.4225 | L77: 35.162 | M77: 34.629 | N77: 5.3 | O77: 41.796 | P77: 50 | Q77: 49.5
B78: Solar PV | C78: South Africa | E78: #N/A | F78: 1.2 | G78: 32.5 | H78: 44 | I78: 82.5 | J78: 41.797 | K78: 84.25 | L78: #N/A | M78: 78 | N78: 55 | O78: 35 | P78: 10 | Q78: 49.685

Sheet Turbine size, Onshore wind
F1: Turbine size, Onshore wind
A3: Dataset | B3: Turbine size, Onshore wind
A4: Units | B4: MW
A5: Source | B5: BloombergNEF
A6: Subject to terms and conditions
B41: Statistics on onshore wind turbine size, global
B42: MW | C42: 2002 | F42: 05 | K42: 2010 | M42: 12 | O42: 14 | Q42: 16 | S42: 18 | V42: 21
B43: Closing year | C43: 2002 | D43: 2003 | E43: 2004 | F43: 2005 | G43: 2006 | H43: 2007 | I43: 2008 | J43: 2009 | K43: 2010 | L43: 2011 | M43: 2012 | N43: 2013 | O43: 2014 | P43: 2015 | Q43: 2016 | R43: 2017 | S43: 2018 | T43: 2019 | U43: 2020 | V43: 2021
B44: Min | C44: 1.3 | D44: 1.3 | E44: 1.2972973 | F44: 1 | G44: 0.85 | H44: 0.037096774 | I44: 0.33333333 | J44: 1 | K44: 1 | L44: 1 | M44: 1 | N44: 0.2 | O44: 1.25 | P44: 1 | Q44: 0.25641026 | R44: 1.5 | S44: 1.6666667 | T44: 0.12592593 | U44: 2 | V44: 1.345
B45: Quartile 1 | C45: 1.35 | D45: 1.4960317 | E45: 1.65 | F45: 1.65 | G45: 1.8 | H45: 1.6632231 | I45: 1.5 | J45: 1.5 | K45: 1.65 | L45: 1.803834 | M45: 2 | N45: 2 | O45: 2 | P45: 2 | Q45: 2 | R45: 2.1 | S45: 2.475 | T45: 2.7625 | U45: 3.3 | V45: 3.4650431
B46: Average | C46: 1.9711187 | D46: 1.7914017 | E46: 1.8856764 | F46: 1.907332 | G46: 2.0904434 | H46: 2.0710742 | I46: 1.9844396 | J46: 1.9466171 | K46: 2.0226873 | L46: 2.1506747 | M46: 2.2604466 | N46: 2.4019892 | O46: 2.4989702 | P46: 2.4991072 | Q46: 2.4835679 | R46: 2.838449 | S46: 3.2177053 | T46: 3.6295206 | U46: 3.9557077 | V46: 4.1635798
B47: Median | C47: 2 | D47: 1.5 | E47: 1.9036145 | F47: 2 | G47: 2 | H47: 2 | I47: 2 | J47: 2 | K47: 2 | L47: 2.05 | M47: 2.1 | N47: 2.3 | O47: 2.4 | P47: 2.3 | Q47: 2.2075472 | R47: 3 | S47: 3.4491379 | T47: 3.625 | U47: 4.1666667 | V47: 4.2
B48: Quartile 3 | C48: 2.5 | D48: 2.15 | E48: 2 | F48: 2 | G48: 2.5 | H48: 2.3 | I48: 2.2513158 | J48: 2.1 | K48: 2.3 | L48: 2.5 | M48: 2.5 | N48: 3 | O48: 3 | P48: 3 | Q48: 3 | R48: 3.4597902 | S48: 3.6 | T48: 4.2 | U48: 4.5 | V48: 5.025
B49: Max | C49: 2.5 | D49: 3.4117647 | E49: 3 | F49: 3 | G49: 3.2 | H49: 7.58 | I49: 3 | J49: 5 | K49: 3.4 | L49: 3.4 | M49: 4.5 | N49: 5 | O49: 6 | P49: 8 | Q49: 4.5 | R49: 4.5 | S49: 4.5 | T49: 6.6 | U49: 7.58 | V49: 6.2
B50: Quartiles | C50: 1.15 | D50: 0.65396825 | E50: 0.35 | F50: 0.35 | G50: 0.7 | H50: 0.63677686 | I50: 0.75131579 | J50: 0.6 | K50: 0.65 | L50: 0.69616597 | M50: 0.5 | N50: 1 | O50: 1 | P50: 1 | Q50: 1 | R50: 1.3597902 | S50: 1.125 | T50: 1.4375 | U50: 1.2 | V50: 1.5599569
B51: Reset | C51: -2.5 | D51: -2.15 | E51: -2 | F51: -2 | G51: -2.5 | H51: -2.3 | I51: -2.2513158 | J51: -2.1 | K51: -2.3 | L51: -2.5 | M51: -2.5 | N51: -3 | O51: -3 | P51: -3 | Q51: -3 | R51: -3.4597902 | S51: -3.6 | T51: -4.2 | U51: -4.5 | V51: -5.025
B52: Min-max | C52: 1.2 | D52: 2.1117647 | E52: 1.7027027 | F52: 2 | G52: 2.35 | H52: 7.5429032 | I52: 2.6666667 | J52: 4 | K52: 2.4 | L52: 2.4 | M52: 3.5 | N52: 4.8 | O52: 4.75 | P52: 7 | Q52: 4.2435897 | R52: 3 | S52: 2.8333333 | T52: 6.4740741 | U52: 5.58 | V52: 4.855
B53: MW of contracts | C53: 449.8 | D53: 1244.1 | E53: 1926.9 | F53: 5099.87 | G53: 5186.5 | H53: 17123.25 | I53: 13624.62 | J53: 9500.02 | K53: 12754.2 | L53: 9252.85 | M53: 8763.15 | N53: 11379.58 | O53: 12848.01 | P53: 17315.18 | Q53: 19406.55 | R53: 20728.61 | S53: 23297.9 | T53: 24284.84 | U53: 23327.02 | V53: 18020.07
B54: Turbine number | C54: 230 | D54: 764 | E54: 1072 | F54: 2561 | G54: 2514 | H54: 8778 | I54: 7575 | J54: 4890 | K54: 6343 | L54: 4180 | M54: 3973 | N54: 5022 | O54: 5465 | P54: 7436 | Q54: 8218 | R54: 7765 | S54: 7751 | T54: 7341 | U54: 5516 | V54: 4260
B55: Count deals | C55: 12 | D55: 17 | E55: 30 | F55: 43 | G55: 52 | H55: 126 | I55: 132 | J55: 111 | K55: 161 | L55: 126 | M55: 133 | N55: 139 | O55: 221 | P55: 217 | Q55: 265 | R55: 228 | S55: 246 | T55: 188 | U55: 221 | V55: 158

Sheet Project size, Onshore wind
F1: Project size, Onshore wind
A3: Dataset | B3: Project size, Onshore wind
A4: Units | B4: MW
A5: Source | B5: BNEF Renewable Asset Database
A6: Subject to terms and conditions
B41: Distribution of onshore wind project size, global
B42: MW | E42: Financing date ->
B43: Technology | D43: Metric | E43: 2010 | F43: 2011 | G43: 2012 | H43: 2013 | I43: 2014 | J43: 2015 | K43: 2016 | L43: 2017 | M43: 2018 | N43: 2019 | O43: 2020 | P43: 2021 | Q43: 2022
B44: Wind Onshore | D44: Min | E44: 1 | F44: 1 | G44: 1 | H44: 1.25 | I44: 1.5 | J44: 1 | K44: 1.1 | L44: 1 | M44: 1.2 | N44: 1 | O44: 1.5 | P44: 1.98 | Q44: 3.6
B45: Wind Onshore | D45: Decile 1 | E45: 2.1 | F45: 1.6 | G45: 3.155 | H45: 3.2 | I45: 3.2 | J45: 3 | K45: 2.782 | L45: 2.4 | M45: 3.1 | N45: 6 | O45: 4.5 | P45: 8.4 | Q45: 18
B46: Wind Onshore | D46: Quartile 1 | E46: 5 | F46: 4.2 | G46: 9 | H46: 10 | I46: 9 | J46: 7 | K46: 6.6 | L46: 7.05 | M46: 9.6 | N46: 13.8 | O46: 11.2 | P46: 19.5 | Q46: 31.5
B47: Wind Onshore | D47: Median | E47: 15.65 | F47: 15 | G47: 25.8 | H47: 25.85 | I47: 23.1 | J47: 18.9 | K47: 17 | L47: 20.845 | M47: 28.8 | N47: 42 | O47: 39 | P47: 39.6 | Q47: 52.825
B48: Wind Onshore | D48: Average | E48: 30.909953 | F48: 26.643944 | G48: 35.898325 | H48: 39.138586 | I48: 35.877882 | J48: 34.953982 | K48: 33.658694 | L48: 39.036306 | M48: 48.668 | N48: 61.675723 | O48: 54.607356 | P48: 72.976724 | Q48: 139.74448
B49: Wind Onshore | D49: Quartile 3 | E49: 49.5 | F49: 49.075 | G49: 49.5 | H49: 49.5 | I49: 49.5 | J49: 49.5 | K49: 48.3 | L49: 50 | M49: 50.6 | N49: 72.72375 | O49: 50.6 | P49: 70 | Q49: 194
B50: Wind Onshore | D50: Decile 9 | E50: 50 | F50: 50 | G50: 63.3 | H50: 69.72 | I50: 57.7 | J50: 76 | K50: 75 | L50: 99.5 | M50: 105.4 | N50: 150 | O50: 103.66 | P50: 166.88 | Q50: 348
B51: Wind Onshore | D51: Max | E51: 845 | F51: 300 | G51: 470 | H51: 502 | I51: 402 | J51: 300.3 | K51: 400 | L51: 644.4 | M51: 600 | N51: 1001.85 | O51: 1000 | P51: 2267.1 | Q51: 1750
B52: Wind Onshore | D52: Number | E52: 1476 | F52: 1458 | G52: 1176 | H52: 1043 | I52: 1525 | J52: 1793 | K52: 1750 | L52: 1600 | M52: 1325 | N52: 1556 | O52: 1441 | P52: 1227 | Q52: 210
B53: Wind Onshore | D53: Min-Max range | E53: 844 | F53: 299 | G53: 469 | H53: 500.75 | I53: 400.5 | J53: 299.3 | K53: 398.9 | L53: 643.4 | M53: 598.8 | N53: 1000.85 | O53: 998.5 | P53: 2265.12 | Q53: 1746.4
B54: Wind Onshore | D54: Quartile range | E54: 44.5 | F54: 44.875 | G54: 40.5 | H54: 39.5 | I54: 40.5 | J54: 42.5 | K54: 41.7 | L54: 42.95 | M54: 41 | N54: 58.92375 | O54: 39.4 | P54: 50.5 | Q54: 162.5
B57: For Chart | D57: Metric | E57: 2010 | G57: 12 | I57: 14 | K57: 16 | M57: 18 | O57: 20 | Q57: 22 ytd
D58: Min | E58: =E44 -> 1 | F58: =F44 -> 1 | G58: =G44 -> 1 | H58: =H44 -> 1.25 | I58: =I44 -> 1.5 | J58: =J44 -> 1 | K58: =K44 -> 1.1 | L58: =L44 -> 1 | ... Q58: =Q44 -> 3.6
B59: Min to Q1 | D59: 25% smallest | E59: =E46-E44 -> 4 | F59: =F46-F44 -> 3.2 | G59: =G46-G44 -> 8 | H59: =H46-H44 -> 8.75 | I59: =I46-I44 -> 7.5 | J59: =J46-J44 -> 6 | K59: =K46-K44 -> 5.5 | L59: =L46-L44 -> 6.05 | ... Q59: =Q46-Q44 -> 27.9
B60: Q1 tp Q3 | D60: 50% of projects | E60: =E49-E45 -> 47.4 | F60: =F49-F45 -> 47.475 | G60: =G49-G45 -> 46.345 | H60: =H49-H45 -> 46.3 | I60: =I49-I45 -> 46.3 | J60: =J49-J45 -> 46.5 | K60: =K49-K45 -> 45.518 | L60: =L49-L45 -> 47.6 | ... Q60: =Q49-Q45 -> 176
B61: Q3 to max | D61: 25% largest | E61: =E51-E49 -> 795.5 | F61: =F51-F49 -> 250.925 | G61: =G51-G49 -> 420.5 | H61: =H51-H49 -> 452.5 | I61: =I51-I49 -> 352.5 | J61: =J51-J49 -> 250.8 | K61: =K51-K49 -> 351.7 | L61: =L51-L49 -> 594.4 | ... Q61: =Q51-Q49 -> 1556
B65: Median project size, by country
B66: MW
B67: Technology | D67: Metric | E67: 2010 | F67: 2011 | G67: 2012 | H67: 2013 | I67: 2014 | J67: 2015 | K67: 2016 | L67: 2017 | M67: 2018 | N67: 2019 | O67: 2020 | P67: 2021 | Q67: 2022
B68: Wind Onshore | C68: Australia | E68: 48.3 | F68: 55 | G68: 131.2 | H68: 106.8 | I68: 6.15 | J68: 102.4 | K68: 100.8 | L68: 116.1 | M68: 133.2 | N68: 152.95 | O68: 12 | P68: 180.6 | Q68: 686.7
B69: Wind Onshore | C69: China | E69: 49.5 | F69: 49.5 | G69: 49.5 | H69: 49.5 | I69: 49.5 | J69: 49.5 | K69: 49.8 | L69: 50 | M69: 50 | N69: 50 | O69: 50 | P69: 49.5 | Q69: 124.45
B70: Wind Onshore | C70: Germany | E70: 6 | F70: 6.9 | G70: 9.2 | H70: 9.6 | I70: 9.4 | J70: 9.2 | K70: 8.3 | L70: 9 | M70: 7.2 | N70: 9 | O70: 8.4 | P70: 8.45 | Q70: 16.95
B71: Wind Onshore | C71: India | E71: 4.5 | F71: 2.1 | G71: 6.8 | H71: 13 | I71: 8.2 | J71: 4 | K71: 6 | L71: 2.1 | M71: 2.1 | N71: 18.9 | O71: 2.775 | P71: 132.25 | Q71: 99.9
B72: Wind Onshore | C72: Japan | E72: 10 | F72: 2 | G72: 6 | H72: 4 | I72: 7.48 | J72: 2 | K72: 16 | L72: 20.4 | M72: 7.485 | N72: 6.9 | O72: 17.1 | P72: 14.46 | Q72: 42
B73: Wind Onshore | C73: United Kingdom | E73: 9.1 | F73: 10.1 | G73: 10 | H73: 12 | I73: 9 | J73: 15 | K73: 8.3 | L73: 12.85 | M73: 9 | N73: 23.75 | O73: 43.2 | P73: 40.04 | Q73: 27.4
B74: Wind Onshore | C74: United States | E74: 72 | F74: 25.15 | G74: 62.1 | H74: 115.8 | I74: 124.55 | J74: 107.5 | K74: 104 | L74: 114 | M74: 103.5 | N74: 162 | O74: 160.8 | P74: 145 | Q74: 301.5
B75: Wind Onshore | C75: Spain | E75: 30 | F75: 30.3 | G75: 18 | H75: 9 | I75: #N/A | J75: 35 | K75: 4.5 | L75: 9.6 | M75: 25.3 | N75: 26.15 | O75: 31.5 | P75: 49 | Q75: 38.3
B76: Wind Onshore | C76: France | E76: 12 | F76: 11.75 | G76: 12 | H76: 12 | I76: 12 | J76: 12 | K76: 12 | L76: 12.5 | M76: 14.1 | N76: 13.2 | O76: 12 | P76: 14 | Q76: 23.4
B77: Wind Onshore | C77: Brazil | E77: 30 | F77: 27.45 | G77: 29.65 | H77: 27.975 | I77: 28.9 | J77: 22.295 | K77: 27.3 | L77: 27.6 | M77: 25 | N77: 34.125 | O77: 42 | P77: 37.2 | Q77: 39.2
B78: Wind Onshore | C78: South Africa | E78: 1.8 | F78: #N/A | G78: 76.9 | H78: 94.5 | I78: 88 | J78: 125.65 | K78: #N/A | L78: #N/A | M78: 142.6 | N78: #N/A | O78: #N/A | P78: #N/A | Q78: #N/A

Sheet Onshore wind capacity factors
D1: Onshore wind capacity factors
A3: Dataset | B3: Onshore wind capacity factors, global
A4: Units | B4: %
A5: Source | B5: BloombergNEF
A6: Subject to terms and conditions
B30: Historic onshore wind capacity factors
B31: % | C31: 2000 | D31: =C31+1 -> 2001 | E31: =D31+1 -> 2002 | F31: =E31+1 -> 2003 | G31: =F31+1 -> 2004 | H31: =G31+1 -> 2005 | I31: =H31+1 -> 2006 | J31: =I31+1 -> 2007 | K31: =J31+1 -> 2008 | ... W31: =V31+1 -> 2020 | X31: 2021 | Y31: 2022
B32: Metric | C32: 2000 | H32: 05 | M32: 2010 | R32: 2015 | W32: 2020 | Y32: 22e
B33: Average | C33: 0.24402003 | D33: 0.23743326 | E33: 0.20201359 | F33: 0.24025931 | G33: 0.22413255 | H33: 0.24535077 | I33: 0.25398772 | J33: 0.26282345 | K33: 0.25543425 | L33: 0.2692925 | M33: 0.26464488 | N33: 0.27156429 | O33: 0.28680344 | P33: 0.27859975 | Q33: 0.30357821 | R33: 0.3051872 | S33: 0.32965487 | T33: 0.32579091 | U33: 0.333031 | V33: 0.33455556 | W33: 0.32596386 | X33: 0.34265241 | Y33: 0.34678663
B34: Median | C34: 0.22186542 | D34: 0.21442863 | E34: 0.20241749 | F34: 0.21346807 | G34: 0.20971918 | H34: 0.21025424 | I34: 0.22865558 | J34: 0.231389 | K34: 0.23814942 | L34: 0.24455651 | M34: 0.2466323 | N34: 0.25113411 | O34: 0.2607714 | P34: 0.26598415 | Q34: 0.28142027 | R34: 0.28734809 | S34: 0.29118149 | T34: 0.29373881 | U34: 0.30211771 | V34: 0.30160873 | W34: 0.33339963 | X34: 0.34579633 | Y34: 0.34977966
B35: First quartile | C35: 0.17268308 | D35: 0.16756671 | E35: 0.15830452 | F35: 0.16883988 | G35: 0.16507535 | H35: 0.16622139 | I35: 0.17609526 | J35: 0.18017832 | K35: 0.18375302 | L35: 0.19509409 | M35: 0.19543589 | N35: 0.19583611 | O35: 0.2050759 | P35: 0.21618569 | Q35: 0.21985929 | R35: 0.22891107 | S35: 0.2397562 | T35: 0.24378788 | U35: 0.25773993 | V35: 0.25129924 | W35: 0.26615654 | X35: 0.28881052 | Y35: 0.29148884
B36: Last quartile | C36: 0.28584254 | D36: 0.25982114 | E36: 0.2494596 | F36: 0.27050206 | G36: 0.25867964 | H36: 0.27538676 | I36: 0.28667611 | J36: 0.28728899 | K36: 0.29798276 | L36: 0.30580143 | M36: 0.30240533 | N36: 0.31602719 | O36: 0.32305098 | P36: 0.31733565 | Q36: 0.33991224 | R36: 0.34493394 | S36: 0.3491288 | T36: 0.33938316 | U36: 0.35947183 | V36: 0.36850844 | W36: 0.39214841 | X36: 0.39734746 | Y36: 0.41125736
B37: Range quartile | C37: 0.11315946 | D37: 0.092254435 | E37: 0.091155077 | F37: 0.10166218 | G37: 0.09360429 | H37: 0.10916537 | I37: 0.11058085 | J37: 0.10711067 | K37: 0.11422974 | L37: 0.11070734 | M37: 0.10696944 | N37: 0.12019109 | O37: 0.11797508 | P37: 0.10114996 | Q37: 0.12005295 | R37: 0.11602286 | S37: 0.10937261 | T37: 0.095595283 | U37: 0.1017319 | V37: 0.1172092 | W37: 0.12599186 | X37: 0.10853695 | Y37: 0.11976852
B38: First decile | C38: 0.13105102 | D38: 0.13698956 | E38: 0.13011667 | F38: 0.13693481 | G38: 0.13360093 | H38: 0.13461337 | I38: 0.13427735 | J38: 0.13524367 | K38: 0.14056741 | L38: 0.15417242 | M38: 0.15799993 | N38: 0.15468788 | O38: 0.16119991 | P38: 0.17088535 | Q38: 0.18532887 | R38: 0.18258784 | S38: 0.19426934 | T38: 0.20687386 | U38: 0.21531428 | V38: 0.21661956 | W38: 0.21537316 | X38: 0.23746557 | Y38: 0.23721717
B39: Last decile | C39: 0.34428095 | D39: 0.31567568 | E39: 0.29360026 | F39: 0.34431153 | G39: 0.31802613 | H39: 0.34693575 | I39: 0.34687128 | J39: 0.34850008 | K39: 0.34668251 | L39: 0.36342063 | M39: 0.35760088 | N39: 0.37448153 | O39: 0.38620823 | P39: 0.36886005 | Q39: 0.4073199 | R39: 0.40782411 | S39: 0.42155096 | T39: 0.40052578 | U39: 0.44216073 | V39: 0.42750207 | W39: 0.43710045 | X39: 0.4433775 | Y39: 0.4465836
B40: Decile range | C40: 0.21322993 | D40: 0.17868612 | E40: 0.16348359 | F40: 0.20737672 | G40: 0.1844252 | H40: 0.21232238 | I40: 0.21259394 | J40: 0.2132564 | K40: 0.2061151 | L40: 0.20924821 | M40: 0.19960094 | N40: 0.21979365 | O40: 0.22500832 | P40: 0.1979747 | Q40: 0.22199102 | R40: 0.22523627 | S40: 0.22728162 | T40: 0.19365192 | U40: 0.22684644 | V40: 0.2108825 | W40: 0.22172729 | X40: 0.20591193 | Y40: 0.20936643
B41: Reset | C41: -0.34428095 | D41: -0.31567568 | E41: -0.29360026 | F41: -0.34431153 | G41: -0.31802613 | H41: -0.34693575 | I41: -0.34687128 | J41: -0.34850008 | K41: -0.34668251 | L41: -0.36342063 | M41: -0.35760088 | N41: -0.37448153 | O41: -0.38620823 | P41: -0.36886005 | Q41: -0.4073199 | R41: -0.40782411 | S41: -0.42155096 | T41: -0.40052578 | U41: -0.44216073 | V41: -0.42750207 | W41: -0.43710045 | X41: -0.4433775 | Y41: -0.4465836

Sheet Turbine Size, Offshore wind
F1: Turbine size, offshore wind
A3: Dataset | B3: Turbine size, offshore wind
A4: Units | B4: MW
A5: Source | B5: BloombergNEF
A6: Subject to terms and conditions
B36: Statistics on offshore wind turbine size, global
B37: MW | C37: 2002 | F37: 05 | K37: 2010 | M37: 12 | O37: 14 | Q37: 16 | S37: 18 | V37: 21
B38: Closing year | C38: 2002 | D38: 2003 | E38: 2004 | F38: 2005 | G38: 2006 | H38: 2007 | I38: 2008 | J38: 2009 | K38: 2010 | L38: 2011 | M38: 2012 | N38: 2013 | O38: 2014 | P38: 2015 | Q38: 2016 | R38: 2017 | S38: 2018 | T38: 2019 | U38: 2020 | V38: 2021
B39: Min | C39: 2 | D39: 2 | E39: 3 | F39: 3 | G39: 2.2916667 | H39: 2.2967033 | I39: 2.3 | J39: 2.3 | K39: 3.6 | L39: 1.5 | M39: 1.5 | N39: 1.6 | O39: 3 | P39: 3.4482759 | Q39: 4 | R39: 6 | S39: 2 | T39: 3 | U39: 3.8461538 | V39: 4
B40: Quartile 1 | C40: =NA() -> #N/A | D40: =NA() -> #N/A | E40: =NA() -> #N/A | F40: =NA() -> #N/A | G40: 2.2916667 | H40: 3.6 | I40: 2.475 | J40: 2.825 | K40: 3.6 | L40: 2.625 | M40: 2.625 | N40: 2.3 | O40: 4 | P40: 6 | Q40: 6.25 | R40: 6.34375 | S40: 6.5 | T40: 4.1115385 | U40: 4.140625 | V40: 7
B41: Average | C41: 2 | D41: 2 | E41: 3 | F41: 3.3 | G41: 2.6458333 | H41: 3.6138148 | I41: 3.825 | J41: 3.5166667 | K41: 4.4486111 | L41: 3.525 | M41: 3 | N41: 3.9866667 | O41: 5.5555556 | P41: 6.1069552 | Q41: 6.9853896 | R41: 7.3961118 | S41: 7.8978205 | T41: 6.228022 | U41: 7.4255655 | V41: 9.7142857
B42: Median | C42: 2 | D42: 2 | E42: 3 | F42: 3.3 | G42: 2.6458333 | H42: 3.6 | I42: 4 | J42: 3.6 | K42: 3.6 | L42: 3.6 | M42: 3 | N42: 3.3333333 | O42: 6 | P42: 6 | Q42: 7 | R42: 8 | S42: 8.4 | T42: 7 | U42: 7.5 | V42: 9.5
B43: Quartile 3 | C43: =NA() -> #N/A | D43: =NA() -> #N/A | E43: =NA() -> #N/A | F43: =NA() -> #N/A | G43: 3 | H43: 3.6 | I43: 5 | J43: 3.95 | K43: 6.1458333 | L43: 3.9 | M43: 3.9 | N43: 6 | O43: 7 | P43: 6.4053191 | Q43: 8.2964286 | R43: 8.1290323 | S43: 9.5 | T43: 8 | U43: 10.243902 | V43: 13
B44: Max | C44: 2 | D44: 2 | E44: 3 | F44: 3.6 | G44: 3 | H44: 5 | I44: 5 | J44: 5 | K44: 6.1458333 | L44: 6 | M44: 6 | N44: 6 | O44: 8 | P44: 8.25 | Q44: 8.4727273 | R44: 8.3 | S44: 9.5555556 | T44: 9.5 | U44: 13 | V44: 14
B45: Quartiles | C45: =NA() -> #N/A | D45: =NA() -> #N/A | E45: =NA() -> #N/A | F45: =NA() -> #N/A | G45: 0.70833333 | H45: 0 | I45: 2.525 | J45: 1.125 | K45: 2.5458333 | L45: 1.275 | M45: 1.275 | N45: 3.7 | O45: 3 | P45: 0.40531915 | Q45: 2.0464286 | R45: 1.7852823 | S45: 3 | T45: 3.8884615 | U45: 6.1032774 | V45: 6
B46: Reset | C46: =NA() -> #N/A | D46: =NA() -> #N/A | E46: =NA() -> #N/A | F46: =NA() -> #N/A | G46: -3 | H46: -3.6 | I46: -5 | J46: -3.95 | K46: -6.1458333 | L46: -3.9 | M46: -3.9 | N46: -6 | O46: -7 | P46: -6.4053191 | Q46: -8.2964286 | R46: -8.1290323 | S46: -9.5 | T46: -8 | U46: -10.243902 | V46: -13
B47: Min-max | C47: 0 | D47: 0 | E47: 0 | F47: 0.6 | G47: 0.70833333 | H47: 2.7032967 | I47: 2.7 | J47: 2.7 | K47: 2.5458333 | L47: 4.5 | M47: 4.5 | N47: 4.4 | O47: 5 | P47: 4.8017241 | Q47: 4.4727273 | R47: 2.3 | S47: 7.5555556 | T47: 6.5 | U47: 9.1538462 | V47: 10
B48: MW of contracts | C48: 60 | D48: 60 | E48: 90 | F48: 198 | G48: 520 | H48: 1243.4 | I48: 627 | J48: 1454.1 | K48: 1673.6 | L48: 1190.2 | M48: 216 | N48: 844.2 | O48: 2033 | P48: 3215.5 | Q48: 3536.7 | R48: 2377.8 | S48: 5307.7 | T48: 4442.1 | U48: 8956.4 | V48: 4244.5
B49: Turbine number | C49: 30 | D49: 30 | E49: 30 | F49: 61 | G49: 196 | H49: 376 | I49: 214 | J49: 401 | K49: 397 | L49: 354 | M49: 72 | N49: 207 | O49: 420 | P49: 560 | Q49: 500 | R49: 304 | S49: 603 | T49: 644 | U49: 870 | V49: 397
B50: Count deals | C50: 1 | D50: 1 | E50: 1 | F50: 2 | G50: 4 | H50: 7 | I50: 4 | J50: 6 | K50: 6 | L50: 8 | M50: 1 | N50: 5 | O50: 9 | P50: 10 | Q50: 12 | R50: 7 | S50: 12 | T50: 14 | U50: 18 | V50: 7

Sheet Project size, Offshore wind
F1: Project size, Offshore wind
A3: Dataset | B3: Project size, Offshore wind
A4: Units | B4: MW
A5: Source | B5: BNEF Renewable Asset Database
A6: Subject to terms and conditions
B41: Distribution of offshore wind project size, global
E42: Financing date ->
B43: Technology | D43: Metric | E43: 2010 | F43: 2011 | G43: 2012 | H43: 2013 | I43: 2014 | J43: 2015 | K43: 2016 | L43: 2017 | M43: 2018 | N43: 2019 | O43: 2020 | P43: 2021 | Q43: 2022
B44: Wind Onshore | D44: Min | E44: 2.3 | F44: 2 | G44: 1.99 | H44: 7 | I44: 6 | J44: 5 | K44: 2 | L44: 4.2 | M44: 2 | N44: 12 | O44: 2 | P44: 4.25 | Q44: 6.2
B45: Wind Onshore | D45: Decile 1 | E45: 2.3 | F45: 2.2 | G45: 1.99 | H45: 8.5 | I45: 19.05 | J45: 30 | K45: 10 | L45: 32.76 | M45: 3.3 | N45: 50 | O45: 27.72 | P45: 13.04 | Q45: 7.25
B46: Wind Onshore | D46: Quartile 1 | E46: 75.05 | F46: 16 | G46: 5.5 | H46: 27.375 | I46: 96 | J46: 75 | K46: 70.8 | L46: 201.6 | M46: 106.9 | N46: 200 | O46: 50 | P46: 30 | Q46: 100
B47: Wind Onshore | D47: Median | E47: 151.2 | F47: 149.3 | G47: 60 | H47: 111.3 | I47: 300 | J47: 200 | K47: 254 | L47: 302.4 | M47: 235.75 | N47: 300 | O47: 254.2 | P47: 176.4 | Q47: 300
B48: Wind Onshore | D48: Average | E48: 220 | F48: 171.69091 | G48: 112.26556 | H48: 136.025 | I48: 268.35833 | J48: 215.50952 | K48: 225.00333 | L48: 285.58519 | M48: 242.25882 | N48: 266.70286 | O48: 273.09462 | P48: 272.73902 | Q48: 375.49737
B49: Wind Onshore | D49: Quartile 3 | E49: 376.4 | F49: 301.6 | G49: 243 | H49: 241.5 | I49: 397.2 | J49: 331 | K49: 373.45 | L49: 376 | M49: 314 | N49: 303.15 | O49: 400 | P49: 403 | Q49: 504
B50: Wind Onshore | D50: Decile 9 | E50: 576 | F50: 399.92 | G50: 288 | H50: 288 | I50: 540.6 | J50: 401.64 | K50: 406 | L50: 462 | M50: 493.85 | N50: 462 | O50: 617.5 | P50: 700 | Q50: 1000
B51: Wind Onshore | D51: Max | E51: 576 | F51: 400 | G51: 288 | H51: 288 | I51: 600 | J51: 573 | K51: 464.8 | L51: 497 | M51: 731.5 | N51: 605.2 | O51: 1540 | P51: 1001 | Q51: 1001
B52: Wind Onshore | D52: Number | E52: 9 | F52: 11 | G52: 9 | H52: 12 | I52: 12 | J52: 21 | K52: 30 | L52: 27 | M52: 34 | N52: 35 | O52: 65 | P52: 41 | Q52: 19
B53: Wind Onshore | D53: Min-Max range | E53: 573.7 | F53: 398 | G53: 286.01 | H53: 281 | I53: 594 | J53: 568 | K53: 462.8 | L53: 492.8 | M53: 729.5 | N53: 593.2 | O53: 1538 | P53: 996.75 | Q53: 994.8
B54: Wind Onshore | D54: Quartile range | E54: 301.35 | F54: 285.6 | G54: 237.5 | H54: 214.125 | I54: 301.2 | J54: 256 | K54: 302.65 | L54: 174.4 | M54: 207.1 | N54: 103.15 | O54: 350 | P54: 373 | Q54: 404
B57: For Chart | D57: Metric | E57: 2010 | G57: 12 | I57: 14 | K57: 16 | M57: 18 | O57: 20 | Q57: 22 ytd
B58: 0 to Min | D58: Min | E58: =E44 -> 2.3 | F58: =F44 -> 2 | G58: =G44 -> 1.99 | H58: =H44 -> 7 | I58: =I44 -> 6 | J58: =J44 -> 5 | K58: =K44 -> 2 | L58: =L44 -> 4.2 | ... Q58: =Q44 -> 6.2
B59: D1 to Q1 | D59: 25% smallest | E59: =E46-E44 -> 72.75 | F59: =F46-F44 -> 14 | G59: =G46-G44 -> 3.51 | H59: =H46-H44 -> 20.375 | I59: =I46-I44 -> 90 | J59: =J46-J44 -> 70 | K59: =K46-K44 -> 68.8 | L59: =L46-L44 -> 197.4 | ... Q59: =Q46-Q44 -> 93.8
B60: Q1 to Q3 | D60: 50% central | E60: =E49-E45 -> 374.1 | F60: =F49-F45 -> 299.4 | G60: =G49-G45 -> 241.01 | H60: =H49-H45 -> 233 | I60: =I49-I45 -> 378.15 | J60: =J49-J45 -> 301 | K60: =K49-K45 -> 363.45 | L60: =L49-L45 -> 343.24 | ... Q60: =Q49-Q45 -> 496.75
B61: Q3 to Q4 | D61: 25% largest projects | E61: =E51-E49 -> 199.6 | F61: =F51-F49 -> 98.4 | G61: =G51-G49 -> 45 | H61: =H51-H49 -> 46.5 | I61: =I51-I49 -> 202.8 | J61: =J51-J49 -> 242 | K61: =K51-K49 -> 91.35 | L61: =L51-L49 -> 121 | ... Q61: =Q51-Q49 -> 497
B65: Median project size, by country
B66: MW
B67: Technology | D67: Metric | E67: 2010 | F67: 2011 | G67: 2012 | H67: 2013 | I67: 2014 | J67: 2015 | K67: 2016 | L67: 2017 | M67: 2018 | N67: 2019 | O67: 2020 | P67: 2021 | Q67: 2022
B68: Wind Onshore | C68: Australia | E68: 48.3 | F68: 55 | G68: 131.2 | H68: 106.8 | I68: 6.15 | J68: 102.4 | K68: 100.8 | L68: 116.1 | M68: 133.2 | N68: 152.95 | O68: 12 | P68: 180.6 | Q68: 686.7
B69: Wind Onshore | C69: China | E69: 49.5 | F69: 49.5 | G69: 49.5 | H69: 49.5 | I69: 49.5 | J69: 49.5 | K69: 49.8 | L69: 50 | M69: 50 | N69: 50 | O69: 50 | P69: 49.5 | Q69: 124.45
B70: Wind Onshore | C70: Germany | E70: 6 | F70: 6.9 | G70: 9.2 | H70: 9.6 | I70: 9.4 | J70: 9.2 | K70: 8.3 | L70: 9 | M70: 7.2 | N70: 9 | O70: 8.4 | P70: 8.45 | Q70: 16.95
B71: Wind Onshore | C71: India | E71: 4.5 | F71: 2.1 | G71: 6.8 | H71: 13 | I71: 8.2 | J71: 4 | K71: 6 | L71: 2.1 | M71: 2.1 | N71: 18.9 | O71: 2.775 | P71: 132.25 | Q71: 99.9
B72: Wind Onshore | C72: Japan | E72: 10 | F72: 2 | G72: 6 | H72: 4 | I72: 7.48 | J72: 2 | K72: 16 | L72: 20.4 | M72: 7.485 | N72: 6.9 | O72: 17.1 | P72: 14.46 | Q72: 42
B73: Wind Onshore | C73: United Kingdom | E73: 9.1 | F73: 10.1 | G73: 10 | H73: 12 | I73: 9 | J73: 15 | K73: 8.3 | L73: 12.85 | M73: 9 | N73: 23.75 | O73: 43.2 | P73: 40.04 | Q73: 27.4
B74: Wind Onshore | C74: United States | E74: 72 | F74: 25.15 | G74: 62.1 | H74: 115.8 | I74: 124.55 | J74: 107.5 | K74: 104 | L74: 114 | M74: 103.5 | N74: 162 | O74: 160.8 | P74: 145 | Q74: 301.5
B75: Wind Onshore | C75: Spain | E75: 30 | F75: 30.3 | G75: 18 | H75: 9 | I75: #N/A | J75: 35 | K75: 4.5 | L75: 9.6 | M75: 25.3 | N75: 26.15 | O75: 31.5 | P75: 49 | Q75: 38.3
B76: Wind Onshore | C76: France | E76: 12 | F76: 11.75 | G76: 12 | H76: 12 | I76: 12 | J76: 12 | K76: 12 | L76: 12.5 | M76: 14.1 | N76: 13.2 | O76: 12 | P76: 14 | Q76: 23.4
B77: Wind Onshore | C77: Brazil | E77: 30 | F77: 27.45 | G77: 29.65 | H77: 27.975 | I77: 28.9 | J77: 22.295 | K77: 27.3 | L77: 27.6 | M77: 25 | N77: 34.125 | O77: 42 | P77: 37.2 | Q77: 39.2
B78: Wind Onshore | C78: South Africa | E78: 1.8 | F78: #N/A | G78: 76.9 | H78: 94.5 | I78: 88 | J78: 125.65 | K78: #N/A | L78: #N/A | M78: 142.6 | N78: #N/A | O78: #N/A | P78: #N/A | Q78: #N/A

Sheet Battery storage characteristics
F1: Battery storage project characteristics
A3: Dataset | B3: Battery storage project characteristics, global
A4: Units | B4: As indicated
A5: Source | B5: BloombergNEF
A6: Subject to terms and conditions
B8: Power output | H8: Storage duration
B41: Battery storage project characteristics
D42: 2010 | F42: 12 | H42: 14 | J42: 16 | L42: 18 | O42: 21e
B43: Statistic | C43: Metric | D43: 2010 | E43: 2011 | F43: 2012 | G43: 2013 | H43: 2014 | I43: 2015 | J43: 2016 | K43: 2017 | L43: 2018 | M43: 2019 | N43: 2020 | O43: 2021
B44: Average | C44: Output (MW) | D44: 0.35555556 | E44: 2.6968966 | F44: 0.59759259 | G44: 0.62591837 | H44: 1.6182716 | I44: 2.9605882 | J44: 4.9713103 | K44: 5.0516185 | L44: 5.8207491 | M44: 7.4100417 | N44: 12.03317 | O44: 22.053138
C45: Duration (hours) | D45: 0.83333333 | E45: 1.1348272 | F45: 1.0335354 | G45: 1.3796296 | H45: 1.9414706 | I45: 1.2003602 | J45: 1.3674631 | K45: 1.6884781 | L45: 2.3341843 | M45: 1.8034737 | N45: 1.7487052 | O45: 2.2000636
B46: First quartile | C46: Output (MW) | D46: 0.075 | E46: 0.05 | F46: 0.05 | G46: 0.1225 | H46: 0.25 | I46: 0.33 | J46: 0.45 | K46: 0.5 | L46: 0.67 | M46: 1 | N46: 1.3 | O46: 2.3
C47: Duration (hours) | D47: #N/A | E47: 0.25 | F47: 0.44545455 | G47: 0.25333333 | H47: 0.825 | I47: 0.5 | J47: 0.48333333 | K47: 0.5 | L47: 1 | M47: 0.86234818 | N47: 1 | O47: 1.1055276
B48: Last quartile | C48: Output (MW) | D48: 0.6 | E48: 2 | F48: 0.825 | G48: 0.67 | H48: 1.585 | I48: 1.7 | J48: 7.5 | K48: 5.8 | L48: 9 | M48: 10 | N48: 10 | O48: 20
C49: Duration (hours) | D49: #N/A | E49: 1.6666667 | F49: 1.335 | G49: 2 | H49: 2.4666667 | I49: 1.7981651 | J49: 1.9125683 | K49: 2.3229167 | L49: 3.42 | M49: 2 | N49: 2 | O49: 3
B50: Min | C50: Output (MW) | D50: 0.05 | E50: 0.02 | F50: 0.01 | G50: 0.02 | H50: 0.02 | I50: 0.02 | J50: 0.07 | K50: 0.03 | L50: 0.01 | M50: 0.03 | N50: 0.05 | O50: 0.1
C51: Duration (hours) | D51: 0.66666667 | E51: 0.15 | F51: 0.25 | G51: 0.16666667 | H51: 0.31764706 | I51: 0.25 | J51: 0.25 | K51: 0.15666667 | L51: 0.375 | M51: 0.24553571 | N51: 0.25 | O51: 0.21818182
B52: Max | C52: Output (MW) | D52: 1.5 | E52: 21.33 | F52: 11 | G52: 5 | H52: 28 | I52: 100 | J52: 50.4 | K52: 66.67 | L52: 50 | M52: 100 | N52: 301.46 | O52: 400
C53: Duration (hours) | D53: 1 | E53: 4 | F53: 3 | G53: 5 | H53: 7.6666667 | I53: 4.195 | J53: 4 | K53: 6.5 | L53: 8 | M53: 8 | N53: 5 | O53: 7.1157025
B54: Median | C54: Output (MW) | D54: 0.1 | E54: 0.5 | F54: 0.11 | G54: 0.33 | H54: 0.67 | I54: 0.6 | J54: 1 | K54: 1 | L54: 2 | M54: 2.345 | N54: 4.06 | O54: 6.67
C55: Duration (hours) | D55: 0.83333333 | E55: 0.50023441 | F55: 0.9 | G55: 0.76 | H55: 1.665 | I55: 1 | J55: 1 | K55: 1 | L55: 2 | M55: 1.010101 | N55: 1.49 | O55: 2
B56: Note: Reflect projects commissioned, financed or under construction. Statistics based on a global subset of 1654 Li-ion energy storage projects since 2010. See BNEF’s Storage Asset Database (web).
B60: For Charting Purposes
B61: Duration (hours)
D62: 2010 | F62: 12 | H62: 14 | J62: 16 | L62: 18 | O62: 21
B63: Min | C63: Min | D63: =D51 -> 0.66666667 | E63: =E51 -> 0.15 | F63: =F51 -> 0.25 | G63: =G51 -> 0.16666667 | H63: =H51 -> 0.31764706 | I63: =I51 -> 0.25 | J63: =J51 -> 0.25 | K63: =K51 -> 0.15666667 | ... O63: =O51 -> 0.21818182
B64: Min to Q1 | C64: Min to Q1 | D64: =D47-D63 -> #N/A | E64: =E47-E63 -> 0.1 | F64: =F47-F63 -> 0.19545455 | G64: =G47-G63 -> 0.086666667 | H64: =H47-H63 -> 0.50735294 | I64: =I47-I63 -> 0.25 | J64: =J47-J63 -> 0.23333333 | K64: =K47-K63 -> 0.34333333 | ... O64: =O47-O63 -> 0.88734582
B65: Q1 to Q4 | C65: Q1 to Q4 | D65: =D49-D47 -> #N/A | E65: =E49-E47 -> 1.4166667 | F65: =F49-F47 -> 0.88954545 | G65: =G49-G47 -> 1.7466667 | H65: =H49-H47 -> 1.6416667 | I65: =I49-I47 -> 1.2981651 | J65: =J49-J47 -> 1.429235 | K65: =K49-K47 -> 1.8229167 | ... O65: =O49-O47 -> 1.8944724
B66: Q4 to Max | C66: Q4 to Max | D66: =D53-D49 -> #N/A | E66: =E53-E49 -> 2.3333333 | F66: =F53-F49 -> 1.665 | G66: =G53-G49 -> 3 | H66: =H53-H49 -> 5.2 | I66: =I53-I49 -> 2.3968349 | J66: =J53-J49 -> 2.0874317 | K66: =K53-K49 -> 4.1770833 | ... O66: =O53-O49 -> 4.1157025
B69: Power output (MW)
D70: 2010 | F70: 12 | H70: 14 | J70: 16 | L70: 18 | O70: 21
B71: Min | C71: Min | D71: =D50 -> 0.05 | E71: =E50 -> 0.02 | F71: =F50 -> 0.01 | G71: =G50 -> 0.02 | H71: =H50 -> 0.02 | I71: =I50 -> 0.02 | J71: =J50 -> 0.07 | K71: =K50 -> 0.03 | ... O71: =O50 -> 0.1
B72: Min to Q1 | C72: Min to Q1 | D72: =D46-D50 -> 0.025 | E72: =E46-E50 -> 0.03 | F72: =F46-F50 -> 0.04 | G72: =G46-G50 -> 0.1025 | H72: =H46-H50 -> 0.23 | I72: =I46-I50 -> 0.31 | J72: =J46-J50 -> 0.38 | K72: =K46-K50 -> 0.47 | ... O72: =O46-O50 -> 2.2
B73: Q1 to Q4 | C73: Q1 to Q4 | D73: =D48-D46 -> 0.525 | E73: =E48-E46 -> 1.95 | F73: =F48-F46 -> 0.775 | G73: =G48-G46 -> 0.5475 | H73: =H48-H46 -> 1.335 | I73: =I48-I46 -> 1.37 | J73: =J48-J46 -> 7.05 | K73: =K48-K46 -> 5.3 | ... O73: =O48-O46 -> 17.7
B74: Q4 to Max | C74: Q4 to Max | D74: =D52-D48 -> 0.9 | E74: =E52-E48 -> 19.33 | F74: =F52-F48 -> 10.175 | G74: =G52-G48 -> 4.33 | H74: =H52-H48 -> 26.415 | I74: =I52-I48 -> 98.3 | J74: =J52-J48 -> 42.9 | K74: =K52-K48 -> 60.87 | ... O74: =O52-O48 -> 380

Sheet APAC spotlight -->
F1: APAC spotlight

Sheet Central bank base rates
F1: Central bank base rates
A3: Dataset | B3: Central bank base rates
A4: Units | B4: As indicated
A5: Source | B5: BloombergNEF
A6: Subject to terms and conditions
B8: Central bank base rates | K8: Impact of central bank base rates on utility-scale PV LCOE
B37: Central bank base rate | J37: Base rate versus utility-scale PV LCOE
B38: Basis points | J38: $/MWh (nominal)
B39: Date | C39: India | D39: Australia | E39: Green | F39: Yellow | G39: Red | L39: India | M39: Australia | N39: Label
B40: Ticker --> | C40: INRPYLPD Index (L1) | D40: RBATCTR Index (R1) | J40: 1H 2022 | K40: 400bps | L40: 33.431939 | N40: 33.431939
B41: 41640 | C41: 775 | E41: 1 | J41: June hike | K41: 490bps | L41: 34.635784 | N41: 34.635784
B42: 41641 | C42: 775 | E42: 1 | J42: 1H 2022 | K42: 10bps | L42: 0 | M42: 48.151525 | N42: 48.151525
B43: 41642 | C43: 775 | E43: 1 | J43: June hike | K43: 85bps | L43: 0 | M43: 49.168846 | N43: 49.168846
B44: 41643 | C44: 775 | E44: 1
B45: 41644 | C45: 775 | E45: 1
B46: 41645 | C46: 775 | E46: 1
B47: 41646 | C47: 775 | E47: 1
B48: 41647 | C48: 775 | E48: 1
B49: 41648 | C49: 775 | E49: 1
B50: 41649 | C50: 775 | E50: 1
B51: 41650 | C51: 775 | E51: 1
B52: 41651 | C52: 775 | E52: 1
B53: 41652 | C53: 775 | E53: 1
B54: 41653 | C54: 775 | E54: 1
B55: 41654 | C55: 775 | E55: 1
... B74: 41673 | C74: 800 | E74: 1
B75: 41674 | C75: 800 | D75: 250 | E75: 1
B76: 41675 | C76: 800 | E76: 1
B77: 41676 | C77: 800 | E77: 1
B78: 41677 | C78: 800 | E78: 1
B79: 41678 | C79: 800 | E79: 1
B80: 41679 | C80: 800 | E80: 1
B81: 41680 | C81: 800 | E81: 1
B82: 41681 | C82: 800 | E82: 1
B83: 41682 | C83: 800 | E83: 1
B84: 41683 | C84: 800 | E84: 1
B85: 41684 | C85: 800 | E85: 1
B86: 41685 | C86: 800 | E86: 1
B87: 41686 | C87: 800 | E87: 1
... B102: 41701 | C102: 800 | E102: 1
B103: 41702 | C103: 800 | D103: 250 | E103: 1
B104: 41703 | C104: 800 | E104: 1
B105: 41704 | C105: 800 | E105: 1
B106: 41705 | C106: 800 | E106: 1
B107: 41706 | C107: 800 | E107: 1
B108: 41707 | C108: 800 | E108: 1
B109: 41708 | C109: 800 | E109: 1
B110: 41709 | C110: 800 | E110: 1
B111: 41710 | C111: 800 | E111: 1
B112: 41711 | C112: 800 | E112: 1
B113: 41712 | C113: 800 | E113: 1
B114: 41713 | C114: 800 | E114: 1
B115: 41714 | C115: 800 | E115: 1
... B130: 41729 | C130: 800 | E130: 1
B131: 41730 | C131: 800 | D131: 250 | E131: 1
B132: 41731 | C132: 800 | E132: 1
B133: 41732 | C133: 800 | E133: 1
B134: 41733 | C134: 800 | E134: 1
B135: 41734 | C135: 800 | E135: 1
B136: 41735 | C136: 800 | E136: 1
B137: 41736 | C137: 800 | E137: 1
B138: 41737 | C138: 800 | E138: 1
B139: 41738 | C139: 800 | E139: 1
B140: 41739 | C140: 800 | E140: 1
B141: 41740 | C141: 800 | E141: 1
B142: 41741 | C142: 800 | E142: 1
B143: 41742 | C143: 800 | E143: 1
... B165: 41764 | C165: 800 | E165: 1
B166: 41765 | C166: 800 | D166: 250 | E166: 1
B167: 41766 | C167: 800 | E167: 1
B168: 41767 | C168: 800 | E168: 1
B169: 41768 | C169: 800 | E169: 1
B170: 41769 | C170: 800 | E170: 1
B171: 41770 | C171: 800 | E171: 1
B172: 41771 | C172: 800 | E172: 1
B173: 41772 | C173: 800 | E173: 1
B174: 41773 | C174: 800 | E174: 1
B175: 41774 | C175: 800 | E175: 1
B176: 41775 | C176: 800 | E176: 1
B177: 41776 | C177: 800 | E177: 1
B178: 41777 | C178: 800 | E178: 1
... B193: 41792 | C193: 800 | E193: 1
B194: 41793 | C194: 800 | D194: 250 | E194: 1
B195: 41794 | C195: 800 | E195: 1
B196: 41795 | C196: 800 | E196: 1
B197: 41796 | C197: 800 | E197: 1
B198: 41797 | C198: 800 | E198: 1
B199: 41798 | C199: 800 | E199: 1
B200: 41799 | C200: 800 | E200: 1
B201: 41800 | C201: 800 | E201: 1
B202: 41801 | C202: 800 | E202: 1
B203: 41802 | C203: 800 | E203: 1
B204: 41803 | C204: 800 | E204: 1
B205: 41804 | C205: 800 | E205: 1
B206: 41805 | C206: 800 | E206: 1
... B221: 41820 | C221: 800 | E221: 1
B222: 41821 | C222: 800 | D222: 250 | E222: 1
B223: 41822 | C223: 800 | E223: 1
B224: 41823 | C224: 800 | E224: 1
B225: 41824 | C225: 800 | E225: 1
...

Sheet PV module imports, India
F1: PV module imports, India
A3: Dataset | B3: PV module imports, India
A4: Units | B4: GW
A5: Source | B5: Sinoimex, BloombergNEF
A6: Subject to terms and conditions
B37: PV module imports, India
B38: MW | C38: Capacity
B39: 44197 | C39: 0.65497574
B40: 44228 | C40: 0.76945847
B41: 44256 | C41: 1.7525042
B42: 44287 | C42: 0.81422406
B43: 44317 | C43: 0.93059256
B44: 44348 | C44: 1.1365474
B45: 44378 | C45: 0.91790593
B46: 44409 | C46: 0.7409011
B47: 44440 | C47: 1.4950885
B48: 44470 | C48: 1.9118186
B49: 44501 | C49: 1.9877723
B50: 44531 | C50: 1.4756976
... B54: 44652 | C54: 0.072083898

Sheet Onshore wind in Vietnam
F1: Onshore wind in Vietnam
A3: Dataset | B3: Onshore wind in Vietnam
A4: Units | B4: MW
A5: Source | B5: BloombergNEF
A6: Subject to terms and conditions
B36: Capacity additions, Vietnam
B37: MW
C38: 2016 | D38: 2017 | E38: 2018 | F38: 2019 | G38: 2020 | H38: 2021
B39: Onshore wind | C39: 24 | D39: 37.88 | E39: 31.5 | F39: 77.55 | G39: 183.59 | H39: 2847

Sheet Dollar exchange rate
F1: Dollar exchange rate
A3: Dataset | B3: Dollar exchange rate
A4: Units | B4: December 31, 2021 = 100
A5: Source | B5: BloombergNEF
A6: Subject to terms and conditions
B36: Exchange rate, APAC
B37: December 31, 2021 = 100
C38: Chinese yuan | D38: Indian rupee | E38: Australian dollar | F38: Japanese yen
B39: Ticker --> | C39: CNY REGN Curncy | D39: INR Curncy | E39: AUD Curncy | F39: JPY Curncy
B40: 44561 | C40: 100 | D40: 100 | E40: 100 | F40: 100 | G40: 100 | H40: 15
B41: 44564 | D41: 99.8941 | E41: 98.9949 | F41: 100.2085 | G41: 100 | H41: 15
B42: 44565 | C42: 100.2596 | D42: 100.2959 | E42: 99.6283 | F42: 100.9385 | G42: 100 | H42: 15
B43: 44566 | C43: 100.1227 | D43: 100.0303 | E43: 99.4217 | F43: 100.895 | G43: 100 | H43: 15
B44: 44567 | C44: 100.4232 | D44: 100.2169 | E44: 98.6094 | F44: 100.6517 | G44: 100 | H44: 15
B45: 44568 | C45: 100.3414 | D45: 99.9579 | E45: 98.871 | F45: 100.4171 | G45: 100 | H45: 15
B46: 44571 | C46: 100.3162 | D46: 99.5964 | E46: 98.7195 | F46: 100.1043 | G46: 100 | H46: 15
B47: 44572 | C47: 100.2816 | D47: 99.4283 | E47: 99.2703 | F47: 100.1912 | G47: 100 | H47: 15
B48: 44573 | C48: 100.0362 | D48: 99.435 | E48: 100.2891 | F48: 99.6177 | G48: 100 | H48: 15
B49: 44574 | C49: 100.0582 | D49: 99.3913 | E49: 100.2754 | F49: 99.2353 | G49: 100 | H49: 15
B50: 44575 | C50: 99.9465 | D50: 99.7527 | E50: 99.2427 | F50: 99.2266 | G50: 100 | H50: 15
B51: 44578 | C51: 99.8789 | D51: 99.8722 | E51: 99.3667 | F51: 99.609 | G51: 100 | H51: 15
B52: 44579 | C52: 99.9512 | D52: 100.3296 | E52: 98.9261 | F52: 99.5916 | G52: 100 | H52: 15
B53: 44580 | C53: 99.8269 | D53: 100.1262 | E53: 99.284 | F53: 99.3483 | G53: 100 | H53: 15
... B57: 44586 | C57: 99.528 | D57: 100.5901 | E57: 98.4579 | F57: 98.9572 | G57: 100 | H57: 15
B58: 44587 | C58: 99.4462 | E58: 97.9623 | F58: 99.6177 | G58: 100 | H58: 15
B59: 44588 | C59: 100.1904 | D59: 100.9838 | E59: 96.8333 | F59: 100.252 | G59: 100 | H59: 15
B60: 44589 | C60: 100.0802 | D60: 100.945 | E60: 96.2137 | F60: 100.1564 | G60: 100 | H60: 15
B61: 44592 | D61: 100.3834 | E61: 97.3014 | F61: 100.0261 | G61: 100 | H61: 15
B62: 44593 | D62: 100.6239 | E62: 98.155 | F62: 99.6785 | G62: 100 | H62: 15
B63: 44594 | D63: 100.676 | E63: 98.2652 | F63: 99.4612 | G63: 100 | H63: 15
B64: 44595 | D64: 100.7029 | E64: 98.3203 | F64: 99.9044 | G64: 100 | H64: 15
B65: 44596 | D65: 100.4827 | E65: 97.3702 | F65: 100.1564 | G65: 100 | H65: 15
B66: 44599 | C66: 100.0975 | E66: 98.1137 | F66: 100.0174 | G66: 100 | H66: 15
B67: 44600 | C67: 100.1636 | D67: 100.5532 | E67: 98.3891 | F67: 100.4084 | G67: 100 | H67: 15
B68: 44601 | C68: 100.1038 | D68: 100.6322 | E68: 98.8435 | F68: 100.3823 | G68: 100 | H68: 15
B69: 44602 | C69: 99.9685 | D69: 100.8239 | E69: 98.6782 | F69: 100.8081 | G69: 100 | H69: 15
B70: 44603 | C70: 99.9764 | D70: 101.399 | E70: 98.2652 | F70: 100.2954 | G70: 100 | H70: 15
B71: 44606 | C71: 100.0189 | D71: 101.7001 | E71: 98.1275 | F71: 100.3997 | G71: 100 | H71: 15
B72: 44607 | C72: 99.7357 | D72: 101.3468 | E72: 98.4717 | F72: 100.4605 | G72: 100 | H72: 15
B73: 44608 | C73: 99.7026 | D73: 100.9937 | E73: 99.0638 | F73: 100.3823 | G73: 100 | H73: 15
B74: 44609 | C74: 99.7215 | D74: 101.0392 | E74: 98.9536 | F74: 99.8783 | G74: 100 | H74: 15
B75: 44610 | C75: 99.5201 | D75: 100.4372 | E75: 98.8159 | F75: 99.9392 | G75: 100 | H75: 15
B76: 44613 | C76: 99.6712 | D76: 100.2388 | E76: 98.9949 | F76: 99.7046 | G76: 100 | H76: 15
B77: 44614 | C77: 99.5327 | D77: 100.7231 | E77: 99.3942 | F77: 100 | G77: 100 | H77: 15
B78: 44615 | C78: 99.3455 | D78: 100.3078 | E78: 99.6007 | F78: 99.9392 | G78: 100 | H78: 15
... B81: 44620 | C81: 99.2621 | D81: 101.3519 | E81: 100 | F81: 99.9305 | G81: 100 | H81: 15
B82: 44621 | C82: 99.3046 | E82: 99.8485 | F82: 99.861 | G82: 100 | H82: 15
B83: 44622 | C83: 99.4493 | D83: 101.8497 | E83: 100.4681 | F83: 100.3823 | G83: 100 | H83: 15
B84: 44623 | C84: 99.4368 | D84: 102.1153 | E84: 100.9087 | F84: 100.3302 | G84: 100 | H84: 15
B85: 44624 | C85: 99.4258 | D85: 102.4617 | E85: 101.4732 | F85: 99.7741 | G85: 100 | H85: 15
B86: 44627 | C86: 99.4446 | D86: 103.5362 | E86: 100.7435 | F86: 100.2085 | G86: 100 | H86: 15
B87: 44628 | C87: 99.4116 | D87: 103.4639 | E87: 100.0826 | F87: 100.5127 | G87: 100 | H87: 15
B88: 44629 | C88: 99.3943 | D88: 102.9949 | E88: 100.8123 | F88: 100.6517 | G88: 100 | H88: 15
B89: 44630 | C89: 99.4667 | D89: 102.6501 | E89: 101.308 | F89: 100.9211 | G89: 100 | H89: 15
B90: 44631 | C90: 99.7357 | D90: 103.0352 | E90: 100.4131 | F90: 101.9204 | G90: 100 | H90: 15
B91: 44634 | C91: 100.151 | D91: 102.9982 | E91: 98.9674 | F91: 102.7025 | G91: 100 | H91: 15
B92: 44635 | C92: 100.2281 | D92: 103.0588 | E92: 99.0775 | F92: 102.798 | G92: 100 | H92: 15
B93: 44636 | C93: 99.9449 | D93: 102.5929 | E93: 100.3717 | F93: 103.1717 | G93: 100 | H93: 15
B94: 44637 | C94: 99.8568 | D94: 101.9741 | E94: 101.5558 | F94: 103.0587 | G94: 100 | H94: 15
B95: 44638 | C95: 100.0802 | E95: 102.0928 | F95: 103.554 | G95: 100 | H95: 15
B96: 44641 | C96: 99.9969 | D96: 102.4046 | E96: 101.8863 | F96: 103.8147 | G96: 100 | H96: 15
B97: 44642 | C97: 100.1605 | D97: 102.4869 | E97: 102.8501 | F97: 104.9705 | G97: 100 | H97: 15
B98: 44643 | C98: 100.2564 | D98: 102.645 | E98: 103.2493 | F98: 105.2746 | G98: 100 | H98: 15
B99: 44644 | C99: 100.1841 | D99: 102.7375 | E99: 103.4421 | F99: 106.3173 | G99: 100 | H99: 15
B100: 44645 | C100: 100.1589 | D100: 102.5139 | E100: 103.4696 | F100: 106.0567 | G100: 100 | H100: 15
B101: 44648 | C101: 100.2517 | D101: 102.4584 | E101: 103.1117 | F101: 107.6295 | G101: 100 | H101: 15
B102: 44649 | C102: 100.1274 | D102: 102.2196 | E102: 103.387 | F102: 106.7779 | G102: 100 | H102: 15
B103: 44650 | C103: 99.8678 | D103: 102.112 | E103: 103.387 | F103: 105.8655 | G103: 100 | H103: 15
B104: 44651 | C104: 99.7467 | D104: 101.9488 | E104: 103.0153 | F104: 105.7525 | G104: 100 | H104: 15
B105: 44652 | C105: 100.107 | E105: 103.208 | F105: 106.4651 | G105: 100 | H105: 15
B106: 44655 | D106: 101.6244 | E106: 103.8552 | F106: 106.6997 | G106: 100 | H106: 15
B107: 44656 | D107: 101.3318 | E107: 104.3508 | F107: 107.4035 | G107: 100 | H107: 15
B108: 44657 | C108: 100.0582 | D108: 101.9136 | E108: 103.4283 | F108: 107.5773 | G108: 100 | H108: 15
B109: 44658 | C109: 100.0676 | D109: 102.1826 | E109: 102.9877 | F109: 107.7077 | G109: 100 | H109: 15
B110: 44659 | C110: 100.14 | D110: 102.1086 | E110: 102.6848 | F110: 108.0466 | G110: 100 | H110: 15
B111: 44662 | C111: 100.2187 | D111: 102.1826 | E111: 102.1203 | F111: 108.9416 | G111: 100 | H111: 15
B112: 44663 | C112: 100.151 | D112: 102.4196 | E112: 102.6573 | F112: 108.9503 | G112: 100 | H112: 15
B113: 44664 | C113: 100.1904 | D113: 102.4786 | E113: 102.5885 | F113: 109.1588 | G113: 100 | H113: 15
B114: 44665 | C114: 100.3508 | E114: 102.1479 | F114: 109.3848 | G114: 100 | H114: 15
B115: 44666 | C115: 100.2423 | E115: 101.8174 | F115: 109.8888 | G115: 100 | H115: 15
B116: 44669 | C116: 100.1731 | D116: 102.5912 | E116: 101.1841 | F116: 110.3493 | G116: 100 | H116: 15
B117: 44670 | C117: 100.5884 | D117: 102.9174 | E117: 101.5283 | F117: 112.0177 | G117: 100 | H117: 15
B118: 44671 | C118: 100.9927 | D118: 102.5189 | E118: 102.5747 | F118: 111.1053 | G118: 100 | H118: 15
B119: 44672 | C119: 101.4883 | D119: 102.45 | E119: 101.5283 | F119: 111.5572 | G119: 100 | H119: 15
B120: 44673 | C120: 102.286 | D120: 102.8889 | E120: 99.7384 | F120: 111.6615 | G120: 100 | H120: 15
B121: 44676 | C121: 103.1985 | D121: 103.1713 | E121: 98.8297 | F121: 111.3486 | G121: 100 | H121: 15
B122: 44677 | C122: 103.1544 | D122: 103.0166 | E122: 98.0724 | F122: 110.5579 | G122: 100 | H122: 15
B123: 44678 | C123: 103.2174 | D123: 102.9443 | E123: 98.1137 | F123: 111.6006 | G123: 100 | H123: 15
B124: 44679 | C124: 104.2558 | D124: 102.894 | E124: 97.7144 | F124: 113.7035 | G124: 100 | H124: 15
B125: 44680 | C125: 103.971 | D125: 102.8182 | E125: 97.2188 | F125: 112.7042 | G125: 100 | H125: 15
B126: 44683 | D126: 102.9292 | E126: 97.0673 | F126: 113.1039 | G126: 100 | H126: 15
B127: 44684 | E127: 97.7007 | F127: 113.0865 | G127: 100 | H127: 15
B128: 44685 | D128: 102.803 | E128: 99.9587 | F128: 112.1741 | G128: 100 | H128: 15
B129: 44686 | C129: 104.7152 | D129: 102.5895 | E129: 97.921 | F129: 113.1387 | G129: 100 | H129: 15
B130: 44687 | C130: 104.8882 | D130: 103.4875 | E130: 97.4253 | F130: 113.4515 | G130: 100 | H130: 15
B131: 44690 | C131: 105.8951 | D131: 104.2054 | E131: 95.718 | F131: 113.2169 | G131: 100 | H131: 15
B132: 44691 | C132: 105.9565 | D132: 104.0121 | E132: 95.5253 | F132: 113.3559 | G132: 100 | H132: 15
B133: 44692 | C133: 105.752 | D133: 103.9079 | E133: 95.5253 | F133: 112.9388 | G133: 100 | H133: 15
B134: 44693 | C134: 106.7683 | D134: 104.1534 | E134: 94.3963 | F134: 111.5224 | G134: 100 | H134: 15
B135: 44694 | C135: 106.8139 | D135: 104.1803 | E135: 95.5528 | F135: 112.2871 | G135: 100 | H135: 15
...

Sheet Appendix ->
F1: Appendix

Sheet Manual Values MWh
A1: element | B1: Unit new | C1: Unit | D1: 2019 | E1: 2020 | F1: 2021 | G1: 2022 | H1: 2023 | I1: 2024 | J1: 2025 | K1: 2026 | L1: 2027 | M1: 2028 | N1: 2029 | O1: 2030 | P1: 2031 | Q1: 2032 | R1: 2033 | S1: 2034 | T1: 2035 | U1: 2036 | V1: 2037 | W1: 2038 | X1: 2039 | Y1: 2040 | Z1: 2041 | AA1: 2042 | AB1: 2043 | AC1: 2044 | AD1: 2045 | AE1: 2046 | AF1: 2047 | AG1: 2048 | AH1: 2049 | AI1: 2050 | AJ1: Conversion Factor
A2: natural_gas | B2: $/MWh (2021 real) | C2: ='Gas prices'!B33 -> $/MMBtu (2021 real) | D2: {='Gas prices'!E41:AJ41*AJ2} -> 16.139195 | E2: 11.726198 | F2: 55.688543 | G2: 38.356711 | H2: 17.401727 | I2: 16.330485 | J2: 16.7767 | K2: 17.222915 | L2: 17.669129 | M2: 18.115344 | N2: 18.561559 | O2: 19.007773 | P2: 19.147074 | Q2: 19.277382 | R2: 19.40769 | S2: 19.540486 | T2: 19.675817 | U2: 19.784396 | V2: 19.894603 | W2: 20.006463 | X2: 20.120001 | Y2: 20.235242 | Z2: 20.352212 | AA2: 20.470936 | AB2: 20.591441 | AC2: 20.713754 | AD2: 20.837902 | AE2: 20.963911 | AF2: 21.091811 | AG2: 21.221629 | AH2: 21.353395 | AI2: 21.462376 | AJ2: =1/0.293071 -> 3.4121425
A3: hard_coal | B3: $/MWh (2021 real) | C3: ='Coal Prices'!B31 -> $/t (6,000kcal/kg, 2021 real) | D3: {='Coal Prices'!E35:AJ35*AJ3} -> 11.196954 | E3: 8.47592 | F3: 18.38996 | G3: 36.868385 | H3: 26.257166 | I3: 16.521302 | J3: 12.575423 | K3: 10.346453 | L3: 7.3000224 | M3: 8.0574591 | N3: 7.9873012 | O3: 7.9873012 | P3: 7.9696615 | Q3: 7.9696615 | R3: 7.8470513 | S3: 7.7925579 | T3: 7.4519741 | U3: 7.1859425 | V3: 7.1859425 | W3: 7.1859425 | X3: 7.1859425 | Y3: 7.1859425 | Z3: 7.1859425 | AA3: 7.1859425 | AB3: 7.1859425 | AC3: 7.1859425 | AD3: 7.1859425 | AE3: 7.1859425 | AF3: 7.179507 | AG3: 7.179507 | AH3: 7.179507 | AI3: 7.179507 | AJ3: =1/(6*1.16222) -> 0.14340372
A4: oil | B4: $/MWh (2021 real) | C4: ='Oil Prices'!B31 -> $/bbl (2021 real) | D4: {='Oil Prices'!J33:AO33*AJ4} -> 40.091181 | E4: 26.636995 | F4: 42.238922 | G4: 42.823793 | H4: 39.103804 | I4: 36.84737 | J4: 34.684949 | K4: 34.645834 | L4: 34.653928 | M4: 34.625629 | N4: 34.613696 | O4: 34.405836 | P4: 34.402446 | Q4: 34.40221 | R4: 34.403498 | S4: 34.402718 | T4: 34.402809 | U4: 34.403008 | V4: 34.402845 | W4: 34.402887 | X4: 34.402913 | Y4: 34.402882 | Z4: 34.402894 | AA4: 34.402897 | AB4: 34.402891 | AC4: 34.402894 | AD4: 34.402894 | AE4: 34.402893 | AF4: 34.402893 | AG4: 34.402893 | AH4: 34.402893 | AI4: 34.402893 | AJ4: =1/1.6282 -> 0.61417516
A5: lng | B5: $/MWh (2021 real) | C5: ='Gas prices'!B33 -> $/MMBtu (2021 real) | D5: =D2 -> 16.139195 | E5: =E2 -> 11.726198 | F5: =F2 -> 55.688543 | G5: =G2 -> 38.356711 | H5: =H2 -> 17.401727 | I5: =I2 -> 16.330485 | J5: =J2 -> 16.7767 | K5: =K2 -> 17.222915 | ... AJ5: =AJ2 -> 3.4121425

Sheet Carbon Prices
F1: Carbon Prices
A3: Dataset | B3: Carbon price forecast
A4: Units | B4: $/tCO2 (2021 real)
A5: Source | B5: BloombergNEF
A6: Subject to terms and conditions
B30: Carbon price forecasts | AJ30: .
B31: $/tCO2 (2021 real) | C31: 2017 | H31: 2022 | P31: 2030 | U31: 2035 | Z31: 2040 | AE31: 2045 | AJ31: 2050
B32: Country/region | C32: 2017 | D32: 2018 | E32: 2019 | F32: 2020 | G32: 2021 | H32: 2022 | I32: 2023 | J32: 2024 | K32: 2025 | L32: 2026 | M32: 2027 | N32: 2028 | O32: 2029 | P32: 2030 | Q32: 2031 | R32: 2032 | S32: 2033 | T32: 2034 | U32: 2035 | V32: 2036 | W32: 2037 | X32: 2038 | Y32: 2039 | Z32: 2040 | AA32: 2041 | AB32: 2042 | AC32: 2043 | AD32: 2044 | AE32: 2045 | AF32: 2046 | AG32: 2047 | AH32: 2048 | AI32: 2049 | AJ32: 2050
B33: Canada | C33: 0 | D33: 0.50506557 | E33: 14.47 | F33: 20.65 | G33: 28.61 | H33: 34.84 | I33: 44.18 | J33: 53.32 | K33: 61.87 | L33: 70.24 | M33: 79.22 | N33: 87.02 | O33: 94.49 | P33: 101.64 | Q33: 101.64 | R33: 101.64 | S33: 101.64 | T33: 101.64 | U33: 101.64 | V33: 101.64 | W33: 101.64 | X33: 101.64 | Y33: 101.64 | Z33: 101.64 | AA33: 101.64 | AB33: 101.64 | AC33: 101.64 | AD33: 101.64 | AE33: 101.64 | AF33: 101.64 | AG33: 101.64 | AH33: 101.64 | AI33: 101.64 | AJ33: 101.64
B34: China (price felt by power plants) | C34: 0 | D34: 0 | E34: 0 | F34: 0 | G34: 0 | H34: 0 | I34: 0 | J34: 0 | K34: 0 | L34: 2 | M34: 5 | N34: 9 | O34: 14 | P34: 20 | Q34: 20 | R34: 20 | S34: 20 | T34: 20 | U34: 20 | V34: 20 | W34: 20 | X34: 20 | Y34: 20 | Z34: 20 | AA34: 20 | AB34: 20 | AC34: 20 | AD34: 20 | AE34: 20 | AF34: 20 | AG34: 20 | AH34: 20 | AI34: 20 | AJ34: 20
B35: China (ETS market price) | C35: 0 | D35: 0 | E35: 0 | F35: 0 | G35: 7.5 | H35: 8 | I35: 10 | J35: 12 | K35: 14 | L35: 20 | M35: 25 | N35: 30 | O35: 35 | P35: 40 | Q35: 40 | R35: 40 | S35: 40 | T35: 40 | U35: 40 | V35: 40 | W35: 40 | X35: 40 | Y35: 40 | Z35: 40 | AA35: 40 | AB35: 40 | AC35: 40 | AD35: 40 | AE35: 40 | AF35: 40 | AG35: 40 | AH35: 40 | AI35: 40 | AJ35: 40
B36: Europe | C36: 6.8784581 | D36: 19.282996 | E36: 27.893354 | F36: 28.303544 | G36: 62.16211 | H36: 94.614775 | I36: 98.676827 | J36: 101.34956 | K36: 99.309799 | L36: 116.14894 | M36: 119.19624 | N36: 116.86802 | O36: 123.54951 | P36: 131.59922 | Q36: 131.59922 | R36: 131.59922 | S36: 131.59922 | T36: 131.59922 | U36: 131.59922 | V36: 131.59922 | W36: 131.59922 | X36: 131.59922 | Y36: 131.59922 | Z36: 131.59922 | AA36: 131.59922 | AB36: 131.59922 | AC36: 131.59922 | AD36: 131.59922 | AE36: 131.59922 | AF36: 131.59922 | AG36: 131.59922 | AH36: 131.59922 | AI36: 131.59922 | AJ36: 131.59922
B37: United Kingdom | C37: 32.895022 | D37: 33.421479 | E37: 27.955056 | F37: 28.303544 | G37: 62.16211 | H37: 94.614775 | I37: 98.676827 | J37: 101.34956 | K37: 99.309799 | L37: 116.14894 | M37: 119.19624 | N37: 116.86802 | O37: 123.54951 | P37: 131.59922 | Q37: 131.59922 | R37: 131.59922 | S37: 131.59922 | T37: 131.59922 | U37: 131.59922 | V37: 131.59922 | W37: 131.59922 | X37: 131.59922 | Y37: 131.59922 | Z37: 131.59922 | AA37: 131.59922 | AB37: 131.59922 | AC37: 131.59922 | AD37: 131.59922 | AE37: 131.59922 | AF37: 131.59922 | AG37: 131.59922 | AH37: 131.59922 | AI37: 131.59922 | AJ37: 131.59922
B38: California ETS | C38: 15.56 | D38: 15.98 | E38: 17.6 | F38: 17.17 | G38: 23.7 | H38: 29.14 | I38: 30.597 | J38: 32.12685 | K38: 33.733193 | L38: 35.419852 | M38: 37.190845 | N38: 39.050387 | O38: 41.002906 | P38: 41.002906 | Q38: 41.002906 | R38: 41.002906 | S38: 41.002906 | T38: 41.002906 | U38: 41.002906 | V38: 41.002906 | W38: 41.002906 | X38: 41.002906 | Y38: 41.002906 | Z38: 41.002906 | AA38: 41.002906 | AB38: 41.002906 | AC38: 41.002906 | AD38: 41.002906 | AE38: 41.002906 | AF38: 41.002906 | AG38: 41.002906 | AH38: 41.002906 | AI38: 41.002906 | AJ38: 41.002906
B39: PJM - U.S. RGGI | C39: 4.29 | D39: 5.26 | E39: 6.25 | F39: 7.03 | G39: 9.69 | H39: 13.65 | I39: 13.99125 | J39: 14.341031 | K39: 14.699557 | L39: 15.067046 | M39: 15.443722 | N39: 15.829815 | O39: 16.225561 | P39: 16.225561 | Q39: 16.225561 | R39: 16.225561 | S39: 16.225561 | T39: 16.225561 | U39: 16.225561 | V39: 16.225561 | W39: 16.225561 | X39: 16.225561 | Y39: 16.225561 | Z39: 16.225561 | AA39: 16.225561 | AB39: 16.225561 | AC39: 16.225561 | AD39: 16.225561 | AE39: 16.225561 | AF39: 16.225561 | AG39: 16.225561 | AH39: 16.225561 | AI39: 16.225561 | AJ39: 16.225561

Sheet Coal Prices
F1: Coal Prices
A3: Dataset | B3: Coal price forecasts
A4: Units | B4: $/t (6,000kcal/kg, 2021 real)
A5: Source | B5: BloombergNEF
A6: Subject to terms and conditions
B30: Coal price forecasts | AJ30: .
B31: $/t (6,000kcal/kg, 2021 real) | C31: 2017 | F31: 2020 | K31: 2025 | P31: 2030 | U31: 2035 | Z31: 2040 | AE31: 2045 | AJ31: 2050
B32: Country/region | C32: 2017 | D32: 2018 | E32: 2019 | F32: 2020 | G32: 2021 | H32: 2022 | I32: 2023 | J32: 2024 | K32: 2025 | L32: 2026 | M32: 2027 | N32: 2028 | O32: 2029 | P32: 2030 | Q32: 2031 | R32: 2032 | S32: 2033 | T32: 2034 | U32: 2035 | V32: 2036 | W32: 2037 | X32: 2038 | Y32: 2039 | Z32: 2040 | AA32: 2041 | AB32: 2042 | AC32: 2043 | AD32: 2044 | AE32: 2045 | AF32: 2046 | AG32: 2047 | AH32: 2048 | AI32: 2049 | AJ32: 2050
B33: Australia | C33: 83.522743 | D33: 100.65864 | E33: 73.970473 | F33: 55.994497 | G33: 121.48965 | H33: 243.56373 | I33: 173.4628 | J33: 109.14473 | K33: 83.077056 | L33: 68.351803 | M33: 48.226161 | N33: 53.230017 | O33: 52.766533 | P33: 52.766533 | Q33: 52.65 | R33: 52.65 | S33: 51.84 | T33: 51.48 | U33: 49.23 | V33: 47.472515 | W33: 47.472515 | X33: 47.472515 | Y33: 47.472515 | Z33: 47.472515 | AA33: 47.472515 | AB33: 47.472515 | AC33: 47.472515 | AD33: 47.472515 | AE33: 47.472515 | AF33: 47.472515 | AG33: 47.43 | AH33: 47.43 | AI33: 47.43 | AJ33: 47.43
B34: China | C34: 100.4735 | D34: 119.8561 | E34: 89.668824 | F34: 69.335998 | G34: 71.4574 | H34: 281.49764 | I34: 202.2057 | J34: 129.45481 | K34: 99.969381 | L34: 83.313484 | M34: 60.549147 | N34: 66.209064 | O34: 65.684812 | P34: 65.684812 | Q34: 65.553 | R34: 65.553 | S34: 64.6368 | T34: 64.2296 | U34: 61.6846 | V34: 59.696689 | W34: 59.696689 | X34: 59.696689 | Y34: 59.696689 | Z34: 59.696689 | AA34: 59.696689 | AB34: 59.696689 | AC34: 59.696689 | AD34: 59.696689 | AE34: 59.696689 | AF34: 59.696689 | AG34: 59.696689 | AH34: 59.696689 | AI34: 59.696689 | AJ34: 59.696689
B35: Europe | C35: 88.162896 | D35: 106.25078 | E35: 78.079944 | F35: 59.105302 | G35: 128.23907 | H35: 257.09505 | I35: 183.09962 | J35: 115.20832 | K35: 87.692448 | L35: 72.149125 | M35: 50.905393 | N35: 56.187241 | O35: 55.698007 | P35: 55.698007 | Q35: 55.575 | R35: 55.575 | S35: 54.72 | T35: 54.34 | U35: 51.965 | V35: 50.109877 | W35: 50.109877 | X35: 50.109877 | Y35: 50.109877 | Z35: 50.109877 | AA35: 50.109877 | AB35: 50.109877 | AC35: 50.109877 | AD35: 50.109877 | AE35: 50.109877 | AF35: 50.109877 | AG35: 50.065 | AH35: 50.065 | AI35: 50.065 | AJ35: 50.065
B36: India | F36: 57.033603 | G36: 76.122472 | H36: 68.895559 | I36: 62.342562 | J36: 59.723108 | K36: 58.336724 | L36: 56.304789 | M36: 56.793929 | N36: 56.762306 | O36: 56.802398 | P36: 56.854398 | Q36: 56.939822 | R36: 57.207865 | S36: 57.498677 | T36: 57.57893 | U36: 57.6818 | V36: 57.929517 | W36: 58.18517 | X36: 58.450526 | Y36: 58.723816 | Z36: 59.005008 | AA36: 59.29408 | AB36: 59.59102 | AC36: 59.89583 | AD36: 60.208525 | AE36: 60.529134 | AF36: 60.853446 | AG36: 61.190043 | AH36: 61.578039 | AI36: 61.433985 | AJ36: 61.377512
B37: Japan | C37: 110.36256 | D37: 126.71336 | E37: 118.77797 | F37: 89.788953 | G37: 137.35816 | H37: 293.44825 | I37: 214.79595 | J37: 142.7588 | K37: 113.25063 | L37: 96.378639 | M37: 73.550414 | N37: 78.627529 | O37: 77.648937 | P37: 77.200072 | Q37: 76.627536 | R37: 76.196984 | S37: 74.87692 | T37: 74.066042 | U37: 71.165363 | V37: 68.821413 | W37: 68.439401 | X37: 68.066553 | Y37: 67.702546 | Z37: 67.347173 | AA37: 67.00026 | AB37: 66.661584 | AC37: 66.330955 | AD37: 66.008185 | AE37: 65.693083 | AF37: 65.385468 | AG37: 65.037924 | AH37: 64.744755 | AI37: 64.458552 | AJ37: 64.179149
B38: South Korea | C38: 123.29795 | D38: 143.20324 | E38: 120.28705 | F38: 99.848419 | G38: 173.82744 | H38: 308.0226 | I38: 230.59319 | J38: 159.50836 | K38: 130.80624 | L38: 114.54213 | M38: 92.429634 | N38: 98.194372 | O38: 97.864896 | P38: 98.080405 | Q38: 98.154917 | R38: 98.358593 | S38: 97.668438 | T38: 97.476347 | U38: 95.185575 | V38: 93.443921 | W38: 93.655446 | X38: 93.868191 | Y38: 94.08212 | Z38: 94.296999 | AA38: 94.513007 | AB38: 94.730114 | AC38: 94.94829 | AD38: 95.167577 | AE38: 95.387969 | AF38: 95.609466 | AG38: 95.784842 | AH38: 96.008577 | AI38: 96.233438 | AJ38: 96.459433
B39: United States | C39: 52.859317 | D39: 57.267506 | E39: 59.826479 | F39: 51.163655 | G39: 59.872105 | H39: 75.136439 | I39: 68.470909 | J39: 62.30457 | K39: 59.835532 | L39: 58.422699 | M39: 56.491719 | N39: 56.953437 | O39: 56.90899 | P39: 56.90899 | Q39: 56.897815 | R39: 56.897815 | S39: 56.820138 | T39: 56.785615 | U39: 56.569845 | V39: 56.401306 | W39: 56.401306 | X39: 56.401306 | Y39: 56.401306 | Z39: 56.401306 | AA39: 56.401306 | AB39: 56.401306 | AC39: 56.401306 | AD39: 56.401306 | AE39: 56.401306 | AF39: 56.401306 | AG39: 56.397229 | AH39: 56.397229 | AI39: 56.397229 | AJ39: 56.397229
B40: Seaborne benchmark | C40: 92.803048 | D40: 111.84293 | E40: 82.189414 | F40: 62.216108 | G40: 134.9885 | H40: 270.62637 | I40: 192.73644 | J40: 121.27192 | K40: 92.30784 | L40: 75.946448 | M40: 53.584624 | N40: 59.144464 | O40: 58.629481 | P40: 58.629481 | Q40: 58.5 | R40: 58.5 | S40: 57.6 | T40: 57.2 | U40: 54.7 | V40: 52.747239 | W40: 52.747239 | X40: 52.747239 | Y40: 52.747239 | Z40: 52.747239 | AA40: 52.747239 | AB40: 52.747239 | AC40: 52.747239 | AD40: 52.747239 | AE40: 52.747239 | AF40: 52.747239 | AG40: 52.7 | AH40: 52.7 | AI40: 52.7 | AJ40: 52.7

Sheet Oil Prices
F1: Oil Prices
A3: Dataset | B3: Brent price forecasts
A4: Units | B4: $/bbl (2021 real)
A5: Source | B5: BloombergNEF
A6: Subject to terms and conditions
B30: Coal price forecasts | AO30: .
B31: $/bbl (2021 real) | C31: 2012 | F31: 15 | K31: 20 | P31: 25 | U31: 30 | Z31: 35 | AE31: 40 | AJ31: 45 | AO31: 50
B32: Country/region | C32: 2012 | D32: 2013 | E32: 2014 | F32: 2015 | G32: 2016 | H32: 2017 | I32: 2018 | J32: 2019 | K32: 2020 | L32: 2021 | M32: 2022 | N32: 2023 | O32: 2024 | P32: 2025 | Q32: 2026 | R32: 2027 | S32: 2028 | T32: 2029 | U32: 2030 | V32: 2031 | W32: 2032 | X32: 2033 | Y32: 2034 | Z32: 2035 | AA32: 2036 | AB32: 2037 | AC32: 2038 | AD32: 2039 | AE32: 2040 | AF32: 2041 | AG32: 2042 | AH32: 2043 | AI32: 2044 | AJ32: 2045 | AK32: 2046 | AL32: 2047 | AM32: 2048 | AN32: 2049 | AO32: 2050
B33: 2H 2021 | C33: 126.28024 | D33: 120.82605 | E33: 108.36315 | F33: 58.17839 | G33: 48.266233 | H33: 58.125309 | I33: 74.858987 | J33: 65.276461 | K33: 43.370355 | L33: 68.773412 | M33: 69.725699 | N33: 63.668813 | O33: 59.994888 | P33: 56.474035 | Q33: 56.410348 | R33: 56.423526 | S33: 56.377449 | T33: 56.358019 | U33: 56.019582 | V33: 56.014063 | W33: 56.013679 | X33: 56.015775 | Y33: 56.014506 | Z33: 56.014653 | AA33: 56.014978 | AB33: 56.014712 | AC33: 56.014781 | AD33: 56.014824 | AE33: 56.014772 | AF33: 56.014792 | AG33: 56.014796 | AH33: 56.014787 | AI33: 56.014792 | AJ33: 56.014792 | AK33: 56.01479 | AL33: 56.014791 | AM33: 56.014791 | AN33: 56.014791 | AO33: 56.014791
B34: 1H 2022 | C34: 127.85622 | D34: 122.33396 | E34: 109.71552 | F34: 58.904457 | G34: 48.868596 | H34: 58.850713 | I34: 75.793227 | J34: 66.091111 | K34: 43.911617 | L34: 57.034066 | M34: 74.196425 | N34: 68.311548 | O34: 69.382205 | P34: 66.10736 | Q34: 63.306577 | R34: 60.699598 | S34: 58.098222 | T34: 55.60892 | U34: 53.21583 | V34: 53.210017 | W34: 53.209213 | X34: 53.211687 | Y34: 53.210306 | Z34: 53.210402 | AA34: 53.210798 | AB34: 53.210502 | AC34: 53.210567 | AD34: 53.210622 | AE34: 53.210564 | AF34: 53.210585 | AG34: 53.21059 | AH34: 53.21058 | AI34: 53.210585 | AJ34: 53.210585 | AK34: 53.210583 | AL34: 53.210584 | AM34: 53.210584 | AN34: 53.210584 | AO34: 53.210584

Sheet Gas prices
F1: Gas prices
A3: Dataset | B3: Natural gas prices forecasts. 1H 2022
A4: Units | B4: $/MMBtu (2021 real)
A5: Source | B5: BloombergNEF
A6: Subject to terms and conditions
B8: U.S. | J8: EU | R8: APAC
B32: Natural gas prices | AJ32: .
B33: $/MMBtu (2021 real) | E33: 2019 | H33: 22 | K33: 25 | P33: 30 | U33: 35 | Z33: 40 | AE33: 45 | AJ33: 50
B34: Country | C34: Scenario | D34: Semester | E34: 2019 | F34: 2020 | G34: 2021 | H34: 2022 | I34: 2023 | J34: 2024 | K34: 2025 | L34: 2026 | M34: 2027 | N34: 2028 | O34: 2029 | P34: 2030 | Q34: 2031 | R34: 2032 | S34: 2033 | T34: 2034 | U34: 2035 | V34: 2036 | W34: 2037 | X34: 2038 | Y34: 2039 | Z34: 2040 | AA34: 2041 | AB34: 2042 | AC34: 2043 | AD34: 2044 | AE34: 2045 | AF34: 2046 | AG34: 2047 | AH34: 2048 | AI34: 2049 | AJ34: 2050
B35: US | C35: Mid | D35: 2H 2021 | E35: 2.5547127 | F35: 2.0001734 | G35: 3.9322745 | H35: 4.31775 | I35: 3.5651667 | J35: 3.2921667 | K35: 3.1524167 | L35: 3.0984167 | M35: 3.1478333 | N35: 3.2149167 | O35: 3.2575833 | P35: 3.3489167 | Q35: 3.4199167 | R35: 3.4863333 | S35: 3.55275 | T35: 3.6204346 | U35: 3.6894113 | V35: 3.7447525 | W35: 3.8009238 | X35: 3.8579376 | Y35: 3.9158067 | Z35: 3.9745438 | AA35: 4.0341619 | AB35: 4.0946744 | AC35: 4.1560945 | AD35: 4.2184359 | AE35: 4.2817124 | AF35: 4.3459381 | AG35: 4.4111272 | AH35: 4.4772941 | AI35: 4.5444535 | AJ35: 4.6
B36: US | C36: Mid | D36: 1H 2022 | E36: 2.5547127 | F36: 2.0001734 | G36: 3.9645495 | H36: 5.2803333 | I36: 4.1669167 | J36: 3.545 | K36: 3.4488333 | L36: 3.4958866 | M36: 3.5516425 | N36: 3.6273314 | O36: 3.6754714 | P36: 3.7785211 | Q36: 3.8586291 | R36: 3.9335658 | S36: 4.0085025 | T36: 4.0848698 | U36: 4.162695 | V36: 4.242006 | W36: 4.3228312 | X36: 4.4051997 | Y36: 4.4891408 | Z36: 4.5746848 | AA36: 4.6618623 | AB36: 4.7507045 | AC36: 4.8412433 | AD36: 4.9335111 | AE36: 5.0275411 | AF36: 5.123367 | AG36: 5.2210231 | AH36: 5.3205444 | AI36: 5.4219668 | AJ36: 5.5253264
B37: US | C37: PJM | D37: 1H 2022 | E37: 2.4333068 | F37: 1.5933333 | G37: 3.5124513 | H37: 4.6781895 | I37: 3.6917415 | J37: 3.1407452 | K37: 3.055545 | L37: 3.0972325 | M37: 3.1466303 | N37: 3.213688 | O37: 3.2563383 | P37: 3.3476367 | Q37: 3.4186096 | R37: 3.4850009 | S37: 3.5513922 | T37: 3.6190509 | U37: 3.6880013 | V37: 3.758268 | W37: 3.8298763 | X37: 3.9028519 | Y37: 3.9772208 | Z37: 4.0530097 | AA37: 4.1302459 | AB37: 4.208957 | AC37: 4.2891712 | AD37: 4.3709172 | AE37: 4.4542245 | AF37: 4.5391229 | AG37: 4.6256427 | AH37: 4.7138151 | AI37: 4.8036717 | AJ37: 4.8952447
B38: US | C38: New England | D38: 1H 2022 | E38: 3.3190712 | F38: 2.02 | G38: 4.6717699 | H38: 6.2222712 | I38: 4.9102365 | J38: 4.1773786 | K38: 4.0640571 | L38: 4.119504 | M38: 4.185206 | N38: 4.2743968 | O38: 4.3311243 | P38: 4.4525566 | Q38: 4.5469548 | R38: 4.6352592 | S38: 4.7235635 | T38: 4.8135536 | U38: 4.9052618 | V38: 4.9987207 | W38: 5.0939641 | X38: 5.1910259 | Y38: 5.289941 | Z38: 5.3907448 | AA38: 5.4934735 | AB38: 5.598164 | AC38: 5.7048536 | AD38: 5.8135808 | AE38: 5.9243844 | AF38: 6.0373043 | AG38: 6.1523809 | AH38: 6.2696554 | AI38: 6.3891701 | AJ38: 6.5109676
B39: US | C39: Range | D39: 1H 2022 | E39: =E38-E37 -> 0.8857644 | F39: =F38-F37 -> 0.42666667 | G39: =G38-G37 -> 1.1593185 | H39: =H38-H37 -> 1.5440817 | I39: =I38-I37 -> 1.218495 | J39: =J38-J37 -> 1.0366334 | K39: =K38-K37 -> 1.0085122 | L39: =L38-L37 -> 1.0222716 | ... AJ39: =AJ38-AJ37 -> 1.6157229
B40: U.K. | C40: TTF | D40: 1H 2022 | E40: 4.7889595 | F40: 3.4794973 | G40: 18.718538 | H40: 32.106575 | I40: 24.501271 | J40: 5.07675 | K40: 5.2002333 | L40: 5.3237166 | M40: 5.4471998 | N40: 5.5706831 | O40: 5.6941664 | P40: 5.8176497 | Q40: 5.8637117 | R40: 5.9068004 | S40: 5.949889 | T40: 5.9938001 | U40: 6.0385496 | V40: 6.0841534 | W40: 6.1306279 | X40: 6.1779898 | Y40: 6.226256 | Z40: 6.2754438 | AA40: 6.29 | AB40: 6.29 | AC40: 6.29 | AD40: 6.29 | AE40: 6.29 | AF40: 6.29 | AG40: 6.29 | AH40: 6.29 | AI40: 6.29 | AJ40: 6.29
B41: U.K. | C41: TTF | D41: 2H 2021 | E41: 4.72993 | F41: 3.4366085 | G41: 16.320697 | H41: 11.24124 | I41: 5.0999417 | J41: 4.7859917 | K41: 4.9167642 | L41: 5.0475368 | M41: 5.1783094 | N41: 5.3090819 | O41: 5.4398545 | P41: 5.5706271 | Q41: 5.6114521 | R41: 5.6496417 | S41: 5.6878313 | T41: 5.7267499 | U41: 5.7664115 | V41: 5.7982327 | W41: 5.8305312 | X41: 5.8633141 | Y41: 5.8965888 | Z41: 5.9303627 | AA41: 5.9646431 | AB41: 5.9994378 | AC41: 6.0347543 | AD41: 6.0706006 | AE41: 6.1069847 | AF41: 6.1439144 | AG41: 6.1813981 | AH41: 6.2194441 | AI41: 6.2580608 | AJ41: 6.29
B42: Australia | C42: Mid | D42: 1H 2022 | E42: 5.5025959 | F42: 4.6457436 | G42: 5.8804942 | H42: 7.0351639 | I42: 6.2521569 | J42: 6.4228246 | K42: 6.4296988 | L42: 6.4464275 | M42: 6.45114 | N42: 6.4725081 | O42: 6.4833488 | P42: 6.5088971 | Q42: 6.5470745 | R42: 6.5824794 | S42: 6.6176946 | T42: 6.6539494 | U42: 6.6906652 | V42: 6.7280339 | W42: 6.7661486 | X42: 6.8049084 | Y42: 6.8443768 | Z42: 6.8845728 | AA42: 6.9000223 | AB42: 6.905064 | AC42: 6.9101108 | AD42: 6.9151596 | AE42: 6.9202127 | AF42: 6.9252697 | AG42: 6.9303301 | AH42: 6.9353944 | AI42: 6.9404624 | AJ42: 6.945534
B43: China | C43: Mid | D43: 1H 2022 | E43: 7.2948106 | F43: 7.2273793 | G43: 7.8488755 | H43: 8.0010691 | I43: 7.761461 | J43: 7.5973466 | K43: 7.5565608 | L43: 7.52664 | M43: 7.4863332 | N43: 7.4081123 | O43: 7.3414533 | P43: 7.1142676 | Q43: 7.0159939 | R43: 6.9368053 | S43: 6.8627615 | T43: 6.883468 | U43: 6.906363 | V43: 6.930201 | W43: 7.0484849 | X43: 7.1221186 | Y43: 7.1495994 | Z43: 7.1956112 | AA43: 7.1589021 | AB43: 7.1505807 | AC43: 7.1421445 | AD43: 7.1335929 | AE43: 7.1249209 | AF43: 7.1161255 | AG43: 7.1072036 | AH43: 7.0981515 | AI43: 7.0889657 | AJ43: 7.0796425
B44: India | C44: Mid | D44: 1H 2022 | E44: 6.9469157 | F44: 5.6754738 | G44: 6.5879682 | H44: 12.000449 | I44: 12.219957 | J44: 8.3177296 | K44: 6.0471582 | L44: 6.3280462 | M44: 6.6138246 | N44: 6.8285485 | O44: 7.1176035 | P44: 7.2466048 | Q44: 7.4756222 | R44: 7.7225528 | S44: 7.955951 | T44: 8.1809134 | U44: 8.3830701 | V44: 8.3839685 | W44: 8.3844309 | X44: 8.3828092 | Y44: 8.3901152 | Z44: 8.390821 | AA44: 8.3903953 | AB44: 8.3893138 | AC44: 8.3882734 | AD44: 8.3872735 | AE44: 8.3863119 | AF44: 8.3860739 | AG44: 8.3858382 | AH44: 8.3856049 | AI44: 8.3853739 | AJ44: 8.3851451
B45: Japan | C45: Mid | D45: 1H 2022 | E45: 9.883198 | F45: 7.6897513 | G45: 10.016347 | H45: 15.346736 | I45: 11.58984 | J45: 10.040191 | K45: 9.892421 | L45: 9.6999272 | M45: 9.8275541 | N45: 9.4080549 | O45: 9.2241217 | P45: 9.061012 | Q45: 9.082892 | R45: 9.0381636 | S45: 9.0100654 | T45: 9.1031961 | U45: 9.0226579 | V45: 9.0327125 | W45: 9.119647 | X45: 8.9907221 | Y45: 9.0047823 | Z45: 8.808379 | AA45: 8.8791117 | AB45: 8.8987159 | AC45: 8.9378749 | AD45: 8.9395746 | AE45: 8.9370326 | AF45: 8.9340625 | AG45: 8.9275812 | AH45: 8.9161706 | AI45: 8.9052065 | AJ45: 8.892914
B46: Australia | C46: Mid | D46: 2H 2021 | E46: 5.1826197 | F46: 4.5449005 | G46: 5.5074333 | H46: 5.6762932 | I46: 5.8433602 | J46: 5.5799808 | K46: 5.4060236 | L46: 5.4726588 | M46: 5.5614234 | N46: 5.6608393 | O46: 5.7520502 | P46: 5.8560041 | Q46: 5.8820599 | R46: 5.9059487 | S46: 5.9297141 | T46: 5.9541894 | U46: 5.9790459 | V46: 5.9987208 | W46: 6.018751 | X46: 6.0390767 | Y46: 6.0597319 | Z46: 6.0807237 | AA46: 6.1020457 | AB46: 6.1237097 | AC46: 6.14572 | AD46: 6.1680802 | AE46: 6.1907967 | AF46: 6.2138747 | AG46: 6.2373193 | AH46: 6.2611363 | AI46: 6.285331 | AJ46: 6.3051153
B47: China | C47: Mid | D47: 2H 2021 | E47: 7.287211 | F47: 7.217575 | G47: 7.8853645 | H47: 7.8775004 | I47: 7.7740369 | J47: 7.7279741 | K47: 7.6879398 | L47: 7.6241825 | M47: 7.6235924 | N47: 7.5589755 | O47: 7.5370802 | P47: 7.3973121 | Q47: 7.3226518 | R47: 7.2416586 | S47: 7.1614246 | T47: 7.1894411 | U47: 7.2203728 | V47: 7.286402 | W47: 7.3003445 | X47: 7.3573044 | Y47: 7.3820224 | Z47: 7.4195634 | AA47: 7.3898411 | AB47: 7.3931839 | AC47: 7.396469 | AD47: 7.399695 | AE47: 7.4028557 | AF47: 7.4059472 | AG47: 7.4089652 | AH47: 7.4119044 | AI47: 7.4147602 | AJ47: 7.4161036
B48: India | C48: Mid | D48: 2H 2021 | E48: 6.8817354 | F48: 5.6200123 | G48: 6.3794691 | H48: 7.1645296 | I48: 6.0322632 | J48: 5.5026993 | K48: 5.3417415 | L48: 5.6937581 | M48: 6.0439474 | N48: 6.344191 | O48: 6.7043477 | P48: 6.891627 | Q48: 7.173017 | R48: 7.4457971 | S48: 7.7046216 | T48: 7.9541247 | U48: 8.1778363 | V48: 8.1780262 | W48: 8.1778189 | X48: 8.1711798 | Y48: 8.1772853 | Z48: 8.1774971 | AA48: 8.1781337 | AB48: 8.1788333 | AC48: 8.1795949 | AD48: 8.1804182 | AE48: 8.1813017 | AF48: 8.1828607 | AG48: 8.1844485 | AH48: 8.1860653 | AI48: 8.1877116 | AJ48: 8.1890394
B49: Japan | C49: Mid | D49: 2H 2021 | E49: 9.8087136 | F49: 7.6255652 | G49: 11.399148 | H49: 11.224533 | I49: 9.6202584 | J49: 9.0806949 | K49: 8.8899025 | L49: 8.9247184 | M49: 9.2994824 | N49: 9.1203283 | O49: 9.1618314 | P49: 9.1729495 | Q49: 9.2113249 | R49: 9.1554446 | S49: 9.0582593 | T49: 9.1516899 | U49: 9.025251 | V49: 8.9863336 | W49: 9.0676608 | X49: 8.9423561 | Y49: 8.9505544 | Z49: 8.7797974 | AA49: 8.7397059 | AB49: 8.7561297 | AC49: 8.7724076 | AD49: 8.7999206 | AE49: 8.8288424 | AF49: 8.8583272 | AG49: 8.8814553 | AH49: 8.9040036 | AI49: 8.9271329 | AJ49: 8.9435383

Sheet PV Capex
F1: PV capex forecast
A3: Dataset | B3: PV capex forecasts 2021-50, select countries
A4: Units | B4: $m/MW (2021 real)
A5: Source | B5: BloombergNEF
A6: Subject to terms and conditions
B30: Fixed-axis PV Capex | AF30: .
B31: $m/MW (2021 real) | D31: 2022 | G31: 2025 | L31: 2030 | Q31: 2035 | V31: 2040 | AA31: 2045 | AF31: 2050
B32: Forecast | D32: 2022 | E32: 2023 | F32: 2024 | G32: 2025 | H32: 2026 | I32: 2027 | J32: 2028 | K32: 2029 | L32: 2030 | M32: 2031 | N32: 2032 | O32: 2033 | P32: 2034 | Q32: 2035 | R32: 2036 | S32: 2037 | T32: 2038 | U32: 2039 | V32: 2040 | W32: 2041 | X32: 2042 | Y32: 2043 | Z32: 2044 | AA32: 2045 | AB32: 2046 | AC32: 2047 | AD32: 2048 | AE32: 2049 | AF32: 2050
B33: Global benchmark | D33: 0.71645814 | E33: 0.63615473 | F33: 0.58535884 | G33: 0.55749026 | H33: 0.53349067 | I33: 0.51521696 | J33: 0.49841992 | K33: 0.48277255 | L33: 0.46808446 | M33: 0.45544003 | N33: 0.44380838 | O33: 0.43300879 | P33: 0.42290719 | Q33: 0.41340149 | R33: 0.40441227 | S33: 0.39587649 | T33: 0.3877433 | U33: 0.37997103 | V33: 0.37252511 | W33: 0.36537648 | X33: 0.35850048 | Y33: 0.35187592 | Z33: 0.34548448 | AA33: 0.33931017 | AB33: 0.33333892 | AC33: 0.32755826 | AD33: 0.32195709 | AE33: 0.31652542 | AF33: 0.31125429
B34: Japan | D34: 1.3505437 | E34: 1.05603 | F34: 0.91449919 | G34: 0.82574106 | H34: 0.76287175 | I34: 0.71507393 | J34: 0.67700555 | K34: 0.64567132 | L34: 0.61923858 | M34: 0.60311568 | N34: 0.58803876 | O34: 0.57382702 | P34: 0.56036652 | Q34: 0.54755541 | R34: 0.53531686 | S34: 0.52359231 | T34: 0.51233132 | U34: 0.50149316 | V34: 0.491044 | W34: 0.48095465 | X34: 0.47120026 | Y34: 0.4617593 | Z34: 0.45261284 | AA34: 0.4437442 | AB34: 0.43513853 | AC34: 0.42678248 | AD34: 0.41866403 | AE34: 0.41077224 | AF34: 0.40309714
B35: U.S. | D35: 0.90441507 | E35: 0.77956349 | F35: 0.74002426 | G35: 0.64964262 | H35: 0.63281393 | I35: 0.60645158 | J35: 0.5900001 | K35: 0.5453401 | L35: 0.50068009 | M35: 0.45602008 | N35: 0.41136007 | O35: 0.40135008 | P35: 0.39198703 | Q35: 0.38317633 | R35: 0.37484434 | S35: 0.36693264 | T35: 0.35939409 | U35: 0.35219008 | V35: 0.34528856 | W35: 0.33866259 | X35: 0.33228931 | Y35: 0.3261491 | Z35: 0.32022496 | AA35: 0.31450208 | AB35: 0.3089674 | AC35: 0.30360939 | AD35: 0.29841773 | AE35: 0.2933832 | AF35: 0.28849745
B36: Germany | D36: 0.6673584 | E36: 0.58723445 | F36: 0.54490182 | G36: 0.51673029 | H36: 0.49448539 | I36: 0.47754774 | J36: 0.46197878 | K36: 0.44747544 | L36: 0.43386124 | M36: 0.42214129 | N36: 0.41136007 | O36: 0.40135008 | P36: 0.39198703 | Q36: 0.38317633 | R36: 0.37484434 | S36: 0.36693264 | T36: 0.35939409 | U36: 0.35219008 | V36: 0.34528856 | W36: 0.33866259 | X36: 0.33228931 | Y36: 0.3261491 | Z36: 0.32022496 | AA36: 0.31450208 | AB36: 0.3089674 | AC36: 0.30360939 | AD36: 0.29841773 | AE36: 0.2933832 | AF36: 0.28849745
B37: India | D37: 0.47057804 | E37: 0.46598844 | F37: 0.46139884 | G37: 0.45680924 | H37: 0.45221964 | I37: 0.44763004 | J37: 0.44304044 | K37: 0.43845084 | L37: 0.43386124 | M37: 0.42214129 | N37: 0.41136007 | O37: 0.40135008 | P37: 0.39198703 | Q37: 0.38317633 | R37: 0.37484434 | S37: 0.36693264 | T37: 0.35939409 | U37: 0.35219008 | V37: 0.34528856 | W37: 0.33866259 | X37: 0.33228931 | Y37: 0.3261491 | Z37: 0.32022496 | AA37: 0.31450208 | AB37: 0.3089674 | AC37: 0.30360939 | AD37: 0.29841773 | AE37: 0.2933832 | AF37: 0.28849745
B38: China | D38: 0.6021956 | E38: 0.57909335 | F38: 0.55810993 | G38: 0.53634907 | H38: 0.52130265 | I38: 0.50647229 | J38: 0.49197275 | K38: 0.47827071 | L38: 0.46544108 | M38: 0.45487244 | N38: 0.44421562 | O38: 0.43390967 | P38: 0.42392401 | Q38: 0.41477757 | R38: 0.40575036 | S38: 0.39768683 | T38: 0.38966146 | U38: 0.38236602 | V38: 0.37497352 | W38: 0.36828924 | X38: 0.36193933 | Y38: 0.35584328 | Z38: 0.35024936 | AA38: 0.34436364 | AB38: 0.33889844 | AC38: 0.3333726 | AD38: 0.32840218 | AE38: 0.32373459 | AF38: 0.31917857
D68: 2021 | E68: 2022 | F68: 2023 | G68: 2024 | H68: 2025 | I68: 2026 | J68: 2027 | K68: 2028 | L68: 2029 | M68: 2030 | N68: 2031 | O68: 2032 | P68: 2033 | Q68: 2034 | R68: 2035 | S68: 2036 | T68: 2037 | U68: 2038 | V68: 2039 | W68: 2040 | X68: 2041 | Y68: 2042 | Z68: 2043 | AA68: 2044 | AB68: 2045 | AC68: 2046 | AD68: 2047 | AE68: 2048 | AF68: 2049 | AG68: 2050
B69: Japan | D69: 1613.0787 | E69: 1350.5437 | F69: 1056.03 | G69: 914.49919 | H69: 825.74106 | I69: 762.87175 | J69: 715.07393 | K69: 677.00555 | L69: 645.67132 | M69: 619.23858 | N69: 603.11568 | O69: 588.03876 | P69: 573.82702 | Q69: 560.36652 | R69: 547.55541 | S69: 535.31686 | T69: 523.59231 | U69: 512.33132 | V69: 501.49316 | W69: 491.044 | X69: 480.95465 | Y69: 471.20026 | Z69: 461.7593 | AA69: 452.61284 | AB69: 443.7442 | AC69: 435.13853 | AD69: 426.78248 | AE69: 418.66403 | AF69: 410.77224 | AG69: 403.09714
B70: United States | D70: 840.35559 | E70: 904.41507 | F70: 779.56349 | G70: 740.02426 | H70: 649.64262 | I70: 632.81393 | J70: 606.45158 | K70: 590.0001 | L70: 545.3401 | M70: 500.68009 | N70: 456.02008 | O70: 411.36007 | P70: 401.35008 | Q70: 391.98703 | R70: 383.17633 | S70: 374.84434 | T70: 366.93264 | U70: 359.39409 | V70: 352.19008 | W70: 345.28856 | X70: 338.66259 | Y70: 332.28931 | Z70: 326.1491 | AA70: 320.22496 | AB70: 314.50208 | AC70: 308.9674 | AD70: 303.60939 | AE70: 298.41773 | AF70: 293.3832 | AG70: 288.49745
B71: Germany | D71: 704.55189 | E71: 667.3584 | F71: 587.23445 | G71: 544.90182 | H71: 516.73029 | I71: 494.48539 | J71: 477.54774 | K71: 461.97878 | L71: 447.47544 | M71: 433.86124 | N71: 422.14129 | O71: 411.36007 | P71: 401.35008 | Q71: 391.98703 | R71: 383.17633 | S71: 374.84434 | T71: 366.93264 | U71: 359.39409 | V71: 352.19008 | W71: 345.28856 | X71: 338.66259 | Y71: 332.28931 | Z71: 326.1491 | AA71: 320.22496 | AB71: 314.50208 | AC71: 308.9674 | AD71: 303.60939 | AE71: 298.41773 | AF71: 293.3832 | AG71: 288.49745
B72: India | D72: 429.09766 | E72: 470.57804 | F72: 465.98844 | G72: 461.39884 | H72: 456.80924 | I72: 452.21964 | J72: 447.63004 | K72: 443.04044 | L72: 438.45084 | M72: 433.86124 | N72: 422.14129 | O72: 411.36007 | P72: 401.35008 | Q72: 391.98703 | R72: 383.17633 | S72: 374.84434 | T72: 366.93264 | U72: 359.39409 | V72: 352.19008 | W72: 345.28856 | X72: 338.66259 | Y72: 332.28931 | Z72: 326.1491 | AA72: 320.22496 | AB72: 314.50208 | AC72: 308.9674 | AD72: 303.60939 | AE72: 298.41773 | AF72: 293.3832 | AG72: 288.49745
B73: China | D73: 570.81317 | E73: 602.1956 | F73: 579.09335 | G73: 558.10993 | H73: 536.34907 | I73: 521.30265 | J73: 506.47229 | K73: 491.97275 | L73: 478.27071 | M73: 465.44108 | N73: 454.87244 | O73: 444.21562 | P73: 433.90967 | Q73: 423.92401 | R73: 414.77757 | S73: 405.75036 | T73: 397.68683 | U73: 389.66146 | V73: 382.36602 | W73: 374.97352 | X73: 368.28924 | Y73: 361.93933 | Z73: 355.84328 | AA73: 350.24936 | AB73: 344.36364 | AC73: 338.89844 | AD73: 333.3726 | AE73: 328.40218 | AF73: 323.73459 | AG73: 319.17857

Sheet PV module price
F1: PV module price
A3: Dataset | B3: PV module price
A4: Units | B4: $/MW, 2021 real
A5: Source | B5: BNEF, Maycock
A6: Subject to terms and conditions
B25: Module prices ($/W) and cumulative capacity (MW)
C26: 1976 | D26: =C26+1 -> 1977 | E26: =D26+1 -> 1978 | F26: =E26+1 -> 1979 | G26: =F26+1 -> 1980 | H26: =G26+1 -> 1981 | I26: =H26+1 -> 1982 | J26: =I26+1 -> 1983 | K26: =J26+1 -> 1984 | ... AV26: =AU26+1 -> 2021
B27: Cumulative manufactured capacity (MW) | C27: 4 | D27: 6.25 | E27: 8.75 | F27: 12.75 | G27: 19.25 | H27: 27 | I27: 39 | J27: 59 | K27: 81 | L27: 107 | M27: 135 | N27: 164 | O27: 198 | P27: 238 | Q27: 285 | R27: 340 | S27: 400 | T27: 460 | U27: 530 | V27: 610 | W27: 699 | X27: 825 | Y27: 978 | Z27: 1179 | AA27: 1469 | AB27: 1766 | AC27: 2133 | AD27: 2621 | AE27: 3665 | AF27: 5132 | AG27: 6621 | AH27: 9392 | AI27: 15939 | AJ27: 24251 | AK27: 42567 | AL27: 71394 | AM27: 102024 | AN27: 143022 | AO27: 188028 | AP27: 244023 | AQ27: 318983 | AR27: 417938 | AS27: 525829 | AT27: 643671 | AU27: 770718 | AV27: 945718
B28: Historic module prices (Maycock) | C28: 98.896895 | D28: 74.603303 | E28: 51.470097 | F28: 38.447345 | G28: 31.579958 | H28: 24.8429 | I28: 22.336274 | J28: 18.894257 | K28: 16.850804 | L28: 15.692794 | M28: 12.610609 | N28: 9.5733719 | O28: 8.5156193 | P28: 9.4101894 | Q28: 10.09442 | R28: 9.8064079 | S28: 9.1730951 | T28: 9.0862586 | U28: 8.1787325 | V28: 7.4290969 | W28: 7.8616772 | X28: 8.2215339 | Y28: 8.1922176 | Z28: 6.9117766 | AA28: 6.6222506 | AB28: 6.8953331 | AC28: 6.210725 | AD28: 5.5206444
B29: c-Si module prices (BNEF) | AE29: 5.4243976 | AF29: 5.5981816 | AG29: 5.8675702 | AH29: 5.3345377 | AI29: 5.6008397 | AJ29: 2.8023576 | AK29: 2.3767392 | AL29: 1.2382754 | AM29: 1.0439238 | AN29: 0.97130135 | AO29: 0.85965903 | AP29: 0.81585878 | AQ29: 0.53324104 | AR29: 0.47089513 | AS29: 0.3337106 | AT29: 0.28945628 | AU29: 0.2732719 | AV29: 0.271
B30: Experience curve | C30: 98.896895 | D30: 79.940728 | E30: 68.091573 | F30: 56.902922 | G30: 46.754581 | H30: 39.789237 | I30: 33.390221 | J30: 27.40915 | K30: 23.56521 | L30: 20.636026 | M30: 18.471089 | N30: 16.834398 | O30: 15.388089 | P30: 14.095558 | Q30: 12.934917 | R30: 11.891156 | S30: 11.004507 | T30: 10.295075 | U30: 9.6227084 | V30: 8.9988378 | W30: 8.4330489 | X30: 7.7922999 | Y30: 7.1851674 | Z30: 6.572524 | AA30: 5.9182512 | AB30: 5.4208045 | AC30: 4.9541092 | AD30: 4.4905837 | AE30: 3.8271591 | AF30: 3.2595785 | AG30: 2.8867494 | AH30: 2.4435064 | AI30: 1.8988458 | AJ30: 1.5544722 | AK30: 1.1887172 | AL30: 0.92895208 | AM30: 0.78355413 | AN30: 0.66699307 | AO30: 0.58541976 | AP30: 0.51699817 | AQ30: 0.4550079 | AR30: 0.40000779 | AS30: 0.35852159 | AT30: 0.32556858 | AU30: 0.2987729 | AV30: 0.271

Sheet Onshore wind capex
F1: Onshore wind capex
A3: Dataset | B3: Onshore wind capex
A4: Units | B4: $/kW (2021 real)
A5: Source | B5: BloombergNEF
A6: Subject to terms and conditions
B30: Onshore wind capex
B31: $/kW (2021 real) | C31: 2022 | F31: 2025 | K31: 2030 | P31: 2035 | U31: 2040 | Z31: 2045 | AE31: 2050
B32: Country | C32: 2022 | D32: 2023 | E32: 2024 | F32: 2025 | G32: 2026 | H32: 2027 | I32: 2028 | J32: 2029 | K32: 2030 | L32: 2031 | M32: 2032 | N32: 2033 | O32: 2034 | P32: 2035 | Q32: 2036 | R32: 2037 | S32: 2038 | T32: 2039 | U32: 2040 | V32: 2041 | W32: 2042 | X32: 2043 | Y32: 2044 | Z32: 2045 | AA32: 2046 | AB32: 2047 | AC32: 2048 | AD32: 2049 | AE32: 2050
B33: Australia | C33: 1463530.9 | D33: 1381289.4 | E33: 1304917.7 | F33: 1293212.6 | G33: 1277594.2 | H33: 1262968.1 | I33: 1249329 | J33: 1232353.4 | K33: 1216455.3 | L33: 1201364.8 | M33: 1188743 | N33: 1176774.5 | O33: 1164721.4 | P33: 1153395.9 | Q33: 1143660.9 | R33: 1136214 | S33: 1129565.7 | T33: 1121805.9 | U33: 1113360.6 | V33: 1107438.4 | W33: 1102027.9 | X33: 1096357.1 | Y33: 1092015.8 | Z33: 1086344.3 | AA33: 1082383.1 | AB33: 1078033 | AC33: 1074470 | AD33: 1070379.2 | AE33: 1066356.3
B34: China | C34: 786426 | D34: 780493.53 | E34: 775448 | F34: 770054.22 | G34: 762303.5 | H34: 754745.82 | I34: 746473.61 | J34: 738379.46 | K34: 730822.48 | L34: 723747.3 | M34: 718098.08 | N34: 712795.98 | O34: 707411.05 | P34: 702424.82 | Q34: 698371.28 | R34: 695687.43 | S34: 693467.54 | T34: 690540.87 | U34: 687164.92 | V34: 685321.67 | W34: 683775.63 | X34: 682049.09 | Y34: 679182.48 | Z34: 675490.15 | AA34: 672862.81 | AB34: 669994.99 | AC34: 667617.55 | AD34: 664913.44 | AE34: 662252.72
B35: Germany | C35: 1718038.4 | D35: 1593591.9 | E35: 1486488.8 | F35: 1474871.9 | G35: 1459324 | H35: 1444060 | I35: 1427329.4 | J35: 1406848.5 | K35: 1387493.2 | L35: 1369168.5 | M35: 1353676.2 | N35: 1338931.5 | O35: 1324130.1 | P35: 1310174.6 | Q35: 1298043.8 | R35: 1288530 | S35: 1279934.7 | T35: 1270094.2 | U35: 1259493.9 | V35: 1251762 | W35: 1244619.9 | X35: 1237195 | Y35: 1231280.5 | Z35: 1223876.3 | AA35: 1218408.8 | AB35: 1212512 | AC35: 1207508.5 | AD35: 1201920 | AE35: 1196415.9
B36: India | C36: 848276.06 | D36: 838926.63 | E36: 828322.29 | F36: 825832.81 | G36: 820252.54 | H36: 814325.38 | I36: 807082.5 | J36: 797107.48 | K36: 787254.71 | L36: 777478.83 | M36: 768804.03 | N36: 757936.85 | O36: 746643.04 | P36: 735447.59 | Q36: 724913.31 | R36: 715481.84 | S36: 706207.15 | T36: 695910.58 | U36: 684887.91 | V36: 675124.16 | W36: 665379.61 | X36: 655200.2 | Y36: 645547.21 | Z36: 634560.72 | AA36: 624055.08 | AB36: 613115.27 | AC36: 602426.8 | AD36: 591261 | AE36: 579971.84
B37: Japan | C37: 2636196.4 | D37: 2356964.2 | E37: 2127464.5 | F37: 2108172.3 | G37: 2082711.4 | H37: 2057577.7 | I37: 2034864.9 | J37: 2006634.3 | K37: 1979982.8 | L37: 1954822.2 | M37: 1933651.4 | N37: 1913532.9 | O37: 1893319.3 | P37: 1874289.6 | Q37: 1857853.9 | R37: 1845149.9 | S37: 1833747.6 | T37: 1820549.1 | U37: 1806247.6 | V37: 1796046.9 | W37: 1786682.5 | X37: 1776902.3 | Y37: 1769282.1 | Z37: 1759512.5 | AA37: 1752518.3 | AB37: 1744899.1 | AC37: 1738558.1 | AD37: 1731367.6 | AE37: 1724291.3
B38: UK | C38: 1538014.9 | D38: 1444251.1 | E38: 1361311.6 | F38: 1351842.8 | G38: 1338236.3 | H38: 1324968.6 | I38: 1310446.6 | J38: 1292360.1 | K38: 1275318.9 | L38: 1259217.2 | M38: 1245684.7 | N38: 1232832.5 | O38: 1219913.2 | P38: 1207755.4 | Q38: 1197267.8 | R38: 1189182.7 | S38: 1181935.5 | T38: 1173529.3 | U38: 1164410.5 | V38: 1157934 | W38: 1151995.5 | X38: 1145787.9 | Y38: 1140972.2 | Z38: 1134769.4 | AA38: 1130355.6 | AB38: 1125537.9 | AC38: 1121544 | AD38: 1117001.3 | AE38: 1112531.5
B39: US | C39: 1548529.2 | D39: 1431676.7 | E39: 1331205.5 | F39: 1323573.1 | G39: 1311365.9 | H39: 1299751.4 | I39: 1286855.5 | J39: 1270350.6 | K39: 1254898.2 | L39: 1240324.7 | M39: 1228242.9 | N39: 1216817.8 | O39: 1205297.8 | P39: 1194505 | Q39: 1185344.5 | R39: 1178544 | S39: 1172559.6 | T39: 1165411 | U39: 1157538 | V39: 1152277.1 | W39: 1147540.2 | X39: 1142524 | Y39: 1138885.8 | Z39: 1133852.8 | AA39: 1130597.9 | AB39: 1126930.7 | AC39: 1124080.4 | AD39: 1120672.5 | AE39: 1117329.7
B40: Min | C40: 726057.35 | D40: 684212.72 | E40: 645009.08 | F40: 640607.04 | G40: 633879.01 | H40: 627679.13 | I40: 620760.61 | J40: 612114.86 | K40: 604029.6 | L40: 596358.39 | M40: 589902.47 | N40: 582926.02 | O40: 575931.23 | P40: 569316.37 | Q40: 563508.13 | R40: 558844.08 | S40: 554586.53 | T40: 549797.9 | U40: 544689.06 | V40: 540828.84 | W40: 537230.1 | X40: 533515.76 | Y40: 530458.71 | Z40: 526765.86 | AA40: 523912.32 | AB40: 520879.34 | AC40: 518235.08 | AD40: 515344.52 | AE40: 512495.19
B41: Max | C41: 2636196.4 | D41: 2356964.2 | E41: 2127464.5 | F41: 2108172.3 | G41: 2082711.4 | H41: 2057577.7 | I41: 2034864.9 | J41: 2006634.3 | K41: 1979982.8 | L41: 1954822.2 | M41: 1933651.4 | N41: 1913532.9 | O41: 1893319.3 | P41: 1874289.6 | Q41: 1857853.9 | R41: 1845149.9 | S41: 1833747.6 | T41: 1820549.1 | U41: 1806247.6 | V41: 1796046.9 | W41: 1786682.5 | X41: 1776902.3 | Y41: 1769282.1 | Z41: 1759512.5 | AA41: 1752518.3 | AB41: 1744899.1 | AC41: 1738558.1 | AD41: 1731367.6 | AE41: 1724291.3
B42: Global range | C42: =C41-C40 -> 1910139.1 | D42: =D41-D40 -> 1672751.5 | E42: =E41-E40 -> 1482455.4 | F42: =F41-F40 -> 1467565.3 | G42: =G41-G40 -> 1448832.4 | H42: =H41-H40 -> 1429898.6 | I42: =I41-I40 -> 1414104.3 | J42: =J41-J40 -> 1394519.5 | ... AE42: =AE41-AE40 -> 1211796.1

Sheet Onshore wind CF
F1: Onshore wind CF
A3: Dataset | B3: Onshore wind capacity factor forecast, China
A4: Units | B4: %
A5: Source | B5: BloombergNEF
A6: Subject to terms and conditions
B30: Onshore wind capacity factor forecast, China | AE30: .
B31: % | C31: 2022 | F31: 2025 | K31: 2030 | P31: 2035 | U31: 2040 | Z31: 2045 | AE31: 2050
B32: Scenario | C32: 2022 | D32: 2023 | E32: 2024 | F32: 2025 | G32: 2026 | H32: 2027 | I32: 2028 | J32: 2029 | K32: 2030 | L32: 2031 | M32: 2032 | N32: 2033 | O32: 2034 | P32: 2035 | Q32: 2036 | R32: 2037 | S32: 2038 | T32: 2039 | U32: 2040 | V32: 2041 | W32: 2042 | X32: 2043 | Y32: 2044 | Z32: 2045 | AA32: 2046 | AB32: 2047 | AC32: 2048 | AD32: 2049 | AE32: 2050
B33: High | C33: 0.35 | D33: 0.38066408 | E33: 0.41132815 | F33: 0.43277679 | G33: 0.44925583 | H33: 0.46286933 | I33: 0.47455809 | J33: 0.48484664 | K33: 0.49406315 | L33: 0.50242874 | M33: 0.51010037 | N33: 0.51719393 | O33: 0.52284799 | P33: 0.52648022 | Q33: 0.52885729 | R33: 0.53094372 | S33: 0.53386228 | T33: 0.53742025 | U33: 0.54074905 | V33: 0.54377263 | W33: 0.5465437 | X33: 0.54912517 | Y33: 0.55157293 | Z33: 0.5539825 | AA33: 0.55641403 | AB33: 0.5588501 | AC33: 0.56122255 | AD33: 0.56348406 | AE33: 0.56566314
B34: Mid | C34: 0.27 | D34: 0.29603059 | E34: 0.32206118 | F34: 0.34037775 | G34: 0.35452058 | H34: 0.36624421 | I34: 0.37633728 | J34: 0.38524099 | K34: 0.39323212 | L34: 0.40049754 | M34: 0.40717015 | N34: 0.41334824 | O34: 0.41832452 | P34: 0.42156405 | Q34: 0.42367751 | R34: 0.42548293 | S34: 0.42787734 | T34: 0.43075654 | U34: 0.43348711 | V34: 0.43605628 | W34: 0.43853103 | X34: 0.44094852 | Y34: 0.4433795 | Z34: 0.44590857 | AA34: 0.44854132 | AB34: 0.45120977 | AC34: 0.4538442 | AD34: 0.45641615 | AE34: 0.45890177
B35: Low | C35: 0.24 | D35: 0.26362953 | E35: 0.28725905 | F35: 0.30390897 | G35: 0.3167796 | H35: 0.32745705 | I35: 0.33665511 | J35: 0.34477341 | K35: 0.35206282 | L35: 0.35869278 | M35: 0.36478386 | N35: 0.37042526 | O35: 0.3748372 | P35: 0.37759687 | Q35: 0.37958649 | R35: 0.38173162 | S35: 0.38491147 | T35: 0.38876215 | U35: 0.39243293 | V35: 0.39589598 | W35: 0.39922374 | X35: 0.40250818 | Y35: 0.40584057 | Z35: 0.40930085 | AA35: 0.41285833 | AB35: 0.41645797 | AC35: 0.42004804 | AD35: 0.42352759 | AE35: 0.42687231
B36: Range | C36: =C33-C35 -> 0.11 | D36: =D33-D35 -> 0.11703455 | E36: =E33-E35 -> 0.1240691 | F36: =F33-F35 -> 0.12886782 | G36: =G33-G35 -> 0.13247623 | H36: =H33-H35 -> 0.13541228 | I36: =I33-I35 -> 0.13790298 | J36: =J33-J35 -> 0.14007322 | ... AE36: =AE33-AE35 -> 0.13879083

Sheet Offshore wind capex
F1: Offshore wind capex
A3: Dataset | B3: Offshore wind capex forecast, global
A4: Units | B4: $m/MW (2021 real)
A5: Source | B5: BloombergNEF
A6: Subject to terms and conditions
B30: Capex global benchmark
B31: $m/MW (2021 real) | D31: 2018 | F31: 2020 | H31: 2022 | J31: 2024 | L31: 2026 | N31: 2028
B32: Financing year | D32: 2018 | E32: 2019 | F32: 2020 | G32: 2021 | H32: 2022 | I32: 2023 | J32: 2024 | K32: 2025 | L32: 2026 | M32: 2027 | N32: 2028
B33: Capex w/o transmission | D33: 2.0751491 | E33: 2.0106367 | F33: 1.9461243 | G33: 1.892364 | H33: 1.8493557 | I33: 1.8278515 | J33: 1.8063474 | K33: 1.7740912 | L33: 1.7525871 | M33: 1.7310829 | N33: 1.7095788
B34: Capex with transmission | D34: 3.0320832 | E34: 2.9675707 | F34: 2.9030583 | G34: 2.7417773 | H34: 2.698769 | I34: 2.6665128 | J34: 2.6450087 | K34: 2.6127525 | L34: 2.5804963 | M34: 2.5589922 | N34: 2.526736

Sheet Offshore wind CF
F1: Offshore wind CF
A3: Dataset | B3: Offshore wind capacity factors, select countries
A4: Units | B4: %
A5: Source | B5: BloombergNEF
A6: Subject to terms and conditions
B30: Offshore wind capacity factors
B31: % | C31: 2022 | F31: 2025 | K31: 2030 | P31: 2035 | U31: 2040 | Z31: 2045 | AE31: 2050
B32: Country | C32: 2022 | D32: 2023 | E32: 2024 | F32: 2025 | G32: 2026 | H32: 2027 | I32: 2028 | J32: 2029 | K32: 2030 | L32: 2031 | M32: 2032 | N32: 2033 | O32: 2034 | P32: 2035 | Q32: 2036 | R32: 2037 | S32: 2038 | T32: 2039 | U32: 2040 | V32: 2041 | W32: 2042 | X32: 2043 | Y32: 2044 | Z32: 2045 | AA32: 2046 | AB32: 2047 | AC32: 2048 | AD32: 2049 | AE32: 2050
B33: U.K. | C33: 0.55 | D33: 0.55 | E33: 0.55 | F33: 0.55 | G33: 0.55 | H33: 0.55 | I33: 0.55 | J33: 0.55 | K33: 0.55 | L33: 0.55 | M33: 0.55 | N33: 0.55 | O33: 0.55 | P33: 0.55 | Q33: 0.55 | R33: 0.55 | S33: 0.55 | T33: 0.55 | U33: 0.55 | V33: 0.55 | W33: 0.55 | X33: 0.55 | Y33: 0.55 | Z33: 0.55 | AA33: 0.55 | AB33: 0.55 | AC33: 0.55004317 | AD33: 0.55033343 | AE33: 0.55104873
B34: U.S. | C34: 0.465 | D34: 0.47258141 | E34: 0.48016282 | F34: 0.48519555 | G34: 0.4888931 | H34: 0.49185589 | I34: 0.49434005 | J34: 0.49648413 | K34: 0.49837281 | L34: 0.50006208 | M34: 0.50159105 | N34: 0.5029882 | O34: 0.50449688 | P34: 0.50645247 | Q34: 0.50896171 | R34: 0.51191594 | S34: 0.51489032 | T34: 0.51755782 | U34: 0.51992085 | V34: 0.52205893 | W34: 0.52412417 | X34: 0.52615694 | Y34: 0.5281185 | Z34: 0.53001186 | AA34: 0.53184049 | AB34: 0.53361375 | AC34: 0.53531079 | AD34: 0.53693302 | AE34: 0.5385118
B35: Germany | C35: 0.49 | D35: 0.50116984 | E35: 0.51233967 | F35: 0.51979227 | G35: 0.52529204 | H35: 0.52971216 | I35: 0.53342689 | J35: 0.53663924 | K35: 0.5394736 | L35: 0.54201235 | M35: 0.54431314 | N35: 0.54641799 | O35: 0.54846305 | P35: 0.55059628 | Q35: 0.55284589 | R35: 0.55516955 | S35: 0.55737183 | T35: 0.55927421 | U35: 0.56084437 | V35: 0.56212069 | W35: 0.56327263 | X35: 0.56442939 | Y35: 0.56567506 | Z35: 0.56711339 | AA35: 0.56875334 | AB35: 0.57055379 | AC35: 0.57238826 | AD35: 0.57415199 | AE35: 0.57580398
B36: China | C36: 0.37 | D36: 0.38875827 | E36: 0.40751654 | F36: 0.4202988 | G36: 0.42990478 | H36: 0.43772111 | I36: 0.44435353 | J36: 0.45013471 | K36: 0.45527038 | L36: 0.45989788 | M36: 0.46411389 | N36: 0.46798933 | O36: 0.47168526 | P36: 0.47540558 | Q36: 0.47925185 | R36: 0.48321838 | S36: 0.48701862 | T36: 0.49036133 | U36: 0.4932301 | V36: 0.4957436 | W36: 0.49815119 | X36: 0.50056354 | Y36: 0.50295805 | Z36: 0.50533638 | AA36: 0.50767229 | AB36: 0.50994305 | AC36: 0.51211522 | AD36: 0.51420217 | AE36: 0.51624203

Sheet Coal capex
F1: Coal capex
A3: Dataset | B3: Coal-fired power plant capex
A4: Units | B4: $m/MW (2021 real)
A5: Source | B5: BloombergNEF
A6: Subject to terms and conditions
B30: Coal-fired power plant capex
B31: $m/MW (2021 real) | C31: 2022 | F31: 2025 | K31: 2030 | P31: 2035 | U31: 2040 | Z31: 2045 | AE31: 2050
B32: Country | C32: 2022 | D32: 2023 | E32: 2024 | F32: 2025 | G32: 2026 | H32: 2027 | I32: 2028 | J32: 2029 | K32: 2030 | L32: 2031 | M32: 2032 | N32: 2033 | O32: 2034 | P32: 2035 | Q32: 2036 | R32: 2037 | S32: 2038 | T32: 2039 | U32: 2040 | V32: 2041 | W32: 2042 | X32: 2043 | Y32: 2044 | Z32: 2045 | AA32: 2046 | AB32: 2047 | AC32: 2048 | AD32: 2049 | AE32: 2050
B33: Japan | C33: 1.8147882 | D33: 1.7992586 | E33: 1.7840063 | F33: 1.778023 | G33: 1.7729006 | H33: 1.767157 | I33: 1.7651636 | J33: 1.7632902 | K33: 1.7612949 | L33: 1.7593452 | M33: 1.75741 | N33: 1.7554543 | O33: 1.7535118 | P33: 1.7515716 | Q33: 1.7496297 | R33: 1.7476925 | S33: 1.7457571 | T33: 1.7438232 | U33: 1.7418919 | V33: 1.7399627 | W33: 1.7380355 | X33: 1.7361106 | Y33: 1.7341877 | Z33: 1.732267 | AA33: 1.7303484 | AB33: 1.7284319 | AC33: 1.7265176 | AD33: 1.7246054 | AE33: 1.7226952
B34: China | C34: 0.52903029 | D34: 0.53595949 | E34: 0.54301049 | F34: 0.5433971 | G34: 0.54398835 | H34: 0.54446007 | I34: 0.54493999 | J34: 0.54545116 | K34: 0.54593558 | L34: 0.54642426 | M34: 0.54691588 | N34: 0.54740098 | O34: 0.54788631 | P34: 0.54837053 | Q34: 0.54885228 | R34: 0.54933293 | S34: 0.54981203 | T34: 0.55028942 | U34: 0.55024626 | V34: 0.54968403 | W34: 0.54912235 | X34: 0.54856127 | Y34: 0.54800075 | Z34: 0.5474408 | AA34: 0.54688143 | AB34: 0.54632263 | AC34: 0.5457644 | AD34: 0.54520674 | AE34: 0.54464965
B35: Poland | C35: 1.7663789 | D35: 1.768081 | E35: 1.7717507 | F35: 1.7712992 | G35: 1.7697933 | H35: 1.7703658 | I35: 1.7699046 | J35: 1.7694401 | K35: 1.7693225 | L35: 1.7689748 | M35: 1.7686651 | N35: 1.7684068 | O35: 1.7681016 | P35: 1.7678107 | Q35: 1.767526 | R35: 1.7672325 | S35: 1.7669428 | T35: 1.7666537 | U35: 1.766363 | V35: 1.7660732 | W35: 1.7657835 | X35: 1.7654935 | Y35: 1.7652038 | Z35: 1.7649141 | AA35: 1.7646243 | AB35: 1.7643347 | AC35: 1.7640451 | AD35: 1.7637556 | AE35: 1.7634661
B36: Indonesia | C36: 1.4404142 | D36: 1.442012 | E36: 1.4412637 | F36: 1.4403593 | G36: 1.4400019 | H36: 1.4393323 | I36: 1.438689 | J36: 1.4381326 | K36: 1.43751 | L36: 1.4369031 | M36: 1.4363083 | N36: 1.4357007 | O36: 1.4350981 | P36: 1.4344969 | Q36: 1.4338936 | R36: 1.4332918 | S36: 1.4326902 | T36: 1.4320884 | U36: 1.4314872 | V36: 1.4308862 | W36: 1.4302854 | X36: 1.4296849 | Y36: 1.4290846 | Z36: 1.4284845 | AA36: 1.4278848 | AB36: 1.4272853 | AC36: 1.426686 | AD36: 1.426087 | AE36: 1.4254882
B37: India | C37: 0.9046956 | D37: 0.91954566 | E37: 0.93193078 | F37: 0.93448776 | G37: 0.93681339 | H37: 0.9383548 | I37: 0.93932858 | J37: 0.93977238 | K37: 0.93958519 | L37: 0.93882056 | M37: 0.93747736 | N37: 0.93378306 | O37: 0.92953376 | P37: 0.92473457 | Q37: 0.91939159 | R37: 0.91351649 | S37: 0.9071188 | T37: 0.90020948 | U37: 0.89280101 | V37: 0.8849061 | W37: 0.87653843 | X37: 0.86771255 | Y37: 0.85844356 | Z37: 0.84796579 | AA37: 0.83632788 | AB37: 0.82434075 | AC37: 0.81202378 | AD37: 0.79939668 | AE37: 0.78647947

Sheet Coal & gas WACC
F1: Coal and gas WACC
A3: Dataset | B3: Coal and gas power WACC
A4: Units | B4: %
A5: Source | B5: BloombergNEF
A6: Subject to terms and conditions
B30: Weighted average cost of capital (WACC), India
B31: % | C31: 2022 | F31: 2025 | K31: 2030 | P31: 2035 | U31: 2040 | Z31: 2045 | AE31: 2050
C32: 2022 | D32: 2023 | E32: 2024 | F32: 2025 | G32: 2026 | H32: 2027 | I32: 2028 | J32: 2029 | K32: 2030 | L32: 2031 | M32: 2032 | N32: 2033 | O32: 2034 | P32: 2035 | Q32: 2036 | R32: 2037 | S32: 2038 | T32: 2039 | U32: 2040 | V32: 2041 | W32: 2042 | X32: 2043 | Y32: 2044 | Z32: 2045 | AA32: 2046 | AB32: 2047 | AC32: 2048 | AD32: 2049 | AE32: 2050
B33: Coal | C33: 0.10713263 | D33: 0.11049726 | E33: 0.11264528 | F33: 0.1142474 | G33: 0.11553387 | H33: 0.11661299 | I33: 0.11754479 | J33: 0.11836621 | K33: 0.11910166 | L33: 0.11976814 | M33: 0.12037801 | N33: 0.12094051 | O33: 0.12146278 | P33: 0.12195043 | Q33: 0.12240795 | R33: 0.12283899 | S33: 0.1232466 | T33: 0.12363328 | U33: 0.12400117 | V33: 0.12435209 | W33: 0.12435209 | X33: 0.12435209 | Y33: 0.12435209 | Z33: 0.12435209 | AA33: 0.12435209 | AB33: 0.12435209 | AC33: 0.12435209 | AD33: 0.12435209 | AE33: 0.12435209
B34: CCGT | C34: 0.10713263 | D34: 0.10752805 | E34: 0.10775618 | F34: 0.10791664 | G34: 0.1080403 | H34: 0.10814082 | I34: 0.10822545 | J34: 0.1082985 | K34: 0.10836273 | L34: 0.10842002 | M34: 0.10847172 | N34: 0.1085188 | O34: 0.10856203 | P34: 0.10860197 | Q34: 0.10863909 | R34: 0.10867376 | S34: 0.10870627 | T34: 0.10873687 | U34: 0.10876578 | V34: 0.10879317 | W34: 0.10879317 | X34: 0.10879317 | Y34: 0.10879317 | Z34: 0.10879317 | AA34: 0.10879317 | AB34: 0.10879317 | AC34: 0.10879317 | AD34: 0.10879317 | AE34: 0.10879317
B35: Inflation | C35: 0.04876 | D35: 0.04317 | E35: 0.0409 | F35: 0.04018 | G35: 0.0395464 | H35: 0.0389128 | I35: 0.0382792 | J35: 0.0376456 | K35: 0.037012 | L35: 0.0363784 | M35: 0.0357448 | N35: 0.0351112 | O35: 0.034477601 | P35: 0.033844001 | Q35: 0.033210401 | R35: 0.032576801 | S35: 0.031943201 | T35: 0.031309601 | U35: 0.030676001 | V35: 0.030042401 | W35: 0.029408801 | X35: 0.028775201 | Y35: 0.028141601 | Z35: 0.027508001 | AA35: 0.026874401 | AB35: 0.026240801 | AC35: 0.025607201 | AD35: 0.024973601 | AE35: 0.024340001

Sheet CCGT efficiency
F1: CCGT efficiency forecast
A3: Dataset | B3: Combined-cycle gas turbine efficiency, 1975-2050
A4: Units | B4: % (High heating value)
A5: Source | B5: BloombergNEF, S. Can Gulen, BloombergNEF U.S. Plant Stack
A6: Subject to terms and conditions
B8: Combined-cycle gas turbine efficiency, 1975-2050
B30: CCGT efficiency (HHV)
D31: 1975 | E31: 1976 | F31: 1977 | G31: 1978 | H31: 1979 | I31: 1980 | J31: 1981 | K31: 1982 | L31: 1983 | M31: 1984 | N31: 1985 | O31: 1986 | P31: 1987 | Q31: 1988 | R31: 1989 | S31: 1990 | T31: 1991 | U31: 1992 | V31: 1993 | W31: 1994 | X31: 1995 | Y31: 1996 | Z31: 1997 | AA31: 1998 | AB31: 1999 | AC31: 2000 | AD31: 2001 | AE31: 2002 | AF31: 2003 | AG31: 2004 | AH31: 2005 | AI31: 2006 | AJ31: 2007 | AK31: 2008 | AL31: 2009 | AM31: 2010 | AN31: 2011 | AO31: 2012 | AP31: 2013 | AQ31: 2014 | AR31: 2015 | AS31: 2016 | AT31: 2017 | AU31: 2018 | AV31: 2019 | AW31: 2020 | AX31: 2021 | AY31: 2022 | AZ31: 2023 | BA31: 2024 | BB31: 2025 | BC31: 2026 | BD31: 2027 | BE31: 2028 | BF31: 2029 | BG31: 2030 | BH31: 2031 | BI31: 2032 | BJ31: 2033 | BK31: 2034 | BL31: 2035 | BM31: 2036 | BN31: 2037 | BO31: 2038 | BP31: 2039 | BQ31: 2040 | BR31: 2041 | BS31: 2042 | BT31: 2043 | BU31: 2044 | BV31: 2045 | BW31: 2046 | BX31: 2047 | BY31: 2048 | BZ31: 2049 | CA31: 2050
B32: U.S. fleet average (operational) | AH32: 0.40556613 | AI32: 0.41114058 | AJ32: 0.41438814 | AK32: 0.41631058 | AL32: 0.42218646 | AM32: 0.42391845 | AN32: 0.42218646 | AO32: 0.42925478 | AP32: 0.42952513 | AQ32: 0.42460466 | AR32: 0.43701141 | AS32: 0.4381344 | AT32: 0.43594988 | AU32: 0.43667563
B33: U.S. best performing (operational, Colorado Bend) | AU33: 0.51666667
B34: Global best performing (test conditions) | D34: 0.445 | E34: #N/A | F34: #N/A | G34: #N/A | H34: #N/A | I34: #N/A | J34: #N/A | K34: #N/A | L34: #N/A | M34: #N/A | N34: 0.43343 | O34: #N/A | P34: 0.44055 | Q34: #N/A | R34: 0.4628 | S34: 0.45568 | T34: 0.46725 | U34: #N/A | V34: #N/A | W34: 0.4895 | X34: 0.48683 | Y34: 0.4984 | Z34: 0.5073 | AA34: 0.50285 | AB34: #N/A | AC34: 0.5073 | AD34: 0.5162 | AE34: #N/A | AF34: #N/A | AG34: 0.5251 | AH34: #N/A | AI34: 0.52065 | AJ34: #N/A | AK34: 0.51887 | AL34: 0.5251 | AM34: 0.53845 | AN34: 0.534 | AO34: #N/A | AP34: 0.53667 | AQ34: #N/A | AR34: 0.5429 | AU34: 0.55855856
B35: Global forecast for new plants (operational) | AU35: 0.49 | AV35: 0.4918424 | AW35: 0.49358077 | AX35: 0.49522061 | AY35: 0.49676718 | AZ35: 0.4982255 | BA35: 0.49960034 | BB35: 0.50089626 | BC35: 0.50211758 | BD35: 0.50326843 | BE35: 0.5043527 | BF35: 0.50537411 | BG35: 0.50633618 | BH35: 0.50724225 | BI35: 0.50809548 | BJ35: 0.50889886 | BK35: 0.50965524 | BL35: 0.51036729 | BM35: 0.51103755 | BN35: 0.51166842 | BO35: 0.51226217 | BP35: 0.51282095 | BQ35: 0.51334677 | BR35: 0.51384155 | BS35: 0.51430709 | BT35: 0.51474509 | BU35: 0.51515717 | BV35: 0.51554483 | BW35: 0.51590951 | BX35: 0.51625254 | BY35: 0.51657521 | BZ35: 0.51687871 | CA35: 0.51716417
B36: World record nominal efficiency | AU36: 0.55855856

Sheet Battery learning
F1: Battery pack price
A3: Dataset | B3: Historic battery pack price vs. cumulative deployed capacity (GWh)
A4: Units | B4: As indicated
A5: Source | B5: BloombergNEF
A6: Subject to terms and conditions
B30: Battery learning curve
C31: 2010 | H31: 2015 | M31: 2020 | R31: 2025 | W31: 2030 | AB31: 2035
C32: 2010 | D32: 2011 | E32: 2012 | F32: 2013 | G32: 2014 | H32: 2015 | I32: 2016 | J32: 2017 | K32: 2018 | L32: 2019 | M32: 2020 | N32: 2021 | O32: 2022 | P32: 2023 | Q32: 2024 | R32: 2025 | S32: 2026 | T32: 2027 | U32: 2028 | V32: 2029 | W32: 2030 | X32: =W32+1 -> 2031 | Y32: =X32+1 -> 2032 | Z32: =Y32+1 -> 2033 | AA32: =Z32+1 -> 2034 | AB32: =AA32+1 -> 2035
B33: Li-ion battery pack price ($/kWh, 2021 real) | C33: 1220.1317 | D33: 702.70062 | E33: 508.44703 | F33: 410.44893 | G33: 325.79625 | H33: 281.01042 | I33: 244.3036 | J33: 216.05751 | K33: 187.86913 | L33: 167.95411 | M33: 149.50381 | N33: 132 | O33: 116.6774 | P33: 104.23537 | Q33: 93.948908 | R33: 85.084786 | S33: 77.897184 | T33: 71.989972 | U33: 66.858538 | V33: 62.441681 | W33: 58.540089 | X33: 55.158148 | Y33: 52.19786 | Z33: 49.586681 | AA33: 47.275106 | AB33: 45.232517
B34: EV (GWh) | C34: 0.2 | D34: 1.2 | E34: 3.2 | F34: 8.2 | G34: 15.2 | H34: 28.448052 | I34: 52.164728 | J34: 88.95606 | K34: 158.86258 | L34: 251.3145 | M34: 402.64694 | N34: 657.26423 | O34: 1056.2666 | P34: 1602.0091 | Q34: 2337.4958 | R34: 3320.9665 | S34: 4553.6408 | T34: 6037.4277 | U34: 7831.4557 | V34: 9976.4941 | W34: 12517.608 | X34: 15438.896 | Y34: 18750.521 | Z34: 22455.321 | AA34: 26528.368 | AB34: 30941.581
B35: E-bus (GWh) | C35: 0 | D35: 0.261606 | E35: 0.770068 | F35: 4.2726286 | G35: 16.966015 | H35: 26.604816 | I35: 38.837091 | J35: 51.723806 | K35: 67.853339 | L35: 82.689291 | M35: 95.544991 | N35: 110.26246 | O35: 128.18072 | P35: 149.23306 | Q35: 172.21292 | R35: 195.98375 | S35: 220.99595 | T35: 247.22253 | U35: 275.24732 | V35: 305.64994 | W35: 339.12803 | X35: 375.76964 | Y35: 414.34287 | Z35: 454.92568 | AA35: 497.49844 | AB35: 541.45367
B36: ESS (GWh) | C36: 0.3 | D36: 1 | E36: 4 | F36: 4 | G36: 5 | H36: 7 | I36: 9 | J36: 12 | K36: 21 | L36: 27 | M36: 38 | N36: 67 | O36: 112 | P36: 171 | Q36: 253 | R36: 349 | S36: 453 | T36: 570 | U36: 708 | V36: 860 | W36: 1033 | X36: 1150 | Y36: 1271 | Z36: 1401 | AA36: 1558 | AB36: 1730
B37: Note: ESS = Energy storage system; EV = electric vehicle

Sheet Storage capex 4hrs
D1: Battery storage capex
A3: Dataset | B3: Capital costs for a fully-installed usable 20MW/80MWh AC energy storage system at beginning of life
A4: Units | B4: $/kWh (2021 real, usable capacity)
A5: Source | B5: BloombergNEF
A6: Subject to terms and conditions
B29: Capital costs for a 20MW/80MWh energy storage system
B30: $/kWh (2021 real, usable capacity)
C31: 2021 | D31: 2025 | E31: 2030
B32: Total | C32: 288 | D32: 209.27943 | E32: 167.11512

Sheet Battery sensitivity WACC
F1: Battery sensitivity to WACC
A3: Dataset | B3: Battery storage LCOE sensitivity to WACC
A4: Units | B4: $/MWh (nominal)
A5: Source | B5: BloombergNEF
A6: Subject to terms and conditions
C30: Benchmark capex | F30: Central capex 2020 | I30: Capex +15% | L30: Capex -15%
C31: WACC | D31: LCOE | F31: WACC | G31: LCOE | I31: WACC | J31: LCOE | L31: WACC | M31: LCOE
C32: 0.08507 | D32: 141.20831 | F32: 0.00857 | G32: 81.228372 | I32: 0.00677 | J32: 89.769812 | L32: 0.00857 | M32: 70.139121
F33: 0.01757 | G33: 87.119063 | I33: 0.00677 | J33: 89.769812 | L33: 0.01757 | M33: 75.033525
F34: 0.02657 | G34: 93.405001 | I34: 0.00857 | J34: 91.062622 | L34: 0.02657 | M34: 80.256378
F35: 0.03557 | G35: 99.994673 | I35: 0.01757 | J35: 97.837965 | L35: 0.03557 | M35: 85.731572
F36: 0.04457 | G36: 106.87412 | I36: 0.02657 | J36: 105.06675 | L36: 0.04457 | M36: 91.447533
F37: 0.05357 | G37: 114.03639 | I37: 0.03557 | J37: 112.64487 | L37: 0.05357 | M37: 97.39848
F38: 0.06257 | G38: 121.47347 | I38: 0.04457 | J38: 120.55624 | L38: 0.06257 | M38: 103.57777
F39: 0.07157 | G39: 129.17648 | I39: 0.05357 | J39: 128.79284 | L39: 0.07157 | M39: 109.978
F40: 0.08057 | G40: 137.13576 | I40: 0.06257 | J40: 137.34549 | L40: 0.08057 | M40: 116.59117
F41: 0.08957 | G41: 145.34105 | I41: 0.07157 | J41: 146.20395 | L41: 0.08957 | M41: 123.40875
F42: 0.09857 | G42: 153.78164 | I42: 0.08057 | J42: 155.35712 | L42: 0.09857 | M42: 130.42182
F43: 0.10757 | G43: 162.44645 | I43: 0.08957 | J43: 164.79321 | L43: 0.10757 | M43: 137.6212
F44: 0.11657 | G44: 171.32424 | I44: 0.09857 | J44: 174.49989 | L44: 0.11657 | M44: 144.99752
... F48: 0.15257 | G48: 208.73899 | I48: 0.13457 | J48: 215.77534 | L48: 0.15257 | M48: 176.08451
I49: 0.14357 | J49: 226.64144 | L49: 0.16157 | M49: 184.20566
I50: 0.15257 | J50: 237.70084
I51: 0.16157 | J51: 248.94119

Sheet Battery sensitivity to Charging
F1: Battery sensitivity to charging costs
A3: Dataset | B3: Battery sensitivity to charging cost
A4: Units | B4: $/MWh (nominal)
A5: Source | B5: BloombergNEF
A6: Subject to terms and conditions
B30: Impact of charging costs on LCOE
B31: $/MWh (nominal)
B32: Charging costs -> | C32: -5 | D32: 0 | E32: 5 | F32: 10 | G32: 15 | H32: 20 | I32: 25 | J32: 30 | K32: 35
B33: LCOE | C33: 120.54831 | D33: 125.54831 | E33: 130.54831 | F33: 135.54831 | G33: 140.54831 | H33: 145.54831 | I33: 150.54831 | J33: 155.54831 | K33: 160.54831

Sheet Battery sensitivity to Cycles
F1: Battery sensitivity to cycle lifetime
A3: Dataset | B3: Battery sensitivity to cycle lifetime
A4: Units | B4: $/MWh (nominal)
A5: Source | B5: BloombergNEF
A6: Subject to terms and conditions
B30: Cycle lifetime impact on LCOE
B31: $/MWh,(nominal)
B32: Cycles -> | C32: 2000 | D32: 2500 | E32: 3000 | F32: 3500 | G32: 4000 | H32: 4500 | I32: 5000 | J32: 5500 | K32: 6000 | L32: 6500 | M32: 7000 | N32: 7500 | O32: 8000 | P32: 8500 | Q32: 9000 | R32: 9500 | S32: 10000
B33: LCOE benchmark | C33: 289.40884 | D33: 252.06507 | E33: 206.5988 | F33: 191.29813 | G33: 179.74713 | H33: 162.72504 | I33: 156.31376 | J33: 146.24817 | K33: 142.23196 | L33: 138.75075 | M33: 133.0171 | N33: 130.63212 | O33: 128.51816 | P33: 124.93786 | Q33: 123.41121 | R33: 120.79939 | S33: 119.67565
B34: LCOE @95% efficiency | C34: 275.00101 | D34: 239.6227 | E34: 196.54939 | F34: 182.05401 | G34: 171.11097 | H34: 154.98477 | I34: 148.91093 | J34: 139.3751 | K34: 135.57028 | L34: 132.27229 | M34: 126.84041 | N34: 124.58095 | O34: 122.57826 | P34: 119.18639 | Q34: 117.74009 | R34: 115.26574 | S34: 114.20114
B35: LCOE @85% efficiency | C35: 305.51172 | D35: 265.97125 | E35: 217.8305 | F35: 201.62978 | G35: 189.39932 | H35: 171.37592 | I35: 164.58751 | J35: 153.92982 | K35: 149.67737 | L35: 145.99138 | M35: 139.92046 | N35: 137.39518 | O35: 135.15688 | P35: 131.36597 | Q35: 129.74952 | R35: 126.98406 | S35: 125.79421

Sheet ChartTemplates
F1: Development sheet used for creating chart templates only
U2: COLUMN BUBBLE | AH2: 1 | AI2: 2 | AJ2: 3 | AK2: 4 | AL2: 5 | AM2: 6 | AN2: 7 | AO2: 8 | AP2: 9 | AQ2: 10
A3: Column chart | AG3: 2010 | AH3: 84.3 | AI3: =AH3*1.1 -> 92.73 | AJ3: =AH3/1.1 -> 76.636364 | AK3: =AI3/1.1 -> 84.3 | AL3: =AJ3/1.1 -> 69.669421 | AM3: =AK3/1.1 -> 76.636364 | AN3: =AL3/1.1 -> 63.335838 | AO3: =AM3/1.1 -> 69.669421 | AP3: =AN3/1.1 -> 57.578034 | AQ3: =AO3/1.1 -> 63.335838 | ... BA3: =AY3/1.1 -> 39.326572
AG4: 2011 | AH4: 89.5 | AI4: =AH4*1.1 -> 98.45 | AJ4: =AH4/1.1 -> 81.363636 | AK4: =AI4/1.1 -> 89.5 | AL4: =AJ4/1.1 -> 73.966942 | AM4: =AK4/1.1 -> 81.363636 | AN4: =AL4/1.1 -> 67.242675 | AO4: =AM4/1.1 -> 73.966942 | AP4: =AN4/1.1 -> 61.129704 | AQ4: =AO4/1.1 -> 67.242675 | ... BA4: =AY4/1.1 -> 41.752411
A5: Year | B5: US coal miners (k) | AG5: 2012 | AH5: 78.8 | AI5: =AH5*1.1 -> 86.68 | AJ5: =AH5/1.1 -> 71.636364 | AK5: =AI5/1.1 -> 78.8 | AL5: =AJ5/1.1 -> 65.123967 | AM5: =AK5/1.1 -> 71.636364 | AN5: =AL5/1.1 -> 59.203606 | AO5: =AM5/1.1 -> 65.123967 | AP5: =AN5/1.1 -> 53.82146 | AQ5: =AO5/1.1 -> 59.203606 | ... BA5: =AY5/1.1 -> 36.760782
A6: 2010 | B6: 84.3 | AG6: 2013 | AH6: 76.9 | AI6: =AH6*1.1 -> 84.59 | AJ6: =AH6/1.1 -> 69.909091 | AK6: =AI6/1.1 -> 76.9 | AL6: =AJ6/1.1 -> 63.553719 | AM6: =AK6/1.1 -> 69.909091 | AN6: =AL6/1.1 -> 57.776108 | AO6: =AM6/1.1 -> 63.553719 | AP6: =AN6/1.1 -> 52.523735 | AQ6: =AO6/1.1 -> 57.776108 | ... BA6: =AY6/1.1 -> 35.874418
A7: 2011 | B7: 89.5 | AG7: 2014 | AH7: 70.1 | AI7: =AH7*1.1 -> 77.11 | AJ7: =AH7/1.1 -> 63.727273 | AK7: =AI7/1.1 -> 70.1 | AL7: =AJ7/1.1 -> 57.933884 | AM7: =AK7/1.1 -> 63.727273 | AN7: =AL7/1.1 -> 52.667168 | AO7: =AM7/1.1 -> 57.933884 | AP7: =AN7/1.1 -> 47.879243 | AQ7: =AO7/1.1 -> 52.667168 | ... BA7: =AY7/1.1 -> 32.702167
A8: 2012 | B8: 78.8 | AG8: 2015 | AH8: 57.6 | AI8: =AH8*1.1 -> 63.36 | AJ8: =AH8/1.1 -> 52.363636 | AK8: =AI8/1.1 -> 57.6 | AL8: =AJ8/1.1 -> 47.603306 | AM8: =AK8/1.1 -> 52.363636 | AN8: =AL8/1.1 -> 43.275733 | AO8: =AM8/1.1 -> 47.603306 | AP8: =AN8/1.1 -> 39.341575 | AQ8: =AO8/1.1 -> 43.275733 | ... BA8: =AY8/1.1 -> 26.870825
A9: 2013 | B9: 76.9 | AG9: 2016 | AH9: 50.2 | AI9: =AH9*1.1 -> 55.22 | AJ9: =AH9/1.1 -> 45.636364 | AK9: =AI9/1.1 -> 50.2 | AL9: =AJ9/1.1 -> 41.487603 | AM9: =AK9/1.1 -> 45.636364 | AN9: =AL9/1.1 -> 37.716003 | AO9: =AM9/1.1 -> 41.487603 | AP9: =AN9/1.1 -> 34.287275 | AQ9: =AO9/1.1 -> 37.716003 | ... BA9: =AY9/1.1 -> 23.41867
A10: 2014 | B10: 70.1
A11: 2015 | B11: 57.6
A12: 2016 | B12: 50.2
BE20: Font | BH20: 10
BE21: Font | BH21: 10
BE22: Font | BH22: 10
BE23: Font | BH23: 10
U24: AREA | BE24: Font | BH24: 10
BE25: Font | BH25: 10
BE26: Font | BH26: 10
A27: Two-axis column-line chart | BE27: Font | BH27: 10
BE28: Font | BH28: 10
A29: Year | B29: US coal miners (k) | C29: US coal production (Mt) | BE29: Font | BH29: 10
A30: 2010 | B30: 84.3 | C30: 1084.3681 | BE30: Font | BH30: 10
A31: 2011 | B31: 89.5 | C31: 1095.6275 | AH31: a | AI31: b | AJ31: c | AK31: d | AL31: e | AM31: f | AN31: g | AO31: h | AP31: i | AQ31: j | BE31: Font | BH31: 10
A32: 2012 | B32: 78.8 | C32: 1016.4584 | AG32: 2010 | AH32: 84.3 | AI32: =AH32*1.1 -> 92.73 | AJ32: =AH32/1.1 -> 76.636364 | AK32: =AI32/1.1 -> 84.3 | AL32: =AJ32/1.1 -> 69.669421 | AM32: =AK32/1.1 -> 76.636364 | AN32: =AL32/1.1 -> 63.335838 | AO32: =AM32/1.1 -> 69.669421 | AP32: =AN32/1.1 -> 57.578034 | AQ32: =AO32/1.1 -> 63.335838 | BE32: Font | BH32: 10
A33: 2013 | B33: 76.9 | C33: 984.84178 | AG33: 2011 | AH33: 89.5 | AI33: =AH33*1.1 -> 98.45 | AJ33: =AH33/1.1 -> 81.363636 | AK33: =AI33/1.1 -> 89.5 | AL33: =AJ33/1.1 -> 73.966942 | AM33: =AK33/1.1 -> 81.363636 | AN33: =AL33/1.1 -> 67.242675 | AO33: =AM33/1.1 -> 73.966942 | AP33: =AN33/1.1 -> 61.129704 | AQ33: =AO33/1.1 -> 67.242675 | BE33: Font | BH33: 10
A34: 2014 | B34: 70.1 | C34: 1000.0488 | AG34: 2012 | AH34: 78.8 | AI34: =AH34*1.1 -> 86.68 | AJ34: =AH34/1.1 -> 71.636364 | AK34: =AI34/1.1 -> 78.8 | AL34: =AJ34/1.1 -> 65.123967 | AM34: =AK34/1.1 -> 71.636364 | AN34: =AL34/1.1 -> 59.203606 | AO34: =AM34/1.1 -> 65.123967 | AP34: =AN34/1.1 -> 53.82146 | AQ34: =AO34/1.1 -> 59.203606 | BE34: Font | BH34: 10
A35: 2015 | B35: 57.6 | C35: 896.94056 | AG35: 2013 | AH35: 76.9 | AI35: =AH35*1.1 -> 84.59 | AJ35: =AH35/1.1 -> 69.909091 | AK35: =AI35/1.1 -> 76.9 | AL35: =AJ35/1.1 -> 63.553719 | AM35: =AK35/1.1 -> 69.909091 | AN35: =AL35/1.1 -> 57.776108 | AO35: =AM35/1.1 -> 63.553719 | AP35: =AN35/1.1 -> 52.523735 | AQ35: =AO35/1.1 -> 57.776108 | BE35: Font | BH35: 10 | BI35: 0
A36: 2016 | B36: 50.2 | C36: 739 | AG36: 2014 | AH36: 70.1 | AI36: =AH36*1.1 -> 77.11 | AJ36: =AH36/1.1 -> 63.727273 | AK36: =AI36/1.1 -> 70.1 | AL36: =AJ36/1.1 -> 57.933884 | AM36: =AK36/1.1 -> 63.727273 | AN36: =AL36/1.1 -> 52.667168 | AO36: =AM36/1.1 -> 57.933884 | AP36: =AN36/1.1 -> 47.879243 | AQ36: =AO36/1.1 -> 52.667168 | BE36: Font | BH36: 10 | BI36: 182
AG37: 2015 | AH37: 57.6 | AI37: =AH37*1.1 -> 63.36 | AJ37: =AH37/1.1 -> 52.363636 | AK37: =AI37/1.1 -> 57.6 | AL37: =AJ37/1.1 -> 47.603306 | AM37: =AK37/1.1 -> 52.363636 | AN37: =AL37/1.1 -> 43.275733 | AO37: =AM37/1.1 -> 47.603306 | AP37: =AN37/1.1 -> 39.341575 | AQ37: =AO37/1.1 -> 43.275733 | BE37: Font | BH37: 10 | BI37: 67
AG38: 2016 | AH38: 50.2 | AI38: =AH38*1.1 -> 55.22 | AJ38: =AH38/1.1 -> 45.636364 | AK38: =AI38/1.1 -> 50.2 | AL38: =AJ38/1.1 -> 41.487603 | AM38: =AK38/1.1 -> 45.636364 | AN38: =AL38/1.1 -> 37.716003 | AO38: =AM38/1.1 -> 41.487603 | AP38: =AN38/1.1 -> 34.287275 | AQ38: =AO38/1.1 -> 37.716003 | BE38: Font | BH38: 10 | BI38: 255
BE39: Font | BH39: 10 | BI39: 237
BE40: Font | BH40: 10 | BI40: 25
BE41: Font | BH41: 10 | BI41: 118
R42: 0 | S42: 174 | T42: 229 | BE42: Font | BH42: 10 | BI42: 65
R43: 118 | S43: 84 | T43: 163 | BE43: Font | BI43: 255
R44: 67 | S44: 190 | T44: 173 | BE44: Font | BI44: 210
R45: 255 | S45: 232 | T45: 56 | BE45: Font
R46: 237 | S46: 49 | T46: 36 | BE46: Font
R47: 25 | S47: 178 | T47: 78 | U47: COLUMN LINE 2 AXIS | BE47: Font
R48: 189 | S48: 92 | T48: 163 | BE48: Font
R49: 65 | S49: 65 | T49: 65 | BE49: Font
A50: Bar chart | R50: 255 | S50: 201 | T50: 29 | BE50: Font
R51: 210 | S51: 210 | T51: 210 | BE51: Font
A52: Country | B52: Coal capacity additions 2015 - 2040 (GW) | R52: 0 | S52: 0 | T52: 0 | BE52: Font
A53: India | B53: 258 | C53: =B53*2 -> 516 | D53: =C53*2 -> 1032 | R53: 179 | S53: 179 | T53: 179 | BE53: Font
A54: China | B54: 188 | C54: =B54*2 -> 376 | D54: =C54*2 -> 752 | R54: 192 | S54: 192 | T54: 192 | BE54: Font
A55: Southeast Asia | B55: 73 | C55: =B55*2 -> 146 | D55: =C55*2 -> 292 | R55: 210 | S55: 210 | T55: 210 | AD55: ` | BE55: Font
A56: Middle East and Africa | B56: 67 | C56: =B56*2 -> 134 | D56: =C56*2 -> 268 | BE56: Font
A57: Japan | B57: 17 | C57: =B57*2 -> 34 | D57: =C57*2 -> 68 | BE57: Font
BE58: Font
A59: Rest of world | B59: 354 | C59: =B59*2 -> 708 | D59: =C59*2 -> 1416 | BE59: Font
BE60: Font
BE61: Font
BE62: Font
BE63: Font
BE64: Font
BE65: Font
BE66: Font
AA67: A | AJ67: B | BE67: Font
BE68: Font
A69: Line chart | U69: BAR | BE69: Font
BE70: Font
A71: Date | B71: US light truck sales | C71: Thousands | D71: 1000 | E71: 2 | F71: 3 | G71: 4 | H71: 5 | I71: 6 | J71: 7 | BE71: Font
A72: 36556 | B72: 583082 | C72: =B72/$D$71 -> 583.082 | D72: =C72*0.8 -> 466.4656 | E72: =D72*0.8 -> 373.17248 | F72: =E72*0.8 -> 298.53798 | G72: =F72*0.8 -> 238.83039 | H72: =G72*0.8 -> 191.06431 | I72: =H72*0.8 -> 152.85145 | BE72: Font
A73: 36585 | B73: 731349 | C73: =B73/$D$71 -> 731.349 | D73: =C73*0.8 -> 585.0792 | E73: =D73*0.8 -> 468.06336 | F73: =E73*0.8 -> 374.45069 | G73: =F73*0.8 -> 299.56055 | H73: =G73*0.8 -> 239.64844 | I73: =H73*0.8 -> 191.71875 | BE73: Font
A74: 36616 | B74: 834060 | C74: =B74/$D$71 -> 834.06 | D74: =C74*0.8 -> 667.248 | E74: =D74*0.8 -> 533.7984 | F74: =E74*0.8 -> 427.03872 | G74: =F74*0.8 -> 341.63098 | H74: =G74*0.8 -> 273.30478 | I74: =H74*0.8 -> 218.64382 | BE74: Font
A75: 36646 | B75: 727079 | C75: =B75/$D$71 -> 727.079 | D75: =C75*0.8 -> 581.6632 | E75: =D75*0.8 -> 465.33056 | F75: =E75*0.8 -> 372.26445 | G75: =F75*0.8 -> 297.81156 | H75: =G75*0.8 -> 238.24925 | I75: =H75*0.8 -> 190.5994 | BE75: Font
A76: 36677 | B76: 791619 | C76: =B76/$D$71 -> 791.619 | D76: =C76*0.8 -> 633.2952 | E76: =D76*0.8 -> 506.63616 | F76: =E76*0.8 -> 405.30893 | G76: =F76*0.8 -> 324.24714 | H76: =G76*0.8 -> 259.39771 | I76: =H76*0.8 -> 207.51817 | BE76: Font
A77: 36707 | B77: 780133 | C77: =B77/$D$71 -> 780.133 | D77: =C77*0.8 -> 624.1064 | E77: =D77*0.8 -> 499.28512 | F77: =E77*0.8 -> 399.4281 | G77: =F77*0.8 -> 319.54248 | H77: =G77*0.8 -> 255.63398 | I77: =H77*0.8 -> 204.50719 | BE77: Font
A78: 36738 | B78: 692486 | C78: =B78/$D$71 -> 692.486 | D78: =C78*0.8 -> 553.9888 | E78: =D78*0.8 -> 443.19104 | F78: =E78*0.8 -> 354.55283 | G78: =F78*0.8 -> 283.64227 | H78: =G78*0.8 -> 226.91381 | I78: =H78*0.8 -> 181.53105
A79: 36769 | B79: 740253 | C79: =B79/$D$71 -> 740.253 | D79: =C79*0.8 -> 592.2024 | E79: =D79*0.8 -> 473.76192 | F79: =E79*0.8 -> 379.00954 | G79: =F79*0.8 -> 303.20763 | H79: =G79*0.8 -> 242.5661 | I79: =H79*0.8 -> 194.05288
A80: 36799 | B80: 728546 | C80: =B80/$D$71 -> 728.546 | D80: =C80*0.8 -> 582.8368 | E80: =D80*0.8 -> 466.26944 | F80: =E80*0.8 -> 373.01555 | G80: =F80*0.8 -> 298.41244 | H80: =G80*0.8 -> 238.72995 | I80: =H80*0.8 -> 190.98396
A81: 36830 | B81: 658815 | C81: =B81/$D$71 -> 658.815 | D81: =C81*0.8 -> 527.052 | E81: =D81*0.8 -> 421.6416 | F81: =E81*0.8 -> 337.31328 | G81: =F81*0.8 -> 269.85062 | H81: =G81*0.8 -> 215.8805 | I81: =H81*0.8 -> 172.7044
A82: 36860 | B82: 630488 | C82: =B82/$D$71 -> 630.488 | D82: =C82*0.8 -> 504.3904 | E82: =D82*0.8 -> 403.51232 | F82: =E82*0.8 -> 322.80986 | G82: =F82*0.8 -> 258.24788 | H82: =G82*0.8 -> 206.59831 | I82: =H82*0.8 -> 165.27865
A83: 36891 | B83: 627215 | C83: =B83/$D$71 -> 627.215 | D83: =C83*0.8 -> 501.772 | E83: =D83*0.8 -> 401.4176 | F83: =E83*0.8 -> 321.13408 | G83: =F83*0.8 -> 256.90726 | H83: =G83*0.8 -> 205.52581 | I83: =H83*0.8 -> 164.42065
A84: 36922 | B84: 573878 | C84: =B84/$D$71 -> 573.878 | D84: =C84*0.8 -> 459.1024 | E84: =D84*0.8 -> 367.28192 | F84: =E84*0.8 -> 293.82554 | G84: =F84*0.8 -> 235.06043 | H84: =G84*0.8 -> 188.04834 | I84: =H84*0.8 -> 150.43867
A85: 36950 | B85: 655104 | C85: =B85/$D$71 -> 655.104 | D85: =C85*0.8 -> 524.0832 | E85: =D85*0.8 -> 419.26656 | F85: =E85*0.8 -> 335.41325 | G85: =F85*0.8 -> 268.3306 | H85: =G85*0.8 -> 214.66448 | I85: =H85*0.8 -> 171.73158
A86: 36981 | B86: 808024 | C86: =B86/$D$71 -> 808.024 | D86: =C86*0.8 -> 646.4192 | E86: =D86*0.8 -> 517.13536 | F86: =E86*0.8 -> 413.70829 | G86: =F86*0.8 -> 330.96663 | H86: =G86*0.8 -> 264.7733 | I86: =H86*0.8 -> 211.81864
A87: 37011 | B87: 659604 | C87: =B87/$D$71 -> 659.604 | D87: =C87*0.8 -> 527.6832 | E87: =D87*0.8 -> 422.14656 | F87: =E87*0.8 -> 337.71725 | G87: =F87*0.8 -> 270.1738 | H87: =G87*0.8 -> 216.13904 | I87: =H87*0.8 -> 172.91123
A88: 37042 | B88: 788154 | C88: =B88/$D$71 -> 788.154 | D88: =C88*0.8 -> 630.5232 | E88: =D88*0.8 -> 504.41856 | F88: =E88*0.8 -> 403.53485 | G88: =F88*0.8 -> 322.82788 | H88: =G88*0.8 -> 258.2623 | I88: =H88*0.8 -> 206.60984
A89: 37072 | B89: 809225 | C89: =B89/$D$71 -> 809.225 | D89: =C89*0.8 -> 647.38 | E89: =D89*0.8 -> 517.904 | F89: =E89*0.8 -> 414.3232 | G89: =F89*0.8 -> 331.45856 | H89: =G89*0.8 -> 265.16685 | I89: =H89*0.8 -> 212.13348
... A92: 37164 | B92: 649229 | C92: =B92/$D$71 -> 649.229 | D92: =C92*0.8 -> 519.3832 | E92: =D92*0.8 -> 415.50656 | F92: =E92*0.8 -> 332.40525 | G92: =F92*0.8 -> 265.9242 | H92: =G92*0.8 -> 212.73936 | I92: =H92*0.8 -> 170.19149
A93: 37195 | B93: 909756 | C93: =B93/$D$71 -> 909.756 | D93: =C93*0.8 -> 727.8048 | E93: =D93*0.8 -> 582.24384 | F93: =E93*0.8 -> 465.79507 | G93: =F93*0.8 -> 372.63606 | H93: =G93*0.8 -> 298.10885 | I93: =H93*0.8 -> 238.48708 | U93: LINE
A94: 37225 | B94: 722769 | C94: =B94/$D$71 -> 722.769 | D94: =C94*0.8 -> 578.2152 | E94: =D94*0.8 -> 462.57216 | F94: =E94*0.8 -> 370.05773 | G94: =F94*0.8 -> 296.04618 | H94: =G94*0.8 -> 236.83695 | I94: =H94*0.8 -> 189.46956
A95: 37256 | B95: 736423 | C95: =B95/$D$71 -> 736.423 | D95: =C95*0.8 -> 589.1384 | E95: =D95*0.8 -> 471.31072 | F95: =E95*0.8 -> 377.04858 | G95: =F95*0.8 -> 301.63886 | H95: =G95*0.8 -> 241.31109 | I95: =H95*0.8 -> 193.04887
A96: 37287 | B96: 582916 | C96: =B96/$D$71 -> 582.916 | D96: =C96*0.8 -> 466.3328 | E96: =D96*0.8 -> 373.06624 | F96: =E96*0.8 -> 298.45299 | G96: =F96*0.8 -> 238.76239 | H96: =G96*0.8 -> 191.00991 | I96: =H96*0.8 -> 152.80793
A97: 37315 | B97: 683576 | C97: =B97/$D$71 -> 683.576 | D97: =C97*0.8 -> 546.8608 | E97: =D97*0.8 -> 437.48864 | F97: =E97*0.8 -> 349.99091 | G97: =F97*0.8 -> 279.99273 | H97: =G97*0.8 -> 223.99418 | I97: =H97*0.8 -> 179.19535
A98: 37346 | B98: 773509 | C98: =B98/$D$71 -> 773.509 | D98: =C98*0.8 -> 618.8072 | E98: =D98*0.8 -> 495.04576 | F98: =E98*0.8 -> 396.03661 | G98: =F98*0.8 -> 316.82929 | H98: =G98*0.8 -> 253.46343 | I98: =H98*0.8 -> 202.77074
A99: 37376 | B99: 726236 | C99: =B99/$D$71 -> 726.236 | D99: =C99*0.8 -> 580.9888 | E99: =D99*0.8 -> 464.79104 | F99: =E99*0.8 -> 371.83283 | G99: =F99*0.8 -> 297.46627 | H99: =G99*0.8 -> 237.97301 | I99: =H99*0.8 -> 190.37841
A100: 37407 | B100: 746438 | C100: =B100/$D$71 -> 746.438 | D100: =C100*0.8 -> 597.1504 | E100: =D100*0.8 -> 477.72032 | F100: =E100*0.8 -> 382.17626 | G100: =F100*0.8 -> 305.741 | H100: =G100*0.8 -> 244.5928 | I100: =H100*0.8 -> 195.67424
A101: 37437 | B101: 775205 | C101: =B101/$D$71 -> 775.205 | D101: =C101*0.8 -> 620.164 | E101: =D101*0.8 -> 496.1312 | F101: =E101*0.8 -> 396.90496 | G101: =F101*0.8 -> 317.52397 | H101: =G101*0.8 -> 254.01917 | I101: =H101*0.8 -> 203.21534
A102: 37468 | B102: 783624 | C102: =B102/$D$71 -> 783.624 | D102: =C102*0.8 -> 626.8992 | E102: =D102*0.8 -> 501.51936 | F102: =E102*0.8 -> 401.21549 | G102: =F102*0.8 -> 320.97239 | H102: =G102*0.8 -> 256.77791 | I102: =H102*0.8 -> 205.42233
A103: 37499 | B103: 875790 | C103: =B103/$D$71 -> 875.79 | D103: =C103*0.8 -> 700.632 | E103: =D103*0.8 -> 560.5056 | F103: =E103*0.8 -> 448.40448 | G103: =F103*0.8 -> 358.72358 | H103: =G103*0.8 -> 286.97887 | I103: =H103*0.8 -> 229.58309
A104: 37529 | B104: 622187 | C104: =B104/$D$71 -> 622.187 | D104: =C104*0.8 -> 497.7496 | E104: =D104*0.8 -> 398.19968 | F104: =E104*0.8 -> 318.55974 | G104: =F104*0.8 -> 254.8478 | H104: =G104*0.8 -> 203.87824 | I104: =H104*0.8 -> 163.10259
A105: 37560 | B105: 695167 | C105: =B105/$D$71 -> 695.167 | D105: =C105*0.8 -> 556.1336 | E105: =D105*0.8 -> 444.90688 | F105: =E105*0.8 -> 355.9255 | G105: =F105*0.8 -> 284.7404 | H105: =G105*0.8 -> 227.79232 | I105: =H105*0.8 -> 182.23386
... A111: 37741 | B111: 754861 | C111: =B111/$D$71 -> 754.861 | D111: =C111*0.8 -> 603.8888 | E111: =D111*0.8 -> 483.11104 | F111: =E111*0.8 -> 386.48883 | G111: =F111*0.8 -> 309.19107 | H111: =G111*0.8 -> 247.35285 | I111: =H111*0.8 -> 197.88228
A112: 37772 | B112: 845966 | C112: =B112/$D$71 -> 845.966 | D112: =C112*0.8 -> 676.7728 | E112: =D112*0.8 -> 541.41824 | F112: =E112*0.8 -> 433.13459 | G112: =F112*0.8 -> 346.50767 | H112: =G112*0.8 -> 277.20614 | I112: =H112*0.8 -> 221.76491 | AP112: `
A113: 37802 | B113: 785910 | C113: =B113/$D$71 -> 785.91 | D113: =C113*0.8 -> 628.728 | E113: =D113*0.8 -> 502.9824 | F113: =E113*0.8 -> 402.38592 | G113: =F113*0.8 -> 321.90874 | H113: =G113*0.8 -> 257.52699 | I113: =H113*0.8 -> 206.02159
A114: 37833 | B114: 830231 | C114: =B114/$D$71 -> 830.231 | D114: =C114*0.8 -> 664.1848 | E114: =D114*0.8 -> 531.34784 | F114: =E114*0.8 -> 425.07827 | G114: =F114*0.8 -> 340.06262 | H114: =G114*0.8 -> 272.05009 | I114: =H114*0.8 -> 217.64008
...
